Workbook

Sheet Acta #1 Bloque A-B
A1: NOMBRE DE LA OBRA | C1: MANTENIMIENTO DE FACHADAS CONJUNTO RESERVA DE LA COLINA APARTASOLES | G1: MANTENIMIENTO INTREGRAL DE FACHADAS CONJUNTO RESERVA DE LA COLINA | O1: NÚMERO DE ACTA
A2: DIRECCIÓN | C2: Calle 10 # 3 - 03, La Tebaida, El Edén | O2: 1
A3: CONTRATANTE | C3: CONJUNTO RESERVA DE LA COLINA APARTASOLES
A4: CONSTRATISTA | C4: FRESHOUSE S.A.S
A5: NIT | C5: 901718258 - 4
A7: ITEM | B7: Descripción | C7: Presupuesto oficial | G7: Balance del Contrato | M7: Actas | O7: Acumulado
G8: Obra Contratada Ejecutada | I8: Obra Contratada No Ejecutada | K8: Obra Ejecutada No Contratada | M8: Acta parcial No. 001
M9: 45925
C10: Und | D10: Cant. | E10: Vr. Unitario | F10: Vr. Total | G10: Cant. | H10: Vr. Total | I10: Cant. | J10: Vr. Total | K10: Cant. | L10: Vr. Total | M10: Cant. | N10: Valor. Total | O10: Cant. | P10: Vr. Total
A11: BLOQUE A Y B
A12: 1.1.1 | B12: INSTALACION Y DEMARCACIÓN DE SEÑALETICA | C12: GLB | D12: 1 | E12: 80000 | F12: =D12*E12 -> 80000 | G12: 1 | H12: =G12*E12 -> 80000 | I12: =D12-G12 -> 0 | J12: =I12*E12 -> 0 | K12: 0 | L12: =K12*E12 -> 0 | M12: 1 | N12: =M12*E12 -> 80000 | O12: =M12 -> 1 | P12: =O12*E12 -> 80000 | R12: =O12*100/D12 -> 100 | S12: %
A13: 1.2.1 | B13: LAVADO Y LIMPIEZA DE SUPERFICIES QUE PRESENTAN HONGOS, INCLUYE PAREDES, VENTANAS Y VIDRIERAS. EL LAVADO SE REALIZARA CON BACTERICIDAS O HIPOCLORITO AL 10%, SE DEBEN ELIMINAR POLVOS Y GRASAS QUE IMPIDAN EL CORRECTO FUNCIONAMIENTO DE LOS PRODUCTOS | C13: M2 | D13: 1122.4 | E13: 3300 | F13: =D13*E13 -> 3703920 | G13: 1122.4 | H13: =G13*E13 -> 3703920 | I13: =D13-G13 -> 0 | J13: =I13*E13 -> 0 | K13: 0 | L13: =K13*E13 -> 0 | M13: 1122.4 | N13: =M13*E13 -> 3703920 | O13: =M13 -> 1122.4 | P13: =O13*E13 -> 3703920 | R13: =O13*100/D13 -> 100 | S13: %
A14: 1.2.2 | B14: LEVANTAMIENTO Y REMOCION DE TEXTURAS EN MAL ESTADO Y QUE YA NO PRESENTAN ADHERENCIA, SE REMOVERAN TEXTURAS SOPLADAS A LA VISTA Y EL QUE POR REMOCION CON LA ESPATULA NO PRESENTE SUFICIENTE ADHERENCIA, EN LOS RESANES MAYORES A UN M2 SE REALIZARA EL PAÑO COMPLETO | C14: M2 | D14: 80 | E14: 3000 | F14: =D14*E14 -> 240000 | G14: 80 | H14: =G14*E14 -> 240000 | I14: =D14-G14 -> 0 | J14: =I14*E14 -> 0 | K14: 0 | L14: =K14*E14 -> 0 | M14: 80 | N14: =M14*E14 -> 240000 | O14: =M14 -> 80 | P14: =O14*E14 -> 240000 | R14: =O14*100/D14 -> 100 | S14: %
A15: 1.2.3 | B15: APLICACIÓN DE IMPRIMANTE O ACRONAL, RESANE CON ESTUKA PAÑETE DE SIKA Y REPOSICION DE TEXTURA CON GRANIPLAST DE LA MARCA IMPATEXTURA, SE VOLVERA A IMPRIMAR PARA PERMITIR UN CORRECTO PUENTE DE ADHERENCIA | C15: ML | D15: 80 | E15: 37000 | F15: =D15*E15 -> 2960000 | G15: 80 | H15: =G15*E15 -> 2960000 | I15: =D15-G15 -> 0 | J15: =I15*E15 -> 0 | K15: 0 | L15: =K15*E15 -> 0 | M15: 80 | N15: =M15*E15 -> 2960000 | O15: =M15 -> 80 | P15: =O15*E15 -> 2960000 | R15: =O15*100/D15 -> 100 | S15: %
A16: 1.2.4 | B16: SE HARA TRATAMIENTO A ALFAJIAS, INCLUYE RESANE Y SELLO DE LAS MISMAS | C16: ML | D16: 122 | E16: 7000 | F16: =D16*E16 -> 854000 | G16: 15 | H16: =G16*E16 -> 105000 | I16: =D16-G16 -> 107 | J16: =I16*E16 -> 749000 | K16: 0 | L16: =K16*E16 -> 0 | M16: 15 | N16: =M16*E16 -> 105000 | O16: =M16 -> 15 | P16: =O16*E16 -> 105000 | R16: =O16*100/D16 -> 12.295082 | S16: %
A17: 1.2.5 | B17: REPARACIÓN DE MORTEROS EN CUCHILLAS DE CUBIERTA, TODA EL AREA PERIMETRAL CON MORTERO ACRILICO | C17: M2 | D17: =384+'[1]ACTA BLOQUE A'!D13 -> 806 | E17: 26000 | F17: =D17*E17 -> 20956000 | G17: 806 | H17: =G17*E17 -> 20956000 | I17: =D17-G17 -> 0 | J17: =I17*E17 -> 0 | K17: 0 | L17: =K17*E17 -> 0 | M17: =D17 -> 806 | N17: =M17*E17 -> 20956000 | O17: =M17 -> 806 | P17: =O17*E17 -> 20956000 | R17: =O17*100/D17 -> 100 | S17: %
A18: 1.3.1 | B18: SUMINISTRO Y APLICACIÓN DE PINTURA KORAZA PRO 550 EN IGUALES COLORES A LOS ACTUALES A DOS MANOS TENIENDO UN TIEMPO MINIMO ENTRE MANOS DE DOS HORAS | C18: M2 | D18: 1122.4 | E18: 17500 | F18: =D18*E18 -> 19642000 | G18: 1122.4 | H18: =G18*E18 -> 19642000 | I18: =D18-G18 -> 0 | J18: =I18*E18 -> 0 | K18: 0 | L18: =K18*E18 -> 0 | M18: =D18 -> 1122.4 | N18: =M18*E18 -> 19642000 | O18: =M18 -> 1122.4 | P18: =O18*E18 -> 19642000 | R18: =O18*100/D18 -> 100 | S18: %
A19: 1.3.2 | B19: SUMINISTRO Y APLICACIÓN DE PINTURA KORAZA PRO 550 EN IGUALES COLORES A LOS ACTUALES A DOS MANOS TENIENDO UN TIEMPO MINIMO ENTRE MANOS DE DOS HORAS, EN AREA DE CUCHILLAS REPARADAS DE CUBIERTA | C19: M2 | D19: =384+'[1]ACTA BLOQUE A'!D14 -> 806 | E19: 12000 | F19: =D19*E19 -> 9672000 | G19: 806 | H19: =G19*E19 -> 9672000 | I19: =D19-G19 -> 0 | J19: =I19*E19 -> 0 | K19: 0 | L19: =K19*E19 -> 0 | M19: =D19 -> 806 | N19: =M19*E19 -> 9672000 | O19: =M19 -> 806 | P19: =O19*E19 -> 9672000 | R19: =O19*100/D19 -> 100 | S19: %
A20: 1.4.1 | B20: ASEO GENERAL Y RETIRO DE PINTURA | C20: GLB | D20: 1 | E20: 200000 | F20: =D20*E20 -> 200000 | G20: 1 | H20: =G20*E20 -> 200000 | I20: =D20-G20 -> 0 | J20: =I20*E20 -> 0 | K20: 0 | L20: =K20*E20 -> 0 | M20: 1 | N20: =M20*E20 -> 200000 | O20: =M20 -> 1 | P20: =O20*E20 -> 200000 | R20: =O20*100/D20 -> 100 | S20: %
A21: SUBTOTAL GENERAL | F21: =SUM(F12:F20) -> 58307920 | H21: =SUM(H12:H20) -> 57558920 | J21: =SUM(J12:J20) -> 749000 | L21: =SUM(L12:L20) -> 0 | N21: =SUM(N12:N20) -> 57558920 | P21: =SUM(P12:P20) -> 57558920
A23: VALOR TOTAL COSTOS DIRECTOS | F23: =F21 -> 58307920 | H23: =H21 -> 57558920 | J23: =J21 -> 749000 | L23: =L21 -> 0 | N23: =N21 -> 57558920 | P23: =P21 -> 57558920
A24: ADMINISTRACIÓN | E24: 0.08 | F24: =$F$23*E24 -> 4664633.6 | H24: =$H$23*E24 -> 4604713.6 | J24: =$J$23*E24 -> 59920 | L24: =$L$23*E24 -> 0 | N24: =$N$23*E24 -> 4604713.6 | P24: =$P$23*E24 -> 4604713.6
A25: SEGURIDAD SOCIAL | E25: 0 | F25: =$F$23*E25 -> 0 | H25: =$H$23*E25 -> 0 | J25: =$J$23*E25 -> 0 | L25: =$L$23*E25 -> 0 | N25: =$N$23*E25 -> 0 | P25: =$P$23*E25 -> 0
A26: IMPREVISTOS | E26: 0.05 | F26: =$F$23*E26 -> 2915396 | H26: =$H$23*E26 -> 2877946 | J26: =$J$23*E26 -> 37450 | L26: =$L$23*E26 -> 0 | N26: =$N$23*E26 -> 2877946 | P26: =$P$23*E26 -> 2877946
A27: UTILIDADES | E27: 0.05 | F27: =$F$23*E27 -> 2915396 | H27: =$H$23*E27 -> 2877946 | J27: =$J$23*E27 -> 37450 | L27: =$L$23*E27 -> 0 | N27: =$N$23*E27 -> 2877946 | P27: =$P$23*E27 -> 2877946
A28: TOTAL AIU | E28: =SUM(E24:E27) -> 0.18 | F28: =SUM(F24:F27) -> 10495426 | H28: =$H$23*E28 -> 10360606 | J28: =$J$23*E28 -> 134820 | L28: =$L$23*E28 -> 0 | N28: =$N$23*E28 -> 10360606 | P28: =$P$23*E28 -> 10360606
A29: IVA SOBRE UTILIDAD | E29: 0.19 | F29: =E29*F27 -> 553925.24 | H29: =H27*$E$29 -> 546809.74 | J29: =J27*$E$29 -> 7115.5 | L29: =$L$23*E29 -> 0 | N29: =N27*$E$29 -> 546809.74 | P29: =P27*$E$29 -> 546809.74
A30: VALOR TOTAL DEL PRESUPUESTO | F30: =SUM(F23:F29)-F28 -> 69357271 | H30: =SUM(H23:H29)-H28 -> 68466335 | J30: =SUM(J23:J29)-J28 -> 890935.5 | L30: =SUM(L23:L29)-L28 -> 0 | N30: =SUM(N23:N29)-N28 -> 68466335 | P30: =SUM(P23:P29)-P28 -> 68466335
J32: Valor Total Presente Acta | M32: =N30 -> 68466335 | O32: =P30 -> 68466335 | S32: 1.1111111
I33: (-) Rete fuente | L33: 0.02 | M33: -1358390.5 | O33: -1358390.5
I34: (-) Rete ICA | L34: No | M34: 0 | O34: 0
I35: (-) Rete Garantía | L35: 0 | M35: 0 | O35: 0
B36: RENSO MONTOYA UPEGUI | I36: (-) Anticipo | K36: 0.2 | L36: 6000000 | M36: =-M32*(0) -> 0 | O36: =M36 -> 0
B37: Representante Legal | I37: VALOR NETO A PAGAR | N37: =SUM(M32:N36) -> 67107945 | O37: =SUM(O32:P36) -> 67107945

Sheet Acta #2 Bloque C
A1: NOMBRE DE LA OBRA | C1: MANTENIMIENTO DE FACHADAS CONJUNTO RESERVA DE LA COLINA APARTASOLES | G1: MANTENIMIENTO INTREGRAL DE FACHADAS CONJUNTO RESERVA DE LA COLINA BLOQUE C - ACTA DE AVANCE DE OBRA | O1: NÚMERO DE ACTA
A2: DIRECCIÓN | C2: Calle 10 # 3 - 03, La Tebaida, El Edén | O2: 2
A3: CONTRATANTE | C3: CONJUNTO RESERVA DE LA COLINA APARTASOLES
A4: CONSTRATISTA | C4: FRESHOUSE S.A.S
A5: NIT | C5: 901718258 - 4
A7: ITEM | B7: Descripción | C7: Presupuesto oficial | G7: Balance del Contrato | M7: Actas | O7: Acumulado
G8: Obra Contratada Ejecutada | I8: Obra Contratada No Ejecutada | K8: Obra Ejecutada No Contratada | M8: Acta parcial No. 002
M9: 45961
C10: Und | D10: Cant. | E10: Vr. Unitario | F10: Vr. Total | G10: Cant. | H10: Vr. Total | I10: Cant. | J10: Vr. Total | K10: Cant. | L10: Vr. Total | M10: Cant. | N10: Valor. Total | O10: Cant. | P10: Vr. Total
A11: BLOQUE D
A12: 1.1.1 | B12: INSTALACION Y DEMARCACIÓN DE SEÑALETICA | C12: GLB | D12: 1 | E12: 80000 | F12: =D12*E12 -> 80000 | G12: 1 | H12: =G12*E12 -> 80000 | I12: =D12-G12 -> 0 | J12: =I12*E12 -> 0 | K12: 0 | L12: =K12*E12 -> 0 | M12: 1 | N12: =M12*E12 -> 80000 | O12: =M12 -> 1 | P12: =O12*E12 -> 80000 | R12: =O12*100/D12 -> 100 | S12: %
A13: 1.2.1 | B13: LAVADO Y LIMPIEZA DE SUPERFICIES QUE PRESENTAN HONGOS, INCLUYE PAREDES, VENTANAS Y VIDRIERAS. EL LAVADO SE REALIZARA CON BACTERICIDAS O HIPOCLORITO AL 10%, SE DEBEN ELIMINAR POLVOS Y GRASAS QUE IMPIDAN EL CORRECTO FUNCIONAMIENTO DE LOS PRODUCTOS | C13: M2 | D13: 2483 | E13: 3300 | F13: =D13*E13 -> 8193900 | G13: 2483 | H13: =G13*E13 -> 8193900 | I13: =D13-G13 -> 0 | J13: =I13*E13 -> 0 | K13: 0 | L13: =K13*E13 -> 0 | M13: 2483 | N13: =M13*E13 -> 8193900 | O13: =M13 -> 2483 | P13: =O13*E13 -> 8193900 | R13: =O13*100/D13 -> 100 | S13: %
A14: 1.2.2 | B14: LEVANTAMIENTO Y REMOCION DE TEXTURAS EN MAL ESTADO Y QUE YA NO PRESENTAN ADHERENCIA, SE REMOVERAN TEXTURAS SOPLADAS A LA VISTA Y EL QUE POR REMOCION CON LA ESPATULA NO PRESENTE SUFICIENTE ADHERENCIA, EN LOS RESANES MAYORES A UN M2 SE REALIZARA EL PAÑO COMPLETO | C14: M2 | D14: 180 | E14: 3000 | F14: =D14*E14 -> 540000 | G14: 42 | H14: =G14*E14 -> 126000 | I14: =D14-G14 -> 138 | J14: =I14*E14 -> 414000 | K14: 0 | L14: =K14*E14 -> 0 | M14: 42 | N14: =M14*E14 -> 126000 | O14: =M14 -> 42 | P14: =O14*E14 -> 126000 | R14: =O14*100/D14 -> 23.333333 | S14: %
A15: 1.2.3 | B15: APLICACIÓN DE IMPRIMANTE O ACRONAL, RESANE CON ESTUKA PAÑETE DE SIKA Y REPOSICION DE TEXTURA CON GRANIPLAST DE LA MARCA IMPATEXTURA, SE VOLVERA A IMPRIMAR PARA PERMITIR UN CORRECTO PUENTE DE ADHERENCIA | C15: ML | D15: 180 | E15: 37000 | F15: =D15*E15 -> 6660000 | G15: 42 | H15: =G15*E15 -> 1554000 | I15: =D15-G15 -> 138 | J15: =I15*E15 -> 5106000 | K15: 0 | L15: =K15*E15 -> 0 | M15: 42 | N15: =M15*E15 -> 1554000 | O15: =M15 -> 42 | P15: =O15*E15 -> 1554000 | R15: =O15*100/D15 -> 23.333333 | S15: %
A16: 1.2.4 | B16: SE HARA TRATAMIENTO A ALFAJIAS, INCLUYE RESANE Y SELLO DE LAS MISMAS | C16: ML | D16: 276 | E16: 7000 | F16: =D16*E16 -> 1932000 | G16: 5 | H16: =G16*E16 -> 35000 | I16: =D16-G16 -> 271 | J16: =I16*E16 -> 1897000 | K16: 0 | L16: =K16*E16 -> 0 | M16: 5 | N16: =M16*E16 -> 35000 | O16: =M16 -> 5 | P16: =O16*E16 -> 35000 | R16: =O16*100/D16 -> 1.8115942 | S16: %
A17: 1.2.5 | B17: REPARACIÓN DE MORTEROS EN CUCHILLAS DE CUBIERTA, TODA EL AREA PERIMETRAL CON MORTERO ACRILICO | C17: M2 | D17: 384 | E17: 26000 | F17: =D17*E17 -> 9984000 | G17: 384 | H17: =G17*E17 -> 9984000 | I17: =D17-G17 -> 0 | J17: =I17*E17 -> 0 | K17: 0 | L17: =K17*E17 -> 0 | M17: 384 | N17: =M17*E17 -> 9984000 | O17: =M17 -> 384 | P17: =O17*E17 -> 9984000 | R17: =O17*100/D17 -> 100 | S17: %
A18: 1.3.1 | B18: SUMINISTRO Y APLICACIÓN DE PINTURA KORAZA PRO 550 EN IGUALES COLORES A LOS ACTUALES A DOS MANOS TENIENDO UN TIEMPO MINIMO ENTRE MANOS DE DOS HORAS | C18: M2 | D18: 2483 | E18: 17500 | F18: =D18*E18 -> 43452500 | G18: 2483 | H18: =G18*E18 -> 43452500 | I18: =D18-G18 -> 0 | J18: =I18*E18 -> 0 | K18: 0 | L18: =K18*E18 -> 0 | M18: =D18 -> 2483 | N18: =M18*E18 -> 43452500 | O18: =M18 -> 2483 | P18: =O18*E18 -> 43452500 | R18: =O18*100/D18 -> 100 | S18: %
A19: 1.3.2 | B19: SUMINISTRO Y APLICACIÓN DE PINTURA KORAZA PRO 550 EN IGUALES COLORES A LOS ACTUALES A DOS MANOS TENIENDO UN TIEMPO MINIMO ENTRE MANOS DE DOS HORAS, EN AREA DE CUCHILLAS REPARADAS DE CUBIERTA | C19: M2 | D19: 384 | E19: 12000 | F19: =D19*E19 -> 4608000 | G19: 384 | H19: =G19*E19 -> 4608000 | I19: =D19-G19 -> 0 | J19: =I19*E19 -> 0 | K19: 0 | L19: =K19*E19 -> 0 | M19: =D19 -> 384 | N19: =M19*E19 -> 4608000 | O19: =M19 -> 384 | P19: =O19*E19 -> 4608000 | R19: =O19*100/D19 -> 100 | S19: %
A20: 1.4.1 | B20: RETIRO Y REPOSICIÓN DE SUPERBOARD EN BUITRONES, INCLUYE SELLO DE LOS MISMOS Y APLICACIÓN DE PINTURA KORAZA | C20: UND | D20: 16 | E20: 126100 | F20: =D20*E20 -> 2017600 | G20: 16 | H20: =G20*E20 -> 2017600 | I20: =D20-G20 -> 0 | J20: =I20*E20 -> 0 | K20: 12 | L20: =K20*E20 -> 1513200 | M20: 28 | N20: =M20*E20 -> 3530800 | O20: =M20 -> 28 | P20: =O20*E20 -> 3530800
A21: 1.4.2 | B21: ASEO GENERAL Y RETIRO DE PINTURA | C21: GLB | D21: 1 | E21: 200000 | F21: =D21*E21 -> 200000 | G21: 1 | H21: =G21*E21 -> 200000 | I21: =D21-G21 -> 0 | J21: =I21*E21 -> 0 | K21: 0 | L21: =K21*E21 -> 0 | M21: 1 | N21: =M21*E21 -> 200000 | O21: =M21 -> 1 | P21: =O21*E21 -> 200000 | R21: =O21*100/D21 -> 100 | S21: %
A22: SUBTOTAL GENERAL | F22: =SUM(F12:F21) -> 77668000 | H22: =SUM(H12:H21) -> 70251000 | J22: =SUM(J12:J21) -> 7417000 | L22: =SUM(L12:L21) -> 1513200 | N22: =SUM(N12:N21) -> 71764200 | P22: =SUM(P12:P21) -> 71764200
A24: VALOR TOTAL COSTOS DIRECTOS | F24: =F22 -> 77668000 | H24: =H22 -> 70251000 | J24: =J22 -> 7417000 | L24: =L22 -> 1513200 | N24: =N22 -> 71764200 | P24: =P22 -> 71764200
A25: ADMINISTRACIÓN | E25: 0.08 | F25: =$F$24*E25 -> 6213440 | H25: =$H$24*E25 -> 5620080 | J25: =$J$24*E25 -> 593360 | L25: =$L$24*E25 -> 121056 | N25: =$N$24*E25 -> 5741136 | P25: =$P$24*E25 -> 5741136
A26: SEGURIDAD SOCIAL | E26: 0 | F26: =$F$24*E26 -> 0 | H26: =$H$24*E26 -> 0 | J26: =$J$24*E26 -> 0 | L26: =$L$24*E26 -> 0 | N26: =$N$24*E26 -> 0 | P26: =$P$24*E26 -> 0
A27: IMPREVISTOS | E27: 0.05 | F27: =$F$24*E27 -> 3883400 | H27: =$H$24*E27 -> 3512550 | J27: =$J$24*E27 -> 370850 | L27: =$L$24*E27 -> 75660 | N27: =$N$24*E27 -> 3588210 | P27: =$P$24*E27 -> 3588210
A28: UTILIDADES | E28: 0.05 | F28: =$F$24*E28 -> 3883400 | H28: =$H$24*E28 -> 3512550 | J28: =$J$24*E28 -> 370850 | L28: =$L$24*E28 -> 75660 | N28: =$N$24*E28 -> 3588210 | P28: =$P$24*E28 -> 3588210
A29: TOTAL AIU | E29: =SUM(E25:E28) -> 0.18 | F29: =SUM(F25:F28) -> 13980240 | H29: =$H$24*E29 -> 12645180 | J29: =$J$24*E29 -> 1335060 | L29: =$L$24*E29 -> 272376 | N29: =$N$24*E29 -> 12917556 | P29: =$P$24*E29 -> 12917556
A30: IVA SOBRE UTILIDAD | E30: 0.19 | F30: =E30*F28 -> 737846 | H30: =H28*$E$30 -> 667384.5 | J30: =J28*$E$30 -> 70461.5 | L30: =$L$24*E30 -> 287508 | N30: =N28*$E$30 -> 681759.9 | P30: =P28*$E$30 -> 681759.9
A31: VALOR TOTAL DEL PRESUPUESTO | F31: =SUM(F24:F30)-F29 -> 92386086 | H31: =SUM(H24:H30)-H29 -> 83563564 | J31: =SUM(J24:J30)-J29 -> 8822521.5 | L31: =SUM(L24:L30)-L29 -> 2073084 | N31: =SUM(N24:N30)-N29 -> 85363516 | P31: =SUM(P24:P30)-P29 -> 85363516
J33: Valor Total Presente Acta | M33: =N31 -> 85363516 | O33: =P31 -> 85363516
I34: (-) Rete fuente | L34: 0.02 | M34: -1693635.1 | O34: -1693635.1
I35: (-) Rete ICA | L35: No | M35: 0 | O35: 0
I36: (-) Rete Garantía | L36: 0 | M36: 0 | O36: 0
I37: (-) Anticipo | K37: 0.4 | L37: =M33*K37 -> 34145406 | M37: =-M33*(K37) -> -34145406 | O37: =M37 -> -34145406
I38: VALOR NETO A PAGAR | N38: =SUM(M33:N37) -> 49524474 | O38: =SUM(O33:P37) -> 49524474

Sheet Acta #3 Bloque D
A1: NOMBRE DE LA OBRA | C1: MANTENIMIENTO DE FACHADAS CONJUNTO RESERVA DE LA COLINA APARTASOLES | G1: MANTENIMIENTO INTREGRAL DE FACHADAS CONJUNTO RESERVA DE LA COLINA BLOQUE D - ACTA DE AVANCE DE OBRA | O1: NÚMERO DE ACTA
A2: DIRECCIÓN | C2: Calle 10 # 3 - 03, La Tebaida, El Edén | O2: 3
A3: CONTRATANTE | C3: CONJUNTO RESERVA DE LA COLINA APARTASOLES
A4: CONSTRATISTA | C4: FRESHOUSE S.A.S
A5: NIT | C5: 901718258 - 4
A7: ITEM | B7: Descripción | C7: Presupuesto oficial | G7: Balance del Contrato | M7: Actas | O7: Acumulado
G8: Obra Contratada Ejecutada | I8: Obra Contratada No Ejecutada | K8: Obra Ejecutada No Contratada | M8: Acta parcial No. 003
M9: 46006
C10: Und | D10: Cant. | E10: Vr. Unitario | F10: Vr. Total | G10: Cant. | H10: Vr. Total | I10: Cant. | J10: Vr. Total | K10: Cant. | L10: Vr. Total | M10: Cant. | N10: Valor. Total | O10: Cant. | P10: Vr. Total
A11: BLOQUE D
A12: 1.1.1 | B12: INSTALACION Y DEMARCACIÓN DE SEÑALETICA | C12: GLB | D12: 1 | E12: 80000 | F12: =D12*E12 -> 80000 | G12: 1 | H12: =G12*E12 -> 80000 | I12: =D12-G12 -> 0 | J12: =I12*E12 -> 0 | K12: 0 | L12: =K12*E12 -> 0 | M12: 1 | N12: =M12*E12 -> 80000 | O12: =M12 -> 1 | P12: =O12*E12 -> 80000 | R12: =O12*100/D12 -> 100 | S12: %
A13: 1.2.1 | B13: LAVADO Y LIMPIEZA DE SUPERFICIES QUE PRESENTAN HONGOS, INCLUYE PAREDES, VENTANAS Y VIDRIERAS. EL LAVADO SE REALIZARA CON BACTERICIDAS O HIPOCLORITO AL 10%, SE DEBEN ELIMINAR POLVOS Y GRASAS QUE IMPIDAN EL CORRECTO FUNCIONAMIENTO DE LOS PRODUCTOS | C13: M2 | D13: 1987 | E13: 3300 | F13: =D13*E13 -> 6557100 | G13: 1987 | H13: =G13*E13 -> 6557100 | I13: =D13-G13 -> 0 | J13: =I13*E13 -> 0 | K13: 0 | L13: =K13*E13 -> 0 | M13: 1987 | N13: =M13*E13 -> 6557100 | O13: =M13 -> 1987 | P13: =O13*E13 -> 6557100 | R13: =O13*100/D13 -> 100 | S13: %
A14: 1.2.2 | B14: LEVANTAMIENTO Y REMOCION DE TEXTURAS EN MAL ESTADO Y QUE YA NO PRESENTAN ADHERENCIA, SE REMOVERAN TEXTURAS SOPLADAS A LA VISTA Y EL QUE POR REMOCION CON LA ESPATULA NO PRESENTE SUFICIENTE ADHERENCIA, EN LOS RESANES MAYORES A UN M2 SE REALIZARA EL PAÑO COMPLETO | C14: M2 | D14: 139 | E14: 3000 | F14: =D14*E14 -> 417000 | G14: 72.55 | H14: =G14*E14 -> 217650 | I14: =D14-G14 -> 66.45 | J14: =I14*E14 -> 199350 | K14: 0 | L14: =K14*E14 -> 0 | M14: 72.55 | N14: =M14*E14 -> 217650 | O14: =M14 -> 72.55 | P14: =O14*E14 -> 217650 | R14: =O14*100/D14 -> 52.194245 | S14: %
A15: 1.2.3 | B15: APLICACIÓN DE IMPRIMANTE O ACRONAL, RESANE CON ESTUKA PAÑETE DE SIKA Y REPOSICION DE TEXTURA CON GRANIPLAST DE LA MARCA IMPATEXTURA, SE VOLVERA A IMPRIMAR PARA PERMITIR UN CORRECTO PUENTE DE ADHERENCIA | C15: ML | D15: 139 | E15: 37000 | F15: =D15*E15 -> 5143000 | G15: 73 | H15: =G15*E15 -> 2701000 | I15: =D15-G15 -> 66 | J15: =I15*E15 -> 2442000 | K15: 0 | L15: =K15*E15 -> 0 | M15: 73 | N15: =M15*E15 -> 2701000 | O15: =M15 -> 73 | P15: =O15*E15 -> 2701000 | R15: =O15*100/D15 -> 52.517986 | S15: %
A16: 1.2.4 | B16: SE HARA TRATAMIENTO A ALFAJIAS, INCLUYE RESANE Y SELLO DE LAS MISMAS | C16: ML | D16: 212 | E16: 7000 | F16: =D16*E16 -> 1484000 | G16: 0 | H16: =G16*E16 -> 0 | I16: =D16-G16 -> 212 | J16: =I16*E16 -> 1484000 | K16: 0 | L16: =K16*E16 -> 0 | M16: 0 | N16: =M16*E16 -> 0 | O16: =M16 -> 0 | P16: =O16*E16 -> 0 | R16: =O16*100/D16 -> 0 | S16: %
A17: 1.2.5 | B17: REPARACIÓN DE MORTEROS EN CUCHILLAS DE CUBIERTA, TODA EL AREA PERIMETRAL CON MORTERO ACRILICO | C17: M2 | D17: 345.6 | E17: 26000 | F17: =D17*E17 -> 8985600 | G17: 345.6 | H17: =G17*E17 -> 8985600 | I17: =D17-G17 -> 0 | J17: =I17*E17 -> 0 | K17: 0 | L17: =K17*E17 -> 0 | M17: =D17 -> 345.6 | N17: =M17*E17 -> 8985600 | O17: =M17 -> 345.6 | P17: =O17*E17 -> 8985600 | R17: =O17*100/D17 -> 100 | S17: %
A18: 1.3.1 | B18: SUMINISTRO Y APLICACIÓN DE PINTURA KORAZA PRO 550 EN IGUALES COLORES A LOS ACTUALES A DOS MANOS TENIENDO UN TIEMPO MINIMO ENTRE MANOS DE DOS HORAS | C18: M2 | D18: 1950.4 | E18: 17500 | F18: =D18*E18 -> 34132000 | G18: 1950.4 | H18: =G18*E18 -> 34132000 | I18: =D18-G18 -> 0 | J18: =I18*E18 -> 0 | K18: 0 | L18: =K18*E18 -> 0 | M18: =D18 -> 1950.4 | N18: =M18*E18 -> 34132000 | O18: =M18 -> 1950.4 | P18: =O18*E18 -> 34132000 | R18: =O18*100/D18 -> 100 | S18: %
A19: 1.3.2 | B19: SUMINISTRO Y APLICACIÓN DE PINTURA KORAZA PRO 550 EN IGUALES COLORES A LOS ACTUALES A DOS MANOS TENIENDO UN TIEMPO MINIMO ENTRE MANOS DE DOS HORAS, EN AREA DE CUCHILLAS REPARADAS DE CUBIERTA | C19: M2 | D19: 345.6 | E19: 12000 | F19: =D19*E19 -> 4147200 | G19: 345.6 | H19: =G19*E19 -> 4147200 | I19: =D19-G19 -> 0 | J19: =I19*E19 -> 0 | K19: 0 | L19: =K19*E19 -> 0 | M19: =D19 -> 345.6 | N19: =M19*E19 -> 4147200 | O19: =M19 -> 345.6 | P19: =O19*E19 -> 4147200 | R19: =O19*100/D19 -> 100 | S19: %
A20: 1.4.1 | B20: RETIRO Y REPOSICIÓN DE SUPERBOARD EN BUITRONES, INCLUYE SELLO DE LOS MISMOS Y APLICACIÓN DE PINTURA KORAZA | C20: UND | D20: 12 | E20: 140000 | F20: =D20*E20 -> 1680000 | G20: 12 | H20: =G20*E20 -> 1680000 | I20: =D20-G20 -> 0 | J20: =I20*E20 -> 0 | K20: 0 | L20: =K20*E20 -> 0 | M20: 12 | N20: =M20*E20 -> 1680000 | O20: =M20 -> 12 | P20: =O20*E20 -> 1680000
A21: 1.4.2 | B21: ASEO GENERAL Y RETIRO DE PINTURA | C21: GLB | D21: 1 | E21: 200000 | F21: =D21*E21 -> 200000 | G21: 1 | H21: =G21*E21 -> 200000 | I21: =D21-G21 -> 0 | J21: =I21*E21 -> 0 | K21: 0 | L21: =K21*E21 -> 0 | M21: 1 | N21: =M21*E21 -> 200000 | O21: =M21 -> 1 | P21: =O21*E21 -> 200000 | R21: =O21*100/D21 -> 100 | S21: %
A22: SUBTOTAL GENERAL | F22: =SUM(F12:F21) -> 62825900 | H22: =SUM(H12:H21) -> 58700550 | J22: =SUM(J12:J21) -> 4125350 | L22: =SUM(L12:L21) -> 0 | N22: =SUM(N12:N21) -> 58700550 | P22: =SUM(P12:P21) -> 58700550
A24: VALOR TOTAL COSTOS DIRECTOS | F24: =F22 -> 62825900 | H24: =H22 -> 58700550 | J24: =J22 -> 4125350 | L24: =L22 -> 0 | N24: =N22 -> 58700550 | P24: =P22 -> 58700550
A25: ADMINISTRACIÓN | E25: 0.08 | F25: =$F$24*E25 -> 5026072 | H25: =$H$24*E25 -> 4696044 | J25: =$J$24*E25 -> 330028 | L25: =$L$24*E25 -> 0 | N25: =$N$24*E25 -> 4696044 | P25: =$P$24*E25 -> 4696044
A26: SEGURIDAD SOCIAL | E26: 0 | F26: =$F$24*E26 -> 0 | H26: =$H$24*E26 -> 0 | J26: =$J$24*E26 -> 0 | L26: =$L$24*E26 -> 0 | N26: =$N$24*E26 -> 0 | P26: =$P$24*E26 -> 0
A27: IMPREVISTOS | E27: 0.05 | F27: =$F$24*E27 -> 3141295 | H27: =$H$24*E27 -> 2935027.5 | J27: =$J$24*E27 -> 206267.5 | L27: =$L$24*E27 -> 0 | N27: =$N$24*E27 -> 2935027.5 | P27: =$P$24*E27 -> 2935027.5
A28: UTILIDADES | E28: 0.05 | F28: =$F$24*E28 -> 3141295 | H28: =$H$24*E28 -> 2935027.5 | J28: =$J$24*E28 -> 206267.5 | L28: =$L$24*E28 -> 0 | N28: =$N$24*E28 -> 2935027.5 | P28: =$P$24*E28 -> 2935027.5
A29: TOTAL AIU | E29: =SUM(E25:E28) -> 0.18 | F29: =SUM(F25:F28) -> 11308662 | H29: =$H$24*E29 -> 10566099 | J29: =$J$24*E29 -> 742563 | L29: =$L$24*E29 -> 0 | N29: =$N$24*E29 -> 10566099 | P29: =$P$24*E29 -> 10566099
A30: IVA SOBRE UTILIDAD | E30: 0.19 | F30: =E30*F28 -> 596846.05 | H30: =H28*$E$30 -> 557655.22 | J30: =J28*$E$30 -> 39190.825 | L30: =$L$24*E30 -> 0 | N30: =N28*$E$30 -> 557655.22 | P30: =P28*$E$30 -> 557655.22
A31: VALOR TOTAL DEL PRESUPUESTO | F31: =SUM(F24:F30)-F29 -> 74731408 | H31: =SUM(H24:H30)-H29 -> 69824304 | J31: =SUM(J24:J30)-J29 -> 4907103.8 | L31: =SUM(L24:L30)-L29 -> 0 | N31: =SUM(N24:N30)-N29 -> 69824304 | P31: =SUM(P24:P30)-P29 -> 69824304
J33: Valor Total Presente Acta | M33: =N31 -> 69824304 | O33: =P31 -> 69824304
I34: (-) Rete fuente | L34: 0.02 | M34: -1385333 | O34: -1385333
I35: (-) Rete ICA | L35: No | M35: 0 | O35: 0
I36: (-) Rete Garantía | L36: 0 | M36: 0 | O36: 0
I37: (-) Anticipo | K37: 0.17078131 | L37: =M33*K37 -> 11924686 | M37: =-M33*(K37) -> -11924686 | O37: =M37 -> -11924686
I38: VALOR NETO A PAGAR | N38: =SUM(M33:N37) -> 56514285 | O38: =SUM(O33:P37) -> 56514285

Sheet Acta #4 Bloque E
A1: NOMBRE DE LA OBRA | C1: MANTENIMIENTO DE FACHADAS CONJUNTO RESERVA DE LA COLINA APARTASOLES | G1: MANTENIMIENTO INTREGRAL DE FACHADAS CONJUNTO RESERVA DE LA COLINA BLOQUE E - ACTA DE AVANCE DE OBRA | O1: NÚMERO DE ACTA
A2: DIRECCIÓN | C2: Calle 10 # 3 - 03, La Tebaida, El Edén | O2: 4
A3: CONTRATANTE | C3: CONJUNTO RESERVA DE LA COLINA APARTASOLES
A4: CONSTRATISTA | C4: FRESHOUSE S.A.S
A5: NIT | C5: 901718258 - 4
A7: ITEM | B7: Descripción | C7: Presupuesto oficial | G7: Balance del Contrato | M7: Actas | O7: Acumulado
G8: Obra Contratada Ejecutada | I8: Obra Contratada No Ejecutada | K8: Obra Ejecutada No Contratada | M8: Acta parcial No. 004
M9: 46055
C10: Und | D10: Cant. | E10: Vr. Unitario | F10: Vr. Total | G10: Cant. | H10: Vr. Total | I10: Cant. | J10: Vr. Total | K10: Cant. | L10: Vr. Total | M10: Cant. | N10: Valor. Total | O10: Cant. | P10: Vr. Total
A11: BLOQUE D
A12: 1.1.1 | B12: INSTALACION Y DEMARCACIÓN DE SEÑALETICA | C12: GLB | D12: 1 | E12: 80000 | F12: =D12*E12 -> 80000 | G12: 1 | H12: =G12*E12 -> 80000 | I12: =D12-G12 -> 0 | J12: =I12*E12 -> 0 | K12: 0 | L12: =K12*E12 -> 0 | M12: 1 | N12: =M12*E12 -> 80000 | O12: =M12 -> 1 | P12: =O12*E12 -> 80000 | R12: =O12*100/D12 -> 100 | S12: %
A13: 1.2.1 | B13: LAVADO Y LIMPIEZA DE SUPERFICIES QUE PRESENTAN HONGOS, INCLUYE PAREDES, VENTANAS Y VIDRIERAS. EL LAVADO SE REALIZARA CON BACTERICIDAS O HIPOCLORITO AL 10%, SE DEBEN ELIMINAR POLVOS Y GRASAS QUE IMPIDAN EL CORRECTO FUNCIONAMIENTO DE LOS PRODUCTOS | C13: M2 | D13: 1813 | E13: 3300 | F13: =D13*E13 -> 5982900 | G13: 1813 | H13: =G13*E13 -> 5982900 | I13: =D13-G13 -> 0 | J13: =I13*E13 -> 0 | K13: 0 | L13: =K13*E13 -> 0 | M13: 1813 | N13: =M13*E13 -> 5982900 | O13: =M13 -> 1813 | P13: =O13*E13 -> 5982900 | R13: =O13*100/D13 -> 100 | S13: %
A14: 1.2.2 | B14: LEVANTAMIENTO Y REMOCION DE TEXTURAS EN MAL ESTADO Y QUE YA NO PRESENTAN ADHERENCIA, SE REMOVERAN TEXTURAS SOPLADAS A LA VISTA Y EL QUE POR REMOCION CON LA ESPATULA NO PRESENTE SUFICIENTE ADHERENCIA, EN LOS RESANES MAYORES A UN M2 SE REALIZARA EL PAÑO COMPLETO | C14: M2 | D14: 20 | E14: 3000 | F14: =D14*E14 -> 60000 | G14: 20 | H14: =G14*E14 -> 60000 | I14: =D14-G14 -> 0 | J14: =I14*E14 -> 0 | K14: 80 | L14: =K14*E14 -> 240000 | M14: 100 | N14: =M14*E14 -> 300000 | O14: =M14 -> 100 | P14: =O14*E14 -> 300000 | R14: =O14*100/D14 -> 500 | S14: %
A15: 1.2.3 | B15: APLICACIÓN DE IMPRIMANTE O ACRONAL, RESANE CON ESTUKA PAÑETE DE SIKA Y REPOSICION DE TEXTURA CON GRANIPLAST DE LA MARCA IMPATEXTURA, SE VOLVERA A IMPRIMAR PARA PERMITIR UN CORRECTO PUENTE DE ADHERENCIA | C15: ML | D15: 20 | E15: 37000 | F15: =D15*E15 -> 740000 | G15: 20 | H15: =G15*E15 -> 740000 | I15: =D15-G15 -> 0 | J15: =I15*E15 -> 0 | K15: 80 | L15: =K15*E15 -> 2960000 | M15: 100 | N15: =M15*E15 -> 3700000 | O15: =M15 -> 100 | P15: =O15*E15 -> 3700000 | R15: =O15*100/D15 -> 500 | S15: %
A16: 1.3.1 | B16: SUMINISTRO Y APLICACIÓN DE PINTURA KORAZA PRO 550 EN IGUALES COLORES A LOS ACTUALES A DOS MANOS TENIENDO UN TIEMPO MINIMO ENTRE MANOS DE DOS HORAS | C16: M2 | D16: 271.9 | E16: 17500 | F16: =D16*E16 -> 4758250 | G16: 271.9 | H16: =G16*E16 -> 4758250 | I16: =D16-G16 -> 0 | J16: =I16*E16 -> 0 | K16: 200 | L16: =K16*E16 -> 3500000 | M16: 471.9 | N16: =M16*E16 -> 8258250 | O16: =M16 -> 471.9 | P16: =O16*E16 -> 8258250 | R16: =O16*100/D16 -> 173.55645 | S16: %
A17: 1.4.2 | B17: ASEO GENERAL Y RETIRO DE PINTURA | C17: GLB | D17: 1 | E17: 200000 | F17: =D17*E17 -> 200000 | G17: 1 | H17: =G17*E17 -> 200000 | I17: =D17-G17 -> 0 | J17: =I17*E17 -> 0 | K17: 0 | L17: =K17*E17 -> 0 | M17: 1 | N17: =M17*E17 -> 200000 | O17: =M17 -> 1 | P17: =O17*E17 -> 200000 | R17: =O17*100/D17 -> 100 | S17: %
A18: SUBTOTAL GENERAL | F18: =SUM(F12:F17) -> 11821150 | H18: =SUM(H12:H17) -> 11821150 | J18: =SUM(J12:J17) -> 0 | L18: =SUM(L12:L17) -> 6700000 | N18: =SUM(N12:N17) -> 18521150 | P18: =SUM(P12:P17) -> 18521150
A20: VALOR TOTAL COSTOS DIRECTOS | F20: =F18 -> 11821150 | H20: =H18 -> 11821150 | J20: =J18 -> 0 | L20: =L18 -> 6700000 | N20: =N18 -> 18521150 | P20: =P18 -> 18521150
A21: ADMINISTRACIÓN | E21: 0.08 | F21: =$F$20*E21 -> 945692 | H21: =$H$20*E21 -> 945692 | J21: =$J$20*E21 -> 0 | L21: =$L$20*E21 -> 536000 | N21: =$N$20*E21 -> 1481692 | P21: =$P$20*E21 -> 1481692
A22: SEGURIDAD SOCIAL | E22: 0 | F22: =$F$20*E22 -> 0 | H22: =$H$20*E22 -> 0 | J22: =$J$20*E22 -> 0 | L22: =$L$20*E22 -> 0 | N22: =$N$20*E22 -> 0 | P22: =$P$20*E22 -> 0
A23: IMPREVISTOS | E23: 0.05 | F23: =$F$20*E23 -> 591057.5 | H23: =$H$20*E23 -> 591057.5 | J23: =$J$20*E23 -> 0 | L23: =$L$20*E23 -> 335000 | N23: =$N$20*E23 -> 926057.5 | P23: =$P$20*E23 -> 926057.5
A24: UTILIDADES | E24: 0.05 | F24: =$F$20*E24 -> 591057.5 | H24: =$H$20*E24 -> 591057.5 | J24: =$J$20*E24 -> 0 | L24: =$L$20*E24 -> 335000 | N24: =$N$20*E24 -> 926057.5 | P24: =$P$20*E24 -> 926057.5
A25: TOTAL AIU | E25: =SUM(E21:E24) -> 0.18 | F25: =SUM(F21:F24) -> 2127807 | H25: =$H$20*E25 -> 2127807 | J25: =$J$20*E25 -> 0 | L25: =$L$20*E25 -> 1206000 | N25: =$N$20*E25 -> 3333807 | P25: =$P$20*E25 -> 3333807
A26: IVA SOBRE UTILIDAD | E26: 0.19 | F26: =E26*F24 -> 112300.93 | H26: =H24*$E$26 -> 112300.93 | J26: =J24*$E$26 -> 0 | L26: =$L$20*E26 -> 1273000 | N26: =N24*$E$26 -> 175950.92 | P26: =P24*$E$26 -> 175950.92
A27: VALOR TOTAL DEL PRESUPUESTO | F27: =SUM(F20:F26)-F25 -> 14061258 | H27: =SUM(H20:H26)-H25 -> 14061258 | J27: =SUM(J20:J26)-J25 -> 0 | L27: =SUM(L20:L26)-L25 -> 9179000 | N27: =SUM(N20:N26)-N25 -> 22030908 | P27: =SUM(P20:P26)-P25 -> 22030908
J29: Valor Total Presente Acta | M29: =N27 -> 22030908 | O29: =P27 -> 22030908
I30: (-) Rete fuente | L30: 0.02 | M30: -437099.14 | O30: -437099.14
I31: (-) Rete ICA | L31: No | M31: 0 | O31: 0
I32: (-) Rete Garantía | L32: 0 | M32: 0 | O32: 0
I33: (-) Anticipo | K33: 0.1 | L33: =M29*K33 -> 2203090.8 | M33: =-M29*(K33) -> -2203090.8 | O33: =M33 -> -2203090.8
I34: VALOR NETO A PAGAR | N34: =SUM(M29:N33) -> 19390718 | O34: =SUM(O29:P33) -> 19390718

Sheet Acta #5 Bloque F
A1: NOMBRE DE LA OBRA | C1: MANTENIMIENTO DE FACHADAS CONJUNTO RESERVA DE LA COLINA APARTASOLES | G1: MANTENIMIENTO INTREGRAL DE FACHADAS CONJUNTO RESERVA DE LA COLINA BLOQUE F - ACTA DE AVANCE DE OBRA | O1: NÚMERO DE ACTA
A2: DIRECCIÓN | C2: Calle 10 # 3 - 03, La Tebaida, El Edén | O2: 5
A3: CONTRATANTE | C3: CONJUNTO RESERVA DE LA COLINA APARTASOLES
A4: CONSTRATISTA | C4: FRESHOUSE S.A.S
A5: NIT | C5: 901718258 - 4
A7: ITEM | B7: Descripción | C7: Presupuesto oficial | G7: Balance del Contrato | M7: Actas | O7: Acumulado
G8: Obra Contratada Ejecutada | I8: Obra Contratada No Ejecutada | K8: Obra Ejecutada No Contratada | M8: Acta parcial No. 005
M9: 46055
C10: Und | D10: Cant. | E10: Vr. Unitario | F10: Vr. Total | G10: Cant. | H10: Vr. Total | I10: Cant. | J10: Vr. Total | K10: Cant. | L10: Vr. Total | M10: Cant. | N10: Valor. Total | O10: Cant. | P10: Vr. Total
A11: BLOQUE D
A12: 1.1.1 | B12: INSTALACION Y DEMARCACIÓN DE SEÑALETICA | C12: GLB | D12: 1 | E12: 80000 | F12: =D12*E12 -> 80000 | G12: 1 | H12: =G12*E12 -> 80000 | I12: =D12-G12 -> 0 | J12: =I12*E12 -> 0 | K12: 0 | L12: =K12*E12 -> 0 | M12: 1 | N12: =M12*E12 -> 80000 | O12: =M12 -> 1 | P12: =O12*E12 -> 80000 | R12: =O12*100/D12 -> 100 | S12: %
A13: 1.2.1 | B13: LAVADO Y LIMPIEZA DE SUPERFICIES QUE PRESENTAN HONGOS, INCLUYE PAREDES, VENTANAS Y VIDRIERAS. EL LAVADO SE REALIZARA CON BACTERICIDAS O HIPOCLORITO AL 10%, SE DEBEN ELIMINAR POLVOS Y GRASAS QUE IMPIDAN EL CORRECTO FUNCIONAMIENTO DE LOS PRODUCTOS | C13: M2 | D13: 2539.2 | E13: 3300 | F13: =D13*E13 -> 8379360 | G13: 2539.2 | H13: =G13*E13 -> 8379360 | I13: =D13-G13 -> 0 | J13: =I13*E13 -> 0 | K13: 0 | L13: =K13*E13 -> 0 | M13: 2539.2 | N13: =M13*E13 -> 8379360 | O13: =M13 -> 2539.2 | P13: =O13*E13 -> 8379360 | R13: =O13*100/D13 -> 100 | S13: %
A14: 1.2.2 | B14: LEVANTAMIENTO Y REMOCION DE TEXTURAS EN MAL ESTADO Y QUE YA NO PRESENTAN ADHERENCIA, SE REMOVERAN TEXTURAS SOPLADAS A LA VISTA Y EL QUE POR REMOCION CON LA ESPATULA NO PRESENTE SUFICIENTE ADHERENCIA, EN LOS RESANES MAYORES A UN M2 SE REALIZARA EL PAÑO COMPLETO | C14: M2 | D14: 25 | E14: 3000 | F14: =D14*E14 -> 75000 | G14: 25 | H14: =G14*E14 -> 75000 | I14: =D14-G14 -> 0 | J14: =I14*E14 -> 0 | K14: =M14-D14 -> 35 | L14: =K14*E14 -> 105000 | M14: 60 | N14: =M14*E14 -> 180000 | O14: =M14 -> 60 | P14: =O14*E14 -> 180000 | R14: =O14*100/D14 -> 240 | S14: %
A15: 1.2.3 | B15: APLICACIÓN DE IMPRIMANTE O ACRONAL, RESANE CON ESTUKA PAÑETE DE SIKA Y REPOSICION DE TEXTURA CON GRANIPLAST DE LA MARCA IMPATEXTURA, SE VOLVERA A IMPRIMAR PARA PERMITIR UN CORRECTO PUENTE DE ADHERENCIA | C15: ML | D15: 25 | E15: 37000 | F15: =D15*E15 -> 925000 | G15: 25 | H15: =G15*E15 -> 925000 | I15: =D15-G15 -> 0 | J15: =I15*E15 -> 0 | K15: =M15-D15 -> 35 | L15: =K15*E15 -> 1295000 | M15: 60 | N15: =M15*E15 -> 2220000 | O15: =M15 -> 60 | P15: =O15*E15 -> 2220000 | R15: =O15*100/D15 -> 240 | S15: %
A16: 1.3.1 | B16: SUMINISTRO Y APLICACIÓN DE PINTURA KORAZA PRO 550 EN IGUALES COLORES A LOS ACTUALES A DOS MANOS TENIENDO UN TIEMPO MINIMO ENTRE MANOS DE DOS HORAS | C16: M2 | D16: 253.9 | E16: 17500 | F16: =D16*E16 -> 4443250 | G16: 253.9 | H16: =G16*E16 -> 4443250 | I16: =D16-G16 -> 0 | J16: =I16*E16 -> 0 | K16: =M16-D16 -> 100 | L16: =K16*E16 -> 1750000 | M16: 353.9 | N16: =M16*E16 -> 6193250 | O16: =M16 -> 353.9 | P16: =O16*E16 -> 6193250 | R16: =O16*100/D16 -> 139.38558 | S16: %
A17: 1.2.1 | B17: LAVADO Y LIMPIEZA DE SUPERFICIES QUE PRESENTAN HONGOS, INCLUYE PAREDES, VENTANAS Y VIDRIERAS. EL LAVADO SE REALIZARA CON BACTERICIDAS O HIPOCLORITO AL 10%, SE DEBEN ELIMINAR POLVOS Y GRASAS QUE IMPIDAN EL CORRECTO FUNCIONAMIENTO DE LOS PRODUCTOS EN ZONAS SOCIALES | C17: M2 | D17: 0 | E17: 3300 | F17: =D17*E17 -> 0 | H17: =G17*E17 -> 0 | J17: =I17*E17 -> 0 | K17: =M17-D17 -> 130 | L17: =K17*E17 -> 429000 | M17: 130 | N17: =M17*E17 -> 429000 | O17: =M17 -> 130 | P17: =O17*E17 -> 429000 | R17: =O17*100/D17 -> #DIV/0! | S17: %
A18: 1.3.1 | B18: SUMINISTRO Y APLICACIÓN DE PINTURA KORAZA PRO 550 EN IGUALES COLORES A LOS ACTUALES A DOS MANOS TENIENDO UN TIEMPO MINIMO ENTRE MANOS DE DOS HORAS EN ZONAS SOCIALES | C18: M2 | D18: 0 | E18: 17500 | F18: =D18*E18 -> 0 | H18: =G18*E18 -> 0 | J18: =I18*E18 -> 0 | K18: =M18-D18 -> 130 | L18: =K18*E18 -> 2275000 | M18: 130 | N18: =M18*E18 -> 2275000 | O18: =M18 -> 130 | P18: =O18*E18 -> 2275000 | R18: =O18*100/D18 -> #DIV/0! | S18: %
A19: 1.4.1 | B19: RETIRO Y REPOSICIÓN DE SUPERBOARD EN BUITRONES, INCLUYE SELLO DE LOS MISMOS Y APLICACIÓN DE PINTURA KORAZA | C19: UND | D19: 0 | E19: 126100 | F19: =D19*E19 -> 0 | G19: 12 | H19: =G19*E19 -> 1513200 | I19: =D19-G19 -> -12 | J19: =I19*E19 -> -1513200 | L19: =K19*E19 -> 0 | M19: 28 | N19: =M19*E19 -> 3530800 | O19: =M19 -> 28 | P19: =O19*E19 -> 3530800
A20: 1.4.2 | B20: ASEO GENERAL Y RETIRO DE PINTURA | C20: GLB | D20: 1 | E20: 200000 | F20: =D20*E20 -> 200000 | G20: 1 | H20: =G20*E20 -> 200000 | I20: =D20-G20 -> 0 | J20: =I20*E20 -> 0 | K20: 0 | L20: =K20*E20 -> 0 | M20: 1 | N20: =M20*E20 -> 200000 | O20: =M20 -> 1 | P20: =O20*E20 -> 200000 | R20: =O20*100/D20 -> 100 | S20: %
A21: SUBTOTAL GENERAL | F21: =SUM(F12:F20) -> 14102610 | H21: =SUM(H12:H20) -> 15615810 | J21: =SUM(J12:J20) -> -1513200 | L21: =SUM(L12:L20) -> 5854000 | N21: =SUM(N12:N20) -> 23487410 | P21: =SUM(P12:P20) -> 23487410
A23: VALOR TOTAL COSTOS DIRECTOS | F23: =F21 -> 14102610 | H23: =H21 -> 15615810 | J23: =J21 -> -1513200 | L23: =L21 -> 5854000 | N23: =N21 -> 23487410 | P23: =P21 -> 23487410
A24: ADMINISTRACIÓN | E24: 0.08 | F24: =$F$23*E24 -> 1128208.8 | H24: =$H$23*E24 -> 1249264.8 | J24: =$J$23*E24 -> -121056 | L24: =$L$23*E24 -> 468320 | N24: =$N$23*E24 -> 1878992.8 | P24: =$P$23*E24 -> 1878992.8
A25: SEGURIDAD SOCIAL | E25: 0 | F25: =$F$23*E25 -> 0 | H25: =$H$23*E25 -> 0 | J25: =$J$23*E25 -> 0 | L25: =$L$23*E25 -> 0 | N25: =$N$23*E25 -> 0 | P25: =$P$23*E25 -> 0
A26: IMPREVISTOS | E26: 0.05 | F26: =$F$23*E26 -> 705130.5 | H26: =$H$23*E26 -> 780790.5 | J26: =$J$23*E26 -> -75660 | L26: =$L$23*E26 -> 292700 | N26: =$N$23*E26 -> 1174370.5 | P26: =$P$23*E26 -> 1174370.5
A27: UTILIDADES | E27: 0.05 | F27: =$F$23*E27 -> 705130.5 | H27: =$H$23*E27 -> 780790.5 | J27: =$J$23*E27 -> -75660 | L27: =$L$23*E27 -> 292700 | N27: =$N$23*E27 -> 1174370.5 | P27: =$P$23*E27 -> 1174370.5
A28: TOTAL AIU | E28: =SUM(E24:E27) -> 0.18 | F28: =SUM(F24:F27) -> 2538469.8 | H28: =$H$23*E28 -> 2810845.8 | J28: =$J$23*E28 -> -272376 | L28: =$L$23*E28 -> 1053720 | N28: =$N$23*E28 -> 4227733.8 | P28: =$P$23*E28 -> 4227733.8
A29: IVA SOBRE UTILIDAD | E29: 0.19 | F29: =E29*F27 -> 133974.8 | H29: =H27*$E$29 -> 148350.2 | J29: =J27*$E$29 -> -14375.4 | L29: =$L$23*E29 -> 1112260 | N29: =N27*$E$29 -> 223130.39 | P29: =P27*$E$29 -> 223130.39
A30: VALOR TOTAL DEL PRESUPUESTO | F30: =SUM(F23:F29)-F28 -> 16775055 | H30: =SUM(H23:H29)-H28 -> 18575006 | J30: =SUM(J23:J29)-J28 -> -1799951.4 | L30: =SUM(L23:L29)-L28 -> 8019980 | N30: =SUM(N23:N29)-N28 -> 27938274 | P30: =SUM(P23:P29)-P28 -> 27938274
J32: Valor Total Presente Acta | M32: =N30 -> 27938274 | O32: =P30 -> 27938274
I33: (-) Rete fuente | L33: 0.02 | M33: -486221.6 | O33: -486221.6
I34: (-) Rete ICA | L34: No | M34: 0 | O34: 0
I35: (-) Rete Garantía | L35: 0 | M35: 0 | O35: 0
I36: (-) Anticipo | K36: 0.1 | L36: =M32*K36 -> 2793827.4 | M36: =-M32*(K36) -> -2793827.4 | O36: =M36 -> -2793827.4
I37: VALOR NETO A PAGAR | N37: =SUM(M32:N36) -> 24658225 | O37: =SUM(O32:P36) -> 24658225

Sheet Acta #6 Bloque G
A1: NOMBRE DE LA OBRA | C1: MANTENIMIENTO DE FACHADAS CONJUNTO RESERVA DE LA COLINA APARTASOLES | G1: MANTENIMIENTO INTREGRAL DE FACHADAS CONJUNTO RESERVA DE LA COLINA BLOQUE G - ACTA DE AVANCE DE OBRA | O1: NÚMERO DE ACTA
A2: DIRECCIÓN | C2: Calle 10 # 3 - 03, La Tebaida, El Edén | O2: 6
A3: CONTRATANTE | C3: CONJUNTO RESERVA DE LA COLINA APARTASOLES
A4: CONSTRATISTA | C4: FRESHOUSE S.A.S
A5: NIT | C5: 901718258 - 4
A7: ITEM | B7: Descripción | C7: Presupuesto oficial | G7: Balance del Contrato | M7: Actas | O7: Acumulado
G8: Obra Contratada Ejecutada | I8: Obra Contratada No Ejecutada | K8: Obra Ejecutada No Contratada | M8: Acta parcial No. 006
M9: 46055
C10: Und | D10: Cant. | E10: Vr. Unitario | F10: Vr. Total | G10: Cant. | H10: Vr. Total | I10: Cant. | J10: Vr. Total | K10: Cant. | L10: Vr. Total | M10: Cant. | N10: Valor. Total | O10: Cant. | P10: Vr. Total
A11: BLOQUE D
A12: 1.1.1 | B12: INSTALACION Y DEMARCACIÓN DE SEÑALETICA | C12: GLB | D12: 1 | E12: 80000 | F12: =D12*E12 -> 80000 | G12: 1 | H12: =G12*E12 -> 80000 | I12: =D12-G12 -> 0 | J12: =I12*E12 -> 0 | K12: 0 | L12: =K12*E12 -> 0 | M12: 1 | N12: =M12*E12 -> 80000 | O12: =M12 -> 1 | P12: =O12*E12 -> 80000 | R12: =O12*100/D12 -> 100 | S12: %
A13: 1.2.1 | B13: LAVADO Y LIMPIEZA DE SUPERFICIES QUE PRESENTAN HONGOS, INCLUYE PAREDES, VENTANAS Y VIDRIERAS. EL LAVADO SE REALIZARA CON BACTERICIDAS O HIPOCLORITO AL 10%, SE DEBEN ELIMINAR POLVOS Y GRASAS QUE IMPIDAN EL CORRECTO FUNCIONAMIENTO DE LOS PRODUCTOS | C13: M2 | D13: 1450 | E13: 3300 | F13: =D13*E13 -> 4785000 | G13: 1450 | H13: =G13*E13 -> 4785000 | I13: =D13-G13 -> 0 | J13: =I13*E13 -> 0 | K13: 0 | L13: =K13*E13 -> 0 | M13: 1450 | N13: =M13*E13 -> 4785000 | O13: =M13 -> 1450 | P13: =O13*E13 -> 4785000 | R13: =O13*100/D13 -> 100 | S13: %
A14: 1.2.2 | B14: LEVANTAMIENTO Y REMOCION DE TEXTURAS EN MAL ESTADO Y QUE YA NO PRESENTAN ADHERENCIA, SE REMOVERAN TEXTURAS SOPLADAS A LA VISTA Y EL QUE POR REMOCION CON LA ESPATULA NO PRESENTE SUFICIENTE ADHERENCIA, EN LOS RESANES MAYORES A UN M2 SE REALIZARA EL PAÑO COMPLETO | C14: M2 | D14: 20 | E14: 3000 | F14: =D14*E14 -> 60000 | G14: 20 | H14: =G14*E14 -> 60000 | I14: =D14-G14 -> 0 | J14: =I14*E14 -> 0 | K14: =M14-D14 -> 40 | L14: =K14*E14 -> 120000 | M14: 60 | N14: =M14*E14 -> 180000 | O14: =M14 -> 60 | P14: =O14*E14 -> 180000 | R14: =O14*100/D14 -> 300 | S14: %
A15: 1.2.3 | B15: APLICACIÓN DE IMPRIMANTE O ACRONAL, RESANE CON ESTUKA PAÑETE DE SIKA Y REPOSICION DE TEXTURA CON GRANIPLAST DE LA MARCA IMPATEXTURA, SE VOLVERA A IMPRIMAR PARA PERMITIR UN CORRECTO PUENTE DE ADHERENCIA | C15: ML | D15: 20 | E15: 37000 | F15: =D15*E15 -> 740000 | G15: 20 | H15: =G15*E15 -> 740000 | I15: =D15-G15 -> 0 | J15: =I15*E15 -> 0 | K15: =M15-D15 -> 40 | L15: =K15*E15 -> 1480000 | M15: 60 | N15: =M15*E15 -> 2220000 | O15: =M15 -> 60 | P15: =O15*E15 -> 2220000 | R15: =O15*100/D15 -> 300 | S15: %
A16: 1.3.1 | B16: SUMINISTRO Y APLICACIÓN DE PINTURA KORAZA PRO 550 EN IGUALES COLORES A LOS ACTUALES A DOS MANOS TENIENDO UN TIEMPO MINIMO ENTRE MANOS DE DOS HORAS | C16: M2 | D16: 216.4 | E16: 17500 | F16: =D16*E16 -> 3787000 | G16: 216.4 | H16: =G16*E16 -> 3787000 | I16: =D16-G16 -> 0 | J16: =I16*E16 -> 0 | K16: =M16-D16 -> 103.64203 | L16: =K16*E16 -> 1813735.5 | M16: 320.04203 | N16: =M16*E16 -> 5600735.5 | O16: =M16 -> 320.04203 | P16: =O16*E16 -> 5600735.5 | R16: =O16*100/D16 -> 147.89373 | S16: %
A17: 1.4.2 | B17: ASEO GENERAL Y RETIRO DE PINTURA | C17: GLB | D17: 1 | E17: 200000 | F17: =D17*E17 -> 200000 | G17: 1 | H17: =G17*E17 -> 200000 | I17: =D17-G17 -> 0 | J17: =I17*E17 -> 0 | K17: 0 | L17: =K17*E17 -> 0 | M17: 1 | N17: =M17*E17 -> 200000 | O17: =M17 -> 1 | P17: =O17*E17 -> 200000 | R17: =O17*100/D17 -> 100 | S17: %
A18: SUBTOTAL GENERAL | F18: =SUM(F12:F17) -> 9652000 | H18: =SUM(H12:H17) -> 9652000 | J18: =SUM(J12:J17) -> 0 | L18: =SUM(L12:L17) -> 3413735.5 | N18: =SUM(N12:N17) -> 13065736 | P18: =SUM(P12:P17) -> 13065736
A20: VALOR TOTAL COSTOS DIRECTOS | F20: =F18 -> 9652000 | H20: =H18 -> 9652000 | J20: =J18 -> 0 | L20: =L18 -> 3413735.5 | N20: =N18 -> 13065736 | P20: =P18 -> 13065736
A21: ADMINISTRACIÓN | E21: 0.08 | F21: =$F$20*E21 -> 772160 | H21: =$H$20*E21 -> 772160 | J21: =$J$20*E21 -> 0 | L21: =$L$20*E21 -> 273098.84 | N21: =$N$20*E21 -> 1045258.8 | P21: =$P$20*E21 -> 1045258.8
A22: SEGURIDAD SOCIAL | E22: 0 | F22: =$F$20*E22 -> 0 | H22: =$H$20*E22 -> 0 | J22: =$J$20*E22 -> 0 | L22: =$L$20*E22 -> 0 | N22: =$N$20*E22 -> 0 | P22: =$P$20*E22 -> 0
A23: IMPREVISTOS | E23: 0.05 | F23: =$F$20*E23 -> 482600 | H23: =$H$20*E23 -> 482600 | J23: =$J$20*E23 -> 0 | L23: =$L$20*E23 -> 170686.78 | N23: =$N$20*E23 -> 653286.78 | P23: =$P$20*E23 -> 653286.78
A24: UTILIDADES | E24: 0.05 | F24: =$F$20*E24 -> 482600 | H24: =$H$20*E24 -> 482600 | J24: =$J$20*E24 -> 0 | L24: =$L$20*E24 -> 170686.78 | N24: =$N$20*E24 -> 653286.78 | P24: =$P$20*E24 -> 653286.78
A25: TOTAL AIU | E25: =SUM(E21:E24) -> 0.18 | F25: =SUM(F21:F24) -> 1737360 | H25: =$H$20*E25 -> 1737360 | J25: =$J$20*E25 -> 0 | L25: =$L$20*E25 -> 614472.4 | N25: =$N$20*E25 -> 2351832.4 | P25: =$P$20*E25 -> 2351832.4
A26: IVA SOBRE UTILIDAD | E26: 0.19 | F26: =E26*F24 -> 91694 | H26: =H24*$E$26 -> 91694 | J26: =J24*$E$26 -> 0 | L26: =$L$20*E26 -> 648609.75 | N26: =N24*$E$26 -> 124124.49 | P26: =P24*$E$26 -> 124124.49
A27: VALOR TOTAL DEL PRESUPUESTO | F27: =SUM(F20:F26)-F25 -> 11481054 | H27: =SUM(H20:H26)-H25 -> 11481054 | J27: =SUM(J20:J26)-J25 -> 0 | L27: =SUM(L20:L26)-L25 -> 4676817.7 | N27: =SUM(N20:N26)-N25 -> 15541692 | P27: =SUM(P20:P26)-P25 -> 15541692
J29: Valor Total Presente Acta | M29: =N27 -> 15541692 | O29: =P27 -> 15541692
I30: (-) Rete fuente | L30: 0.02 | M30: -383040.64 | O30: -383040.64
I31: (-) Rete ICA | L31: No | M31: 0 | O31: 0
I32: (-) Rete Garantía | L32: 0 | M32: 0 | O32: 0
I33: (-) Anticipo | K33: 0.048632248 | L33: =M29*K33 -> 755827.44 | M33: =-M29*(K33) -> -755827.44 | O33: =M33 -> -755827.44
I34: VALOR NETO A PAGAR | N34: =SUM(M29:N33) -> 14402824 | O34: =SUM(O29:P33) -> 14402824
N38: =N20+'Acta #5 Bloque F'!N23+'Acta #4 Bloque E'!N20 -> 55074296
N39: =M29+'Acta #5 Bloque F'!M32+'Acta #4 Bloque E'!M29 -> 65510875
N41: =N34+'Acta #5 Bloque F'!N37+'Acta #4 Bloque E'!N34 -> 58451768
N42: =M29+'Acta #5 Bloque F'!M32+'Acta #4 Bloque E'!M29 -> 65510875
N44: =M33+'Acta #5 Bloque F'!M36+'Acta #4 Bloque E'!M33 -> -5752745.7
N45: =M29+'Acta #5 Bloque F'!M32+'Acta #4 Bloque E'!M29 -> 65510875
N47: =N34+'Acta #5 Bloque F'!N37+'Acta #4 Bloque E'!N34+'Acta #3 Bloque D'!N38+'Acta #2 Bloque C'!N38+'Acta #1 Bloque A-B'!N37+'Acta #1 Bloque A-B'!G35 -> 231598472
