Workbook

Sheet acta 01 nov 5 2025
A1: ACTA 01 DE AVANCE DE OBRA-PARQUE RESIDENCIAL LOS CEDROS
A2: Contratante: Parque residencial Los Cedros | D2: INTERVENTOR: Ing. Luis Fernando Márquez Jaramillo
A3: Contratista: Freshouse SAS | D3: FECHA: 04/03/2026 | G3: PNK-001-2025 | H3: Acta 01- Periodo del
A4: Periodo de Ejecucion: 15/01/2026 a 28/02/3026 | H4: sept 22 a noviembre 5 de 2025
A5: CAPT | B5: ITEMS | C5: DESCRIPCION | D5: UNIDAD | E5: CANTIDAD | F5: VR UNITARIO | G5: VALOR DIRECTO ACTIVIDAD | H5: Cantidad | I5: % avance | J5: Valor Total
A6: 1.0 | C6: PRELIMINARES | G6: =+G7+G8 -> 1800000 | J6: =+J7+J8 -> 1602000
B7: 1.1 | C7: Campamento | D7: Gl | E7: 1 | F7: 1500000 | G7: =F7*E7 -> 1500000 | H7: 1 | I7: =+H7/E7 -> 1 | J7: =+H7*F7 -> 1500000
B8: 1.2 | C8: Señalizacion y Seguridad | D8: Gl | E8: 1 | F8: 300000 | G8: =F8*E8 -> 300000 | H8: 0.34 | I8: =+H8/E8 -> 0.34 | J8: =+H8*F8 -> 102000
A9: 2 | C9: PREPARACION DE SUPERFICIES | G9: =+G10+G12 -> 61681852 | J9: =+J10+J12 -> 8404871.5
B10: 2.1 | C10: LAVADO Y LIMPIEZA | G10: =+SUM(G11:G11) -> 14562834 | J10: =+SUM(J11:J11) -> 7052797.2
B11: 2.1.1 | C11: Lavado de Fachadas Externas (blanco, gris, negro, color madera) | D11: M2 | E11: 4629 | F11: 3146 | G11: =F11*E11 -> 14562834 | H11: =Lavado!S69 -> 2241.83 | I11: =+H11/E11 -> 0.48430114 | J11: =+F11*H11 -> 7052797.2
B12: 2.2 | C12: REPARACIONES Y TRATAMIENTOS ESPECIALES en Fachada | G12: =SUM(G13:G17) -> 47119018 | J12: =SUM(J13:J17) -> 1352074.4
B13: 2.2.1 | C13: Suministro y Reposicion de mortero quemado o desprendido | D13: M2 | E13: 40 | F13: 39400 | G13: =F13*E13 -> 1576000 | H13: 0 | I13: =+H13/E13 -> 0 | J13: =+F13*H13 -> 0
B14: 2.2.2 | C14: Suministro y Reposición de graniplast - silcoplast deteriorado | D14: M2 | E14: =+SUM(E21:E23)*15% -> 791.8635 | F14: 36500 | G14: =F14*E14 -> 28903018 | H14: =Sicoplast!S50 -> 32.8719 | I14: =+H14/E14 -> 0.041512079 | J14: =+F14*H14 -> 1199824.4
B15: 2.2.3 | C15: Retiro y Sustitucion de laminas de Superboard en mal estado | D15: M2 | E15: 100 | F15: 87000 | G15: =F15*E15 -> 8700000 | H15: 1.75 | I15: =+H15/E15 -> 0.0175 | J15: =+F15*H15 -> 152250
B16: 2.2.4 | C16: Retiro y Sustitucion de laminas de superboard tipo Siding Color Madera | D16: M2 | E16: 60 | F16: 87000 | G16: =F16*E16 -> 5220000 | H16: 0 | I16: =+H16/E16 -> 0 | J16: =+F16*H16 -> 0
B17: 2.2.5 | C17: Retiro y Sustitución de láminas de Drywall en mal estado, interiores y exteriores | D17: M2 | E17: 40 | F17: 68000 | G17: =F17*E17 -> 2720000 | H17: 0 | I17: =+H17/E17 -> 0 | J17: =+F17*H17 -> 0
B18: 2.2.6 | C18: Suministro e Instalacion de Cortagoteras en Balcones y Accesos a los bloques de aptos | D18: ML | E18: 1055.3 | F18: 28877 | G18: =F18*E18 -> 30473898 | H18: =14.5+16.2 -> 30.7 | I18: =+H18/E18 -> 0.029091254 | J18: =+F18*H18 -> 886523.9
A19: 3 | C19: PINTURA | G19: =+G20+G27+G32 -> 182335405 | J19: =+J20+J27+J32 -> 34478535
B20: 3.1 | C20: Pintura Tipo Koraza para Exteriores | G20: =+SUM(G21:G26) -> 107586123 | J20: =+SUM(J21:J26) -> 20579023
B21: 3.1.1 | C21: Suministro y Aplicación de Pintura para exteriores, tipo Koraza, sobre superficies de Fachadas y Muros Externos de los bloques de apartamentos | D21: M2 | E21: 4629 | F21: 16692 | G21: =F21*E21 -> 77267268 | H21: =Pintura!S50 -> 1232.8674 | I21: =+H21/E21 -> 0.26633558 | J21: =+F21*H21 -> 20579023
B22: 3.1.2 | C22: Pintura gris para exteriores tipo Koraza Proteccion Sol y Lluvia Impermeabilizante | D22: M2 | E22: 467.17 | F22: 21000 | G22: =F22*E22 -> 9810570 | H22: 0 | I22: =+H22/E22 -> 0 | J22: =+F22*H22 -> 0
B23: 3.1.3 | C23: Pintura negra para exteriores tipo Koraza Proteccion Sol y Lluvia Impermeabilizante | D23: M2 | E23: 182.92 | F23: 21000 | G23: =F23*E23 -> 3841320 | H23: 0 | I23: =+H23/E23 -> 0 | J23: =+F23*H23 -> 0
B24: 3.1.4 | C24: Pintura Tipo Koraza Proteccion Sol y Lluvia Impermeabilizante sobre lamina tipo siding (color madera cedro) | D24: M2 | E24: 565.54 | F24: 17500 | G24: =F24*E24 -> 9896950 | H24: 0 | I24: =+H24/E24 -> 0 | J24: =+F24*H24 -> 0
B25: 3.1.5 | C25: Pintura gris basalto koraza (parqueaderos) | D25: M2 | E25: 161.75 | F25: 17500 | G25: =F25*E25 -> 2830625 | I25: =+H25/E25 -> 0 | J25: =+F25*H25 -> 0
B26: 3.1.6 | C26: Pintura sobre alfajías Tipo Koraza Proteccion Sol y Lluvia Impermeabilizante | D26: ML | E26: 532.35 | F26: 7400 | G26: =F26*E26 -> 3939390 | H26: 0 | I26: =+H26/E26 -> 0 | J26: =+F26*H26 -> 0
B27: 3.2 | C27: Pintura Tipo Pintulux 3 en 1 sobre Elementos Metalicos | G27: =+SUM(G28:G31) -> 52090282 | J27: =+SUM(J28:J31) -> 8892692.5
B28: 3.2.1 | C28: Pintura Pintulux 3 en 1 estructura metalica parqueaderos | D28: M2 | E28: 1306 | F28: 16717 | G28: =F28*E28 -> 21832402 | H28: =185.5+185.5 -> 371 | I28: =+H28/E28 -> 0.28407351 | J28: =+F28*H28 -> 6202007
B29: 3.2.2 | C29: Suministro y Aplicación de Pintuco Fill sobre las cubiertas de los parqueaderos | D29: M2 | E29: 1306 | F29: 15125 | G29: =F29*E29 -> 19753250 | H29: 124.02 | I29: =+H29/E29 -> 0.094961715 | J29: =+F29*H29 -> 1875802.5
B30: 3.2.3 | C30: Suministro y Aplicación de Pintura para Barandas Metalicas en areas exteriores: gimnasio, pasillos, cuarto de acueducto, piscina | D30: ML | E30: 187 | F30: 19006 | G30: =F30*E30 -> 3554122 | H30: 23 | I30: =+H30/E30 -> 0.12299465 | J30: =+F30*H30 -> 437138
B31: 3.2.4 | C31: Suministro y Aplicación de Pintura tipo 3 en 1, en puertas de los apartamentos (estan incluidas las de los exteriores, porteria motobombas) | D31: UND | E31: 92 | F31: 75549 | G31: =F31*E31 -> 6950508 | H31: =1+1+3 -> 5 | I31: =+H31/E31 -> 0.054347826 | J31: =+F31*H31 -> 377745
B32: 3.3 | C32: Pintura Tipo Viniltex Advanced de Pintuco en Interiores | G32: =+SUM(G33:G33) -> 22659000 | J32: =+SUM(J33:J33) -> 5006820
B33: 3.3.1 | C33: Suministro y Aplicación de Pintura tipo Vinilo en areas comunes internas de los bloques de aptos: paredes y cielos rasos | D33: M2 | E33: 2158 | F33: 10500 | G33: =F33*E33 -> 22659000 | H33: =Pasillos!S22 -> 476.84 | I33: =+H33/E33 -> 0.22096386 | J33: =+F33*H33 -> 5006820
A34: 4 | C34: CARPINTERIA EN ALUMINIO y Vidrio | G34: =+SUM(G35:G35) -> 6020406.4 | J34: =+SUM(J35:J35) -> 6550252.8
B35: 4.1 | C35: Retiro y Reposicion de sello perimetral en elementos vidriados de los bloque de apartamentos (30% DEL TOTAL) | D35: ML | E35: 817.99 | F35: 7360 | G35: =F35*E35 -> 6020406.4 | H35: =Sellos!S50 -> 889.98 | I35: =+H35/E35 -> 1.0880084 | J35: =+F35*H35 -> 6550252.8
A36: 5 | C36: VARIOS | G36: =++G37+G38 -> 5450000 | J36: =++J37+J38 -> 0
B37: 5.1 | C37: Media caña en concreto incluye impermeabilizado | D37: ML | E37: 30 | F37: 55000 | G37: =F37*E37 -> 1650000 | H37: 0 | I37: =+H37/E37 -> 0 | J37: =+F37*H37 -> 0
B38: 5.2 | C38: Acondicionamiento de Acceso a Terraza | D38: Gl | E38: 1 | F38: 3800000 | G38: =F38*E38 -> 3800000 | H38: 0 | I38: =+H38/E38 -> 0 | J38: =+F38*H38 -> 0
A39: 6 | C39: CUBIERTA | G39: =+SUM(G40:G45) -> 33191144 | J39: =+SUM(J40:J45) -> 0
B40: 6.1 | C40: Recorrido General de Cubierta Principal en UPVC | D40: M2 | E40: 312 | F40: 25000 | G40: =+E40*F40 -> 7800000 | H40: 0 | I40: =+H40/E40 -> 0 | J40: =+F40*H40 -> 0
B41: 6.2 | C41: Impermeabilizacion de Placa de Concreto en Terraza | D41: M2 | E41: 113.32 | F41: 21964 | G41: =+E41*F41 -> 2488960.5 | H41: 0 | I41: =+H41/E41 -> 0 | J41: =+F41*H41 -> 0
B42: 6.3 | C42: Desmonte y Suministro e Instalacion de Teja Translucida | D42: M2 | E42: 115 | F42: 52750 | G42: =+E42*F42 -> 6066250 | H42: 0 | I42: =+H42/E42 -> 0 | J42: =+F42*H42 -> 0
B43: 6.4 | C43: Suministro e Instalacion de Alfajia en Lamina Galvanizada | D43: ML | E43: =24+24+42 -> 90 | F43: 45000 | G43: =+E43*F43 -> 4050000 | H43: 0 | I43: =+H43/E43 -> 0 | J43: =+F43*H43 -> 0
B44: 6.5 | C44: Suministro e Instalacion de Anclajes Certificados | D44: UN | E44: 25 | F44: 405000 | G44: =+E44*F44 -> 10125000 | H44: 0 | I44: =+H44/E44 -> 0 | J44: =+F44*H44 -> 0
B45: 6.6 | C45: Reemplazo de Pasto Sintetico por Enchape | D45: Gl | E45: 1 | F45: 2660933 | G45: =+E45*F45 -> 2660933 | H45: 0 | I45: =+H45/E45 -> 0 | J45: =+F45*H45 -> 0
A46: 7 | C46: Aseo General y Retiro de Escombros | G46: =+G47 -> 1000000 | J46: =+J47 -> 0
B47: 7.1 | C47: Aseo y Retiro de Escombros | D47: GLB | E47: 1 | F47: 1000000 | G47: =F47*E47 -> 1000000 | H47: 0 | I47: =+H47/E47 -> 0 | J47: =+F47*H47 -> 0
A48: Aprobado: Ing. Luis Fernando Márquez Jaramillo-Interventoria | D48: TOTAL DIRECTOS | G48: =+G6+G9+G19+G34+G36+G39+G46 -> 2.9147881e+08 | H48: T. directos | J48: =+J6+J9+J19+J34+J36+J39+J46 -> 51035660
D49: IVA | F49: 0.19 | G49: =+G48*F49 -> 55380973 | H49: IVA | I49: 0.19 | J49: =J48*I49 -> 9696775.4
D50: TOTAL PROPUESTA | G50: =G49+G48 -> 3.4685978e+08 | H50: Total Vr. Acta | J50: =J48+J49 -> 60732435
H51: retefuente | I51: 0.02 | J51: =J48*I51 -> 1020713.2
H52: amortizac anticipo | I52: 0.2 | J52: =+J50*I52 -> 12146487
H53: retegarantia | I53: 0.1 | J53: =+J50*I53 -> 6073243.5
H54: Total Desembolso | J54: =+J50-J51-J52-J53 -> 41491991
C56: Valor Contrato | E56: =+G50 -> 3.4685978e+08
C57: Valor Anticipo | E57: =+E56*20% -> 69371956
C58: Vr Amortizacion Anticipo esta acta | D58: =+E58/E57 -> 0.17509218 | E58: =+J52 -> 12146487
C59: Saldo por Amortizar | E59: =+E57-E58 -> 57225469
C60: Vr Esta Acta | E60: =+J50 -> 60732435
C61: % ejecucion | E61: =+E60/E56 -> 0.17509218

Sheet acta 02 dic 15 2025
A1: ACTA 01 DE AVANCE DE OBRA-EDIF PANORAMIKA
A2: Contratante: Edificio Panoramika PH | D2: INTERVENTOR: Ing. Luis Fernando Márquez Jaramillo
A3: Contratista: Freshouse SAS | D3: FECHA: 19/01/2026 | G3: PNK-001-2025 | H3: Acta 01- Periodo del | K3: Acta 02- Periodo del | N3: Acta 03- Periodo del | Q3: Acumulado de actas
A4: Periodo de Ejecucion: | H4: sept 22 a noviembre 5 de 2025 | K4: nov 06 a dic 05 de 2025 | N4: dic 06 a enero 19 de 2025 | Q4: sept 22 a enero 19 de 2026
A5: CAPT | B5: ITEMS | C5: DESCRIPCION | D5: UNIDAD | E5: CANTIDAD | F5: VR UNITARIO | G5: VALOR DIRECTO ACTIVIDAD | H5: Cantidad | I5: % avance | J5: Valor Total | K5: Cantidad | L5: % avance | M5: Valor Total | N5: Cantidad | O5: % avance | P5: Valor Total | Q5: Cantidad | R5: % avance | S5: Valor Total
A6: 1.0 | C6: PRELIMINARES | G6: =+G7+G8 -> 880000 | J6: =+J7+J8 -> 707500 | M6: =+M7+M8 -> 57500 | P6: =+P7+P8 -> 57500 | S6: =+S7+S8 -> 822500
B7: 1.1 | C7: Campamento | D7: Gl | E7: 1 | F7: 650000 | G7: =F7*E7 -> 650000 | H7: 1 | I7: =+H7/E7 -> 1 | J7: =+H7*F7 -> 650000 | K7: 0 | L7: =K7/E7 -> 0 | M7: =+K7*F7 -> 0 | N7: 0 | O7: =N7/E7 -> 0 | P7: =+N7*F7 -> 0 | Q7: =H7+K7+N7 -> 1 | R7: =Q7/E7 -> 1 | S7: =+Q7*F7 -> 650000
B8: 1.2 | C8: Señalizacion y Seguridad | D8: Gl | E8: 1 | F8: 230000 | G8: =F8*E8 -> 230000 | H8: 0.25 | I8: =+H8/E8 -> 0.25 | J8: =+H8*F8 -> 57500 | K8: 0.25 | L8: =K8/E8 -> 0.25 | M8: =+K8*F8 -> 57500 | N8: 0.25 | O8: =N8/E8 -> 0.25 | P8: =+N8*F8 -> 57500 | Q8: =H8+K8+N8 -> 0.75 | R8: =Q8/E8 -> 0.75 | S8: =+Q8*F8 -> 172500
A9: 2 | C9: PREPARACION DE SUPERFICIES | G9: =+G10+G14 -> 56542255 | J9: =+J10+J14 -> 10058452 | M9: =+M10+M14 -> #REF! | P9: =+P10+P14 -> 0 | S9: =+S10+S14 -> #REF!
B10: 2.1 | C10: LAVADO Y LIMPIEZA | G10: =+SUM(G11:G13) -> 22197398 | J10: =+SUM(J11:J13) -> 9529202.1 | M10: =+SUM(M11:M13) -> #REF! | P10: =+SUM(P11:P13) -> 0 | S10: =+SUM(S11:S13) -> #REF!
B11: 2.1.1 | C11: Lavado de Fachadas Externas (blanco, gris, negro, color madera) | D11: M2 | E11: 2535.74 | F11: 3300 | G11: =F11*E11 -> 8367942 | H11: 988.22935 | I11: =+H11/E11 -> 0.3897203 | J11: =+F11*H11 -> 3261156.9 | K11: =Lavado!#REF! -> #REF! | L11: =K11/E11 -> #REF! | M11: =+K11*F11 -> #REF! | N11: =Lavado!X72 -> 0 | O11: =N11/E11 -> 0 | P11: =+N11*F11 -> 0 | Q11: =H11+K11+N11 -> #REF! | R11: =Q11/E11 -> #REF! | S11: =+Q11*F11 -> #REF!
B12: 2.1.2 | C12: Limpieza de carpinteria en aluminio (Ventanas, marcos, pasamanos y balcones) | D12: M2 | E12: 1970.54 | F12: 3400 | G12: =F12*E12 -> 6699836 | H12: 686.73565 | I12: =+H12/E12 -> 0.34850125 | J12: =+F12*H12 -> 2334901.2 | K12: =Lavado!#REF! -> #REF! | L12: =K12/E12 -> #REF! | M12: =+K12*F12 -> #REF! | N12: =Lavado!X73 -> 0 | O12: =N12/E12 -> 0 | P12: =+N12*F12 -> 0 | Q12: =H12+K12+N12 -> #REF! | R12: =Q12/E12 -> #REF! | S12: =+Q12*F12 -> #REF!
B13: 2.1.3 | C13: Limpieza de fachadas internas | D13: M2 | E13: 2640.6 | F13: 2700 | G13: =F13*E13 -> 7129620 | H13: 1456.72 | I13: =+H13/E13 -> 0.5516625 | J13: =+F13*H13 -> 3933144 | K13: =2640*0.4 -> 1056 | L13: =K13/E13 -> 0.39990911 | M13: =+K13*F13 -> 2851200 | N13: 0 | O13: =N13/E13 -> 0 | P13: =+N13*F13 -> 0 | Q13: =H13+K13+N13 -> 2512.72 | R13: =Q13/E13 -> 0.95157161 | S13: =+Q13*F13 -> 6784344
B14: 2.2 | C14: REPARACIONES Y TRATAMIENTOS ESPECIALES en Fachada | G14: =SUM(G15:G19) -> 34344857 | J14: =SUM(J15:J19) -> 529250 | M14: =SUM(M15:M19) -> 0 | P14: =SUM(P15:P19) -> 0 | S14: =SUM(S15:S19) -> 529250
B15: 2.2.1 | C15: Suministro y Reposicion de mortero quemado o desprendido | D15: M2 | E15: 40 | F15: 39400 | G15: =F15*E15 -> 1576000 | H15: 0 | I15: =+H15/E15 -> 0 | J15: =+F15*H15 -> 0 | K15: 0 | L15: =K15/E15 -> 0 | M15: =+K15*F15 -> 0 | N15: 0 | O15: =N15/E15 -> 0 | P15: =+N15*F15 -> 0 | Q15: =H15+K15+N15 -> 0 | R15: =Q15/E15 -> 0 | S15: =+Q15*F15 -> 0
B16: 2.2.2 | C16: Suministro y Reposición de graniplast - silcoplast deteriorado | D16: M2 | E16: =+SUM(E22:E24)*15% -> 441.8865 | F16: 36500 | G16: =F16*E16 -> 16128857 | H16: 14.5 | I16: =+H16/E16 -> 0.032813856 | J16: =+F16*H16 -> 529250 | K16: =Sicoplast!AA22 -> 0 | L16: =K16/E16 -> 0 | M16: =+K16*F16 -> 0 | N16: =Sicoplast!AF22 -> 0 | O16: =N16/E16 -> 0 | P16: =+N16*F16 -> 0 | Q16: =H16+K16+N16 -> 14.5 | R16: =Q16/E16 -> 0.032813856 | S16: =+Q16*F16 -> 529250
B17: 2.2.3 | C17: Retiro y Sustitucion de laminas de Superboard en mal estado | D17: M2 | E17: 100 | F17: 87000 | G17: =F17*E17 -> 8700000 | H17: 0 | I17: =+H17/E17 -> 0 | J17: =+F17*H17 -> 0 | K17: 0 | L17: =K17/E17 -> 0 | M17: =+K17*F17 -> 0 | N17: 0 | O17: =N17/E17 -> 0 | P17: =+N17*F17 -> 0 | Q17: =H17+K17+N17 -> 0 | R17: =Q17/E17 -> 0 | S17: =+Q17*F17 -> 0
B18: 2.2.4 | C18: Retiro y Sustitucion de laminas de superboard tipo Siding Color Madera | D18: M2 | E18: 60 | F18: 87000 | G18: =F18*E18 -> 5220000 | H18: 0 | I18: =+H18/E18 -> 0 | J18: =+F18*H18 -> 0 | K18: 0 | L18: =K18/E18 -> 0 | M18: =+K18*F18 -> 0 | N18: 0 | O18: =N18/E18 -> 0 | P18: =+N18*F18 -> 0 | Q18: =H18+K18+N18 -> 0 | R18: =Q18/E18 -> 0 | S18: =+Q18*F18 -> 0
B19: 2.2.5 | C19: Retiro y Sustitución de láminas de Drywall en mal estado, interiores y exteriores | D19: M2 | E19: 40 | F19: 68000 | G19: =F19*E19 -> 2720000 | H19: 0 | I19: =+H19/E19 -> 0 | J19: =+F19*H19 -> 0 | K19: 0 | L19: =K19/E19 -> 0 | M19: =+K19*F19 -> 0 | N19: 0 | O19: =N19/E19 -> 0 | P19: =+N19*F19 -> 0 | Q19: =H19+K19+N19 -> 0 | R19: =Q19/E19 -> 0 | S19: =+Q19*F19 -> 0
A20: 3 | C20: PINTURA | G20: =+G21+G28+G31 -> 130602942 | J20: =+J21+J28+J31 -> 33667857 | M20: =+M21+M28+M31 -> #REF! | P20: =+P21+P28+P31 -> #REF! | S20: =+S21+S28+S31 -> #REF!
B21: 3.1 | C21: Pintura Tipo Koraza para Exteriores | G21: =+SUM(G22:G27) -> 78531075 | J21: =+SUM(J22:J27) -> 16187217 | M21: =+SUM(M22:M27) -> #REF! | P21: =+SUM(P22:P27) -> #REF! | S21: =+SUM(S22:S27) -> #REF!
B22: 3.1.1 | C22: Pintura blanca para exteriores tipo Koraza Proteccion Sol y Lluvia Impermeabilizante | D22: M2 | E22: 2295.82 | F22: 21000 | G22: =F22*E22 -> 48212220 | H22: 471.33018 | I22: =+H22/E22 -> 0.20529928 | J22: =+F22*H22 -> 9897933.8 | K22: =Pintura!#REF! -> #REF! | L22: =K22/E22 -> #REF! | M22: =+K22*F22 -> #REF! | N22: =Pintura!#REF! -> #REF! | O22: =N22/E22 -> #REF! | P22: =+N22*F22 -> #REF! | Q22: =H22+K22+N22 -> #REF! | R22: =Q22/E22 -> #REF! | S22: =+Q22*F22 -> #REF!
B23: 3.1.2 | C23: Pintura gris para exteriores tipo Koraza Proteccion Sol y Lluvia Impermeabilizante | D23: M2 | E23: 467.17 | F23: 21000 | G23: =F23*E23 -> 9810570 | H23: 181.28084 | I23: =+H23/E23 -> 0.38804041 | J23: =+F23*H23 -> 3806897.6 | K23: =Pintura!#REF! -> #REF! | L23: =K23/E23 -> #REF! | M23: =+K23*F23 -> #REF! | N23: =Pintura!#REF! -> #REF! | O23: =N23/E23 -> #REF! | P23: =+N23*F23 -> #REF! | Q23: =H23+K23+N23 -> #REF! | R23: =Q23/E23 -> #REF! | S23: =+Q23*F23 -> #REF!
B24: 3.1.3 | C24: Pintura negra para exteriores tipo Koraza Proteccion Sol y Lluvia Impermeabilizante | D24: M2 | E24: 182.92 | F24: 21000 | G24: =F24*E24 -> 3841320 | H24: 14.502467 | I24: =+H24/E24 -> 0.079283114 | J24: =+F24*H24 -> 304551.81 | K24: =Pintura!#REF! -> #REF! | L24: =K24/E24 -> #REF! | M24: =+K24*F24 -> #REF! | N24: =Pintura!#REF! -> #REF! | O24: =N24/E24 -> #REF! | P24: =+N24*F24 -> #REF! | Q24: =H24+K24+N24 -> #REF! | R24: =Q24/E24 -> #REF! | S24: =+Q24*F24 -> #REF!
B25: 3.1.4 | C25: Pintura Tipo Koraza Proteccion Sol y Lluvia Impermeabilizante sobre lamina tipo siding (color madera cedro) | D25: M2 | E25: 565.54 | F25: 17500 | G25: =F25*E25 -> 9896950 | H25: 72.512336 | I25: =+H25/E25 -> 0.12821787 | J25: =+F25*H25 -> 1268965.9 | K25: =Pintura!#REF! -> #REF! | L25: =K25/E25 -> #REF! | M25: =+K25*F25 -> #REF! | N25: =Pintura!#REF! -> #REF! | O25: =N25/E25 -> #REF! | P25: =+N25*F25 -> #REF! | Q25: =H25+K25+N25 -> #REF! | R25: =Q25/E25 -> #REF! | S25: =+Q25*F25 -> #REF!
B26: 3.1.5 | C26: Pintura gris basalto koraza (parqueaderos) | D26: M2 | E26: 161.75 | F26: 17500 | G26: =F26*E26 -> 2830625 | H26: 0 | I26: =+H26/E26 -> 0 | J26: =+F26*H26 -> 0 | K26: 0 | L26: =K26/E26 -> 0 | M26: =+K26*F26 -> 0 | N26: 0 | O26: =N26/E26 -> 0 | P26: =+N26*F26 -> 0 | Q26: =H26+K26+N26 -> 0 | R26: =Q26/E26 -> 0 | S26: =+Q26*F26 -> 0
B27: 3.1.6 | C27: Pintura sobre alfajías Tipo Koraza Proteccion Sol y Lluvia Impermeabilizante | D27: ML | E27: 532.35 | F27: 7400 | G27: =F27*E27 -> 3939390 | H27: 122.82 | I27: =+H27/E27 -> 0.23071288 | J27: =+F27*H27 -> 908868 | K27: =Pintura!#REF! -> #REF! | L27: =K27/E27 -> #REF! | M27: =+K27*F27 -> #REF! | N27: =Pintura!#REF! -> #REF! | O27: =N27/E27 -> #REF! | P27: =+N27*F27 -> #REF! | Q27: =H27+K27+N27 -> #REF! | R27: =Q27/E27 -> #REF! | S27: =+Q27*F27 -> #REF!
B28: 3.2 | C28: Pintura Tipo Pintulux 3 en 1 sobre Elementos Metalicos | G28: =+SUM(G29:G30) -> 8043387 | J28: =+SUM(J29:J30) -> 0 | M28: =+SUM(M29:M30) -> 0 | P28: =+SUM(P29:P30) -> 0 | S28: =+SUM(S29:S30) -> 0
B29: 3.2.1 | C29: Pintura Pintulux 3 en 1 (carpinteria metalica parqueaderos) | D29: M2 | E29: 245.69 | F29: 22300 | G29: =F29*E29 -> 5478887 | H29: 0 | I29: =+H29/E29 -> 0 | J29: =+F29*H29 -> 0 | K29: 0 | L29: =K29/E29 -> 0 | M29: =+K29*F29 -> 0 | N29: 0 | O29: =N29/E29 -> 0 | P29: =+N29*F29 -> 0 | Q29: =H29+K29+N29 -> 0 | R29: =Q29/E29 -> 0 | S29: =+Q29*F29 -> 0
B30: 3.2.2 | C30: Pintura Pintulux 3 en 1 en carpinteria metalica de soporte y de guia de teja translucida | D30: M2 | E30: 115 | F30: 22300 | G30: =F30*E30 -> 2564500 | H30: 0 | I30: =+H30/E30 -> 0 | J30: =+F30*H30 -> 0 | K30: 0 | L30: =K30/E30 -> 0 | M30: =+K30*F30 -> 0 | N30: 0 | O30: =N30/E30 -> 0 | P30: =+N30*F30 -> 0 | Q30: =H30+K30+N30 -> 0 | R30: =Q30/E30 -> 0 | S30: =+Q30*F30 -> 0
B31: 3.3 | C31: Pintura Tipo Viniltex Advanced de Pintuco en Interiores | G31: =+SUM(G32:G33) -> 44028480 | J31: =+SUM(J32:J33) -> 17480640 | M31: =+SUM(M32:M33) -> 8169600 | P31: =+SUM(P32:P33) -> 0 | S31: =+SUM(S32:S33) -> 25650240
B32: 3.3.1 | C32: Pintura para Muros Interiores tipo 1 viniltex advanced de pintuco color blanco | D32: M2 | E32: 2640.6 | F32: 12000 | G32: =F32*E32 -> 31687200 | H32: 874.032 | I32: =+H32/E32 -> 0.3309975 | J32: =+F32*H32 -> 10488384 | K32: 680.8 | L32: =K32/E32 -> 0.25782019 | M32: =+K32*F32 -> 8169600 | N32: 0 | O32: =N32/E32 -> 0 | P32: =+N32*F32 -> 0 | Q32: =H32+K32+N32 -> 1554.832 | R32: =Q32/E32 -> 0.58881769 | S32: =+Q32*F32 -> 18657984
B33: 3.3.2 | C33: Pintura para Cielorrasos Interiores Tipo Viniltex Advanced de Pintuco Color Blanco | D33: M2 | E33: 1028.44 | F33: 12000 | G33: =F33*E33 -> 12341280 | H33: 582.688 | I33: =+H33/E33 -> 0.56657462 | J33: =+F33*H33 -> 6992256 | K33: 0 | L33: =K33/E33 -> 0 | M33: =+K33*F33 -> 0 | N33: 0 | O33: =N33/E33 -> 0 | P33: =+N33*F33 -> 0 | Q33: =H33+K33+N33 -> 582.688 | R33: =Q33/E33 -> 0.56657462 | S33: =+Q33*F33 -> 6992256
A34: 4 | C34: CARPINTERIA EN ALUMINIO y Vidrio | G34: =+SUM(G35:G37) -> 13115377 | J34: =+SUM(J35:J37) -> 1869038 | M34: =+SUM(M35:M37) -> #REF! | P34: =+SUM(P35:P37) -> #REF! | S34: =+SUM(S35:S37) -> #REF!
B35: 4.1 | C35: Resellado Perimetral de Elementos Vidriados en Fachada | D35: ML | E35: 1610.82 | F35: 5700 | G35: =F35*E35 -> 9181674 | H35: 214.4 | I35: =+H35/E35 -> 0.13309991 | J35: =+F35*H35 -> 1222080 | K35: =Sellos!#REF! -> #REF! | L35: =K35/E35 -> #REF! | M35: =+K35*F35 -> #REF! | N35: =Sellos!#REF! -> #REF! | O35: =N35/E35 -> #REF! | P35: =+N35*F35 -> #REF! | Q35: =H35+K35 -> #REF! | R35: =Q35/E35 -> #REF! | S35: =+Q35*F35 -> #REF!
B36: 4.2 | C36: Desmonte y vuelta a instalar de vidrio templado de cerramiento en terraza y Jacuzzi | D36: M2 | E36: 86.09 | F36: 16700 | G36: =F36*E36 -> 1437703 | H36: 38.74 | I36: =+H36/E36 -> 0.44999419 | J36: =+F36*H36 -> 646958 | K36: 0 | L36: =K36/E36 -> 0 | M36: =+K36*F36 -> 0 | N36: 0 | O36: =N36/E36 -> 0 | P36: =+N36*F36 -> 0 | Q36: =H36+K36 -> 38.74 | R36: =Q36/E36 -> 0.44999419 | S36: =+Q36*F36 -> 646958
B37: 4.3 | C37: Suministro e instalación de cortagoteras en aluminio | D37: ML | E37: 48 | F37: 52000 | G37: =F37*E37 -> 2496000 | H37: 0 | I37: =+H37/E37 -> 0 | J37: =+F37*H37 -> 0 | K37: 0 | L37: =K37/E37 -> 0 | M37: =+K37*F37 -> 0 | N37: 0 | O37: =N37/E37 -> 0 | P37: =+N37*F37 -> 0 | Q37: =H37+K37 -> 0 | R37: =Q37/E37 -> 0 | S37: =+Q37*F37 -> 0
A38: 5 | C38: VARIOS | G38: =++G39+G40 -> 5450000 | J38: =++J39+J40 -> 0 | M38: =++M39+M40 -> 0 | P38: =++P39+P40 -> 0 | S38: =++S39+S40 -> 0
B39: 5.1 | C39: Media caña en concreto incluye impermeabilizado | D39: ML | E39: 30 | F39: 55000 | G39: =F39*E39 -> 1650000 | H39: 0 | I39: =+H39/E39 -> 0 | J39: =+F39*H39 -> 0 | K39: 0 | L39: =K39/E39 -> 0 | M39: =+K39*F39 -> 0 | N39: 0 | O39: =N39/E39 -> 0 | P39: =+N39*F39 -> 0 | Q39: =H39+K39 -> 0 | R39: =Q39/E39 -> 0 | S39: =+Q39*F39 -> 0
B40: 5.2 | C40: Acondicionamiento de Acceso a Terraza | D40: Gl | E40: 1 | F40: 3800000 | G40: =F40*E40 -> 3800000 | H40: 0 | I40: =+H40/E40 -> 0 | J40: =+F40*H40 -> 0 | K40: 0 | L40: =K40/E40 -> 0 | M40: =+K40*F40 -> 0 | N40: 0 | O40: =N40/E40 -> 0 | P40: =+N40*F40 -> 0 | Q40: =H40+K40 -> 0 | R40: =Q40/E40 -> 0 | S40: =+Q40*F40 -> 0
A41: 6 | C41: CUBIERTA | G41: =+SUM(G42:G47) -> 33191144 | J41: =+SUM(J42:J47) -> 8100000 | M41: =+SUM(M42:M47) -> 0 | P41: =+SUM(P42:P47) -> 0 | S41: =+SUM(S42:S47) -> 8100000
B42: 6.1 | C42: Recorrido General de Cubierta Principal en UPVC | D42: M2 | E42: 312 | F42: 25000 | G42: =+E42*F42 -> 7800000 | H42: 0 | I42: =+H42/E42 -> 0 | J42: =+F42*H42 -> 0 | K42: 0 | L42: =K42/E42 -> 0 | M42: =+K42*F42 -> 0 | N42: 0 | O42: =N42/E42 -> 0 | P42: =+N42*F42 -> 0 | Q42: =H42+K42 -> 0 | R42: =Q42/E42 -> 0 | S42: =+Q42*F42 -> 0
B43: 6.2 | C43: Impermeabilizacion de Placa de Concreto en Terraza | D43: M2 | E43: 113.32 | F43: 21964 | G43: =+E43*F43 -> 2488960.5 | H43: 0 | I43: =+H43/E43 -> 0 | J43: =+F43*H43 -> 0 | K43: 0 | L43: =K43/E43 -> 0 | M43: =+K43*F43 -> 0 | N43: 0 | O43: =N43/E43 -> 0 | P43: =+N43*F43 -> 0 | Q43: =H43+K43 -> 0 | R43: =Q43/E43 -> 0 | S43: =+Q43*F43 -> 0
B44: 6.3 | C44: Desmonte y Suministro e Instalacion de Teja Translucida | D44: M2 | E44: 115 | F44: 52750 | G44: =+E44*F44 -> 6066250 | H44: 0 | I44: =+H44/E44 -> 0 | J44: =+F44*H44 -> 0 | K44: 0 | L44: =K44/E44 -> 0 | M44: =+K44*F44 -> 0 | N44: 0 | O44: =N44/E44 -> 0 | P44: =+N44*F44 -> 0 | Q44: =H44+K44 -> 0 | R44: =Q44/E44 -> 0 | S44: =+Q44*F44 -> 0
B45: 6.4 | C45: Suministro e Instalacion de Alfajia en Lamina Galvanizada | D45: ML | E45: =24+24+42 -> 90 | F45: 45000 | G45: =+E45*F45 -> 4050000 | H45: 0 | I45: =+H45/E45 -> 0 | J45: =+F45*H45 -> 0 | K45: 0 | L45: =K45/E45 -> 0 | M45: =+K45*F45 -> 0 | N45: 0 | O45: =N45/E45 -> 0 | P45: =+N45*F45 -> 0 | Q45: =H45+K45 -> 0 | R45: =Q45/E45 -> 0 | S45: =+Q45*F45 -> 0
B46: 6.5 | C46: Suministro e Instalacion de Anclajes Certificados | D46: UN | E46: 25 | F46: 405000 | G46: =+E46*F46 -> 10125000 | H46: 20 | I46: =+H46/E46 -> 0.8 | J46: =+F46*H46 -> 8100000 | K46: 0 | L46: =K46/E46 -> 0 | M46: =+K46*F46 -> 0 | N46: 0 | O46: =N46/E46 -> 0 | P46: =+N46*F46 -> 0 | Q46: =H46+K46 -> 20 | R46: =Q46/E46 -> 0.8 | S46: =+Q46*F46 -> 8100000
B47: 6.6 | C47: Reemplazo de Pasto Sintetico por Enchape | D47: Gl | E47: 1 | F47: 2660933 | G47: =+E47*F47 -> 2660933 | H47: 0 | I47: =+H47/E47 -> 0 | J47: =+F47*H47 -> 0 | K47: 0 | L47: =K47/E47 -> 0 | M47: =+K47*F47 -> 0 | N47: 0 | O47: =N47/E47 -> 0 | P47: =+N47*F47 -> 0 | Q47: =H47+K47 -> 0 | R47: =Q47/E47 -> 0 | S47: =+Q47*F47 -> 0
A48: 7 | C48: Aseo General y Retiro de Escombros | G48: =+G49 -> 1000000 | J48: =+J49 -> 0 | M48: =+M49 -> 0 | P48: =+P49 -> 0 | S48: =+S49 -> 0
B49: 7.1 | C49: Aseo y Retiro de Escombros | D49: GLB | E49: 1 | F49: 1000000 | G49: =F49*E49 -> 1000000 | H49: 0 | I49: =+H49/E49 -> 0 | J49: =+F49*H49 -> 0 | K49: 0 | L49: =K49/E49 -> 0 | M49: =+K49*F49 -> 0 | N49: 0 | O49: =N49/E49 -> 0 | P49: =+N49*F49 -> 0 | Q49: =H49+K49 -> 0 | R49: =Q49/E49 -> 0 | S49: =+Q49*F49 -> 0
A50: Aprobado: Ing. Luis Fernando Márquez Jaramillo-Interventoria | D50: TOTALES DIRECTOS | G50: =+G6+G9+G20+G34+G38+G41+G48 -> 2.4078172e+08 | H50: T. directos | J50: =+J6+J9+J20+J34+J38+J41+J48 -> 54402847 | K50: T. directos | M50: =+M6+M9+M20+M34+M38+M41+M48 -> #REF! | N50: T. directos | P50: =+P6+P9+P20+P34+P38+P41+P48 -> #REF! | Q50: T. directos | S50: =+S6+S9+S20+S34+S38+S41+S48 -> #REF!
D51: Administracion | F51: 0.1 | G51: =+$G$50*F51 -> 24078172 | H51: Admon | I51: 0.1 | J51: =+J50*I51 -> 5440284.7 | K51: Admon | L51: 0.1 | M51: =+M50*L51 -> #REF! | N51: Admon | O51: 0.1 | P51: =+P50*O51 -> #REF! | Q51: Admon | R51: 0.1 | S51: =+S50*R51 -> #REF!
D52: Imprevistos | F52: 0.07 | G52: =+$G$50*F52 -> 16854720 | H52: Imprev. | I52: 0.07 | J52: =+J50*I52 -> 3808199.3 | K52: Imprev. | L52: 0.07 | M52: =+M50*L52 -> #REF! | N52: Imprev. | O52: 0.07 | P52: =+P50*O52 -> #REF! | Q52: Imprev. | R52: 0.07 | S52: =+S50*R52 -> #REF!
D53: Utilidad | F53: 0.05 | G53: =+$G$50*F53 -> 12039086 | H53: Utilidad | I53: 0.05 | J53: =+J50*I53 -> 2720142.4 | K53: Utilidad | L53: 0.05 | M53: =+M50*L53 -> #REF! | N53: Utilidad | O53: 0.05 | P53: =+P50*O53 -> #REF! | Q53: Utilidad | R53: 0.05 | S53: =+S50*R53 -> #REF!
D54: TOTAL SIN IVA | G54: =+SUM(G50:G53) -> 2.937537e+08 | H54: TOTAL SIN IVA | J54: =+SUM(J50:J53) -> 66371474 | K54: TOTAL SIN IVA | M54: =+SUM(M50:M53) -> #REF! | N54: TOTAL SIN IVA | P54: =+SUM(P50:P53) -> #REF! | Q54: TOTAL SIN IVA | S54: =+SUM(S50:S53) -> #REF!
D55: IVA/U | F55: 0.19 | G55: =+G53*F55 -> 2287426.3 | H55: IVA/U | I55: 0.19 | J55: =+J53*I55 -> 516827.05 | K55: IVA/U | L55: 0.19 | M55: =+M53*L55 -> #REF! | N55: IVA/U | O55: 0.19 | P55: =+P53*O55 -> #REF! | Q55: IVA/U | R55: 0.19 | S55: =+S53*R55 -> #REF!
D56: TOTAL PROPUESTA | G56: =+G54+G55 -> 296041122 | H56: Total Vr. Acta | J56: =+J54+J55 -> 66888301 | K56: Total Vr. Acta | M56: =+M54+M55 -> #REF! | N56: Total Vr. Acta | P56: =+P54+P55 -> #REF! | Q56: Total Vr. Acta | S56: =+S54+S55 -> #REF!
H57: retefuente | I57: 0.02 | J57: =+J54*I57 -> 1327429.5 | K57: retefuente | L57: 0.02 | M57: =+M54*L57 -> #REF! | N57: retefuente | O57: 0.02 | P57: =+P54*O57 -> #REF! | Q57: retefuente | R57: 0.02 | S57: =+S54*R57 -> #REF!
H58: amortizac anticipo | I58: 0.2 | J58: =+J56*I58 -> 13377660 | K58: amortizac anticipo | L58: 0.2 | M58: =+M56*L58 -> #REF! | N58: amortizac anticipo | O58: 0.2 | P58: =+P56*O58 -> #REF! | Q58: amortizac anticipo | R58: 0.2 | S58: =+S56*R58 -> #REF!
H59: retegarantia | I59: 0.1 | J59: =+J56*I59 -> 6688830.1 | K59: retegarantia | L59: 0.1 | M59: =+M56*L59 -> #REF! | N59: retegarantia | O59: 0.1 | P59: =+P56*O59 -> #REF! | Q59: retegarantia | R59: 0.1 | S59: =+S56*R59 -> #REF!
H60: Total Desembolso | J60: =+J56-J57-J58-J59 -> 45494381 | K60: Total Desembolso | M60: =+M56-M57-M58-M59 -> #REF! | N60: Total Desembolso | P60: =+P56-P57-P58-P59 -> #REF! | Q60: Total Desembolso | S60: =+S56-S57-S58-S59 -> #REF!
C62: Valor Contrato | E62: =+G56 -> 296041122
C63: Valor Anticipo | E63: =+E62*20% -> 59208224
C64: Vr Amortizacion Anticipo esta acta | D64: =+E64/E63 -> 0.2259426 | E64: =+J58 -> 13377660
C65: Saldo por Amortizar | E65: =+E63-E64 -> 45830564
C66: Vr Esta Acta | E66: =+J56 -> 66888301
C67: % ejecucion | E67: =+E66/E62 -> 0.2259426

Sheet acta 03 enero 21 2026
A1: ACTA 03 DE AVANCE DE OBRA-EDIF PANORAMIKA
A2: Contratante: Edificio Panoramika PH | D2: INTERVENTOR: Ing. Luis Fernando Márquez Jaramillo
A3: Contratista: Freshouse SAS | D3: FECHA: 21/01/2026 | G3: PNK-001-2025 | H3: Acta 01- Periodo del | K3: Acta 02- Periodo del | N3: Acta 03- Periodo del | Q3: Acumulado de actas
A4: Periodo de Ejecucion: | H4: sept 22 a noviembre 5 de 2025 | K4: nov 06 a dic 05 de 2025 | N4: dic 06 a enero 19 de 2025 | Q4: sept 22 a enero 19 de 2026
A5: CAPT | B5: ITEMS | C5: DESCRIPCION | D5: UNIDAD | E5: CANTIDAD | F5: VR UNITARIO | G5: VALOR DIRECTO ACTIVIDAD | H5: Cantidad | I5: % avance | J5: Valor Total | K5: Cantidad | L5: % avance | M5: Valor Total | N5: Cantidad | O5: % avance | P5: Valor Total | Q5: Cantidad | R5: % avance | S5: Valor Total
A6: 1.0 | C6: PRELIMINARES | G6: =+G7+G8 -> 880000 | J6: =+J7+J8 -> 707500 | M6: =+M7+M8 -> 57500 | P6: =+P7+P8 -> 57500 | S6: =+S7+S8 -> 822500
B7: 1.1 | C7: Campamento | D7: Gl | E7: 1 | F7: 650000 | G7: =F7*E7 -> 650000 | H7: 1 | I7: =+H7/E7 -> 1 | J7: =+H7*F7 -> 650000 | K7: 0 | L7: =K7/E7 -> 0 | M7: =+K7*F7 -> 0 | N7: 0 | O7: =N7/E7 -> 0 | P7: =+N7*F7 -> 0 | Q7: =H7+K7+N7 -> 1 | R7: =Q7/E7 -> 1 | S7: =+Q7*F7 -> 650000
B8: 1.2 | C8: Señalizacion y Seguridad | D8: Gl | E8: 1 | F8: 230000 | G8: =F8*E8 -> 230000 | H8: 0.25 | I8: =+H8/E8 -> 0.25 | J8: =+H8*F8 -> 57500 | K8: 0.25 | L8: =K8/E8 -> 0.25 | M8: =+K8*F8 -> 57500 | N8: 0.25 | O8: =N8/E8 -> 0.25 | P8: =+N8*F8 -> 57500 | Q8: =H8+K8+N8 -> 0.75 | R8: =Q8/E8 -> 0.75 | S8: =+Q8*F8 -> 172500
A9: 2 | C9: PREPARACION DE SUPERFICIES | G9: =+G10+G14 -> 56542255 | J9: =+J10+J14 -> 10058452 | M9: =+M10+M14 -> #REF! | P9: =+P10+P14 -> #REF! | S9: =+S10+S14 -> #REF!
B10: 2.1 | C10: LAVADO Y LIMPIEZA | G10: =+SUM(G11:G13) -> 22197398 | J10: =+SUM(J11:J13) -> 9529202.1 | M10: =+SUM(M11:M13) -> #REF! | P10: =+SUM(P11:P13) -> #REF! | S10: =+SUM(S11:S13) -> #REF!
B11: 2.1.1 | C11: Lavado de Fachadas Externas (blanco, gris, negro, color madera) | D11: M2 | E11: 2535.74 | F11: 3300 | G11: =F11*E11 -> 8367942 | H11: 988.22935 | I11: =+H11/E11 -> 0.3897203 | J11: =+F11*H11 -> 3261156.9 | K11: =Lavado!#REF! -> #REF! | L11: =K11/E11 -> #REF! | M11: =+K11*F11 -> #REF! | N11: =Lavado!#REF! -> #REF! | O11: =N11/E11 -> #REF! | P11: =+N11*F11 -> #REF! | Q11: =H11+K11+N11 -> #REF! | R11: =Q11/E11 -> #REF! | S11: =+Q11*F11 -> #REF!
B12: 2.1.2 | C12: Limpieza de carpinteria en aluminio (Ventanas, marcos, pasamanos y balcones) | D12: M2 | E12: 1970.54 | F12: 3400 | G12: =F12*E12 -> 6699836 | H12: 686.73565 | I12: =+H12/E12 -> 0.34850125 | J12: =+F12*H12 -> 2334901.2 | K12: =Lavado!#REF! -> #REF! | L12: =K12/E12 -> #REF! | M12: =+K12*F12 -> #REF! | N12: =Lavado!#REF! -> #REF! | O12: =N12/E12 -> #REF! | P12: =+N12*F12 -> #REF! | Q12: =H12+K12+N12 -> #REF! | R12: =Q12/E12 -> #REF! | S12: =+Q12*F12 -> #REF!
B13: 2.1.3 | C13: Limpieza de fachadas internas | D13: M2 | E13: 2640.6 | F13: 2700 | G13: =F13*E13 -> 7129620 | H13: 1456.72 | I13: =+H13/E13 -> 0.5516625 | J13: =+F13*H13 -> 3933144 | K13: =2640*0.4 -> 1056 | L13: =K13/E13 -> 0.39990911 | M13: =+K13*F13 -> 2851200 | N13: 0 | O13: =N13/E13 -> 0 | P13: =+N13*F13 -> 0 | Q13: =H13+K13+N13 -> 2512.72 | R13: =Q13/E13 -> 0.95157161 | S13: =+Q13*F13 -> 6784344
B14: 2.2 | C14: REPARACIONES Y TRATAMIENTOS ESPECIALES en Fachada | G14: =SUM(G15:G19) -> 34344857 | J14: =SUM(J15:J19) -> 529250 | M14: =SUM(M15:M19) -> 0 | P14: =SUM(P15:P19) -> 0 | S14: =SUM(S15:S19) -> 529250
B15: 2.2.1 | C15: Suministro y Reposicion de mortero quemado o desprendido | D15: M2 | E15: 40 | F15: 39400 | G15: =F15*E15 -> 1576000 | H15: 0 | I15: =+H15/E15 -> 0 | J15: =+F15*H15 -> 0 | K15: 0 | L15: =K15/E15 -> 0 | M15: =+K15*F15 -> 0 | N15: 0 | O15: =N15/E15 -> 0 | P15: =+N15*F15 -> 0 | Q15: =H15+K15+N15 -> 0 | R15: =Q15/E15 -> 0 | S15: =+Q15*F15 -> 0
B16: 2.2.2 | C16: Suministro y Reposición de graniplast - silcoplast deteriorado | D16: M2 | E16: =+SUM(E22:E24)*15% -> 441.8865 | F16: 36500 | G16: =F16*E16 -> 16128857 | H16: 14.5 | I16: =+H16/E16 -> 0.032813856 | J16: =+F16*H16 -> 529250 | K16: =Sicoplast!AA22 -> 0 | L16: =K16/E16 -> 0 | M16: =+K16*F16 -> 0 | N16: =Sicoplast!AC36 -> 0 | O16: =N16/E16 -> 0 | P16: =+N16*F16 -> 0 | Q16: =H16+K16+N16 -> 14.5 | R16: =Q16/E16 -> 0.032813856 | S16: =+Q16*F16 -> 529250
B17: 2.2.3 | C17: Retiro y Sustitucion de laminas de Superboard en mal estado | D17: M2 | E17: 100 | F17: 87000 | G17: =F17*E17 -> 8700000 | H17: 0 | I17: =+H17/E17 -> 0 | J17: =+F17*H17 -> 0 | K17: 0 | L17: =K17/E17 -> 0 | M17: =+K17*F17 -> 0 | N17: 0 | O17: =N17/E17 -> 0 | P17: =+N17*F17 -> 0 | Q17: =H17+K17+N17 -> 0 | R17: =Q17/E17 -> 0 | S17: =+Q17*F17 -> 0
B18: 2.2.4 | C18: Retiro y Sustitucion de laminas de superboard tipo Siding Color Madera | D18: M2 | E18: 60 | F18: 87000 | G18: =F18*E18 -> 5220000 | H18: 0 | I18: =+H18/E18 -> 0 | J18: =+F18*H18 -> 0 | K18: 0 | L18: =K18/E18 -> 0 | M18: =+K18*F18 -> 0 | N18: 0 | O18: =N18/E18 -> 0 | P18: =+N18*F18 -> 0 | Q18: =H18+K18+N18 -> 0 | R18: =Q18/E18 -> 0 | S18: =+Q18*F18 -> 0
B19: 2.2.5 | C19: Retiro y Sustitución de láminas de Drywall en mal estado, interiores y exteriores | D19: M2 | E19: 40 | F19: 68000 | G19: =F19*E19 -> 2720000 | H19: 0 | I19: =+H19/E19 -> 0 | J19: =+F19*H19 -> 0 | K19: 0 | L19: =K19/E19 -> 0 | M19: =+K19*F19 -> 0 | N19: 0 | O19: =N19/E19 -> 0 | P19: =+N19*F19 -> 0 | Q19: =H19+K19+N19 -> 0 | R19: =Q19/E19 -> 0 | S19: =+Q19*F19 -> 0
A20: 3 | C20: PINTURA | G20: =+G21+G28+G31 -> 130602942 | J20: =+J21+J28+J31 -> 33667857 | M20: =+M21+M28+M31 -> #REF! | P20: =+P21+P28+P31 -> #REF! | S20: =+S21+S28+S31 -> #REF!
B21: 3.1 | C21: Pintura Tipo Koraza para Exteriores | G21: =+SUM(G22:G27) -> 78531075 | J21: =+SUM(J22:J27) -> 16187217 | M21: =+SUM(M22:M27) -> #REF! | P21: =+SUM(P22:P27) -> #REF! | S21: =+SUM(S22:S27) -> #REF!
B22: 3.1.1 | C22: Pintura blanca para exteriores tipo Koraza Proteccion Sol y Lluvia Impermeabilizante | D22: M2 | E22: 2295.82 | F22: 21000 | G22: =F22*E22 -> 48212220 | H22: 471.33018 | I22: =+H22/E22 -> 0.20529928 | J22: =+F22*H22 -> 9897933.8 | K22: =Pintura!#REF! -> #REF! | L22: =K22/E22 -> #REF! | M22: =+K22*F22 -> #REF! | N22: =Pintura!#REF! -> #REF! | O22: =N22/E22 -> #REF! | P22: =+N22*F22 -> #REF! | Q22: =H22+K22+N22 -> #REF! | R22: =Q22/E22 -> #REF! | S22: =+Q22*F22 -> #REF!
B23: 3.1.2 | C23: Pintura gris para exteriores tipo Koraza Proteccion Sol y Lluvia Impermeabilizante | D23: M2 | E23: 467.17 | F23: 21000 | G23: =F23*E23 -> 9810570 | H23: 181.28084 | I23: =+H23/E23 -> 0.38804041 | J23: =+F23*H23 -> 3806897.6 | K23: =Pintura!#REF! -> #REF! | L23: =K23/E23 -> #REF! | M23: =+K23*F23 -> #REF! | N23: =Pintura!#REF! -> #REF! | O23: =N23/E23 -> #REF! | P23: =+N23*F23 -> #REF! | Q23: =H23+K23+N23 -> #REF! | R23: =Q23/E23 -> #REF! | S23: =+Q23*F23 -> #REF!
B24: 3.1.3 | C24: Pintura negra para exteriores tipo Koraza Proteccion Sol y Lluvia Impermeabilizante | D24: M2 | E24: 182.92 | F24: 21000 | G24: =F24*E24 -> 3841320 | H24: 14.502467 | I24: =+H24/E24 -> 0.079283114 | J24: =+F24*H24 -> 304551.81 | K24: =Pintura!#REF! -> #REF! | L24: =K24/E24 -> #REF! | M24: =+K24*F24 -> #REF! | N24: =Pintura!#REF! -> #REF! | O24: =N24/E24 -> #REF! | P24: =+N24*F24 -> #REF! | Q24: =H24+K24+N24 -> #REF! | R24: =Q24/E24 -> #REF! | S24: =+Q24*F24 -> #REF!
B25: 3.1.4 | C25: Pintura Tipo Koraza Proteccion Sol y Lluvia Impermeabilizante sobre lamina tipo siding (color madera cedro) | D25: M2 | E25: 565.54 | F25: 17500 | G25: =F25*E25 -> 9896950 | H25: 72.512336 | I25: =+H25/E25 -> 0.12821787 | J25: =+F25*H25 -> 1268965.9 | K25: =Pintura!#REF! -> #REF! | L25: =K25/E25 -> #REF! | M25: =+K25*F25 -> #REF! | N25: =Pintura!#REF! -> #REF! | O25: =N25/E25 -> #REF! | P25: =+N25*F25 -> #REF! | Q25: =H25+K25+N25 -> #REF! | R25: =Q25/E25 -> #REF! | S25: =+Q25*F25 -> #REF!
B26: 3.1.5 | C26: Pintura gris basalto koraza (parqueaderos) | D26: M2 | E26: 161.75 | F26: 17500 | G26: =F26*E26 -> 2830625 | H26: 0 | I26: =+H26/E26 -> 0 | J26: =+F26*H26 -> 0 | K26: 0 | L26: =K26/E26 -> 0 | M26: =+K26*F26 -> 0 | N26: 0 | O26: =N26/E26 -> 0 | P26: =+N26*F26 -> 0 | Q26: =H26+K26+N26 -> 0 | R26: =Q26/E26 -> 0 | S26: =+Q26*F26 -> 0
B27: 3.1.6 | C27: Pintura sobre alfajías Tipo Koraza Proteccion Sol y Lluvia Impermeabilizante | D27: ML | E27: 532.35 | F27: 7400 | G27: =F27*E27 -> 3939390 | H27: 122.82 | I27: =+H27/E27 -> 0.23071288 | J27: =+F27*H27 -> 908868 | K27: =Pintura!#REF! -> #REF! | L27: =K27/E27 -> #REF! | M27: =+K27*F27 -> #REF! | N27: =Pintura!#REF! -> #REF! | O27: =N27/E27 -> #REF! | P27: =+N27*F27 -> #REF! | Q27: =H27+K27+N27 -> #REF! | R27: =Q27/E27 -> #REF! | S27: =+Q27*F27 -> #REF!
B28: 3.2 | C28: Pintura Tipo Pintulux 3 en 1 sobre Elementos Metalicos | G28: =+SUM(G29:G30) -> 8043387 | J28: =+SUM(J29:J30) -> 0 | M28: =+SUM(M29:M30) -> 0 | P28: =+SUM(P29:P30) -> 0 | S28: =+SUM(S29:S30) -> 0
B29: 3.2.1 | C29: Pintura Pintulux 3 en 1 (carpinteria metalica parqueaderos) | D29: M2 | E29: 245.69 | F29: 22300 | G29: =F29*E29 -> 5478887 | H29: 0 | I29: =+H29/E29 -> 0 | J29: =+F29*H29 -> 0 | K29: 0 | L29: =K29/E29 -> 0 | M29: =+K29*F29 -> 0 | N29: 0 | O29: =N29/E29 -> 0 | P29: =+N29*F29 -> 0 | Q29: =H29+K29+N29 -> 0 | R29: =Q29/E29 -> 0 | S29: =+Q29*F29 -> 0
B30: 3.2.2 | C30: Pintura Pintulux 3 en 1 en carpinteria metalica de soporte y de guia de teja translucida | D30: M2 | E30: 115 | F30: 22300 | G30: =F30*E30 -> 2564500 | H30: 0 | I30: =+H30/E30 -> 0 | J30: =+F30*H30 -> 0 | K30: 0 | L30: =K30/E30 -> 0 | M30: =+K30*F30 -> 0 | N30: 0 | O30: =N30/E30 -> 0 | P30: =+N30*F30 -> 0 | Q30: =H30+K30+N30 -> 0 | R30: =Q30/E30 -> 0 | S30: =+Q30*F30 -> 0
B31: 3.3 | C31: Pintura Tipo Viniltex Advanced de Pintuco en Interiores | G31: =+SUM(G32:G33) -> 44028480 | J31: =+SUM(J32:J33) -> 17480640 | M31: =+SUM(M32:M33) -> 8169600 | P31: =+SUM(P32:P33) -> 0 | S31: =+SUM(S32:S33) -> 25650240
B32: 3.3.1 | C32: Pintura para Muros Interiores tipo 1 viniltex advanced de pintuco color blanco | D32: M2 | E32: 2640.6 | F32: 12000 | G32: =F32*E32 -> 31687200 | H32: 874.032 | I32: =+H32/E32 -> 0.3309975 | J32: =+F32*H32 -> 10488384 | K32: 680.8 | L32: =K32/E32 -> 0.25782019 | M32: =+K32*F32 -> 8169600 | N32: 0 | O32: =N32/E32 -> 0 | P32: =+N32*F32 -> 0 | Q32: =H32+K32+N32 -> 1554.832 | R32: =Q32/E32 -> 0.58881769 | S32: =+Q32*F32 -> 18657984
B33: 3.3.2 | C33: Pintura para Cielorrasos Interiores Tipo Viniltex Advanced de Pintuco Color Blanco | D33: M2 | E33: 1028.44 | F33: 12000 | G33: =F33*E33 -> 12341280 | H33: 582.688 | I33: =+H33/E33 -> 0.56657462 | J33: =+F33*H33 -> 6992256 | K33: 0 | L33: =K33/E33 -> 0 | M33: =+K33*F33 -> 0 | N33: 0 | O33: =N33/E33 -> 0 | P33: =+N33*F33 -> 0 | Q33: =H33+K33+N33 -> 582.688 | R33: =Q33/E33 -> 0.56657462 | S33: =+Q33*F33 -> 6992256
A34: 4 | C34: CARPINTERIA EN ALUMINIO y Vidrio | G34: =+SUM(G35:G37) -> 13115377 | J34: =+SUM(J35:J37) -> 1869038 | M34: =+SUM(M35:M37) -> #REF! | P34: =+SUM(P35:P37) -> #REF! | S34: =+SUM(S35:S37) -> #REF!
B35: 4.1 | C35: Resellado Perimetral de Elementos Vidriados en Fachada | D35: ML | E35: 1610.82 | F35: 5700 | G35: =F35*E35 -> 9181674 | H35: 214.4 | I35: =+H35/E35 -> 0.13309991 | J35: =+F35*H35 -> 1222080 | K35: =Sellos!#REF! -> #REF! | L35: =K35/E35 -> #REF! | M35: =+K35*F35 -> #REF! | N35: =Sellos!#REF! -> #REF! | O35: =N35/E35 -> #REF! | P35: =+N35*F35 -> #REF! | Q35: =H35+K35+N35 -> #REF! | R35: =Q35/E35 -> #REF! | S35: =+Q35*F35 -> #REF!
B36: 4.2 | C36: Desmonte y vuelta a instalar de vidrio templado de cerramiento en terraza y Jacuzzi | D36: M2 | E36: 86.09 | F36: 16700 | G36: =F36*E36 -> 1437703 | H36: 38.74 | I36: =+H36/E36 -> 0.44999419 | J36: =+F36*H36 -> 646958 | K36: 0 | L36: =K36/E36 -> 0 | M36: =+K36*F36 -> 0 | N36: 0 | O36: =N36/E36 -> 0 | P36: =+N36*F36 -> 0 | Q36: =H36+K36+N36 -> 38.74 | R36: =Q36/E36 -> 0.44999419 | S36: =+Q36*F36 -> 646958
B37: 4.3 | C37: Suministro e instalación de cortagoteras en aluminio | D37: ML | E37: 48 | F37: 52000 | G37: =F37*E37 -> 2496000 | H37: 0 | I37: =+H37/E37 -> 0 | J37: =+F37*H37 -> 0 | K37: 0 | L37: =K37/E37 -> 0 | M37: =+K37*F37 -> 0 | N37: 0 | O37: =N37/E37 -> 0 | P37: =+N37*F37 -> 0 | Q37: =H37+K37+N37 -> 0 | R37: =Q37/E37 -> 0 | S37: =+Q37*F37 -> 0
A38: 5 | C38: VARIOS | G38: =++G39+G40 -> 5450000 | J38: =++J39+J40 -> 0 | M38: =++M39+M40 -> 0 | P38: =++P39+P40 -> 0 | S38: =++S39+S40 -> 0
B39: 5.1 | C39: Media caña en concreto incluye impermeabilizado | D39: ML | E39: 30 | F39: 55000 | G39: =F39*E39 -> 1650000 | H39: 0 | I39: =+H39/E39 -> 0 | J39: =+F39*H39 -> 0 | K39: 0 | L39: =K39/E39 -> 0 | M39: =+K39*F39 -> 0 | N39: 0 | O39: =N39/E39 -> 0 | P39: =+N39*F39 -> 0 | Q39: =H39+K39+N39 -> 0 | R39: =Q39/E39 -> 0 | S39: =+Q39*F39 -> 0
B40: 5.2 | C40: Acondicionamiento de Acceso a Terraza | D40: Gl | E40: 1 | F40: 3800000 | G40: =F40*E40 -> 3800000 | H40: 0 | I40: =+H40/E40 -> 0 | J40: =+F40*H40 -> 0 | K40: 0 | L40: =K40/E40 -> 0 | M40: =+K40*F40 -> 0 | N40: 0 | O40: =N40/E40 -> 0 | P40: =+N40*F40 -> 0 | Q40: =H40+K40+N40 -> 0 | R40: =Q40/E40 -> 0 | S40: =+Q40*F40 -> 0
A41: 6 | C41: CUBIERTA | G41: =+SUM(G42:G47) -> 33191144 | J41: =+SUM(J42:J47) -> 8100000 | M41: =+SUM(M42:M47) -> 0 | P41: =+SUM(P42:P47) -> 0 | S41: =+SUM(S42:S47) -> 8100000
B42: 6.1 | C42: Recorrido General de Cubierta Principal en UPVC | D42: M2 | E42: 312 | F42: 25000 | G42: =+E42*F42 -> 7800000 | H42: 0 | I42: =+H42/E42 -> 0 | J42: =+F42*H42 -> 0 | K42: 0 | L42: =K42/E42 -> 0 | M42: =+K42*F42 -> 0 | N42: 0 | O42: =N42/E42 -> 0 | P42: =+N42*F42 -> 0 | Q42: =H42+K42+N42 -> 0 | R42: =Q42/E42 -> 0 | S42: =+Q42*F42 -> 0
B43: 6.2 | C43: Impermeabilizacion de Placa de Concreto en Terraza | D43: M2 | E43: 113.32 | F43: 21964 | G43: =+E43*F43 -> 2488960.5 | H43: 0 | I43: =+H43/E43 -> 0 | J43: =+F43*H43 -> 0 | K43: 0 | L43: =K43/E43 -> 0 | M43: =+K43*F43 -> 0 | N43: 0 | O43: =N43/E43 -> 0 | P43: =+N43*F43 -> 0 | Q43: =H43+K43+N43 -> 0 | R43: =Q43/E43 -> 0 | S43: =+Q43*F43 -> 0
B44: 6.3 | C44: Desmonte y Suministro e Instalacion de Teja Translucida | D44: M2 | E44: 115 | F44: 52750 | G44: =+E44*F44 -> 6066250 | H44: 0 | I44: =+H44/E44 -> 0 | J44: =+F44*H44 -> 0 | K44: 0 | L44: =K44/E44 -> 0 | M44: =+K44*F44 -> 0 | N44: 0 | O44: =N44/E44 -> 0 | P44: =+N44*F44 -> 0 | Q44: =H44+K44+N44 -> 0 | R44: =Q44/E44 -> 0 | S44: =+Q44*F44 -> 0
B45: 6.4 | C45: Suministro e Instalacion de Alfajia en Lamina Galvanizada | D45: ML | E45: =24+24+42 -> 90 | F45: 45000 | G45: =+E45*F45 -> 4050000 | H45: 0 | I45: =+H45/E45 -> 0 | J45: =+F45*H45 -> 0 | K45: 0 | L45: =K45/E45 -> 0 | M45: =+K45*F45 -> 0 | N45: 0 | O45: =N45/E45 -> 0 | P45: =+N45*F45 -> 0 | Q45: =H45+K45+N45 -> 0 | R45: =Q45/E45 -> 0 | S45: =+Q45*F45 -> 0
B46: 6.5 | C46: Suministro e Instalacion de Anclajes Certificados | D46: UN | E46: 25 | F46: 405000 | G46: =+E46*F46 -> 10125000 | H46: 20 | I46: =+H46/E46 -> 0.8 | J46: =+F46*H46 -> 8100000 | K46: 0 | L46: =K46/E46 -> 0 | M46: =+K46*F46 -> 0 | N46: 0 | O46: =N46/E46 -> 0 | P46: =+N46*F46 -> 0 | Q46: =H46+K46+N46 -> 20 | R46: =Q46/E46 -> 0.8 | S46: =+Q46*F46 -> 8100000
B47: 6.6 | C47: Reemplazo de Pasto Sintetico por Enchape | D47: Gl | E47: 1 | F47: 2660933 | G47: =+E47*F47 -> 2660933 | H47: 0 | I47: =+H47/E47 -> 0 | J47: =+F47*H47 -> 0 | K47: 0 | L47: =K47/E47 -> 0 | M47: =+K47*F47 -> 0 | N47: 0 | O47: =N47/E47 -> 0 | P47: =+N47*F47 -> 0 | Q47: =H47+K47+N47 -> 0 | R47: =Q47/E47 -> 0 | S47: =+Q47*F47 -> 0
A48: 7 | C48: Aseo General y Retiro de Escombros | G48: =+G49 -> 1000000 | J48: =+J49 -> 0 | M48: =+M49 -> 0 | P48: =+P49 -> 0 | S48: =+S49 -> 0
B49: 7.1 | C49: Aseo y Retiro de Escombros | D49: GLB | E49: 1 | F49: 1000000 | G49: =F49*E49 -> 1000000 | H49: 0 | I49: =+H49/E49 -> 0 | J49: =+F49*H49 -> 0 | K49: 0 | L49: =K49/E49 -> 0 | M49: =+K49*F49 -> 0 | N49: 0 | O49: =N49/E49 -> 0 | P49: =+N49*F49 -> 0 | Q49: =H49+K49+N49 -> 0 | R49: =Q49/E49 -> 0 | S49: =+Q49*F49 -> 0
A50: Aprobado: Ing. Luis Fernando Márquez Jaramillo-Interventoria | D50: TOTALES DIRECTOS | G50: =+G6+G9+G20+G34+G38+G41+G48 -> 2.4078172e+08 | H50: T. directos | J50: =+J6+J9+J20+J34+J38+J41+J48 -> 54402847 | K50: T. directos | M50: =+M6+M9+M20+M34+M38+M41+M48 -> #REF! | N50: T. directos | P50: =+P6+P9+P20+P34+P38+P41+P48 -> #REF! | Q50: T. directos | S50: =+S6+S9+S20+S34+S38+S41+S48 -> #REF!
D51: Administracion | F51: 0.1 | G51: =+$G$50*F51 -> 24078172 | H51: Admon | I51: 0.1 | J51: =+J50*I51 -> 5440284.7 | K51: Admon | L51: 0.1 | M51: =+M50*L51 -> #REF! | N51: Admon | O51: 0.1 | P51: =+P50*O51 -> #REF! | Q51: Admon | R51: 0.1 | S51: =+S50*R51 -> #REF!
D52: Imprevistos | F52: 0.07 | G52: =+$G$50*F52 -> 16854720 | H52: Imprev. | I52: 0.07 | J52: =+J50*I52 -> 3808199.3 | K52: Imprev. | L52: 0.07 | M52: =+M50*L52 -> #REF! | N52: Imprev. | O52: 0.07 | P52: =+P50*O52 -> #REF! | Q52: Imprev. | R52: 0.07 | S52: =+S50*R52 -> #REF!
D53: Utilidad | F53: 0.05 | G53: =+$G$50*F53 -> 12039086 | H53: Utilidad | I53: 0.05 | J53: =+J50*I53 -> 2720142.4 | K53: Utilidad | L53: 0.05 | M53: =+M50*L53 -> #REF! | N53: Utilidad | O53: 0.05 | P53: =+P50*O53 -> #REF! | Q53: Utilidad | R53: 0.05 | S53: =+S50*R53 -> #REF!
D54: TOTAL SIN IVA | G54: =+SUM(G50:G53) -> 2.937537e+08 | H54: TOTAL SIN IVA | J54: =+SUM(J50:J53) -> 66371474 | K54: TOTAL SIN IVA | M54: =+SUM(M50:M53) -> #REF! | N54: TOTAL SIN IVA | P54: =+SUM(P50:P53) -> #REF! | Q54: TOTAL SIN IVA | S54: =+SUM(S50:S53) -> #REF!
D55: IVA/U | F55: 0.19 | G55: =+G53*F55 -> 2287426.3 | H55: IVA/U | I55: 0.19 | J55: =+J53*I55 -> 516827.05 | K55: IVA/U | L55: 0.19 | M55: =+M53*L55 -> #REF! | N55: IVA/U | O55: 0.19 | P55: =+P53*O55 -> #REF! | Q55: IVA/U | R55: 0.19 | S55: =+S53*R55 -> #REF!
D56: TOTAL PROPUESTA | G56: =+G54+G55 -> 296041122 | H56: Total Vr. Acta | J56: =+J54+J55 -> 66888301 | K56: Total Vr. Acta | M56: =+M54+M55 -> #REF! | N56: Total Vr. Acta | P56: =+P54+P55 -> #REF! | Q56: Total Vr. Acta | S56: =+S54+S55 -> #REF!
H57: retefuente | I57: 0.02 | J57: =+J54*I57 -> 1327429.5 | K57: retefuente | L57: 0.02 | M57: =+M54*L57 -> #REF! | N57: retefuente | O57: 0.02 | P57: =+P54*O57 -> #REF! | Q57: retefuente | R57: 0.02 | S57: =+S54*R57 -> #REF!
H58: amortizac anticipo | I58: 0.2 | J58: =+J56*I58 -> 13377660 | K58: amortizac anticipo | L58: 0.2 | M58: =+M56*L58 -> #REF! | N58: amortizac anticipo | O58: 0.2 | P58: =+P56*O58 -> #REF! | Q58: amortizac anticipo | R58: 0.2 | S58: =+S56*R58 -> #REF!
H59: retegarantia | I59: 0.1 | J59: =+J56*I59 -> 6688830.1 | K59: retegarantia | L59: 0.1 | M59: =+M56*L59 -> #REF! | N59: retegarantia | O59: 0.1 | P59: =+P56*O59 -> #REF! | Q59: retegarantia | R59: 0.1 | S59: =+S56*R59 -> #REF!
H60: Total Desembolso | J60: =+J56-J57-J58-J59 -> 45494381 | K60: Total Desembolso | M60: =+M56-M57-M58-M59 -> #REF! | N60: Total Desembolso | P60: =+P56-P57-P58-P59 -> #REF! | Q60: Total Desembolso | S60: =+S56-S57-S58-S59 -> #REF!
C62: Valor Contrato | E62: =+G56 -> 296041122 | S62: ='[1]Inventario Materiales'!$W$30 -> 17708500 | T62: =S62/S60 -> #REF!
C63: Valor Anticipo | E63: =+E62*20% -> 59208224 | S63: =[1]Operarios!$BE$24 -> 66144000 | T63: =S63/S60 -> #REF!
C64: Vr Amortizacion Anticipo esta acta | D64: =+E64/E63 -> 0.2259426 | E64: =+J58 -> 13377660 | K64: KORAZA EXTERIORES | S64: =SUM(S62:S63) -> 83852500 | T64: =S64/S60 -> #REF!
C65: Saldo por Amortizar | E65: =+E63-E64 -> 45830564 | K65: real en obra | L65: =+Q22+Q23+Q24+Q25+Q26 -> #REF!
C66: Vr Esta Acta | E66: =+J56 -> 66888301 | K66: contrato | L66: =+E22+E23+E24+E25+E26 -> 3673.2 | S66: =S60-S64 -> #REF!
C67: % ejecucion | E67: =+E66/E62 -> 0.2259426 | K67: diferencia | L67: =+L65-L66 -> #REF!
K68: VR UNITARIO | L68: =+F22 -> 21000
K69: vr diferencia | L69: =+L67*L68 -> #REF!
K71: GRANIPLAST-SILCOPLAST
K72: real en obra | L72: =+Q16 -> 14.5
K73: contrato | L73: =+E16 -> 441.8865
K74: diferencia | L74: =+L72-L73 -> -427.3865
K75: VR UNITARIO | L75: =+F16 -> 36500
K76: vr diferencia | L76: =+L74*L75 -> -15599607
K78: SUPERBOARD NORMAL
K79: real en obra | L79: =+Q18 -> 0
K80: contrato | L80: =+E17 -> 100
K81: diferencia | L81: =+L79-L80 -> -100
K82: VR UNITARIO | L82: =+F17 -> 87000
K83: vr diferencia | L83: =+L81*L82 -> -8700000
K85: SUPERBOARD SIDING
K86: real en obra | L86: =+Q18 -> 0
K87: contrato | L87: =+E18 -> 60
K88: diferencia | L88: =+L86-L87 -> -60
K89: VR UNITARIO | L89: =+F18 -> 87000
K90: vr diferencia | L90: =+L88*L89 -> -5220000
K92: SELLADO VENTANERIA
K93: real en obra | L93: =+Q35 -> #REF!
K94: contrato | L94: =+E35 -> 1610.82
K95: diferencia | L95: =+L93-L94 -> #REF!
K96: VR UNITARIO | L96: =+F35 -> 5700
K97: vr diferencia | L97: =+L95*L96 -> #REF!

Sheet Estado de la Obra
A6: Estado de obra - Actividades ejecutadas | D6: Semana # | E6: 14 | F6: 45677
A7: Edificio Panoramika
B9: Descripción | C9: UM | D9: Cantidad | E9: Cantidas Ejecutada | F9: Cantidad Restante | G9: Porcentaje restante | H9: %
B11: Lavado de superficie de fachada | C11: M2 | D11: 4506.28 | E11: =Lavado!S69 -> 2241.83 | F11: =D11-E11 -> 2264.45 | G11: =1-(E11/D11) -> 0.50250983 | H11: =E11/D11 -> 0.49749017 | I11: 0.15 | J11: =H11*I11 -> 0.074623525 | L11: =I11+I17+I15+I19 -> 0.65
B13: Aplicación de sicoplast en superficie de fachada | C13: M2 | D13: =441.8865*0.35 -> 154.66027 | E13: =Sicoplast!Y36+45 -> 45 | F13: =D13-E13 -> 109.66027 | G13: =1-(E13/D13) -> 0.7090397 | H13: =E13/D13 -> 0.2909603 | I13: 0.075 | J13: =H13*I13 -> 0.021822022 | L13: =I21 -> 0.15
B15: Aplicación de sello en ventanas, volumenes y dilataciones | C15: M2 | D15: =1610.82*0.6 -> 966.492 | E15: =Sellos!#REF!+Sellos!#REF! -> #REF! | F15: =D15-E15 -> #REF! | G15: =1-(E15/D15) -> #REF! | H15: =E15/D15 -> #REF! | I15: 0.1 | J15: =H15*I15 -> #REF! | L15: =L11+L13 -> 0.8
B17: Aplicación de pintura en superficie de fachada | C17: Und | D17: 3673.2 | E17: =Pintura!#REF! -> #REF! | F17: =D17-E17 -> #REF! | G17: =1-(E17/D17) -> #REF! | H17: =E17/D17 -> #REF! | I17: 0.3 | J17: =H17*I17 -> #REF!
B19: Aplicación de pintura en alfajías | C19: ML | D19: 532.35 | E19: =Pintura!#REF! -> #REF! | F19: =D19-E19 -> #REF! | G19: =1-(E19/D19) -> #REF! | H19: =E19/D19 -> #REF! | I19: 0.1 | J19: =H19*I19 -> #REF!
B21: Aplicación de pintura en pasillos | C21: M2 | D21: 3669.04 | E21: =Pasillos!S22 -> 476.84 | F21: =D21-E21 -> 3192.2 | G21: =1-(E21/D21) -> 0.87003685 | H21: =E21/D21 -> 0.12996315 | I21: 0.15 | J21: =H21*I21 -> 0.019494473
B23: Puntos de anclaje | C23: UND | D23: 28 | E23: 20 | F23: =D23-E23 -> 8 | G23: =1-(E23/D23) -> 0.28571429 | H23: =E23/D23 -> 0.71428571 | I23: 0.025 | J23: =H23*I23 -> 0.017857143
B25: Mantenimiento de cubiertas | C25: GLB | D25: 1 | E25: 0 | F25: =D25-E25 -> 1 | G25: =1-(E25/D25) -> 1 | H25: =E25/D25 -> 0 | I25: 0.1 | J25: =H25*I25 -> 0
B27: Estado General de la Obra | C27: GLB | D27: 1 | E27: =J27 -> #REF! | F27: =D27-E27 -> #REF! | G27: =1-(E27/D27) -> #REF! | H27: =E27/D27 -> #REF! | I27: =SUM(I11:I26) -> 1 | J27: =SUM(J11:J26) -> #REF!
B29: Plantilla | C29: UND | D29: 1 | E29: 1 | F29: =D29-E29 -> 0 | G29: 1 | H29: =E29/D29 -> 1

Sheet CO
A2: EDIFICIO PANORAMIKA
E3: DIMENSIONES | H3: DESCUENTOS
A4: FACHADA | B4: SECCIÓN | C4: PISO | D4: DESCRIPCIÓN | E4: ALTO | F4: ANCHO | G4: TOTAL (M2) | H4: ALTO | I4: ANCHO | J4: CANTIDAD | K4: TOTAL (M2) | L4: CARTERAS (ML) | M4: DILATACIÓN (ML) | N4: ÁREA TOTAL (BLANCA) | O4: ÁREA TOTAL (GRIS) | P4: ÁREA TOTAL (SIGIND) | Q4: ÁREA TOTAL (NEGRO) | R4: ÁREA TOTAL
A5: SUR | B5: 1 | C5: 10 | D5: Muro Blanco doble altura | E5: 6.2 | F5: 21.71 | G5: =E5*F5 -> 134.602 | H5: 4.02 | J5: 2 | K5: =(H5)*J5 -> 8.04 | N5: =G5-(K5+K6+K7+K8+K9) -> 112.852 | R5: =SUM(N5:Q5) -> 112.852
H6: 5.88 | J6: 1 | K6: =(H6)*J6 -> 5.88
H7: 2.16 | J7: 2 | K7: =(H7)*J7 -> 4.32
H8: 2.15 | J8: 1 | K8: =(H8)*J8 -> 2.15
H9: 1.36 | J9: 1 | K9: =(H9)*J9 -> 1.36
C10: 9 | D10: Muro gris | G10: 6.88 | O10: =G10 -> 6.88 | R10: =SUM(N10:Q10) -> 6.88
C11: 8 | D11: Lámina siding | G11: 12.6 | K11: 8.1 | N11: =G11-K11 -> 4.5 | R11: =SUM(N11:Q11) -> 4.5
C12: 7 | D12: Muro gris | G12: 6.88 | O12: =G12 -> 6.88 | R12: =SUM(N12:Q12) -> 6.88
C13: 6 | D13: Muro blanco | G13: 12.6 | P13: =G13 -> 12.6 | R13: =SUM(N13:Q13) -> 12.6
C14: 5 | D14: Muro gris | G14: 6.88 | O14: =G14 -> 6.88 | R14: =SUM(N14:Q14) -> 6.88
C15: 4 | D15: Muro blanco | G15: 12.6 | N15: =G15 -> 12.6 | R15: =SUM(N15:Q15) -> 12.6
C16: 3 | D16: Muro gris | G16: 6.88 | O16: =G16 -> 6.88 | R16: =SUM(N16:Q16) -> 6.88
C17: 2 | D17: Muro blanco | G17: 12.6 | N17: =G17 -> 12.6 | R17: =SUM(N17:Q17) -> 12.6
C18: 1 | D18: Muro blanco | G18: 7.5 | N18: =G18 -> 7.5 | R18: =SUM(N18:Q18) -> 7.5
B19: 2 | C19: 9 | D19: Muro blanco | G19: 26.97 | K19: 10.5 | N19: =G19-K19 -> 16.47 | R19: =SUM(N19:Q19) -> 16.47
C20: 8 | D20: Muro balcón blanco | G20: 6.87 | N20: =G20-K20 -> 6.87 | R20: =SUM(N20:Q20) -> 6.87
C21: 7 | D21: Lámina siding | G21: 26.97 | K21: 10.5 | P21: =G21-K21 -> 16.47 | R21: =SUM(N21:Q21) -> 16.47
C22: 6 | D22: Muro balcón blanco | G22: 6.87 | N22: =G22-K22 -> 6.87 | R22: =SUM(N22:Q22) -> 6.87
C23: 5 | D23: Muro blanco | G23: 26.97 | K23: 10.5 | N23: =G23-K23 -> 16.47 | R23: =SUM(N23:Q23) -> 16.47
C24: 4 | D24: Muro balcón blanco | G24: 6.87 | N24: =G24-K24 -> 6.87 | R24: =SUM(N24:Q24) -> 6.87
C25: 3 | D25: Muro blanco | G25: 26.97 | K25: 10.5 | N25: =G25-K25 -> 16.47 | R25: =SUM(N25:Q25) -> 16.47
C26: 2 | D26: Muro balcón blanco | G26: 6.87 | N26: =G26-K26 -> 6.87 | R26: =SUM(N26:Q26) -> 6.87
C27: 1 | D27: Muro blanco | G27: 26.97 | K27: 10.5 | N27: =G27-K27 -> 16.47 | R27: =SUM(N27:Q27) -> 16.47
B28: 3 | C28: 9 | D28: Muro gris | G28: 3.85 | M28: =F28*10 -> 0 | O28: =G28-K28 -> 3.85 | R28: =SUM(N28:Q28) -> 3.85
D29: Volumen blanco | G29: 65.71 | K29: 29 | N29: =G29-K29 -> 36.71 | R29: =SUM(N29:Q29) -> 36.71
D30: Muro gris | G30: 2.4 | O30: =G30-K30 -> 2.4 | R30: =SUM(N30:Q30) -> 2.4
C31: 8 | D31: Muros grises | G31: 5 | O31: =G31 -> 5 | R31: =SUM(N31:Q31) -> 5
C32: 7 | D32: Lámina siding | G32: 3.85 | M32: =F32*10 -> 0 | P32: =G32-K32 -> 3.85 | R32: =SUM(N32:Q32) -> 3.85
D33: Volumen siding | G33: 65.71 | K33: 29 | P33: =G33-K33 -> 36.71 | R33: =SUM(N33:Q33) -> 36.71
D34: Muro internos balcón siding | E34: 2.55 | F34: 2 | G34: =E34*F34 -> 5.1 | P34: =G34-K34 -> 5.1 | R34: =SUM(N34:Q34) -> 5.1
D35: Muro gris | G35: 2.4 | O35: =G35-K35 -> 2.4 | R35: =SUM(N35:Q35) -> 2.4
D36: Muro internos balcón gris | E36: 2.55 | F36: 2 | G36: =E36*F36 -> 5.1 | O36: =G36-K36 -> 5.1 | R36: =SUM(N36:Q36) -> 5.1
C37: 6 | D37: Muros grises | G37: 5 | O37: =G37 -> 5 | R37: =SUM(N37:Q37) -> 5
C38: 5 | D38: Muro gris | G38: 3.85 | M38: =F38*10 -> 0 | O38: =G38-K38 -> 3.85 | R38: =SUM(N38:Q38) -> 3.85
D39: Volumen blanco | G39: 65.71 | K39: 29 | N39: =G39-K39 -> 36.71 | R39: =SUM(N39:Q39) -> 36.71
D40: Muro internos balcón blanco | E40: 2.55 | F40: 2 | G40: =E40*F40 -> 5.1 | P40: =G40-K40 -> 5.1 | R40: =SUM(N40:Q40) -> 5.1
D41: Muro gris | G41: 2.4 | O41: =G41-K41 -> 2.4 | R41: =SUM(N41:Q41) -> 2.4
D42: Muro internos balcón gris | E42: 2.55 | F42: 2 | G42: =E42*F42 -> 5.1 | O42: =G42-K42 -> 5.1 | R42: =SUM(N42:Q42) -> 5.1
C43: 4 | D43: Muros grises | G43: 5 | O43: =G43 -> 5 | R43: =SUM(N43:Q43) -> 5
C44: 3 | D44: Muro gris | G44: 3.85 | M44: =F44*10 -> 0 | O44: =G44-K44 -> 3.85 | R44: =SUM(N44:Q44) -> 3.85
D45: Volumen blanco | G45: 65.71 | K45: 29 | N45: =G45-K45 -> 36.71 | R45: =SUM(N45:Q45) -> 36.71
D46: Muro internos balcón blanco | E46: 2.55 | F46: 2 | G46: =E46*F46 -> 5.1 | P46: =G46-K46 -> 5.1 | R46: =SUM(N46:Q46) -> 5.1
D47: Muro gris | G47: 2.4 | O47: =G47-K47 -> 2.4 | R47: =SUM(N47:Q47) -> 2.4
D48: Muro internos balcón gris | E48: 2.55 | F48: 2 | G48: =E48*F48 -> 5.1 | O48: =G48-K48 -> 5.1 | R48: =SUM(N48:Q48) -> 5.1
C49: 2 | D49: Muros grises | G49: 5 | O49: =G49 -> 5 | R49: =SUM(N49:Q49) -> 5
C50: 1 | D50: Muro gris | G50: 3.85 | M50: =F50*10 -> 0 | O50: =G50-K50 -> 3.85 | R50: =SUM(N50:Q50) -> 3.85
D51: Volumen blanco | G51: 65.71 | K51: 29 | N51: =G51-K51 -> 36.71 | R51: =SUM(N51:Q51) -> 36.71
D52: Muro internos balcón blanco | E52: 2.55 | F52: 2 | G52: =E52*F52 -> 5.1 | P52: =G52-K52 -> 5.1 | R52: =SUM(N52:Q52) -> 5.1
D53: Muro internos balcón gris | E53: 2.55 | F53: 2 | G53: =E53*F53 -> 5.1 | O53: =G53-K53 -> 5.1 | R53: =SUM(N53:Q53) -> 5.1
C54: Sotanos | D54: Muro negro | G54: 34 | Q54: =G54 -> 34 | R54: =SUM(N54:Q54) -> 34
B55: 4 | C55: 9 | D55: Muro blanco | G55: 26.73 | K55: 4.2 | N55: =G55-K55 -> 22.53 | R55: =SUM(N55:Q55) -> 22.53
D56: Carteras vano ventana blanco | G56: =(2.35*2)+(1.85*2) -> 8.4 | N56: =G56-K56 -> 8.4 | R56: =SUM(N56:Q56) -> 8.4
C57: 8 | D57: Muro gris | G57: 10.62 | K57: 5 | O57: =G57-K57 -> 5.62 | R57: =SUM(N57:Q57) -> 5.62
C58: 7 | D58: Lámina siding | G58: 26.73 | K58: 4.2 | P58: =G58-K58 -> 22.53 | R58: =SUM(N58:Q58) -> 22.53
D59: Carteras vano ventana siding | G59: =(2.35*2)+(1.85*2) -> 8.4 | P59: =G59-K59 -> 8.4 | R59: =SUM(N59:Q59) -> 8.4
C60: 6 | D60: Muro gris | G60: 10.62 | K60: 5 | O60: =G60-K60 -> 5.62 | R60: =SUM(N60:Q60) -> 5.62
C61: 5 | D61: Muro blanco | G61: 26.73 | K61: 4.2 | N61: =G61-K61 -> 22.53 | R61: =SUM(N61:Q61) -> 22.53
D62: Carteras vano ventana blanco | G62: =(2.35*2)+(1.85*2) -> 8.4 | N62: =G62-K62 -> 8.4 | R62: =SUM(N62:Q62) -> 8.4
C63: 4 | D63: Muro gris | G63: 10.62 | K63: 5 | O63: =G63-K63 -> 5.62 | R63: =SUM(N63:Q63) -> 5.62
C64: 3 | D64: Muro blanco | G64: 26.73 | K64: 4.2 | N64: =G64-K64 -> 22.53 | R64: =SUM(N64:Q64) -> 22.53
D65: Carteras vano ventana blanco | G65: =(2.35*2)+(1.85*2) -> 8.4 | N65: =G65-K65 -> 8.4 | R65: =SUM(N65:Q65) -> 8.4
C66: 2 | D66: Muro gris | G66: 10.62 | K66: 5 | O66: =G66-K66 -> 5.62 | R66: =SUM(N66:Q66) -> 5.62
C67: 1 | D67: Muro blanco | G67: 26.73 | K67: 4.2 | N67: =G67-K67 -> 22.53 | R67: =SUM(N67:Q67) -> 22.53
C68: Parq | D68: Muro negro | G68: 42.78 | Q68: =G68 -> 42.78 | R68: =SUM(N68:Q68) -> 42.78
B69: 5 | C69: 10 | D69: Muro blanco | G69: =1.7*7.25 -> 12.325 | O69: =G69-K71 -> 12.325 | R69: =SUM(N69:Q69) -> 12.325
C70: 8 | D70: Muro blanco | G70: 6.34 | N70: =G70-K70 -> 6.34 | R70: =SUM(N70:Q70) -> 6.34
C71: 7 | D71: Muro gris | G71: 3.85 | O71: =G71-K73 -> 3.85 | R71: =SUM(N71:Q71) -> 3.85
C72: 6 | D72: Muro blanco | G72: 6.34 | N72: =G72-K72 -> 6.34 | R72: =SUM(N72:Q72) -> 6.34
C73: 5 | D73: Muro gris | G73: 3.85 | O73: =G73-K75 -> 3.85 | R73: =SUM(N73:Q73) -> 3.85
C74: 4 | D74: Lámina siding | G74: 6.34 | P74: =G74-K74 -> 6.34 | R74: =SUM(N74:Q74) -> 6.34
C75: 3 | D75: Muro gris | G75: 3.85 | O75: =G75-K80 -> 3.85 | R75: =SUM(N75:Q75) -> 3.85
C76: 2 | D76: Muro blanco | G76: 6.34 | N76: =G76-K76 -> 6.34 | R76: =SUM(N76:Q76) -> 6.34
C77: 3 | D77: Lámina siding | G77: 3.85 | P77: =G77-K82 -> 3.85 | R77: =SUM(N77:Q77) -> 3.85
B78: General | C78: Todos | D78: Alfajía en volumenes de fachada | G78: =13.5+17.5 -> 31 | N78: =G78 -> 31 | R78: =SUM(N78:Q78) -> 31
B79: General | C79: Todos | D79: Cielorasos en volumenes de fachada | G79: =13.5+17.5 -> 31 | N79: =G79 -> 31 | R79: =SUM(N79:Q79) -> 31
D81: TOTAL M2 DE FACHADA SIN DESCUENTOS | G81: =SUM(G5:G80)-(Q68+Q54) -> 1125.367 | J81: TOTAL M2 DE FACHADA CON DESCUENTOS | N81: =SUM(N5:N80) -> 586.592 | O81: =SUM(O5:O80) -> 139.275 | P81: =SUM(P5:P80) -> 131.15 | Q81: =SUM(Q5:Q80) -> 76.78 | R81: =SUM(R5:R80) -> 933.797
L82: =G81-R81 -> 191.57 | N82: =SUM(N81:Q81) -> 933.797
R83: =R81*2 -> 1867.594
R84: 3511
N85: PINTURA BLANCA | O85: PINTURA GRIS | P85: PINTURA AMARILLA | Q85: PINTURA NEGRA | R85: =R84-R83 -> 1643.406
N86: =N81/70 -> 8.3798857 | O86: =O81/70 -> 1.9896429 | P86: =P81/70 -> 1.8735714 | Q86: =Q81/70 -> 1.0968571 | R86: =R85/2 -> 821.703
C88: 1 | D88: Fachada General | E88: 37.85 | F88: 2.25 | G88: =E88*F88 -> 85.1625
C89: 2 | D89: Fachada General | E89: 37.2 | F89: 6.75 | G89: =E89*F89 -> 251.1
C90: 3 | D90: Fachada General | E90: 38.77 | F90: 18.2 | G90: =E90*F90 -> 705.614
C91: 4 | D91: Fachada General | E91: 37.2 | F91: 6.75 | G91: =E91*F91 -> 251.1
C92: 5 | D92: Fachada General | E92: 37.85 | F92: 2.25 | G92: =E92*F92 -> 85.1625
C93: 6 | D93: Fachada doble altura | E93: 6.2 | F93: 21.7 | G93: =E93*F93 -> 134.54
G94: =SUM(G88:G93) -> 1512.679
D97: FACHADA SUR
A98: SUR | B98: 6 | C98: 10 | D98: Muro Blanco doble altura | E98: 7.5 | F98: 24 | G98: =E98*F98 -> 180 | H98: 6 | I98: 22.5 | J98: 1 | K98: =(H98)*I98*J98 -> 135 | L98: =F98 -> 24 | N98: =G98-K98 -> 45 | R98: =SUM(N98:Q98) -> 45
D99: Muro gris 1 | G99: 1 | O99: =G99 -> 1 | R99: =SUM(N99:Q99) -> 1
D100: Muro gris 2 | G100: 10.57 | O100: =G100 -> 10.57 | R100: =SUM(N100:Q100) -> 10.57
D101: Muro gris 3 | G101: 5.75 | O101: =G101-K101 -> 5.75 | R101: =SUM(N101:Q101) -> 5.75
D102: Muro gris 4 | G102: 1 | O102: =G102 -> 1 | R102: =SUM(N102:Q102) -> 1
C103: 9 | D103: Muro gris 1 | E103: 2.55 | F103: 2.5 | G103: =E103*F103 -> 6.375 | O103: =G103 -> 6.375 | R103: =SUM(N103:Q103) -> 6.375
D104: Muro gris 2 | G104: 4.25 | O104: =G104 -> 4.25 | R104: =SUM(N104:Q104) -> 4.25
D105: Muro gris 3 | G105: 2.3 | O105: 2.32 | R105: =SUM(N105:Q105) -> 2.32
...

Sheet CO SIF
A1: 45969
A2: EDIFICIO PANORAMIKA | F2: 1.03 | G2: =F152 -> 3.82663
A4: FACHADA | B4: SECCIÓN | C4: PISO | D4: DESCRIPCIÓN | E4: ÁREA TOTAL
D5: FACHADA OESTE
A6: SUR | B6: 1 | C6: 10 | D6: Muro Blanco doble altura | E6: =CO!R5 -> 112.852 | F6: =E6*$F$2 -> 116.23756
C7: 8 | D7: Lámina siding | E7: 12.6 | F7: =E7*$F$2 -> 12.978
C8: 6 | D8: Muro blanco | E8: =CO!R13 -> 12.6 | F8: =E8*$F$2 -> 12.978
C9: 4 | D9: Muro blanco | E9: =CO!R15 -> 12.6 | F9: =E9*$F$2 -> 12.978
C10: 2 | D10: Muro blanco | E10: =CO!R17 -> 12.6 | F10: =E10*$F$2 -> 12.978
C11: 1 | D11: Muro blanco | E11: =CO!R18 -> 7.5 | F11: =E11*$F$2 -> 7.725
B12: 2 | C12: 9 | D12: Muro blanco | E12: =CO!R19 -> 16.47 | F12: =E12*$F$2 -> 16.9641
C13: 8 | D13: Muro balcón blanco | E13: =CO!R20 -> 6.87 | F13: =E13*$F$2 -> 7.0761
C14: 7 | D14: Lámina siding | E14: =CO!R21 -> 16.47 | F14: =E14*$F$2 -> 16.9641
C15: 6 | D15: Muro balcón blanco | E15: =CO!R22 -> 6.87 | F15: =E15*$F$2 -> 7.0761
C16: 5 | D16: Muro blanco | E16: =CO!R23 -> 16.47 | F16: =E16*$F$2 -> 16.9641
C17: 4 | D17: Muro balcón blanco | E17: =CO!R24 -> 6.87 | F17: =E17*$F$2 -> 7.0761
C18: 3 | D18: Muro blanco | E18: =CO!R25 -> 16.47 | F18: =E18*$F$2 -> 16.9641
C19: 2 | D19: Muro balcón blanco | E19: =CO!R26 -> 6.87 | F19: =E19*$F$2 -> 7.0761
C20: 1 | D20: Muro blanco | E20: =CO!R27 -> 16.47 | F20: =E20*$F$2 -> 16.9641
B21: 3 | C21: 9 | D21: Muro gris | E21: 6.25 | F21: =E21*$F$2 -> 6.4375
D22: Volumen blanco | E22: =CO!R29 -> 36.71 | F22: =E22*$F$2 -> 37.8113
C23: 8 | D23: Muros grises | E23: =CO!R31 -> 5 | F23: =E23*$F$2 -> 5.15
C24: 7 | D24: Lámina siding | E24: 45.66 | F24: =E24*$F$2 -> 47.0298
D25: Muros gris | E25: 7.5 | F25: =E25*$F$2 -> 7.725
C26: 6 | D26: Muros grises | E26: =CO!R34 -> 5.1 | F26: =E26*$F$2 -> 5.253
C27: 5 | D27: Muro blanco | E27: 45.66 | F27: =E27*$F$2 -> 47.0298
D28: Muros gris | E28: 7.5 | F28: =E28*$F$2 -> 7.725
C29: 4 | D29: Muros grises | E29: =CO!R37 -> 5 | F29: =E29*$F$2 -> 5.15
C30: 3 | D30: Muro blanco | E30: 45.66 | F30: =E30*$F$2 -> 47.0298
D31: Muros gris | E31: 7.5 | F31: =E31*$F$2 -> 7.725
C32: 2 | D32: Muros grises | E32: =CO!R49 -> 5 | F32: =E32*$F$2 -> 5.15
C33: 1 | D33: Muro blanco | E33: 45.66 | F33: =E33*$F$2 -> 47.0298
D34: Muros gris | E34: 7.5 | F34: =E34*$F$2 -> 7.725
C35: Sotanos | D35: Muro negro | E35: =CO!R54 -> 34 | F35: =E35*$F$2 -> 35.02
B36: 4 | C36: 9 | D36: Muro blanco | E36: 30.93 | F36: =E36*$F$2 -> 31.8579
C37: 8 | D37: Muro gris | E37: =CO!R57 -> 5.62 | F37: =E37*$F$2 -> 5.7886
C38: 7 | D38: Lámina siding | E38: 30.93 | F38: =E38*$F$2 -> 31.8579
C39: 6 | D39: Muro gris | E39: =CO!R60 -> 5.62 | F39: =E39*$F$2 -> 5.7886
C40: 5 | D40: Muro blanco | E40: 30.93 | F40: =E40*$F$2 -> 31.8579
C41: 4 | D41: Muro gris | E41: =CO!R63 -> 5.62 | F41: =E41*$F$2 -> 5.7886
C42: 3 | D42: Muro blanco | E42: 30.93 | F42: =E42*$F$2 -> 31.8579
C43: 2 | D43: Muro gris | E43: =CO!R66 -> 5.62 | F43: =E43*$F$2 -> 5.7886
C44: 1 | D44: Muro blanco | E44: 30.93 | F44: =E44*$F$2 -> 31.8579
C45: Parq | D45: Muro negro | E45: =CO!R68 -> 42.78 | F45: =E45*$F$2 -> 44.0634
C46: Parq | D46: Cieloraso en fachada | E46: =17.6*4.5 -> 79.2 | F46: =E46*$F$2 -> 81.576
B47: 5 | C47: 10 | D47: Muro blanco | E47: =CO!R69 -> 12.325 | F47: =E47*$F$2 -> 12.69475
C48: 8 | D48: Muro blanco | E48: =CO!R70 -> 6.34 | F48: =E48*$F$2 -> 6.5302
C49: 6 | D49: Muro blanco | E49: =CO!R72 -> 6.34 | F49: =E49*$F$2 -> 6.5302
C50: 4 | D50: Lámina siding | E50: =CO!R74 -> 6.34 | F50: =E50*$F$2 -> 6.5302
C51: 2 | D51: Muro blanco | E51: =CO!R76 -> 6.34 | F51: =E51*$F$2 -> 6.5302
B52: General | C52: Todos | D52: Alfajía en volumenes de fachada | E52: =CO!R78 -> 31 | F52: =E52*$F$2 -> 31.93
B53: General | C53: Todos | D53: Cielorasos en volumenes de fachada | E53: =CO!R79 -> 31 | F53: =E53*$F$2 -> 31.93
B54: General | C54: Todos | D54: Cielorasos en balcones | E54: =((8.1*2)*4)+((9.2*1.5)*5) -> 133.8 | F54: =E54*$F$2 -> 137.814
D55: TOTAL M2 DE FACHADA SIN DESCUENTOS | E55: =SUM(E6:E54) -> 1122.877 | F55: =SUM(F6:F54) -> 1156.5633
D58: FACHADA NORTE
A59: SUR | B59: 6 | C59: 10 | D59: Muro Blanco doble altura | E59: =CO!R98 -> 45 | F59: =E59*$F$2 -> 46.35
D60: Muros gris | E60: 18.32 | F60: =E60*$F$2 -> 18.8696
C61: 9 | D61: Muros gris | E61: 13.95 | F61: =E61*$F$2 -> 14.3685
C62: 8 | D62: Muros blancos | E62: 41.63 | F62: =E62*$F$2 -> 42.8789
D63: Muros gris | E63: 19.32 | F63: =E63*$F$2 -> 19.8996
C64: 7 | D64: Muros gris | E64: 13.95 | F64: =E64*$F$2 -> 14.3685
C65: 6 | D65: Muros blancos | E65: 41.63 | F65: =E65*$F$2 -> 42.8789
D66: Muros gris | E66: 19.32 | F66: =E66*$F$2 -> 19.8996
C67: 5 | D67: Muros gris | E67: 13.95 | F67: =E67*$F$2 -> 14.3685
C68: 4 | D68: Lámina Siding | E68: 41.63 | F68: =E68*$F$2 -> 42.8789
D69: Muros gris | E69: 19.32 | F69: =E69*$F$2 -> 19.8996
C70: 3 | D70: Muros gris | E70: 13.95 | F70: =E70*$F$2 -> 14.3685
C71: 2 | D71: Muros blancos | E71: 41.63 | F71: =E71*$F$2 -> 42.8789
D72: Muros gris | E72: 19.32 | F72: =E72*$F$2 -> 19.8996
C73: 1 | D73: Lámina Siding (Borde placa y carteras) | E73: =CO!R147 -> 39.42 | F73: =E73*$F$2 -> 40.6026
C74: Sótanos | D74: Muro negro 1 | E74: 140.11 | F74: =E74*$F$2 -> 144.3133
B75: General | C75: Todos | D75: Alfajía en volumenes de fachada | E75: =24*9 -> 216 | F75: =E75*$F$2 -> 222.48
B76: General | C76: Todos | D76: Cielorasos en volumenes de fachada | E76: =CO!R152 -> 27 | F76: =E76*$F$2 -> 27.81
B77: General | C77: Todos | D77: Cielorasos en balcones | E77: =4.5*10 -> 45 | F77: =E77*$F$2 -> 46.35
D78: TOTAL M2 DE FACHADA SIN DESCUENTOS | E78: =SUM(E59:E77) -> 830.45 | F78: =SUM(F59:F77) -> 855.3635 | H78: =F78*0.5 -> 427.68175
D81: FACHADA ESTE
A82: SUR | B82: 7 | C82: 10 | D82: Muro Blanco doble altura | E82: =CO!R163 -> 112.852 | F82: =E82*$F$2 -> 116.23756
C83: 8 | D83: Muro blanco | E83: =CO!R169 -> 6.5 | F83: =E83*$F$2 -> 6.695
C84: 6 | D84: Muro blanco | E84: =CO!R171 -> 6.5 | F84: =E84*$F$2 -> 6.695
C85: 4 | D85: Lámina siding | E85: =CO!R173 -> 6.5 | F85: =E85*$F$2 -> 6.695
C86: 2 | D86: Muro blanco | E86: =CO!R175 -> 6.5 | F86: =E86*$F$2 -> 6.695
C87: 1 | D87: Muro blanco | E87: =CO!R176 -> 4.5 | F87: =E87*$F$2 -> 4.635
B88: 8 | C88: 9 | D88: Lámina siding | E88: =CO!R177 -> 16.47 | F88: =E88*$F$2 -> 16.9641
C89: 8 | D89: Muro balcón blanco | E89: =CO!R178 -> 6.87 | F89: =E89*$F$2 -> 7.0761
C90: 7 | D90: Muro blanco | E90: =CO!R179 -> 16.47 | F90: =E90*$F$2 -> 16.9641
C91: 6 | D91: Muro balcón blanco | E91: =CO!R180 -> 6.87 | F91: =E91*$F$2 -> 7.0761
C92: 5 | D92: Muro blanco | E92: =CO!R181 -> 16.47 | F92: =E92*$F$2 -> 16.9641
C93: 4 | D93: Muro balcón blanco | E93: =CO!R182 -> 6.87 | F93: =E93*$F$2 -> 7.0761
C94: 3 | D94: Muro blanco | E94: =CO!R183 -> 16.47 | F94: =E94*$F$2 -> 16.9641
C95: 2 | D95: Muro balcón blanco | E95: =CO!R184 -> 6.87 | F95: =E95*$F$2 -> 7.0761
C96: 1 | D96: Lámina siding | E96: =CO!R185 -> 12 | F96: =E96*$F$2 -> 12.36
B97: 9 | C97: 9 | D97: Lámina siding | E97: 42.6 | F97: =E97*$F$2 -> 43.878
D98: Muros gris | E98: 7 | F98: =E98*$F$2 -> 7.21
C99: 8 | D99: Muros gris | E99: 28.3 | F99: =E99*$F$2 -> 29.149
C100: 7 | D100: Muros blancos | E100: 42.6 | F100: =E100*$F$2 -> 43.878
D101: Muros gris | E101: 7 | F101: =E101*$F$2 -> 7.21
C102: 6 | D102: Muros gris | E102: 28.3 | F102: =E102*$F$2 -> 29.149
C103: 5 | D103: Muros blancos | E103: 42.6 | F103: =E103*$F$2 -> 43.878
D104: Muros gris | E104: 7 | F104: =E104*$F$2 -> 7.21
C105: 4 | D105: Muros gris | E105: 28.3 | F105: =E105*$F$2 -> 29.149
...

Sheet CO SIF 2
A1: 45969
A2: EDIFICIO PANORAMIKA | F2: 1.03 | H2: EDIFICIO PANORAMIKA | L2: 1.03
F3: =F152 -> 3.82663
A4: FACHADA | B4: SECCIÓN | C4: PISO | D4: DESCRIPCIÓN | E4: ÁREA TOTAL | H4: FACHADA | I4: SECCIÓN | J4: DESCRIPCIÓN | K4: ÁREA TOTAL
D5: FACHADA OESTE | J5: FACHADA OESTE
A6: SUR | B6: 1 | C6: 10 | D6: Muro Blanco doble altura | E6: =CO!R5 -> 112.852 | F6: =E6*$F$2 -> 116.23756 | G6: =SUM(F6:F11) -> 175.87456 | H6: SUR | I6: 1 | J6: Muro Blanco doble altura | K6: =E6 -> 112.852 | L6: =K6*$F$2 -> 116.23756 | M6: =SUM(L6:L8) -> 175.87456
C7: 8 | D7: Lámina siding | E7: 12.6 | F7: =E7*$F$2 -> 12.978 | J7: Lámina siding | K7: 12.6 | L7: =K7*$F$2 -> 12.978
C8: 6 | D8: Muro blanco | E8: =CO!R13 -> 12.6 | F8: =E8*$F$2 -> 12.978 | J8: Muro blanco | K8: =SUM(E8:E11) -> 45.3 | L8: =K8*$F$2 -> 46.659
C9: 4 | D9: Muro blanco | E9: =CO!R15 -> 12.6 | F9: =E9*$F$2 -> 12.978
C10: 2 | D10: Muro blanco | E10: =CO!R17 -> 12.6 | F10: =E10*$F$2 -> 12.978
C11: 1 | D11: Muro blanco | E11: =CO!R18 -> 7.5 | F11: =E11*$F$2 -> 7.725
B12: 2 | C12: 9 | D12: Muro blanco | E12: =CO!R19 -> 16.47 | F12: =E12*$F$2 -> 16.9641 | G12: =SUM(F12:F20) -> 113.1249 | I12: 2 | J12: Muro blanco | K12: =E12+E16+E18+E20 -> 65.88 | L12: =K12*$F$2 -> 67.8564 | M12: =SUM(L12:L14) -> 113.1249
C13: 8 | D13: Muro balcón blanco | E13: =CO!R20 -> 6.87 | F13: =E13*$F$2 -> 7.0761 | J13: Muro balcón blanco | K13: =E13+E15+E17+E19 -> 27.48 | L13: =K13*$F$2 -> 28.3044
C14: 7 | D14: Lámina siding | E14: =CO!R21 -> 16.47 | F14: =E14*$F$2 -> 16.9641 | J14: Lámina siding | K14: =E14 -> 16.47 | L14: =K14*$F$2 -> 16.9641
C15: 6 | D15: Muro balcón blanco | E15: =CO!R22 -> 6.87 | F15: =E15*$F$2 -> 7.0761
C16: 5 | D16: Muro blanco | E16: =CO!R23 -> 16.47 | F16: =E16*$F$2 -> 16.9641
C17: 4 | D17: Muro balcón blanco | E17: =CO!R24 -> 6.87 | F17: =E17*$F$2 -> 7.0761
C18: 3 | D18: Muro blanco | E18: =CO!R25 -> 16.47 | F18: =E18*$F$2 -> 16.9641
C19: 2 | D19: Muro balcón blanco | E19: =CO!R26 -> 6.87 | F19: =E19*$F$2 -> 7.0761
C20: 1 | D20: Muro blanco | E20: =CO!R27 -> 16.47 | F20: =E20*$F$2 -> 16.9641
B21: 3 | C21: 9 | D21: Muro gris | E21: 6.25 | F21: =E21*$F$2 -> 6.4375 | G21: =SUM(F21:F35) -> 318.991 | I21: 3 | J21: Muro gris | K21: =E21+E23+E25+E28+E29+E31+E32+E34+E26 -> 56.35 | L21: =K21*$F$2 -> 58.0405 | M21: =SUM(L21:L24) -> 318.991
D22: Volumen blanco | E22: =CO!R29 -> 36.71 | F22: =E22*$F$2 -> 37.8113 | J22: Volumen blanco | K22: =E22++E27+E30+E33 -> 173.69 | L22: =K22*$F$2 -> 178.9007
C23: 8 | D23: Muros grises | E23: =CO!R31 -> 5 | F23: =E23*$F$2 -> 5.15 | J23: Lámina siding | K23: =E24 -> 45.66 | L23: =K23*$F$2 -> 47.0298
C24: 7 | D24: Lámina siding | E24: 45.66 | F24: =E24*$F$2 -> 47.0298 | J24: Muro negro | K24: =E35 -> 34 | L24: =K24*$F$2 -> 35.02
D25: Muros gris | E25: 7.5 | F25: =E25*$F$2 -> 7.725
C26: 6 | D26: Muros grises | E26: =CO!R34 -> 5.1 | F26: =E26*$F$2 -> 5.253
C27: 5 | D27: Muro blanco | E27: 45.66 | F27: =E27*$F$2 -> 47.0298
D28: Muros gris | E28: 7.5 | F28: =E28*$F$2 -> 7.725
C29: 4 | D29: Muros grises | E29: =CO!R37 -> 5 | F29: =E29*$F$2 -> 5.15
C30: 3 | D30: Muro blanco | E30: 45.66 | F30: =E30*$F$2 -> 47.0298
D31: Muros gris | E31: 7.5 | F31: =E31*$F$2 -> 7.725
C32: 2 | D32: Muros grises | E32: =CO!R49 -> 5 | F32: =E32*$F$2 -> 5.15
C33: 1 | D33: Muro blanco | E33: 45.66 | F33: =E33*$F$2 -> 47.0298
D34: Muros gris | E34: 7.5 | F34: =E34*$F$2 -> 7.725
C35: Sotanos | D35: Muro negro | E35: =CO!R54 -> 34 | F35: =E35*$F$2 -> 35.02
B36: 4 | C36: 9 | D36: Muro blanco | E36: 30.93 | F36: =E36*$F$2 -> 31.8579 | G36: =SUM(F36:F46) -> 308.0833 | I36: 4 | J36: Muro blanco | K36: =E36+E40+E42+E44 -> 123.72 | L36: =K36*$F$2 -> 127.4316 | M36: =SUM(L36:L40) -> 308.0833
C37: 8 | D37: Muro gris | E37: =CO!R57 -> 5.62 | F37: =E37*$F$2 -> 5.7886 | J37: Muro gris | K37: =E37+E39+E41+E43 -> 22.48 | L37: =K37*$F$2 -> 23.1544
C38: 7 | D38: Lámina siding | E38: 30.93 | F38: =E38*$F$2 -> 31.8579 | J38: Lámina siding | K38: =E38 -> 30.93 | L38: =K38*$F$2 -> 31.8579
C39: 6 | D39: Muro gris | E39: =CO!R60 -> 5.62 | F39: =E39*$F$2 -> 5.7886 | J39: Muro negro | K39: =E45 -> 42.78 | L39: =K39*$F$2 -> 44.0634
C40: 5 | D40: Muro blanco | E40: 30.93 | F40: =E40*$F$2 -> 31.8579 | J40: Cieloraso en fachada | K40: =17.6*4.5 -> 79.2 | L40: =K40*$F$2 -> 81.576
C41: 4 | D41: Muro gris | E41: =CO!R63 -> 5.62 | F41: =E41*$F$2 -> 5.7886
C42: 3 | D42: Muro blanco | E42: 30.93 | F42: =E42*$F$2 -> 31.8579
C43: 2 | D43: Muro gris | E43: =CO!R66 -> 5.62 | F43: =E43*$F$2 -> 5.7886
C44: 1 | D44: Muro blanco | E44: 30.93 | F44: =E44*$F$2 -> 31.8579
C45: Parq | D45: Muro negro | E45: =CO!R68 -> 42.78 | F45: =E45*$F$2 -> 44.0634
C46: Parq | D46: Cieloraso en fachada | E46: =17.6*4.5 -> 79.2 | F46: =E46*$F$2 -> 81.576
B47: 5 | C47: 10 | D47: Muro blanco | E47: =CO!R69 -> 12.325 | F47: =E47*$F$2 -> 12.69475 | G47: =SUM(F47:F54) -> 240.48955 | I47: 5 | J47: Muro blanco | K47: =E47+E48+E49+E51 -> 31.345 | L47: =K47*$F$2 -> 32.28535 | M47: =SUM(L47:L54) -> 240.48955
C48: 8 | D48: Muro blanco | E48: =CO!R70 -> 6.34 | F48: =E48*$F$2 -> 6.5302 | J48: Lámina siding | K48: =E50 -> 6.34 | L48: =K48*$F$2 -> 6.5302
C49: 6 | D49: Muro blanco | E49: =CO!R72 -> 6.34 | F49: =E49*$F$2 -> 6.5302
C50: 4 | D50: Lámina siding | E50: =CO!R74 -> 6.34 | F50: =E50*$F$2 -> 6.5302
C51: 2 | D51: Muro blanco | E51: =CO!R76 -> 6.34 | F51: =E51*$F$2 -> 6.5302
B52: General | C52: Todos | D52: Alfajía en volumenes de fachada | E52: =CO!R78 -> 31 | F52: =E52*$F$2 -> 31.93 | I52: General | J52: Alfajía en volumenes de fachada | K52: =E52 -> 31 | L52: =K52*$F$2 -> 31.93
B53: General | C53: Todos | D53: Cielorasos en volumenes de fachada | E53: =CO!R79 -> 31 | F53: =E53*$F$2 -> 31.93 | I53: General | J53: Cielorasos en volumenes de fachada | K53: =E53 -> 31 | L53: =K53*$F$2 -> 31.93
B54: General | C54: Todos | D54: Cielorasos en balcones | E54: =((8.1*2)*4)+((9.2*1.5)*5) -> 133.8 | F54: =E54*$F$2 -> 137.814 | I54: General | J54: Cielorasos en balcones | K54: =E54 -> 133.8 | L54: =K54*$F$2 -> 137.814
D55: TOTAL M2 DE FACHADA SIN DESCUENTOS | E55: =SUM(E6:E54) -> 1122.877 | F55: =SUM(F6:F54) -> 1156.5633 | J55: TOTAL M2 DE FACHADA SIN DESCUENTOS | K55: =SUM(K6:K54) -> 1122.877 | L55: =SUM(L6:L54) -> 1156.5633
D58: FACHADA NORTE | J58: FACHADA NORTE
A59: SUR | B59: 6 | C59: 10 | D59: Muro Blanco doble altura | E59: =CO!R98 -> 45 | F59: =E59*$F$2 -> 46.35 | G59: =SUM(F59:F77) -> 855.3635 | H59: SUR | I59: 6 | J59: Muro Blanco doble altura | K59: =E59 -> 45 | L59: =K59*$F$2 -> 46.35 | M59: =SUM(L59:L77) -> 855.3635
D60: Muros gris | E60: 18.32 | F60: =E60*$F$2 -> 18.8696 | J60: Muros gris | K60: =E60+E61+E63+E64+E66+E67+E69+E70+E72 -> 151.4 | L60: =K60*$F$2 -> 155.942
C61: 9 | D61: Muros gris | E61: 13.95 | F61: =E61*$F$2 -> 14.3685 | J61: Muros blancos | K61: =E62+E65+E71 -> 124.89 | L61: =K61*$F$2 -> 128.6367
C62: 8 | D62: Muros blancos | E62: 41.63 | F62: =E62*$F$2 -> 42.8789 | J62: Lámina Siding | K62: =E68+E73 -> 81.05 | L62: =K62*$F$2 -> 83.4815
D63: Muros gris | E63: 19.32 | F63: =E63*$F$2 -> 19.8996
C64: 7 | D64: Muros gris | E64: 13.95 | F64: =E64*$F$2 -> 14.3685
C65: 6 | D65: Muros blancos | E65: 41.63 | F65: =E65*$F$2 -> 42.8789
D66: Muros gris | E66: 19.32 | F66: =E66*$F$2 -> 19.8996
C67: 5 | D67: Muros gris | E67: 13.95 | F67: =E67*$F$2 -> 14.3685
C68: 4 | D68: Lámina Siding | E68: 41.63 | F68: =E68*$F$2 -> 42.8789
D69: Muros gris | E69: 19.32 | F69: =E69*$F$2 -> 19.8996
C70: 3 | D70: Muros gris | E70: 13.95 | F70: =E70*$F$2 -> 14.3685
C71: 2 | D71: Muros blancos | E71: 41.63 | F71: =E71*$F$2 -> 42.8789
D72: Muros gris | E72: 19.32 | F72: =E72*$F$2 -> 19.8996
C73: 1 | D73: Lámina Siding (Borde placa y carteras) | E73: =CO!R147 -> 39.42 | F73: =E73*$F$2 -> 40.6026
C74: Sótanos | D74: Muro negro 1 | E74: 140.11 | F74: =E74*$F$2 -> 144.3133 | J74: Muro negro 1 | K74: =E74 -> 140.11 | L74: =K74*$F$2 -> 144.3133
B75: General | C75: Todos | D75: Alfajía en volumenes de fachada | E75: =24*9 -> 216 | F75: =E75*$F$2 -> 222.48 | I75: General | J75: Alfajía en volumenes de fachada | K75: =E75 -> 216 | L75: =K75*$F$2 -> 222.48
B76: General | C76: Todos | D76: Cielorasos en volumenes de fachada | E76: =CO!R152 -> 27 | F76: =E76*$F$2 -> 27.81 | I76: General | J76: Cielorasos en volumenes de fachada | K76: =E76 -> 27 | L76: =K76*$F$2 -> 27.81
B77: General | C77: Todos | D77: Cielorasos en balcones | E77: =4.5*10 -> 45 | F77: =E77*$F$2 -> 46.35 | I77: General | J77: Cielorasos en balcones | K77: =E77 -> 45 | L77: =K77*$F$2 -> 46.35
D78: TOTAL M2 DE FACHADA SIN DESCUENTOS | E78: =SUM(E59:E77) -> 830.45 | F78: =SUM(F59:F77) -> 855.3635 | J78: TOTAL M2 DE FACHADA SIN DESCUENTOS | K78: =SUM(K59:K77) -> 830.45 | L78: =SUM(L59:L77) -> 855.3635
D81: FACHADA ESTE | J81: FACHADA ESTE
A82: SUR | B82: 7 | C82: 10 | D82: Muro Blanco doble altura | E82: =CO!R163 -> 112.852 | F82: =E82*$F$2 -> 116.23756 | G82: =SUM(F82:F87) -> 147.65256 | H82: SUR | I82: 7 | J82: Muro Blanco doble altura | K82: =E82 -> 112.852 | L82: =K82*$F$2 -> 116.23756 | M82: =SUM(L82:L84) -> 147.65256
C83: 8 | D83: Muro blanco | E83: =CO!R169 -> 6.5 | F83: =E83*$F$2 -> 6.695 | J83: Muro blanco | K83: =E83+E84+E86+E87 -> 24 | L83: =K83*$F$2 -> 24.72
C84: 6 | D84: Muro blanco | E84: =CO!R171 -> 6.5 | F84: =E84*$F$2 -> 6.695 | J84: Lámina siding | K84: =E85 -> 6.5 | L84: =K84*$F$2 -> 6.695
C85: 4 | D85: Lámina siding | E85: =CO!R173 -> 6.5 | F85: =E85*$F$2 -> 6.695
C86: 2 | D86: Muro blanco | E86: =CO!R175 -> 6.5 | F86: =E86*$F$2 -> 6.695
C87: 1 | D87: Muro blanco | E87: =CO!R176 -> 4.5 | F87: =E87*$F$2 -> 4.635
B88: 8 | C88: 9 | D88: Lámina siding | E88: =CO!R177 -> 16.47 | F88: =E88*$F$2 -> 16.9641 | G88: =SUM(F88:F96) -> 108.5208 | I88: 8 | J88: Lámina siding | K88: =E88+E96 -> 28.47 | L88: =K88*$F$2 -> 29.3241 | M88: =SUM(L88:L90) -> 108.5208
C89: 8 | D89: Muro balcón blanco | E89: =CO!R178 -> 6.87 | F89: =E89*$F$2 -> 7.0761 | J89: Muro balcón blanco | K89: =E89+E91+E93+E95 -> 27.48 | L89: =K89*$F$2 -> 28.3044
C90: 7 | D90: Muro blanco | E90: =CO!R179 -> 16.47 | F90: =E90*$F$2 -> 16.9641 | J90: Muro blanco | K90: =E90+E92+E94 -> 49.41 | L90: =K90*$F$2 -> 50.8923
C91: 6 | D91: Muro balcón blanco | E91: =CO!R180 -> 6.87 | F91: =E91*$F$2 -> 7.0761
C92: 5 | D92: Muro blanco | E92: =CO!R181 -> 16.47 | F92: =E92*$F$2 -> 16.9641
C93: 4 | D93: Muro balcón blanco | E93: =CO!R182 -> 6.87 | F93: =E93*$F$2 -> 7.0761
C94: 3 | D94: Muro blanco | E94: =CO!R183 -> 16.47 | F94: =E94*$F$2 -> 16.9641
C95: 2 | D95: Muro balcón blanco | E95: =CO!R184 -> 6.87 | F95: =E95*$F$2 -> 7.0761
C96: 1 | D96: Lámina siding | E96: =CO!R185 -> 12 | F96: =E96*$F$2 -> 12.36
B97: 9 | C97: 9 | D97: Lámina siding | E97: 42.6 | F97: =E97*$F$2 -> 43.878 | I97: 9 | J97: Lámina siding | K97: =E97 -> 42.6 | L97: =K97*$F$2 -> 43.878
D98: Muros gris | E98: 7 | F98: =E98*$F$2 -> 7.21 | J98: Muros gris | K98: =E98+E99+E101+E102+E104+E105+E107+E108 -> 141.2 | L98: =K98*$F$2 -> 145.436
C99: 8 | D99: Muros gris | E99: 28.3 | F99: =E99*$F$2 -> 29.149 | J99: Muros blancos | K99: =E100+E103+E106 -> 127.8 | L99: =K99*$F$2 -> 131.634
C100: 7 | D100: Muros blancos | E100: 42.6 | F100: =E100*$F$2 -> 43.878 | J100: Muro placa blanco | K100: =E109 -> 8.2 | L100: =K100*$F$2 -> 8.446
D101: Muros gris | E101: 7 | F101: =E101*$F$2 -> 7.21 | J101: Muro placa siding | K101: =E110 -> 3.4 | L101: =K101*$F$2 -> 3.502
C102: 6 | D102: Muros gris | E102: 28.3 | F102: =E102*$F$2 -> 29.149
C103: 5 | D103: Muros blancos | E103: 42.6 | F103: =E103*$F$2 -> 43.878
D104: Muros gris | E104: 7 | F104: =E104*$F$2 -> 7.21
...

Sheet Lavado
A1: CEDROS - LAVADO DE FACHADA
E2: ENE 15 - 17 | G2: ENE 19 - 24 | I2: ENE 26 - 31 | K2: FEB 02-07 | M2: FEB 09-14 | O2: FEB 16 - 21 | Q2: FEB 23 - 28
A3: Fachada | B3: Sección | C3: Descripción | D3: M2 | E3: Semana 01 | G3: Semana 02 | I3: Semana 03 | K3: Semana 04 | M3: Semana 05 | O3: Semana 06 | Q3: Semana 07 | S3: Total Ejecutado | U3: Total Ejecutado Acta 01
E4: M2 | F4: % | G4: M2 | H4: % | I4: M2 | J4: % | K4: M2 | L4: % | M4: M2 | N4: % | O4: M2 | P4: % | Q4: M2 | R4: % | S4: M2 | T4: % | U4: M2 | V4: %
A5: A | B5: 1 | C5: Lavado de fachada | D5: 68.2 | E5: =D5*F5 -> 0 | F5: 0 | G5: =D5*H5 -> 0 | H5: 0 | I5: =D5*J5 -> 0 | J5: 0 | K5: =D5*L5 -> 0 | L5: 0 | M5: =N5*D5 -> 0 | N5: 0 | O5: =P5*D5 -> 68.2 | P5: 1 | Q5: =R5*D5 -> 0 | R5: 0 | S5: =E5+G5+I5+K5+M5+O5+Q5 -> 68.2 | T5: =S5/D5 -> 1 | U5: =E5+G5+I5+K5+M5 -> 0 | V5: =U5/D5 -> 0
C6: Lavado de vidrios | D6: 6 | E6: =D6*F6 -> 0 | F6: 0 | G6: =D6*H6 -> 0 | H6: 0 | I6: =D6*J6 -> 0 | J6: 0 | K6: =D6*L6 -> 0 | L6: 0 | M6: =N6*D6 -> 0 | N6: 0 | O6: =P6*D6 -> 6 | P6: 1 | Q6: =R6*D6 -> 0 | R6: 0 | S6: =E6+G6+I6+K6+M6+O6+Q6 -> 6 | T6: =S6/D6 -> 1 | U6: =E6+G6+I6+K6+M6 -> 0 | V6: =U6/D6 -> 0
B7: 2 | C7: Lavado de fachada | D7: 33.8 | E7: =D7*F7 -> 0 | F7: 0 | G7: =D7*H7 -> 0 | H7: 0 | I7: =D7*J7 -> 0 | J7: 0 | K7: =D7*L7 -> 0 | L7: 0 | M7: =N7*D7 -> 0 | N7: 0 | O7: =P7*D7 -> 33.8 | P7: 1 | Q7: =R7*D7 -> 0 | R7: 0 | S7: =E7+G7+I7+K7+M7+O7+Q7 -> 33.8 | T7: =S7/D7 -> 1 | U7: =E7+G7+I7+K7+M7 -> 0 | V7: =U7/D7 -> 0
C8: Lavado de vidrios | D8: 8.64 | E8: =D8*F8 -> 0 | F8: 0 | G8: =D8*H8 -> 0 | H8: 0 | I8: =D8*J8 -> 0 | J8: 0 | K8: =D8*L8 -> 0 | L8: 0 | M8: =N8*D8 -> 0 | N8: 0 | O8: =P8*D8 -> 0 | P8: 0 | Q8: =R8*D8 -> 8.64 | R8: 1 | S8: =E8+G8+I8+K8+M8+O8+Q8 -> 8.64 | T8: =S8/D8 -> 1 | U8: =E8+G8+I8+K8+M8 -> 0 | V8: =U8/D8 -> 0
B9: 3 | C9: Lavado de fachada | D9: 60.9 | E9: =D9*F9 -> 0 | F9: 0 | G9: =D9*H9 -> 0 | H9: 0 | I9: =D9*J9 -> 45.675 | J9: 0.75 | K9: =D9*L9 -> 60.9 | L9: 1 | M9: =N9*D9 -> 0 | N9: 0 | O9: =P9*D9 -> 0 | P9: 0 | Q9: =R9*D9 -> 0 | R9: 0 | S9: =E9+G9+I9+K9+M9+O9+Q9 -> 106.575 | T9: =S9/D9 -> 1.75 | U9: =E9+G9+I9+K9+M9 -> 106.575 | V9: =U9/D9 -> 1.75
C10: Lavado de vidrios | D10: 1 | E10: =D10*F10 -> 0 | F10: 0 | G10: =D10*H10 -> 0 | H10: 0 | I10: =D10*J10 -> 1 | J10: 1 | K10: =D10*L10 -> 0 | L10: 0 | M10: =N10*D10 -> 0 | N10: 0 | O10: =P10*D10 -> 0 | P10: 0 | Q10: =R10*D10 -> 0 | R10: 0 | S10: =E10+G10+I10+K10+M10+O10+Q10 -> 1 | T10: =S10/D10 -> 1 | U10: =E10+G10+I10+K10+M10 -> 1 | V10: =U10/D10 -> 1
B11: 4 | C11: Lavado de fachada | D11: 33.8 | E11: =D11*F11 -> 0 | F11: 0 | G11: =D11*H11 -> 16.9 | H11: 0.5 | I11: =D11*J11 -> 16.9 | J11: 0.5 | K11: =D11*L11 -> 33.8 | L11: 1 | M11: =N11*D11 -> 0 | N11: 0 | O11: =P11*D11 -> 0 | P11: 0 | Q11: =R11*D11 -> 0 | R11: 0 | S11: =E11+G11+I11+K11+M11+O11+Q11 -> 67.6 | T11: =S11/D11 -> 2 | U11: =E11+G11+I11+K11+M11 -> 67.6 | V11: =U11/D11 -> 2
C12: Lavado de vidrios | D12: 8.64 | E12: =D12*F12 -> 0 | F12: 0 | G12: =D12*H12 -> 4.32 | H12: 0.5 | I12: =D12*J12 -> 4.32 | J12: 0.5 | K12: =D12*L12 -> 0 | L12: 0 | M12: =N12*D12 -> 0 | N12: 0 | O12: =P12*D12 -> 0 | P12: 0 | Q12: =R12*D12 -> 0 | R12: 0 | S12: =E12+G12+I12+K12+M12+O12+Q12 -> 8.64 | T12: =S12/D12 -> 1 | U12: =E12+G12+I12+K12+M12 -> 8.64 | V12: =U12/D12 -> 1
B13: 5 | C13: Lavado de fachada | D13: 106.45 | E13: =D13*F13 -> 0 | F13: 0 | G13: =D13*H13 -> 106.45 | H13: 1 | I13: =D13*J13 -> 0 | J13: 0 | K13: =D13*L13 -> 106.45 | L13: 1 | M13: =N13*D13 -> 0 | N13: 0 | O13: =P13*D13 -> 0 | P13: 0 | Q13: =R13*D13 -> 0 | R13: 0 | S13: =E13+G13+I13+K13+M13+O13+Q13 -> 212.9 | T13: =S13/D13 -> 2 | U13: =E13+G13+I13+K13+M13 -> 212.9 | V13: =U13/D13 -> 2
C14: Lavado de vidrios | D14: 6 | E14: =D14*F14 -> 0 | F14: 0 | G14: =D14*H14 -> 6 | H14: 1 | I14: =D14*J14 -> 0 | J14: 0 | K14: =D14*L14 -> 0 | L14: 0 | M14: =N14*D14 -> 0 | N14: 0 | O14: =P14*D14 -> 0 | P14: 0 | Q14: =R14*D14 -> 0 | R14: 0 | S14: =E14+G14+I14+K14+M14+O14+Q14 -> 6 | T14: =S14/D14 -> 1 | U14: =E14+G14+I14+K14+M14 -> 6 | V14: =U14/D14 -> 1
C16: Total M2 de Fachada | D16: =SUM(D5:D14) -> 333.43 | E16: =SUM(E5:E14) -> 0 | F16: =E16/$D$16 -> 0 | G16: =SUM(G5:G14) -> 133.67 | H16: =G16/$D$16 -> 0.40089374 | I16: =SUM(I5:I14) -> 67.895 | J16: =I16/$D$16 -> 0.20362595 | K16: =SUM(K5:K14) -> 201.15 | L16: =K16/$D$16 -> 0.60327505 | M16: =SUM(M5:M14) -> 0 | N16: =M16/$D$16 -> 0 | O16: =SUM(O5:O14) -> 108 | P16: =O16/$D$16 -> 0.32390607 | Q16: =SUM(Q5:Q14) -> 8.64 | R16: =Q16/$D$16 -> 0.025912485 | S16: =SUM(S5:S14) -> 519.355 | T16: =S16/D16 -> 1.5576133 | U16: =SUM(U5:U14) -> 402.715 | V16: =U16/$D$16 -> 1.2077947
S17: =D16-S16 -> -185.925 | T17: =S17/D16 -> -0.55761329
A19: B | B19: 6 | C19: Lavado de fachada | D19: 193.3 | E19: =D19*F19 -> 0 | F19: 0 | G19: =D19*H19 -> 193.3 | H19: 1 | I19: =D19*J19 -> 0 | J19: 0 | K19: =D19*L19 -> 0 | L19: 0 | M19: =D19*N19 -> 121.3924 | N19: 0.628 | O19: =P19*D19 -> 0 | P19: 0 | Q19: =R19*D19 -> 71.9076 | R19: 0.372 | S19: =E19+G19+I19+K19+M19+O19+Q19 -> 386.6 | T19: =S19/D19 -> 2 | U19: =E19+G19+I19+K19+M19 -> 314.6924 | V19: =U19/D19 -> 1.628
C20: Lavado de vidrios | D20: 106.45 | E20: =D20*F20 -> 0 | F20: 0 | G20: =D20*H20 -> 0 | H20: 0 | I20: =D20*J20 -> 0 | J20: 0 | K20: =D20*L20 -> 0 | L20: 0 | M20: =D20*N20 -> 66.8506 | N20: 0.628 | O20: =P20*D20 -> 106.45 | P20: 1 | Q20: =R20*D20 -> 39.5994 | R20: 0.372 | S20: =E20+G20+I20+K20+M20+O20+Q20 -> 212.9 | T20: =S20/D20 -> 2 | U20: =E20+G20+I20+K20+M20 -> 66.8506 | V20: =U20/D20 -> 0.628
C22: Total M2 de Fachada | D22: =SUM(D19:D20) -> 299.75 | E22: =SUM(E19:E20) -> 0 | F22: =E22/$D$22 -> 0 | G22: =SUM(G19:G20) -> 193.3 | H22: =G22/$D$22 -> 0.64487073 | I22: =SUM(I19:I20) -> 0 | J22: =I22/$D$22 -> 0 | K22: =SUM(K19:K20) -> 0 | L22: =K22/$D$22 -> 0 | M22: =SUM(M19:M20) -> 188.243 | N22: =M22/$D$22 -> 0.628 | O22: =SUM(O19:O20) -> 106.45 | P22: =O22/$D$22 -> 0.35512927 | Q22: =SUM(Q19:Q20) -> 111.507 | R22: =Q22/$D$22 -> 0.372 | S22: =SUM(S19:S20) -> 599.5 | T22: =S22/$D$22 -> 2 | U22: =SUM(U19:U20) -> 381.543 | V22: =U22/D22 -> 1.2728707
S23: =D22-S22 -> -299.75 | T23: =S23/D22 -> -1
A25: C | B25: 1 | C25: Lavado de fachada | D25: 76.2 | E25: =D25*F25 -> 0 | F25: 0 | G25: =D25*H25 -> 0 | H25: 0 | I25: =D25*J25 -> 0 | J25: 0 | K25: =D25*L25 -> 0 | L25: 0 | M25: =F25*N25 -> 0 | N25: 0 | O25: =P25*D25 -> 0 | P25: 0 | Q25: =R25*D25 -> 0 | R25: 0 | S25: =E25+G25+I25+K25+M25+O25+Q25 -> 0 | T25: =S25/D25 -> 0 | U25: =E25+G25+I25+K25+M25 -> 0 | V25: =U25/D25 -> 0
C26: Lavado de vidrios | D26: 0 | E26: =D26*F26 -> 0 | F26: 0 | G26: =D26*H26 -> 0 | H26: 0 | I26: =D26*J26 -> 0 | J26: 0 | K26: =D26*L26 -> 0 | L26: 0 | M26: =F26*N26 -> 0 | N26: 0 | O26: =H26*P26 -> 0 | P26: 0 | Q26: =J26*R26 -> 0 | R26: 0 | S26: =E26+G26+I26+K26+M26+O26+Q26 -> 0 | T26: =S26/D26 -> #DIV/0! | U26: =E26+G26+I26+K26+M26 -> 0 | V26: =U26/D26 -> #DIV/0!
B27: 7 | C27: Lavado de fachada | D27: 194.2 | E27: =D27*F27 -> 0 | F27: 0 | G27: =D27*H27 -> 0 | H27: 0 | I27: =D27*J27 -> 0 | J27: 0 | K27: =D27*L27 -> 0 | L27: 0 | M27: =F27*N27 -> 0 | N27: 0 | O27: =H27*P27 -> 0 | P27: 0 | Q27: =J27*R27 -> 0 | R27: 0 | S27: =E27+G27+I27+K27+M27+O27+Q27 -> 0 | T27: =S27/D27 -> 0 | U27: =E27+G27+I27+K27+M27 -> 0 | V27: =U27/D27 -> 0
C28: Lavado de vidrios | D28: 117.83 | E28: =D28*F28 -> 0 | F28: 0 | G28: =D28*H28 -> 0 | H28: 0 | I28: =D28*J28 -> 0 | J28: 0 | K28: =D28*L28 -> 117.83 | L28: 1 | M28: =F28*N28 -> 0 | N28: 0 | O28: =H28*P28 -> 0 | P28: 0 | Q28: =J28*R28 -> 0 | R28: 0 | S28: =E28+G28+I28+K28+M28+O28+Q28 -> 117.83 | T28: =S28/D28 -> 1 | U28: =E28+G28+I28+K28+M28 -> 117.83 | V28: =U28/D28 -> 1
C30: Total M2 de Fachada | D30: =SUM(D25:D28) -> 388.23 | E30: =SUM(E25:E28) -> 0 | F30: =E30/$D$30 -> 0 | G30: =SUM(G25:G28) -> 0 | H30: =G30/$D$30 -> 0 | I30: =SUM(I25:I28) -> 0 | J30: =I30/$D$30 -> 0 | K30: =SUM(K25:K28) -> 117.83 | L30: =K30/$D$30 -> 0.30350565 | M30: =SUM(M25:M28) -> 0 | N30: =M30/$D$30 -> 0 | O30: =SUM(O25:O28) -> 0 | P30: =O30/$D$30 -> 0 | Q30: =SUM(Q25:Q28) -> 0 | R30: =Q30/$D$30 -> 0 | S30: =SUM(S25:S28) -> 117.83 | T30: =S30/D30 -> 0.30350565 | U30: =SUM(U25:U28) -> 117.83 | V30: =U30/D30 -> 0.30350565
S31: =D30-S30 -> 270.4 | T31: =S31/D30 -> 0.69649435
A33: D | B33: 8 | C33: Lavado de fachada | D33: 68.8 | E33: =D33*F33 -> 68.8 | F33: 1 | G33: =D33*H33 -> 0 | H33: 0 | I33: =D33*J33 -> 0 | J33: 0 | K33: =D33*L33 -> 0 | L33: 0 | M33: =D33*N33 -> 0 | N33: 0 | O33: =P33*D33 -> 0 | P33: 0 | Q33: =R33*D33 -> 0 | R33: 0 | S33: =E33+G33+I33+K33+M33+O33+Q33 -> 68.8 | T33: =S33/D33 -> 1 | U33: =E33+G33+I33+K33+M33 -> 68.8 | V33: =U33/D33 -> 1
C34: Lavado de vidrios | D34: 0 | E34: =D34*F34 -> 0 | F34: 0 | G34: =D34*H34 -> 0 | H34: 0 | I34: =D34*J34 -> 0 | J34: 0 | K34: =D34*L34 -> 0 | L34: 0 | M34: =D34*N34 -> 0 | N34: 0 | O34: =F34*P34 -> 0 | P34: 0 | Q34: =H34*R34 -> 0 | R34: 0 | S34: =E34+G34+I34+K34+M34+O34+Q34 -> 0 | T34: =S34/D34 -> #DIV/0! | U34: =E34+G34+I34+K34+M34 -> 0 | V34: =U34/D34 -> #DIV/0!
B35: 9 | C35: Lavado de fachada | D35: 33.8 | E35: =D35*F35 -> 33.8 | F35: 1 | G35: =D35*H35 -> 0 | H35: 0 | I35: =D35*J35 -> 0 | J35: 0 | K35: =D35*L35 -> 0 | L35: 0 | M35: =D35*N35 -> 0 | N35: 0 | O35: =P35*D35 -> 0 | P35: 0 | Q35: =R35*D35 -> 0 | R35: 0 | S35: =E35+G35+I35+K35+M35+O35+Q35 -> 33.8 | T35: =S35/D35 -> 1 | U35: =E35+G35+I35+K35+M35 -> 33.8 | V35: =U35/D35 -> 1
C36: Lavado de vidrios | D36: 2.1 | E36: =D36*F36 -> 0 | F36: 0 | G36: =D36*H36 -> 0 | H36: 0 | I36: =D36*J36 -> 0 | J36: 0 | K36: =D36*L36 -> 0 | L36: 0 | M36: =D36*N36 -> 2.1 | N36: 1 | O36: =F36*P36 -> 0 | P36: 0 | Q36: =H36*R36 -> 0 | R36: 0 | S36: =E36+G36+I36+K36+M36+O36+Q36 -> 2.1 | T36: =S36/D36 -> 1 | U36: =E36+G36+I36+K36+M36 -> 2.1 | V36: =U36/D36 -> 1
B37: 10 | C37: Lavado de fachada | D37: 60.9 | E37: =D37*F37 -> 60.9 | F37: 1 | G37: =D37*H37 -> 0 | H37: 0 | I37: =D37*J37 -> 0 | J37: 0 | K37: =D37*L37 -> 0 | L37: 0 | M37: =D37*N37 -> 0 | N37: 0 | O37: =P37*D37 -> 0 | P37: 0 | Q37: =R37*D37 -> 0 | R37: 0 | S37: =E37+G37+I37+K37+M37+O37+Q37 -> 60.9 | T37: =S37/D37 -> 1 | U37: =E37+G37+I37+K37+M37 -> 60.9 | V37: =U37/D37 -> 1
C38: Lavado de vidrios | D38: =0 -> 0 | E38: =D38*F38 -> 0 | F38: 0 | G38: =D38*H38 -> 0 | H38: 0 | I38: =D38*J38 -> 0 | J38: 0 | K38: =D38*L38 -> 0 | L38: 0 | M38: =D38*N38 -> 0 | N38: 0 | O38: =F38*P38 -> 0 | P38: 0 | Q38: =H38*R38 -> 0 | R38: 0 | S38: =E38+G38+I38+K38+M38+O38+Q38 -> 0 | T38: =S38/D38 -> #DIV/0! | U38: =E38+G38+I38+K38+M38 -> 0 | V38: =U38/D38 -> #DIV/0!
B39: 11 | C39: Lavado de fachada | D39: 33.8 | E39: =D39*F39 -> 33.8 | F39: 1 | G39: =D39*H39 -> 0 | H39: 0 | I39: =D39*J39 -> 0 | J39: 0 | K39: =D39*L39 -> 0 | L39: 0 | M39: =D39*N39 -> 0 | N39: 0 | O39: =P39*D39 -> 0 | P39: 0 | Q39: =R39*D39 -> 0 | R39: 0 | S39: =E39+G39+I39+K39+M39+O39+Q39 -> 33.8 | T39: =S39/D39 -> 1 | U39: =E39+G39+I39+K39+M39 -> 33.8 | V39: =U39/D39 -> 1
C40: Lavado de vidrios | D40: 2.1 | E40: =D40*F40 -> 0 | F40: 0 | G40: =D40*H40 -> 0 | H40: 0 | I40: =D40*J40 -> 0 | J40: 0 | K40: =D40*L40 -> 0 | L40: 0 | M40: =D40*N40 -> 2.1 | N40: 1 | O40: =F40*P40 -> 0 | P40: 0 | Q40: =H40*R40 -> 0 | R40: 0 | S40: =E40+G40+I40+K40+M40+O40+Q40 -> 2.1 | T40: =S40/D40 -> 1 | U40: =E40+G40+I40+K40+M40 -> 2.1 | V40: =U40/D40 -> 1
B41: 12 | C41: Lavado de fachada | D41: 69.1 | E41: =D41*F41 -> 69.1 | F41: 1 | G41: =D41*H41 -> 0 | H41: 0 | I41: =D41*J41 -> 0 | J41: 0 | K41: =D41*L41 -> 0 | L41: 0 | M41: =D41*N41 -> 0 | N41: 0 | O41: =P41*D41 -> 0 | P41: 0 | Q41: =R41*D41 -> 0 | R41: 0 | S41: =E41+G41+I41+K41+M41+O41+Q41 -> 69.1 | T41: =S41/D41 -> 1 | U41: =E41+G41+I41+K41+M41 -> 69.1 | V41: =U41/D41 -> 1
C42: Lavado de vidrios | D42: 1.24 | E42: =D42*F42 -> 0 | F42: 0 | G42: =D42*H42 -> 0 | H42: 0 | I42: =D42*J42 -> 0 | J42: 0 | K42: =D42*L42 -> 0 | L42: 0 | M42: =D42*N42 -> 0 | N42: 0 | O42: =F42*P42 -> 0 | P42: 0 | Q42: =H42*R42 -> 0 | R42: 0 | S42: =E42+G42+I42+K42+M42+O42+Q42 -> 0 | T42: =S42/D42 -> 0 | U42: =E42+G42+I42+K42+M42 -> 0 | V42: =U42/D42 -> 0
C44: Total M2 de Fachada | D44: =SUM(D33:D42) -> 271.84 | E44: =SUM(E33:E42) -> 266.4 | F44: =E44/$D$44 -> 0.97998823 | G44: =SUM(G33:G42) -> 0 | H44: =G44/$D$44 -> 0 | I44: =SUM(I33:I42) -> 0 | J44: =I44/$D$44 -> 0 | K44: =SUM(K33:K42) -> 0 | L44: =K44/$D$44 -> 0 | M44: =SUM(M33:M42) -> 4.2 | N44: =M44/$D$44 -> 0.015450265 | O44: =SUM(O33:O42) -> 0 | P44: =O44/$D$44 -> 0 | Q44: =SUM(Q33:Q42) -> 0 | R44: =Q44/$D$44 -> 0 | S44: =SUM(S33:S42) -> 270.6 | T44: =S44/$D$44 -> 0.99543849 | U44: =SUM(U33:U42) -> 270.6 | V44: =U44/$D$44 -> 0.99543849
S45: =D44-S44 -> 1.24 | T45: =S45/D44 -> 0.0045615068
A47: E | B47: 13 | C47: Lavado de fachada | D47: 181.8 | E47: =D47*F47 -> 0 | F47: 0 | G47: 100 | H47: 0 | I47: =D47*J47 -> 0 | J47: 0 | K47: =D47*L47 -> 0 | L47: 0 | M47: =D47*N47 -> 0 | N47: 0 | O47: =P47*D47 -> 0 | P47: 0 | Q47: =R47*D47 -> 0 | R47: 0 | S47: =E47+G47+I47+K47+M47+O47+Q47 -> 100 | T47: =S47/D47 -> 0.55005501 | U47: =E47+G47+I47+K47+M47 -> 100 | V47: =U47/D47 -> 0.55005501
C48: Lavado de vidrios | D48: 100.38 | E48: =D48*F48 -> 0 | F48: 0 | G48: =D48*H48 -> 0 | H48: 0 | I48: =D48*J48 -> 0 | J48: 0 | K48: =D48*L48 -> 0 | L48: 0 | M48: =D48*N48 -> 0 | N48: 0 | O48: =F48*P48 -> 0 | P48: 0 | Q48: =H48*R48 -> 0 | R48: 0 | S48: =E48+G48+I48+K48+M48+O48+Q48 -> 0 | T48: =S48/D48 -> 0 | U48: =E48+G48+I48+K48+M48 -> 0 | V48: =U48/D48 -> 0
C50: Total M2 de Fachada | D50: =SUM(D47:D48) -> 282.18 | E50: =SUM(E47:E48) -> 0 | F50: =E50/$D$50 -> 0 | G50: =SUM(G47:G48) -> 100 | H50: =G50/$D$50 -> 0.35438373 | I50: =SUM(I47:I48) -> 0 | J50: =I50/$D$50 -> 0 | K50: =SUM(K47:K48) -> 0 | L50: =K50/$D$50 -> 0 | M50: =SUM(M47:M48) -> 0 | N50: =M50/$D$50 -> 0 | O50: =SUM(O47:O48) -> 0 | P50: =O50/$D$50 -> 0 | Q50: =SUM(Q47:Q48) -> 0 | R50: =Q50/$D$50 -> 0 | S50: =SUM(S47:S48) -> 100 | T50: =S50/D50 -> 0.35438373 | U50: =SUM(U47:U48) -> 100 | V50: =U50/D50 -> 0.35438373
A53: F | B53: 14 | C53: Lavado de fachada | D53: 61 | E53: =D53*F53 -> 0 | F53: 0 | G53: =H53*D53 -> 30.5 | H53: 0.5 | I53: =D53*J53 -> 30.5 | J53: 0.5 | K53: =D53*L53 -> 15.25 | L53: 0.25 | M53: =F53*N53 -> 0 | N53: 0 | O53: =P53*D53 -> 0 | P53: 0 | Q53: =R53*D53 -> 0 | R53: 0 | S53: =E53+G53+I53+K53+M53+O53+Q53 -> 76.25 | T53: =S53/D53 -> 1.25 | U53: =E53+G53+I53+K53+M53 -> 76.25 | V53: =U53/D53 -> 1.25
C54: Lavado de vidrios | D54: 33.79 | E54: =D54*F54 -> 0 | F54: 0 | G54: =D54*H54 -> 0 | H54: 0 | I54: =D54*J54 -> 0 | J54: 0 | K54: =D54*L54 -> 0 | L54: 0 | M54: =F54*N54 -> 0 | N54: 0 | O54: =H54*P54 -> 0 | P54: 0 | Q54: =J54*R54 -> 0 | R54: 0 | S54: =E54+G54+I54+K54+M54+O54+Q54 -> 0 | T54: =S54/D54 -> 0 | U54: =E54+G54+I54+K54+M54 -> 0 | V54: =U54/D54 -> 0
B55: 15 | C55: Lavado de fachada | D55: 181.4 | E55: =D55*F55 -> 0 | F55: 0 | G55: =H55*D55 -> 90.7 | H55: 0.5 | I55: =D55*J55 -> 90.7 | J55: 0.5 | K55: =D55*L55 -> 45.35 | L55: 0.25 | M55: =F55*N55 -> 0 | N55: 0 | O55: =H55*P55 -> 0 | P55: 0 | Q55: =J55*R55 -> 0 | R55: 0 | S55: =E55+G55+I55+K55+M55+O55+Q55 -> 226.75 | T55: =S55/D55 -> 1.25 | U55: =E55+G55+I55+K55+M55 -> 226.75 | V55: =U55/D55 -> 1.25
C56: Lavado de vidrios | D56: 100.38 | E56: =D56*F56 -> 0 | F56: 0 | G56: =D56*H56 -> 0 | H56: 0 | I56: =D56*J56 -> 0 | J56: 0 | K56: =D56*L56 -> 0 | L56: 0 | M56: =F56*N56 -> 0 | N56: 0 | O56: =H56*P56 -> 0 | P56: 0 | Q56: =J56*R56 -> 0 | R56: 0 | S56: =E56+G56+I56+K56+M56+O56+Q56 -> 0 | T56: =S56/D56 -> 0 | U56: =E56+G56+I56+K56+M56 -> 0 | V56: =U56/D56 -> 0
C58: Total M2 de Fachada | D58: =SUM(D53:D56) -> 376.57 | E58: =SUM(E53:E56) -> 0 | F58: =E58/$D$58 -> 0 | G58: =SUM(G53:G56) -> 121.2 | H58: =G58/$D$58 -> 0.32185251 | I58: =SUM(I53:I56) -> 121.2 | J58: =I58/$D$58 -> 0.32185251 | K58: =SUM(K53:K56) -> 60.6 | L58: =K58/$D$58 -> 0.16092626 | M58: =SUM(M53:M56) -> 0 | N58: =M58/$D$58 -> 0 | O58: =SUM(O53:O56) -> 0 | P58: =O58/$D$58 -> 0 | Q58: =SUM(Q53:Q56) -> 0 | R58: =Q58/$D$58 -> 0 | S58: =SUM(S53:S56) -> 303 | T58: =S58/D58 -> 0.80463128 | U58: =SUM(U53:U56) -> 303 | V58: =U58/D58 -> 0.80463128
A60: PUNTO FIJO | B60: 1 IZQUIERDA | C60: Lavado de fachada | D60: 76.44 | E60: =D60*F60 -> 0 | F60: 0 | G60: =D60*H60 -> 0 | H60: 0 | I60: =D60*J60 -> 0 | J60: 0 | K60: =D60*L60 -> 0 | L60: 0 | M60: =F60*N60 -> 0 | N60: 0 | O60: =P60*D60 -> 0 | P60: 0 | Q60: =R60*D60 -> 0 | R60: 0 | S60: =E60+G60+I60+K60+M60+O60+Q60 -> 0 | T60: =S60/D60 -> 0 | U60: =E60+G60+I60+K60+M60 -> 0 | V60: =U60/D60 -> 0
C61: Lavado de vidrios | D61: 0 | E61: =D61*F61 -> 0 | F61: 0 | G61: =D61*H61 -> 0 | H61: 0 | I61: =D61*J61 -> 0 | J61: 0 | K61: =D61*L61 -> 0 | L61: 0 | M61: =F61*N61 -> 0 | N61: 0 | O61: =H61*P61 -> 0 | P61: 0 | Q61: =J61*R61 -> 0 | R61: 0 | S61: =E61+G61+I61+K61+M61+O61+Q61 -> 0 | T61: =S61/D61 -> #DIV/0! | U61: =E61+G61+I61+K61+M61 -> 0 | V61: =U61/D61 -> #DIV/0!
B62: CARACOL | C62: Lavado de fachada | D62: =16.2*4+22.3+47.92+28.125+37.4+131 -> 331.545 | E62: =D62*F62 -> 0 | F62: 0 | G62: =D62*H62 -> 165.7725 | H62: 0.5 | I62: =D62*J62 -> 165.7725 | J62: 0.5 | K62: =D62*L62 -> 0 | L62: 0 | M62: =F62*N62 -> 0 | N62: 0 | O62: =H62*P62 -> 0 | P62: 0 | Q62: =J62*R62 -> 0 | R62: 0 | S62: =E62+G62+I62+K62+M62+O62+Q62 -> 331.545 | T62: =S62/D62 -> 1 | U62: =E62+G62+I62+K62+M62 -> 331.545 | V62: =U62/D62 -> 1
C63: Lavado de vidrios | D63: 0 | E63: =D63*F63 -> 0 | F63: 0 | G63: =D63*H63 -> 0 | H63: 0 | I63: =D63*J63 -> 0 | J63: 0 | K63: =D63*L63 -> 0 | L63: 0 | M63: =F63*N63 -> 0 | N63: 0 | O63: =H63*P63 -> 0 | P63: 0 | Q63: =J63*R63 -> 0 | R63: 0 | S63: =E63+G63+I63+K63+M63+O63+Q63 -> 0 | T63: =S63/D63 -> #DIV/0! | U63: =E63+G63+I63+K63+M63 -> 0 | V63: =U63/D63 -> #DIV/0!
B64: 1 DERECHA | C64: Lavado de fachada | D64: 76.44 | E64: =D64*F64 -> 0 | F64: 0 | G64: =D64*H64 -> 0 | H64: 0 | I64: =D64*J64 -> 0 | J64: 0 | K64: =D64*L64 -> 0 | L64: 0 | M64: =F64*N64 -> 0 | N64: 0 | O64: =H64*P64 -> 0 | P64: 0 | Q64: =J64*R64 -> 0 | R64: 0 | S64: =E64+G64+I64+K64+M64+O64+Q64 -> 0 | T64: =S64/D64 -> 0 | U64: =E64+G64+I64+K64+M64 -> 0 | V64: =U64/D64 -> 0
C65: Lavado de vidrios | D65: 0 | E65: =D65*F65 -> 0 | F65: 0 | G65: =D65*H65 -> 0 | H65: 0 | I65: =D65*J65 -> 0 | J65: 0 | K65: =D65*L65 -> 0 | L65: 0 | M65: =F65*N65 -> 0 | N65: 0 | O65: =H65*P65 -> 0 | P65: 0 | Q65: =J65*R65 -> 0 | R65: 0 | S65: =E65+G65+I65+K65+M65+O65+Q65 -> 0 | T65: =S65/D65 -> #DIV/0! | U65: =E65+G65+I65+K65+M65 -> 0 | V65: =U65/D65 -> #DIV/0!
C67: Total M2 de Fachada | D67: =SUM(D60:D65) -> 484.425 | E67: =SUM(E60:E65) -> 0 | F67: =E67/$D$67 -> 0 | G67: =SUM(G60:G65) -> 165.7725 | H67: =G67/$D$67 -> 0.34220468 | I67: =SUM(I60:I65) -> 165.7725 | J67: =I67/$D$67 -> 0.34220468 | K67: =SUM(K60:K65) -> 0 | L67: =K67/$D$67 -> 0 | M67: =SUM(M60:M65) -> 0 | N67: =M67/$D$67 -> 0 | O67: =SUM(O60:O65) -> 0 | P67: =O67/$D$67 -> 0 | Q67: =SUM(Q60:Q65) -> 0 | R67: =Q67/$D$67 -> 0 | S67: =SUM(S60:S65) -> 331.545 | T67: =S67/D67 -> 0.68440935 | U67: =SUM(U60:U65) -> 331.545 | V67: =U67/D67 -> 0.68440935
C69: Total M2 de Fachada General | D69: =D16+D22+D30+D44+D50+D58+D67 -> 2436.425 | K69: Total de M2 Ejecutados | S69: =S16+S22+S30+S44+S50+S58+S67 -> 2241.83 | T69: =S69/D69 -> 0.92013093 | U69: =U16+U22+U30+U44 -> 1172.688 | V69: =U69/D69 -> 0.48131504
S70: =D69-S69 -> 194.595 | T70: =S70/D69 -> 0.07986907
T72: 0.59
T73: 0.41

Sheet Sellos
A1: CEDROS - SELLO PERIMETRAL
E2: ENE 15 - 17 | G2: ENE 19 - 24 | I2: ENE 26 - 31 | K2: FEB 02-07 | M2: FEB 09-14 | O2: FEB 16 - 21 | Q2: FEB 23 - 28
A3: Fachada | B3: Sección | C3: Descripción | D3: M2 | E3: Semana 01 | G3: Semana 02 | I3: Semana 03 | K3: Semana 04 | M3: Semana 05 | O3: Semana 06 | Q3: Semana 07 | S3: Total Ejecutado | U3: Total Ejecutado Acta 01
E4: M2 | F4: % | G4: M2 | H4: % | I4: M2 | J4: % | K4: M2 | L4: % | M4: M2 | N4: % | O4: M2 | P4: % | Q4: M2 | R4: % | S4: M2 | T4: % | U4: M2 | V4: %
A5: A | B5: 1 | C5: SELLO PERIMETRAL | D5: 30 | E5: =D5*F5 -> 0 | F5: 0 | G5: =D5*H5 -> 0 | H5: 0 | I5: =D5*J5 -> 0 | J5: 0 | K5: =D5*L5 -> 0 | L5: 0 | M5: =N5*D5 -> 0 | N5: 0 | O5: =P5*D5 -> 30 | P5: 1 | Q5: =R5*D5 -> 0 | R5: 0 | S5: =E5+G5+I5+K5+M5+O5+Q5 -> 30 | T5: =S5/D5 -> 1 | U5: =E5+G5+I5+K5+M5 -> 0 | V5: =U5/D5 -> 0
B6: 2 | C6: SELLO PERIMETRAL | D6: 15.2 | E6: =D6*F6 -> 0 | F6: 0 | G6: =D6*H6 -> 0 | H6: 0 | I6: =D6*J6 -> 0 | J6: 0 | K6: =D6*L6 -> 0 | L6: 0 | M6: =N6*D6 -> 0 | N6: 0 | O6: =P6*D6 -> 15.2 | P6: 1 | Q6: =R6*D6 -> 0 | R6: 0 | S6: =E6+G6+I6+K6+M6+O6+Q6 -> 15.2 | T6: =S6/D6 -> 1 | U6: =E6+G6+I6+K6+M6 -> 0 | V6: =U6/D6 -> 0
B7: 3 | C7: SELLO PERIMETRAL | D7: 1 | E7: =D7*F7 -> 0 | F7: 0 | G7: =D7*H7 -> 0 | H7: 0 | I7: =D7*J7 -> 0 | J7: 0 | K7: =D7*L7 -> 1 | L7: 1 | M7: =N7*D7 -> 0 | N7: 0 | O7: =P7*D7 -> 0 | P7: 0 | Q7: =R7*D7 -> 0 | R7: 0 | S7: =E7+G7+I7+K7+M7+O7+Q7 -> 1 | T7: =S7/D7 -> 1 | U7: =E7+G7+I7+K7+M7 -> 1 | V7: =U7/D7 -> 1
B8: 4 | C8: SELLO PERIMETRAL | D8: 15.2 | E8: =D8*F8 -> 0 | F8: 0 | G8: =D8*H8 -> 0 | H8: 0 | I8: =D8*J8 -> 0 | J8: 0 | K8: =D8*L8 -> 15.2 | L8: 1 | M8: =N8*D8 -> 0 | N8: 0 | O8: =P8*D8 -> 0 | P8: 0 | Q8: =R8*D8 -> 0 | R8: 0 | S8: =E8+G8+I8+K8+M8+O8+Q8 -> 15.2 | T8: =S8/D8 -> 1 | U8: =E8+G8+I8+K8+M8 -> 15.2 | V8: =U8/D8 -> 1
B9: 5 | C9: SELLO PERIMETRAL | D9: 30 | E9: =D9*F9 -> 0 | F9: 0 | G9: =D9*H9 -> 30 | H9: 1 | I9: =D9*J9 -> 0 | J9: 0 | K9: =D9*L9 -> 0 | L9: 0 | M9: =N9*D9 -> 0 | N9: 0 | O9: =P9*D9 -> 0 | P9: 0 | Q9: =R9*D9 -> 0 | R9: 0 | S9: =E9+G9+I9+K9+M9+O9+Q9 -> 30 | T9: =S9/D9 -> 1 | U9: =E9+G9+I9+K9+M9 -> 30 | V9: =U9/D9 -> 1
C11: Total M2 de Fachada | D11: =SUM(D5:D9) -> 91.4 | E11: =SUM(E5:E9) -> 0 | F11: =E11/$D$11 -> 0 | G11: =SUM(G5:G9) -> 30 | H11: =G11/$D$11 -> 0.32822757 | I11: =SUM(I5:I9) -> 0 | J11: =I11/$D$11 -> 0 | K11: =SUM(K5:K9) -> 16.2 | L11: =K11/$D$11 -> 0.17724289 | M11: =SUM(M5:M9) -> 0 | N11: =M11/$D$11 -> 0 | O11: =SUM(O5:O9) -> 45.2 | P11: =O11/$D$11 -> 0.49452954 | Q11: =SUM(Q5:Q9) -> 0 | R11: =Q11/$D$11 -> 0 | S11: =SUM(S5:S9) -> 91.4 | T11: =S11/D11 -> 1 | U11: =SUM(U5:U9) -> 46.2 | V11: =U11/$D$11 -> 0.50547046
S12: =D11-S11 -> 0 | T12: =S12/D11 -> 0
A14: B | B14: 6 | C14: SELLO PERIMETRAL | D14: 166 | E14: =D14*F14 -> 0 | F14: 0 | G14: =D14*H14 -> 166 | H14: 1 | I14: =D14*J14 -> 0 | J14: 0 | K14: =D14*L14 -> 0 | L14: 0 | M14: =D14*N14 -> 0 | N14: 0 | O14: =P14*D14 -> 0 | P14: 0 | Q14: =R14*D14 -> 0 | R14: 0 | S14: =E14+G14+I14+K14+M14+O14+Q14 -> 166 | T14: =S14/D14 -> 1 | U14: =E14+G14+I14+K14+M14 -> 166 | V14: =U14/D14 -> 1
C16: Total M2 de Fachada | D16: =SUM(D14:D14) -> 166 | E16: =SUM(E14:E14) -> 0 | F16: =E16/$D$16 -> 0 | G16: =SUM(G14:G14) -> 166 | H16: =G16/$D$16 -> 1 | I16: =SUM(I14:I14) -> 0 | J16: =I16/$D$16 -> 0 | K16: =SUM(K14:K14) -> 0 | L16: =K16/$D$16 -> 0 | M16: =SUM(M14:M14) -> 0 | N16: =M16/$D$16 -> 0 | O16: =SUM(O14:O14) -> 0 | P16: =O16/$D$16 -> 0 | Q16: =SUM(Q14:Q14) -> 0 | R16: =Q16/$D$16 -> 0 | S16: =SUM(S14:S14) -> 166 | T16: =S16/$D$16 -> 1 | U16: =SUM(U14:U14) -> 166 | V16: =U16/D16 -> 1
S17: =D16-S16 -> 0 | T17: =S17/D16 -> 0
A19: C | B19: 1 | C19: SELLO PERIMETRAL | D19: 1 | E19: =D19*F19 -> 0 | F19: 0 | G19: =D19*H19 -> 0 | H19: 0 | I19: =D19*J19 -> 0 | J19: 0 | K19: =D19*L19 -> 0 | L19: 0 | M19: =F19*N19 -> 0 | N19: 0 | O19: =P19*D19 -> 0 | P19: 0 | Q19: =R19*D19 -> 0 | R19: 0 | S19: =E19+G19+I19+K19+M19+O19+Q19 -> 0 | T19: =S19/D19 -> 0 | U19: =E19+G19+I19+K19+M19 -> 0 | V19: =U19/D19 -> 0
B20: 7 | C20: SELLO PERIMETRAL | D20: 179.8 | E20: =D20*F20 -> 0 | F20: 0 | G20: =D20*H20 -> 0 | H20: 0 | I20: =D20*J20 -> 179.8 | J20: 1 | K20: =D20*L20 -> 0 | L20: 0 | M20: =F20*N20 -> 0 | N20: 0 | O20: =H20*P20 -> 0 | P20: 0 | Q20: =J20*R20 -> 0 | R20: 0 | S20: =E20+G20+I20+K20+M20+O20+Q20 -> 179.8 | T20: =S20/D20 -> 1 | U20: =E20+G20+I20+K20+M20 -> 179.8 | V20: =U20/D20 -> 1
C22: Total M2 de Fachada | D22: =SUM(D19:D20) -> 180.8 | E22: =SUM(E19:E20) -> 0 | F22: =E22/$D$22 -> 0 | G22: =SUM(G19:G20) -> 0 | H22: =G22/$D$22 -> 0 | I22: =SUM(I19:I20) -> 179.8 | J22: =I22/$D$22 -> 0.99446903 | K22: =SUM(K19:K20) -> 0 | L22: =K22/$D$22 -> 0 | M22: =SUM(M19:M20) -> 0 | N22: =M22/$D$22 -> 0 | O22: =SUM(O19:O20) -> 0 | P22: =O22/$D$22 -> 0 | Q22: =SUM(Q19:Q20) -> 0 | R22: =Q22/$D$22 -> 0 | S22: =SUM(S19:S20) -> 179.8 | T22: =S22/D22 -> 0.99446903 | U22: =SUM(U19:U20) -> 179.8 | V22: =U22/D22 -> 0.99446903
S23: =D22-S22 -> 1 | T23: =S23/D22 -> 0.0055309735
A25: D | B25: 8 | C25: SELLO PERIMETRAL | D25: 115.2 | E25: =D25*F25 -> 92.16 | F25: 0.8 | G25: =D25*H25 -> 0 | H25: 0 | I25: =D25*J25 -> 0 | J25: 0 | K25: =D25*L25 -> 0 | L25: 0 | M25: =D25*N25 -> 0 | N25: 0 | O25: =P25*D25 -> 0 | P25: 0 | Q25: =R25*D25 -> 0 | R25: 0 | S25: =E25+G25+I25+K25+M25+O25+Q25 -> 92.16 | T25: =S25/D25 -> 0.8 | U25: =E25+G25+I25+K25+M25 -> 92.16 | V25: =U25/D25 -> 0.8
B26: 9 | C26: SELLO PERIMETRAL | D26: 3.6 | E26: =D26*F26 -> 3.6 | F26: 1 | G26: =D26*H26 -> 0 | H26: 0 | I26: =D26*J26 -> 0 | J26: 0 | K26: =D26*L26 -> 0 | L26: 0 | M26: =D26*N26 -> 0 | N26: 0 | O26: =P26*D26 -> 0 | P26: 0 | Q26: =R26*D26 -> 0 | R26: 0 | S26: =E26+G26+I26+K26+M26+O26+Q26 -> 3.6 | T26: =S26/D26 -> 1 | U26: =E26+G26+I26+K26+M26 -> 3.6 | V26: =U26/D26 -> 1
B27: 10 | C27: SELLO PERIMETRAL | D27: 3 | E27: =D27*F27 -> 3 | F27: 1 | G27: =D27*H27 -> 0 | H27: 0 | I27: =D27*J27 -> 0 | J27: 0 | K27: =D27*L27 -> 0 | L27: 0 | M27: =D27*N27 -> 0 | N27: 0 | O27: =P27*D27 -> 0 | P27: 0 | Q27: =R27*D27 -> 0 | R27: 0 | S27: =E27+G27+I27+K27+M27+O27+Q27 -> 3 | T27: =S27/D27 -> 1 | U27: =E27+G27+I27+K27+M27 -> 3 | V27: =U27/D27 -> 1
B28: 11 | C28: SELLO PERIMETRAL | D28: 18 | E28: =D28*F28 -> 0 | F28: 0 | G28: =D28*H28 -> 0 | H28: 0 | I28: =D28*J28 -> 0 | J28: 0 | K28: =D28*L28 -> 0 | L28: 0 | M28: =D28*N28 -> 0 | N28: 0 | O28: =P28*D28 -> 0 | P28: 0 | Q28: =R28*D28 -> 0 | R28: 0 | S28: =E28+G28+I28+K28+M28+O28+Q28 -> 0 | T28: =S28/D28 -> 0 | U28: =E28+G28+I28+K28+M28 -> 0 | V28: =U28/D28 -> 0
B29: 12 | C29: SELLO PERIMETRAL | D29: 18 | E29: =D29*F29 -> 0 | F29: 0 | G29: =D29*H29 -> 0 | H29: 0 | I29: =D29*J29 -> 0 | J29: 0 | K29: =D29*L29 -> 0 | L29: 0 | M29: =D29*N29 -> 0 | N29: 0 | O29: =P29*D29 -> 0 | P29: 0 | Q29: =R29*D29 -> 0 | R29: 0 | S29: =E29+G29+I29+K29+M29+O29+Q29 -> 0 | T29: =S29/D29 -> 0 | U29: =E29+G29+I29+K29+M29 -> 0 | V29: =U29/D29 -> 0
C31: Total M2 de Fachada | D31: =SUM(D25:D29) -> 157.8 | E31: =SUM(E25:E29) -> 98.76 | F31: =E31/$D$31 -> 0.62585551 | G31: =SUM(G25:G29) -> 0 | H31: =G31/$D$31 -> 0 | I31: =SUM(I25:I29) -> 0 | J31: =I31/$D$31 -> 0 | K31: =SUM(K25:K29) -> 0 | L31: =K31/$D$31 -> 0 | M31: =SUM(M25:M29) -> 0 | N31: =M31/$D$31 -> 0 | O31: =SUM(O25:O29) -> 0 | P31: =O31/$D$31 -> 0 | Q31: =SUM(Q25:Q29) -> 0 | R31: =Q31/$D$31 -> 0 | S31: =SUM(S25:S29) -> 98.76 | T31: =S31/$D$31 -> 0.62585551 | U31: =SUM(U25:U29) -> 98.76 | V31: =U31/$D$31 -> 0.62585551
S32: =D31-S31 -> 59.04 | T32: =S32/D31 -> 0.37414449
A34: E | B34: 13 | C34: SELLO PERIMETRAL | D34: 158.02 | E34: =D34*F34 -> 158.02 | F34: 1 | G34: =H34*D34 -> 0 | H34: 0 | I34: =D34*J34 -> 0 | J34: 0 | K34: =D34*L34 -> 0 | L34: 0 | M34: =D34*N34 -> 0 | N34: 0 | O34: =P34*D34 -> 0 | P34: 0 | Q34: =R34*D34 -> 0 | R34: 0 | S34: =E34+G34+I34+K34+M34+O34+Q34 -> 158.02 | T34: =S34/D34 -> 1 | U34: =E34+G34+I34+K34+M34 -> 158.02 | V34: =U34/D34 -> 1
C36: Total M2 de Fachada | D36: =SUM(D34:D34) -> 158.02 | E36: =SUM(E34:E34) -> 158.02 | F36: =E36/$D$36 -> 1 | G36: =SUM(G34:G34) -> 0 | H36: =G36/$D$36 -> 0 | I36: =SUM(I34:I34) -> 0 | J36: =I36/$D$36 -> 0 | K36: =SUM(K34:K34) -> 0 | L36: =K36/$D$36 -> 0 | M36: =SUM(M34:M34) -> 0 | N36: =M36/$D$36 -> 0 | O36: =SUM(O34:O34) -> 0 | P36: =O36/$D$36 -> 0 | Q36: =SUM(Q34:Q34) -> 0 | R36: =Q36/$D$36 -> 0 | S36: =SUM(S34:S34) -> 158.02 | T36: =S36/D36 -> 1 | U36: =SUM(U34:U34) -> 158.02 | V36: =U36/D36 -> 1
A39: F | B39: 14 | C39: SELLO PERIMETRAL | D39: =196/2 -> 98 | E39: =D39*F39 -> 0 | F39: 0 | G39: =H39*D39 -> 49 | H39: 0.5 | I39: =D39*J39 -> 49 | J39: 0.5 | K39: =D39*L39 -> 0 | L39: 0 | M39: =F39*N39 -> 0 | N39: 0 | O39: =P39*D39 -> 0 | P39: 0 | Q39: =R39*D39 -> 0 | R39: 0 | S39: =E39+G39+I39+K39+M39+O39+Q39 -> 98 | T39: =S39/D39 -> 1 | U39: =E39+G39+I39+K39+M39 -> 98 | V39: =U39/D39 -> 1
B40: 15 | C40: SELLO PERIMETRAL | D40: 98 | E40: =D40*F40 -> 0 | F40: 0 | G40: =H40*D40 -> 49 | H40: 0.5 | I40: =D40*J40 -> 49 | J40: 0.5 | K40: =D40*L40 -> 0 | L40: 0 | M40: =F40*N40 -> 0 | N40: 0 | O40: =H40*P40 -> 0 | P40: 0 | Q40: =J40*R40 -> 0 | R40: 0 | S40: =E40+G40+I40+K40+M40+O40+Q40 -> 98 | T40: =S40/D40 -> 1 | U40: =E40+G40+I40+K40+M40 -> 98 | V40: =U40/D40 -> 1
C42: Total M2 de Fachada | D42: =SUM(D39:D40) -> 196 | E42: =SUM(E39:E40) -> 0 | F42: =E42/$D$42 -> 0 | G42: =SUM(G39:G40) -> 98 | H42: =G42/$D$42 -> 0.5 | I42: =SUM(I39:I40) -> 98 | J42: =I42/$D$42 -> 0.5 | K42: =SUM(K39:K40) -> 0 | L42: =K42/$D$42 -> 0 | M42: =SUM(M39:M40) -> 0 | N42: =M42/$D$42 -> 0 | O42: =SUM(O39:O40) -> 0 | P42: =O42/$D$42 -> 0 | Q42: =SUM(Q39:Q40) -> 0 | R42: =Q42/$D$42 -> 0 | S42: =SUM(S39:S40) -> 196 | T42: =S42/D42 -> 1 | U42: =SUM(U39:U40) -> 196 | V42: =U42/D42 -> 1
A44: PUNTO FIJO | B44: 1 IZQUIERDA | C44: SELLO PERIMETRAL | D44: 1 | E44: =D44*F44 -> 0 | F44: 0 | G44: =D44*H44 -> 0 | H44: 0 | I44: =D44*J44 -> 0 | J44: 0 | K44: =D44*L44 -> 0 | L44: 0 | M44: =F44*N44 -> 0 | N44: 0 | O44: =P44*D44 -> 0 | P44: 0 | Q44: =R44*D44 -> 0 | R44: 0 | S44: =E44+G44+I44+K44+M44+O44+Q44 -> 0 | T44: =S44/D44 -> 0 | U44: =E44+G44+I44+K44+M44 -> 0 | V44: =U44/D44 -> 0
B45: CARACOL | C45: SELLO PERIMETRAL | D45: 1 | E45: =D45*F45 -> 0 | F45: 0 | G45: =D45*H45 -> 0 | H45: 0 | I45: =D45*J45 -> 0 | J45: 0 | K45: =D45*L45 -> 0 | L45: 0 | M45: =F45*N45 -> 0 | N45: 0 | O45: =H45*P45 -> 0 | P45: 0 | Q45: =J45*R45 -> 0 | R45: 0 | S45: =E45+G45+I45+K45+M45+O45+Q45 -> 0 | T45: =S45/D45 -> 0 | U45: =E45+G45+I45+K45+M45 -> 0 | V45: =U45/D45 -> 0
B46: 1 DERECHA | C46: SELLO PERIMETRAL | D46: 1 | E46: =D46*F46 -> 0 | F46: 0 | G46: =D46*H46 -> 0 | H46: 0 | I46: =D46*J46 -> 0 | J46: 0 | K46: =D46*L46 -> 0 | L46: 0 | M46: =F46*N46 -> 0 | N46: 0 | O46: =H46*P46 -> 0 | P46: 0 | Q46: =J46*R46 -> 0 | R46: 0 | S46: =E46+G46+I46+K46+M46+O46+Q46 -> 0 | T46: =S46/D46 -> 0 | U46: =E46+G46+I46+K46+M46 -> 0 | V46: =U46/D46 -> 0
C48: Total M2 de Fachada | D48: =SUM(D44:D46) -> 3 | E48: =SUM(E44:E46) -> 0 | F48: =E48/$D$48 -> 0 | G48: =SUM(G44:G46) -> 0 | H48: =G48/$D$48 -> 0 | I48: =SUM(I44:I46) -> 0 | J48: =I48/$D$48 -> 0 | K48: =SUM(K44:K46) -> 0 | L48: =K48/$D$48 -> 0 | M48: =SUM(M44:M46) -> 0 | N48: =M48/$D$48 -> 0 | O48: =SUM(O44:O46) -> 0 | P48: =O48/$D$48 -> 0 | Q48: =SUM(Q44:Q46) -> 0 | R48: =Q48/$D$48 -> 0 | S48: =SUM(S44:S46) -> 0 | T48: =S48/D48 -> 0 | U48: =SUM(U44:U46) -> 0 | V48: =U48/D48 -> 0
C50: Total M2 de Fachada General | D50: =D11+D16+D22+D31+D36+D42+D48 -> 953.02 | K50: Total de M2 Ejecutados | S50: =S11+S16+S22+S31+S36+S42+S48 -> 889.98 | T50: =S50/D50 -> 0.93385239 | U50: =U11+U16+U22+U31 -> 490.76 | V50: =U50/D50 -> 0.51495247
S51: =D50-S50 -> 63.04 | T51: =S51/D50 -> 0.066147615
T53: 0.59
T54: 0.41

Sheet Sicoplast
A1: CEDROS - GRANIPLAST DE FACHADA
E2: ENE 15 - 17 | G2: ENE 19 - 24 | I2: ENE 26 - 31 | K2: FEB 02-07 | M2: FEB 09-14 | O2: FEB 16 - 21 | Q2: FEB 23 - 28
A3: Fachada | B3: Sección | C3: Descripción | D3: M2 | E3: Semana 01 | G3: Semana 02 | I3: Semana 03 | K3: Semana 04 | M3: Semana 05 | O3: Semana 06 | Q3: Semana 07 | S3: Total Ejecutado | U3: Total Ejecutado Acta 01
E4: M2 | F4: % | G4: M2 | H4: % | I4: M2 | J4: % | K4: M2 | L4: % | M4: M2 | N4: % | O4: M2 | P4: % | Q4: M2 | R4: % | S4: M2 | T4: % | U4: M2 | V4: %
A5: A | B5: 1 | C5: Graniplast fachada | D5: 2.98 | E5: =D5*F5 -> 0 | F5: 0 | G5: =D5*H5 -> 0 | H5: 0 | I5: =D5*J5 -> 0 | J5: 0 | K5: =D5*L5 -> 0 | L5: 0 | M5: =N5*D5 -> 0 | N5: 0 | O5: =P5*D5 -> 1.2814 | P5: 0.43 | Q5: =R5*D5 -> 0 | R5: 0 | S5: =E5+G5+I5+K5+M5+O5+Q5 -> 1.2814 | T5: =S5/D5 -> 0.43 | U5: =E5+G5+I5+K5+M5 -> 0 | V5: =U5/D5 -> 0
B6: 2 | C6: Graniplast fachada | D6: 2.98 | E6: =D6*F6 -> 0 | F6: 0 | G6: =D6*H6 -> 0 | H6: 0 | I6: =D6*J6 -> 0 | J6: 0 | K6: =D6*L6 -> 0 | L6: 0 | M6: =N6*D6 -> 2.533 | N6: 0.85 | O6: =P6*D6 -> 0.447 | P6: 0.15 | Q6: =R6*D6 -> 0 | R6: 0 | S6: =E6+G6+I6+K6+M6+O6+Q6 -> 2.98 | T6: =S6/D6 -> 1 | U6: =E6+G6+I6+K6+M6 -> 2.533 | V6: =U6/D6 -> 0.85
B7: 3 | C7: Graniplast fachada | D7: 2.98 | E7: =D7*F7 -> 0 | F7: 0 | G7: =D7*H7 -> 0 | H7: 0 | I7: =D7*J7 -> 0 | J7: 0 | K7: =D7*L7 -> 0 | L7: 0 | M7: =N7*D7 -> 2.98 | N7: 1 | O7: =P7*D7 -> 0 | P7: 0 | Q7: =R7*D7 -> 0 | R7: 0 | S7: =E7+G7+I7+K7+M7+O7+Q7 -> 2.98 | T7: =S7/D7 -> 1 | U7: =E7+G7+I7+K7+M7 -> 2.98 | V7: =U7/D7 -> 1
B8: 4 | C8: Graniplast fachada | D8: 2.98 | E8: =D8*F8 -> 0 | F8: 0 | G8: =D8*H8 -> 0 | H8: 0 | I8: =D8*J8 -> 0 | J8: 0 | K8: =D8*L8 -> 0 | L8: 0 | M8: =N8*D8 -> 1.788 | N8: 0.6 | O8: =P8*D8 -> 1.192 | P8: 0.4 | Q8: =R8*D8 -> 0 | R8: 0 | S8: =E8+G8+I8+K8+M8+O8+Q8 -> 2.98 | T8: =S8/D8 -> 1 | U8: =E8+G8+I8+K8+M8 -> 1.788 | V8: =U8/D8 -> 0.6
B9: 5 | C9: Graniplast fachada | D9: 2.98 | E9: =D9*F9 -> 0 | F9: 0 | G9: =D9*H9 -> 0 | H9: 0 | I9: =D9*J9 -> 0 | J9: 0 | K9: =D9*L9 -> 0 | L9: 0 | M9: =N9*D9 -> 2.533 | N9: =0.85 -> 0.85 | O9: =P9*D9 -> 0.447 | P9: 0.15 | Q9: =R9*D9 -> 0 | R9: 0 | S9: =E9+G9+I9+K9+M9+O9+Q9 -> 2.98 | T9: =S9/D9 -> 1 | U9: =E9+G9+I9+K9+M9 -> 2.533 | V9: =U9/D9 -> 0.85
C11: Total M2 de Fachada | D11: =SUM(D5:D9) -> 14.9 | E11: =SUM(E5:E9) -> 0 | F11: =E11/$D$11 -> 0 | G11: =SUM(G5:G9) -> 0 | H11: =G11/$D$11 -> 0 | I11: =SUM(I5:I9) -> 0 | J11: =I11/$D$11 -> 0 | K11: =SUM(K5:K9) -> 0 | L11: =K11/$D$11 -> 0 | M11: =SUM(M5:M9) -> 9.834 | N11: =M11/$D$11 -> 0.66 | O11: =SUM(O5:O9) -> 3.3674 | P11: =O11/$D$11 -> 0.226 | Q11: =SUM(Q5:Q9) -> 0 | R11: =Q11/$D$11 -> 0 | S11: =SUM(S5:S9) -> 13.2014 | T11: =S11/D11 -> 0.886 | U11: =SUM(U5:U9) -> 9.834 | V11: =U11/$D$11 -> 0.66
S12: =D11-S11 -> 1.6986 | T12: =S12/D11 -> 0.114
A14: B | B14: 6 | C14: Pintura de fachada | D14: 14.91 | E14: =D14*F14 -> 0 | F14: 0 | G14: =D14*H14 -> 0 | H14: 0 | I14: =D14*J14 -> 0 | J14: 0 | K14: =D14*L14 -> 0 | L14: 0 | M14: =D14*N14 -> 0 | N14: 0 | O14: =P14*D14 -> 0 | P14: 0 | Q14: =R14*D14 -> 0 | R14: 0 | S14: =E14+G14+I14+K14+M14+O14+Q14 -> 0 | T14: =S14/D14 -> 0 | U14: =E14+G14+I14+K14+M14 -> 0 | V14: =U14/D14 -> 0
C16: Total M2 de Fachada | D16: =SUM(D14:D14) -> 14.91 | E16: =SUM(E14:E14) -> 0 | F16: =E16/$D$16 -> 0 | G16: =SUM(G14:G14) -> 0 | H16: =G16/$D$16 -> 0 | I16: =SUM(I14:I14) -> 0 | J16: =I16/$D$16 -> 0 | K16: =SUM(K14:K14) -> 0 | L16: =K16/$D$16 -> 0 | M16: =SUM(M14:M14) -> 0 | N16: =M16/$D$16 -> 0 | O16: =SUM(O14:O14) -> 0 | P16: =O16/$D$16 -> 0 | Q16: =SUM(Q14:Q14) -> 0 | R16: =Q16/$D$16 -> 0 | S16: =SUM(S14:S14) -> 0 | T16: =S16/$D$16 -> 0 | U16: =SUM(U14:U14) -> 0 | V16: =U16/D16 -> 0
S17: =D16-S16 -> 14.91 | T17: =S17/D16 -> 1
A19: C | B19: 1 | C19: Pintura de fachada | D19: 7.45 | E19: =D19*F19 -> 0 | F19: 0 | G19: =D19*H19 -> 0 | H19: 0 | I19: =D19*J19 -> 0 | J19: 0 | K19: =D19*L19 -> 0 | L19: 0 | M19: =F19*N19 -> 0 | N19: 0 | O19: =P19*D19 -> 0 | P19: 0 | Q19: =R19*D19 -> 0 | R19: 0 | S19: =E19+G19+I19+K19+M19+O19+Q19 -> 0 | T19: =S19/D19 -> 0 | U19: =E19+G19+I19+K19+M19 -> 0 | V19: =U19/D19 -> 0
B20: 7 | C20: Pintura de fachada | D20: 7.45 | E20: =D20*F20 -> 0 | F20: 0 | G20: =D20*H20 -> 0 | H20: 0 | I20: =D20*J20 -> 0 | J20: 0 | K20: =D20*L20 -> 0 | L20: 0 | M20: =F20*N20 -> 0 | N20: 0 | O20: =H20*P20 -> 0 | P20: 0 | Q20: =J20*R20 -> 0 | R20: 0 | S20: =E20+G20+I20+K20+M20+O20+Q20 -> 0 | T20: =S20/D20 -> 0 | U20: =E20+G20+I20+K20+M20 -> 0 | V20: =U20/D20 -> 0
C22: Total M2 de Fachada | D22: =SUM(D19:D20) -> 14.9 | E22: =SUM(E19:E20) -> 0 | F22: =E22/$D$22 -> 0 | G22: =SUM(G19:G20) -> 0 | H22: =G22/$D$22 -> 0 | I22: =SUM(I19:I20) -> 0 | J22: =I22/$D$22 -> 0 | K22: =SUM(K19:K20) -> 0 | L22: =K22/$D$22 -> 0 | M22: =SUM(M19:M20) -> 0 | N22: =M22/$D$22 -> 0 | O22: =SUM(O19:O20) -> 0 | P22: =O22/$D$22 -> 0 | Q22: =SUM(Q19:Q20) -> 0 | R22: =Q22/$D$22 -> 0 | S22: =SUM(S19:S20) -> 0 | T22: =S22/D22 -> 0 | U22: =SUM(U19:U20) -> 0 | V22: =U22/D22 -> 0
S23: =D22-S22 -> 14.9 | T23: =S23/D22 -> 1
A25: D | B25: 8 | C25: Pintura de fachada | D25: 2.98 | E25: =D25*F25 -> 0 | F25: 0 | G25: =D25*H25 -> 0 | H25: 0 | I25: =D25*J25 -> 0 | J25: 0 | K25: =D25*L25 -> 0 | L25: 0 | M25: =D25*N25 -> 0 | N25: 0 | O25: =P25*D25 -> 0 | P25: 0 | Q25: =R25*D25 -> 0 | R25: 0 | S25: =E25+G25+I25+K25+M25+O25+Q25 -> 0 | T25: =S25/D25 -> 0 | U25: =E25+G25+I25+K25+M25 -> 0 | V25: =U25/D25 -> 0
B26: 9 | C26: Pintura de fachada | D26: 2.98 | E26: =D26*F26 -> 0 | F26: 0 | G26: =D26*H26 -> 0 | H26: 0 | I26: =D26*J26 -> 0 | J26: 0 | K26: =D26*L26 -> 0 | L26: 0 | M26: =D26*N26 -> 0 | N26: 0 | O26: =P26*D26 -> 0 | P26: 0 | Q26: =R26*D26 -> 0 | R26: 0 | S26: =E26+G26+I26+K26+M26+O26+Q26 -> 0 | T26: =S26/D26 -> 0 | U26: =E26+G26+I26+K26+M26 -> 0 | V26: =U26/D26 -> 0
B27: 10 | C27: Pintura de fachada | D27: 2.98 | E27: =D27*F27 -> 2.682 | F27: 0.9 | G27: =D27*H27 -> 0 | H27: 0 | I27: =D27*J27 -> 0 | J27: 0 | K27: =D27*L27 -> 0 | L27: 0 | M27: =D27*N27 -> 0 | N27: 0 | O27: =P27*D27 -> 0 | P27: 0 | Q27: =R27*D27 -> 0 | R27: 0 | S27: =E27+G27+I27+K27+M27+O27+Q27 -> 2.682 | T27: =S27/D27 -> 0.9 | U27: =E27+G27+I27+K27+M27 -> 2.682 | V27: =U27/D27 -> 0.9
B28: 11 | C28: Pintura de fachada | D28: 2.98 | E28: =D28*F28 -> 1.192 | F28: 0.4 | G28: =D28*H28 -> 0 | H28: 0 | I28: =D28*J28 -> 0 | J28: 0 | K28: =D28*L28 -> 0 | L28: 0 | M28: =D28*N28 -> 0 | N28: 0 | O28: =P28*D28 -> 0 | P28: 0 | Q28: =R28*D28 -> 0 | R28: 0 | S28: =E28+G28+I28+K28+M28+O28+Q28 -> 1.192 | T28: =S28/D28 -> 0.4 | U28: =E28+G28+I28+K28+M28 -> 1.192 | V28: =U28/D28 -> 0.4
B29: 12 | C29: Pintura de fachada | D29: 2.98 | E29: =D29*F29 -> 0 | F29: 0 | G29: =D29*H29 -> 0 | H29: 0 | I29: =D29*J29 -> 0 | J29: 0 | K29: =D29*L29 -> 0 | L29: 0 | M29: =D29*N29 -> 0 | N29: 0 | O29: =P29*D29 -> 0 | P29: 0 | Q29: =R29*D29 -> 0 | R29: 0 | S29: =E29+G29+I29+K29+M29+O29+Q29 -> 0 | T29: =S29/D29 -> 0 | U29: =E29+G29+I29+K29+M29 -> 0 | V29: =U29/D29 -> 0
C31: Total M2 de Fachada | D31: =SUM(D25:D29) -> 14.9 | E31: =SUM(E25:E29) -> 3.874 | F31: =E31/$D$31 -> 0.26 | G31: =SUM(G25:G29) -> 0 | H31: =G31/$D$31 -> 0 | I31: =SUM(I25:I29) -> 0 | J31: =I31/$D$31 -> 0 | K31: =SUM(K25:K29) -> 0 | L31: =K31/$D$31 -> 0 | M31: =SUM(M25:M29) -> 0 | N31: =M31/$D$31 -> 0 | O31: =SUM(O25:O29) -> 0 | P31: =O31/$D$31 -> 0 | Q31: =SUM(Q25:Q29) -> 0 | R31: =Q31/$D$31 -> 0 | S31: =SUM(S25:S29) -> 3.874 | T31: =S31/$D$31 -> 0.26 | U31: =SUM(U25:U29) -> 3.874 | V31: =U31/$D$31 -> 0.26
S32: =D31-S31 -> 11.026 | T32: =S32/D31 -> 0.74
A34: E | B34: 13 | C34: Pintura de fachada | D34: 14.9 | E34: =D34*F34 -> 9.834 | F34: 0.66 | G34: =H34*D34 -> 0 | H34: 0 | I34: =D34*J34 -> 0 | J34: 0 | K34: =D34*L34 -> 0 | L34: 0 | M34: =D34*N34 -> 0 | N34: 0 | O34: =P34*D34 -> 0 | P34: 0 | Q34: =R34*D34 -> 0.894 | R34: 0.06 | S34: =E34+G34+I34+K34+M34+O34+Q34 -> 10.728 | T34: =S34/D34 -> 0.72 | U34: =E34+G34+I34+K34+M34 -> 9.834 | V34: =U34/D34 -> 0.66
C36: Total M2 de Fachada | D36: =SUM(D34:D34) -> 14.9 | E36: =SUM(E34:E34) -> 9.834 | F36: =E36/$D$36 -> 0.66 | G36: =SUM(G34:G34) -> 0 | H36: =G36/$D$36 -> 0 | I36: =SUM(I34:I34) -> 0 | J36: =I36/$D$36 -> 0 | K36: =SUM(K34:K34) -> 0 | L36: =K36/$D$36 -> 0 | M36: =SUM(M34:M34) -> 0 | N36: =M36/$D$36 -> 0 | O36: =SUM(O34:O34) -> 0 | P36: =O36/$D$36 -> 0 | Q36: =SUM(Q34:Q34) -> 0.894 | R36: =Q36/$D$36 -> 0.06 | S36: =SUM(S34:S34) -> 10.728 | T36: =S36/D36 -> 0.72 | U36: =SUM(U34:U34) -> 9.834 | V36: =U36/D36 -> 0.66
A39: F | B39: 14 | C39: Pintura de fachada | D39: 7.45 | E39: =D39*F39 -> 0 | F39: 0 | G39: =H39*D39 -> 0 | H39: 0 | I39: =D39*J39 -> 0 | J39: 0 | K39: =D39*L39 -> 0 | L39: 0 | M39: =F39*N39 -> 0 | N39: 0 | O39: =P39*D39 -> 0 | P39: 0 | Q39: =R39*D39 -> 1.341 | R39: 0.18 | S39: =E39+G39+I39+K39+M39+O39+Q39 -> 1.341 | T39: =S39/D39 -> 0.18 | U39: =E39+G39+I39+K39+M39 -> 0 | V39: =U39/D39 -> 0
B40: 15 | C40: Pintura de fachada | D40: 7.45 | E40: =D40*F40 -> 0 | F40: 0 | G40: =H40*D40 -> 0 | H40: 0 | I40: =D40*J40 -> 0 | J40: 0 | K40: =D40*L40 -> 0 | L40: 0 | M40: =F40*N40 -> 0 | N40: 0 | O40: =H40*P40 -> 0 | P40: 0 | Q40: =J40*R40 -> 0 | R40: 0 | S40: =E40+G40+I40+K40+M40+O40+Q40 -> 0 | T40: =S40/D40 -> 0 | U40: =E40+G40+I40+K40+M40 -> 0 | V40: =U40/D40 -> 0
C42: Total M2 de Fachada | D42: =SUM(D39:D40) -> 14.9 | E42: =SUM(E39:E40) -> 0 | F42: =E42/$D$42 -> 0 | G42: =SUM(G39:G40) -> 0 | H42: =G42/$D$42 -> 0 | I42: =SUM(I39:I40) -> 0 | J42: =I42/$D$42 -> 0 | K42: =SUM(K39:K40) -> 0 | L42: =K42/$D$42 -> 0 | M42: =SUM(M39:M40) -> 0 | N42: =M42/$D$42 -> 0 | O42: =SUM(O39:O40) -> 0 | P42: =O42/$D$42 -> 0 | Q42: =SUM(Q39:Q40) -> 1.341 | R42: =Q42/$D$42 -> 0.09 | S42: =SUM(S39:S40) -> 1.341 | T42: =S42/D42 -> 0.09 | U42: =SUM(U39:U40) -> 0 | V42: =U42/D42 -> 0
A44: PUNTO FIJO | B44: 1 IZQUIERDA | C44: Graniplast fachada | D44: 4.97 | E44: =D44*F44 -> 0 | F44: 0 | G44: =D44*H44 -> 0 | H44: 0 | I44: =D44*J44 -> 0 | J44: 0 | K44: =D44*L44 -> 0 | L44: 0 | M44: =D44*N44 -> 0 | N44: 0 | O44: =P44*D44 -> 0 | P44: 0 | Q44: =R44*D44 -> 0 | R44: 0 | S44: =E44+G44+I44+K44+M44+O44+Q44 -> 0 | T44: =S44/D44 -> 0 | U44: =E44+G44+I44+K44+M44 -> 0 | V44: =U44/D44 -> 0
B45: CARACOL | C45: Graniplast fachada | D45: 4.97 | E45: =D45*F45 -> 0 | F45: 0 | G45: =D45*H45 -> 0 | H45: 0 | I45: =D45*J45 -> 0 | J45: 0 | K45: =D45*L45 -> 0.497 | L45: 0.1 | M45: =D45*N45 -> 0.2485 | N45: 0.05 | O45: =H45*P45 -> 0 | P45: 0 | Q45: =R45*D45 -> 2.982 | R45: 0.6 | S45: =E45+G45+I45+K45+M45+O45+Q45 -> 3.7275 | T45: =S45/D45 -> 0.75 | U45: =E45+G45+I45+K45+M45 -> 0.7455 | V45: =U45/D45 -> 0.15
B46: 1 DERECHA | C46: Graniplast fachada | D46: 4.97 | E46: =D46*F46 -> 0 | F46: 0 | G46: =D46*H46 -> 0 | H46: 0 | I46: =D46*J46 -> 0 | J46: 0 | K46: =D46*L46 -> 0 | L46: 0 | M46: =D46*N46 -> 0 | N46: 0 | O46: =H46*P46 -> 0 | P46: 0 | Q46: =R46*D46 -> 0 | R46: 0 | S46: =E46+G46+I46+K46+M46+O46+Q46 -> 0 | T46: =S46/D46 -> 0 | U46: =E46+G46+I46+K46+M46 -> 0 | V46: =U46/D46 -> 0
C48: Total M2 de Fachada | D48: =SUM(D44:D46) -> 14.91 | E48: =SUM(E44:E46) -> 0 | F48: =E48/$D$48 -> 0 | G48: =SUM(G44:G46) -> 0 | H48: =G48/$D$48 -> 0 | I48: =SUM(I44:I46) -> 0 | J48: =I48/$D$48 -> 0 | K48: =SUM(K44:K46) -> 0.497 | L48: =K48/$D$48 -> 0.033333333 | M48: =SUM(M44:M46) -> 0.2485 | N48: =M48/$D$48 -> 0.016666667 | O48: =SUM(O44:O46) -> 0 | P48: =O48/$D$48 -> 0 | Q48: =SUM(Q44:Q46) -> 2.982 | R48: =Q48/$D$48 -> 0.2 | S48: =SUM(S44:S46) -> 3.7275 | T48: =S48/D48 -> 0.25 | U48: =SUM(U44:U46) -> 0.7455 | V48: =U48/D48 -> 0.05
C50: Total M2 de Fachada General | D50: =D11+D16+D22+D31+D36+D42+D48 -> 104.32 | K50: Total de M2 Ejecutados | S50: =S11+S16+S22+S31+S36+S42+S48 -> 32.8719 | T50: =S50/D50 -> 0.3151064 | U50: =U11+U16+U22+U31 -> 13.708 | V50: =U50/D50 -> 0.13140337
S51: =D50-S50 -> 71.4481 | T51: =S51/D50 -> 0.6848936
T53: 0.59
T54: 0.41

Sheet Pintura
A1: CEDROS - PINTURA DE FACHADA
E2: ENE 15 - 17 | G2: ENE 19 - 24 | I2: ENE 26 - 31 | K2: FEB 02-07 | M2: FEB 09-14 | O2: FEB 16 - 21 | Q2: FEB 23 - 28
A3: Fachada | B3: Sección | C3: Descripción | D3: M2 | E3: Semana 01 | G3: Semana 02 | I3: Semana 03 | K3: Semana 04 | M3: Semana 05 | O3: Semana 06 | Q3: Semana 07 | S3: Total Ejecutado | U3: Total Ejecutado Acta 01
E4: M2 | F4: % | G4: M2 | H4: % | I4: M2 | J4: % | K4: M2 | L4: % | M4: M2 | N4: % | O4: M2 | P4: % | Q4: M2 | R4: % | S4: M2 | T4: % | U4: M2 | V4: %
A5: A | B5: 1 | C5: Pintura de fachada | D5: 69.21 | E5: =D5*F5 -> 0 | F5: 0 | G5: =D5*H5 -> 0 | H5: 0 | I5: =D5*J5 -> 0 | J5: 0 | K5: =D5*L5 -> 0 | L5: 0 | M5: =N5*D5 -> 0 | N5: 0 | O5: =P5*D5 -> 0 | P5: 0 | Q5: =R5*D5 -> 69.21 | R5: 1 | S5: =E5+G5+I5+K5+M5+O5+Q5 -> 69.21 | T5: =S5/D5 -> 1 | U5: =E5+G5+I5+K5+M5 -> 0 | V5: =U5/D5 -> 0
B6: 2 | C6: Pintura de fachada | D6: 35.17 | E6: =D6*F6 -> 0 | F6: 0 | G6: =D6*H6 -> 0 | H6: 0 | I6: =D6*J6 -> 0 | J6: 0 | K6: =D6*L6 -> 0 | L6: 0 | M6: =N6*D6 -> 0 | N6: 0 | O6: =P6*D6 -> 17.585 | P6: 0.5 | Q6: =R6*D6 -> 17.585 | R6: 0.5 | S6: =E6+G6+I6+K6+M6+O6+Q6 -> 35.17 | T6: =S6/D6 -> 1 | U6: =E6+G6+I6+K6+M6 -> 0 | V6: =U6/D6 -> 0
B7: 3 | C7: Pintura de fachada | D7: 60.86 | E7: =D7*F7 -> 0 | F7: 0 | G7: =D7*H7 -> 0 | H7: 0 | I7: =D7*J7 -> 0 | J7: 0 | K7: =D7*L7 -> 60.86 | L7: 1 | M7: =N7*D7 -> 0 | N7: 0 | O7: =P7*D7 -> 0 | P7: 0 | Q7: =R7*D7 -> 0 | R7: 0 | S7: =E7+G7+I7+K7+M7+O7+Q7 -> 60.86 | T7: =S7/D7 -> 1 | U7: =E7+G7+I7+K7+M7 -> 60.86 | V7: =U7/D7 -> 1
B8: 4 | C8: Pintura de fachada | D8: 35.17 | E8: =D8*F8 -> 0 | F8: 0 | G8: =D8*H8 -> 0 | H8: 0 | I8: =D8*J8 -> 0 | J8: 0 | K8: =D8*L8 -> 0 | L8: 0 | M8: =N8*D8 -> 0 | N8: 0 | O8: =P8*D8 -> 17.585 | P8: 0.5 | Q8: =R8*D8 -> 17.585 | R8: 0.5 | S8: =E8+G8+I8+K8+M8+O8+Q8 -> 35.17 | T8: =S8/D8 -> 1 | U8: =E8+G8+I8+K8+M8 -> 0 | V8: =U8/D8 -> 0
B9: 5 | C9: Pintura de fachada | D9: 69.56 | E9: =D9*F9 -> 0 | F9: 0 | G9: =D9*H9 -> 0 | H9: 0 | I9: =D9*J9 -> 0 | J9: 0 | K9: =D9*L9 -> 0 | L9: 0 | M9: =N9*D9 -> 0 | N9: 0 | O9: =P9*D9 -> 0 | P9: 0 | Q9: =R9*D9 -> 69.56 | R9: 1 | S9: =E9+G9+I9+K9+M9+O9+Q9 -> 69.56 | T9: =S9/D9 -> 1 | U9: =E9+G9+I9+K9+M9 -> 0 | V9: =U9/D9 -> 0
C11: Total M2 de Fachada | D11: =SUM(D5:D9) -> 269.97 | E11: =SUM(E5:E9) -> 0 | F11: =E11/$D$11 -> 0 | G11: =SUM(G5:G9) -> 0 | H11: =G11/$D$11 -> 0 | I11: =SUM(I5:I9) -> 0 | J11: =I11/$D$11 -> 0 | K11: =SUM(K5:K9) -> 60.86 | L11: =K11/$D$11 -> 0.22543246 | M11: =SUM(M5:M9) -> 0 | N11: =M11/$D$11 -> 0 | O11: =SUM(O5:O9) -> 35.17 | P11: =O11/$D$11 -> 0.13027373 | Q11: =SUM(Q5:Q9) -> 173.94 | R11: =Q11/$D$11 -> 0.64429381 | S11: =SUM(S5:S9) -> 269.97 | T11: =S11/D11 -> 1 | U11: =SUM(U5:U9) -> 60.86 | V11: =U11/$D$11 -> 0.22543246
S12: =D11-S11 -> 0 | T12: =S12/D11 -> 0
A14: B | B14: 6 | C14: Pintura de fachada | D14: 96.86 | E14: =D14*F14 -> 0 | F14: 0 | G14: =D14*H14 -> 0 | H14: 0 | I14: =D14*J14 -> 0 | J14: 0 | K14: =D14*L14 -> 48.43 | L14: 0.5 | M14: =D14*N14 -> 48.43 | N14: 0.5 | O14: =P14*D14 -> 0 | P14: 0 | Q14: =R14*D14 -> 36.03192 | R14: 0.372 | S14: =E14+G14+I14+K14+M14+O14+Q14 -> 132.89192 | T14: =S14/D14 -> 1.372 | U14: =E14+G14+I14+K14+M14 -> 96.86 | V14: =U14/D14 -> 1
C16: Total M2 de Fachada | D16: =SUM(D14:D14) -> 96.86 | E16: =SUM(E14:E14) -> 0 | F16: =E16/$D$16 -> 0 | G16: =SUM(G14:G14) -> 0 | H16: =G16/$D$16 -> 0 | I16: =SUM(I14:I14) -> 0 | J16: =I16/$D$16 -> 0 | K16: =SUM(K14:K14) -> 48.43 | L16: =K16/$D$16 -> 0.5 | M16: =SUM(M14:M14) -> 48.43 | N16: =M16/$D$16 -> 0.5 | O16: =SUM(O14:O14) -> 0 | P16: =O16/$D$16 -> 0 | Q16: =SUM(Q14:Q14) -> 36.03192 | R16: =Q16/$D$16 -> 0.372 | S16: =SUM(S14:S14) -> 132.89192 | T16: =S16/$D$16 -> 1.372 | U16: =SUM(U14:U14) -> 96.86 | V16: =U16/D16 -> 1
S17: =D16-S16 -> -36.03192 | T17: =S17/D16 -> -0.372
A19: C | B19: 1 | C19: Pintura de fachada | D19: 76.22 | E19: =D19*F19 -> 0 | F19: 0 | G19: =D19*H19 -> 0 | H19: 0 | I19: =D19*J19 -> 0 | J19: 0 | K19: =D19*L19 -> 76.22 | L19: 1 | M19: =F19*N19 -> 0 | N19: 0 | O19: =P19*D19 -> 0 | P19: 0 | Q19: =R19*D19 -> 0 | R19: 0 | S19: =E19+G19+I19+K19+M19+O19+Q19 -> 76.22 | T19: =S19/D19 -> 1 | U19: =E19+G19+I19+K19+M19 -> 76.22 | V19: =U19/D19 -> 1
B20: 7 | C20: Pintura de fachada | D20: 76.36 | E20: =D20*F20 -> 0 | F20: 0 | G20: =D20*H20 -> 0 | H20: 0 | I20: =D20*J20 -> 0 | J20: 0 | K20: =D20*L20 -> 76.36 | L20: 1 | M20: =F20*N20 -> 0 | N20: 0 | O20: =H20*P20 -> 0 | P20: 0 | Q20: =J20*R20 -> 0 | R20: 0 | S20: =E20+G20+I20+K20+M20+O20+Q20 -> 76.36 | T20: =S20/D20 -> 1 | U20: =E20+G20+I20+K20+M20 -> 76.36 | V20: =U20/D20 -> 1
C22: Total M2 de Fachada | D22: =SUM(D19:D20) -> 152.58 | E22: =SUM(E19:E20) -> 0 | F22: =E22/$D$22 -> 0 | G22: =SUM(G19:G20) -> 0 | H22: =G22/$D$22 -> 0 | I22: =SUM(I19:I20) -> 0 | J22: =I22/$D$22 -> 0 | K22: =SUM(K19:K20) -> 152.58 | L22: =K22/$D$22 -> 1 | M22: =SUM(M19:M20) -> 0 | N22: =M22/$D$22 -> 0 | O22: =SUM(O19:O20) -> 0 | P22: =O22/$D$22 -> 0 | Q22: =SUM(Q19:Q20) -> 0 | R22: =Q22/$D$22 -> 0 | S22: =SUM(S19:S20) -> 152.58 | T22: =S22/D22 -> 1 | U22: =SUM(U19:U20) -> 152.58 | V22: =U22/D22 -> 1
S23: =D22-S22 -> 0 | T23: =S23/D22 -> 0
A25: D | B25: 8 | C25: Pintura de fachada | D25: 78.8 | E25: =D25*F25 -> 78.8 | F25: 1 | G25: =D25*H25 -> 0 | H25: 0 | I25: =D25*J25 -> 0 | J25: 0 | K25: =D25*L25 -> 0 | L25: 0 | M25: =D25*N25 -> 0 | N25: 0 | O25: =P25*D25 -> 0 | P25: 0 | Q25: =R25*D25 -> 0 | R25: 0 | S25: =E25+G25+I25+K25+M25+O25+Q25 -> 78.8 | T25: =S25/D25 -> 1 | U25: =E25+G25+I25+K25+M25 -> 78.8 | V25: =U25/D25 -> 1
B26: 9 | C26: Pintura de fachada | D26: 41.71 | E26: =D26*F26 -> 41.71 | F26: 1 | G26: =D26*H26 -> 0 | H26: 0 | I26: =D26*J26 -> 0 | J26: 0 | K26: =D26*L26 -> 0 | L26: 0 | M26: =D26*N26 -> 0 | N26: 0 | O26: =P26*D26 -> 0 | P26: 0 | Q26: =R26*D26 -> 0 | R26: 0 | S26: =E26+G26+I26+K26+M26+O26+Q26 -> 41.71 | T26: =S26/D26 -> 1 | U26: =E26+G26+I26+K26+M26 -> 41.71 | V26: =U26/D26 -> 1
B27: 10 | C27: Pintura de fachada | D27: 70.9 | E27: =D27*F27 -> 70.9 | F27: 1 | G27: =D27*H27 -> 0 | H27: 0 | I27: =D27*J27 -> 0 | J27: 0 | K27: =D27*L27 -> 0 | L27: 0 | M27: =D27*N27 -> 0 | N27: 0 | O27: =P27*D27 -> 0 | P27: 0 | Q27: =R27*D27 -> 0 | R27: 0 | S27: =E27+G27+I27+K27+M27+O27+Q27 -> 70.9 | T27: =S27/D27 -> 1 | U27: =E27+G27+I27+K27+M27 -> 70.9 | V27: =U27/D27 -> 1
B28: 11 | C28: Pintura de fachada | D28: 41.71 | E28: =D28*F28 -> 41.71 | F28: 1 | G28: =D28*H28 -> 0 | H28: 0 | I28: =D28*J28 -> 0 | J28: 0 | K28: =D28*L28 -> 0 | L28: 0 | M28: =D28*N28 -> 0 | N28: 0 | O28: =P28*D28 -> 0 | P28: 0 | Q28: =R28*D28 -> 0 | R28: 0 | S28: =E28+G28+I28+K28+M28+O28+Q28 -> 41.71 | T28: =S28/D28 -> 1 | U28: =E28+G28+I28+K28+M28 -> 41.71 | V28: =U28/D28 -> 1
B29: 12 | C29: Pintura de fachada | D29: 70.85 | E29: =D29*F29 -> 70.85 | F29: 1 | G29: =D29*H29 -> 0 | H29: 0 | I29: =D29*J29 -> 0 | J29: 0 | K29: =D29*L29 -> 0 | L29: 0 | M29: =D29*N29 -> 0 | N29: 0 | O29: =P29*D29 -> 0 | P29: 0 | Q29: =R29*D29 -> 0 | R29: 0 | S29: =E29+G29+I29+K29+M29+O29+Q29 -> 70.85 | T29: =S29/D29 -> 1 | U29: =E29+G29+I29+K29+M29 -> 70.85 | V29: =U29/D29 -> 1
C31: Total M2 de Fachada | D31: =SUM(D25:D29) -> 303.97 | E31: =SUM(E25:E29) -> 303.97 | F31: =E31/$D$31 -> 1 | G31: =SUM(G25:G29) -> 0 | H31: =G31/$D$31 -> 0 | I31: =SUM(I25:I29) -> 0 | J31: =I31/$D$31 -> 0 | K31: =SUM(K25:K29) -> 0 | L31: =K31/$D$31 -> 0 | M31: =SUM(M25:M29) -> 0 | N31: =M31/$D$31 -> 0 | O31: =SUM(O25:O29) -> 0 | P31: =O31/$D$31 -> 0 | Q31: =SUM(Q25:Q29) -> 0 | R31: =Q31/$D$31 -> 0 | S31: =SUM(S25:S29) -> 303.97 | T31: =S31/$D$31 -> 1 | U31: =SUM(U25:U29) -> 303.97 | V31: =U31/$D$31 -> 1
S32: =D31-S31 -> 0 | T32: =S32/D31 -> 0
A34: E | B34: 13 | C34: Pintura de fachada | D34: 91.46 | E34: =D34*F34 -> 0 | F34: 0 | G34: 100 | H34: 0 | I34: =D34*J34 -> 0 | J34: 0 | K34: =D34*L34 -> 0 | L34: 0 | M34: =D34*N34 -> 0 | N34: 0 | O34: =P34*D34 -> 0 | P34: 0 | Q34: =R34*D34 -> 0 | R34: 0 | S34: =E34+G34+I34+K34+M34+O34+Q34 -> 100 | T34: =S34/D34 -> 1.0933742 | U34: =E34+G34+I34+K34+M34 -> 100 | V34: =U34/D34 -> 1.0933742
C36: Total M2 de Fachada | D36: =SUM(D34:D34) -> 91.46 | E36: =SUM(E34:E34) -> 0 | F36: =E36/$D$36 -> 0 | G36: =SUM(G34:G34) -> 100 | H36: =G36/$D$36 -> 1.0933742 | I36: =SUM(I34:I34) -> 0 | J36: =I36/$D$36 -> 0 | K36: =SUM(K34:K34) -> 0 | L36: =K36/$D$36 -> 0 | M36: =SUM(M34:M34) -> 0 | N36: =M36/$D$36 -> 0 | O36: =SUM(O34:O34) -> 0 | P36: =O36/$D$36 -> 0 | Q36: =SUM(Q34:Q34) -> 0 | R36: =Q36/$D$36 -> 0 | S36: =SUM(S34:S34) -> 100 | T36: =S36/D36 -> 1.0933742 | U36: =SUM(U34:U34) -> 100 | V36: =U36/D36 -> 1.0933742
A39: F | B39: 14 | C39: Pintura de fachada | D39: =27.22+27.22 -> 54.44 | E39: =D39*F39 -> 0 | F39: 0 | G39: =H39*D39 -> 27.22 | H39: 0.5 | I39: =D39*J39 -> 27.22 | J39: 0.5 | K39: =D39*L39 -> 0 | L39: 0 | M39: =F39*N39 -> 0 | N39: 0 | O39: =P39*D39 -> 0 | P39: 0 | Q39: =R39*D39 -> 0 | R39: 0 | S39: =E39+G39+I39+K39+M39+O39+Q39 -> 54.44 | T39: =S39/D39 -> 1 | U39: =E39+G39+I39+K39+M39 -> 54.44 | V39: =U39/D39 -> 1
B40: 15 | C40: Pintura de fachada | D40: 91.01 | E40: =D40*F40 -> 0 | F40: 0 | G40: =H40*D40 -> 45.505 | H40: 0.5 | I40: =D40*J40 -> 45.505 | J40: 0.5 | K40: =D40*L40 -> 0 | L40: 0 | M40: =F40*N40 -> 0 | N40: 0 | O40: =H40*P40 -> 0 | P40: 0 | Q40: =R40*D40 -> 30.9434 | R40: 0.34 | S40: =E40+G40+I40+K40+M40+O40+Q40 -> 121.9534 | T40: =S40/D40 -> 1.34 | U40: =E40+G40+I40+K40+M40 -> 91.01 | V40: =U40/D40 -> 1
C42: Total M2 de Fachada | D42: =SUM(D39:D40) -> 145.45 | E42: =SUM(E39:E40) -> 0 | F42: =E42/$D$42 -> 0 | G42: =SUM(G39:G40) -> 72.725 | H42: =G42/$D$42 -> 0.5 | I42: =SUM(I39:I40) -> 72.725 | J42: =I42/$D$42 -> 0.5 | K42: =SUM(K39:K40) -> 0 | L42: =K42/$D$42 -> 0 | M42: =SUM(M39:M40) -> 0 | N42: =M42/$D$42 -> 0 | O42: =SUM(O39:O40) -> 0 | P42: =O42/$D$42 -> 0 | Q42: =SUM(Q39:Q40) -> 30.9434 | R42: =Q42/$D$42 -> 0.21274252 | S42: =SUM(S39:S40) -> 176.3934 | T42: =S42/D42 -> 1.2127425 | U42: =SUM(U39:U40) -> 145.45 | V42: =U42/D42 -> 1
A44: PUNTO FIJO | B44: 1 IZQUIERDA | C44: Pintura de fachada | D44: 76.44 | E44: =D44*F44 -> 0 | F44: 0 | G44: =D44*H44 -> 0 | H44: 0 | I44: =D44*J44 -> 0 | J44: 0 | K44: =D44*L44 -> 0 | L44: 0 | M44: =D44*N44 -> 0 | N44: 0 | O44: =P44*D44 -> 0 | P44: 0 | Q44: =R44*D44 -> 0 | R44: 0 | S44: =E44+G44+I44+K44+M44+O44+Q44 -> 0 | T44: =S44/D44 -> 0 | U44: =E44+G44+I44+K44+M44 -> 0 | V44: =U44/D44 -> 0
B45: CARACOL | C45: Pintura de fachada | D45: =16.2*4+22.3+47.92+28.125+37.4+131 -> 331.545 | E45: =D45*F45 -> 0 | F45: 0 | G45: =D45*H45 -> 0 | H45: 0 | I45: =D45*J45 -> 0 | J45: 0 | K45: =D45*L45 -> 4.044849 | L45: =0.0122 -> 0.0122 | M45: =D45*N45 -> 16.57725 | N45: 0.05 | O45: =D45*P45 -> 0 | P45: 0 | Q45: =J45*R45 -> 0 | R45: 0 | S45: =E45+G45+I45+K45+M45+O45+Q45 -> 20.622099 | T45: =S45/D45 -> 0.0622 | U45: =E45+G45+I45+K45+M45 -> 20.622099 | V45: =U45/D45 -> 0.0622
B46: 1 DERECHA | C46: Pintura de fachada | D46: 76.44 | E46: =D46*F46 -> 0 | F46: 0 | G46: =D46*H46 -> 0 | H46: 0 | I46: =D46*J46 -> 0 | J46: 0 | K46: =D46*L46 -> 0 | L46: 0 | M46: =D46*N46 -> 38.22 | N46: 0.5 | O46: =D46*P46 -> 38.22 | P46: 0.5 | Q46: =J46*R46 -> 0 | R46: 0 | S46: =E46+G46+I46+K46+M46+O46+Q46 -> 76.44 | T46: =S46/D46 -> 1 | U46: =E46+G46+I46+K46+M46 -> 38.22 | V46: =U46/D46 -> 0.5
C48: Total M2 de Fachada | D48: =SUM(D44:D46) -> 484.425 | E48: =SUM(E44:E46) -> 0 | F48: =E48/$D$48 -> 0 | G48: =SUM(G44:G46) -> 0 | H48: =G48/$D$48 -> 0 | I48: =SUM(I44:I46) -> 0 | J48: =I48/$D$48 -> 0 | K48: =SUM(K44:K46) -> 4.044849 | L48: =K48/$D$48 -> 0.0083497941 | M48: =SUM(M44:M46) -> 54.79725 | N48: =M48/$D$48 -> 0.11311813 | O48: =SUM(O44:O46) -> 38.22 | P48: =O48/$D$48 -> 0.078897662 | Q48: =SUM(Q44:Q46) -> 0 | R48: =Q48/$D$48 -> 0 | S48: =SUM(S44:S46) -> 97.062099 | T48: =S48/D48 -> 0.20036559 | U48: =SUM(U44:U46) -> 58.842099 | V48: =U48/D48 -> 0.12146792
C50: Total M2 de Fachada General | D50: =D11+D16+D22+D31+D36+D42+D48 -> 1544.715 | K50: Total de M2 Ejecutados | S50: =S11+S16+S22+S31+S36+S42+S48 -> 1232.8674 | T50: =S50/D50 -> 0.79811967 | U50: =U11+U16+U22+U31 -> 614.27 | V50: =U50/D50 -> 0.39765912
S51: =D50-S50 -> 311.84758 | T51: =S51/D50 -> 0.20188033
T53: 0.59
T54: 0.41

Sheet Pasillos
A1: CEDROS - INTERVENCIÓN DE ZONAS INTERIORES
E3: ENE 15 - 17 | G3: ENE 19 - 24 | I3: ENE 26 - 31 | K3: FEB 02-07 | M3: FEB 09-14 | O3: FEB 16-21 | Q3: FEB 23-28
B4: Piso | C4: Descripción | D4: M2 | E4: Semana 01 | G4: Semana 02 | I4: Semana 03 | K4: Semana 04 | M4: Semana 05 | O4: Semana 06 | Q4: Semana 07 | S4: TOTAL EJECUTADO
E5: M2 | F5: % | G5: M2 | H5: % | I5: M2 | J5: % | K5: M2 | L5: % | M5: M2 | N5: % | O5: M2 | P5: % | Q5: M2 | R5: % | S5: M2 | T5: %
B6: 5 | C6: Punto fijo | D6: 28 | E6: =D6*F6 -> 0 | F6: 0 | G6: =D6*H6 -> 0 | H6: 0 | I6: =D6*J6 -> 0 | J6: 0 | K6: =D6*L6 -> 0 | L6: 0 | M6: =D6*N6 -> 0 | N6: 0 | O6: =D6*P6 -> 0 | P6: 0 | Q6: =H6*R6 -> 0 | R6: 0 | S6: =E6+G6+I6+K6+M6+O6+Q6 -> 0 | T6: =S6/D6 -> 0
C7: Pasillos | D7: 63.4 | E7: =D7*F7 -> 0 | F7: 0 | G7: =D7*H7 -> 0 | H7: 0 | I7: =D7*J7 -> 0 | J7: 0 | K7: =D7*L7 -> 0 | L7: 0 | M7: =D7*N7 -> 0 | N7: 0 | O7: =D7*P7 -> 6.34 | P7: 0.1 | Q7: =H7*R7 -> 0 | R7: 0 | S7: =E7+G7+I7+K7+M7+O7+Q7 -> 6.34 | T7: =S7/D7 -> 0.1
C8: Cielo rasos | D8: 45 | E8: =D8*F8 -> 0 | F8: 0 | G8: =D8*H8 -> 0 | H8: 0 | I8: =D8*J8 -> 0 | J8: 0 | K8: =D8*L8 -> 0 | L8: 0 | M8: =D8*N8 -> 0 | N8: 0 | O8: =D8*P8 -> 4.5 | P8: 0.1 | Q8: =H8*R8 -> 0 | R8: 0 | S8: =E8+G8+I8+K8+M8+O8+Q8 -> 4.5 | T8: =S8/D8 -> 0.1
B9: 4 | C9: Punto fijo | D9: 28 | E9: =D9*F9 -> 0 | F9: 0 | G9: =D9*H9 -> 0 | H9: 0 | I9: =D9*J9 -> 0 | J9: 0 | K9: =D9*L9 -> 0 | L9: 0 | M9: =D9*N9 -> 0 | N9: 0 | O9: =D9*P9 -> 0 | P9: 0 | Q9: =H9*R9 -> 0 | R9: 0 | S9: =E9+G9+I9+K9+M9+O9+Q9 -> 0 | T9: =S9/D9 -> 0
C10: Pasillos | D10: 63.4 | E10: =D10*F10 -> 0 | F10: 0 | G10: =D10*H10 -> 0 | H10: 0 | I10: =D10*J10 -> 0 | J10: 0 | K10: =D10*L10 -> 31.7 | L10: 0.5 | M10: =D10*N10 -> 31.7 | N10: 0.5 | O10: =D10*P10 -> 31.7 | P10: 0.5 | Q10: =H10*R10 -> 0 | R10: 0.5 | S10: =E10+G10+I10+K10+M10+O10+Q10 -> 95.1 | T10: =S10/D10 -> 1.5
C11: Cielo rasos | D11: 45 | E11: =D11*F11 -> 0 | F11: 0 | G11: =D11*H11 -> 0 | H11: 0 | I11: =D11*J11 -> 0 | J11: 0 | K11: =D11*L11 -> 22.5 | L11: 0.5 | M11: =D11*N11 -> 22.5 | N11: 0.5 | O11: =D11*P11 -> 22.5 | P11: 0.5 | Q11: =H11*R11 -> 0 | R11: 0.5 | S11: =E11+G11+I11+K11+M11+O11+Q11 -> 67.5 | T11: =S11/D11 -> 1.5
B12: 3 | C12: Punto fijo | D12: 28 | E12: =D12*F12 -> 0 | F12: 0 | G12: =D12*H12 -> 14 | H12: 0.5 | I12: =D12*J12 -> 0 | J12: 0 | K12: =D12*L12 -> 0 | L12: 0 | M12: =D12*N12 -> 0 | N12: 0 | O12: =D12*P12 -> 0 | P12: 0 | Q12: =H12*R12 -> 0 | R12: 0 | S12: =E12+G12+I12+K12+M12+O12+Q12 -> 14 | T12: =S12/D12 -> 0.5
C13: Pasillos | D13: 63.4 | E13: =D13*F13 -> 0 | F13: 0 | G13: =D13*H13 -> 31.7 | H13: 0.5 | I13: =D13*J13 -> 0 | J13: 0 | K13: =D13*L13 -> 0 | L13: 0 | M13: =D13*N13 -> 63.4 | N13: 1 | O13: =D13*P13 -> 0 | P13: 0 | Q13: =H13*R13 -> 0 | R13: 0 | S13: =E13+G13+I13+K13+M13+O13+Q13 -> 95.1 | T13: =S13/D13 -> 1.5
C14: Cielo rasos | D14: 45 | E14: =D14*F14 -> 0 | F14: 0 | G14: =D14*H14 -> 22.5 | H14: 0.5 | I14: =D14*J14 -> 0 | J14: 0 | K14: =D14*L14 -> 0 | L14: 0 | M14: =D14*N14 -> 45 | N14: 1 | O14: =D14*P14 -> 0 | P14: 0 | Q14: =H14*R14 -> 0 | R14: 0 | S14: =E14+G14+I14+K14+M14+O14+Q14 -> 67.5 | T14: =S14/D14 -> 1.5
B15: 2 | C15: Punto fijo | D15: 28 | E15: =D15*F15 -> 0 | F15: 0 | G15: =D15*H15 -> 0 | H15: 0 | I15: =D15*J15 -> 0 | J15: 0 | K15: =D15*L15 -> 0 | L15: 0 | M15: =D15*N15 -> 0 | N15: 0 | O15: =D15*P15 -> 0 | P15: 0 | Q15: =H15*R15 -> 0 | R15: 0 | S15: =E15+G15+I15+K15+M15+O15+Q15 -> 0 | T15: =S15/D15 -> 0
C16: Pasillos | D16: 63.4 | E16: =D16*F16 -> 0 | F16: 0 | G16: =D16*H16 -> 0 | H16: 0 | I16: =D16*J16 -> 0 | J16: 0 | K16: =D16*L16 -> 0 | L16: 0 | M16: =D16*N16 -> 0 | N16: 0 | O16: =D16*P16 -> 63.4 | P16: 1 | Q16: =H16*R16 -> 0 | R16: 0 | S16: =E16+G16+I16+K16+M16+O16+Q16 -> 63.4 | T16: =S16/D16 -> 1
C17: Cielo rasos | D17: 45 | E17: =D17*F17 -> 0 | F17: 0 | G17: =D17*H17 -> 0 | H17: 0 | I17: =D17*J17 -> 0 | J17: 0 | K17: =D17*L17 -> 0 | L17: 0 | M17: =D17*N17 -> 0 | N17: 0 | O17: =D17*P17 -> 45 | P17: 1 | Q17: =H17*R17 -> 0 | R17: 0 | S17: =E17+G17+I17+K17+M17+O17+Q17 -> 45 | T17: =S17/D17 -> 1
B18: 1 | C18: Punto fijo | D18: 13 | E18: =D18*F18 -> 0 | F18: 0 | G18: =D18*H18 -> 0 | H18: 0 | I18: =D18*J18 -> 0 | J18: 0 | K18: =D18*L18 -> 0 | L18: 0 | M18: =D18*N18 -> 0 | N18: 0 | O18: =D18*P18 -> 0 | P18: 0 | Q18: =H18*R18 -> 0 | R18: 0 | S18: =E18+G18+I18+K18+M18+O18+Q18 -> 0 | T18: =S18/D18 -> 0
C19: Pasillos | D19: 73.6 | E19: =D19*F19 -> 0 | F19: 0 | G19: =D19*H19 -> 0 | H19: 0 | I19: =D19*J19 -> 0 | J19: 0 | K19: =D19*L19 -> 0 | L19: 0 | M19: =D19*N19 -> 0 | N19: 0 | O19: =D19*P19 -> 18.4 | P19: 0.25 | Q19: =H19*R19 -> 0 | R19: 0.75 | S19: =E19+G19+I19+K19+M19+O19+Q19 -> 18.4 | T19: =S19/D19 -> 0.25
C20: Cielo rasos | D20: 87.3 | E20: =D20*F20 -> 0 | F20: 0 | G20: =D20*H20 -> 0 | H20: 0 | I20: =D20*J20 -> 0 | J20: 0 | K20: =D20*L20 -> 0 | L20: 0 | M20: =D20*N20 -> 0 | N20: 0 | O20: =D20*P20 -> 0 | P20: 0 | Q20: =H20*R20 -> 0 | R20: 1 | S20: =E20+G20+I20+K20+M20+O20+Q20 -> 0 | T20: =S20/D20 -> 0
A21: =#REF!*2 -> #REF!
C22: TOTAL M2 DE MUROS Y CIELORASO | D22: =SUM(D6:D20) -> 719.5 | E22: =SUM(E6:E20) -> 0 | F22: =E22/D22 -> 0 | G22: =SUM(G6:G20) -> 68.2 | H22: =G22/D22 -> 0.094788047 | I22: =SUM(I6:I20) -> 0 | J22: =I22/D22 -> 0 | K22: =SUM(K6:K20) -> 54.2 | L22: =K22/D22 -> 0.07533009 | M22: =SUM(M6:M20) -> 162.6 | N22: =M22/D22 -> 0.22599027 | O22: =SUM(O6:O20) -> 191.84 | P22: =O22/D22 -> 0.2666296 | Q22: =SUM(Q6:Q20) -> 0 | R22: =Q22/H22 -> 0 | S22: =SUM(S6:S20) -> 476.84 | T22: =S22/D22 -> 0.66273801 | V22: 1554.832
S23: =D22-S22 -> 242.66 | T23: =S23/D22 -> 0.33726199 | V23: 582.688
V24: =SUM(V22:V23) -> 2137.52
C26: La cantidad que se encuentra consignada en el acta #1 respecto a los M2 de pintura en pasillos corresponde al 70% de la cantidad ejecutada a la fecha.
C30: Pintura para interiores blanca tipo 1 viniltex ultralavable a dos manos | D30: =S22*E30 -> 286.104 | E30: 0.6
C31: Pintura para interiores cieloraso tipo 3 icolatex pintuco a dos manos | D31: =S22*E31 -> 190.736 | E31: 0.4
