Workbook

Sheet APU I
A1: CONDOMINIO PARQUE RESIDENCIAL LOS CEDROS
A3: PRELIMINARES
A5: ACTIVIDAD: Desmontaje de piso tipo Deck | D5: ITEM | E5: 1.0
D6: UNIDAD | E6: M2
A7: I. EQUIPOS
A8: DESCRIPCIÓN | B8: UNIDAD | C8: RENDIMIENTO | D8: TARIFA | E8: VALOR - PARCIAL
A9: Herramienta menor | B9: %MO | C9: 0.1 | D9: =E27 -> 2600 | E9: =C9*D9 -> 260
A11: SUB - TOTAL | E11: =SUM(E9:E9) -> 260
A12: II. MATERIALES
A13: DESCRIPCIÓN | B13: UNIDAD | C13: CANTIDAD | D13: PRECIO - UNIT | E13: VALOR - PARCIAL
A15: Desperdicio 2% | E15: =SUM(E14:E14)*0.02 -> 0
A17: SUB - TOTAL | E17: =SUM(E14:E15) -> 0
A18: III. TRANSPORTE
A19: DESCRIPCIÓN | B19: UNIDAD | C19: RENDIMIENTO | D19: TARIFA | E19: VALOR - PARCIAL
A20: Acarreo LUV | B20: Día | C20: 0 | D20: 0 | E20: 0
A22: SUB - TOTAL | E22: =SUM(E20) -> 0
A23: IV. MANO DE OBRA
A24: DESCRIPCIÓN | B24: UNIDAD | C24: RENDIMIENTO | D24: JORNAL | E24: VALOR - PARCIAL
A25: Oficial | B25: Día | C25: 50 | D25: 130000 | E25: =D25/C25 -> 2600
A27: SUB - TOTAL | E27: =SUM(E25) -> 2600
A29: TOTAL UNITARIO | E29: =SUM(E11,E17,E22,E27) -> 2860
A32: ACTIVIDAD: Restructuración e instalación de lámina de fibrocemento | D32: ITEM | E32: 2
D33: UNIDAD | E33: M2
A34: I. EQUIPOS
A35: DESCRIPCIÓN | B35: UNIDAD | C35: RENDIMIENTO | D35: TARIFA | E35: VALOR - PARCIAL
A36: Herramienta menor | B36: %MO | C36: 0.05 | D36: =E58 -> 7000 | E36: =C36*D36 -> 350
A38: SUB - TOTAL | E38: =SUM(E36:E36) -> 350
A39: II. MATERIALES
A40: DESCRIPCIÓN | B40: UNIDAD | C40: CANTIDAD | D40: PRECIO - UNIT | E40: VALOR - PARCIAL
A41: Lamina fibrocemento de 10mm | B41: Und | C41: 0.35 | D41: 96000 | E41: =C41*D41 -> 33600
A42: Paral Estructural | B42: Und | C42: 1 | D42: 9500 | E42: =C42*D42 -> 9500
A43: Canal Estructural | B43: Und | C43: 1 | D43: 9000 | E43: =C43*D43 -> 9000
A44: Tornillos | B44: Und | C44: 50 | D44: 40 | E44: =C44*D44 -> 2000
A46: Desperdicio 2% | E46: 0
A48: SUB - TOTAL | E48: =SUM(E41:E46) -> 54100
A49: III. TRANSPORTE
A50: DESCRIPCIÓN | B50: UNIDAD | C50: RENDIMIENTO | D50: TARIFA | E50: VALOR - PARCIAL
A51: Acarreo LUV | B51: Día | C51: 0.025 | D51: 60000 | E51: =D51*C51 -> 1500
A53: SUB - TOTAL | E53: =SUM(E51) -> 1500
A54: IV. MANO DE OBRA
A55: DESCRIPCIÓN | B55: UNIDAD | C55: RENDIMIENTO | D55: JORNAL | E55: VALOR - PARCIAL
A56: CUADRILLA 1: 1 Oficial y 1 ayudante | B56: Día | C56: 30 | D56: 210000 | E56: =D56/C56 -> 7000
A58: SUB - TOTAL | E58: =SUM(E56) -> 7000
A60: TOTAL UNITARIO | E60: =SUM(E38,E48,E53,E58) -> 62950
A63: ACTIVIDAD: Impermeabilización de laminas de fibrocemento | D63: ITEM | E63: 3
D64: UNIDAD | E64: M2
A65: I. EQUIPOS
A66: DESCRIPCIÓN | B66: UNIDAD | C66: RENDIMIENTO | D66: TARIFA | E66: VALOR - PARCIAL
A67: Herramienta menor | B67: %MO | C67: 0.8 | D67: =E87 -> 1300 | E67: =C67*D67 -> 1040
A69: SUB - TOTAL | E69: =SUM(E67:E67) -> 1040
A70: II. MATERIALES
A71: DESCRIPCIÓN | B71: UNIDAD | C71: CANTIDAD | D71: PRECIO - UNIT | E71: VALOR - PARCIAL
A72: Emulsión asfáltica x 18kg | B72: KG | C72: 0.022 | D72: 300000 | E72: =C72*D72 -> 6600
A73: Manto de refuerzo - Sika Felp | B73: M2 | C73: 0.015 | D73: 100000 | E73: =C73*D73 -> 1500
A75: Desperdicio 3% | E75: =E72*0.03 -> 198
A77: SUB - TOTAL | E77: =SUM(E72:E75) -> 8298
A78: III. TRANSPORTE
A79: DESCRIPCIÓN | B79: UNIDAD | C79: RENDIMIENTO | D79: TARIFA | E79: VALOR - PARCIAL
A80: Acarreo | B80: Día | C80: 0.025 | D80: 25000 | E80: =D80*C80 -> 625
A82: SUB - TOTAL | E82: =SUM(E80) -> 625
A83: IV. MANO DE OBRA
A84: DESCRIPCIÓN | B84: UNIDAD | C84: RENDIMIENTO | D84: JORNAL | E84: VALOR - PARCIAL
A85: Oficial | B85: Día | C85: 100 | D85: 130000 | E85: =D85/C85 -> 1300
A87: SUB - TOTAL | E87: =SUM(E85) -> 1300
A89: TOTAL UNITARIO | E89: =SUM(E69,E77,E82,E87) -> 11263
A92: ACTIVIDAD: Mortero de alistamiento | D92: ITEM | E92: 4
D93: UNIDAD | E93: M2
A94: I. EQUIPOS
A95: DESCRIPCIÓN | B95: UNIDAD | C95: RENDIMIENTO | D95: TARIFA | E95: VALOR - PARCIAL
A96: Herramienta menor | B96: %MO | C96: 0.1 | D96: =E116 -> 2888.8889 | E96: =C96*D96 -> 288.88889
A98: SUB - TOTAL | E98: =SUM(E96:E96) -> 288.88889
A99: II. MATERIALES
A100: DESCRIPCIÓN | B100: UNIDAD | C100: CANTIDAD | D100: PRECIO - UNIT | E100: VALOR - PARCIAL
A101: MorteroListo Impadoc x 40 kg | B101: M2 | C101: 0.15 | D101: 48000 | E101: =C101*D101 -> 7200
A102: Acronal | B102: GL | C102: 0.008 | D102: 56000 | E102: =C102*D102 -> 448
A104: Desperdicio 3% | E104: =E101*0.03 -> 216
A106: SUB - TOTAL | E106: =SUM(E101:E104) -> 7864
A107: III. TRANSPORTE
A108: DESCRIPCIÓN | B108: UNIDAD | C108: RENDIMIENTO | D108: TARIFA | E108: VALOR - PARCIAL
A109: Acarreo | B109: Día | C109: 0.025 | D109: 45000 | E109: =D109*C109 -> 1125
A111: SUB - TOTAL | E111: =SUM(E109) -> 1125
A112: IV. MANO DE OBRA
A113: DESCRIPCIÓN | B113: UNIDAD | C113: RENDIMIENTO | D113: JORNAL | E113: VALOR - PARCIAL
A114: Oficial | B114: Día | C114: 45 | D114: 130000 | E114: =D114/C114 -> 2888.8889
A116: SUB - TOTAL | E116: =SUM(E114) -> 2888.8889
A118: TOTAL UNITARIO | E118: =SUM(E98,E106,E111,E116) -> 12166.778
A122: ACTIVIDAD: Instalación de piso cerámico incluye boquilla | D122: ITEM | E122: 5
D123: UNIDAD | E123: ML
A124: I. EQUIPOS
A125: DESCRIPCIÓN | B125: UNIDAD | C125: RENDIMIENTO | D125: TARIFA | E125: VALOR - PARCIAL
A126: Herramienta menor | B126: %MO | C126: 0.1 | D126: =E148 -> 2888.8889 | E126: =C126*D126 -> 288.88889
A128: SUB - TOTAL | E128: =SUM(E126:E126) -> 288.88889
A129: II. MATERIALES
A130: DESCRIPCIÓN | B130: UNIDAD | C130: CANTIDAD | D130: PRECIO - UNIT | E130: VALOR - PARCIAL
A131: Piso cerámico | B131: M2 | C131: 1 | D131: 60000 | E131: =C131*D131 -> 60000
A132: Mortero de pega | B132: M2 | C132: 0.15 | D132: 38000 | E132: =C132*D132 -> 5700
A133: Boquilla | B133: M2 | C133: 0.1 | D133: 28000 | E133: =C133*D133 -> 2800
A134: Separadores | B134: GLB | C134: 0.1 | D134: 15000 | E134: =C134*D134 -> 1500
A136: Desperdicio 5% | E136: =(E131+E135)*0.05 -> 3000
A138: SUB - TOTAL | E138: =SUM(E131:E136) -> 73000
...

Sheet APU II
A1: CONDOMINIO PARQUE RESIDENCIAL LOS CEDROS
A3: PREPARACIÓN DE SUPERFICIES | G3: TIEMPO ESTIMADO
A5: ACTIVIDAD: Lavado General de Superficies | D5: ITEM | E5: 1.0
D6: UNIDAD | E6: M2
A7: I. EQUIPOS
A8: DESCRIPCIÓN | B8: UNIDAD | C8: RENDIMIENTO | D8: TARIFA | E8: VALOR - PARCIAL
A9: Herramienta menor | B9: %MO | C9: 0.1 | D9: =E31 -> 633.33333 | E9: =C9*D9 -> 63.333333
A10: Equipos Freshouse | B10: Día | C10: 0.015 | D10: 25000 | E10: =C10*D10 -> 375
A11: Equipo Hidrolavadora | B11: Día | C11: 0.01 | D11: 15000 | E11: =C11*D11 -> 150
A13: SUB - TOTAL | E13: =SUM(E9:E11) -> 588.33333
A14: II. MATERIALES
A15: DESCRIPCIÓN | B15: UNIDAD | C15: CANTIDAD | D15: PRECIO - UNIT | E15: VALOR - PARCIAL
A16: Hipoclorito | B16: GL | C16: 0.05 | D16: 35000 | E16: =C16*D16 -> 1750
A17: Agua | B17: Und | C17: 0.1 | D17: 500 | E17: =C17*D17 -> 50
A19: Desperdicio 2% | E19: 0
A21: SUB - TOTAL | E21: =SUM(E16:E19) -> 1800
A22: III. TRANSPORTE
A23: DESCRIPCIÓN | B23: UNIDAD | C23: RENDIMIENTO | D23: TARIFA | E23: VALOR - PARCIAL
A24: Acarreo LUV | B24: Día | C24: 0 | D24: 0 | E24: 0
A26: SUB - TOTAL | E26: =SUM(E24) -> 0
A27: IV. MANO DE OBRA
A28: DESCRIPCIÓN | B28: UNIDAD | C28: RENDIMIENTO | D28: JORNAL | E28: VALOR - PARCIAL
A29: Práctico | B29: Día | C29: 150 | D29: 95000 | E29: =D29/C29 -> 633.33333 | G29: =480/C29 -> 3.2
A31: SUB - TOTAL | E31: =SUM(E29) -> 633.33333
A33: TOTAL UNITARIO | E33: =SUM(E13,E21,E26,E31) -> 3021.6667
A35: Retiro y Reemplazo de Graniplast Deteriorado | E35: 2.2
A37: ACTIVIDAD: Inspección de superficie incluye rasqueteado | D37: ITEM
D38: UNIDAD | E38: M2
A39: I. EQUIPOS
A40: DESCRIPCIÓN | B40: UNIDAD | C40: RENDIMIENTO | D40: TARIFA | E40: VALOR - PARCIAL
A41: Herramienta menor | B41: %MO | C41: 0.05 | D41: =E60 -> 730.76923 | E41: =C41*D41 -> 36.538462
A42: Equipos Freshouse | B42: Día | C42: 0.015 | D42: 25000 | E42: =C42*D42 -> 375
A44: SUB - TOTAL | E44: =SUM(E41:E42) -> 411.53846
A45: II. MATERIALES
A46: DESCRIPCIÓN | B46: UNIDAD | C46: CANTIDAD | D46: PRECIO - UNIT | E46: VALOR - PARCIAL
A48: Desperdicio 2% | E48: 0
A50: SUB - TOTAL | E50: =SUM(E47:E48) -> 0
A51: III. TRANSPORTE
A52: DESCRIPCIÓN | B52: UNIDAD | C52: RENDIMIENTO | D52: TARIFA | E52: VALOR - PARCIAL
A53: Acarreo LUV | B53: Día | C53: 0 | D53: 60000 | E53: =D53*C53 -> 0
A55: SUB - TOTAL | E55: =SUM(E53) -> 0
A56: IV. MANO DE OBRA
A57: DESCRIPCIÓN | B57: UNIDAD | C57: RENDIMIENTO | D57: JORNAL | E57: VALOR - PARCIAL
A58: Práctico | B58: Día | C58: 130 | D58: 95000 | E58: =D58/C58 -> 730.76923 | G58: =480/C58 -> 3.6923077
A60: SUB - TOTAL | E60: =SUM(E58) -> 730.76923
A62: TOTAL UNITARIO | E62: =SUM(E44,E50,E55,E60) -> 1142.3077
A65: ACTIVIDAD: Nivelación de superficie con Mortero Listo | D65: ITEM
D66: UNIDAD | E66: M2
A67: I. EQUIPOS
A68: DESCRIPCIÓN | B68: UNIDAD | C68: RENDIMIENTO | D68: TARIFA | E68: VALOR - PARCIAL
A69: Herramienta menor | B69: %MO | C69: 0.8 | D69: =E90 -> 6142.8571 | E69: =C69*D69 -> 4914.2857
A70: Equipos Freshouse | B70: Día | C70: 0.02 | D70: 25000 | E70: =C70*D70 -> 500
A72: SUB - TOTAL | E72: =SUM(E69:E70) -> 5414.2857
A73: II. MATERIALES
A74: DESCRIPCIÓN | B74: UNIDAD | C74: CANTIDAD | D74: PRECIO - UNIT | E74: VALOR - PARCIAL
A75: Mortero Listo Impadoc x 40kg | B75: Saco | C75: 0.1 | D75: 42000 | E75: =C75*D75 -> 4200
A76: Acronal | B76: GL | C76: 0.01 | D76: 32500 | E76: =C76*D76 -> 325
A78: Desperdicio 3% | E78: =E75*0.03 -> 126
A80: SUB - TOTAL | E80: =SUM(E75:E78) -> 4651
A81: III. TRANSPORTE
A82: DESCRIPCIÓN | B82: UNIDAD | C82: RENDIMIENTO | D82: TARIFA | E82: VALOR - PARCIAL
A83: Acarreo | B83: Día | C83: 0.005 | D83: 60000 | E83: =D83*C83 -> 300
A85: SUB - TOTAL | E85: =SUM(E83) -> 300
A86: IV. MANO DE OBRA
A87: DESCRIPCIÓN | B87: UNIDAD | C87: RENDIMIENTO | D87: JORNAL | E87: VALOR - PARCIAL
A88: CUADRILLA 1: 1 Oficial y 1 ayudante | B88: Día | C88: 35 | D88: 215000 | E88: =D88/C88 -> 6142.8571
A90: SUB - TOTAL | E90: =SUM(E88) -> 6142.8571
A92: TOTAL UNITARIO | E92: =SUM(E72,E80,E85,E90) -> 16508.143
A95: ACTIVIDAD: Aplicación de Graniplast | D95: ITEM
D96: UNIDAD | E96: M2
A97: I. EQUIPOS
A98: DESCRIPCIÓN | B98: UNIDAD | C98: RENDIMIENTO | D98: TARIFA | E98: VALOR - PARCIAL
A99: Herramienta menor | B99: %MO | C99: 0.1 | D99: =E120 -> 8800 | E99: =C99*D99 -> 880
A100: Equipos Freshouse | B100: Día | C100: 0.02 | D100: 25000 | E100: =C100*D100 -> 500
A102: SUB - TOTAL | E102: =SUM(E99:E100) -> 1380
A103: II. MATERIALES
A104: DESCRIPCIÓN | B104: UNIDAD | C104: CANTIDAD | D104: PRECIO - UNIT | E104: VALOR - PARCIAL
A105: Graniplast Premium Escagrafiado | B105: M2 | C105: 0.14 | D105: 170000 | E105: =C105*D105 -> 23800
A106: Acronal | B106: GL | C106: 0.01 | D106: 32500 | E106: =C106*D106 -> 325
A108: Desperdicio 3% | E108: =E105*0.03 -> 714
A110: SUB - TOTAL | E110: =SUM(E105:E108) -> 24839
A111: III. TRANSPORTE
A112: DESCRIPCIÓN | B112: UNIDAD | C112: RENDIMIENTO | D112: TARIFA | E112: VALOR - PARCIAL
A113: Acarreo | B113: Día | C113: 0.025 | D113: 45000 | E113: =D113*C113 -> 1125
A115: SUB - TOTAL | E115: =SUM(E113) -> 1125
A116: IV. MANO DE OBRA
A117: DESCRIPCIÓN | B117: UNIDAD | C117: RENDIMIENTO | D117: JORNAL | E117: VALOR - PARCIAL
A118: CUADRILLA 1: 1 Oficial y 1 ayudante | B118: Día | C118: 25 | D118: 220000 | E118: =D118/C118 -> 8800 | G118: =480/C118 -> 19.2
A120: SUB - TOTAL | E120: =SUM(E118) -> 8800
A122: TOTAL UNITARIO | E122: =SUM(E102,E110,E115,E120) -> 36144
A126: ACTIVIDAD: Reposicion de Mortero en mal estado | D126: ITEM | E126: 2.3
D127: UNIDAD | E127: M2
A128: I. EQUIPOS
A129: DESCRIPCIÓN | B129: UNIDAD | C129: RENDIMIENTO | D129: TARIFA | E129: VALOR - PARCIAL
A130: Herramienta menor | B130: %MO | C130: 0.1 | D130: =E152 -> 11000 | E130: =C130*D130 -> 1100
A131: Equipos Freshouse | B131: Día | C131: 0.02 | D131: 25000 | E131: =C131*D131 -> 500
A133: SUB - TOTAL | E133: =SUM(E130:E131) -> 1600
A134: II. MATERIALES
A135: DESCRIPCIÓN | B135: UNIDAD | C135: CANTIDAD | D135: PRECIO - UNIT | E135: VALOR - PARCIAL
A136: Mortero 1:3 | B136: M2 | C136: 0.025 | D136: 650000 | E136: =C136*D136 -> 16250 | G136: =0.1*0.1*1 -> 0.01
...

Sheet APU III
A1: CONDOMINIO PARQUE RESIDENCIAL LOS CEDROS
A3: ACABADO DE PINTURA | G3: TIEMPO ESTIMADO
A5: ACTIVIDAD: Suministro y Aplicación de Pintura para exteriores | D5: ITEM | E5: 1.0
D6: UNIDAD | E6: M2
A7: I. EQUIPOS
A8: DESCRIPCIÓN | B8: UNIDAD | C8: RENDIMIENTO | D8: TARIFA | E8: VALOR - PARCIAL
A9: Herramienta menor | B9: %MO | C9: 0.1 | D9: =E32 -> 2166.6667 | E9: =C9*D9 -> 216.66667
A10: Equipos Freshouse | B10: Día | C10: 0.015 | D10: 25000 | E10: =C10*D10 -> 375
A12: SUB - TOTAL | E12: =SUM(E9:E10) -> 591.66667
A13: II. MATERIALES
A14: DESCRIPCIÓN | B14: UNIDAD | C14: CANTIDAD | D14: PRECIO - UNIT | E14: VALOR - PARCIAL
A15: Koraza Pro 550 | B15: CÑ | C15: 0.02 | D15: 450000 | E15: =C15*D15 -> 9000
A16: Rodillo 9" | B16: Und | C16: 0.001 | D16: 38000 | E16: =C16*D16 -> 38
A17: Brocha | B17: Und | C17: 0.001 | D17: 10000 | E17: =C17*D17 -> 10
A20: Desperdicio 2% | E20: =SUM(E15:E19)*0.05 -> 452.4
A22: SUB - TOTAL | E22: =SUM(E15:E20) -> 9500.4
A23: III. TRANSPORTE
A24: DESCRIPCIÓN | B24: UNIDAD | C24: RENDIMIENTO | D24: TARIFA | E24: VALOR - PARCIAL
A25: Acarreo | B25: Día | C25: 0.025 | D25: 25000 | E25: =D25*C25 -> 625
A27: SUB - TOTAL | E27: =SUM(E25) -> 625
A28: IV. MANO DE OBRA
A29: DESCRIPCIÓN | B29: UNIDAD | C29: RENDIMIENTO | D29: JORNAL | E29: VALOR - PARCIAL
A30: Oficial | B30: Día | C30: 60 | D30: 130000 | E30: =D30/C30 -> 2166.6667 | G30: =480/C30 -> 8
A32: SUB - TOTAL | E32: =SUM(E30) -> 2166.6667
A34: TOTAL UNITARIO | E34: =SUM(E12,E22,E27,E32) -> 12883.733
A36: Retiro y Reemplazo de Graniplast Deteriorado | E36: 2.2
A38: ACTIVIDAD: Inspección de superficie incluye rasqueteado | D38: ITEM
D39: UNIDAD | E39: M2
A40: I. EQUIPOS
A41: DESCRIPCIÓN | B41: UNIDAD | C41: RENDIMIENTO | D41: TARIFA | E41: VALOR - PARCIAL
A42: Herramienta menor | B42: %MO | C42: 0.05 | D42: =E61 -> 730.76923 | E42: =C42*D42 -> 36.538462
A43: Equipos Freshouse | B43: Día | C43: 0.015 | D43: 25000 | E43: =C43*D43 -> 375
A45: SUB - TOTAL | E45: =SUM(E42:E43) -> 411.53846
A46: II. MATERIALES
A47: DESCRIPCIÓN | B47: UNIDAD | C47: CANTIDAD | D47: PRECIO - UNIT | E47: VALOR - PARCIAL
A49: Desperdicio 2% | E49: 0
A51: SUB - TOTAL | E51: =SUM(E48:E49) -> 0
A52: III. TRANSPORTE
A53: DESCRIPCIÓN | B53: UNIDAD | C53: RENDIMIENTO | D53: TARIFA | E53: VALOR - PARCIAL
A54: Acarreo LUV | B54: Día | C54: 0 | D54: 60000 | E54: =D54*C54 -> 0
A56: SUB - TOTAL | E56: =SUM(E54) -> 0
A57: IV. MANO DE OBRA
A58: DESCRIPCIÓN | B58: UNIDAD | C58: RENDIMIENTO | D58: JORNAL | E58: VALOR - PARCIAL
A59: Práctico | B59: Día | C59: 130 | D59: 95000 | E59: =D59/C59 -> 730.76923 | G59: =480/C59 -> 3.6923077
A61: SUB - TOTAL | E61: =SUM(E59) -> 730.76923
A63: TOTAL UNITARIO | E63: =SUM(E45,E51,E56,E61) -> 1142.3077
A66: ACTIVIDAD: Nivelación de superficie con Mortero Listo | D66: ITEM
D67: UNIDAD | E67: M2
A68: I. EQUIPOS
A69: DESCRIPCIÓN | B69: UNIDAD | C69: RENDIMIENTO | D69: TARIFA | E69: VALOR - PARCIAL
A70: Herramienta menor | B70: %MO | C70: 0.8 | D70: =E91 -> 4777.7778 | E70: =C70*D70 -> 3822.2222
A71: Equipos Freshouse | B71: Día | C71: 0.02 | D71: 25000 | E71: =C71*D71 -> 500
A73: SUB - TOTAL | E73: =SUM(E70:E71) -> 4322.2222
A74: II. MATERIALES
A75: DESCRIPCIÓN | B75: UNIDAD | C75: CANTIDAD | D75: PRECIO - UNIT | E75: VALOR - PARCIAL
A76: Mortero Listo Impadoc x 40kg | B76: Saco | C76: 0.1 | D76: 42000 | E76: =C76*D76 -> 4200
A77: Acronal | B77: GL | C77: 0.01 | D77: 32500 | E77: =C77*D77 -> 325
A79: Desperdicio 3% | E79: =E76*0.03 -> 126
A81: SUB - TOTAL | E81: =SUM(E76:E79) -> 4651
A82: III. TRANSPORTE
A83: DESCRIPCIÓN | B83: UNIDAD | C83: RENDIMIENTO | D83: TARIFA | E83: VALOR - PARCIAL
A84: Acarreo | B84: Día | C84: 0.005 | D84: 60000 | E84: =D84*C84 -> 300
A86: SUB - TOTAL | E86: =SUM(E84) -> 300
A87: IV. MANO DE OBRA
A88: DESCRIPCIÓN | B88: UNIDAD | C88: RENDIMIENTO | D88: JORNAL | E88: VALOR - PARCIAL
A89: CUADRILLA 1: 1 Oficial y 1 ayudante | B89: Día | C89: 45 | D89: 215000 | E89: =D89/C89 -> 4777.7778
A91: SUB - TOTAL | E91: =SUM(E89) -> 4777.7778
A93: TOTAL UNITARIO | E93: =SUM(E73,E81,E86,E91) -> 14051
A96: ACTIVIDAD: Aplicación de Graniplast | D96: ITEM
D97: UNIDAD | E97: M2
A98: I. EQUIPOS
A99: DESCRIPCIÓN | B99: UNIDAD | C99: RENDIMIENTO | D99: TARIFA | E99: VALOR - PARCIAL
A100: Herramienta menor | B100: %MO | C100: 0.1 | D100: =E121 -> 8800 | E100: =C100*D100 -> 880
A101: Equipos Freshouse | B101: Día | C101: 0.02 | D101: 25000 | E101: =C101*D101 -> 500
A103: SUB - TOTAL | E103: =SUM(E100:E101) -> 1380
A104: II. MATERIALES
A105: DESCRIPCIÓN | B105: UNIDAD | C105: CANTIDAD | D105: PRECIO - UNIT | E105: VALOR - PARCIAL
A106: Graniplast Premium Escagrafiado | B106: M2 | C106: 0.08 | D106: 170000 | E106: =C106*D106 -> 13600
A107: Acronal | B107: GL | C107: 0.01 | D107: 32500 | E107: =C107*D107 -> 325
A109: Desperdicio 3% | E109: =E106*0.03 -> 408
A111: SUB - TOTAL | E111: =SUM(E106:E109) -> 14333
A112: III. TRANSPORTE
A113: DESCRIPCIÓN | B113: UNIDAD | C113: RENDIMIENTO | D113: TARIFA | E113: VALOR - PARCIAL
A114: Acarreo | B114: Día | C114: 0.025 | D114: 45000 | E114: =D114*C114 -> 1125
A116: SUB - TOTAL | E116: =SUM(E114) -> 1125
A117: IV. MANO DE OBRA
A118: DESCRIPCIÓN | B118: UNIDAD | C118: RENDIMIENTO | D118: JORNAL | E118: VALOR - PARCIAL
A119: CUADRILLA 1: 1 Oficial y 1 ayudante | B119: Día | C119: 25 | D119: 220000 | E119: =D119/C119 -> 8800 | G119: =480/C119 -> 19.2
A121: SUB - TOTAL | E121: =SUM(E119) -> 8800
A123: TOTAL UNITARIO | E123: =SUM(E103,E111,E116,E121) -> 25638
A127: ACTIVIDAD: Reposicion de Mortero en mal estado | D127: ITEM | E127: 2.3
D128: UNIDAD | E128: M2
A129: I. EQUIPOS
A130: DESCRIPCIÓN | B130: UNIDAD | C130: RENDIMIENTO | D130: TARIFA | E130: VALOR - PARCIAL
A131: Herramienta menor | B131: %MO | C131: 0.1 | D131: =E152 -> 22000 | E131: =C131*D131 -> 2200
A132: Equipos Freshouse | B132: Día | C132: 0.02 | D132: 25000 | E132: =C132*D132 -> 500
A134: SUB - TOTAL | E134: =SUM(E131:E132) -> 2700
A135: II. MATERIALES
A136: DESCRIPCIÓN | B136: UNIDAD | C136: CANTIDAD | D136: PRECIO - UNIT | E136: VALOR - PARCIAL
A137: Mortero 1:3 | B137: M2 | C137: 0.045 | D137: 650000 | E137: =C137*D137 -> 29250 | G137: =0.1*0.1*1 -> 0.01
...

Sheet APU IV
A1: CONDOMINIO PARQUE RESIDENCIAL LOS CEDROS
A3: ACABADO DE PINTURA | G3: TIEMPO ESTIMADO
A5: ACTIVIDAD: Suministro y Aplicación de Pintura para exteriores | D5: ITEM | E5: 1.0
D6: UNIDAD | E6: M2
A7: I. EQUIPOS
A8: DESCRIPCIÓN | B8: UNIDAD | C8: RENDIMIENTO | D8: TARIFA | E8: VALOR - PARCIAL
A9: Herramienta menor | B9: %MO | C9: 0.1 | D9: =E32 -> 2166.6667 | E9: =C9*D9 -> 216.66667
A10: Equipos Freshouse | B10: Día | C10: 0.015 | D10: 25000 | E10: =C10*D10 -> 375
A12: SUB - TOTAL | E12: =SUM(E9:E10) -> 591.66667
A13: II. MATERIALES
A14: DESCRIPCIÓN | B14: UNIDAD | C14: CANTIDAD | D14: PRECIO - UNIT | E14: VALOR - PARCIAL
A15: Koraza Pro 550 | B15: CÑ | C15: 0.04 | D15: 450000 | E15: =C15*D15 -> 18000
A16: Rodillo 9" | B16: Und | C16: 0.001 | D16: 38000 | E16: =C16*D16 -> 38
A17: Brocha | B17: Und | C17: 0.001 | D17: 10000 | E17: =C17*D17 -> 10
A20: Desperdicio 2% | E20: =SUM(E15:E19)*0.05 -> 902.4
A22: SUB - TOTAL | E22: =SUM(E15:E20) -> 18950.4
A23: III. TRANSPORTE
A24: DESCRIPCIÓN | B24: UNIDAD | C24: RENDIMIENTO | D24: TARIFA | E24: VALOR - PARCIAL
A25: Acarreo | B25: Día | C25: 0.025 | D25: 25000 | E25: =D25*C25 -> 625
A27: SUB - TOTAL | E27: =SUM(E25) -> 625
A28: IV. MANO DE OBRA
A29: DESCRIPCIÓN | B29: UNIDAD | C29: RENDIMIENTO | D29: JORNAL | E29: VALOR - PARCIAL
A30: Oficial | B30: Día | C30: 60 | D30: 130000 | E30: =D30/C30 -> 2166.6667 | G30: =480/C30 -> 8
A32: SUB - TOTAL | E32: =SUM(E30) -> 2166.6667
A34: TOTAL UNITARIO | E34: =SUM(E12,E22,E27,E32) -> 22333.733
A37: Reparación de antepechos y jardineras | E37: 2.2
A39: ACTIVIDAD: Aplicación de Aqua Block | D39: ITEM
D40: UNIDAD | E40: M2
A41: I. EQUIPOS
A42: DESCRIPCIÓN | B42: UNIDAD | C42: RENDIMIENTO | D42: TARIFA | E42: VALOR - PARCIAL
A43: Herramienta menor | B43: %MO | C43: 0.05 | D43: =E63 -> 2000 | E43: =C43*D43 -> 100
A44: Equipos Freshouse | B44: Día | C44: 0.015 | D44: 25000 | E44: =C44*D44 -> 375
A46: SUB - TOTAL | E46: =SUM(E43:E44) -> 475
A47: II. MATERIALES
A48: DESCRIPCIÓN | B48: UNIDAD | C48: CANTIDAD | D48: PRECIO - UNIT | E48: VALOR - PARCIAL
A49: AquaBlock | B49: CÑ | C49: 0.016 | D49: 574900 | E49: =C49*D49 -> 9198.4 | G49: =D49/32 -> 17965.625 | H49: =19/32 -> 0.59375
A51: Desperdicio 2% | E51: 0
A53: SUB - TOTAL | E53: =SUM(E49:E51) -> 9198.4
A54: III. TRANSPORTE
A55: DESCRIPCIÓN | B55: UNIDAD | C55: RENDIMIENTO | D55: TARIFA | E55: VALOR - PARCIAL
A56: Acarreo LUV | B56: Día | C56: 0.005 | D56: 25000 | E56: =D56*C56 -> 125
A58: SUB - TOTAL | E58: =SUM(E56) -> 125
A59: IV. MANO DE OBRA
A60: DESCRIPCIÓN | B60: UNIDAD | C60: RENDIMIENTO | D60: JORNAL | E60: VALOR - PARCIAL
A61: Oficial | B61: Día | C61: 65 | D61: 130000 | E61: =D61/C61 -> 2000 | G61: =480/C61 -> 7.3846154
A63: SUB - TOTAL | E63: =SUM(E61) -> 2000
A65: TOTAL UNITARIO | E65: =SUM(E46,E53,E58,E63) -> 11798.4
A68: ACTIVIDAD: Nivelación de superficie con Mortero Listo | D68: ITEM
D69: UNIDAD | E69: M2
A70: I. EQUIPOS
A71: DESCRIPCIÓN | B71: UNIDAD | C71: RENDIMIENTO | D71: TARIFA | E71: VALOR - PARCIAL
A72: Herramienta menor | B72: %MO | C72: 0.8 | D72: =E93 -> 4777.7778 | E72: =C72*D72 -> 3822.2222
A73: Equipos Freshouse | B73: Día | C73: 0.02 | D73: 25000 | E73: =C73*D73 -> 500
A75: SUB - TOTAL | E75: =SUM(E72:E73) -> 4322.2222
A76: II. MATERIALES
A77: DESCRIPCIÓN | B77: UNIDAD | C77: CANTIDAD | D77: PRECIO - UNIT | E77: VALOR - PARCIAL
A78: Mortero Listo Impadoc x 40kg | B78: Saco | C78: 0.08 | D78: 42000 | E78: =C78*D78 -> 3360
A79: Acronal | B79: GL | C79: 0.01 | D79: 32500 | E79: =C79*D79 -> 325
A81: Desperdicio 3% | E81: =E78*0.03 -> 100.8
A83: SUB - TOTAL | E83: =SUM(E78:E81) -> 3785.8
A84: III. TRANSPORTE
A85: DESCRIPCIÓN | B85: UNIDAD | C85: RENDIMIENTO | D85: TARIFA | E85: VALOR - PARCIAL
A86: Acarreo | B86: Día | C86: 0.005 | D86: 60000 | E86: =D86*C86 -> 300
A88: SUB - TOTAL | E88: =SUM(E86) -> 300
A89: IV. MANO DE OBRA
A90: DESCRIPCIÓN | B90: UNIDAD | C90: RENDIMIENTO | D90: JORNAL | E90: VALOR - PARCIAL
A91: CUADRILLA 1: 1 Oficial y 1 ayudante | B91: Día | C91: 45 | D91: 215000 | E91: =D91/C91 -> 4777.7778
A93: SUB - TOTAL | E93: =SUM(E91) -> 4777.7778
A95: TOTAL UNITARIO | E95: =SUM(E75,E83,E88,E93) -> 13185.8
A98: ACTIVIDAD: Piintura de alfajías | D98: ITEM
D99: UNIDAD | E99: ML
A100: I. EQUIPOS
A101: DESCRIPCIÓN | B101: UNIDAD | C101: RENDIMIENTO | D101: TARIFA | E101: VALOR - PARCIAL
A102: Herramienta menor | B102: %MO | C102: 0.1 | D102: =E123 -> 3142.8571 | E102: =C102*D102 -> 314.28571
A103: Equipos Freshouse | B103: Día | C103: 0.02 | D103: 25000 | E103: =C103*D103 -> 500
A105: SUB - TOTAL | E105: =SUM(E102:E103) -> 814.28571
A106: II. MATERIALES
A107: DESCRIPCIÓN | B107: UNIDAD | C107: CANTIDAD | D107: PRECIO - UNIT | E107: VALOR - PARCIAL
A108: Koraza Pro 550 | B108: CÑ | C108: 0.004 | D108: 450000 | E108: =C108*D108 -> 1800 | G108: =0.5*0.5*1 -> 0.25
A109: Rodillo 9" | B109: Und | C109: 0.001 | D109: 38000 | E109: =C109*D109 -> 38
A111: Desperdicio 3% | E111: =E108*0.03 -> 54
A113: SUB - TOTAL | E113: =SUM(E108:E111) -> 1892
A114: III. TRANSPORTE
A115: DESCRIPCIÓN | B115: UNIDAD | C115: RENDIMIENTO | D115: TARIFA | E115: VALOR - PARCIAL
A116: Acarreo | B116: Día | C116: 0.001 | D116: 45000 | E116: =D116*C116 -> 45
A118: SUB - TOTAL | E118: =SUM(E116) -> 45
A119: IV. MANO DE OBRA
A120: DESCRIPCIÓN | B120: UNIDAD | C120: RENDIMIENTO | D120: JORNAL | E120: VALOR - PARCIAL
A121: CUADRILLA 1: 1 Oficial y 1 ayudante | B121: Día | C121: 70 | D121: 220000 | E121: =D121/C121 -> 3142.8571 | G121: =480/C121 -> 6.8571429
A123: SUB - TOTAL | E123: =SUM(E121) -> 3142.8571
A125: TOTAL UNITARIO | E125: =SUM(E105,E113,E118,E123) -> 5894.1429
A128: ACTIVIDAD: Suministro y Aplicación de Pintura para interiores | D128: ITEM | E128: 3.5
D129: UNIDAD | E129: M2
A130: I. EQUIPOS
A131: DESCRIPCIÓN | B131: UNIDAD | C131: RENDIMIENTO | D131: TARIFA | E131: VALOR - PARCIAL
A132: Herramienta menor | B132: %MO | C132: 0.1 | D132: =E154 -> 2933.3333 | E132: =C132*D132 -> 293.33333
A133: Equipos Freshouse | B133: Día | C133: 0.02 | D133: 25000 | E133: =C133*D133 -> 500
A135: SUB - TOTAL | E135: =SUM(E132:E133) -> 793.33333
A136: II. MATERIALES
A137: DESCRIPCIÓN | B137: UNIDAD | C137: CANTIDAD | D137: PRECIO - UNIT | E137: VALOR - PARCIAL
...

Sheet APU V
A1: CONDOMINIO PARQUE RESIDENCIAL LOS CEDROS
A3: Recorrido General de Cubiertas existentes sobre los tres bloques de apartamentos. Se estima una reposicion total de al menos el 25% de la cubierta existente.
A5: ACTIVIDAD: Suministro e instalación de teja de fibrocemento | D5: ITEM | E5: 4.1
D6: UNIDAD | E6: M2
A7: I. EQUIPOS
A8: DESCRIPCIÓN | B8: UNIDAD | C8: RENDIMIENTO | D8: TARIFA | E8: VALOR - PARCIAL
A9: Herramienta menor | B9: %MO | C9: 0.1 | D9: =E30 -> 7333.3333 | E9: =C9*D9 -> 733.33333
A11: SUB - TOTAL | E11: =SUM(E9:E9) -> 733.33333
A12: II. MATERIALES
A13: DESCRIPCIÓN | B13: UNIDAD | C13: CANTIDAD | D13: PRECIO - UNIT | E13: VALOR - PARCIAL
A14: Teja de fibrocemento | B14: Und | C14: 0.5 | D14: 35000 | E14: =C14*D14 -> 17500
A15: Amarras | B15: Und | C15: 4 | D15: 800 | E15: =C15*D15 -> 3200
A16: Ganchos | B16: Und | C16: 2 | D16: 1500 | E16: =C16*D16 -> 3000
A18: Desperdicio 2% | E18: =SUM(E14:E14)*0.02 -> 350
A20: SUB - TOTAL | E20: =SUM(E14:E18) -> 24050
A21: III. TRANSPORTE
A22: DESCRIPCIÓN | B22: UNIDAD | C22: RENDIMIENTO | D22: TARIFA | E22: VALOR - PARCIAL
A23: Acarreo LUV | B23: Día | C23: 0.025 | D23: 60000 | E23: =D23*C23 -> 1500
A25: SUB - TOTAL | E25: =SUM(E23) -> 1500
A26: IV. MANO DE OBRA
A27: DESCRIPCIÓN | B27: UNIDAD | C27: RENDIMIENTO | D27: JORNAL | E27: VALOR - PARCIAL
A28: CUADRILLA 1: 1 Oficial y 1 ayudante | B28: Día | C28: 30 | D28: 220000 | E28: =D28/C28 -> 7333.3333
A30: SUB - TOTAL | E30: =SUM(E28) -> 7333.3333
A32: TOTAL UNITARIO | E32: =SUM(E11,E20,E25,E30) -> 33616.667
A35: ACTIVIDAD: Desmonte de teja de fibrocemento | D35: ITEM | E35: 4.1
D36: UNIDAD | E36: M2
A37: I. EQUIPOS
A38: DESCRIPCIÓN | B38: UNIDAD | C38: RENDIMIENTO | D38: TARIFA | E38: VALOR - PARCIAL
A39: Herramienta menor | B39: %MO | C39: 0.05 | D39: =E57 -> 7333.3333 | E39: =C39*D39 -> 366.66667
A41: SUB - TOTAL | E41: =SUM(E39:E39) -> 366.66667
A42: II. MATERIALES
A43: DESCRIPCIÓN | B43: UNIDAD | C43: CANTIDAD | D43: PRECIO - UNIT | E43: VALOR - PARCIAL
A45: Desperdicio 2% | E45: 0
A47: SUB - TOTAL | E47: =SUM(E44:E45) -> 0
A48: III. TRANSPORTE
A49: DESCRIPCIÓN | B49: UNIDAD | C49: RENDIMIENTO | D49: TARIFA | E49: VALOR - PARCIAL
A50: Acarreo LUV | B50: Día | C50: 0 | D50: 60000 | E50: =D50*C50 -> 0
A52: SUB - TOTAL | E52: =SUM(E50) -> 0
A53: IV. MANO DE OBRA
A54: DESCRIPCIÓN | B54: UNIDAD | C54: RENDIMIENTO | D54: JORNAL | E54: VALOR - PARCIAL
A55: CUADRILLA 1: 1 Oficial y 1 ayudante | B55: Día | C55: 30 | D55: 220000 | E55: =D55/C55 -> 7333.3333
A57: SUB - TOTAL | E57: =SUM(E55) -> 7333.3333
A59: TOTAL UNITARIO | E59: =SUM(E41,E47,E52,E57) -> 7700
A62: ACTIVIDAD: Impermeabilización de viga canal | D62: ITEM | E62: 4.1
D63: UNIDAD | E63: M2
A64: I. EQUIPOS
A65: DESCRIPCIÓN | B65: UNIDAD | C65: RENDIMIENTO | D65: TARIFA | E65: VALOR - PARCIAL
A66: Herramienta menor | B66: %MO | C66: 0.8 | D66: =E88 -> 3714.2857 | E66: =C66*D66 -> 2971.4286
A67: Equipo Hidrolavadora | B67: Día | C67: 0.01 | D67: 15000 | E67: =C67*D67 -> 150
A69: SUB - TOTAL | E69: =SUM(E66:E67) -> 3121.4286
A70: II. MATERIALES
A71: DESCRIPCIÓN | B71: UNIDAD | C71: CANTIDAD | D71: PRECIO - UNIT | E71: VALOR - PARCIAL
A72: Emulsión asfáltica x 18kg | B72: KG | C72: 0.025 | D72: 160000 | E72: =C72*D72 -> 4000
A73: Manto de refuerzo - Sika Felp | B73: M2 | C73: 0.015 | D73: 100000 | E73: =C73*D73 -> 1500
A74: Hipoclorito | B74: GL | C74: 0.05 | D74: 35000 | E74: =C74*D74 -> 1750
A76: Desperdicio 3% | E76: =E72*0.03 -> 120
A78: SUB - TOTAL | E78: =SUM(E72:E76) -> 7370
A79: III. TRANSPORTE
A80: DESCRIPCIÓN | B80: UNIDAD | C80: RENDIMIENTO | D80: TARIFA | E80: VALOR - PARCIAL
A81: Acarreo | B81: Día | C81: 0.025 | D81: 25000 | E81: =D81*C81 -> 625
A83: SUB - TOTAL | E83: =SUM(E81) -> 625
A84: IV. MANO DE OBRA
A85: DESCRIPCIÓN | B85: UNIDAD | C85: RENDIMIENTO | D85: JORNAL | E85: VALOR - PARCIAL
A86: Oficial | B86: Día | C86: 35 | D86: 130000 | E86: =D86/C86 -> 3714.2857
A88: SUB - TOTAL | E88: =SUM(E86) -> 3714.2857
A90: TOTAL UNITARIO | E90: =SUM(E69,E78,E83,E88) -> 14830.714
A93: ACTIVIDAD: Suministro y Aplicación de Pintuco Fill | D93: ITEM | E93: 4.1
D94: UNIDAD | E94: M2
A95: I. EQUIPOS
A96: DESCRIPCIÓN | B96: UNIDAD | C96: RENDIMIENTO | D96: TARIFA | E96: VALOR - PARCIAL
A97: Herramienta menor | B97: %MO | C97: 0.1 | D97: =E120 -> 2888.8889 | E97: =C97*D97 -> 288.88889
A98: Equipos Freshouse | B98: Día | C98: 0.015 | D98: 25000 | E98: =C98*D98 -> 375
A100: SUB - TOTAL | E100: =SUM(E97:E98) -> 663.88889
A101: II. MATERIALES
A102: DESCRIPCIÓN | B102: UNIDAD | C102: CANTIDAD | D102: PRECIO - UNIT | E102: VALOR - PARCIAL
A103: Pintuco Fill | B103: CÑ | C103: 0.04 | D103: 250000 | E103: =C103*D103 -> 10000
A104: Rodillo 9" | B104: Und | C104: 0.001 | D104: 38000 | E104: =C104*D104 -> 38
A105: Brocha | B105: Und | C105: 0.001 | D105: 10000 | E105: =C105*D105 -> 10
A108: Desperdicio 2% | E108: =SUM(E103:E107)*0.05 -> 502.4
A110: SUB - TOTAL | E110: =SUM(E103:E108) -> 10550.4
A111: III. TRANSPORTE
A112: DESCRIPCIÓN | B112: UNIDAD | C112: RENDIMIENTO | D112: TARIFA | E112: VALOR - PARCIAL
A113: Acarreo | B113: Día | C113: 0.025 | D113: 25000 | E113: =D113*C113 -> 625
A115: SUB - TOTAL | E115: =SUM(E113) -> 625
A116: IV. MANO DE OBRA
A117: DESCRIPCIÓN | B117: UNIDAD | C117: RENDIMIENTO | D117: JORNAL | E117: VALOR - PARCIAL
A118: Oficial | B118: Día | C118: 45 | D118: 130000 | E118: =D118/C118 -> 2888.8889
A120: SUB - TOTAL | E120: =SUM(E118) -> 2888.8889
A122: TOTAL UNITARIO | E122: =SUM(E100,E110,E115,E120) -> 14728.178
A125: ACTIVIDAD: Aplicación de boquilla en piso exterior | D125: ITEM | E125: 4.2
D126: UNIDAD | E126: M2
A127: I. EQUIPOS
A128: DESCRIPCIÓN | B128: UNIDAD | C128: RENDIMIENTO | D128: TARIFA | E128: VALOR - PARCIAL
A129: Herramienta menor | B129: %MO | C129: 0.1 | D129: =E149 -> 3250 | E129: =C129*D129 -> 325
A131: SUB - TOTAL | E131: =SUM(E129:E129) -> 325
A132: II. MATERIALES
A133: DESCRIPCIÓN | B133: UNIDAD | C133: CANTIDAD | D133: PRECIO - UNIT | E133: VALOR - PARCIAL
A134: Boquilla | B134: M2 | C134: 0.2 | D134: 28000 | E134: =C134*D134 -> 5600
A135: Separadores | B135: GLB | C135: 0.1 | D135: 15000 | E135: =C135*D135 -> 1500
A137: Desperdicio 5% | E137: =(E134+E135)*0.05 -> 355
...

Sheet RESUMEN APU
A1: CONDOMINIO PARQUE RESIDENCIAL LOS CEDROS
A3: ITEM | B3: DESCRIPCIÓN | D3: 0.05 | E3: 0.1
A4: 1.1 | B4: Campamento de Obra | C4: 4900000 | D4: =C4*1.05 -> 5145000 | E4: =C4*1.1 -> 5390000
A6: 1.2 | B6: Señalización de Obra | C6: 550000 | D6: =C6*1.05 -> 577500 | E6: =C6*1.1 -> 605000
A8: ITEM | B8: DESCRIPCIÓN | C8: VALOR | D8: 0.05 | E8: 0.1
A9: 2.1 | B9: Lavado de superficie | C9: ='APU II'!E33 -> 3021.6667 | D9: =C9*1.05 -> 3172.75 | E9: =C9*1.1 -> 3323.8333
A11: 2.2 | B11: Retiro y Reemplazo de Graniplast Deteriorado | C11: =SUM(C12:C15) -> 53794.451 | D11: =SUM(D12:D14) -> 56484.173 | E11: =SUM(E12:E14) -> 62132.59
A12: 2.1.1 | B12: Inspección de superficie incluye rasqueteado | C12: ='APU II'!E62 -> 1142.3077 | D12: =C12*1.05 -> 1199.4231 | E12: =D12*1.1 -> 1319.3654
A13: 2.1.2 | B13: Nivelación de superficie con Mortero Listo | C13: ='APU II'!E92 -> 16508.143 | D13: =C13*1.05 -> 17333.55 | E13: =D13*1.1 -> 19066.905
A14: 2.1.3 | B14: Aplicación de Graniplast | C14: ='APU II'!E122 -> 36144 | D14: =C14*1.05 -> 37951.2 | E14: =D14*1.1 -> 41746.32
C15: 0
A16: 2.3 | B16: Reposicion de Mortero en mal estado | C16: ='APU II'!E154 -> 34908.75 | D16: =C16*1.05 -> 36654.188 | E16: =C16*1.1 -> 38399.625
B17: Aplicación de revoque impermeabilizado | C17: 0 | D17: =C17*1.05 -> 0 | E17: =C17*1.1 -> 0
A19: 2.4 | B19: Retiro y Reemplazo de Superboard | C19: =SUM(C20:C21) -> 88306.944 | D19: =SUM(D20:D21) -> 92722.292 | E19: =SUM(E20:E21) -> 97137.639
A20: 2.3.1 | B20: Remoción de lámina superboard | C20: ='APU II'!E185 -> 13944.444 | D20: =C20*1.05 -> 14641.667 | E20: =C20*1.1 -> 15338.889
A21: 2.3.2 | B21: Restructuración e Instalación de lámina de fibrocemento | C21: ='APU II'!E218 -> 74362.5 | D21: =C21*1.05 -> 78080.625 | E21: =C21*1.1 -> 81798.75
A23: 2.5 | B23: Retiro y Reemplazo de lamina Drywall | C23: =SUM(C24:C25) -> 54400 | D23: =SUM(D24:D25) -> 57120 | E23: =SUM(E24:E25) -> 59840
A24: 2.3.1 | B24: Remoción de lámina de panel yeso | C24: 7200 | D24: =C24*1.05 -> 7560 | E24: =C24*1.1 -> 7920
A25: 2.3.2 | B25: Restructuración e Instalación de lámina de fibrocemento | C25: ='APU II'!E249 -> 47200 | D25: =C25*1.05 -> 49560 | E25: =C25*1.1 -> 51920
A27: ITEM | B27: DESCRIPCIÓN | D27: 0.05 | E27: 0.1
A28: 3.1 | B28: Suministro y Aplicación de Pintura para exteriores | C28: =SUM(C29:C29) -> 12883.733 | D28: =SUM(D29:D29) -> 13527.92 | E28: =SUM(E29:E29) -> 14172.107
B29: Suministro y Aplicación de Pintura para exteriores | C29: ='APU III'!E34 -> 12883.733 | D29: =C29*1.05 -> 13527.92 | E29: =C29*1.1 -> 14172.107
A31: 3.2 | B31: Suministro y Aplicación de Pintura incluye tratamiento con Aqua Block | C31: =SUM(C32:C33) -> 37867.933 | D31: =SUM(D32:D33) -> 39761.33 | E31: =SUM(E32:E33) -> 41654.727
B32: Reparación de antepechos y aplicación de Aqua Block | C32: ='APU IV'!E65+'APU IV'!E95 -> 24984.2 | D32: =C32*1.05 -> 26233.41 | E32: =C32*1.1 -> 27482.62
B33: Suministro y Aplicación de Pintura para exteriores | C33: =C29 -> 12883.733 | D33: =C33*1.05 -> 13527.92 | E33: =C33*1.1 -> 14172.107
A35: 3.3 | B35: Suministro y Aplicación de Pintura incluye reconstrucción de pendiente | C35: =SUM(C36:C37) -> 26069.533 | D35: =SUM(D36:D37) -> 27373.01 | E35: =SUM(E36:E37) -> 28676.487
B36: Reconstrucción de pendiente en volumenes | C36: ='APU IV'!E95 -> 13185.8 | D36: =C36*1.05 -> 13845.09 | E36: =C36*1.1 -> 14504.38
B37: Suministro y Aplicación de Pintura para exteriores | C37: =C29 -> 12883.733 | D37: =C37*1.05 -> 13527.92 | E37: =C37*1.1 -> 14172.107
A39: 3.4 | B39: Suministro y Aplicación de Pintura para exteriores alfajías | C39: ='APU IV'!E125 -> 5894.1429 | D39: =C39*1.05 -> 6188.85 | E39: =C39*1.1 -> 6483.5571
A41: 3.5 | B41: Suministro y Aplicación de Pintura para interiores | C41: =SUM(C42:C42) -> 10414.567 | D41: =SUM(D42:D42) -> 10935.295 | E41: =SUM(E42:E42) -> 11456.023
B42: Suministro y Aplicación de Pintura para interiores | C42: ='APU IV'!E156 -> 10414.567 | D42: =C42*1.05 -> 10935.295 | E42: =C42*1.1 -> 11456.023
A44: 3.6 | B44: Suministro y Aplicación de Pintura para puertas | C44: =SUM(C45:C45) -> 80998.75 | D44: =SUM(D45:D45) -> 85048.688 | E44: =SUM(E45:E45) -> 89098.625
B45: Suministro y Aplicación de Pintura para puertas | C45: ='APU IV'!E188 -> 80998.75 | D45: =C45*1.05 -> 85048.688 | E45: =C45*1.1 -> 89098.625
A47: 3.7 | B47: Suministro y Aplicación de Pintura en barandas | C47: =SUM(C48:C48) -> 10066.964 | D47: =SUM(D48:D48) -> 10570.313 | E47: =SUM(E48:E48) -> 11073.661
B48: Suministro y Aplicación de Pintura en barandas | C48: ='APU IV'!E220 -> 10066.964 | D48: =C48*1.05 -> 10570.313 | E48: =C48*1.1 -> 11073.661
A50: 3.8 | B50: Suministro y Aplicación de Pintura estructuras de parqueadero | C50: =SUM(C51:C51) -> 18001.25 | D50: =SUM(D51:D51) -> 18901.312 | E50: =SUM(E51:E51) -> 19801.375
B51: Suministro y Aplicación de Pintura estructuras de parqueadero | C51: ='APU IV'!E252 -> 18001.25 | D51: =C51*1.05 -> 18901.312 | E51: =C51*1.1 -> 19801.375
A53: 3.9 | B53: Suministro y Aplicación de Pintucofill | C53: =SUM(C54:C54) -> 21726.428 | D53: =SUM(D54:D54) -> 22812.749 | E53: =SUM(E54:E54) -> 23899.071
B54: Suministro y Aplicación de Pintura en barandas | C54: ='APU IV'!E284 -> 21726.428 | D54: =C54*1.05 -> 22812.749 | E54: =C54*1.1 -> 23899.071
A56: ITEM | B56: DESCRIPCIÓN | C56: VALOR | D56: 0.05 | E56: 0.1
A57: 4.1 | B57: Recorrido General de Cubiertas | C57: =SUM(C58:C63) -> 83175.559 | D57: =SUM(D58:D63) -> 87334.337 | E57: =SUM(E58:E63) -> 96067.77
A58: 4.1.1 | B58: Retiro de tejas en mal estado | C58: ='APU V'!E59 -> 7700 | D58: =C58*1.05 -> 8085 | E58: =D58*1.1 -> 8893.5
A59: 4.1.2 | B59: Suministro e instalación de tejas de fibrocemento | C59: ='APU V'!E32 -> 33616.667 | D59: =C59*1.05 -> 35297.5 | E59: =D59*1.1 -> 38827.25
A60: 4.1.3 | B60: Sellamiento de amarras | C60: 4400 | D60: =C60*1.05 -> 4620 | E60: =D60*1.1 -> 5082
A61: 4.1.4 | B61: Reposición de Flanches en lamina | C61: 7900 | D61: =C61*1.05 -> 8295 | E61: =D61*1.1 -> 9124.5
A62: 4.1.5 | B62: Lavado e impermeabilización de Viga Canal | C62: ='APU V'!E90 -> 14830.714 | D62: =C62*1.05 -> 15572.25 | E62: =D62*1.1 -> 17129.475
A63: 4.1.6 | B63: Aplicación de Pintuco Fill en teja de fibrocemento | C63: ='APU V'!E122 -> 14728.178 | D63: =C63*1.05 -> 15464.587 | E63: =D63*1.1 -> 17011.045
A65: 4.2 | B65: Sellado Perimetral de enchape en terraza del gimnasio | C65: =SUM(C66:C67) -> 18616.857 | D65: =SUM(D66:D67) -> 19547.7 | E65: =SUM(E66:E67) -> 21502.47
A66: 4.2.1 | B66: Aplicación de boquilla en piso exterior | C66: ='APU V'!E151 -> 12155 | D66: =C66*1.05 -> 12762.75 | E66: =D66*1.1 -> 14039.025
A67: 4.2.2 | B67: Aplicación de sello perimetral | C67: ='APU V'!E179 -> 6461.8571 | D67: =C67*1.05 -> 6784.95 | E67: =D67*1.1 -> 7463.445
A69: 4.3 | B69: Sellado Perimetral de ventaneria | C69: =SUM(C70:C70) -> 7543.3333 | D69: =SUM(D70:D70) -> 7920.5 | E69: =SUM(E70:E70) -> 8297.6667
A70: 4.3 | B70: Sellado Perimetral de ventaneria | C70: ='APU V'!E209 -> 7543.3333 | D70: =C70*1.05 -> 7920.5 | E70: =C70*1.1 -> 8297.6667
A72: 4.4 | B72: Suministro e Instalacion de Cortagoteras en Balcones y Accesos a los bloques de aptos | C72: =SUM(C73:C74) -> 40125 | D72: =SUM(D73:D74) -> 42131.25 | E72: =SUM(E73:E74) -> 44137.5
A73: 4.4.1 | B73: Remoción de perfil existente | C73: ='APU V'!E239 -> 4475 | D73: =C73*1.05 -> 4698.75 | E73: =C73*1.1 -> 4922.5
A74: 4.4.2 | B74: Instalación de cortagotera | C74: ='APU V'!E271 -> 35650 | D74: =C74*1.05 -> 37432.5 | E74: =C74*1.1 -> 39215
A76: 4.5 | B76: Reparacion de morteros en cuchillas de cubierta-(30% DEL TOTAL) | C76: =SUM(C77:C77) -> 34908.75 | D76: =SUM(D77:D77) -> 36654.188 | E76: =SUM(E77:E77) -> 38399.625
B77: Aplicación de revoque impermeabilizado | C77: =C16 -> 34908.75 | D77: =C77*1.05 -> 36654.188 | E77: =C77*1.1 -> 38399.625
A79: 4.6 | B79: Suministro e Instalacion de Alfajias en lamina sobre muros perimetrales y medianeros en las cubiertas | C79: =SUM(C80:C80) -> 115600 | D79: =SUM(D80:D80) -> 121380 | E79: =SUM(E80:E80) -> 127160
B80: Suministro e Instalacion de Alfajias en lamina | C80: 115600 | D80: =C80*1.05 -> 121380 | E80: =C80*1.1 -> 127160
A82: 4.6 | B82: Aseo General y Retiro de Escombros y Sobrantes | C82: 2800000 | D82: =C82*1.05 -> 2940000 | E82: =C82*1.1 -> 3080000

Sheet COTIZACIÓN
A1: CONDOMINIO PARQUE RESIDENCIAL LOS CEDROS-ARMENIA-Quindío
A2: Cuadro General de Actividades, Unidades de Medida, Cantidades y Precios Unitarios
A3: ANEXO 01-OPCION 2
A4: Proponente: | D4: Levanto Informacion: | F4: Ing. Carlos Alberto Agudelo Restrepo
A5: Interventor: Ing. Luis Fernando Márquez Jaramillo | F5: Arq. Maria Fernanda Morales Palacio
A6: Ubicación Proyecto: Calle 50 Norte # 15-01 | D6: Fecha: Febrero de 2025 | F6: Sra Maria del Pilar Rubio L. Administradora
A7: ACTIVIDADES EN LOS BLOQUES DE APARTAMENTOS y AREAS COMUNES DE LOS MISMOS
A8: Capitulo | B8: Items | C8: Descripcion de Actividad | D8: Unidad | E8: Cantidad | F8: Vr Unitario | G8: Vr Total
A9: 1 | C9: PRELIMINARES | G9: =+G10+G11 -> 5722500
B10: 1.1 | C10: Campamento de Obra | D10: Gbl | E10: 1 | F10: ='RESUMEN APU'!D4 -> 5145000 | G10: =+E10*F10 -> 5145000
B11: 1.2 | C11: Señalizacion y Seguridad de la Obra | D11: Gbl | E11: 1 | F11: ='RESUMEN APU'!D6 -> 577500 | G11: =+E11*F11 -> 577500
A12: 2 | C12: PREPARACION DE SUPERFICIES | G12: =+G13+G14+G15+G16+G17 -> 1.1184701e+08
B13: 2.1 | C13: Lavado General de Superficies a Intervenir | D13: M2 | E13: 7304.6725 | F13: ='RESUMEN APU'!D9 -> 3172.75 | G13: =+E13*F13 -> 23175900
B14: 2.2 | C14: Retiro y Reemplazo de Graniplast Deteriorado en fachadas de las tres torres (26% DEL TOTAL APROX) | D14: M2 | E14: 1205.1154 | F14: ='RESUMEN APU'!D11 -> 56484.173 | G14: =+E14*F14 -> 68069946
B15: 2.3 | C15: Reposicion de Mortero en mal estado en fachadas de las tres torres | D15: M2 | E15: 90 | F15: ='RESUMEN APU'!D16 -> 36654.188 | G15: =+E15*F15 -> 3298876.9
B16: 2.4 | C16: Retiro y Reemplazo de Superboard en mal estado en fachadas de las tres torres | D16: M2 | E16: 125 | F16: ='RESUMEN APU'!D19 -> 92722.292 | G16: =+E16*F16 -> 11590286
B17: 2.5 | C17: Retiro y Reemplazo de Drywall en mal estado en cielos rasos de fachadas | D17: M2 | E17: 100 | F17: ='RESUMEN APU'!D23 -> 57120 | G17: =+E17*F17 -> 5712000
A18: 3 | C18: ACABADO Y PINTURA | G18: =+G19+G24+G26 -> 1.7124465e+08
B19: PINTURA PARA EXTERIORES-TIPO KORAZA | G19: =+G20+G21+G22+G23 -> 81697917
B20: 3.1 | C20: Suministro y Aplicación de Pintura para exteriores, tipo Koraza, sobre superficies de Fachadas y Muros Externos de los bloques de apartamentos | D20: M2 | E20: 4629.4765 | F20: ='RESUMEN APU'!D28 -> 13527.92 | G20: =+E20*F20 -> 62627188
B21: 3.2 | C21: Suministro y Aplicación de Pintura para exteriores tipo Koraza, en antepechos de terrazas en los primeros pisos de los bloques y en jardineras | D21: M2 | E21: 107.975 | F21: ='RESUMEN APU'!D31 -> 39761.33 | G21: =+E21*F21 -> 4293229.6
B22: 3.3 | C22: Suministro y Aplicación de Pintura para exteriores, tipo Koraza, en elementos volumetricos de superboard en las fachadas | D22: M2 | E22: 455.3 | F22: ='RESUMEN APU'!D35 -> 27373.01 | G22: =+E22*F22 -> 12462931
B23: 3.4 | C23: Suministro y Aplicación de Pintura para exteriores, tipo koraza, color gris basalto, sobre alfajias de escaleras de acceso a los bloques y de areas comunes externas. | D23: ML | E23: 373.99 | F23: ='RESUMEN APU'!D39 -> 6188.85 | G23: =+E23*F23 -> 2314568
B24: PINTURA PARA INTERIORES TIPO VINILO | G24: =+G25 -> 23594430
B25: 3.5 | C25: Suministro y Aplicación de Pintura tipo Vinilo en areas comunes internas de los bloques de aptos: paredes y cielos rasos | D25: M2 | E25: 2157.64 | F25: ='RESUMEN APU'!D41 -> 10935.295 | G25: =+E25*F25 -> 23594430
B26: PINTURA ESMALTE TIPO 3 EN 1 | G26: =+G27+G28+G29+G30 -> 65952302
B27: 3.6 | C27: Suministro y Aplicación de Pintura tipo 3 en 1, en puertas de los apartamentos (estan incluidas las de los exteriores, porteria-motobombas) | D27: UN | E27: 92 | F27: ='RESUMEN APU'!D44 -> 85048.688 | G27: =+E27*F27 -> 7824479.2
B28: 3.7 | C28: Suministro y Aplicación de Pintura para Barandas Metalicas en areas exteriores: gimnasio, pasillos, cuarto de acueducto, piscina, circulacion entre bloques, etc. | D28: ML | E28: 344.25 | F28: ='RESUMEN APU'!D47 -> 10570.313 | G28: =+E28*F28 -> 3638830.1
B29: 3.8 | C29: Suministro y Aplicación de Pintura tipo 3 en 1 en la totalidad de las estructuras metalicas de los parqueaderos externos | D29: M2 | E29: 1306.25 | F29: ='RESUMEN APU'!D50 -> 18901.312 | G29: =+E29*F29 -> 24689839
B30: 3.9 | C30: Suministro y Aplicación de Pintuco Fill sobre las cubiertas de los parqueaderos | D30: M2 | E30: 1306.25 | F30: ='RESUMEN APU'!D53 -> 22812.749 | G30: =+E30*F30 -> 29799154
A31: 4 | C31: TRATAMIENTOS ESPECIALES CONTRA HUMEDADES | G31: =+G32+G33+G34+G35+G36+G37 -> 2.5331236e+08
B32: 4.1 | C32: Cambio Total de Cubiertas | D32: M2 | E32: 1678.12 | F32: ='RESUMEN APU'!D57 -> 87334.337 | G32: =+E32*F32 -> 1.465575e+08
B33: 4.2 | C33: Sellado Perimetral de enchape en terraza del gimnasio | D33: ML | E33: 0 | F33: ='RESUMEN APU'!D65 -> 19547.7 | G33: =+E33*F33 -> 0
B34: 4.3 | C34: Retiro y Reposicion de sello perimetral en elementos vidriados de los bloque de apartamentos (30% DEL TOTAL) | D34: ML | E34: 817.994 | F34: ='RESUMEN APU'!D69 -> 7920.5 | G34: =+E34*F34 -> 6478921.5
B35: 4.4 | C35: Suministro e Instalacion de Cortagoteras en Balcones y Accesos a los bloques de aptos | D35: ML | E35: 1055.3 | F35: ='RESUMEN APU'!D72 -> 42131.25 | G35: =+E35*F35 -> 44461108
B36: 4.5 | C36: Reparacion de morteros en cuchillas de cubierta-(30% DEL TOTAL) | D36: M2 | E36: 290.8665 | F36: ='RESUMEN APU'!D76 -> 36654.188 | G36: =+E36*F36 -> 10661475
B37: 4.6 | C37: Suministro e Instalacion de Alfajias en lamina sobre muros perimetrales y medianeros en las cubiertas | D37: ML | E37: 372 | F37: ='RESUMEN APU'!D79 -> 121380 | G37: =+E37*F37 -> 45153360
A38: 5 | C38: ASEO GENERAL DE OBRA Y RETIRO DE ESCOMBROS | G38: =+G39 -> 0
B39: 5.1 | C39: Aseo General y Retiro de Escombros y Sobrantes | D39: GBL | E39: 0.8 | G39: =+E39*F39 -> 0
D40: TOTAL COSTO DIRECTO | G40: =+G9+G12+G18+G31+G38 -> 5.4212652e+08
D41: ADMINISTRACION | F41: 0.08 | G41: =+$G$40*F41 -> 43370122
D42: IMPREVISTOS | F42: 0.03 | G42: =+$G$40*F42 -> 16263796
D43: UTILIDAD | F43: 0.05 | G43: =+$G$40*F43 -> 27106326
D44: IVA/U | F44: 0.19 | G44: =+G43*F44 -> 5150201.9
D45: COSTO TOTAL | G45: =+G40+G41+G42+G43+G44 -> 6.3401697e+08

Sheet COTIZACIÓN valores actualizados
A1: CONDOMINIO PARQUE RESIDENCIAL LOS CEDROS-ARMENIA-Quindío
A2: Cuadro General de Actividades, Unidades de Medida, Cantidades y Precios Unitarios
A3: ANEXO 01-OPCION 2
A4: Proponente: | D4: Levanto Informacion: | F4: Ing. Carlos Alberto Agudelo Restrepo
A5: Interventor: Ing. Luis Fernando Márquez Jaramillo | F5: Arq. Maria Fernanda Morales Palacio
A6: Ubicación Proyecto: Calle 50 Norte # 15-01 | D6: Fecha: Febrero de 2025 | F6: Sra Maria del Pilar Rubio L. Administradora
A7: ACTIVIDADES EN LOS BLOQUES DE APARTAMENTOS Y AREAS COMUNES DE LOS MISMOS
A8: Capitulo | B8: Items | C8: Descripcion de Actividad | D8: Unidad | E8: Cantidad | F8: Vr Unitario | G8: Vr Total
A9: 1 | C9: PRELIMINARES | G9: =+G10+G11 -> 1800000
B10: 1.1 | C10: Campamento de Obra | D10: Gbl | E10: 1 | F10: 1500000 | G10: =+E10*F10 -> 1500000 | H10: X
B11: 1.2 | C11: Señalizacion y Seguridad de la Obra | D11: Gbl | E11: 1 | F11: 300000 | G11: =+E11*F11 -> 300000 | H11: X
A12: 2 | C12: PREPARACION DE SUPERFICIES | G12: =+G13+G14+G15+G16+G17 -> 95735145
B13: 2.1 | C13: Lavado General de Superficies a Intervenir | D13: M2 | E13: 7304.6725 | F13: 3200 | G13: =+E13*F13 -> 23374952 | H13: X
B14: 2.2 | C14: Retiro y Reemplazo de Graniplast Deteriorado en fachadas de las tres torres (26% DEL TOTAL APROX) | D14: M2 | E14: 1205.1154 | F14: 45000 | G14: =+E14*F14 -> 54230193 | H14: X
B15: 2.3 | C15: Reposicion de Mortero en mal estado en fachadas de las tres torres | D15: M2 | E15: 90 | F15: 52000 | G15: =+E15*F15 -> 4680000
B16: 2.4 | C16: Retiro y Reemplazo de Superboard en mal estado en fachadas de las tres torres | D16: M2 | E16: 125 | F16: 74000 | G16: =+E16*F16 -> 9250000 | I16: 5000000
B17: 2.5 | C17: Retiro y Reemplazo de Drywall en mal estado en cielos rasos de fachadas | D17: M2 | E17: 100 | F17: 42000 | G17: =+E17*F17 -> 4200000
A18: 3 | C18: ACABADO Y PINTURA | G18: =+G19+G24+G26 -> 2.1459437e+08
B19: PINTURA PARA EXTERIORES-TIPO KORAZA | G19: =+G20+G21+G22+G23 -> 99452618
B20: 3.1 | C20: Suministro y Aplicación de Pintura para exteriores, tipo Koraza, sobre superficies de Fachadas y Muros Externos de los bloques de apartamentos | D20: M2 | E20: 4629.4765 | F20: 17500 | G20: =+E20*F20 -> 81015839
B21: 3.2 | C21: Suministro y Aplicación de Pintura para exteriores tipo Koraza, en antepechos de terrazas en los primeros pisos de los bloques y en jardineras | D21: M2 | E21: 107.975 | F21: 28000 | G21: =+E21*F21 -> 3023300
B22: 3.3 | C22: Suministro y Aplicación de Pintura para exteriores, tipo Koraza, en elementos volumetricos de superboard en las fachadas | D22: M2 | E22: 455.3 | F22: 27200 | G22: =+E22*F22 -> 12384160
B23: 3.4 | C23: Suministro y Aplicación de Pintura para exteriores, tipo koraza, color gris basalto, sobre alfajias de escaleras de acceso a los bloques y de areas comunes externas. | D23: ML | E23: 373.99 | F23: 8100 | G23: =+E23*F23 -> 3029319
B24: PINTURA PARA INTERIORES TIPO VINILO | G24: =+G25 -> 25891680
B25: 3.5 | C25: Suministro y Aplicación de Pintura tipo Vinilo en areas comunes internas de los bloques de aptos: paredes y cielos rasos | D25: M2 | E25: 2157.64 | F25: 12000 | G25: =+E25*F25 -> 25891680
B26: PINTURA ESMALTE TIPO 3 EN 1 | G26: =+G27+G28+G29+G30 -> 89250075
B27: 3.6 | C27: Suministro y Aplicación de Pintura tipo 3 en 1, en puertas de los apartamentos (estan incluidas las de los exteriores, porteria-motobombas) | D27: UN | E27: 92 | F27: 121000 | G27: =+E27*F27 -> 11132000
B28: 3.7 | C28: Suministro y Aplicación de Pintura para Barandas Metalicas en areas exteriores: gimnasio, pasillos, cuarto de acueducto, piscina, circulacion entre bloques, etc. | D28: ML | E28: 344.25 | F28: 22400 | G28: =+E28*F28 -> 7711200
B29: 3.8 | C29: Suministro y Aplicación de Pintura tipo 3 en 1 en la totalidad de las estructuras metalicas de los parqueaderos externos | D29: M2 | E29: 1306.25 | F29: 24300 | G29: =+E29*F29 -> 31741875
B30: 3.9 | C30: Suministro y Aplicación de Pintuco Fill sobre las cubiertas de los parqueaderos | D30: M2 | E30: 1306.25 | F30: 29600 | G30: =+E30*F30 -> 38665000
A31: 4 | C31: TRATAMIENTOS ESPECIALES CONTRA HUMEDADES | G31: =+G32+G33+G34+G35+G36+G37 -> 2.8155701e+08
B32: 4.1 | C32: Cambio Total de Cubiertas | D32: M2 | E32: 1678.12 | F32: 119000 | G32: =+E32*F32 -> 199696280
B33: 4.2 | C33: Sellado Perimetral de enchape en terraza del gimnasio | D33: ML | E33: 0 | F33: 11300 | G33: =+E33*F33 -> 0
B34: 4.3 | C34: Retiro y Reposicion de sello perimetral en elementos vidriados de los bloque de apartamentos (30% DEL TOTAL) | D34: ML | E34: 817.994 | F34: 5200 | G34: =+E34*F34 -> 4253568.8
B35: 4.4 | C35: Suministro e Instalacion de Cortagoteras en Balcones y Accesos a los bloques de aptos | D35: ML | E35: 1055.3 | F35: 37000 | G35: =+E35*F35 -> 39046100
B36: 4.5 | C36: Reparacion de morteros en cuchillas de cubierta-(30% DEL TOTAL) | D36: M2 | E36: 290.8665 | F36: 52000 | G36: =+E36*F36 -> 15125058
B37: 4.6 | C37: Suministro e Instalacion de Alfajias en lamina sobre muros perimetrales y medianeros en las cubiertas | D37: ML | E37: 372 | F37: 63000 | G37: =+E37*F37 -> 23436000
A38: 5 | C38: ASEO GENERAL DE OBRA Y RETIRO DE ESCOMBROS | G38: =+G39 -> 2300000
B39: 5.1 | C39: Aseo General y Retiro de Escombros y Sobrantes | D39: GBL | E39: 1 | F39: 2300000 | G39: =+E39*F39 -> 2300000
D40: TOTAL COSTO DIRECTO | G40: =+G9+G12+G18+G31+G38 -> 5.9598652e+08
D41: ADMINISTRACION | F41: 0.08 | G41: =+$G$40*F41 -> 47678922
D42: IMPREVISTOS | F42: 0.03 | G42: =+$G$40*F42 -> 17879596
D43: UTILIDAD | F43: 0.05 | G43: =+$G$40*F43 -> 29799326
D44: IVA/U | F44: 0.19 | G44: =+G43*F44 -> 5661872
D45: COSTO TOTAL | G45: =+G40+G41+G42+G43+G44 -> 6.9700624e+08
