Workbook

Sheet DASHBOARD
B1: TOTALES
B2: LAVADO | D2: RESANE | F2: SELLO | H2: PINTURA | J2: TRAT. DILATACIONES | L2: CARPINTERIA METALICA
B3: =LAVADO!E76 -> 4308.162 | D3: 85 | F3: =SELLO!E42 -> 1272.6 | H3: ='PINTURA T.VERDE'!R64 -> 2447.356 | J3: ='TRT DIL'!E40 -> 1201.844 | L3: ='[1](4A) PINTURA CARP MET'!H40 -> 0
B5: EJECUTADO
B6: LAVADO | D6: RESANE | F6: SELLO | H6: PINTURA | J6: TRAT. DILATACIONES | L6: CARPINTERIA METALICA
B7: =LAVADO!L76 -> 1290.86 | D7: =RESANE!AC81+RESANE!AQ81+RESANE!BE81+RESANE!BS81+RESANE!CG81+RESANE!CU81 -> 0 | F7: =SELLO!L42 -> 42.84 | H7: ='PINTURA T.VERDE'!AC81+'PINTURA T.VERDE'!AQ81+'PINTURA T.VERDE'!BE81+'PINTURA T.VERDE'!BS81+'PINTURA T.VERDE'!CG81+'PINTURA T.VERDE'!CU81 -> 1000 | J7: ='TRT DIL'!L52 -> 135.8 | L7: ='[1](4A) PINTURA CARP MET'!H40 -> 0
B9: PENDIENTE
B10: LAVADO | D10: RESANE | F10: SELLO | H10: PINTURA | J10: TRAT. DILATACIONES | L10: CARPINTERIA METALICA
B11: =B3-B7 -> 3017.302 | D11: =D3-D7 -> 85 | F11: =F3-F7 -> 1229.76 | H11: =H3-H7 -> 1447.356 | J11: =J3-J7 -> 1066.044 | L11: =L3-L7 -> 0
B13: RENDIMIENTOS PROMEDIO
B14: LAVADO | D14: RESANE | F14: SELLO | H14: PINTURA | J14: TRAT. DILATACIONES | L14: CARPINTERIA METALICA
L15: ='[2]COTIZACIÓN (2)'!O15 -> 0
A18: EJECUCIÓN SEMANA ACTUAL (SEMANA 2)
C19: LUNES | E19: MARTES | G19: MIERCOLES | I19: JUEVES | K19: VIERNES | M19: SABADO
A20: LAVADO
A21: RESANE
A22: SELLO
A23: PINTURA
A24: SILICONITE
A25: CARPINTERIA METALICA
A26: CIELOS BALCONES
A28: EJECUCIÓN SEMANA PASADA (SEMANA 1)
C29: LUNES | E29: MARTES | G29: MIERCOLES | I29: JUEVES | K29: VIERNES | M29: SABADO
A30: LAVADO
A31: RESANE
A32: SELLO
A33: PINTURA
A34: SILICONITE
A35: CARPINTERIA METALICA
A36: CIELOS BALCONES
A38: PERSONAL EN SITIO Y ASISTENCIA
C39: LUNES | E39: MARTES | G39: MIERCOLES | I39: JUEVES | K39: VIERNES | M39: SABADO
A40: ALEXIS BETANCOURT | B40: EDWIN TORRES
A41: LISETH GONZALES | B41: DEIBER TORO
A42: CIPRIANO VALENCIA | B42: GERARDO HERRERA
A43: SEBASTIAN VALENCIA | B43: CIPRIANO VALENCIA
B44: DIEGO DUQUE
B45: JHONATAN BENÍTEZ
AD65: Actividad | AE65: Ejecutado | AF65: Pendiente
AD66: LAVADO | AE66: =B3 -> 4308.162 | AF66: =B11 -> 3017.302
AD67: RESANE | AE67: =D7 -> 0 | AF67: =D11 -> 85
AD68: SELLO | AE68: =F7 -> 42.84 | AF68: =F11 -> 1229.76
AD69: PINTURA | AE69: =H7 -> 1000 | AF69: =H11 -> 1447.356
AD70: TRATAMIENTO DILATACIONES | AE70: =J7 -> 135.8 | AF70: =J11 -> 1066.044
AD71: CARPINTERIA METALICA | AE71: =L7 -> 0 | AF71: =J11 -> 1066.044

Sheet SALARIOS
B2: ANÁLISIS DEL COSTO REAL DEL SALARIO
B3: DATOS DE ENTRADA
B4: SALARIO MINIMO MENSUAL VIGENTE 2025 | C4: 1423500
B5: SUBSIDIO DE TRANSPORTE 2025 | C5: 200000
B6: DOTACIÓN 3 VECES AL AÑO | C6: =150000*3 -> 450000
B9: ANÁLISIS DEL COSTO REAL DEL SALARIO
B10: FACTOR PRESTACIONAL > 2 SMMLV
B11: CONCEPTO | C11: PORCENTAJE
B12: PRESTACIONES SOCIALES | C12: 0
B13: Cesantias | C13: =100/12 -> 8.3333333
B14: Intereses a las cesantias | C14: =C13*0.01 -> 0.083333333
B15: Vacaciones | C15: =100/24 -> 4.1666667
B16: Prima anual | C16: =100/12 -> 8.3333333
B18: SEGURIDAD SOCIAL | C18: =SUM(C19:C21) -> 35.46
B19: Fondo de pensiones (A.F.P) | C19: 16
B20: Medicina familiar (E.P.S) | C20: 12.5
B21: Riesgos Laborales (A.R.L) | C21: 6.96
B23: APORTE PARAFISCALES | C23: =SUM(C24:C26) -> 9
B24: SENA | C24: 2
B25: ICBF | C25: 3
B26: Caja de compensación familiar | C26: 4
B28: PORCENTAJE PRESTACIONAL | C28: =C12+C18+C23 -> 44.46
B31: SEGURIDAD SOCIAL
B32: SEGURIDAD SOCIAL X MES | C32: 430000
B33: SEGURIDAD SOCIAL X DÍA | C33: =C32/30 -> 14333.333
B35: SALARIO SEMANAL NETO
B36: OFICIAL III | C36: 700000
B37: OFICIAL II | C37: 650000
B38: OFICIAL I | C38: 600000
B39: PRÁCTICO | C39: 450000
B40: AYUDANTE | C40: 400000
B42: RESIDENTE DE OBRA | C42: 625000
B43: PROFESIONAL SST | C43: 500000
B46: SALARIO DIARIO NETO
B47: OFICIAL III | C47: =C36/6 -> 116666.67
B48: OFICIAL II | C48: =C37/6 -> 108333.33
B49: OFICIAL I | C49: =C38/6 -> 100000
B50: PRÁCTICO | C50: =C39/6 -> 75000
B51: AYUDANTE | C51: =C40/6 -> 66666.667
B53: RESIDENTE DE OBRA | C53: =C42/6 -> 104166.67
B54: PROFESIONAL SST | C54: =C43/6 -> 83333.333
B57: SALARIO DIARIO INCLUYENDO PRESTACIONES
B58: OFICIAL III | C58: =C47+$C$33 -> 131000
B59: OFICIAL III | C59: =C48+$C$33 -> 122666.67
B60: OFICIAL I | C60: =C49+$C$33 -> 114333.33
B61: PRÁCTICO | C61: =C50+$C$33 -> 89333.333
B62: AYUDANTE | C62: =C51+$C$33 -> 81000
B64: RESIDENTE DE OBRA | C64: =C53+$C$33 -> 118500
B65: PROFESIONAL SST | C65: =C54+$C$33 -> 97666.667
B68: VALOR CUADRILLA POR DÍA
B69: CUADRILLA | C69: VALOR
B70: CUADRILLA 1: 1 Oficial II, 1 Oficial l y 1 Práctico | C70: =(C58)+(C60)+C61 -> 334666.67
B71: CUADRILLA 2: 1 Oficial II, 2 Oficial l y 1 Práctico | C71: =(C58)+(C60*2)+C61 -> 449000
B72: CUADRILLA 2: 2 Oficial II, 4 Oficial l y 1 Práctico | C72: =(C58*2)+(C60*4)+C61 -> 808666.67
B73: CUADRILLA 5: 2 Oficial l y 1 Práctico | C73: =(C60*2)+C61 -> 318000

Sheet NÓMINA
E2: 2 | F2: 3 | G2: 4 | H2: 5 | I2: 6 | J2: 7 | K2: 8 | L2: 9 | M2: 10 | N2: 11 | O2: 12 | P2: 13 | Q2: 14 | R2: 15 | S2: 16 | T2: 17 | U2: 18 | V2: 19 | W2: 20 | X2: 21 | Y2: 22 | Z2: 23 | AA2: 24 | AB2: 25 | AC2: 26 | AD2: 27 | AE2: 28 | AF2: 29 | AG2: 30 | AH2: 31 | AI2: 1 | AJ2: 2 | AK2: 3 | AL2: 4 | AM2: 5 | AN2: 6 | AO2: 7 | AP2: 8 | AQ2: 9 | AR2: 10 | AS2: 11
E3: LUNES | F3: MARTES | G3: MIÉRCOLES | H3: JUEVES | I3: VIERNES | J3: SÁBADO | K3: DOMINGO | L3: LUNES | M3: MARTES | N3: MIÉRCOLES | O3: JUEVES | P3: VIERNES | Q3: SÁBADO | R3: DOMINGO | S3: LUNES | T3: MARTES | U3: MIÉRCOLES | V3: JUEVES | W3: VIERNES | X3: SÁBADO | Y3: DOMINGO | Z3: LUNES | AA3: MARTES | AB3: MIÉRCOLES | AC3: JUEVES | AD3: VIERNES | AE3: SÁBADO | AF3: DOMINGO | AG3: LUNES | AH3: MARTES | AI3: MIÉRCOLES | AJ3: JUEVES | AK3: VIERNES | AL3: SÁBADO | AM3: DOMINGO | AN3: LUNES | AO3: MARTES | AP3: MIÉRCOLES | AQ3: JUEVES | AR3: VIERNES | AS3: SÁBADO
A4: NOMBRE | B4: CARGO | C4: DEDICACIÓN | D4: SALARIO DÍA
A5: RENSO MONTOYA | B5: GERENTE | C5: 0.34 | D5: =SALARIOS!C64 -> 118500 | E5: 0 | F5: =D5*C5 -> 40290 | G5: 0 | H5: 0 | I5: 0 | J5: 0 | L5: 0 | M5: 0 | N5: 0 | O5: 0 | P5: 0 | Q5: 0 | S5: 0 | T5: 0 | U5: 0 | V5: 0 | W5: 0 | X5: 0 | Y5: 0 | Z5: 0 | AA5: 0 | AB5: 0 | AC5: 0 | AD5: 0 | AE5: 0 | AF5: 0 | AG5: 0 | AH5: 0 | AI5: 0 | AJ5: 0 | AK5: 0 | AL5: 0 | AM5: 0 | AN5: 0 | AO5: 0 | AP5: 0 | AQ5: 0 | AR5: 0 | AS5: 0 | AT5: =SUM(E5:AS5) -> 40290
A6: GLORIA COLORADO | B6: ADMINIST | C6: 0.34 | D6: =D5 -> 118500 | E6: 0 | F6: =D6*C6 -> 40290 | G6: 0 | H6: 0 | I6: 0 | J6: 0 | L6: 0 | M6: 0 | N6: 0 | O6: 0 | P6: 0 | Q6: 0 | S6: 0 | T6: 0 | U6: 0 | V6: 0 | W6: 0 | X6: 0 | Y6: 0 | Z6: 0 | AA6: 0 | AB6: 0 | AC6: 0 | AD6: 0 | AE6: 0 | AF6: 0 | AG6: 0 | AH6: 0 | AI6: 0 | AJ6: 0 | AK6: 0 | AL6: 0 | AM6: 0 | AN6: 0 | AO6: 0 | AP6: 0 | AQ6: 0 | AR6: 0 | AS6: 0 | AT6: =SUM(E6:AS6) -> 40290
A7: ALEXIS BETANCOURT | B7: RESIDENTE | C7: 1 | D7: =SALARIOS!C64 -> 118500 | E7: 0 | F7: =D7*C7 -> 118500 | G7: 0 | H7: 0 | I7: 0 | J7: 0 | L7: 0 | M7: 0 | N7: 0 | O7: 0 | P7: 0 | Q7: 0 | S7: 0 | T7: 0 | U7: 0 | V7: 0 | W7: 0 | X7: 0 | Y7: 0 | Z7: 0 | AA7: 0 | AB7: 0 | AC7: 0 | AD7: 0 | AE7: 0 | AF7: 0 | AG7: 0 | AH7: 0 | AI7: 0 | AJ7: 0 | AK7: 0 | AL7: 0 | AM7: 0 | AN7: 0 | AO7: 0 | AP7: 0 | AQ7: 0 | AR7: 0 | AS7: 0 | AT7: =SUM(E7:AS7) -> 118500
A8: FELIPE MONTOYA | B8: AUX GERENCIA | C8: 0.34 | D8: =D7 -> 118500 | E8: 0 | F8: =D8*C8 -> 40290 | G8: 0 | H8: 0 | I8: 0 | J8: 0 | L8: 0 | M8: 0 | N8: 0 | O8: 0 | P8: 0 | Q8: 0 | S8: 0 | T8: 0 | U8: 0 | V8: 0 | W8: 0 | X8: 0 | Y8: 0 | Z8: 0 | AA8: 0 | AB8: 0 | AC8: 0 | AD8: 0 | AE8: 0 | AF8: 0 | AG8: 0 | AH8: 0 | AI8: 0 | AJ8: 0 | AK8: 0 | AL8: 0 | AM8: 0 | AN8: 0 | AO8: 0 | AP8: 0 | AQ8: 0 | AR8: 0 | AS8: 0 | AT8: =SUM(E8:AS8) -> 40290
A9: DIEGO LÓPEZ | B9: SUPERVISOR | C9: 0.5 | D9: =[3]SALARIOS!C64 -> 118166.67 | E9: 0 | F9: =D9*C9 -> 59083.333 | G9: 0 | H9: 0 | I9: 0 | J9: 0 | L9: 0 | M9: 0 | N9: 0 | O9: 0 | P9: 0 | Q9: 0 | S9: 0 | T9: 0 | U9: 0 | V9: 0 | W9: 0 | X9: 0 | Y9: 0 | Z9: 0 | AA9: 0 | AB9: 0 | AC9: 0 | AD9: 0 | AE9: 0 | AF9: 0 | AG9: 0 | AH9: 0 | AI9: 0 | AJ9: 0 | AK9: 0 | AL9: 0 | AM9: 0 | AN9: 0 | AO9: 0 | AP9: 0 | AQ9: 0 | AR9: 0 | AS9: 0 | AT9: =SUM(E9:AS9) -> 59083.333
A10: LISETH GONZÁLEZ | B10: PROF SST | C10: 0.34 | D10: =[3]SALARIOS!C65 -> 97333.333 | E10: 0 | F10: =D10*C10 -> 33093.333 | G10: 0 | H10: 0 | I10: 0 | J10: 0 | L10: 0 | M10: 0 | N10: 0 | O10: 0 | P10: 0 | Q10: 0 | S10: 0 | T10: 0 | U10: 0 | V10: 0 | W10: 0 | X10: 0 | Y10: 0 | Z10: 0 | AA10: 0 | AB10: 0 | AC10: 0 | AD10: 0 | AE10: 0 | AF10: 0 | AG10: 0 | AH10: 0 | AI10: 0 | AJ10: 0 | AK10: 0 | AL10: 0 | AM10: 0 | AN10: 0 | AO10: 0 | AP10: 0 | AQ10: 0 | AR10: 0 | AS10: 0 | AT10: =SUM(E10:AS10) -> 33093.333
E11: =SUM(E5:E10) -> 0 | F11: =SUM(F5:F10) -> 331546.67 | G11: =SUM(G5:G10) -> 0 | H11: =SUM(H5:H10) -> 0 | I11: =SUM(I5:I10) -> 0 | J11: =SUM(J5:J10) -> 0 | K11: =SUM(K5:K10) -> 0 | L11: =SUM(L5:L10) -> 0 | ... S11: =SUM(S5:S10) -> 0
A12: JONATHAN ARANGO | B12: OFICIAL II | C12: 1 | D12: =SALARIOS!C59 -> 122666.67 | E12: 0 | F12: 0 | G12: =$F$12 -> 0 | H12: =$F$12 -> 0 | I12: =$F$12 -> 0 | J12: =$F$12 -> 0 | K12: 0 | L12: =$F$12 -> 0 | M12: =$F$12 -> 0 | N12: =$F$12 -> 0 | O12: =$F$12 -> 0 | P12: =$F$12 -> 0 | Q12: =$F$12 -> 0 | R12: 0 | S12: 0 | T12: 0 | U12: 0 | V12: 0 | W12: 0 | X12: 0 | Y12: 0 | Z12: 0 | AA12: 0 | AB12: 0 | AC12: 0 | AD12: 0 | AE12: 0 | AF12: 0 | AG12: 0 | AH12: 0 | AI12: 0 | AJ12: 0 | AK12: 0 | AL12: 0 | AM12: 0 | AN12: 0 | AO12: 0 | AP12: 0 | AQ12: 0 | AR12: 0 | AS12: 0 | AT12: =SUM(E12:AS12) -> 0
A13: CIPRIANO CARDENAS | B13: OFICIAL III | C13: 1 | D13: =D12 -> 122666.67 | E13: 0 | F13: 0 | G13: =$F$13 -> 0 | H13: =$F$13 -> 0 | I13: =$F$13 -> 0 | J13: =$F$13 -> 0 | K13: 0 | L13: =$F$12 -> 0 | M13: =$F$12 -> 0 | N13: =$F$12 -> 0 | O13: =$F$12 -> 0 | P13: =$F$12 -> 0 | Q13: =$F$12 -> 0 | R13: 0 | S13: 0 | T13: 0 | U13: 0 | V13: 0 | W13: 0 | X13: 0 | Y13: 0 | Z13: 0 | AA13: 0 | AB13: 0 | AC13: 0 | AD13: 0 | AE13: 0 | AF13: 0 | AG13: 0 | AH13: 0 | AI13: 0 | AJ13: 0 | AK13: 0 | AL13: 0 | AM13: 0 | AN13: 0 | AO13: 0 | AP13: 0 | AQ13: 0 | AR13: 0 | AS13: 0 | AT13: =SUM(E13:AS13) -> 0
A14: BRAYAN MEJÍA | B14: OFICIAL II | C14: 1 | D14: =SALARIOS!C60 -> 114333.33 | E14: 0 | F14: 0 | G14: 0 | H14: 0 | I14: 0 | J14: 0 | K14: 0 | L14: =$F$12 -> 0 | M14: =$F$12 -> 0 | N14: =$F$12 -> 0 | O14: =$F$12 -> 0 | P14: =$F$12 -> 0 | Q14: =$F$12 -> 0 | R14: 0 | S14: 0 | T14: 0 | U14: 0 | V14: 0 | W14: 0 | X14: 0 | Y14: 0 | Z14: 0 | AA14: 0 | AB14: 0 | AC14: 0 | AD14: 0 | AE14: 0 | AF14: 0 | AG14: 0 | AH14: 0 | AI14: 0 | AJ14: 0 | AK14: 0 | AL14: 0 | AM14: 0 | AN14: 0 | AO14: 0 | AP14: 0 | AQ14: 0 | AR14: 0 | AS14: 0 | AT14: =SUM(E14:AS14) -> 0
A15: JUAN CARLOS | B15: OFICIAL II | C15: 1 | D15: =D14 -> 114333.33 | E15: 0 | F15: 0 | G15: 0 | H15: 0 | I15: 0 | J15: 0 | K15: 0 | L15: =$F$12 -> 0 | M15: =$F$12 -> 0 | N15: =$F$12 -> 0 | O15: =$F$12 -> 0 | P15: =$F$12 -> 0 | Q15: =$F$12 -> 0 | R15: 0 | S15: 0 | T15: =$N$15*$C$15 -> 0 | U15: =$N$15*$C$15 -> 0 | V15: =$N$15*$C$15 -> 0 | W15: =$N$15*$C$15 -> 0 | X15: =$N$15*$C$15 -> 0 | Y15: 0 | Z15: =$N$15*$C$15 -> 0 | AA15: =$N$15*$C$15 -> 0 | AB15: =$N$15*$C$15 -> 0 | AC15: =$N$15*$C$15 -> 0 | AD15: =$N$15*$C$15 -> 0 | AE15: =$N$15*$C$15 -> 0 | AF15: 0 | AG15: =$N$15*$C$15 -> 0 | AH15: =$N$15*$C$15 -> 0 | AI15: =$N$15*$C$15 -> 0 | AJ15: =$N$15*$C$15 -> 0 | AK15: =$N$15*$C$15 -> 0 | AL15: =$N$15*$C$15 -> 0 | AM15: 0 | AN15: =$N$15*$C$15 -> 0 | AO15: =$N$15*$C$15 -> 0 | AP15: =$N$15*$C$15 -> 0 | AQ15: =$N$15*$C$15 -> 0 | AR15: =$N$15*$C$15 -> 0 | AS15: =$N$15*$C$15 -> 0 | AT15: =SUM(E15:AS15) -> 0
A16: JEISON PORTAL | B16: OFICIAL I | C16: 1 | D16: =SALARIOS!C60 -> 114333.33 | E16: 0 | F16: 0 | G16: =$F$16 -> 0 | H16: =$F$16 -> 0 | I16: =$F$16 -> 0 | J16: =$F$16 -> 0 | K16: 0 | L16: =$F$12 -> 0 | M16: =$F$12 -> 0 | N16: =$F$12 -> 0 | O16: =$F$12 -> 0 | P16: =$F$12 -> 0 | Q16: =$F$12 -> 0 | R16: 0 | S16: 0 | T16: 0 | U16: 0 | V16: 0 | W16: 0 | X16: 0 | Y16: 0 | Z16: 0 | AA16: 0 | AB16: 0 | AC16: 0 | AD16: =$N$15*$C$15 -> 0 | AE16: =$N$15*$C$15 -> 0 | AF16: 0 | AG16: =$N$15*$C$15 -> 0 | AH16: 0 | AI16: 0 | AJ16: 0 | AK16: 0 | AL16: 0 | AM16: 0 | AN16: 0 | AO16: 0 | AP16: 0 | AQ16: 0 | AR16: 0 | AS16: 0 | AT16: =SUM(E16:AS16) -> 0
A17: DUBERNEY TORO | B17: OFICIAL I | C17: 1 | D17: =SALARIOS!C60 -> 114333.33 | E17: 0 | F17: 0 | G17: 0 | H17: 0 | I17: 0 | J17: 0 | K17: 0 | L17: =$F$12 -> 0 | M17: =$F$12 -> 0 | N17: =$F$12 -> 0 | O17: =$F$12 -> 0 | P17: =$F$12 -> 0 | Q17: =$F$12 -> 0 | R17: 0 | S17: 0 | T17: 0 | U17: 0 | V17: 0 | W17: 0 | X17: 0 | Y17: 0 | Z17: 0 | AA17: 0 | AB17: 0 | AC17: 0 | AD17: 0 | AE17: 0 | AF17: 0 | AG17: 0 | AH17: 0 | AI17: 0 | AJ17: 0 | AK17: 0 | AL17: 0 | AM17: 0 | AN17: 0 | AO17: 0 | AP17: 0 | AQ17: 0 | AR17: 0 | AS17: 0 | AT17: =SUM(E17:AS17) -> 0
A18: GREGORIO GONZÁLEZ | B18: OFICIAL II | C18: 1 | D18: =SALARIOS!C59 -> 122666.67 | E18: 0 | F18: 0 | G18: 0 | H18: 0 | I18: 0 | J18: 0 | K18: 0 | L18: =$F$12 -> 0 | M18: =$F$12 -> 0 | N18: =$F$12 -> 0 | O18: =$F$12 -> 0 | P18: =$F$12 -> 0 | Q18: =$F$12 -> 0 | R18: 0 | S18: 0 | T18: 0 | U18: 0 | V18: 0 | W18: 0 | X18: 0 | Y18: 0 | Z18: 0 | AA18: 0 | AB18: 0 | AC18: 0 | AD18: 0 | AE18: 0 | AF18: 0 | AG18: 0 | AH18: 0 | AI18: 0 | AJ18: 0 | AK18: 0 | AL18: 0 | AM18: 0 | AN18: 0 | AO18: 0 | AP18: 0 | AQ18: 0 | AR18: 0 | AS18: 0 | AT18: =SUM(E18:AS18) -> 0
A19: WILLIAN BETANCOURT | B19: PRÁCTICO | C19: 1 | D19: =SALARIOS!C62 -> 81000 | E19: 0 | F19: 0 | G19: 0 | H19: 0 | I19: 0 | J19: 0 | K19: 0 | L19: =$F$12 -> 0 | M19: =$F$12 -> 0 | N19: =$F$12 -> 0 | O19: =$F$12 -> 0 | P19: =$F$12 -> 0 | Q19: =$F$12 -> 0 | R19: 0 | S19: 0 | T19: 0 | U19: 0 | V19: 0 | W19: 0 | X19: 0 | Y19: 0 | Z19: 0 | AA19: 0 | AB19: 0 | AC19: 0 | AD19: 0 | AE19: 0 | AF19: 0 | AG19: 0 | AH19: 0 | AI19: 0 | AJ19: 0 | AK19: 0 | AL19: 0 | AM19: 0 | AN19: 0 | AO19: 0 | AP19: 0 | AQ19: 0 | AR19: 0 | AS19: 0 | AT19: =SUM(E19:AS19) -> 0
AT20: =SUM(AT5:AT18) -> 331546.67
E21: =SUM(E12:E20) -> 0 | F21: =SUM(F12:F20) -> 0 | G21: =SUM(G12:G20) -> 0 | H21: =SUM(H12:H20) -> 0 | I21: =SUM(I12:I20) -> 0 | J21: =SUM(J12:J20) -> 0 | K21: =SUM(K12:K20) -> 0 | L21: =SUM(L12:L20) -> 0 | ... AS21: =SUM(AS12:AS20) -> 0 | AT21: =SUM(E21:AS21) -> 0
E22: =E11 -> 0 | F22: =F11+F21 -> 331546.67 | G22: =G11+G21 -> 0 | H22: =H11+H21 -> 0 | I22: =I11+I21 -> 0 | J22: =J11+J21 -> 0 | K22: =K11+K21 -> 0 | L22: =L11+L21 -> 0 | M22: =M11+M21 -> 0 | ... S22: =S11+S21 -> 0

Sheet COS_PROG
F1: FLUJO DE CAJA - EDIFICIO HEBRÓN
F3: 21 | G3: 22 | H3: 23 | I3: 24 | J3: 25 | K3: 26 | L3: 27 | M3: 28 | N3: 29 | O3: 30 | P3: 1 | Q3: 2 | R3: 3 | S3: 4 | T3: 5 | U3: 6 | V3: 7 | W3: 8 | X3: 9 | Y3: 10 | Z3: 11 | AA3: 12 | AB3: 13 | AC3: 14 | AD3: 15 | AE3: 16 | AF3: 17 | AG3: 18 | AH3: 19 | AI3: 20 | AJ3: 21 | AK3: 22 | AL3: 23 | AM3: 24 | AN3: 25 | AO3: 26 | AP3: 27 | AQ3: 28 | AR3: 29 | AS3: 30 | AT3: 31
F4: LUNES | G4: MARTES | H4: MIÉRCOLES | I4: JUEVES | J4: VIERNES | K4: SÁBADO | L4: DOMINGO | M4: LUNES | N4: MARTES | O4: MIÉRCOLES | P4: JUEVES | Q4: VIERNES | R4: SÁBADO | S4: DOMINGO | T4: LUNES | U4: MARTES | V4: MIÉRCOLES | W4: JUEVES | X4: VIERNES | Y4: SÁBADO | Z4: DOMINGO | AA4: LUNES | AB4: MARTES | AC4: MIÉRCOLES | AD4: JUEVES | AE4: VIERNES | AF4: SÁBADO | AG4: DOMINGO | AH4: LUNES | AI4: MARTES | AJ4: MIÉRCOLES | AK4: JUEVES | AL4: VIERNES | AM4: SÁBADO | AN4: DOMINGO | AO4: LUNES | AP4: MARTES | AQ4: MIÉRCOLES | AR4: JUEVES | AS4: VIERNES | AT4: SÁBADO
B5: EGRESOS
B7: CONCEPTO | C7: DEDICACIÓN | D7: VALOR
B8: COSTO INDIRECTOS
B9: OFICINA | C9: 0.25 | F9: 50000 | G9: =$F$9 -> 50000 | H9: =$F$9 -> 50000 | I9: =$F$9 -> 50000 | J9: =$F$9 -> 50000 | K9: =$F$9 -> 50000 | L9: 0 | M9: =$F$9 -> 50000 | N9: =$F$9 -> 50000 | O9: =$F$9 -> 50000 | P9: =$F$9 -> 50000 | Q9: =$F$9 -> 50000 | R9: =$F$9 -> 50000 | S9: 0 | T9: =$F$9 -> 50000 | U9: =$F$9 -> 50000 | V9: =$F$9 -> 50000 | W9: =$F$9 -> 50000 | X9: =$F$9 -> 50000 | Y9: =$F$9 -> 50000 | Z9: 0 | AA9: 0 | AB9: =$F$9 -> 50000 | AC9: =$F$9 -> 50000 | AD9: =$F$9 -> 50000 | AE9: =$F$9 -> 50000 | AF9: =$F$9 -> 50000 | AG9: 0 | AH9: =$F$9 -> 50000 | AI9: =$F$9 -> 50000 | AJ9: =$F$9 -> 50000 | AK9: =$F$9 -> 50000 | AL9: =$F$9 -> 50000 | AM9: =$F$9 -> 50000 | AN9: 0 | AO9: =$F$9 -> 50000 | AP9: =$F$9 -> 50000 | AQ9: =$F$9 -> 50000 | AR9: =$F$9 -> 50000 | AS9: =$F$9 -> 50000 | AT9: =$F$9 -> 50000 | AU9: =SUM(F9:AT9) -> 1750000
B10: PAPELERIA | C10: 0.5 | F10: 5000 | G10: =$F$10 -> 5000 | H10: =$F$10 -> 5000 | I10: =$F$10 -> 5000 | J10: =$F$10 -> 5000 | K10: =$F$10 -> 5000 | L10: 0 | M10: =$D$10*$C$10 -> 0 | N10: =$D$10*$C$10 -> 0 | O10: =$D$10*$C$10 -> 0 | P10: =$D$10*$C$10 -> 0 | Q10: =$D$10*$C$10 -> 0 | R10: =$D$10*$C$10 -> 0 | S10: 0 | T10: =$D$10*$C$10 -> 0 | U10: =$D$10*$C$10 -> 0 | V10: =$D$10*$C$10 -> 0 | W10: =$D$10*$C$10 -> 0 | X10: =$D$10*$C$10 -> 0 | Y10: =$D$10*$C$10 -> 0 | Z10: 0 | AA10: =$D$10*$C$10 -> 0 | AB10: =$D$10*$C$10 -> 0 | AC10: =$D$10*$C$10 -> 0 | AD10: =$D$9*$C$10 -> 0 | AE10: =$D$10*$C$10 -> 0 | AF10: =$D$10*$C$10 -> 0 | AG10: 0 | AH10: =$D$10*$C$10 -> 0 | AI10: =$D$10*$C$10 -> 0 | AJ10: =$D$10*$C$10 -> 0 | AK10: =$D$10*$C$10 -> 0 | AL10: =$D$10*$C$10 -> 0 | AM10: =$D$10*$C$10 -> 0 | AN10: 0 | AO10: =$D$10*$C$10 -> 0 | AP10: =$D$10*$C$10 -> 0 | AQ10: =$D$10*$C$10 -> 0 | AR10: =$D$10*$C$10 -> 0 | AS10: =$D$10*$C$10 -> 0 | AT10: =$D$10*$C$10 -> 0 | AU10: =SUM(F10:AT10) -> 30000
B11: NÓMINA ADMINISTRATIVOS
B13: COSTO DIRECTOS
B14: NÓMINA DE TRABAJADORES | C14: 1 | F14: =NÓMINA!E21 -> 0 | G14: =NÓMINA!F21 -> 0 | H14: =NÓMINA!G21 -> 0 | I14: =NÓMINA!H21 -> 0 | J14: =NÓMINA!I21 -> 0 | K14: =NÓMINA!J21 -> 0 | L14: 0 | M14: =$D$14*$C$14 -> 0 | N14: =$D$14*$C$14 -> 0 | O14: =$D$14*$C$14 -> 0 | P14: =$D$14*$C$14 -> 0 | Q14: =$D$14*$C$14 -> 0 | R14: =$D$14*$C$14 -> 0 | S14: 0 | T14: =$D$14*$C$14 -> 0 | U14: =$D$14*$C$14 -> 0 | V14: =$D$14*$C$14 -> 0 | W14: =$D$14*$C$14 -> 0 | X14: =$D$14*$C$14 -> 0 | Y14: =$D$14*$C$14 -> 0 | Z14: 0 | AA14: =$D$10*$C$10 -> 0 | AB14: =$D$14*$C$14 -> 0 | AC14: =$D$14*$C$14 -> 0 | AD14: =$D$14*$C$14 -> 0 | AE14: =$D$14*$C$14 -> 0 | AF14: =$D$14*$C$14 -> 0 | AG14: 0 | AH14: =$D$14*$C$14 -> 0 | AI14: =$D$14*$C$14 -> 0 | AJ14: =$D$14*$C$14 -> 0 | AK14: =$D$14*$C$14 -> 0 | AL14: =$D$14*$C$14 -> 0 | AM14: =$D$14*$C$14 -> 0 | AN14: 0 | AO14: =$D$14*$C$14 -> 0 | AP14: =$D$14*$C$14 -> 0 | AQ14: =$D$14*$C$14 -> 0 | AR14: =$D$14*$C$14 -> 0 | AS14: =$D$14*$C$14 -> 0 | AT14: =$D$14*$C$14 -> 0 | AU14: =SUM(F14:AT14) -> 0
B15: MATERIALES | C15: 1 | F15: =D15 -> 0 | G15: =$D$14*$C$14 -> 0 | H15: =$D$14*$C$14 -> 0 | I15: =$D$14*$C$14 -> 0 | J15: =$D$14*$C$14 -> 0 | K15: =$D$14*$C$14 -> 0 | L15: 0 | M15: =$D$14*$C$14 -> 0 | N15: =$D$14*$C$14 -> 0 | O15: =$D$14*$C$14 -> 0 | P15: =$D$14*$C$14 -> 0 | Q15: =$D$14*$C$14 -> 0 | R15: =$D$14*$C$14 -> 0 | S15: 0 | T15: =$D$14*$C$14 -> 0 | U15: =$D$14*$C$14 -> 0 | V15: =$D$14*$C$14 -> 0 | W15: =$D$14*$C$14 -> 0 | X15: =$D$14*$C$14 -> 0 | Y15: =$D$14*$C$14 -> 0 | Z15: 0 | AA15: =$D$10*$C$10 -> 0 | AB15: =$D$14*$C$14 -> 0 | AC15: =$D$14*$C$14 -> 0 | AD15: =$D$14*$C$14 -> 0 | AE15: =$D$14*$C$14 -> 0 | AF15: =$D$14*$C$14 -> 0 | AG15: 0 | AH15: =$D$14*$C$14 -> 0 | AI15: =$D$14*$C$14 -> 0 | AJ15: =$D$14*$C$14 -> 0 | AK15: =$D$14*$C$14 -> 0 | AL15: =$D$14*$C$14 -> 0 | AM15: =$D$14*$C$14 -> 0 | AN15: 0 | AO15: =$D$14*$C$14 -> 0 | AP15: =$D$14*$C$14 -> 0 | AQ15: =$D$14*$C$14 -> 0 | AR15: =$D$14*$C$14 -> 0 | AS15: =$D$14*$C$14 -> 0 | AT15: =$D$14*$C$14 -> 0 | AU15: =SUM(F15:AT15) -> 0
B16: HERRAMIENTAS | C16: 1 | F16: =D16 -> 0 | G16: =$D$16*$C$16 -> 0 | H16: =$D$16*$C$16 -> 0 | I16: =$D$16*$C$16 -> 0 | J16: =$D$16*$C$16 -> 0 | K16: =$D$16*$C$16 -> 0 | L16: 0 | M16: =$D$16*$C$16 -> 0 | N16: =$D$16*$C$16 -> 0 | O16: =$D$16*$C$16 -> 0 | P16: =$D$16*$C$16 -> 0 | Q16: =$D$16*$C$16 -> 0 | R16: =$D$16*$C$16 -> 0 | S16: 0 | T16: =$D$16*$C$16 -> 0 | U16: =$D$16*$C$16 -> 0 | V16: =$D$16*$C$16 -> 0 | W16: =$D$16*$C$16 -> 0 | X16: =$D$16*$C$16 -> 0 | Y16: =$D$16*$C$16 -> 0 | Z16: 0 | AA16: =$F$16*$C$16 -> 0 | AB16: =$F$16*$C$16 -> 0 | AC16: =$F$16*$C$16 -> 0 | AD16: =$F$16*$C$16 -> 0 | AE16: =$F$16*$C$16 -> 0 | AF16: =$F$16*$C$16 -> 0 | AG16: 0 | AH16: =$F$16*$C$16 -> 0 | AI16: =$F$16*$C$16 -> 0 | AJ16: =$F$16*$C$16 -> 0 | AK16: =$F$16*$C$16 -> 0 | AL16: =$F$16*$C$16 -> 0 | AM16: =$F$16*$C$16 -> 0 | AN16: 0 | AO16: =$F$16*$C$16 -> 0 | AP16: =$F$16*$C$16 -> 0 | AQ16: =$F$16*$C$16 -> 0 | AR16: =$F$16*$C$16 -> 0 | AS16: =$F$16*$C$16 -> 0 | AT16: =$F$16*$C$16 -> 0 | AU16: =SUM(F16:AT16) -> 0
B17: ALQUILER DE EQUIPOS | C17: 1 | F17: =D17*C17 -> 0 | G17: =$D$17*$C$17 -> 0 | H17: =$D$17*$C$17 -> 0 | I17: =$D$17*$C$17 -> 0 | J17: =$D$17*$C$17 -> 0 | K17: =$D$17*$C$17 -> 0 | L17: 0 | M17: =$D$17*$C$17 -> 0 | N17: =$D$17*$C$17 -> 0 | O17: =$D$17*$C$17 -> 0 | P17: =$D$17*$C$17 -> 0 | Q17: =$D$17*$C$17 -> 0 | R17: =$D$17*$C$17 -> 0 | S17: 0 | T17: =$D$17*$C$17 -> 0 | U17: =$D$17*$C$17 -> 0 | V17: =$D$17*$C$17 -> 0 | W17: =$D$17*$C$17 -> 0 | X17: =$D$17*$C$17 -> 0 | Y17: =$D$17*$C$17 -> 0 | Z17: 0 | AA17: =$D$17*$C$17 -> 0 | AB17: =$D$17*$C$17 -> 0 | AC17: 0 | AD17: 0 | AE17: 0 | AF17: 0 | AG17: 0 | AH17: =$D$17*$C$17 -> 0 | AI17: =$D$17*$C$17 -> 0 | AJ17: =$D$17*$C$17 -> 0 | AK17: =$D$17*$C$17 -> 0 | AL17: =$D$17*$C$17 -> 0 | AM17: =$D$17*$C$17 -> 0 | AN17: 0 | AO17: =$D$17*$C$17 -> 0 | AP17: =$D$17*$C$17 -> 0 | AQ17: =$D$17*$C$17 -> 0 | AR17: =$D$17*$C$17 -> 0 | AS17: =$D$17*$C$17 -> 0 | AT17: =$D$17*$C$17 -> 0 | AU17: =SUM(F17:AT17) -> 0
B18: ALQUILER DE EQUIPOS ALTURAS | C18: 1 | F18: =D18*C18 -> 0 | G18: =$D$17*$C$17 -> 0 | H18: =$D$17*$C$17 -> 0 | I18: =$D$17*$C$17 -> 0 | J18: =$D$17*$C$17 -> 0 | K18: =$D$17*$C$17 -> 0 | L18: 0 | M18: =$D$17*$C$17 -> 0 | N18: =$D$17*$C$17 -> 0 | O18: =$D$17*$C$17 -> 0 | P18: =$D$17*$C$17 -> 0 | Q18: =$D$17*$C$17 -> 0 | R18: =$D$17*$C$17 -> 0 | S18: 0 | T18: =$D$17*$C$17 -> 0 | U18: =$D$17*$C$17 -> 0 | V18: =$D$17*$C$17 -> 0 | W18: =$D$17*$C$17 -> 0 | X18: =$D$17*$C$17 -> 0 | Y18: =$D$17*$C$17 -> 0 | Z18: 0 | AA18: =$D$17*$C$17 -> 0 | AB18: =$D$17*$C$17 -> 0 | AC18: 0 | AD18: 0 | AE18: 0 | AF18: 0 | AG18: 0 | AH18: =$D$17*$C$17 -> 0 | AI18: =$D$17*$C$17 -> 0 | AJ18: =$D$17*$C$17 -> 0 | AK18: =$D$17*$C$17 -> 0 | AL18: =$D$17*$C$17 -> 0 | AM18: =$D$17*$C$17 -> 0 | AN18: 0 | AO18: =$D$17*$C$17 -> 0 | AP18: =$D$17*$C$17 -> 0 | AQ18: =$D$17*$C$17 -> 0 | AR18: =$D$17*$C$17 -> 0 | AS18: =$D$17*$C$17 -> 0 | AT18: =$D$17*$C$17 -> 0 | AU18: =SUM(F18:AT18) -> 0
B20: IMPREVISTOS
B22: TOTAL EGRESOS | F22: =SUM(F9:F21) -> 55000 | G22: =SUM(G9:G21) -> 55000 | H22: =SUM(H9:H21) -> 55000 | I22: =SUM(I9:I21) -> 55000 | J22: =SUM(J9:J21) -> 55000 | K22: =SUM(K9:K21) -> 55000 | L22: =SUM(L9:L21) -> 0 | M22: =SUM(M9:M21) -> 50000 | ... R22: =SUM(R9:R21) -> 50000 | S22: =SUM(S16:S21) -> 0 | T22: =SUM(T9:T21) -> 50000 | U22: =SUM(U9:U21) -> 50000 | V22: =SUM(V9:V21) -> 50000 | W22: =SUM(W9:W21) -> 50000 | X22: =SUM(X9:X21) -> 50000 | Y22: =SUM(Y9:Y21) -> 50000 | Z22: =SUM(Z16:Z21) -> 0 | AA22: =SUM(AA9:AA21) -> 0 | AB22: =SUM(AB9:AB21) -> 50000 | AC22: =SUM(AC9:AC21) -> 50000 | AD22: =SUM(AD9:AD21) -> 50000 | AE22: =SUM(AE9:AE21) -> 50000 | AF22: =SUM(AF9:AF21) -> 50000 | AG22: =SUM(AG16:AG21) -> 0 | AH22: =SUM(AH9:AH21) -> 50000 | AI22: =SUM(AI9:AI21) -> 50000 | AJ22: =SUM(AJ9:AJ21) -> 50000 | AK22: =SUM(AK9:AK21) -> 50000 | AL22: =SUM(AL9:AL21) -> 50000 | AM22: =SUM(AM9:AM21) -> 50000 | AN22: =SUM(AN16:AN21) -> 0 | AO22: =SUM(AO9:AO21) -> 50000 | AP22: =SUM(AP9:AP21) -> 50000 | AQ22: =SUM(AQ9:AQ21) -> 50000 | AR22: =SUM(AR9:AR21) -> 50000 | AS22: =SUM(AS9:AS21) -> 50000 | AT22: =SUM(AT9:AT21) -> 50000 | AU22: =SUM(F22:AT22) -> 1780000
B23: ACUMULADO DE EGRESOS | F23: =F22 -> 55000 | G23: =F23+G22 -> 110000 | H23: =G23+H22 -> 165000 | I23: =H23+I22 -> 220000 | J23: =I23+J22 -> 275000 | K23: =J23+K22 -> 330000 | L23: =K23+L22 -> 330000 | M23: =L23+M22 -> 380000 | N23: =M23+N22 -> 430000 | ... AU23: =AT23+AU22 -> 3560000
B26: INGRESOS
B28: CONCEPTO
B29: COSTO INDIRECTOS
B30: ANTICIPO (INICIO DE OBRA) | C30: 0.2 | D30: 60000000 | F30: =D30 -> 60000000 | G30: =$F$9 -> 50000 | H30: =$F$9 -> 50000 | I30: =$F$9 -> 50000 | J30: =$F$9 -> 50000 | K30: =$F$9 -> 50000 | L30: 0 | M30: =$F$9 -> 50000 | N30: =$F$9 -> 50000 | O30: =$F$9 -> 50000 | P30: =$F$9 -> 50000 | Q30: =$F$9 -> 50000 | R30: =$F$9 -> 50000 | S30: 0 | T30: =$F$9 -> 50000 | U30: =$F$9 -> 50000 | V30: =$F$9 -> 50000 | W30: =$F$9 -> 50000 | X30: =$F$9 -> 50000 | Y30: =$F$9 -> 50000 | Z30: 0 | AA30: 0 | AB30: =$F$9 -> 50000 | AC30: =$F$9 -> 50000 | AD30: =$F$9 -> 50000 | AE30: =$F$9 -> 50000 | AF30: =$F$9 -> 50000 | AG30: 0 | AH30: =$F$9 -> 50000 | AI30: =$F$9 -> 50000 | AJ30: =$F$9 -> 50000 | AK30: =$F$9 -> 50000 | AL30: =$F$9 -> 50000 | AM30: =$F$9 -> 50000 | AN30: 0 | AO30: =$F$9 -> 50000 | AP30: =$F$9 -> 50000 | AQ30: =$F$9 -> 50000 | AR30: =$F$9 -> 50000 | AS30: =$F$9 -> 50000 | AT30: =$F$9 -> 50000 | AU30: =SUM(F30:AT30) -> 61700000
B31: PRESTAMO FRESHOUSE 1 | C31: 0.5 | F31: =D31 -> 0 | G31: =$D$10*$C$10 -> 0 | H31: =$D$10*$C$10 -> 0 | I31: =$D$10*$C$10 -> 0 | J31: =$D$10*$C$10 -> 0 | K31: =$D$10*$C$10 -> 0 | L31: 0 | M31: =$D$10*$C$10 -> 0 | N31: =$D$10*$C$10 -> 0 | O31: =$D$10*$C$10 -> 0 | P31: =$D$10*$C$10 -> 0 | Q31: =$D$10*$C$10 -> 0 | R31: =$D$10*$C$10 -> 0 | S31: 0 | T31: =$D$10*$C$10 -> 0 | U31: =$D$10*$C$10 -> 0 | V31: =$D$10*$C$10 -> 0 | W31: =$D$10*$C$10 -> 0 | X31: =$D$10*$C$10 -> 0 | Y31: =$D$10*$C$10 -> 0 | Z31: 0 | AA31: =$D$10*$C$10 -> 0 | AB31: =$D$10*$C$10 -> 0 | AC31: =$D$10*$C$10 -> 0 | AD31: =$D$9*$C$10 -> 0 | AE31: =$D$10*$C$10 -> 0 | AF31: =$D$10*$C$10 -> 0 | AG31: 0 | AH31: =$D$10*$C$10 -> 0 | AI31: =$D$10*$C$10 -> 0 | AJ31: =$D$10*$C$10 -> 0 | AK31: =$D$10*$C$10 -> 0 | AL31: =$D$10*$C$10 -> 0 | AM31: =$D$10*$C$10 -> 0 | AN31: 0 | AO31: =$D$10*$C$10 -> 0 | AP31: =$D$10*$C$10 -> 0 | AQ31: =$D$10*$C$10 -> 0 | AR31: =$D$10*$C$10 -> 0 | AS31: =$D$10*$C$10 -> 0 | AT31: =$D$10*$C$10 -> 0 | AU31: =SUM(F31:AT31) -> 0
B32: PRESTAMO FRESHOUSE 2 | C32: 1.5
B35: TOTAL INGRESOS | F35: =SUM(F30:F34) -> 60000000 | G35: =SUM(G30:G34) -> 50000 | H35: =SUM(H30:H34) -> 50000 | I35: =SUM(I30:I34) -> 50000 | J35: =SUM(J30:J34) -> 50000 | K35: =SUM(K30:K34) -> 50000 | L35: =SUM(L30:L34) -> 0 | M35: =SUM(M30:M34) -> 50000 | ... R35: =SUM(R30:R34) -> 50000 | S35: =SUM(S34:S34) -> 0 | T35: =SUM(T30:T34) -> 50000 | U35: =SUM(U30:U34) -> 50000 | V35: =SUM(V30:V34) -> 50000 | W35: =SUM(W30:W34) -> 50000 | X35: =SUM(X30:X34) -> 50000 | Y35: =SUM(Y30:Y34) -> 50000 | Z35: =SUM(Z34:Z34) -> 0 | AA35: =SUM(AA30:AA34) -> 0 | AB35: =SUM(AB30:AB34) -> 50000 | AC35: =SUM(AC30:AC34) -> 50000 | AD35: =SUM(AD30:AD34) -> 50000 | AE35: =SUM(AE30:AE34) -> 50000 | AF35: =SUM(AF30:AF34) -> 50000 | AG35: =SUM(AG34:AG34) -> 0 | AH35: =SUM(AH30:AH34) -> 50000 | AI35: =SUM(AI30:AI34) -> 50000 | AJ35: =SUM(AJ30:AJ34) -> 50000 | AK35: =SUM(AK30:AK34) -> 50000 | AL35: =SUM(AL30:AL34) -> 50000 | AM35: =SUM(AM30:AM34) -> 50000 | AN35: =SUM(AN34:AN34) -> 0 | AO35: =SUM(AO30:AO34) -> 50000 | AP35: =SUM(AP30:AP34) -> 50000 | AQ35: =SUM(AQ30:AQ34) -> 50000 | AR35: =SUM(AR30:AR34) -> 50000 | AS35: =SUM(AS30:AS34) -> 50000 | AT35: =SUM(AT30:AT34) -> 50000 | AU35: =SUM(F35:AT35) -> 61700000
B36: ACUMULADO DE INGRESOS | F36: =F35 -> 60000000 | G36: =F36+G35 -> 60050000 | H36: =G36+H35 -> 60100000 | I36: =H36+I35 -> 60150000 | J36: =I36+J35 -> 60200000 | K36: =J36+K35 -> 60250000 | L36: =K36+L35 -> 60250000 | M36: =L36+M35 -> 60300000 | N36: =M36+N35 -> 60350000 | ... AU36: =AT36+AU35 -> 123400000
B39: SALDOS
B41: TOTAL SALDO | F41: =F35-F22 -> 59945000 | G41: =G35-G22 -> -5000 | H41: =H35-H22 -> -5000 | I41: =I35-I22 -> -5000 | J41: =J35-J22 -> -5000 | K41: =K35-K22 -> -5000 | L41: =L35-L22 -> 0 | M41: =M35-M22 -> 0 | ... AT41: =AT35-AT22 -> 0 | AU41: =SUM(F41:AT41) -> 59920000
B42: ACUMULADO DE SALDOS | F42: =F41 -> 59945000 | G42: =F42+G41 -> 59940000 | H42: =G42+H41 -> 59935000 | I42: =H42+I41 -> 59930000 | J42: =I42+J41 -> 59925000 | K42: =J42+K41 -> 59920000 | L42: =K42+L41 -> 59920000 | M42: =L42+M41 -> 59920000 | N42: =M42+N41 -> 59920000 | ... AU42: =AT42+AU41 -> 119840000
F44: =420000/65 -> 6461.5385

Sheet RESANE
A2: EDIFICIO TORRE VERDE | Q2: CANTIDAD EJECUTADA | AC2: TOTAL EJECUTADO | AQ2: TOTAL EJECUTADO | BE2: TOTAL EJECUTADO | BG2: CANTIDAD EJECUTADA | BS2: TOTAL EJECUTADO | CG2: TOTAL EJECUTADO | CU2: TOTAL EJECUTADO
A3: REALIZADO POR: ARQ ALEXIS BETANCOURT | E3: DIMENSIONES | H3: DESCUENTOS | Q3: 45817 | S3: =+Q3+1 -> 45818 | U3: =+S3+1 -> 45819 | W3: =+U3+1 -> 45820 | Y3: =+W3+1 -> 45821 | AA3: =+Y3+1 -> 45822 | AC3: SEMANA 1 | AE3: =AA3+2 -> 45824 | AG3: =+AE3+1 -> 45825 | AI3: =+AG3+1 -> 45826 | AK3: =+AI3+1 -> 45827 | AM3: =+AK3+1 -> 45828 | AO3: =+AM3+1 -> 45829 | AQ3: SEMANA 2 | AS3: =AO3+2 -> 45831 | AU3: =+AS3+1 -> 45832 | AW3: =+AU3+1 -> 45833 | AY3: =+AW3+1 -> 45834 | BA3: =+AY3+1 -> 45835 | BC3: =+BA3+1 -> 45836 | BE3: SEMANA 3 | BG3: =BC3+2 -> 45838 | BI3: =+BG3+1 -> 45839 | BK3: =+BI3+1 -> 45840 | BM3: =+BK3+1 -> 45841 | BO3: =+BM3+1 -> 45842 | BQ3: =+BO3+1 -> 45843 | BS3: SEMANA 4 | BU3: =BQ3+2 -> 45845 | BW3: =+BU3+1 -> 45846 | BY3: =+BW3+1 -> 45847 | CA3: =+BY3+1 -> 45848 | CC3: =+CA3+1 -> 45849 | CE3: =+CC3+1 -> 45850 | CG3: SEMANA 5 | CI3: =CE3+2 -> 45852 | CK3: =+CI3+1 -> 45853 | CM3: =+CK3+1 -> 45854 | CO3: =+CM3+1 -> 45855 | CQ3: =+CO3+1 -> 45856 | CS3: =+CQ3+1 -> 45857 | CU3: SEMANA 6
A4: TORRE | B4: FACHADA | C4: SECCIÓN | D4: DESCRIPCIÓN | E4: ALTO | F4: ANCHO | G4: TOTAL (M2) | H4: ALTO | I4: ANCHO | J4: CANTIDAD | K4: TOTAL (M2) | L4: ÁREA TOTAL (BLANCO) | M4: ÁREA TOTAL (VERDE) | N4: ÁREA TOTAL (NEGRO) | O4: CIELO RASO | Q4: M2 | R4: % | S4: M2 | T4: % | U4: M2 | V4: % | W4: M2 | X4: % | Y4: M2 | Z4: % | AB4: % | AC4: M2 | AD4: % | AE4: M2 | AF4: % | AG4: M2 | AH4: % | AI4: M2 | AJ4: % | AK4: M2 | AL4: % | AM4: M2 | AN4: % | AP4: % | AQ4: M2 | AR4: % | AS4: M2 | AT4: % | AU4: M2 | AV4: % | AW4: M2 | AX4: % | AY4: M2 | AZ4: % | BA4: M2 | BB4: % | BD4: % | BE4: M2 | BF4: % | BG4: M2 | BH4: % | BI4: M2 | BJ4: % | BK4: M2 | BL4: % | BM4: M2 | BN4: % | BO4: M2 | BP4: % | BR4: % | BS4: M2 | BT4: % | BU4: M2 | BV4: % | BW4: M2 | BX4: % | BY4: M2 | BZ4: % | CA4: M2 | CB4: % | CC4: M2 | CD4: % | CF4: % | CG4: M2 | CH4: % | CI4: M2 | CJ4: % | CK4: M2 | CL4: % | CM4: M2 | CN4: % | CO4: M2 | CP4: % | CQ4: M2 | CR4: % | CT4: % | CU4: M2 | CV4: %
A5: B | B5: CULATA IZQ | C5: 1 | D5: Muro con ventana (Negro) | E5: =(2.5*14)+0.6 -> 35.6 | F5: 9.7 | G5: =E5*F5 -> 345.32 | H5: 1.5 | I5: 1.2 | J5: 14 | K5: =(H5*I5)*J5 -> 25.2 | N5: =G5-(K5+K6) -> 318.86 | P5: =SUM(L5:O5) -> 318.86 | Q5: 0 | R5: =Q5/$P5 -> 0 | S5: 0 | T5: =S5/$P5 -> 0 | U5: 0 | V5: =U5/$P5 -> 0 | W5: 0 | X5: =W5/$P5 -> 0 | Y5: 0 | Z5: =Y5/$P5 -> 0 | AA5: 0 | AB5: =AA5/$P5 -> 0 | AC5: =Q5+S5+U5+W5+Y5+AA5 -> 0 | AD5: =AC5/$P5 -> 0 | AE5: 0 | AF5: =AE5/$P5 -> 0 | AG5: 0 | AH5: =AG5/$P5 -> 0 | AI5: 0 | AJ5: =AI5/$P5 -> 0 | AK5: 0 | AL5: =AK5/$P5 -> 0 | AM5: 0 | AN5: =AM5/$P5 -> 0 | AO5: 0 | AP5: =AO5/$P5 -> 0 | AQ5: =AE5+AG5+AI5+AK5+AM5+AO5 -> 0 | AR5: =AQ5/$P5 -> 0 | AS5: 0 | AT5: =AS5/$P5 -> 0 | AU5: 0 | AV5: =AU5/$P5 -> 0 | AW5: 0 | AX5: =AW5/$P5 -> 0 | AY5: 0 | AZ5: =AY5/$P5 -> 0 | BA5: 0 | BB5: =BA5/$P5 -> 0 | BC5: 0 | BD5: =BC5/$P5 -> 0 | BE5: =AS5+AU5+AW5+AY5+BA5+BC5 -> 0 | BF5: =BE5/$P5 -> 0 | BG5: 0 | BH5: =BG5/$P5 -> 0 | BI5: 0 | BJ5: =BI5/$P5 -> 0 | BK5: 0 | BL5: =BK5/$P5 -> 0 | BM5: 0 | BN5: =BM5/$P5 -> 0 | BO5: 0 | BP5: =BO5/$P5 -> 0 | BQ5: 0 | BR5: =BQ5/$P5 -> 0 | BS5: =BG5+BI5+BK5+BM5+BO5+BQ5 -> 0 | BT5: =BS5/$P5 -> 0 | BU5: 0 | BV5: =BU5/$P5 -> 0 | BW5: 0 | BX5: =BW5/$P5 -> 0 | BY5: 0 | BZ5: =BY5/$P5 -> 0 | CA5: 0 | CB5: =CA5/$P5 -> 0 | CC5: 0 | CD5: =CC5/$P5 -> 0 | CE5: 0 | CF5: =CE5/$P5 -> 0 | CG5: =BU5+BW5+BY5+CA5+CC5+CE5 -> 0 | CH5: =CG5/$P5 -> 0 | CI5: 0 | CJ5: =CI5/$P5 -> 0 | CK5: 0 | CL5: =CK5/$P5 -> 0 | CM5: 0 | CN5: =CM5/$P5 -> 0 | CO5: 0 | CP5: =CO5/$P5 -> 0 | CQ5: 0 | CR5: =CQ5/$P5 -> 0 | CS5: 0 | CT5: =CS5/$P5 -> 0 | CU5: =CI5+CK5+CM5+CO5+CQ5+CS5 -> 0 | CV5: =CU5/$P5 -> 0
H6: 0.3 | I6: 0.3 | J6: 14 | K6: =(H6*I6)*J6 -> 1.26 | P6: =SUM(L6:O6) -> 0 | Q6: 0 | S6: 0 | U6: 0 | W6: 0 | Y6: 0 | AA6: 0 | AC6: =Q6+S6+U6+W6+Y6+AA6 -> 0 | AE6: 0 | AG6: 0 | AI6: 0 | AK6: 0 | AM6: 0 | AO6: 0 | AQ6: =AE6+AG6+AI6+AK6+AM6+AO6 -> 0 | AS6: 0 | AU6: 0 | AW6: 0 | AY6: 0 | BA6: 0 | BC6: 0 | BE6: =AS6+AU6+AW6+AY6+BA6+BC6 -> 0 | BG6: 0 | BI6: 0 | BK6: 0 | BM6: 0 | BO6: 0 | BQ6: 0 | BS6: =BG6+BI6+BK6+BM6+BO6+BQ6 -> 0 | BU6: 0 | BW6: 0 | BY6: 0 | CA6: 0 | CC6: 0 | CE6: 0 | CG6: =BU6+BW6+BY6+CA6+CC6+CE6 -> 0 | CI6: 0 | CK6: 0 | CM6: 0 | CO6: 0 | CQ6: 0 | CS6: 0 | CU6: =CI6+CK6+CM6+CO6+CQ6+CS6 -> 0
B7: POSTERIOR | C7: 2 | D7: Muro con ventana (Negro) | E7: =E5 -> 35.6 | F7: 6.1 | G7: =E7*F7 -> 217.16 | H7: 1.5 | I7: 1.2 | J7: 28 | K7: =(H7*I7)*J7 -> 50.4 | N7: =G7-K7 -> 166.76 | P7: =SUM(L7:O7) -> 166.76 | Q7: 0 | R7: =Q7/$P7 -> 0 | S7: 0 | T7: =S7/$P7 -> 0 | U7: 0 | V7: =U7/$P7 -> 0 | W7: 0 | X7: =W7/$P7 -> 0 | Y7: 0 | Z7: =Y7/$P7 -> 0 | AA7: 0 | AB7: =AA7/$P7 -> 0 | AC7: =Q7+S7+U7+W7+Y7+AA7 -> 0 | AD7: =AC7/$P7 -> 0 | AE7: 0 | AF7: =AE7/$P7 -> 0 | AG7: 0 | AH7: =AG7/$P7 -> 0 | AI7: 0 | AJ7: =AI7/$P7 -> 0 | AK7: 0 | AL7: =AK7/$P7 -> 0 | AM7: 0 | AN7: =AM7/$P7 -> 0 | AO7: 0 | AP7: =AO7/$P7 -> 0 | AQ7: =AE7+AG7+AI7+AK7+AM7+AO7 -> 0 | AR7: =AQ7/$P7 -> 0 | AS7: 0 | AT7: =AS7/$P7 -> 0 | AU7: 0 | AV7: =AU7/$P7 -> 0 | AW7: 0 | AX7: =AW7/$P7 -> 0 | AY7: 0 | AZ7: =AY7/$P7 -> 0 | BA7: 0 | BB7: =BA7/$P7 -> 0 | BC7: 0 | BD7: =BC7/$P7 -> 0 | BE7: =AS7+AU7+AW7+AY7+BA7+BC7 -> 0 | BF7: =BE7/$P7 -> 0 | BG7: 0 | BH7: =BG7/$P7 -> 0 | BI7: 0 | BJ7: =BI7/$P7 -> 0 | BK7: 0 | BL7: =BK7/$P7 -> 0 | BM7: 0 | BN7: =BM7/$P7 -> 0 | BO7: 0 | BP7: =BO7/$P7 -> 0 | BQ7: 0 | BR7: =BQ7/$P7 -> 0 | BS7: =BG7+BI7+BK7+BM7+BO7+BQ7 -> 0 | BT7: =BS7/$P7 -> 0 | BU7: 0 | BV7: =BU7/$P7 -> 0 | BW7: 0 | BX7: =BW7/$P7 -> 0 | BY7: 0 | BZ7: =BY7/$P7 -> 0 | CA7: 0 | CB7: =CA7/$P7 -> 0 | CC7: 0 | CD7: =CC7/$P7 -> 0 | CE7: 0 | CF7: =CE7/$P7 -> 0 | CG7: =BU7+BW7+BY7+CA7+CC7+CE7 -> 0 | CH7: =CG7/$P7 -> 0 | CI7: 0 | CJ7: =CI7/$P7 -> 0 | CK7: 0 | CL7: =CK7/$P7 -> 0 | CM7: 0 | CN7: =CM7/$P7 -> 0 | CO7: 0 | CP7: =CO7/$P7 -> 0 | CQ7: 0 | CR7: =CQ7/$P7 -> 0 | CS7: 0 | CT7: =CS7/$P7 -> 0 | CU7: =CI7+CK7+CM7+CO7+CQ7+CS7 -> 0 | CV7: =CU7/$P7 -> 0
C8: 3 | D8: Muro escaleras (Negro) | E8: 35 | F8: 3.1 | G8: =E8*F8 -> 108.5 | H8: 0.25 | I8: 3.1 | J8: 14 | K8: =(H8*I8)*J8 -> 10.85 | N8: =G8-K8 -> 97.65 | P8: =SUM(L8:O8) -> 97.65 | Q8: 0 | R8: =Q8/$P8 -> 0 | S8: 0 | T8: =S8/$P8 -> 0 | U8: 0 | V8: =U8/$P8 -> 0 | W8: 0 | X8: =W8/$P8 -> 0 | Y8: 0 | Z8: =Y8/$P8 -> 0 | AA8: 0 | AB8: =AA8/$P8 -> 0 | AC8: =Q8+S8+U8+W8+Y8+AA8 -> 0 | AD8: =AC8/$P8 -> 0 | AE8: 0 | AF8: =AE8/$P8 -> 0 | AG8: 0 | AH8: =AG8/$P8 -> 0 | AI8: 0 | AJ8: =AI8/$P8 -> 0 | AK8: 0 | AL8: =AK8/$P8 -> 0 | AM8: 0 | AN8: =AM8/$P8 -> 0 | AO8: 0 | AP8: =AO8/$P8 -> 0 | AQ8: =AE8+AG8+AI8+AK8+AM8+AO8 -> 0 | AR8: =AQ8/$P8 -> 0 | AS8: 0 | AT8: =AS8/$P8 -> 0 | AU8: 0 | AV8: =AU8/$P8 -> 0 | AW8: 0 | AX8: =AW8/$P8 -> 0 | AY8: 0 | AZ8: =AY8/$P8 -> 0 | BA8: 0 | BB8: =BA8/$P8 -> 0 | BC8: 0 | BD8: =BC8/$P8 -> 0 | BE8: =AS8+AU8+AW8+AY8+BA8+BC8 -> 0 | BF8: =BE8/$P8 -> 0 | BG8: 0 | BH8: =BG8/$P8 -> 0 | BI8: 0 | BJ8: =BI8/$P8 -> 0 | BK8: 0 | BL8: =BK8/$P8 -> 0 | BM8: 0 | BN8: =BM8/$P8 -> 0 | BO8: 0 | BP8: =BO8/$P8 -> 0 | BQ8: 0 | BR8: =BQ8/$P8 -> 0 | BS8: =BG8+BI8+BK8+BM8+BO8+BQ8 -> 0 | BT8: =BS8/$P8 -> 0 | BU8: 0 | BV8: =BU8/$P8 -> 0 | BW8: 0 | BX8: =BW8/$P8 -> 0 | BY8: 0 | BZ8: =BY8/$P8 -> 0 | CA8: 0 | CB8: =CA8/$P8 -> 0 | CC8: 0 | CD8: =CC8/$P8 -> 0 | CE8: 0 | CF8: =CE8/$P8 -> 0 | CG8: =BU8+BW8+BY8+CA8+CC8+CE8 -> 0 | CH8: =CG8/$P8 -> 0 | CI8: 0 | CJ8: =CI8/$P8 -> 0 | CK8: 0 | CL8: =CK8/$P8 -> 0 | CM8: 0 | CN8: =CM8/$P8 -> 0 | CO8: 0 | CP8: =CO8/$P8 -> 0 | CQ8: 0 | CR8: =CQ8/$P8 -> 0 | CS8: 0 | CT8: =CS8/$P8 -> 0 | CU8: =CI8+CK8+CM8+CO8+CQ8+CS8 -> 0 | CV8: =CU8/$P8 -> 0
C9: 4 | D9: Muro escaleras (Blanco) | E9: 35 | F9: 2.15 | G9: =E9*F9 -> 75.25 | L9: =G9-K9 -> 75.25 | P9: =SUM(L9:O9) -> 75.25 | Q9: 0 | R9: =Q9/$P9 -> 0 | S9: 0 | T9: =S9/$P9 -> 0 | U9: 0 | V9: =U9/$P9 -> 0 | W9: 0 | X9: =W9/$P9 -> 0 | Y9: 0 | Z9: =Y9/$P9 -> 0 | AA9: 0 | AB9: =AA9/$P9 -> 0 | AC9: =Q9+S9+U9+W9+Y9+AA9 -> 0 | AD9: =AC9/$P9 -> 0 | AE9: 0 | AF9: =AE9/$P9 -> 0 | AG9: 0 | AH9: =AG9/$P9 -> 0 | AI9: 0 | AJ9: =AI9/$P9 -> 0 | AK9: 0 | AL9: =AK9/$P9 -> 0 | AM9: 0 | AN9: =AM9/$P9 -> 0 | AO9: 0 | AP9: =AO9/$P9 -> 0 | AQ9: =AE9+AG9+AI9+AK9+AM9+AO9 -> 0 | AR9: =AQ9/$P9 -> 0 | AS9: 0 | AT9: =AS9/$P9 -> 0 | AU9: 0 | AV9: =AU9/$P9 -> 0 | AW9: 0 | AX9: =AW9/$P9 -> 0 | AY9: 0 | AZ9: =AY9/$P9 -> 0 | BA9: 0 | BB9: =BA9/$P9 -> 0 | BC9: 0 | BD9: =BC9/$P9 -> 0 | BE9: =AS9+AU9+AW9+AY9+BA9+BC9 -> 0 | BF9: =BE9/$P9 -> 0 | BG9: 0 | BH9: =BG9/$P9 -> 0 | BI9: 0 | BJ9: =BI9/$P9 -> 0 | BK9: 0 | BL9: =BK9/$P9 -> 0 | BM9: 0 | BN9: =BM9/$P9 -> 0 | BO9: 0 | BP9: =BO9/$P9 -> 0 | BQ9: 0 | BR9: =BQ9/$P9 -> 0 | BS9: =BG9+BI9+BK9+BM9+BO9+BQ9 -> 0 | BT9: =BS9/$P9 -> 0 | BU9: 0 | BV9: =BU9/$P9 -> 0 | BW9: 0 | BX9: =BW9/$P9 -> 0 | BY9: 0 | BZ9: =BY9/$P9 -> 0 | CA9: 0 | CB9: =CA9/$P9 -> 0 | CC9: 0 | CD9: =CC9/$P9 -> 0 | CE9: 0 | CF9: =CE9/$P9 -> 0 | CG9: =BU9+BW9+BY9+CA9+CC9+CE9 -> 0 | CH9: =CG9/$P9 -> 0 | CI9: 0 | CJ9: =CI9/$P9 -> 0 | CK9: 0 | CL9: =CK9/$P9 -> 0 | CM9: 0 | CN9: =CM9/$P9 -> 0 | CO9: 0 | CP9: =CO9/$P9 -> 0 | CQ9: 0 | CR9: =CQ9/$P9 -> 0 | CS9: 0 | CT9: =CS9/$P9 -> 0 | CU9: =CI9+CK9+CM9+CO9+CQ9+CS9 -> 0 | CV9: =CU9/$P9 -> 0
C10: 5 | D10: Muro escaleras (Blanco) | E10: =E8 -> 35 | F10: 1.8 | G10: =E10*F10 -> 63 | L10: =G10-K10 -> 63 | P10: =SUM(L10:O10) -> 63 | Q10: 0 | R10: =Q10/$P10 -> 0 | S10: 0 | T10: =S10/$P10 -> 0 | U10: 0 | V10: =U10/$P10 -> 0 | W10: 0 | X10: =W10/$P10 -> 0 | Y10: 0 | Z10: =Y10/$P10 -> 0 | AA10: 0 | AB10: =AA10/$P10 -> 0 | AC10: =Q10+S10+U10+W10+Y10+AA10 -> 0 | AD10: =AC10/$P10 -> 0 | AE10: 0 | AF10: =AE10/$P10 -> 0 | AG10: 0 | AH10: =AG10/$P10 -> 0 | AI10: 0 | AJ10: =AI10/$P10 -> 0 | AK10: 0 | AL10: =AK10/$P10 -> 0 | AM10: 0 | AN10: =AM10/$P10 -> 0 | AO10: 0 | AP10: =AO10/$P10 -> 0 | AQ10: =AE10+AG10+AI10+AK10+AM10+AO10 -> 0 | AR10: =AQ10/$P10 -> 0 | AS10: 0 | AT10: =AS10/$P10 -> 0 | AU10: 0 | AV10: =AU10/$P10 -> 0 | AW10: 0 | AX10: =AW10/$P10 -> 0 | AY10: 0 | AZ10: =AY10/$P10 -> 0 | BA10: 0 | BB10: =BA10/$P10 -> 0 | BC10: 0 | BD10: =BC10/$P10 -> 0 | BE10: =AS10+AU10+AW10+AY10+BA10+BC10 -> 0 | BF10: =BE10/$P10 -> 0 | BG10: 0 | BH10: =BG10/$P10 -> 0 | BI10: 0 | BJ10: =BI10/$P10 -> 0 | BK10: 0 | BL10: =BK10/$P10 -> 0 | BM10: 0 | BN10: =BM10/$P10 -> 0 | BO10: 0 | BP10: =BO10/$P10 -> 0 | BQ10: 0 | BR10: =BQ10/$P10 -> 0 | BS10: =BG10+BI10+BK10+BM10+BO10+BQ10 -> 0 | BT10: =BS10/$P10 -> 0 | BU10: 0 | BV10: =BU10/$P10 -> 0 | BW10: 0 | BX10: =BW10/$P10 -> 0 | BY10: 0 | BZ10: =BY10/$P10 -> 0 | CA10: 0 | CB10: =CA10/$P10 -> 0 | CC10: 0 | CD10: =CC10/$P10 -> 0 | CE10: 0 | CF10: =CE10/$P10 -> 0 | CG10: =BU10+BW10+BY10+CA10+CC10+CE10 -> 0 | CH10: =CG10/$P10 -> 0 | CI10: 0 | CJ10: =CI10/$P10 -> 0 | CK10: 0 | CL10: =CK10/$P10 -> 0 | CM10: 0 | CN10: =CM10/$P10 -> 0 | CO10: 0 | CP10: =CO10/$P10 -> 0 | CQ10: 0 | CR10: =CQ10/$P10 -> 0 | CS10: 0 | CT10: =CS10/$P10 -> 0 | CU10: =CI10+CK10+CM10+CO10+CQ10+CS10 -> 0 | CV10: =CU10/$P10 -> 0
C11: 6 | D11: Muro escaleras (Blanco) | E11: =E8 -> 35 | F11: 2.05 | G11: =E11*F11 -> 71.75 | L11: =G11-K11 -> 71.75 | P11: =SUM(L11:O11) -> 71.75 | Q11: 0 | R11: =Q11/$P11 -> 0 | S11: 0 | T11: =S11/$P11 -> 0 | U11: 0 | V11: =U11/$P11 -> 0 | W11: 0 | X11: =W11/$P11 -> 0 | Y11: 0 | Z11: =Y11/$P11 -> 0 | AA11: 0 | AB11: =AA11/$P11 -> 0 | AC11: =Q11+S11+U11+W11+Y11+AA11 -> 0 | AD11: =AC11/$P11 -> 0 | AE11: 0 | AF11: =AE11/$P11 -> 0 | AG11: 0 | AH11: =AG11/$P11 -> 0 | AI11: 0 | AJ11: =AI11/$P11 -> 0 | AK11: 0 | AL11: =AK11/$P11 -> 0 | AM11: 0 | AN11: =AM11/$P11 -> 0 | AO11: 0 | AP11: =AO11/$P11 -> 0 | AQ11: =AE11+AG11+AI11+AK11+AM11+AO11 -> 0 | AR11: =AQ11/$P11 -> 0 | AS11: 0 | AT11: =AS11/$P11 -> 0 | AU11: 0 | AV11: =AU11/$P11 -> 0 | AW11: 0 | AX11: =AW11/$P11 -> 0 | AY11: 0 | AZ11: =AY11/$P11 -> 0 | BA11: 0 | BB11: =BA11/$P11 -> 0 | BC11: 0 | BD11: =BC11/$P11 -> 0 | BE11: =AS11+AU11+AW11+AY11+BA11+BC11 -> 0 | BF11: =BE11/$P11 -> 0 | BG11: 0 | BH11: =BG11/$P11 -> 0 | BI11: 0 | BJ11: =BI11/$P11 -> 0 | BK11: 0 | BL11: =BK11/$P11 -> 0 | BM11: 0 | BN11: =BM11/$P11 -> 0 | BO11: 0 | BP11: =BO11/$P11 -> 0 | BQ11: 0 | BR11: =BQ11/$P11 -> 0 | BS11: =BG11+BI11+BK11+BM11+BO11+BQ11 -> 0 | BT11: =BS11/$P11 -> 0 | BU11: 0 | BV11: =BU11/$P11 -> 0 | BW11: 0 | BX11: =BW11/$P11 -> 0 | BY11: 0 | BZ11: =BY11/$P11 -> 0 | CA11: 0 | CB11: =CA11/$P11 -> 0 | CC11: 0 | CD11: =CC11/$P11 -> 0 | CE11: 0 | CF11: =CE11/$P11 -> 0 | CG11: =BU11+BW11+BY11+CA11+CC11+CE11 -> 0 | CH11: =CG11/$P11 -> 0 | CI11: 0 | CJ11: =CI11/$P11 -> 0 | CK11: 0 | CL11: =CK11/$P11 -> 0 | CM11: 0 | CN11: =CM11/$P11 -> 0 | CO11: 0 | CP11: =CO11/$P11 -> 0 | CQ11: 0 | CR11: =CQ11/$P11 -> 0 | CS11: 0 | CT11: =CS11/$P11 -> 0 | CU11: =CI11+CK11+CM11+CO11+CQ11+CS11 -> 0 | CV11: =CU11/$P11 -> 0
C12: 7 | D12: Antepecho poseta PF (Blanco) (X14) | E12: 0.5 | F12: 1.44 | G12: =E12*F12*14 -> 10.08 | L12: =G12-K12 -> 10.08 | P12: =SUM(L12:O12) -> 10.08 | Q12: 0 | R12: =Q12/$P12 -> 0 | S12: 0 | T12: =S12/$P12 -> 0 | U12: 0 | V12: =U12/$P12 -> 0 | W12: 0 | X12: =W12/$P12 -> 0 | Y12: 0 | Z12: =Y12/$P12 -> 0 | AA12: 0 | AB12: =AA12/$P12 -> 0 | AC12: =Q12+S12+U12+W12+Y12+AA12 -> 0 | AD12: =AC12/$P12 -> 0 | AE12: 0 | AF12: =AE12/$P12 -> 0 | AG12: 0 | AH12: =AG12/$P12 -> 0 | AI12: 0 | AJ12: =AI12/$P12 -> 0 | AK12: 0 | AL12: =AK12/$P12 -> 0 | AM12: 0 | AN12: =AM12/$P12 -> 0 | AO12: 0 | AP12: =AO12/$P12 -> 0 | AQ12: =AE12+AG12+AI12+AK12+AM12+AO12 -> 0 | AR12: =AQ12/$P12 -> 0 | AS12: 0 | AT12: =AS12/$P12 -> 0 | AU12: 0 | AV12: =AU12/$P12 -> 0 | AW12: 0 | AX12: =AW12/$P12 -> 0 | AY12: 0 | AZ12: =AY12/$P12 -> 0 | BA12: 0 | BB12: =BA12/$P12 -> 0 | BC12: 0 | BD12: =BC12/$P12 -> 0 | BE12: =AS12+AU12+AW12+AY12+BA12+BC12 -> 0 | BF12: =BE12/$P12 -> 0 | BG12: 0 | BH12: =BG12/$P12 -> 0 | BI12: 0 | BJ12: =BI12/$P12 -> 0 | BK12: 0 | BL12: =BK12/$P12 -> 0 | BM12: 0 | BN12: =BM12/$P12 -> 0 | BO12: 0 | BP12: =BO12/$P12 -> 0 | BQ12: 0 | BR12: =BQ12/$P12 -> 0 | BS12: =BG12+BI12+BK12+BM12+BO12+BQ12 -> 0 | BT12: =BS12/$P12 -> 0 | BU12: 0 | BV12: =BU12/$P12 -> 0 | BW12: 0 | BX12: =BW12/$P12 -> 0 | BY12: 0 | BZ12: =BY12/$P12 -> 0 | CA12: 0 | CB12: =CA12/$P12 -> 0 | CC12: 0 | CD12: =CC12/$P12 -> 0 | CE12: 0 | CF12: =CE12/$P12 -> 0 | CG12: =BU12+BW12+BY12+CA12+CC12+CE12 -> 0 | CH12: =CG12/$P12 -> 0 | CI12: 0 | CJ12: =CI12/$P12 -> 0 | CK12: 0 | CL12: =CK12/$P12 -> 0 | CM12: 0 | CN12: =CM12/$P12 -> 0 | CO12: 0 | CP12: =CO12/$P12 -> 0 | CQ12: 0 | CR12: =CQ12/$P12 -> 0 | CS12: 0 | CT12: =CS12/$P12 -> 0 | CU12: =CI12+CK12+CM12+CO12+CQ12+CS12 -> 0 | CV12: =CU12/$P12 -> 0
C13: 8 | D13: Muro escaleras (Blanco) | E13: 35 | F13: 5.18 | G13: =E13*F13 -> 181.3 | H13: 0.25 | I13: 3.1 | J13: 14 | K13: =(H13*I13)*J13 -> 10.85 | L13: =G13-K13 -> 170.45 | P13: =SUM(L13:O13) -> 170.45 | Q13: 0 | R13: =Q13/$P13 -> 0 | S13: 0 | T13: =S13/$P13 -> 0 | U13: 0 | V13: =U13/$P13 -> 0 | W13: 0 | X13: =W13/$P13 -> 0 | Y13: 0 | Z13: =Y13/$P13 -> 0 | AA13: 0 | AB13: =AA13/$P13 -> 0 | AC13: =Q13+S13+U13+W13+Y13+AA13 -> 0 | AD13: =AC13/$P13 -> 0 | AE13: 0 | AF13: =AE13/$P13 -> 0 | AG13: 0 | AH13: =AG13/$P13 -> 0 | AI13: 0 | AJ13: =AI13/$P13 -> 0 | AK13: 0 | AL13: =AK13/$P13 -> 0 | AM13: 0 | AN13: =AM13/$P13 -> 0 | AO13: 0 | AP13: =AO13/$P13 -> 0 | AQ13: =AE13+AG13+AI13+AK13+AM13+AO13 -> 0 | AR13: =AQ13/$P13 -> 0 | AS13: 0 | AT13: =AS13/$P13 -> 0 | AU13: 0 | AV13: =AU13/$P13 -> 0 | AW13: 0 | AX13: =AW13/$P13 -> 0 | AY13: 0 | AZ13: =AY13/$P13 -> 0 | BA13: 0 | BB13: =BA13/$P13 -> 0 | BC13: 0 | BD13: =BC13/$P13 -> 0 | BE13: =AS13+AU13+AW13+AY13+BA13+BC13 -> 0 | BF13: =BE13/$P13 -> 0 | BG13: 0 | BH13: =BG13/$P13 -> 0 | BI13: 0 | BJ13: =BI13/$P13 -> 0 | BK13: 0 | BL13: =BK13/$P13 -> 0 | BM13: 0 | BN13: =BM13/$P13 -> 0 | BO13: 0 | BP13: =BO13/$P13 -> 0 | BQ13: 0 | BR13: =BQ13/$P13 -> 0 | BS13: =BG13+BI13+BK13+BM13+BO13+BQ13 -> 0 | BT13: =BS13/$P13 -> 0 | BU13: 0 | BV13: =BU13/$P13 -> 0 | BW13: 0 | BX13: =BW13/$P13 -> 0 | BY13: 0 | BZ13: =BY13/$P13 -> 0 | CA13: 0 | CB13: =CA13/$P13 -> 0 | CC13: 0 | CD13: =CC13/$P13 -> 0 | CE13: 0 | CF13: =CE13/$P13 -> 0 | CG13: =BU13+BW13+BY13+CA13+CC13+CE13 -> 0 | CH13: =CG13/$P13 -> 0 | CI13: 0 | CJ13: =CI13/$P13 -> 0 | CK13: 0 | CL13: =CK13/$P13 -> 0 | CM13: 0 | CN13: =CM13/$P13 -> 0 | CO13: 0 | CP13: =CO13/$P13 -> 0 | CQ13: 0 | CR13: =CQ13/$P13 -> 0 | CS13: 0 | CT13: =CS13/$P13 -> 0 | CU13: =CI13+CK13+CM13+CO13+CQ13+CS13 -> 0 | CV13: =CU13/$P13 -> 0
C14: 8.1 | D14: Cielo raso escaleras (X14) | E14: 1 | F14: =2.15+1.44 -> 3.59 | G14: =E14*F14*14 -> 50.26 | O14: =G14 -> 50.26 | P14: =SUM(L14:O14) -> 50.26 | Q14: 0 | R14: =Q14/$P14 -> 0 | S14: 0 | T14: =S14/$P14 -> 0 | U14: 0 | V14: =U14/$P14 -> 0 | W14: 0 | X14: =W14/$P14 -> 0 | Y14: 0 | Z14: =Y14/$P14 -> 0 | AA14: 0 | AB14: =AA14/$P14 -> 0 | AC14: =Q14+S14+U14+W14+Y14+AA14 -> 0 | AD14: =AC14/$P14 -> 0 | AE14: 0 | AF14: =AE14/$P14 -> 0 | AG14: 0 | AH14: =AG14/$P14 -> 0 | AI14: 0 | AJ14: =AI14/$P14 -> 0 | AK14: 0 | AL14: =AK14/$P14 -> 0 | AM14: 0 | AN14: =AM14/$P14 -> 0 | AO14: 0 | AP14: =AO14/$P14 -> 0 | AQ14: =AE14+AG14+AI14+AK14+AM14+AO14 -> 0 | AR14: =AQ14/$P14 -> 0 | AS14: 0 | AT14: =AS14/$P14 -> 0 | AU14: 0 | AV14: =AU14/$P14 -> 0 | AW14: 0 | AX14: =AW14/$P14 -> 0 | AY14: 0 | AZ14: =AY14/$P14 -> 0 | BA14: 0 | BB14: =BA14/$P14 -> 0 | BC14: 0 | BD14: =BC14/$P14 -> 0 | BE14: =AS14+AU14+AW14+AY14+BA14+BC14 -> 0 | BF14: =BE14/$P14 -> 0 | BG14: 0 | BH14: =BG14/$P14 -> 0 | BI14: 0 | BJ14: =BI14/$P14 -> 0 | BK14: 0 | BL14: =BK14/$P14 -> 0 | BM14: 0 | BN14: =BM14/$P14 -> 0 | BO14: 0 | BP14: =BO14/$P14 -> 0 | BQ14: 0 | BR14: =BQ14/$P14 -> 0 | BS14: =BG14+BI14+BK14+BM14+BO14+BQ14 -> 0 | BT14: =BS14/$P14 -> 0 | BU14: 0 | BV14: =BU14/$P14 -> 0 | BW14: 0 | BX14: =BW14/$P14 -> 0 | BY14: 0 | BZ14: =BY14/$P14 -> 0 | CA14: 0 | CB14: =CA14/$P14 -> 0 | CC14: 0 | CD14: =CC14/$P14 -> 0 | CE14: 0 | CF14: =CE14/$P14 -> 0 | CG14: =BU14+BW14+BY14+CA14+CC14+CE14 -> 0 | CH14: =CG14/$P14 -> 0 | CI14: 0 | CJ14: =CI14/$P14 -> 0 | CK14: 0 | CL14: =CK14/$P14 -> 0 | CM14: 0 | CN14: =CM14/$P14 -> 0 | CO14: 0 | CP14: =CO14/$P14 -> 0 | CQ14: 0 | CR14: =CQ14/$P14 -> 0 | CS14: 0 | CT14: =CS14/$P14 -> 0 | CU14: =CI14+CK14+CM14+CO14+CQ14+CS14 -> 0 | CV14: =CU14/$P14 -> 0
C15: 9 | D15: Muro con ventana (Verde) | E15: =E5 -> 35.6 | F15: 5.3 | G15: =E15*F15 -> 188.68 | H15: 1.5 | I15: 1.2 | J15: 28 | K15: =(H15*I15)*J15 -> 50.4 | M15: =G15-K15 -> 138.28 | P15: =SUM(L15:O15) -> 138.28 | Q15: 0 | R15: =Q15/$P15 -> 0 | S15: 0 | T15: =S15/$P15 -> 0 | U15: 0 | V15: =U15/$P15 -> 0 | W15: 0 | X15: =W15/$P15 -> 0 | Y15: 0 | Z15: =Y15/$P15 -> 0 | AA15: 0 | AB15: =AA15/$P15 -> 0 | AC15: =Q15+S15+U15+W15+Y15+AA15 -> 0 | AD15: =AC15/$P15 -> 0 | AE15: 0 | AF15: =AE15/$P15 -> 0 | AG15: 0 | AH15: =AG15/$P15 -> 0 | AI15: 0 | AJ15: =AI15/$P15 -> 0 | AK15: 0 | AL15: =AK15/$P15 -> 0 | AM15: 0 | AN15: =AM15/$P15 -> 0 | AO15: 0 | AP15: =AO15/$P15 -> 0 | AQ15: =AE15+AG15+AI15+AK15+AM15+AO15 -> 0 | AR15: =AQ15/$P15 -> 0 | AS15: 0 | AT15: =AS15/$P15 -> 0 | AU15: 0 | AV15: =AU15/$P15 -> 0 | AW15: 0 | AX15: =AW15/$P15 -> 0 | AY15: 0 | AZ15: =AY15/$P15 -> 0 | BA15: 0 | BB15: =BA15/$P15 -> 0 | BC15: 0 | BD15: =BC15/$P15 -> 0 | BE15: =AS15+AU15+AW15+AY15+BA15+BC15 -> 0 | BF15: =BE15/$P15 -> 0 | BG15: 0 | BH15: =BG15/$P15 -> 0 | BI15: 0 | BJ15: =BI15/$P15 -> 0 | BK15: 0 | BL15: =BK15/$P15 -> 0 | BM15: 0 | BN15: =BM15/$P15 -> 0 | BO15: 0 | BP15: =BO15/$P15 -> 0 | BQ15: 0 | BR15: =BQ15/$P15 -> 0 | BS15: =BG15+BI15+BK15+BM15+BO15+BQ15 -> 0 | BT15: =BS15/$P15 -> 0 | BU15: 0 | BV15: =BU15/$P15 -> 0 | BW15: 0 | BX15: =BW15/$P15 -> 0 | BY15: 0 | BZ15: =BY15/$P15 -> 0 | CA15: 0 | CB15: =CA15/$P15 -> 0 | CC15: 0 | CD15: =CC15/$P15 -> 0 | CE15: 0 | CF15: =CE15/$P15 -> 0 | CG15: =BU15+BW15+BY15+CA15+CC15+CE15 -> 0 | CH15: =CG15/$P15 -> 0 | CI15: 0 | CJ15: =CI15/$P15 -> 0 | CK15: 0 | CL15: =CK15/$P15 -> 0 | CM15: 0 | CN15: =CM15/$P15 -> 0 | CO15: 0 | CP15: =CO15/$P15 -> 0 | CQ15: 0 | CR15: =CQ15/$P15 -> 0 | CS15: 0 | CT15: =CS15/$P15 -> 0 | CU15: =CI15+CK15+CM15+CO15+CQ15+CS15 -> 0 | CV15: =CU15/$P15 -> 0
C16: 10 | D16: Placa de balcón (Negro) (x14) | E16: 0.3 | F16: 2.91 | G16: =E16*F16*14 -> 12.222 | N16: =G16 -> 12.222 | P16: =SUM(L16:O16) -> 12.222 | Q16: 0 | R16: =Q16/$P16 -> 0 | S16: 0 | T16: =S16/$P16 -> 0 | U16: 0 | V16: =U16/$P16 -> 0 | W16: 0 | X16: =W16/$P16 -> 0 | Y16: 0 | Z16: =Y16/$P16 -> 0 | AA16: 0 | AB16: =AA16/$P16 -> 0 | AC16: =Q16+S16+U16+W16+Y16+AA16 -> 0 | AD16: =AC16/$P16 -> 0 | AE16: 0 | AF16: =AE16/$P16 -> 0 | AG16: 0 | AH16: =AG16/$P16 -> 0 | AI16: 0 | AJ16: =AI16/$P16 -> 0 | AK16: 0 | AL16: =AK16/$P16 -> 0 | AM16: 0 | AN16: =AM16/$P16 -> 0 | AO16: 0 | AP16: =AO16/$P16 -> 0 | AQ16: =AE16+AG16+AI16+AK16+AM16+AO16 -> 0 | AR16: =AQ16/$P16 -> 0 | AS16: 0 | AT16: =AS16/$P16 -> 0 | AU16: 0 | AV16: =AU16/$P16 -> 0 | AW16: 0 | AX16: =AW16/$P16 -> 0 | AY16: 0 | AZ16: =AY16/$P16 -> 0 | BA16: 0 | BB16: =BA16/$P16 -> 0 | BC16: 0 | BD16: =BC16/$P16 -> 0 | BE16: =AS16+AU16+AW16+AY16+BA16+BC16 -> 0 | BF16: =BE16/$P16 -> 0 | BG16: 0 | BH16: =BG16/$P16 -> 0 | BI16: 0 | BJ16: =BI16/$P16 -> 0 | BK16: 0 | BL16: =BK16/$P16 -> 0 | BM16: 0 | BN16: =BM16/$P16 -> 0 | BO16: 0 | BP16: =BO16/$P16 -> 0 | BQ16: 0 | BR16: =BQ16/$P16 -> 0 | BS16: =BG16+BI16+BK16+BM16+BO16+BQ16 -> 0 | BT16: =BS16/$P16 -> 0 | BU16: 0 | BV16: =BU16/$P16 -> 0 | BW16: 0 | BX16: =BW16/$P16 -> 0 | BY16: 0 | BZ16: =BY16/$P16 -> 0 | CA16: 0 | CB16: =CA16/$P16 -> 0 | CC16: 0 | CD16: =CC16/$P16 -> 0 | CE16: 0 | CF16: =CE16/$P16 -> 0 | CG16: =BU16+BW16+BY16+CA16+CC16+CE16 -> 0 | CH16: =CG16/$P16 -> 0 | CI16: 0 | CJ16: =CI16/$P16 -> 0 | CK16: 0 | CL16: =CK16/$P16 -> 0 | CM16: 0 | CN16: =CM16/$P16 -> 0 | CO16: 0 | CP16: =CO16/$P16 -> 0 | CQ16: 0 | CR16: =CQ16/$P16 -> 0 | CS16: 0 | CT16: =CS16/$P16 -> 0 | CU16: =CI16+CK16+CM16+CO16+CQ16+CS16 -> 0 | CV16: =CU16/$P16 -> 0
C17: 10.1 | D17: Cielo raso balcón (X14) | E17: 0.6 | F17: 1.71 | G17: =E17*F17*14 -> 14.364 | O17: =G17 -> 14.364 | P17: =SUM(L17:O17) -> 14.364 | Q17: 0 | R17: =Q17/$P17 -> 0 | S17: 0 | T17: =S17/$P17 -> 0 | U17: 0 | V17: =U17/$P17 -> 0 | W17: 0 | X17: =W17/$P17 -> 0 | Y17: 0 | Z17: =Y17/$P17 -> 0 | AA17: 0 | AB17: =AA17/$P17 -> 0 | AC17: =Q17+S17+U17+W17+Y17+AA17 -> 0 | AD17: =AC17/$P17 -> 0 | AE17: 0 | AF17: =AE17/$P17 -> 0 | AG17: 0 | AH17: =AG17/$P17 -> 0 | AI17: 0 | AJ17: =AI17/$P17 -> 0 | AK17: 0 | AL17: =AK17/$P17 -> 0 | AM17: 0 | AN17: =AM17/$P17 -> 0 | AO17: 0 | AP17: =AO17/$P17 -> 0 | AQ17: =AE17+AG17+AI17+AK17+AM17+AO17 -> 0 | AR17: =AQ17/$P17 -> 0 | AS17: 0 | AT17: =AS17/$P17 -> 0 | AU17: 0 | AV17: =AU17/$P17 -> 0 | AW17: 0 | AX17: =AW17/$P17 -> 0 | AY17: 0 | AZ17: =AY17/$P17 -> 0 | BA17: 0 | BB17: =BA17/$P17 -> 0 | BC17: 0 | BD17: =BC17/$P17 -> 0 | BE17: =AS17+AU17+AW17+AY17+BA17+BC17 -> 0 | BF17: =BE17/$P17 -> 0 | BG17: 0 | BH17: =BG17/$P17 -> 0 | BI17: 0 | BJ17: =BI17/$P17 -> 0 | BK17: 0 | BL17: =BK17/$P17 -> 0 | BM17: 0 | BN17: =BM17/$P17 -> 0 | BO17: 0 | BP17: =BO17/$P17 -> 0 | BQ17: 0 | BR17: =BQ17/$P17 -> 0 | BS17: =BG17+BI17+BK17+BM17+BO17+BQ17 -> 0 | BT17: =BS17/$P17 -> 0 | BU17: 0 | BV17: =BU17/$P17 -> 0 | BW17: 0 | BX17: =BW17/$P17 -> 0 | BY17: 0 | BZ17: =BY17/$P17 -> 0 | CA17: 0 | CB17: =CA17/$P17 -> 0 | CC17: 0 | CD17: =CC17/$P17 -> 0 | CE17: 0 | CF17: =CE17/$P17 -> 0 | CG17: =BU17+BW17+BY17+CA17+CC17+CE17 -> 0 | CH17: =CG17/$P17 -> 0 | CI17: 0 | CJ17: =CI17/$P17 -> 0 | CK17: 0 | CL17: =CK17/$P17 -> 0 | CM17: 0 | CN17: =CM17/$P17 -> 0 | CO17: 0 | CP17: =CO17/$P17 -> 0 | CQ17: 0 | CR17: =CQ17/$P17 -> 0 | CS17: 0 | CT17: =CS17/$P17 -> 0 | CU17: =CI17+CK17+CM17+CO17+CQ17+CS17 -> 0 | CV17: =CU17/$P17 -> 0
C18: 11 | D18: Muro con ventana (Verde) | E18: =E5 -> 35.6 | F18: 4.62 | G18: =E18*F18 -> 164.472 | H18: 1 | I18: 0.75 | J18: 28 | K18: =(H18*I18)*J18 -> 21 | M18: =G18-K18 -> 143.472 | P18: =SUM(L18:O18) -> 143.472 | Q18: 0 | R18: =Q18/$P18 -> 0 | S18: 0 | T18: =S18/$P18 -> 0 | U18: 0 | V18: =U18/$P18 -> 0 | W18: 0 | X18: =W18/$P18 -> 0 | Y18: 0 | Z18: =Y18/$P18 -> 0 | AA18: 0 | AB18: =AA18/$P18 -> 0 | AC18: =Q18+S18+U18+W18+Y18+AA18 -> 0 | AD18: =AC18/$P18 -> 0 | AE18: 0 | AF18: =AE18/$P18 -> 0 | AG18: 0 | AH18: =AG18/$P18 -> 0 | AI18: 0 | AJ18: =AI18/$P18 -> 0 | AK18: 0 | AL18: =AK18/$P18 -> 0 | AM18: 0 | AN18: =AM18/$P18 -> 0 | AO18: 0 | AP18: =AO18/$P18 -> 0 | AQ18: =AE18+AG18+AI18+AK18+AM18+AO18 -> 0 | AR18: =AQ18/$P18 -> 0 | AS18: 0 | AT18: =AS18/$P18 -> 0 | AU18: 0 | AV18: =AU18/$P18 -> 0 | AW18: 0 | AX18: =AW18/$P18 -> 0 | AY18: 0 | AZ18: =AY18/$P18 -> 0 | BA18: 0 | BB18: =BA18/$P18 -> 0 | BC18: 0 | BD18: =BC18/$P18 -> 0 | BE18: =AS18+AU18+AW18+AY18+BA18+BC18 -> 0 | BF18: =BE18/$P18 -> 0 | BG18: 0 | BH18: =BG18/$P18 -> 0 | BI18: 0 | BJ18: =BI18/$P18 -> 0 | BK18: 0 | BL18: =BK18/$P18 -> 0 | BM18: 0 | BN18: =BM18/$P18 -> 0 | BO18: 0 | BP18: =BO18/$P18 -> 0 | BQ18: 0 | BR18: =BQ18/$P18 -> 0 | BS18: =BG18+BI18+BK18+BM18+BO18+BQ18 -> 0 | BT18: =BS18/$P18 -> 0 | BU18: 0 | BV18: =BU18/$P18 -> 0 | BW18: 0 | BX18: =BW18/$P18 -> 0 | BY18: 0 | BZ18: =BY18/$P18 -> 0 | CA18: 0 | CB18: =CA18/$P18 -> 0 | CC18: 0 | CD18: =CC18/$P18 -> 0 | CE18: 0 | CF18: =CE18/$P18 -> 0 | CG18: =BU18+BW18+BY18+CA18+CC18+CE18 -> 0 | CH18: =CG18/$P18 -> 0 | CI18: 0 | CJ18: =CI18/$P18 -> 0 | CK18: 0 | CL18: =CK18/$P18 -> 0 | CM18: 0 | CN18: =CM18/$P18 -> 0 | CO18: 0 | CP18: =CO18/$P18 -> 0 | CQ18: 0 | CR18: =CQ18/$P18 -> 0 | CS18: 0 | CT18: =CS18/$P18 -> 0 | CU18: =CI18+CK18+CM18+CO18+CQ18+CS18 -> 0 | CV18: =CU18/$P18 -> 0
C19: 12 | D19: Placa de balcón (Negro) (x14) | E19: 0.3 | F19: 2.91 | G19: =E19*F19*14 -> 12.222 | N19: =G19 -> 12.222 | P19: =SUM(L19:O19) -> 12.222 | Q19: 0 | R19: =Q19/$P19 -> 0 | S19: 0 | T19: =S19/$P19 -> 0 | U19: 0 | V19: =U19/$P19 -> 0 | W19: 0 | X19: =W19/$P19 -> 0 | Y19: 0 | Z19: =Y19/$P19 -> 0 | AA19: 0 | AB19: =AA19/$P19 -> 0 | AC19: =Q19+S19+U19+W19+Y19+AA19 -> 0 | AD19: =AC19/$P19 -> 0 | AE19: 0 | AF19: =AE19/$P19 -> 0 | AG19: 0 | AH19: =AG19/$P19 -> 0 | AI19: 0 | AJ19: =AI19/$P19 -> 0 | AK19: 0 | AL19: =AK19/$P19 -> 0 | AM19: 0 | AN19: =AM19/$P19 -> 0 | AO19: 0 | AP19: =AO19/$P19 -> 0 | AQ19: =AE19+AG19+AI19+AK19+AM19+AO19 -> 0 | AR19: =AQ19/$P19 -> 0 | AS19: 0 | AT19: =AS19/$P19 -> 0 | AU19: 0 | AV19: =AU19/$P19 -> 0 | AW19: 0 | AX19: =AW19/$P19 -> 0 | AY19: 0 | AZ19: =AY19/$P19 -> 0 | BA19: 0 | BB19: =BA19/$P19 -> 0 | BC19: 0 | BD19: =BC19/$P19 -> 0 | BE19: =AS19+AU19+AW19+AY19+BA19+BC19 -> 0 | BF19: =BE19/$P19 -> 0 | BG19: 0 | BH19: =BG19/$P19 -> 0 | BI19: 0 | BJ19: =BI19/$P19 -> 0 | BK19: 0 | BL19: =BK19/$P19 -> 0 | BM19: 0 | BN19: =BM19/$P19 -> 0 | BO19: 0 | BP19: =BO19/$P19 -> 0 | BQ19: 0 | BR19: =BQ19/$P19 -> 0 | BS19: =BG19+BI19+BK19+BM19+BO19+BQ19 -> 0 | BT19: =BS19/$P19 -> 0 | BU19: 0 | BV19: =BU19/$P19 -> 0 | BW19: 0 | BX19: =BW19/$P19 -> 0 | BY19: 0 | BZ19: =BY19/$P19 -> 0 | CA19: 0 | CB19: =CA19/$P19 -> 0 | CC19: 0 | CD19: =CC19/$P19 -> 0 | CE19: 0 | CF19: =CE19/$P19 -> 0 | CG19: =BU19+BW19+BY19+CA19+CC19+CE19 -> 0 | CH19: =CG19/$P19 -> 0 | CI19: 0 | CJ19: =CI19/$P19 -> 0 | CK19: 0 | CL19: =CK19/$P19 -> 0 | CM19: 0 | CN19: =CM19/$P19 -> 0 | CO19: 0 | CP19: =CO19/$P19 -> 0 | CQ19: 0 | CR19: =CQ19/$P19 -> 0 | CS19: 0 | CT19: =CS19/$P19 -> 0 | CU19: =CI19+CK19+CM19+CO19+CQ19+CS19 -> 0 | CV19: =CU19/$P19 -> 0
C20: 12.1 | D20: Cielo raso balcón (X14) | E20: 0.6 | F20: 1.71 | G20: =E20*F20*14 -> 14.364 | O20: =G20 -> 14.364 | P20: =SUM(L20:O20) -> 14.364 | Q20: 0 | R20: =Q20/$P20 -> 0 | S20: 0 | T20: =S20/$P20 -> 0 | U20: 0 | V20: =U20/$P20 -> 0 | W20: 0 | X20: =W20/$P20 -> 0 | Y20: 0 | Z20: =Y20/$P20 -> 0 | AA20: 0 | AB20: =AA20/$P20 -> 0 | AC20: =Q20+S20+U20+W20+Y20+AA20 -> 0 | AD20: =AC20/$P20 -> 0 | AE20: 0 | AF20: =AE20/$P20 -> 0 | AG20: 0 | AH20: =AG20/$P20 -> 0 | AI20: 0 | AJ20: =AI20/$P20 -> 0 | AK20: 0 | AL20: =AK20/$P20 -> 0 | AM20: 0 | AN20: =AM20/$P20 -> 0 | AO20: 0 | AP20: =AO20/$P20 -> 0 | AQ20: =AE20+AG20+AI20+AK20+AM20+AO20 -> 0 | AR20: =AQ20/$P20 -> 0 | AS20: 0 | AT20: =AS20/$P20 -> 0 | AU20: 0 | AV20: =AU20/$P20 -> 0 | AW20: 0 | AX20: =AW20/$P20 -> 0 | AY20: 0 | AZ20: =AY20/$P20 -> 0 | BA20: 0 | BB20: =BA20/$P20 -> 0 | BC20: 0 | BD20: =BC20/$P20 -> 0 | BE20: =AS20+AU20+AW20+AY20+BA20+BC20 -> 0 | BF20: =BE20/$P20 -> 0 | BG20: 0 | BH20: =BG20/$P20 -> 0 | BI20: 0 | BJ20: =BI20/$P20 -> 0 | BK20: 0 | BL20: =BK20/$P20 -> 0 | BM20: 0 | BN20: =BM20/$P20 -> 0 | BO20: 0 | BP20: =BO20/$P20 -> 0 | BQ20: 0 | BR20: =BQ20/$P20 -> 0 | BS20: =BG20+BI20+BK20+BM20+BO20+BQ20 -> 0 | BT20: =BS20/$P20 -> 0 | BU20: 0 | BV20: =BU20/$P20 -> 0 | BW20: 0 | BX20: =BW20/$P20 -> 0 | BY20: 0 | BZ20: =BY20/$P20 -> 0 | CA20: 0 | CB20: =CA20/$P20 -> 0 | CC20: 0 | CD20: =CC20/$P20 -> 0 | CE20: 0 | CF20: =CE20/$P20 -> 0 | CG20: =BU20+BW20+BY20+CA20+CC20+CE20 -> 0 | CH20: =CG20/$P20 -> 0 | CI20: 0 | CJ20: =CI20/$P20 -> 0 | CK20: 0 | CL20: =CK20/$P20 -> 0 | CM20: 0 | CN20: =CM20/$P20 -> 0 | CO20: 0 | CP20: =CO20/$P20 -> 0 | CQ20: 0 | CR20: =CQ20/$P20 -> 0 | CS20: 0 | CT20: =CS20/$P20 -> 0 | CU20: =CI20+CK20+CM20+CO20+CQ20+CS20 -> 0 | CV20: =CU20/$P20 -> 0
C21: 13 | D21: Muro con ventana (Blanco) | E21: =E5 -> 35.6 | F21: 5.3 | G21: =E21*F21 -> 188.68 | H21: 1.5 | I21: 1.2 | J21: 28 | K21: =(H21*I21)*J21 -> 50.4 | L21: =G21-K21 -> 138.28 | P21: =SUM(L21:O21) -> 138.28 | Q21: 0 | R21: =Q21/$P21 -> 0 | S21: 0 | T21: =S21/$P21 -> 0 | U21: 0 | V21: =U21/$P21 -> 0 | W21: 0 | X21: =W21/$P21 -> 0 | Y21: 0 | Z21: =Y21/$P21 -> 0 | AA21: 0 | AB21: =AA21/$P21 -> 0 | AC21: =Q21+S21+U21+W21+Y21+AA21 -> 0 | AD21: =AC21/$P21 -> 0 | AE21: 0 | AF21: =AE21/$P21 -> 0 | AG21: 0 | AH21: =AG21/$P21 -> 0 | AI21: 0 | AJ21: =AI21/$P21 -> 0 | AK21: 0 | AL21: =AK21/$P21 -> 0 | AM21: 0 | AN21: =AM21/$P21 -> 0 | AO21: 0 | AP21: =AO21/$P21 -> 0 | AQ21: =AE21+AG21+AI21+AK21+AM21+AO21 -> 0 | AR21: =AQ21/$P21 -> 0 | AS21: 0 | AT21: =AS21/$P21 -> 0 | AU21: 0 | AV21: =AU21/$P21 -> 0 | AW21: 0 | AX21: =AW21/$P21 -> 0 | AY21: 0 | AZ21: =AY21/$P21 -> 0 | BA21: 0 | BB21: =BA21/$P21 -> 0 | BC21: 0 | BD21: =BC21/$P21 -> 0 | BE21: =AS21+AU21+AW21+AY21+BA21+BC21 -> 0 | BF21: =BE21/$P21 -> 0 | BG21: 0 | BH21: =BG21/$P21 -> 0 | BI21: 0 | BJ21: =BI21/$P21 -> 0 | BK21: 0 | BL21: =BK21/$P21 -> 0 | BM21: 0 | BN21: =BM21/$P21 -> 0 | BO21: 0 | BP21: =BO21/$P21 -> 0 | BQ21: 0 | BR21: =BQ21/$P21 -> 0 | BS21: =BG21+BI21+BK21+BM21+BO21+BQ21 -> 0 | BT21: =BS21/$P21 -> 0 | BU21: 0 | BV21: =BU21/$P21 -> 0 | BW21: 0 | BX21: =BW21/$P21 -> 0 | BY21: 0 | BZ21: =BY21/$P21 -> 0 | CA21: 0 | CB21: =CA21/$P21 -> 0 | CC21: 0 | CD21: =CC21/$P21 -> 0 | CE21: 0 | CF21: =CE21/$P21 -> 0 | CG21: =BU21+BW21+BY21+CA21+CC21+CE21 -> 0 | CH21: =CG21/$P21 -> 0 | CI21: 0 | CJ21: =CI21/$P21 -> 0 | CK21: 0 | CL21: =CK21/$P21 -> 0 | CM21: 0 | CN21: =CM21/$P21 -> 0 | CO21: 0 | CP21: =CO21/$P21 -> 0 | CQ21: 0 | CR21: =CQ21/$P21 -> 0 | CS21: 0 | CT21: =CS21/$P21 -> 0 | CU21: =CI21+CK21+CM21+CO21+CQ21+CS21 -> 0 | CV21: =CU21/$P21 -> 0
C22: 14 | D22: Muro escaleras (Blanco) | E22: 35 | F22: 4.8 | G22: =E22*F22 -> 168 | H22: 0.25 | I22: 3.1 | J22: 14 | K22: =(H22*I22)*J22 -> 10.85 | L22: =G22-K22 -> 157.15 | P22: =SUM(L22:O22) -> 157.15 | Q22: 0 | R22: =Q22/$P22 -> 0 | S22: 0 | T22: =S22/$P22 -> 0 | U22: 0 | V22: =U22/$P22 -> 0 | W22: 0 | X22: =W22/$P22 -> 0 | Y22: 0 | Z22: =Y22/$P22 -> 0 | AA22: 0 | AB22: =AA22/$P22 -> 0 | AC22: =Q22+S22+U22+W22+Y22+AA22 -> 0 | AD22: =AC22/$P22 -> 0 | AE22: 0 | AF22: =AE22/$P22 -> 0 | AG22: 0 | AH22: =AG22/$P22 -> 0 | AI22: 0 | AJ22: =AI22/$P22 -> 0 | AK22: 0 | AL22: =AK22/$P22 -> 0 | AM22: 0 | AN22: =AM22/$P22 -> 0 | AO22: 0 | AP22: =AO22/$P22 -> 0 | AQ22: =AE22+AG22+AI22+AK22+AM22+AO22 -> 0 | AR22: =AQ22/$P22 -> 0 | AS22: 0 | AT22: =AS22/$P22 -> 0 | AU22: 0 | AV22: =AU22/$P22 -> 0 | AW22: 0 | AX22: =AW22/$P22 -> 0 | AY22: 0 | AZ22: =AY22/$P22 -> 0 | BA22: 0 | BB22: =BA22/$P22 -> 0 | BC22: 0 | BD22: =BC22/$P22 -> 0 | BE22: =AS22+AU22+AW22+AY22+BA22+BC22 -> 0 | BF22: =BE22/$P22 -> 0 | BG22: 0 | BH22: =BG22/$P22 -> 0 | BI22: 0 | BJ22: =BI22/$P22 -> 0 | BK22: 0 | BL22: =BK22/$P22 -> 0 | BM22: 0 | BN22: =BM22/$P22 -> 0 | BO22: 0 | BP22: =BO22/$P22 -> 0 | BQ22: 0 | BR22: =BQ22/$P22 -> 0 | BS22: =BG22+BI22+BK22+BM22+BO22+BQ22 -> 0 | BT22: =BS22/$P22 -> 0 | BU22: 0 | BV22: =BU22/$P22 -> 0 | BW22: 0 | BX22: =BW22/$P22 -> 0 | BY22: 0 | BZ22: =BY22/$P22 -> 0 | CA22: 0 | CB22: =CA22/$P22 -> 0 | CC22: 0 | CD22: =CC22/$P22 -> 0 | CE22: 0 | CF22: =CE22/$P22 -> 0 | CG22: =BU22+BW22+BY22+CA22+CC22+CE22 -> 0 | CH22: =CG22/$P22 -> 0 | CI22: 0 | CJ22: =CI22/$P22 -> 0 | CK22: 0 | CL22: =CK22/$P22 -> 0 | CM22: 0 | CN22: =CM22/$P22 -> 0 | CO22: 0 | CP22: =CO22/$P22 -> 0 | CQ22: 0 | CR22: =CQ22/$P22 -> 0 | CS22: 0 | CT22: =CS22/$P22 -> 0 | CU22: =CI22+CK22+CM22+CO22+CQ22+CS22 -> 0 | CV22: =CU22/$P22 -> 0
C23: 15 | D23: Muro escaleras (Blanco) | E23: 35 | F23: 2.15 | G23: =E23*F23 -> 75.25 | L23: =G23-K23 -> 75.25 | P23: =SUM(L23:O23) -> 75.25 | Q23: 0 | R23: =Q23/$P23 -> 0 | S23: 0 | T23: =S23/$P23 -> 0 | U23: 0 | V23: =U23/$P23 -> 0 | W23: 0 | X23: =W23/$P23 -> 0 | Y23: 0 | Z23: =Y23/$P23 -> 0 | AA23: 0 | AB23: =AA23/$P23 -> 0 | AC23: =Q23+S23+U23+W23+Y23+AA23 -> 0 | AD23: =AC23/$P23 -> 0 | AE23: 0 | AF23: =AE23/$P23 -> 0 | AG23: 0 | AH23: =AG23/$P23 -> 0 | AI23: 0 | AJ23: =AI23/$P23 -> 0 | AK23: 0 | AL23: =AK23/$P23 -> 0 | AM23: 0 | AN23: =AM23/$P23 -> 0 | AO23: 0 | AP23: =AO23/$P23 -> 0 | AQ23: =AE23+AG23+AI23+AK23+AM23+AO23 -> 0 | AR23: =AQ23/$P23 -> 0 | AS23: 0 | AT23: =AS23/$P23 -> 0 | AU23: 0 | AV23: =AU23/$P23 -> 0 | AW23: 0 | AX23: =AW23/$P23 -> 0 | AY23: 0 | AZ23: =AY23/$P23 -> 0 | BA23: 0 | BB23: =BA23/$P23 -> 0 | BC23: 0 | BD23: =BC23/$P23 -> 0 | BE23: =AS23+AU23+AW23+AY23+BA23+BC23 -> 0 | BF23: =BE23/$P23 -> 0 | BG23: 0 | BH23: =BG23/$P23 -> 0 | BI23: 0 | BJ23: =BI23/$P23 -> 0 | BK23: 0 | BL23: =BK23/$P23 -> 0 | BM23: 0 | BN23: =BM23/$P23 -> 0 | BO23: 0 | BP23: =BO23/$P23 -> 0 | BQ23: 0 | BR23: =BQ23/$P23 -> 0 | BS23: =BG23+BI23+BK23+BM23+BO23+BQ23 -> 0 | BT23: =BS23/$P23 -> 0 | BU23: 0 | BV23: =BU23/$P23 -> 0 | BW23: 0 | BX23: =BW23/$P23 -> 0 | BY23: 0 | BZ23: =BY23/$P23 -> 0 | CA23: 0 | CB23: =CA23/$P23 -> 0 | CC23: 0 | CD23: =CC23/$P23 -> 0 | CE23: 0 | CF23: =CE23/$P23 -> 0 | CG23: =BU23+BW23+BY23+CA23+CC23+CE23 -> 0 | CH23: =CG23/$P23 -> 0 | CI23: 0 | CJ23: =CI23/$P23 -> 0 | CK23: 0 | CL23: =CK23/$P23 -> 0 | CM23: 0 | CN23: =CM23/$P23 -> 0 | CO23: 0 | CP23: =CO23/$P23 -> 0 | CQ23: 0 | CR23: =CQ23/$P23 -> 0 | CS23: 0 | CT23: =CS23/$P23 -> 0 | CU23: =CI23+CK23+CM23+CO23+CQ23+CS23 -> 0 | CV23: =CU23/$P23 -> 0
C24: 16 | D24: Muro escaleras (Blanco) | E24: 35 | F24: 1.42 | G24: =E24*F24 -> 49.7 | H24: 0.25 | I24: 3.1 | J24: 14 | K24: =(H24*I24)*J24 -> 10.85 | L24: =G24-K24 -> 38.85 | P24: =SUM(L24:O24) -> 38.85 | Q24: 0 | R24: =Q24/$P24 -> 0 | S24: 0 | T24: =S24/$P24 -> 0 | U24: 0 | V24: =U24/$P24 -> 0 | W24: 0 | X24: =W24/$P24 -> 0 | Y24: 0 | Z24: =Y24/$P24 -> 0 | AA24: 0 | AB24: =AA24/$P24 -> 0 | AC24: =Q24+S24+U24+W24+Y24+AA24 -> 0 | AD24: =AC24/$P24 -> 0 | AE24: 0 | AF24: =AE24/$P24 -> 0 | AG24: 0 | AH24: =AG24/$P24 -> 0 | AI24: 0 | AJ24: =AI24/$P24 -> 0 | AK24: 0 | AL24: =AK24/$P24 -> 0 | AM24: 0 | AN24: =AM24/$P24 -> 0 | AO24: 0 | AP24: =AO24/$P24 -> 0 | AQ24: =AE24+AG24+AI24+AK24+AM24+AO24 -> 0 | AR24: =AQ24/$P24 -> 0 | AS24: 0 | AT24: =AS24/$P24 -> 0 | AU24: 0 | AV24: =AU24/$P24 -> 0 | AW24: 0 | AX24: =AW24/$P24 -> 0 | AY24: 0 | AZ24: =AY24/$P24 -> 0 | BA24: 0 | BB24: =BA24/$P24 -> 0 | BC24: 0 | BD24: =BC24/$P24 -> 0 | BE24: =AS24+AU24+AW24+AY24+BA24+BC24 -> 0 | BF24: =BE24/$P24 -> 0 | BG24: 0 | BH24: =BG24/$P24 -> 0 | BI24: 0 | BJ24: =BI24/$P24 -> 0 | BK24: 0 | BL24: =BK24/$P24 -> 0 | BM24: 0 | BN24: =BM24/$P24 -> 0 | BO24: 0 | BP24: =BO24/$P24 -> 0 | BQ24: 0 | BR24: =BQ24/$P24 -> 0 | BS24: =BG24+BI24+BK24+BM24+BO24+BQ24 -> 0 | BT24: =BS24/$P24 -> 0 | BU24: 0 | BV24: =BU24/$P24 -> 0 | BW24: 0 | BX24: =BW24/$P24 -> 0 | BY24: 0 | BZ24: =BY24/$P24 -> 0 | CA24: 0 | CB24: =CA24/$P24 -> 0 | CC24: 0 | CD24: =CC24/$P24 -> 0 | CE24: 0 | CF24: =CE24/$P24 -> 0 | CG24: =BU24+BW24+BY24+CA24+CC24+CE24 -> 0 | CH24: =CG24/$P24 -> 0 | CI24: 0 | CJ24: =CI24/$P24 -> 0 | CK24: 0 | CL24: =CK24/$P24 -> 0 | CM24: 0 | CN24: =CM24/$P24 -> 0 | CO24: 0 | CP24: =CO24/$P24 -> 0 | CQ24: 0 | CR24: =CQ24/$P24 -> 0 | CS24: 0 | CT24: =CS24/$P24 -> 0 | CU24: =CI24+CK24+CM24+CO24+CQ24+CS24 -> 0 | CV24: =CU24/$P24 -> 0
C25: 16.1 | D25: Cielo raso balcón (X14) | E25: 1 | F25: 1.9 | G25: =E25*F25*14 -> 26.6 | O25: =G25 -> 26.6 | P25: =SUM(L25:O25) -> 26.6 | Q25: 0 | R25: =Q25/$P25 -> 0 | S25: 0 | T25: =S25/$P25 -> 0 | U25: 0 | V25: =U25/$P25 -> 0 | W25: 0 | X25: =W25/$P25 -> 0 | Y25: 0 | Z25: =Y25/$P25 -> 0 | AA25: 0 | AB25: =AA25/$P25 -> 0 | AC25: =Q25+S25+U25+W25+Y25+AA25 -> 0 | AD25: =AC25/$P25 -> 0 | AE25: 0 | AF25: =AE25/$P25 -> 0 | AG25: 0 | AH25: =AG25/$P25 -> 0 | AI25: 0 | AJ25: =AI25/$P25 -> 0 | AK25: 0 | AL25: =AK25/$P25 -> 0 | AM25: 0 | AN25: =AM25/$P25 -> 0 | AO25: 0 | AP25: =AO25/$P25 -> 0 | AQ25: =AE25+AG25+AI25+AK25+AM25+AO25 -> 0 | AR25: =AQ25/$P25 -> 0 | AS25: 0 | AT25: =AS25/$P25 -> 0 | AU25: 0 | AV25: =AU25/$P25 -> 0 | AW25: 0 | AX25: =AW25/$P25 -> 0 | AY25: 0 | AZ25: =AY25/$P25 -> 0 | BA25: 0 | BB25: =BA25/$P25 -> 0 | BC25: 0 | BD25: =BC25/$P25 -> 0 | BE25: =AS25+AU25+AW25+AY25+BA25+BC25 -> 0 | BF25: =BE25/$P25 -> 0 | BG25: 0 | BH25: =BG25/$P25 -> 0 | BI25: 0 | BJ25: =BI25/$P25 -> 0 | BK25: 0 | BL25: =BK25/$P25 -> 0 | BM25: 0 | BN25: =BM25/$P25 -> 0 | BO25: 0 | BP25: =BO25/$P25 -> 0 | BQ25: 0 | BR25: =BQ25/$P25 -> 0 | BS25: =BG25+BI25+BK25+BM25+BO25+BQ25 -> 0 | BT25: =BS25/$P25 -> 0 | BU25: 0 | BV25: =BU25/$P25 -> 0 | BW25: 0 | BX25: =BW25/$P25 -> 0 | BY25: 0 | BZ25: =BY25/$P25 -> 0 | CA25: 0 | CB25: =CA25/$P25 -> 0 | CC25: 0 | CD25: =CC25/$P25 -> 0 | CE25: 0 | CF25: =CE25/$P25 -> 0 | CG25: =BU25+BW25+BY25+CA25+CC25+CE25 -> 0 | CH25: =CG25/$P25 -> 0 | CI25: 0 | CJ25: =CI25/$P25 -> 0 | CK25: 0 | CL25: =CK25/$P25 -> 0 | CM25: 0 | CN25: =CM25/$P25 -> 0 | CO25: 0 | CP25: =CO25/$P25 -> 0 | CQ25: 0 | CR25: =CQ25/$P25 -> 0 | CS25: 0 | CT25: =CS25/$P25 -> 0 | CU25: =CI25+CK25+CM25+CO25+CQ25+CS25 -> 0 | CV25: =CU25/$P25 -> 0
B26: CULATA DER | C26: 17 | D26: Muro sin ventanas (Blanco) | E26: 35 | F26: 1.67 | G26: =E26*F26 -> 58.45 | L26: =G26-K26 -> 58.45 | P26: =SUM(L26:O26) -> 58.45 | Q26: 0 | R26: =Q26/$P26 -> 0 | S26: 0 | T26: =S26/$P26 -> 0 | U26: 0 | V26: =U26/$P26 -> 0 | W26: 0 | X26: =W26/$P26 -> 0 | Y26: 0 | Z26: =Y26/$P26 -> 0 | AA26: 0 | AB26: =AA26/$P26 -> 0 | AC26: =Q26+S26+U26+W26+Y26+AA26 -> 0 | AD26: =AC26/$P26 -> 0 | AE26: 0 | AF26: =AE26/$P26 -> 0 | AG26: 0 | AH26: =AG26/$P26 -> 0 | AI26: 0 | AJ26: =AI26/$P26 -> 0 | AK26: 0 | AL26: =AK26/$P26 -> 0 | AM26: 0 | AN26: =AM26/$P26 -> 0 | AO26: 0 | AP26: =AO26/$P26 -> 0 | AQ26: =AE26+AG26+AI26+AK26+AM26+AO26 -> 0 | AR26: =AQ26/$P26 -> 0 | AS26: 0 | AT26: =AS26/$P26 -> 0 | AU26: 0 | AV26: =AU26/$P26 -> 0 | AW26: 0 | AX26: =AW26/$P26 -> 0 | AY26: 0 | AZ26: =AY26/$P26 -> 0 | BA26: 0 | BB26: =BA26/$P26 -> 0 | BC26: 0 | BD26: =BC26/$P26 -> 0 | BE26: =AS26+AU26+AW26+AY26+BA26+BC26 -> 0 | BF26: =BE26/$P26 -> 0 | BG26: 0 | BH26: =BG26/$P26 -> 0 | BI26: 0 | BJ26: =BI26/$P26 -> 0 | BK26: 0 | BL26: =BK26/$P26 -> 0 | BM26: 0 | BN26: =BM26/$P26 -> 0 | BO26: 0 | BP26: =BO26/$P26 -> 0 | BQ26: 0 | BR26: =BQ26/$P26 -> 0 | BS26: =BG26+BI26+BK26+BM26+BO26+BQ26 -> 0 | BT26: =BS26/$P26 -> 0 | BU26: 0 | BV26: =BU26/$P26 -> 0 | BW26: 0 | BX26: =BW26/$P26 -> 0 | BY26: 0 | BZ26: =BY26/$P26 -> 0 | CA26: 0 | CB26: =CA26/$P26 -> 0 | CC26: 0 | CD26: =CC26/$P26 -> 0 | CE26: 0 | CF26: =CE26/$P26 -> 0 | CG26: =BU26+BW26+BY26+CA26+CC26+CE26 -> 0 | CH26: =CG26/$P26 -> 0 | CI26: 0 | CJ26: =CI26/$P26 -> 0 | CK26: 0 | CL26: =CK26/$P26 -> 0 | CM26: 0 | CN26: =CM26/$P26 -> 0 | CO26: 0 | CP26: =CO26/$P26 -> 0 | CQ26: 0 | CR26: =CQ26/$P26 -> 0 | CS26: 0 | CT26: =CS26/$P26 -> 0 | CU26: =CI26+CK26+CM26+CO26+CQ26+CS26 -> 0 | CV26: =CU26/$P26 -> 0
C27: 18 | D27: Antepecho balcones (Negro) (X14) | E27: 0.5 | F27: 1.26 | G27: =E27*F27*14 -> 8.82 | N27: =G27-K27 -> 8.82 | P27: =SUM(L27:O27) -> 8.82 | Q27: 0 | R27: =Q27/$P27 -> 0 | S27: 0 | T27: =S27/$P27 -> 0 | U27: 0 | V27: =U27/$P27 -> 0 | W27: 0 | X27: =W27/$P27 -> 0 | Y27: 0 | Z27: =Y27/$P27 -> 0 | AA27: 0 | AB27: =AA27/$P27 -> 0 | AC27: =Q27+S27+U27+W27+Y27+AA27 -> 0 | AD27: =AC27/$P27 -> 0 | AE27: 0 | AF27: =AE27/$P27 -> 0 | AG27: 0 | AH27: =AG27/$P27 -> 0 | AI27: 0 | AJ27: =AI27/$P27 -> 0 | AK27: 0 | AL27: =AK27/$P27 -> 0 | AM27: 0 | AN27: =AM27/$P27 -> 0 | AO27: 0 | AP27: =AO27/$P27 -> 0 | AQ27: =AE27+AG27+AI27+AK27+AM27+AO27 -> 0 | AR27: =AQ27/$P27 -> 0 | AS27: 0 | AT27: =AS27/$P27 -> 0 | AU27: 0 | AV27: =AU27/$P27 -> 0 | AW27: 0 | AX27: =AW27/$P27 -> 0 | AY27: 0 | AZ27: =AY27/$P27 -> 0 | BA27: 0 | BB27: =BA27/$P27 -> 0 | BC27: 0 | BD27: =BC27/$P27 -> 0 | BE27: =AS27+AU27+AW27+AY27+BA27+BC27 -> 0 | BF27: =BE27/$P27 -> 0 | BG27: 0 | BH27: =BG27/$P27 -> 0 | BI27: 0 | BJ27: =BI27/$P27 -> 0 | BK27: 0 | BL27: =BK27/$P27 -> 0 | BM27: 0 | BN27: =BM27/$P27 -> 0 | BO27: 0 | BP27: =BO27/$P27 -> 0 | BQ27: 0 | BR27: =BQ27/$P27 -> 0 | BS27: =BG27+BI27+BK27+BM27+BO27+BQ27 -> 0 | BT27: =BS27/$P27 -> 0 | BU27: 0 | BV27: =BU27/$P27 -> 0 | BW27: 0 | BX27: =BW27/$P27 -> 0 | BY27: 0 | BZ27: =BY27/$P27 -> 0 | CA27: 0 | CB27: =CA27/$P27 -> 0 | CC27: 0 | CD27: =CC27/$P27 -> 0 | CE27: 0 | CF27: =CE27/$P27 -> 0 | CG27: =BU27+BW27+BY27+CA27+CC27+CE27 -> 0 | CH27: =CG27/$P27 -> 0 | CI27: 0 | CJ27: =CI27/$P27 -> 0 | CK27: 0 | CL27: =CK27/$P27 -> 0 | CM27: 0 | CN27: =CM27/$P27 -> 0 | CO27: 0 | CP27: =CO27/$P27 -> 0 | CQ27: 0 | CR27: =CQ27/$P27 -> 0 | CS27: 0 | CT27: =CS27/$P27 -> 0 | CU27: =CI27+CK27+CM27+CO27+CQ27+CS27 -> 0 | CV27: =CU27/$P27 -> 0
C28: 19 | D28: Muro sin ventanas (Negro) | E28: =E5 -> 35.6 | F28: 2.5 | G28: =E28*F28 -> 89 | N28: =G28-K28 -> 89 | P28: =SUM(L28:O28) -> 89 | Q28: 0 | R28: =Q28/$P28 -> 0 | S28: 0 | T28: =S28/$P28 -> 0 | U28: 0 | V28: =U28/$P28 -> 0 | W28: 0 | X28: =W28/$P28 -> 0 | Y28: 0 | Z28: =Y28/$P28 -> 0 | AA28: 0 | AB28: =AA28/$P28 -> 0 | AC28: =Q28+S28+U28+W28+Y28+AA28 -> 0 | AD28: =AC28/$P28 -> 0 | AE28: 0 | AF28: =AE28/$P28 -> 0 | AG28: 0 | AH28: =AG28/$P28 -> 0 | AI28: 0 | AJ28: =AI28/$P28 -> 0 | AK28: 0 | AL28: =AK28/$P28 -> 0 | AM28: 0 | AN28: =AM28/$P28 -> 0 | AO28: 0 | AP28: =AO28/$P28 -> 0 | AQ28: =AE28+AG28+AI28+AK28+AM28+AO28 -> 0 | AR28: =AQ28/$P28 -> 0 | AS28: 0 | AT28: =AS28/$P28 -> 0 | AU28: 0 | AV28: =AU28/$P28 -> 0 | AW28: 0 | AX28: =AW28/$P28 -> 0 | AY28: 0 | AZ28: =AY28/$P28 -> 0 | BA28: 0 | BB28: =BA28/$P28 -> 0 | BC28: 0 | BD28: =BC28/$P28 -> 0 | BE28: =AS28+AU28+AW28+AY28+BA28+BC28 -> 0 | BF28: =BE28/$P28 -> 0 | BG28: 0 | BH28: =BG28/$P28 -> 0 | BI28: 0 | BJ28: =BI28/$P28 -> 0 | BK28: 0 | BL28: =BK28/$P28 -> 0 | BM28: 0 | BN28: =BM28/$P28 -> 0 | BO28: 0 | BP28: =BO28/$P28 -> 0 | BQ28: 0 | BR28: =BQ28/$P28 -> 0 | BS28: =BG28+BI28+BK28+BM28+BO28+BQ28 -> 0 | BT28: =BS28/$P28 -> 0 | BU28: 0 | BV28: =BU28/$P28 -> 0 | BW28: 0 | BX28: =BW28/$P28 -> 0 | BY28: 0 | BZ28: =BY28/$P28 -> 0 | CA28: 0 | CB28: =CA28/$P28 -> 0 | CC28: 0 | CD28: =CC28/$P28 -> 0 | CE28: 0 | CF28: =CE28/$P28 -> 0 | CG28: =BU28+BW28+BY28+CA28+CC28+CE28 -> 0 | CH28: =CG28/$P28 -> 0 | CI28: 0 | CJ28: =CI28/$P28 -> 0 | CK28: 0 | CL28: =CK28/$P28 -> 0 | CM28: 0 | CN28: =CM28/$P28 -> 0 | CO28: 0 | CP28: =CO28/$P28 -> 0 | CQ28: 0 | CR28: =CQ28/$P28 -> 0 | CS28: 0 | CT28: =CS28/$P28 -> 0 | CU28: =CI28+CK28+CM28+CO28+CQ28+CS28 -> 0 | CV28: =CU28/$P28 -> 0
C29: 20 | D29: Muro con ventanas (Blanco) | E29: =E5 -> 35.6 | F29: 2.33 | G29: =E29*F29 -> 82.948 | H29: 1 | I29: 0.75 | J29: 14 | K29: =(H29*I29)*J29 -> 10.5 | L29: =G29-K29 -> 72.448 | P29: =SUM(L29:O29) -> 72.448 | Q29: 0 | R29: =Q29/$P29 -> 0 | S29: 0 | T29: =S29/$P29 -> 0 | U29: 0 | V29: =U29/$P29 -> 0 | W29: 0 | X29: =W29/$P29 -> 0 | Y29: 0 | Z29: =Y29/$P29 -> 0 | AA29: 0 | AB29: =AA29/$P29 -> 0 | AC29: =Q29+S29+U29+W29+Y29+AA29 -> 0 | AD29: =AC29/$P29 -> 0 | AE29: 0 | AF29: =AE29/$P29 -> 0 | AG29: 0 | AH29: =AG29/$P29 -> 0 | AI29: 0 | AJ29: =AI29/$P29 -> 0 | AK29: 0 | AL29: =AK29/$P29 -> 0 | AM29: 0 | AN29: =AM29/$P29 -> 0 | AO29: 0 | AP29: =AO29/$P29 -> 0 | AQ29: =AE29+AG29+AI29+AK29+AM29+AO29 -> 0 | AR29: =AQ29/$P29 -> 0 | AS29: 0 | AT29: =AS29/$P29 -> 0 | AU29: 0 | AV29: =AU29/$P29 -> 0 | AW29: 0 | AX29: =AW29/$P29 -> 0 | AY29: 0 | AZ29: =AY29/$P29 -> 0 | BA29: 0 | BB29: =BA29/$P29 -> 0 | BC29: 0 | BD29: =BC29/$P29 -> 0 | BE29: =AS29+AU29+AW29+AY29+BA29+BC29 -> 0 | BF29: =BE29/$P29 -> 0 | BG29: 0 | BH29: =BG29/$P29 -> 0 | BI29: 0 | BJ29: =BI29/$P29 -> 0 | BK29: 0 | BL29: =BK29/$P29 -> 0 | BM29: 0 | BN29: =BM29/$P29 -> 0 | BO29: 0 | BP29: =BO29/$P29 -> 0 | BQ29: 0 | BR29: =BQ29/$P29 -> 0 | BS29: =BG29+BI29+BK29+BM29+BO29+BQ29 -> 0 | BT29: =BS29/$P29 -> 0 | BU29: 0 | BV29: =BU29/$P29 -> 0 | BW29: 0 | BX29: =BW29/$P29 -> 0 | BY29: 0 | BZ29: =BY29/$P29 -> 0 | CA29: 0 | CB29: =CA29/$P29 -> 0 | CC29: 0 | CD29: =CC29/$P29 -> 0 | CE29: 0 | CF29: =CE29/$P29 -> 0 | CG29: =BU29+BW29+BY29+CA29+CC29+CE29 -> 0 | CH29: =CG29/$P29 -> 0 | CI29: 0 | CJ29: =CI29/$P29 -> 0 | CK29: 0 | CL29: =CK29/$P29 -> 0 | CM29: 0 | CN29: =CM29/$P29 -> 0 | CO29: 0 | CP29: =CO29/$P29 -> 0 | CQ29: 0 | CR29: =CQ29/$P29 -> 0 | CS29: 0 | CT29: =CS29/$P29 -> 0 | CU29: =CI29+CK29+CM29+CO29+CQ29+CS29 -> 0 | CV29: =CU29/$P29 -> 0
C30: 21 | D30: Muro sin ventanas (Blanco) | E30: =E5 -> 35.6 | F30: 0.8 | G30: =E30*F30 -> 28.48 | L30: =G30-K30 -> 28.48 | P30: =SUM(L30:O30) -> 28.48 | Q30: 0 | R30: =Q30/$P30 -> 0 | S30: 0 | T30: =S30/$P30 -> 0 | U30: 0 | V30: =U30/$P30 -> 0 | W30: 0 | X30: =W30/$P30 -> 0 | Y30: 0 | Z30: =Y30/$P30 -> 0 | AA30: 0 | AB30: =AA30/$P30 -> 0 | AC30: =Q30+S30+U30+W30+Y30+AA30 -> 0 | AD30: =AC30/$P30 -> 0 | AE30: 0 | AF30: =AE30/$P30 -> 0 | AG30: 0 | AH30: =AG30/$P30 -> 0 | AI30: 0 | AJ30: =AI30/$P30 -> 0 | AK30: 0 | AL30: =AK30/$P30 -> 0 | AM30: 0 | AN30: =AM30/$P30 -> 0 | AO30: 0 | AP30: =AO30/$P30 -> 0 | AQ30: =AE30+AG30+AI30+AK30+AM30+AO30 -> 0 | AR30: =AQ30/$P30 -> 0 | AS30: 0 | AT30: =AS30/$P30 -> 0 | AU30: 0 | AV30: =AU30/$P30 -> 0 | AW30: 0 | AX30: =AW30/$P30 -> 0 | AY30: 0 | AZ30: =AY30/$P30 -> 0 | BA30: 0 | BB30: =BA30/$P30 -> 0 | BC30: 0 | BD30: =BC30/$P30 -> 0 | BE30: =AS30+AU30+AW30+AY30+BA30+BC30 -> 0 | BF30: =BE30/$P30 -> 0 | BG30: 0 | BH30: =BG30/$P30 -> 0 | BI30: 0 | BJ30: =BI30/$P30 -> 0 | BK30: 0 | BL30: =BK30/$P30 -> 0 | BM30: 0 | BN30: =BM30/$P30 -> 0 | BO30: 0 | BP30: =BO30/$P30 -> 0 | BQ30: 0 | BR30: =BQ30/$P30 -> 0 | BS30: =BG30+BI30+BK30+BM30+BO30+BQ30 -> 0 | BT30: =BS30/$P30 -> 0 | BU30: 0 | BV30: =BU30/$P30 -> 0 | BW30: 0 | BX30: =BW30/$P30 -> 0 | BY30: 0 | BZ30: =BY30/$P30 -> 0 | CA30: 0 | CB30: =CA30/$P30 -> 0 | CC30: 0 | CD30: =CC30/$P30 -> 0 | CE30: 0 | CF30: =CE30/$P30 -> 0 | CG30: =BU30+BW30+BY30+CA30+CC30+CE30 -> 0 | CH30: =CG30/$P30 -> 0 | CI30: 0 | CJ30: =CI30/$P30 -> 0 | CK30: 0 | CL30: =CK30/$P30 -> 0 | CM30: 0 | CN30: =CM30/$P30 -> 0 | CO30: 0 | CP30: =CO30/$P30 -> 0 | CQ30: 0 | CR30: =CQ30/$P30 -> 0 | CS30: 0 | CT30: =CS30/$P30 -> 0 | CU30: =CI30+CK30+CM30+CO30+CQ30+CS30 -> 0 | CV30: =CU30/$P30 -> 0
C31: 22 | D31: Muro con ventanas (Blanco) | E31: =E5 -> 35.6 | F31: 1.42 | G31: =E31*F31 -> 50.552 | H31: 0.3 | I31: 0.3 | J31: 14 | K31: =(H31*I31)*J31 -> 1.26 | L31: =G31-K31 -> 49.292 | P31: =SUM(L31:O31) -> 49.292 | Q31: 0 | R31: =Q31/$P31 -> 0 | S31: 0 | T31: =S31/$P31 -> 0 | U31: 0 | V31: =U31/$P31 -> 0 | W31: 0 | X31: =W31/$P31 -> 0 | Y31: 0 | Z31: =Y31/$P31 -> 0 | AA31: 0 | AB31: =AA31/$P31 -> 0 | AC31: =Q31+S31+U31+W31+Y31+AA31 -> 0 | AD31: =AC31/$P31 -> 0 | AE31: 0 | AF31: =AE31/$P31 -> 0 | AG31: 0 | AH31: =AG31/$P31 -> 0 | AI31: 0 | AJ31: =AI31/$P31 -> 0 | AK31: 0 | AL31: =AK31/$P31 -> 0 | AM31: 0 | AN31: =AM31/$P31 -> 0 | AO31: 0 | AP31: =AO31/$P31 -> 0 | AQ31: =AE31+AG31+AI31+AK31+AM31+AO31 -> 0 | AR31: =AQ31/$P31 -> 0 | AS31: 0 | AT31: =AS31/$P31 -> 0 | AU31: 0 | AV31: =AU31/$P31 -> 0 | AW31: 0 | AX31: =AW31/$P31 -> 0 | AY31: 0 | AZ31: =AY31/$P31 -> 0 | BA31: 0 | BB31: =BA31/$P31 -> 0 | BC31: 0 | BD31: =BC31/$P31 -> 0 | BE31: =AS31+AU31+AW31+AY31+BA31+BC31 -> 0 | BF31: =BE31/$P31 -> 0 | BG31: 0 | BH31: =BG31/$P31 -> 0 | BI31: 0 | BJ31: =BI31/$P31 -> 0 | BK31: 0 | BL31: =BK31/$P31 -> 0 | BM31: 0 | BN31: =BM31/$P31 -> 0 | BO31: 0 | BP31: =BO31/$P31 -> 0 | BQ31: 0 | BR31: =BQ31/$P31 -> 0 | BS31: =BG31+BI31+BK31+BM31+BO31+BQ31 -> 0 | BT31: =BS31/$P31 -> 0 | BU31: 0 | BV31: =BU31/$P31 -> 0 | BW31: 0 | BX31: =BW31/$P31 -> 0 | BY31: 0 | BZ31: =BY31/$P31 -> 0 | CA31: 0 | CB31: =CA31/$P31 -> 0 | CC31: 0 | CD31: =CC31/$P31 -> 0 | CE31: 0 | CF31: =CE31/$P31 -> 0 | CG31: =BU31+BW31+BY31+CA31+CC31+CE31 -> 0 | CH31: =CG31/$P31 -> 0 | CI31: 0 | CJ31: =CI31/$P31 -> 0 | CK31: 0 | CL31: =CK31/$P31 -> 0 | CM31: 0 | CN31: =CM31/$P31 -> 0 | CO31: 0 | CP31: =CO31/$P31 -> 0 | CQ31: 0 | CR31: =CQ31/$P31 -> 0 | CS31: 0 | CT31: =CS31/$P31 -> 0 | CU31: =CI31+CK31+CM31+CO31+CQ31+CS31 -> 0 | CV31: =CU31/$P31 -> 0
C32: 23 | D32: Muro sin ventanas (Blanco) | E32: =E5 -> 35.6 | F32: 1.72 | G32: =E32*F32 -> 61.232 | L32: =G32-K32 -> 61.232 | P32: =SUM(L32:O32) -> 61.232 | Q32: 0 | R32: =Q32/$P32 -> 0 | S32: 0 | T32: =S32/$P32 -> 0 | U32: 0 | V32: =U32/$P32 -> 0 | W32: 0 | X32: =W32/$P32 -> 0 | Y32: 0 | Z32: =Y32/$P32 -> 0 | AA32: 0 | AB32: =AA32/$P32 -> 0 | AC32: =Q32+S32+U32+W32+Y32+AA32 -> 0 | AD32: =AC32/$P32 -> 0 | AE32: 0 | AF32: =AE32/$P32 -> 0 | AG32: 0 | AH32: =AG32/$P32 -> 0 | AI32: 0 | AJ32: =AI32/$P32 -> 0 | AK32: 0 | AL32: =AK32/$P32 -> 0 | AM32: 0 | AN32: =AM32/$P32 -> 0 | AO32: 0 | AP32: =AO32/$P32 -> 0 | AQ32: =AE32+AG32+AI32+AK32+AM32+AO32 -> 0 | AR32: =AQ32/$P32 -> 0 | AS32: 0 | AT32: =AS32/$P32 -> 0 | AU32: 0 | AV32: =AU32/$P32 -> 0 | AW32: 0 | AX32: =AW32/$P32 -> 0 | AY32: 0 | AZ32: =AY32/$P32 -> 0 | BA32: 0 | BB32: =BA32/$P32 -> 0 | BC32: 0 | BD32: =BC32/$P32 -> 0 | BE32: =AS32+AU32+AW32+AY32+BA32+BC32 -> 0 | BF32: =BE32/$P32 -> 0 | BG32: 0 | BH32: =BG32/$P32 -> 0 | BI32: 0 | BJ32: =BI32/$P32 -> 0 | BK32: 0 | BL32: =BK32/$P32 -> 0 | BM32: 0 | BN32: =BM32/$P32 -> 0 | BO32: 0 | BP32: =BO32/$P32 -> 0 | BQ32: 0 | BR32: =BQ32/$P32 -> 0 | BS32: =BG32+BI32+BK32+BM32+BO32+BQ32 -> 0 | BT32: =BS32/$P32 -> 0 | BU32: 0 | BV32: =BU32/$P32 -> 0 | BW32: 0 | BX32: =BW32/$P32 -> 0 | BY32: 0 | BZ32: =BY32/$P32 -> 0 | CA32: 0 | CB32: =CA32/$P32 -> 0 | CC32: 0 | CD32: =CC32/$P32 -> 0 | CE32: 0 | CF32: =CE32/$P32 -> 0 | CG32: =BU32+BW32+BY32+CA32+CC32+CE32 -> 0 | CH32: =CG32/$P32 -> 0 | CI32: 0 | CJ32: =CI32/$P32 -> 0 | CK32: 0 | CL32: =CK32/$P32 -> 0 | CM32: 0 | CN32: =CM32/$P32 -> 0 | CO32: 0 | CP32: =CO32/$P32 -> 0 | CQ32: 0 | CR32: =CQ32/$P32 -> 0 | CS32: 0 | CT32: =CS32/$P32 -> 0 | CU32: =CI32+CK32+CM32+CO32+CQ32+CS32 -> 0 | CV32: =CU32/$P32 -> 0
C33: 24 | D33: Muro sin ventanas (Blanco) | E33: =E5 -> 35.6 | F33: 1.31 | G33: =E33*F33 -> 46.636 | L33: =G33-K33 -> 46.636 | P33: =SUM(L33:O33) -> 46.636 | Q33: 0 | R33: =Q33/$P33 -> 0 | S33: 0 | T33: =S33/$P33 -> 0 | U33: 0 | V33: =U33/$P33 -> 0 | W33: 0 | X33: =W33/$P33 -> 0 | Y33: 0 | Z33: =Y33/$P33 -> 0 | AA33: 0 | AB33: =AA33/$P33 -> 0 | AC33: =Q33+S33+U33+W33+Y33+AA33 -> 0 | AD33: =AC33/$P33 -> 0 | AE33: 0 | AF33: =AE33/$P33 -> 0 | AG33: 0 | AH33: =AG33/$P33 -> 0 | AI33: 0 | AJ33: =AI33/$P33 -> 0 | AK33: 0 | AL33: =AK33/$P33 -> 0 | AM33: 0 | AN33: =AM33/$P33 -> 0 | AO33: 0 | AP33: =AO33/$P33 -> 0 | AQ33: =AE33+AG33+AI33+AK33+AM33+AO33 -> 0 | AR33: =AQ33/$P33 -> 0 | AS33: 0 | AT33: =AS33/$P33 -> 0 | AU33: 0 | AV33: =AU33/$P33 -> 0 | AW33: 0 | AX33: =AW33/$P33 -> 0 | AY33: 0 | AZ33: =AY33/$P33 -> 0 | BA33: 0 | BB33: =BA33/$P33 -> 0 | BC33: 0 | BD33: =BC33/$P33 -> 0 | BE33: =AS33+AU33+AW33+AY33+BA33+BC33 -> 0 | BF33: =BE33/$P33 -> 0 | BG33: 0 | BH33: =BG33/$P33 -> 0 | BI33: 0 | BJ33: =BI33/$P33 -> 0 | BK33: 0 | BL33: =BK33/$P33 -> 0 | BM33: 0 | BN33: =BM33/$P33 -> 0 | BO33: 0 | BP33: =BO33/$P33 -> 0 | BQ33: 0 | BR33: =BQ33/$P33 -> 0 | BS33: =BG33+BI33+BK33+BM33+BO33+BQ33 -> 0 | BT33: =BS33/$P33 -> 0 | BU33: 0 | BV33: =BU33/$P33 -> 0 | BW33: 0 | BX33: =BW33/$P33 -> 0 | BY33: 0 | BZ33: =BY33/$P33 -> 0 | CA33: 0 | CB33: =CA33/$P33 -> 0 | CC33: 0 | CD33: =CC33/$P33 -> 0 | CE33: 0 | CF33: =CE33/$P33 -> 0 | CG33: =BU33+BW33+BY33+CA33+CC33+CE33 -> 0 | CH33: =CG33/$P33 -> 0 | CI33: 0 | CJ33: =CI33/$P33 -> 0 | CK33: 0 | CL33: =CK33/$P33 -> 0 | CM33: 0 | CN33: =CM33/$P33 -> 0 | CO33: 0 | CP33: =CO33/$P33 -> 0 | CQ33: 0 | CR33: =CQ33/$P33 -> 0 | CS33: 0 | CT33: =CS33/$P33 -> 0 | CU33: =CI33+CK33+CM33+CO33+CQ33+CS33 -> 0 | CV33: =CU33/$P33 -> 0
C34: 25 | D34: Muro con ventanas (Blanco) | E34: =E7 -> 35.6 | F34: 2.73 | G34: =E34*F34 -> 97.188 | H34: 1.5 | I34: 1.2 | J34: 14 | K34: =(H34*I34)*J34 -> 25.2 | L34: =G34-K34 -> 71.988 | P34: =SUM(L34:O34) -> 71.988 | Q34: 0 | R34: =Q34/$P34 -> 0 | S34: 0 | T34: =S34/$P34 -> 0 | U34: 0 | V34: =U34/$P34 -> 0 | W34: 0 | X34: =W34/$P34 -> 0 | Y34: 0 | Z34: =Y34/$P34 -> 0 | AA34: 0 | AB34: =AA34/$P34 -> 0 | AC34: =Q34+S34+U34+W34+Y34+AA34 -> 0 | AD34: =AC34/$P34 -> 0 | AE34: 0 | AF34: =AE34/$P34 -> 0 | AG34: 0 | AH34: =AG34/$P34 -> 0 | AI34: 0 | AJ34: =AI34/$P34 -> 0 | AK34: 0 | AL34: =AK34/$P34 -> 0 | AM34: 0 | AN34: =AM34/$P34 -> 0 | AO34: 0 | AP34: =AO34/$P34 -> 0 | AQ34: =AE34+AG34+AI34+AK34+AM34+AO34 -> 0 | AR34: =AQ34/$P34 -> 0 | AS34: 0 | AT34: =AS34/$P34 -> 0 | AU34: 0 | AV34: =AU34/$P34 -> 0 | AW34: 0 | AX34: =AW34/$P34 -> 0 | AY34: 0 | AZ34: =AY34/$P34 -> 0 | BA34: 0 | BB34: =BA34/$P34 -> 0 | BC34: 0 | BD34: =BC34/$P34 -> 0 | BE34: =AS34+AU34+AW34+AY34+BA34+BC34 -> 0 | BF34: =BE34/$P34 -> 0 | BG34: 0 | BH34: =BG34/$P34 -> 0 | BI34: 0 | BJ34: =BI34/$P34 -> 0 | BK34: 0 | BL34: =BK34/$P34 -> 0 | BM34: 0 | BN34: =BM34/$P34 -> 0 | BO34: 0 | BP34: =BO34/$P34 -> 0 | BQ34: 0 | BR34: =BQ34/$P34 -> 0 | BS34: =BG34+BI34+BK34+BM34+BO34+BQ34 -> 0 | BT34: =BS34/$P34 -> 0 | BU34: 0 | BV34: =BU34/$P34 -> 0 | BW34: 0 | BX34: =BW34/$P34 -> 0 | BY34: 0 | BZ34: =BY34/$P34 -> 0 | CA34: 0 | CB34: =CA34/$P34 -> 0 | CC34: 0 | CD34: =CC34/$P34 -> 0 | CE34: 0 | CF34: =CE34/$P34 -> 0 | CG34: =BU34+BW34+BY34+CA34+CC34+CE34 -> 0 | CH34: =CG34/$P34 -> 0 | CI34: 0 | CJ34: =CI34/$P34 -> 0 | CK34: 0 | CL34: =CK34/$P34 -> 0 | CM34: 0 | CN34: =CM34/$P34 -> 0 | CO34: 0 | CP34: =CO34/$P34 -> 0 | CQ34: 0 | CR34: =CQ34/$P34 -> 0 | CS34: 0 | CT34: =CS34/$P34 -> 0 | CU34: =CI34+CK34+CM34+CO34+CQ34+CS34 -> 0 | CV34: =CU34/$P34 -> 0
B35: FRONTAL | C35: 26 | D35: Muro sin ventana (Blanco) | E35: =E5 -> 35.6 | F35: 4.66 | G35: =E35*F35 -> 165.896 | L35: =G35-K35 -> 165.896 | P35: =SUM(L35:O35) -> 165.896 | Q35: 0 | R35: =Q35/$P35 -> 0 | S35: 0 | T35: =S35/$P35 -> 0 | U35: 0 | V35: =U35/$P35 -> 0 | W35: 0 | X35: =W35/$P35 -> 0 | Y35: 0 | Z35: =Y35/$P35 -> 0 | AA35: 0 | AB35: =AA35/$P35 -> 0 | AC35: =Q35+S35+U35+W35+Y35+AA35 -> 0 | AD35: =AC35/$P35 -> 0 | AE35: 0 | AF35: =AE35/$P35 -> 0 | AG35: 0 | AH35: =AG35/$P35 -> 0 | AI35: 0 | AJ35: =AI35/$P35 -> 0 | AK35: 0 | AL35: =AK35/$P35 -> 0 | AM35: 0 | AN35: =AM35/$P35 -> 0 | AO35: 0 | AP35: =AO35/$P35 -> 0 | AQ35: =AE35+AG35+AI35+AK35+AM35+AO35 -> 0 | AR35: =AQ35/$P35 -> 0 | AS35: 0 | AT35: =AS35/$P35 -> 0 | AU35: 0 | AV35: =AU35/$P35 -> 0 | AW35: 0 | AX35: =AW35/$P35 -> 0 | AY35: 0 | AZ35: =AY35/$P35 -> 0 | BA35: 0 | BB35: =BA35/$P35 -> 0 | BC35: 0 | BD35: =BC35/$P35 -> 0 | BE35: =AS35+AU35+AW35+AY35+BA35+BC35 -> 0 | BF35: =BE35/$P35 -> 0 | BG35: 0 | BH35: =BG35/$P35 -> 0 | BI35: 0 | BJ35: =BI35/$P35 -> 0 | BK35: 0 | BL35: =BK35/$P35 -> 0 | BM35: 0 | BN35: =BM35/$P35 -> 0 | BO35: 0 | BP35: =BO35/$P35 -> 0 | BQ35: 0 | BR35: =BQ35/$P35 -> 0 | BS35: =BG35+BI35+BK35+BM35+BO35+BQ35 -> 0 | BT35: =BS35/$P35 -> 0 | BU35: 0 | BV35: =BU35/$P35 -> 0 | BW35: 0 | BX35: =BW35/$P35 -> 0 | BY35: 0 | BZ35: =BY35/$P35 -> 0 | CA35: 0 | CB35: =CA35/$P35 -> 0 | CC35: 0 | CD35: =CC35/$P35 -> 0 | CE35: 0 | CF35: =CE35/$P35 -> 0 | CG35: =BU35+BW35+BY35+CA35+CC35+CE35 -> 0 | CH35: =CG35/$P35 -> 0 | CI35: 0 | CJ35: =CI35/$P35 -> 0 | CK35: 0 | CL35: =CK35/$P35 -> 0 | CM35: 0 | CN35: =CM35/$P35 -> 0 | CO35: 0 | CP35: =CO35/$P35 -> 0 | CQ35: 0 | CR35: =CQ35/$P35 -> 0 | CS35: 0 | CT35: =CS35/$P35 -> 0 | CU35: =CI35+CK35+CM35+CO35+CQ35+CS35 -> 0 | CV35: =CU35/$P35 -> 0
C36: 27 | D36: Placa de balcón (Negro) (x14) | E36: 0.3 | F36: 2.91 | G36: =E36*F36*14 -> 12.222 | N36: =G36 -> 12.222 | P36: =SUM(L36:O36) -> 12.222 | Q36: 0 | R36: =Q36/$P36 -> 0 | S36: 0 | T36: =S36/$P36 -> 0 | U36: 0 | V36: =U36/$P36 -> 0 | W36: 0 | X36: =W36/$P36 -> 0 | Y36: 0 | Z36: =Y36/$P36 -> 0 | AA36: 0 | AB36: =AA36/$P36 -> 0 | AC36: =Q36+S36+U36+W36+Y36+AA36 -> 0 | AD36: =AC36/$P36 -> 0 | AE36: 0 | AF36: =AE36/$P36 -> 0 | AG36: 0 | AH36: =AG36/$P36 -> 0 | AI36: 0 | AJ36: =AI36/$P36 -> 0 | AK36: 0 | AL36: =AK36/$P36 -> 0 | AM36: 0 | AN36: =AM36/$P36 -> 0 | AO36: 0 | AP36: =AO36/$P36 -> 0 | AQ36: =AE36+AG36+AI36+AK36+AM36+AO36 -> 0 | AR36: =AQ36/$P36 -> 0 | AS36: 0 | AT36: =AS36/$P36 -> 0 | AU36: 0 | AV36: =AU36/$P36 -> 0 | AW36: 0 | AX36: =AW36/$P36 -> 0 | AY36: 0 | AZ36: =AY36/$P36 -> 0 | BA36: 0 | BB36: =BA36/$P36 -> 0 | BC36: 0 | BD36: =BC36/$P36 -> 0 | BE36: =AS36+AU36+AW36+AY36+BA36+BC36 -> 0 | BF36: =BE36/$P36 -> 0 | BG36: 0 | BH36: =BG36/$P36 -> 0 | BI36: 0 | BJ36: =BI36/$P36 -> 0 | BK36: 0 | BL36: =BK36/$P36 -> 0 | BM36: 0 | BN36: =BM36/$P36 -> 0 | BO36: 0 | BP36: =BO36/$P36 -> 0 | BQ36: 0 | BR36: =BQ36/$P36 -> 0 | BS36: =BG36+BI36+BK36+BM36+BO36+BQ36 -> 0 | BT36: =BS36/$P36 -> 0 | BU36: 0 | BV36: =BU36/$P36 -> 0 | BW36: 0 | BX36: =BW36/$P36 -> 0 | BY36: 0 | BZ36: =BY36/$P36 -> 0 | CA36: 0 | CB36: =CA36/$P36 -> 0 | CC36: 0 | CD36: =CC36/$P36 -> 0 | CE36: 0 | CF36: =CE36/$P36 -> 0 | CG36: =BU36+BW36+BY36+CA36+CC36+CE36 -> 0 | CH36: =CG36/$P36 -> 0 | CI36: 0 | CJ36: =CI36/$P36 -> 0 | CK36: 0 | CL36: =CK36/$P36 -> 0 | CM36: 0 | CN36: =CM36/$P36 -> 0 | CO36: 0 | CP36: =CO36/$P36 -> 0 | CQ36: 0 | CR36: =CQ36/$P36 -> 0 | CS36: 0 | CT36: =CS36/$P36 -> 0 | CU36: =CI36+CK36+CM36+CO36+CQ36+CS36 -> 0 | CV36: =CU36/$P36 -> 0
C37: 27.1 | D37: Cielo raso balcón (X14) | E37: 0.6 | F37: 1.71 | G37: =E37*F37*14 -> 14.364 | O37: =G37 -> 14.364 | P37: =SUM(L37:O37) -> 14.364 | Q37: 0 | R37: =Q37/$P37 -> 0 | S37: 0 | T37: =S37/$P37 -> 0 | U37: 0 | V37: =U37/$P37 -> 0 | W37: 0 | X37: =W37/$P37 -> 0 | Y37: 0 | Z37: =Y37/$P37 -> 0 | AA37: 0 | AB37: =AA37/$P37 -> 0 | AC37: =Q37+S37+U37+W37+Y37+AA37 -> 0 | AD37: =AC37/$P37 -> 0 | AE37: 0 | AF37: =AE37/$P37 -> 0 | AG37: 0 | AH37: =AG37/$P37 -> 0 | AI37: 0 | AJ37: =AI37/$P37 -> 0 | AK37: 0 | AL37: =AK37/$P37 -> 0 | AM37: 0 | AN37: =AM37/$P37 -> 0 | AO37: 0 | AP37: =AO37/$P37 -> 0 | AQ37: =AE37+AG37+AI37+AK37+AM37+AO37 -> 0 | AR37: =AQ37/$P37 -> 0 | AS37: 0 | AT37: =AS37/$P37 -> 0 | AU37: 0 | AV37: =AU37/$P37 -> 0 | AW37: 0 | AX37: =AW37/$P37 -> 0 | AY37: 0 | AZ37: =AY37/$P37 -> 0 | BA37: 0 | BB37: =BA37/$P37 -> 0 | BC37: 0 | BD37: =BC37/$P37 -> 0 | BE37: =AS37+AU37+AW37+AY37+BA37+BC37 -> 0 | BF37: =BE37/$P37 -> 0 | BG37: 0 | BH37: =BG37/$P37 -> 0 | BI37: 0 | BJ37: =BI37/$P37 -> 0 | BK37: 0 | BL37: =BK37/$P37 -> 0 | BM37: 0 | BN37: =BM37/$P37 -> 0 | BO37: 0 | BP37: =BO37/$P37 -> 0 | BQ37: 0 | BR37: =BQ37/$P37 -> 0 | BS37: =BG37+BI37+BK37+BM37+BO37+BQ37 -> 0 | BT37: =BS37/$P37 -> 0 | BU37: 0 | BV37: =BU37/$P37 -> 0 | BW37: 0 | BX37: =BW37/$P37 -> 0 | BY37: 0 | BZ37: =BY37/$P37 -> 0 | CA37: 0 | CB37: =CA37/$P37 -> 0 | CC37: 0 | CD37: =CC37/$P37 -> 0 | CE37: 0 | CF37: =CE37/$P37 -> 0 | CG37: =BU37+BW37+BY37+CA37+CC37+CE37 -> 0 | CH37: =CG37/$P37 -> 0 | CI37: 0 | CJ37: =CI37/$P37 -> 0 | CK37: 0 | CL37: =CK37/$P37 -> 0 | CM37: 0 | CN37: =CM37/$P37 -> 0 | CO37: 0 | CP37: =CO37/$P37 -> 0 | CQ37: 0 | CR37: =CQ37/$P37 -> 0 | CS37: 0 | CT37: =CS37/$P37 -> 0 | CU37: =CI37+CK37+CM37+CO37+CQ37+CS37 -> 0 | CV37: =CU37/$P37 -> 0
C38: 28 | D38: Muro con ventanas (Blanco) | E38: =E5 -> 35.6 | F38: 3.19 | G38: =E38*F38 -> 113.564 | H38: 1.5 | I38: 1.2 | J38: 14 | K38: =(H38*I38)*J38 -> 25.2 | L38: =G38-K38 -> 88.364 | P38: =SUM(L38:O38) -> 88.364 | Q38: 0 | R38: =Q38/$P38 -> 0 | S38: 0 | T38: =S38/$P38 -> 0 | U38: 0 | V38: =U38/$P38 -> 0 | W38: 0 | X38: =W38/$P38 -> 0 | Y38: 0 | Z38: =Y38/$P38 -> 0 | AA38: 0 | AB38: =AA38/$P38 -> 0 | AC38: =Q38+S38+U38+W38+Y38+AA38 -> 0 | AD38: =AC38/$P38 -> 0 | AE38: 0 | AF38: =AE38/$P38 -> 0 | AG38: 0 | AH38: =AG38/$P38 -> 0 | AI38: 0 | AJ38: =AI38/$P38 -> 0 | AK38: 0 | AL38: =AK38/$P38 -> 0 | AM38: 0 | AN38: =AM38/$P38 -> 0 | AO38: 0 | AP38: =AO38/$P38 -> 0 | AQ38: =AE38+AG38+AI38+AK38+AM38+AO38 -> 0 | AR38: =AQ38/$P38 -> 0 | AS38: 0 | AT38: =AS38/$P38 -> 0 | AU38: 0 | AV38: =AU38/$P38 -> 0 | AW38: 0 | AX38: =AW38/$P38 -> 0 | AY38: 0 | AZ38: =AY38/$P38 -> 0 | BA38: 0 | BB38: =BA38/$P38 -> 0 | BC38: 0 | BD38: =BC38/$P38 -> 0 | BE38: =AS38+AU38+AW38+AY38+BA38+BC38 -> 0 | BF38: =BE38/$P38 -> 0 | BG38: 0 | BH38: =BG38/$P38 -> 0 | BI38: 0 | BJ38: =BI38/$P38 -> 0 | BK38: 0 | BL38: =BK38/$P38 -> 0 | BM38: 0 | BN38: =BM38/$P38 -> 0 | BO38: 0 | BP38: =BO38/$P38 -> 0 | BQ38: 0 | BR38: =BQ38/$P38 -> 0 | BS38: =BG38+BI38+BK38+BM38+BO38+BQ38 -> 0 | BT38: =BS38/$P38 -> 0 | BU38: 0 | BV38: =BU38/$P38 -> 0 | BW38: 0 | BX38: =BW38/$P38 -> 0 | BY38: 0 | BZ38: =BY38/$P38 -> 0 | CA38: 0 | CB38: =CA38/$P38 -> 0 | CC38: 0 | CD38: =CC38/$P38 -> 0 | CE38: 0 | CF38: =CE38/$P38 -> 0 | CG38: =BU38+BW38+BY38+CA38+CC38+CE38 -> 0 | CH38: =CG38/$P38 -> 0 | CI38: 0 | CJ38: =CI38/$P38 -> 0 | CK38: 0 | CL38: =CK38/$P38 -> 0 | CM38: 0 | CN38: =CM38/$P38 -> 0 | CO38: 0 | CP38: =CO38/$P38 -> 0 | CQ38: 0 | CR38: =CQ38/$P38 -> 0 | CS38: 0 | CT38: =CS38/$P38 -> 0 | CU38: =CI38+CK38+CM38+CO38+CQ38+CS38 -> 0 | CV38: =CU38/$P38 -> 0
C39: 29 | D39: Muro con balcón (Blanco) | E39: =E5 -> 35.6 | F39: 4.32 | G39: =E39*F39 -> 153.792 | H39: 1.5 | I39: 1.2 | J39: 14 | K39: =(H39*I39)*J39 -> 25.2 | L39: =G39-(K39+K40) -> 78.192 | P39: =SUM(L39:O39) -> 78.192 | Q39: 0 | R39: =Q39/$P39 -> 0 | S39: 0 | T39: =S39/$P39 -> 0 | U39: 0 | V39: =U39/$P39 -> 0 | W39: 0 | X39: =W39/$P39 -> 0 | Y39: 0 | Z39: =Y39/$P39 -> 0 | AA39: 0 | AB39: =AA39/$P39 -> 0 | AC39: =Q39+S39+U39+W39+Y39+AA39 -> 0 | AD39: =AC39/$P39 -> 0 | AE39: 0 | AF39: =AE39/$P39 -> 0 | AG39: 0 | AH39: =AG39/$P39 -> 0 | AI39: 0 | AJ39: =AI39/$P39 -> 0 | AK39: 0 | AL39: =AK39/$P39 -> 0 | AM39: 0 | AN39: =AM39/$P39 -> 0 | AO39: 0 | AP39: =AO39/$P39 -> 0 | AQ39: =AE39+AG39+AI39+AK39+AM39+AO39 -> 0 | AR39: =AQ39/$P39 -> 0 | AS39: 0 | AT39: =AS39/$P39 -> 0 | AU39: 0 | AV39: =AU39/$P39 -> 0 | AW39: 0 | AX39: =AW39/$P39 -> 0 | AY39: 0 | AZ39: =AY39/$P39 -> 0 | BA39: 0 | BB39: =BA39/$P39 -> 0 | BC39: 0 | BD39: =BC39/$P39 -> 0 | BE39: =AS39+AU39+AW39+AY39+BA39+BC39 -> 0 | BF39: =BE39/$P39 -> 0 | BG39: 0 | BH39: =BG39/$P39 -> 0 | BI39: 0 | BJ39: =BI39/$P39 -> 0 | BK39: 0 | BL39: =BK39/$P39 -> 0 | BM39: 0 | BN39: =BM39/$P39 -> 0 | BO39: 0 | BP39: =BO39/$P39 -> 0 | BQ39: 0 | BR39: =BQ39/$P39 -> 0 | BS39: =BG39+BI39+BK39+BM39+BO39+BQ39 -> 0 | BT39: =BS39/$P39 -> 0 | BU39: 0 | BV39: =BU39/$P39 -> 0 | BW39: 0 | BX39: =BW39/$P39 -> 0 | BY39: 0 | BZ39: =BY39/$P39 -> 0 | CA39: 0 | CB39: =CA39/$P39 -> 0 | CC39: 0 | CD39: =CC39/$P39 -> 0 | CE39: 0 | CF39: =CE39/$P39 -> 0 | CG39: =BU39+BW39+BY39+CA39+CC39+CE39 -> 0 | CH39: =CG39/$P39 -> 0 | CI39: 0 | CJ39: =CI39/$P39 -> 0 | CK39: 0 | CL39: =CK39/$P39 -> 0 | CM39: 0 | CN39: =CM39/$P39 -> 0 | CO39: 0 | CP39: =CO39/$P39 -> 0 | CQ39: 0 | CR39: =CQ39/$P39 -> 0 | CS39: 0 | CT39: =CS39/$P39 -> 0 | CU39: =CI39+CK39+CM39+CO39+CQ39+CS39 -> 0 | CV39: =CU39/$P39 -> 0
H40: 2.4 | I40: 1.5 | J40: 14 | K40: =(H40*I40)*J40 -> 50.4 | P40: =SUM(L40:O40) -> 0 | Q40: 0 | S40: 0 | U40: 0 | W40: 0 | Y40: 0 | AA40: 0 | AC40: =Q40+S40+U40+W40+Y40+AA40 -> 0 | AE40: 0 | AG40: 0 | AI40: 0 | AK40: 0 | AM40: 0 | AO40: 0 | AQ40: =AE40+AG40+AI40+AK40+AM40+AO40 -> 0 | AS40: 0 | AU40: 0 | AW40: 0 | AY40: 0 | BA40: 0 | BC40: 0 | BE40: =AS40+AU40+AW40+AY40+BA40+BC40 -> 0 | BG40: 0 | BI40: 0 | BK40: 0 | BM40: 0 | BO40: 0 | BQ40: 0 | BS40: =BG40+BI40+BK40+BM40+BO40+BQ40 -> 0 | BU40: 0 | BW40: 0 | BY40: 0 | CA40: 0 | CC40: 0 | CE40: 0 | CG40: =BU40+BW40+BY40+CA40+CC40+CE40 -> 0 | CI40: 0 | CK40: 0 | CM40: 0 | CO40: 0 | CQ40: 0 | CS40: 0 | CU40: =CI40+CK40+CM40+CO40+CQ40+CS40 -> 0
C41: 30 | D41: Placa de balcón (Negro) (x14) | E41: 0.3 | F41: 5.1 | G41: =E41*F41*14 -> 21.42 | N41: =G41 -> 21.42 | P41: =SUM(L41:O41) -> 21.42 | Q41: 0 | R41: =Q41/$P41 -> 0 | S41: 0 | T41: =S41/$P41 -> 0 | U41: 0 | V41: =U41/$P41 -> 0 | W41: 0 | X41: =W41/$P41 -> 0 | Y41: 0 | Z41: =Y41/$P41 -> 0 | AA41: 0 | AB41: =AA41/$P41 -> 0 | AC41: =Q41+S41+U41+W41+Y41+AA41 -> 0 | AD41: =AC41/$P41 -> 0 | AE41: 0 | AF41: =AE41/$P41 -> 0 | AG41: 0 | AH41: =AG41/$P41 -> 0 | AI41: 0 | AJ41: =AI41/$P41 -> 0 | AK41: 0 | AL41: =AK41/$P41 -> 0 | AM41: 0 | AN41: =AM41/$P41 -> 0 | AO41: 0 | AP41: =AO41/$P41 -> 0 | AQ41: =AE41+AG41+AI41+AK41+AM41+AO41 -> 0 | AR41: =AQ41/$P41 -> 0 | AS41: 0 | AT41: =AS41/$P41 -> 0 | AU41: 0 | AV41: =AU41/$P41 -> 0 | AW41: 0 | AX41: =AW41/$P41 -> 0 | AY41: 0 | AZ41: =AY41/$P41 -> 0 | BA41: 0 | BB41: =BA41/$P41 -> 0 | BC41: 0 | BD41: =BC41/$P41 -> 0 | BE41: =AS41+AU41+AW41+AY41+BA41+BC41 -> 0 | BF41: =BE41/$P41 -> 0 | BG41: 0 | BH41: =BG41/$P41 -> 0 | BI41: 0 | BJ41: =BI41/$P41 -> 0 | BK41: 0 | BL41: =BK41/$P41 -> 0 | BM41: 0 | BN41: =BM41/$P41 -> 0 | BO41: 0 | BP41: =BO41/$P41 -> 0 | BQ41: 0 | BR41: =BQ41/$P41 -> 0 | BS41: =BG41+BI41+BK41+BM41+BO41+BQ41 -> 0 | BT41: =BS41/$P41 -> 0 | BU41: 0 | BV41: =BU41/$P41 -> 0 | BW41: 0 | BX41: =BW41/$P41 -> 0 | BY41: 0 | BZ41: =BY41/$P41 -> 0 | CA41: 0 | CB41: =CA41/$P41 -> 0 | CC41: 0 | CD41: =CC41/$P41 -> 0 | CE41: 0 | CF41: =CE41/$P41 -> 0 | CG41: =BU41+BW41+BY41+CA41+CC41+CE41 -> 0 | CH41: =CG41/$P41 -> 0 | CI41: 0 | CJ41: =CI41/$P41 -> 0 | CK41: 0 | CL41: =CK41/$P41 -> 0 | CM41: 0 | CN41: =CM41/$P41 -> 0 | CO41: 0 | CP41: =CO41/$P41 -> 0 | CQ41: 0 | CR41: =CQ41/$P41 -> 0 | CS41: 0 | CT41: =CS41/$P41 -> 0 | CU41: =CI41+CK41+CM41+CO41+CQ41+CS41 -> 0 | CV41: =CU41/$P41 -> 0
C42: 30.1 | D42: Cielo raso balcón (X14) | E42: 0.6 | F42: 5.1 | G42: =E42*F42*14 -> 42.84 | O42: =G42 -> 42.84 | P42: =SUM(L42:O42) -> 42.84 | Q42: 0 | R42: =Q42/$P42 -> 0 | S42: 0 | T42: =S42/$P42 -> 0 | U42: 0 | V42: =U42/$P42 -> 0 | W42: 0 | X42: =W42/$P42 -> 0 | Y42: 0 | Z42: =Y42/$P42 -> 0 | AA42: 0 | AB42: =AA42/$P42 -> 0 | AC42: =Q42+S42+U42+W42+Y42+AA42 -> 0 | AD42: =AC42/$P42 -> 0 | AE42: 0 | AF42: =AE42/$P42 -> 0 | AG42: 0 | AH42: =AG42/$P42 -> 0 | AI42: 0 | AJ42: =AI42/$P42 -> 0 | AK42: 0 | AL42: =AK42/$P42 -> 0 | AM42: 0 | AN42: =AM42/$P42 -> 0 | AO42: 0 | AP42: =AO42/$P42 -> 0 | AQ42: =AE42+AG42+AI42+AK42+AM42+AO42 -> 0 | AR42: =AQ42/$P42 -> 0 | AS42: 0 | AT42: =AS42/$P42 -> 0 | AU42: 0 | AV42: =AU42/$P42 -> 0 | AW42: 0 | AX42: =AW42/$P42 -> 0 | AY42: 0 | AZ42: =AY42/$P42 -> 0 | BA42: 0 | BB42: =BA42/$P42 -> 0 | BC42: 0 | BD42: =BC42/$P42 -> 0 | BE42: =AS42+AU42+AW42+AY42+BA42+BC42 -> 0 | BF42: =BE42/$P42 -> 0 | BG42: 0 | BH42: =BG42/$P42 -> 0 | BI42: 0 | BJ42: =BI42/$P42 -> 0 | BK42: 0 | BL42: =BK42/$P42 -> 0 | BM42: 0 | BN42: =BM42/$P42 -> 0 | BO42: 0 | BP42: =BO42/$P42 -> 0 | BQ42: 0 | BR42: =BQ42/$P42 -> 0 | BS42: =BG42+BI42+BK42+BM42+BO42+BQ42 -> 0 | BT42: =BS42/$P42 -> 0 | BU42: 0 | BV42: =BU42/$P42 -> 0 | BW42: 0 | BX42: =BW42/$P42 -> 0 | BY42: 0 | BZ42: =BY42/$P42 -> 0 | CA42: 0 | CB42: =CA42/$P42 -> 0 | CC42: 0 | CD42: =CC42/$P42 -> 0 | CE42: 0 | CF42: =CE42/$P42 -> 0 | CG42: =BU42+BW42+BY42+CA42+CC42+CE42 -> 0 | CH42: =CG42/$P42 -> 0 | CI42: 0 | CJ42: =CI42/$P42 -> 0 | CK42: 0 | CL42: =CK42/$P42 -> 0 | CM42: 0 | CN42: =CM42/$P42 -> 0 | CO42: 0 | CP42: =CO42/$P42 -> 0 | CQ42: 0 | CR42: =CQ42/$P42 -> 0 | CS42: 0 | CT42: =CS42/$P42 -> 0 | CU42: =CI42+CK42+CM42+CO42+CQ42+CS42 -> 0 | CV42: =CU42/$P42 -> 0
C43: 31 | D43: Muro sin ventanas (Negro) | E43: =E5 -> 35.6 | F43: 0.7 | G43: =E43*F43 -> 24.92 | N43: =G43-K43 -> 24.92 | P43: =SUM(L43:O43) -> 24.92 | Q43: 0 | R43: =Q43/$P43 -> 0 | S43: 0 | T43: =S43/$P43 -> 0 | U43: 0 | V43: =U43/$P43 -> 0 | W43: 0 | X43: =W43/$P43 -> 0 | Y43: 0 | Z43: =Y43/$P43 -> 0 | AA43: 0 | AB43: =AA43/$P43 -> 0 | AC43: =Q43+S43+U43+W43+Y43+AA43 -> 0 | AD43: =AC43/$P43 -> 0 | AE43: 0 | AF43: =AE43/$P43 -> 0 | AG43: 0 | AH43: =AG43/$P43 -> 0 | AI43: 0 | AJ43: =AI43/$P43 -> 0 | AK43: 0 | AL43: =AK43/$P43 -> 0 | AM43: 0 | AN43: =AM43/$P43 -> 0 | AO43: 0 | AP43: =AO43/$P43 -> 0 | AQ43: =AE43+AG43+AI43+AK43+AM43+AO43 -> 0 | AR43: =AQ43/$P43 -> 0 | AS43: 0 | AT43: =AS43/$P43 -> 0 | AU43: 0 | AV43: =AU43/$P43 -> 0 | AW43: 0 | AX43: =AW43/$P43 -> 0 | AY43: 0 | AZ43: =AY43/$P43 -> 0 | BA43: 0 | BB43: =BA43/$P43 -> 0 | BC43: 0 | BD43: =BC43/$P43 -> 0 | BE43: =AS43+AU43+AW43+AY43+BA43+BC43 -> 0 | BF43: =BE43/$P43 -> 0 | BG43: 0 | BH43: =BG43/$P43 -> 0 | BI43: 0 | BJ43: =BI43/$P43 -> 0 | BK43: 0 | BL43: =BK43/$P43 -> 0 | BM43: 0 | BN43: =BM43/$P43 -> 0 | BO43: 0 | BP43: =BO43/$P43 -> 0 | BQ43: 0 | BR43: =BQ43/$P43 -> 0 | BS43: =BG43+BI43+BK43+BM43+BO43+BQ43 -> 0 | BT43: =BS43/$P43 -> 0 | BU43: 0 | BV43: =BU43/$P43 -> 0 | BW43: 0 | BX43: =BW43/$P43 -> 0 | BY43: 0 | BZ43: =BY43/$P43 -> 0 | CA43: 0 | CB43: =CA43/$P43 -> 0 | CC43: 0 | CD43: =CC43/$P43 -> 0 | CE43: 0 | CF43: =CE43/$P43 -> 0 | CG43: =BU43+BW43+BY43+CA43+CC43+CE43 -> 0 | CH43: =CG43/$P43 -> 0 | CI43: 0 | CJ43: =CI43/$P43 -> 0 | CK43: 0 | CL43: =CK43/$P43 -> 0 | CM43: 0 | CN43: =CM43/$P43 -> 0 | CO43: 0 | CP43: =CO43/$P43 -> 0 | CQ43: 0 | CR43: =CQ43/$P43 -> 0 | CS43: 0 | CT43: =CS43/$P43 -> 0 | CU43: =CI43+CK43+CM43+CO43+CQ43+CS43 -> 0 | CV43: =CU43/$P43 -> 0
C44: 32 | D44: Muro sin ventanas (Negro) | E44: =E5 -> 35.6 | F44: 1.45 | G44: =E44*F44 -> 51.62 | N44: =G44-K44 -> 51.62 | P44: =SUM(L44:O44) -> 51.62 | Q44: 0 | R44: =Q44/$P44 -> 0 | S44: 0 | T44: =S44/$P44 -> 0 | U44: 0 | V44: =U44/$P44 -> 0 | W44: 0 | X44: =W44/$P44 -> 0 | Y44: 0 | Z44: =Y44/$P44 -> 0 | AA44: 0 | AB44: =AA44/$P44 -> 0 | AC44: =Q44+S44+U44+W44+Y44+AA44 -> 0 | AD44: =AC44/$P44 -> 0 | AE44: 0 | AF44: =AE44/$P44 -> 0 | AG44: 0 | AH44: =AG44/$P44 -> 0 | AI44: 0 | AJ44: =AI44/$P44 -> 0 | AK44: 0 | AL44: =AK44/$P44 -> 0 | AM44: 0 | AN44: =AM44/$P44 -> 0 | AO44: 0 | AP44: =AO44/$P44 -> 0 | AQ44: =AE44+AG44+AI44+AK44+AM44+AO44 -> 0 | AR44: =AQ44/$P44 -> 0 | AS44: 0 | AT44: =AS44/$P44 -> 0 | AU44: 0 | AV44: =AU44/$P44 -> 0 | AW44: 0 | AX44: =AW44/$P44 -> 0 | AY44: 0 | AZ44: =AY44/$P44 -> 0 | BA44: 0 | BB44: =BA44/$P44 -> 0 | BC44: 0 | BD44: =BC44/$P44 -> 0 | BE44: =AS44+AU44+AW44+AY44+BA44+BC44 -> 0 | BF44: =BE44/$P44 -> 0 | BG44: 0 | BH44: =BG44/$P44 -> 0 | BI44: 0 | BJ44: =BI44/$P44 -> 0 | BK44: 0 | BL44: =BK44/$P44 -> 0 | BM44: 0 | BN44: =BM44/$P44 -> 0 | BO44: 0 | BP44: =BO44/$P44 -> 0 | BQ44: 0 | BR44: =BQ44/$P44 -> 0 | BS44: =BG44+BI44+BK44+BM44+BO44+BQ44 -> 0 | BT44: =BS44/$P44 -> 0 | BU44: 0 | BV44: =BU44/$P44 -> 0 | BW44: 0 | BX44: =BW44/$P44 -> 0 | BY44: 0 | BZ44: =BY44/$P44 -> 0 | CA44: 0 | CB44: =CA44/$P44 -> 0 | CC44: 0 | CD44: =CC44/$P44 -> 0 | CE44: 0 | CF44: =CE44/$P44 -> 0 | CG44: =BU44+BW44+BY44+CA44+CC44+CE44 -> 0 | CH44: =CG44/$P44 -> 0 | CI44: 0 | CJ44: =CI44/$P44 -> 0 | CK44: 0 | CL44: =CK44/$P44 -> 0 | CM44: 0 | CN44: =CM44/$P44 -> 0 | CO44: 0 | CP44: =CO44/$P44 -> 0 | CQ44: 0 | CR44: =CQ44/$P44 -> 0 | CS44: 0 | CT44: =CS44/$P44 -> 0 | CU44: =CI44+CK44+CM44+CO44+CQ44+CS44 -> 0 | CV44: =CU44/$P44 -> 0
C45: 33 | D45: Muro con ventanas (Negro) | E45: 34 | F45: 3.3 | G45: =E45*F45 -> 112.2 | H45: 1.5 | I45: 1 | J45: 14 | K45: =(H45*I45)*J45 -> 21 | N45: =G45-(K45) -> 91.2 | P45: =SUM(L45:O45) -> 91.2 | Q45: 0 | R45: =Q45/$P45 -> 0 | S45: 0 | T45: =S45/$P45 -> 0 | U45: 0 | V45: =U45/$P45 -> 0 | W45: 0 | X45: =W45/$P45 -> 0 | Y45: 0 | Z45: =Y45/$P45 -> 0 | AA45: 0 | AB45: =AA45/$P45 -> 0 | AC45: =Q45+S45+U45+W45+Y45+AA45 -> 0 | AD45: =AC45/$P45 -> 0 | AE45: 0 | AF45: =AE45/$P45 -> 0 | AG45: 0 | AH45: =AG45/$P45 -> 0 | AI45: 0 | AJ45: =AI45/$P45 -> 0 | AK45: 0 | AL45: =AK45/$P45 -> 0 | AM45: 0 | AN45: =AM45/$P45 -> 0 | AO45: 0 | AP45: =AO45/$P45 -> 0 | AQ45: =AE45+AG45+AI45+AK45+AM45+AO45 -> 0 | AR45: =AQ45/$P45 -> 0 | AS45: 0 | AT45: =AS45/$P45 -> 0 | AU45: 0 | AV45: =AU45/$P45 -> 0 | AW45: 0 | AX45: =AW45/$P45 -> 0 | AY45: 0 | AZ45: =AY45/$P45 -> 0 | BA45: 0 | BB45: =BA45/$P45 -> 0 | BC45: 0 | BD45: =BC45/$P45 -> 0 | BE45: =AS45+AU45+AW45+AY45+BA45+BC45 -> 0 | BF45: =BE45/$P45 -> 0 | BG45: 0 | BH45: =BG45/$P45 -> 0 | BI45: 0 | BJ45: =BI45/$P45 -> 0 | BK45: 0 | BL45: =BK45/$P45 -> 0 | BM45: 0 | BN45: =BM45/$P45 -> 0 | BO45: 0 | BP45: =BO45/$P45 -> 0 | BQ45: 0 | BR45: =BQ45/$P45 -> 0 | BS45: =BG45+BI45+BK45+BM45+BO45+BQ45 -> 0 | BT45: =BS45/$P45 -> 0 | BU45: 0 | BV45: =BU45/$P45 -> 0 | BW45: 0 | BX45: =BW45/$P45 -> 0 | BY45: 0 | BZ45: =BY45/$P45 -> 0 | CA45: 0 | CB45: =CA45/$P45 -> 0 | CC45: 0 | CD45: =CC45/$P45 -> 0 | CE45: 0 | CF45: =CE45/$P45 -> 0 | CG45: =BU45+BW45+BY45+CA45+CC45+CE45 -> 0 | CH45: =CG45/$P45 -> 0 | CI45: 0 | CJ45: =CI45/$P45 -> 0 | CK45: 0 | CL45: =CK45/$P45 -> 0 | CM45: 0 | CN45: =CM45/$P45 -> 0 | CO45: 0 | CP45: =CO45/$P45 -> 0 | CQ45: 0 | CR45: =CQ45/$P45 -> 0 | CS45: 0 | CT45: =CS45/$P45 -> 0 | CU45: =CI45+CK45+CM45+CO45+CQ45+CS45 -> 0 | CV45: =CU45/$P45 -> 0
C46: 34 | D46: Muro Ascensor (Blanco) | E46: =E5 -> 35.6 | F46: 2 | G46: =E46*F46 -> 71.2 | L46: =G46-(K46) -> 71.2 | P46: =SUM(L46:O46) -> 71.2 | Q46: 0 | R46: =Q46/$P46 -> 0 | S46: 0 | T46: =S46/$P46 -> 0 | U46: 0 | V46: =U46/$P46 -> 0 | W46: 0 | X46: =W46/$P46 -> 0 | Y46: 0 | Z46: =Y46/$P46 -> 0 | AA46: 0 | AB46: =AA46/$P46 -> 0 | AC46: =Q46+S46+U46+W46+Y46+AA46 -> 0 | AD46: =AC46/$P46 -> 0 | AE46: 0 | AF46: =AE46/$P46 -> 0 | AG46: 0 | AH46: =AG46/$P46 -> 0 | AI46: 0 | AJ46: =AI46/$P46 -> 0 | AK46: 0 | AL46: =AK46/$P46 -> 0 | AM46: 0 | AN46: =AM46/$P46 -> 0 | AO46: 0 | AP46: =AO46/$P46 -> 0 | AQ46: =AE46+AG46+AI46+AK46+AM46+AO46 -> 0 | AR46: =AQ46/$P46 -> 0 | AS46: 0 | AT46: =AS46/$P46 -> 0 | AU46: 0 | AV46: =AU46/$P46 -> 0 | AW46: 0 | AX46: =AW46/$P46 -> 0 | AY46: 0 | AZ46: =AY46/$P46 -> 0 | BA46: 0 | BB46: =BA46/$P46 -> 0 | BC46: 0 | BD46: =BC46/$P46 -> 0 | BE46: =AS46+AU46+AW46+AY46+BA46+BC46 -> 0 | BF46: =BE46/$P46 -> 0 | BG46: 0 | BH46: =BG46/$P46 -> 0 | BI46: 0 | BJ46: =BI46/$P46 -> 0 | BK46: 0 | BL46: =BK46/$P46 -> 0 | BM46: 0 | BN46: =BM46/$P46 -> 0 | BO46: 0 | BP46: =BO46/$P46 -> 0 | BQ46: 0 | BR46: =BQ46/$P46 -> 0 | BS46: =BG46+BI46+BK46+BM46+BO46+BQ46 -> 0 | BT46: =BS46/$P46 -> 0 | BU46: 0 | BV46: =BU46/$P46 -> 0 | BW46: 0 | BX46: =BW46/$P46 -> 0 | BY46: 0 | BZ46: =BY46/$P46 -> 0 | CA46: 0 | CB46: =CA46/$P46 -> 0 | CC46: 0 | CD46: =CC46/$P46 -> 0 | CE46: 0 | CF46: =CE46/$P46 -> 0 | CG46: =BU46+BW46+BY46+CA46+CC46+CE46 -> 0 | CH46: =CG46/$P46 -> 0 | CI46: 0 | CJ46: =CI46/$P46 -> 0 | CK46: 0 | CL46: =CK46/$P46 -> 0 | CM46: 0 | CN46: =CM46/$P46 -> 0 | CO46: 0 | CP46: =CO46/$P46 -> 0 | CQ46: 0 | CR46: =CQ46/$P46 -> 0 | CS46: 0 | CT46: =CS46/$P46 -> 0 | CU46: =CI46+CK46+CM46+CO46+CQ46+CS46 -> 0 | CV46: =CU46/$P46 -> 0
C47: 35 | D47: Muro Ascensor (Blanco) | E47: =E5 -> 35.6 | F47: 2.04 | G47: =E47*F47 -> 72.624 | H47: 32 | I47: 1 | J47: 1 | K47: =(H47*I47)*J47 -> 32 | L47: =G47-(K47) -> 40.624 | P47: =SUM(L47:O47) -> 40.624 | Q47: 0 | R47: =Q47/$P47 -> 0 | S47: 0 | T47: =S47/$P47 -> 0 | U47: 0 | V47: =U47/$P47 -> 0 | W47: 0 | X47: =W47/$P47 -> 0 | Y47: 0 | Z47: =Y47/$P47 -> 0 | AA47: 0 | AB47: =AA47/$P47 -> 0 | AC47: =Q47+S47+U47+W47+Y47+AA47 -> 0 | AD47: =AC47/$P47 -> 0 | AE47: 0 | AF47: =AE47/$P47 -> 0 | AG47: 0 | AH47: =AG47/$P47 -> 0 | AI47: 0 | AJ47: =AI47/$P47 -> 0 | AK47: 0 | AL47: =AK47/$P47 -> 0 | AM47: 0 | AN47: =AM47/$P47 -> 0 | AO47: 0 | AP47: =AO47/$P47 -> 0 | AQ47: =AE47+AG47+AI47+AK47+AM47+AO47 -> 0 | AR47: =AQ47/$P47 -> 0 | AS47: 0 | AT47: =AS47/$P47 -> 0 | AU47: 0 | AV47: =AU47/$P47 -> 0 | AW47: 0 | AX47: =AW47/$P47 -> 0 | AY47: 0 | AZ47: =AY47/$P47 -> 0 | BA47: 0 | BB47: =BA47/$P47 -> 0 | BC47: 0 | BD47: =BC47/$P47 -> 0 | BE47: =AS47+AU47+AW47+AY47+BA47+BC47 -> 0 | BF47: =BE47/$P47 -> 0 | BG47: 0 | BH47: =BG47/$P47 -> 0 | BI47: 0 | BJ47: =BI47/$P47 -> 0 | BK47: 0 | BL47: =BK47/$P47 -> 0 | BM47: 0 | BN47: =BM47/$P47 -> 0 | BO47: 0 | BP47: =BO47/$P47 -> 0 | BQ47: 0 | BR47: =BQ47/$P47 -> 0 | BS47: =BG47+BI47+BK47+BM47+BO47+BQ47 -> 0 | BT47: =BS47/$P47 -> 0 | BU47: 0 | BV47: =BU47/$P47 -> 0 | BW47: 0 | BX47: =BW47/$P47 -> 0 | BY47: 0 | BZ47: =BY47/$P47 -> 0 | CA47: 0 | CB47: =CA47/$P47 -> 0 | CC47: 0 | CD47: =CC47/$P47 -> 0 | CE47: 0 | CF47: =CE47/$P47 -> 0 | CG47: =BU47+BW47+BY47+CA47+CC47+CE47 -> 0 | CH47: =CG47/$P47 -> 0 | CI47: 0 | CJ47: =CI47/$P47 -> 0 | CK47: 0 | CL47: =CK47/$P47 -> 0 | CM47: 0 | CN47: =CM47/$P47 -> 0 | CO47: 0 | CP47: =CO47/$P47 -> 0 | CQ47: 0 | CR47: =CQ47/$P47 -> 0 | CS47: 0 | CT47: =CS47/$P47 -> 0 | CU47: =CI47+CK47+CM47+CO47+CQ47+CS47 -> 0 | CV47: =CU47/$P47 -> 0
C48: 36 | D48: Muro Ascensor (Blanco) | E48: =E7 -> 35.6 | F48: 2 | G48: =E48*F48 -> 71.2 | L48: =G48-(K48) -> 71.2 | P48: =SUM(L48:O48) -> 71.2 | Q48: 0 | R48: =Q48/$P48 -> 0 | S48: 0 | T48: =S48/$P48 -> 0 | U48: 0 | V48: =U48/$P48 -> 0 | W48: 0 | X48: =W48/$P48 -> 0 | Y48: 0 | Z48: =Y48/$P48 -> 0 | AA48: 0 | AB48: =AA48/$P48 -> 0 | AC48: =Q48+S48+U48+W48+Y48+AA48 -> 0 | AD48: =AC48/$P48 -> 0 | AE48: 0 | AF48: =AE48/$P48 -> 0 | AG48: 0 | AH48: =AG48/$P48 -> 0 | AI48: 0 | AJ48: =AI48/$P48 -> 0 | AK48: 0 | AL48: =AK48/$P48 -> 0 | AM48: 0 | AN48: =AM48/$P48 -> 0 | AO48: 0 | AP48: =AO48/$P48 -> 0 | AQ48: =AE48+AG48+AI48+AK48+AM48+AO48 -> 0 | AR48: =AQ48/$P48 -> 0 | AS48: 0 | AT48: =AS48/$P48 -> 0 | AU48: 0 | AV48: =AU48/$P48 -> 0 | AW48: 0 | AX48: =AW48/$P48 -> 0 | AY48: 0 | AZ48: =AY48/$P48 -> 0 | BA48: 0 | BB48: =BA48/$P48 -> 0 | BC48: 0 | BD48: =BC48/$P48 -> 0 | BE48: =AS48+AU48+AW48+AY48+BA48+BC48 -> 0 | BF48: =BE48/$P48 -> 0 | BG48: 0 | BH48: =BG48/$P48 -> 0 | BI48: 0 | BJ48: =BI48/$P48 -> 0 | BK48: 0 | BL48: =BK48/$P48 -> 0 | BM48: 0 | BN48: =BM48/$P48 -> 0 | BO48: 0 | BP48: =BO48/$P48 -> 0 | BQ48: 0 | BR48: =BQ48/$P48 -> 0 | BS48: =BG48+BI48+BK48+BM48+BO48+BQ48 -> 0 | BT48: =BS48/$P48 -> 0 | BU48: 0 | BV48: =BU48/$P48 -> 0 | BW48: 0 | BX48: =BW48/$P48 -> 0 | BY48: 0 | BZ48: =BY48/$P48 -> 0 | CA48: 0 | CB48: =CA48/$P48 -> 0 | CC48: 0 | CD48: =CC48/$P48 -> 0 | CE48: 0 | CF48: =CE48/$P48 -> 0 | CG48: =BU48+BW48+BY48+CA48+CC48+CE48 -> 0 | CH48: =CG48/$P48 -> 0 | CI48: 0 | CJ48: =CI48/$P48 -> 0 | CK48: 0 | CL48: =CK48/$P48 -> 0 | CM48: 0 | CN48: =CM48/$P48 -> 0 | CO48: 0 | CP48: =CO48/$P48 -> 0 | CQ48: 0 | CR48: =CQ48/$P48 -> 0 | CS48: 0 | CT48: =CS48/$P48 -> 0 | CU48: =CI48+CK48+CM48+CO48+CQ48+CS48 -> 0 | CV48: =CU48/$P48 -> 0
C49: 37 | D49: Muro con ventanas (Negro) | E49: 34 | F49: 3.3 | G49: =E49*F49 -> 112.2 | H49: 1.5 | I49: 1 | J49: 14 | K49: =(H49*I49)*J49 -> 21 | N49: =G49-(K49+K50) -> 91.2 | P49: =SUM(L49:O49) -> 91.2 | Q49: 0 | R49: =Q49/$P49 -> 0 | S49: 0 | T49: =S49/$P49 -> 0 | U49: 0 | V49: =U49/$P49 -> 0 | W49: 0 | X49: =W49/$P49 -> 0 | Y49: 0 | Z49: =Y49/$P49 -> 0 | AA49: 0 | AB49: =AA49/$P49 -> 0 | AC49: =Q49+S49+U49+W49+Y49+AA49 -> 0 | AD49: =AC49/$P49 -> 0 | AE49: 0 | AF49: =AE49/$P49 -> 0 | AG49: 0 | AH49: =AG49/$P49 -> 0 | AI49: 0 | AJ49: =AI49/$P49 -> 0 | AK49: 0 | AL49: =AK49/$P49 -> 0 | AM49: 0 | AN49: =AM49/$P49 -> 0 | AO49: 0 | AP49: =AO49/$P49 -> 0 | AQ49: =AE49+AG49+AI49+AK49+AM49+AO49 -> 0 | AR49: =AQ49/$P49 -> 0 | AS49: 0 | AT49: =AS49/$P49 -> 0 | AU49: 0 | AV49: =AU49/$P49 -> 0 | AW49: 0 | AX49: =AW49/$P49 -> 0 | AY49: 0 | AZ49: =AY49/$P49 -> 0 | BA49: 0 | BB49: =BA49/$P49 -> 0 | BC49: 0 | BD49: =BC49/$P49 -> 0 | BE49: =AS49+AU49+AW49+AY49+BA49+BC49 -> 0 | BF49: =BE49/$P49 -> 0 | BG49: 0 | BH49: =BG49/$P49 -> 0 | BI49: 0 | BJ49: =BI49/$P49 -> 0 | BK49: 0 | BL49: =BK49/$P49 -> 0 | BM49: 0 | BN49: =BM49/$P49 -> 0 | BO49: 0 | BP49: =BO49/$P49 -> 0 | BQ49: 0 | BR49: =BQ49/$P49 -> 0 | BS49: =BG49+BI49+BK49+BM49+BO49+BQ49 -> 0 | BT49: =BS49/$P49 -> 0 | BU49: 0 | BV49: =BU49/$P49 -> 0 | BW49: 0 | BX49: =BW49/$P49 -> 0 | BY49: 0 | BZ49: =BY49/$P49 -> 0 | CA49: 0 | CB49: =CA49/$P49 -> 0 | CC49: 0 | CD49: =CC49/$P49 -> 0 | CE49: 0 | CF49: =CE49/$P49 -> 0 | CG49: =BU49+BW49+BY49+CA49+CC49+CE49 -> 0 | CH49: =CG49/$P49 -> 0 | CI49: 0 | CJ49: =CI49/$P49 -> 0 | CK49: 0 | CL49: =CK49/$P49 -> 0 | CM49: 0 | CN49: =CM49/$P49 -> 0 | CO49: 0 | CP49: =CO49/$P49 -> 0 | CQ49: 0 | CR49: =CQ49/$P49 -> 0 | CS49: 0 | CT49: =CS49/$P49 -> 0 | CU49: =CI49+CK49+CM49+CO49+CQ49+CS49 -> 0 | CV49: =CU49/$P49 -> 0
C50: 38 | D50: Muro sin ventanas (Negro) | E50: =E5 -> 35.6 | F50: 0.7 | G50: =E50*F50 -> 24.92 | N50: =G50-K50 -> 24.92 | P50: =SUM(L50:O50) -> 24.92 | Q50: 0 | R50: =Q50/$P50 -> 0 | S50: 0 | T50: =S50/$P50 -> 0 | U50: 0 | V50: =U50/$P50 -> 0 | W50: 0 | X50: =W50/$P50 -> 0 | Y50: 0 | Z50: =Y50/$P50 -> 0 | AA50: 0 | AB50: =AA50/$P50 -> 0 | AC50: =Q50+S50+U50+W50+Y50+AA50 -> 0 | AD50: =AC50/$P50 -> 0 | AE50: 0 | AF50: =AE50/$P50 -> 0 | AG50: 0 | AH50: =AG50/$P50 -> 0 | AI50: 0 | AJ50: =AI50/$P50 -> 0 | AK50: 0 | AL50: =AK50/$P50 -> 0 | AM50: 0 | AN50: =AM50/$P50 -> 0 | AO50: 0 | AP50: =AO50/$P50 -> 0 | AQ50: =AE50+AG50+AI50+AK50+AM50+AO50 -> 0 | AR50: =AQ50/$P50 -> 0 | AS50: 0 | AT50: =AS50/$P50 -> 0 | AU50: 0 | AV50: =AU50/$P50 -> 0 | AW50: 0 | AX50: =AW50/$P50 -> 0 | AY50: 0 | AZ50: =AY50/$P50 -> 0 | BA50: 0 | BB50: =BA50/$P50 -> 0 | BC50: 0 | BD50: =BC50/$P50 -> 0 | BE50: =AS50+AU50+AW50+AY50+BA50+BC50 -> 0 | BF50: =BE50/$P50 -> 0 | BG50: 0 | BH50: =BG50/$P50 -> 0 | BI50: 0 | BJ50: =BI50/$P50 -> 0 | BK50: 0 | BL50: =BK50/$P50 -> 0 | BM50: 0 | BN50: =BM50/$P50 -> 0 | BO50: 0 | BP50: =BO50/$P50 -> 0 | BQ50: 0 | BR50: =BQ50/$P50 -> 0 | BS50: =BG50+BI50+BK50+BM50+BO50+BQ50 -> 0 | BT50: =BS50/$P50 -> 0 | BU50: 0 | BV50: =BU50/$P50 -> 0 | BW50: 0 | BX50: =BW50/$P50 -> 0 | BY50: 0 | BZ50: =BY50/$P50 -> 0 | CA50: 0 | CB50: =CA50/$P50 -> 0 | CC50: 0 | CD50: =CC50/$P50 -> 0 | CE50: 0 | CF50: =CE50/$P50 -> 0 | CG50: =BU50+BW50+BY50+CA50+CC50+CE50 -> 0 | CH50: =CG50/$P50 -> 0 | CI50: 0 | CJ50: =CI50/$P50 -> 0 | CK50: 0 | CL50: =CK50/$P50 -> 0 | CM50: 0 | CN50: =CM50/$P50 -> 0 | CO50: 0 | CP50: =CO50/$P50 -> 0 | CQ50: 0 | CR50: =CQ50/$P50 -> 0 | CS50: 0 | CT50: =CS50/$P50 -> 0 | CU50: =CI50+CK50+CM50+CO50+CQ50+CS50 -> 0 | CV50: =CU50/$P50 -> 0
C51: 39 | D51: Muro sin ventanas (Negro) | E51: =E5 -> 35.6 | F51: 1.45 | G51: =E51*F51 -> 51.62 | N51: =G51-K51 -> 51.62 | P51: =SUM(L51:O51) -> 51.62 | Q51: 0 | R51: =Q51/$P51 -> 0 | S51: 0 | T51: =S51/$P51 -> 0 | U51: 0 | V51: =U51/$P51 -> 0 | W51: 0 | X51: =W51/$P51 -> 0 | Y51: 0 | Z51: =Y51/$P51 -> 0 | AA51: 0 | AB51: =AA51/$P51 -> 0 | AC51: =Q51+S51+U51+W51+Y51+AA51 -> 0 | AD51: =AC51/$P51 -> 0 | AE51: 0 | AF51: =AE51/$P51 -> 0 | AG51: 0 | AH51: =AG51/$P51 -> 0 | AI51: 0 | AJ51: =AI51/$P51 -> 0 | AK51: 0 | AL51: =AK51/$P51 -> 0 | AM51: 0 | AN51: =AM51/$P51 -> 0 | AO51: 0 | AP51: =AO51/$P51 -> 0 | AQ51: =AE51+AG51+AI51+AK51+AM51+AO51 -> 0 | AR51: =AQ51/$P51 -> 0 | AS51: 0 | AT51: =AS51/$P51 -> 0 | AU51: 0 | AV51: =AU51/$P51 -> 0 | AW51: 0 | AX51: =AW51/$P51 -> 0 | AY51: 0 | AZ51: =AY51/$P51 -> 0 | BA51: 0 | BB51: =BA51/$P51 -> 0 | BC51: 0 | BD51: =BC51/$P51 -> 0 | BE51: =AS51+AU51+AW51+AY51+BA51+BC51 -> 0 | BF51: =BE51/$P51 -> 0 | BG51: 0 | BH51: =BG51/$P51 -> 0 | BI51: 0 | BJ51: =BI51/$P51 -> 0 | BK51: 0 | BL51: =BK51/$P51 -> 0 | BM51: 0 | BN51: =BM51/$P51 -> 0 | BO51: 0 | BP51: =BO51/$P51 -> 0 | BQ51: 0 | BR51: =BQ51/$P51 -> 0 | BS51: =BG51+BI51+BK51+BM51+BO51+BQ51 -> 0 | BT51: =BS51/$P51 -> 0 | BU51: 0 | BV51: =BU51/$P51 -> 0 | BW51: 0 | BX51: =BW51/$P51 -> 0 | BY51: 0 | BZ51: =BY51/$P51 -> 0 | CA51: 0 | CB51: =CA51/$P51 -> 0 | CC51: 0 | CD51: =CC51/$P51 -> 0 | CE51: 0 | CF51: =CE51/$P51 -> 0 | CG51: =BU51+BW51+BY51+CA51+CC51+CE51 -> 0 | CH51: =CG51/$P51 -> 0 | CI51: 0 | CJ51: =CI51/$P51 -> 0 | CK51: 0 | CL51: =CK51/$P51 -> 0 | CM51: 0 | CN51: =CM51/$P51 -> 0 | CO51: 0 | CP51: =CO51/$P51 -> 0 | CQ51: 0 | CR51: =CQ51/$P51 -> 0 | CS51: 0 | CT51: =CS51/$P51 -> 0 | CU51: =CI51+CK51+CM51+CO51+CQ51+CS51 -> 0 | CV51: =CU51/$P51 -> 0
C52: 40 | D52: Muro con balcón (Verde) | E52: =E5 -> 35.6 | F52: 4.02 | G52: =E52*F52 -> 143.112 | H52: 1.5 | I52: 1.2 | J52: 14 | K52: =(H52*I52)*J52 -> 25.2 | M52: =G52-(K52+K53) -> 117.912 | P52: =SUM(L52:O52) -> 117.912 | Q52: 0 | R52: =Q52/$P52 -> 0 | S52: 0 | T52: =S52/$P52 -> 0 | U52: 0 | V52: =U52/$P52 -> 0 | W52: 0 | X52: =W52/$P52 -> 0 | Y52: 0 | Z52: =Y52/$P52 -> 0 | AA52: 0 | AB52: =AA52/$P52 -> 0 | AC52: =Q52+S52+U52+W52+Y52+AA52 -> 0 | AD52: =AC52/$P52 -> 0 | AE52: 0 | AF52: =AE52/$P52 -> 0 | AG52: 0 | AH52: =AG52/$P52 -> 0 | AI52: 0 | AJ52: =AI52/$P52 -> 0 | AK52: 0 | AL52: =AK52/$P52 -> 0 | AM52: 0 | AN52: =AM52/$P52 -> 0 | AO52: 0 | AP52: =AO52/$P52 -> 0 | AQ52: =AE52+AG52+AI52+AK52+AM52+AO52 -> 0 | AR52: =AQ52/$P52 -> 0 | AS52: 0 | AT52: =AS52/$P52 -> 0 | AU52: 0 | AV52: =AU52/$P52 -> 0 | AW52: 0 | AX52: =AW52/$P52 -> 0 | AY52: 0 | AZ52: =AY52/$P52 -> 0 | BA52: 0 | BB52: =BA52/$P52 -> 0 | BC52: 0 | BD52: =BC52/$P52 -> 0 | BE52: =AS52+AU52+AW52+AY52+BA52+BC52 -> 0 | BF52: =BE52/$P52 -> 0 | BG52: 0 | BH52: =BG52/$P52 -> 0 | BI52: 0 | BJ52: =BI52/$P52 -> 0 | BK52: 0 | BL52: =BK52/$P52 -> 0 | BM52: 0 | BN52: =BM52/$P52 -> 0 | BO52: 0 | BP52: =BO52/$P52 -> 0 | BQ52: 0 | BR52: =BQ52/$P52 -> 0 | BS52: =BG52+BI52+BK52+BM52+BO52+BQ52 -> 0 | BT52: =BS52/$P52 -> 0 | BU52: 0 | BV52: =BU52/$P52 -> 0 | BW52: 0 | BX52: =BW52/$P52 -> 0 | BY52: 0 | BZ52: =BY52/$P52 -> 0 | CA52: 0 | CB52: =CA52/$P52 -> 0 | CC52: 0 | CD52: =CC52/$P52 -> 0 | CE52: 0 | CF52: =CE52/$P52 -> 0 | CG52: =BU52+BW52+BY52+CA52+CC52+CE52 -> 0 | CH52: =CG52/$P52 -> 0 | CI52: 0 | CJ52: =CI52/$P52 -> 0 | CK52: 0 | CL52: =CK52/$P52 -> 0 | CM52: 0 | CN52: =CM52/$P52 -> 0 | CO52: 0 | CP52: =CO52/$P52 -> 0 | CQ52: 0 | CR52: =CQ52/$P52 -> 0 | CS52: 0 | CT52: =CS52/$P52 -> 0 | CU52: =CI52+CK52+CM52+CO52+CQ52+CS52 -> 0 | CV52: =CU52/$P52 -> 0
C53: 41 | D53: Placa de balcón (Negro) (x14) | E53: 0.3 | F53: 5.1 | G53: =E53*F53*14 -> 21.42 | N53: =G53 -> 21.42 | P53: =SUM(L53:O53) -> 21.42 | Q53: 0 | R53: =Q53/$P53 -> 0 | S53: 0 | T53: =S53/$P53 -> 0 | U53: 0 | V53: =U53/$P53 -> 0 | W53: 0 | X53: =W53/$P53 -> 0 | Y53: 0 | Z53: =Y53/$P53 -> 0 | AA53: 0 | AB53: =AA53/$P53 -> 0 | AC53: =Q53+S53+U53+W53+Y53+AA53 -> 0 | AD53: =AC53/$P53 -> 0 | AE53: 0 | AF53: =AE53/$P53 -> 0 | AG53: 0 | AH53: =AG53/$P53 -> 0 | AI53: 0 | AJ53: =AI53/$P53 -> 0 | AK53: 0 | AL53: =AK53/$P53 -> 0 | AM53: 0 | AN53: =AM53/$P53 -> 0 | AO53: 0 | AP53: =AO53/$P53 -> 0 | AQ53: =AE53+AG53+AI53+AK53+AM53+AO53 -> 0 | AR53: =AQ53/$P53 -> 0 | AS53: 0 | AT53: =AS53/$P53 -> 0 | AU53: 0 | AV53: =AU53/$P53 -> 0 | AW53: 0 | AX53: =AW53/$P53 -> 0 | AY53: 0 | AZ53: =AY53/$P53 -> 0 | BA53: 0 | BB53: =BA53/$P53 -> 0 | BC53: 0 | BD53: =BC53/$P53 -> 0 | BE53: =AS53+AU53+AW53+AY53+BA53+BC53 -> 0 | BF53: =BE53/$P53 -> 0 | BG53: 0 | BH53: =BG53/$P53 -> 0 | BI53: 0 | BJ53: =BI53/$P53 -> 0 | BK53: 0 | BL53: =BK53/$P53 -> 0 | BM53: 0 | BN53: =BM53/$P53 -> 0 | BO53: 0 | BP53: =BO53/$P53 -> 0 | BQ53: 0 | BR53: =BQ53/$P53 -> 0 | BS53: =BG53+BI53+BK53+BM53+BO53+BQ53 -> 0 | BT53: =BS53/$P53 -> 0 | BU53: 0 | BV53: =BU53/$P53 -> 0 | BW53: 0 | BX53: =BW53/$P53 -> 0 | BY53: 0 | BZ53: =BY53/$P53 -> 0 | CA53: 0 | CB53: =CA53/$P53 -> 0 | CC53: 0 | CD53: =CC53/$P53 -> 0 | CE53: 0 | CF53: =CE53/$P53 -> 0 | CG53: =BU53+BW53+BY53+CA53+CC53+CE53 -> 0 | CH53: =CG53/$P53 -> 0 | CI53: 0 | CJ53: =CI53/$P53 -> 0 | CK53: 0 | CL53: =CK53/$P53 -> 0 | CM53: 0 | CN53: =CM53/$P53 -> 0 | CO53: 0 | CP53: =CO53/$P53 -> 0 | CQ53: 0 | CR53: =CQ53/$P53 -> 0 | CS53: 0 | CT53: =CS53/$P53 -> 0 | CU53: =CI53+CK53+CM53+CO53+CQ53+CS53 -> 0 | CV53: =CU53/$P53 -> 0
C54: 41.1 | D54: Cielo raso balcón (X14) | E54: 0.6 | F54: 5.1 | G54: =E54*F54*14 -> 42.84 | O54: =G54 -> 42.84 | P54: =SUM(L54:O54) -> 42.84 | Q54: 0 | R54: =Q54/$P54 -> 0 | S54: 0 | T54: =S54/$P54 -> 0 | U54: 0 | V54: =U54/$P54 -> 0 | W54: 0 | X54: =W54/$P54 -> 0 | Y54: 0 | Z54: =Y54/$P54 -> 0 | AA54: 0 | AB54: =AA54/$P54 -> 0 | AC54: =Q54+S54+U54+W54+Y54+AA54 -> 0 | AD54: =AC54/$P54 -> 0 | AE54: 0 | AF54: =AE54/$P54 -> 0 | AG54: 0 | AH54: =AG54/$P54 -> 0 | AI54: 0 | AJ54: =AI54/$P54 -> 0 | AK54: 0 | AL54: =AK54/$P54 -> 0 | AM54: 0 | AN54: =AM54/$P54 -> 0 | AO54: 0 | AP54: =AO54/$P54 -> 0 | AQ54: =AE54+AG54+AI54+AK54+AM54+AO54 -> 0 | AR54: =AQ54/$P54 -> 0 | AS54: 0 | AT54: =AS54/$P54 -> 0 | AU54: 0 | AV54: =AU54/$P54 -> 0 | AW54: 0 | AX54: =AW54/$P54 -> 0 | AY54: 0 | AZ54: =AY54/$P54 -> 0 | BA54: 0 | BB54: =BA54/$P54 -> 0 | BC54: 0 | BD54: =BC54/$P54 -> 0 | BE54: =AS54+AU54+AW54+AY54+BA54+BC54 -> 0 | BF54: =BE54/$P54 -> 0 | BG54: 0 | BH54: =BG54/$P54 -> 0 | BI54: 0 | BJ54: =BI54/$P54 -> 0 | BK54: 0 | BL54: =BK54/$P54 -> 0 | BM54: 0 | BN54: =BM54/$P54 -> 0 | BO54: 0 | BP54: =BO54/$P54 -> 0 | BQ54: 0 | BR54: =BQ54/$P54 -> 0 | BS54: =BG54+BI54+BK54+BM54+BO54+BQ54 -> 0 | BT54: =BS54/$P54 -> 0 | BU54: 0 | BV54: =BU54/$P54 -> 0 | BW54: 0 | BX54: =BW54/$P54 -> 0 | BY54: 0 | BZ54: =BY54/$P54 -> 0 | CA54: 0 | CB54: =CA54/$P54 -> 0 | CC54: 0 | CD54: =CC54/$P54 -> 0 | CE54: 0 | CF54: =CE54/$P54 -> 0 | CG54: =BU54+BW54+BY54+CA54+CC54+CE54 -> 0 | CH54: =CG54/$P54 -> 0 | CI54: 0 | CJ54: =CI54/$P54 -> 0 | CK54: 0 | CL54: =CK54/$P54 -> 0 | CM54: 0 | CN54: =CM54/$P54 -> 0 | CO54: 0 | CP54: =CO54/$P54 -> 0 | CQ54: 0 | CR54: =CQ54/$P54 -> 0 | CS54: 0 | CT54: =CS54/$P54 -> 0 | CU54: =CI54+CK54+CM54+CO54+CQ54+CS54 -> 0 | CV54: =CU54/$P54 -> 0
C55: 42 | D55: Muro con ventanas (Verde) | E55: =E5 -> 35.6 | F55: 5.12 | G55: =E55*F55 -> 182.272 | H55: 1.5 | I55: 1.2 | J55: 28 | K55: =(H55*I55)*J55 -> 50.4 | M55: =G55-(K55+K56) -> 131.872 | P55: =SUM(L55:O55) -> 131.872 | Q55: 0 | R55: =Q55/$P55 -> 0 | S55: 0 | T55: =S55/$P55 -> 0 | U55: 0 | V55: =U55/$P55 -> 0 | W55: 0 | X55: =W55/$P55 -> 0 | Y55: 0 | Z55: =Y55/$P55 -> 0 | AA55: 0 | AB55: =AA55/$P55 -> 0 | AC55: =Q55+S55+U55+W55+Y55+AA55 -> 0 | AD55: =AC55/$P55 -> 0 | AE55: 0 | AF55: =AE55/$P55 -> 0 | AG55: 0 | AH55: =AG55/$P55 -> 0 | AI55: 0 | AJ55: =AI55/$P55 -> 0 | AK55: 0 | AL55: =AK55/$P55 -> 0 | AM55: 0 | AN55: =AM55/$P55 -> 0 | AO55: 0 | AP55: =AO55/$P55 -> 0 | AQ55: =AE55+AG55+AI55+AK55+AM55+AO55 -> 0 | AR55: =AQ55/$P55 -> 0 | AS55: 0 | AT55: =AS55/$P55 -> 0 | AU55: 0 | AV55: =AU55/$P55 -> 0 | AW55: 0 | AX55: =AW55/$P55 -> 0 | AY55: 0 | AZ55: =AY55/$P55 -> 0 | BA55: 0 | BB55: =BA55/$P55 -> 0 | BC55: 0 | BD55: =BC55/$P55 -> 0 | BE55: =AS55+AU55+AW55+AY55+BA55+BC55 -> 0 | BF55: =BE55/$P55 -> 0 | BG55: 0 | BH55: =BG55/$P55 -> 0 | BI55: 0 | BJ55: =BI55/$P55 -> 0 | BK55: 0 | BL55: =BK55/$P55 -> 0 | BM55: 0 | BN55: =BM55/$P55 -> 0 | BO55: 0 | BP55: =BO55/$P55 -> 0 | BQ55: 0 | BR55: =BQ55/$P55 -> 0 | BS55: =BG55+BI55+BK55+BM55+BO55+BQ55 -> 0 | BT55: =BS55/$P55 -> 0 | BU55: 0 | BV55: =BU55/$P55 -> 0 | BW55: 0 | BX55: =BW55/$P55 -> 0 | BY55: 0 | BZ55: =BY55/$P55 -> 0 | CA55: 0 | CB55: =CA55/$P55 -> 0 | CC55: 0 | CD55: =CC55/$P55 -> 0 | CE55: 0 | CF55: =CE55/$P55 -> 0 | CG55: =BU55+BW55+BY55+CA55+CC55+CE55 -> 0 | CH55: =CG55/$P55 -> 0 | CI55: 0 | CJ55: =CI55/$P55 -> 0 | CK55: 0 | CL55: =CK55/$P55 -> 0 | CM55: 0 | CN55: =CM55/$P55 -> 0 | CO55: 0 | CP55: =CO55/$P55 -> 0 | CQ55: 0 | CR55: =CQ55/$P55 -> 0 | CS55: 0 | CT55: =CS55/$P55 -> 0 | CU55: =CI55+CK55+CM55+CO55+CQ55+CS55 -> 0 | CV55: =CU55/$P55 -> 0
C56: 43 | D56: Muro sin ventanas (Verde) | E56: =E5 -> 35.6 | F56: 0.7 | G56: =E56*F56 -> 24.92 | M56: =G56-K56 -> 24.92 | P56: =SUM(L56:O56) -> 24.92 | Q56: 0 | R56: =Q56/$P56 -> 0 | S56: 0 | T56: =S56/$P56 -> 0 | U56: 0 | V56: =U56/$P56 -> 0 | W56: 0 | X56: =W56/$P56 -> 0 | Y56: 0 | Z56: =Y56/$P56 -> 0 | AA56: 0 | AB56: =AA56/$P56 -> 0 | AC56: =Q56+S56+U56+W56+Y56+AA56 -> 0 | AD56: =AC56/$P56 -> 0 | AE56: 0 | AF56: =AE56/$P56 -> 0 | AG56: 0 | AH56: =AG56/$P56 -> 0 | AI56: 0 | AJ56: =AI56/$P56 -> 0 | AK56: 0 | AL56: =AK56/$P56 -> 0 | AM56: 0 | AN56: =AM56/$P56 -> 0 | AO56: 0 | AP56: =AO56/$P56 -> 0 | AQ56: =AE56+AG56+AI56+AK56+AM56+AO56 -> 0 | AR56: =AQ56/$P56 -> 0 | AS56: 0 | AT56: =AS56/$P56 -> 0 | AU56: 0 | AV56: =AU56/$P56 -> 0 | AW56: 0 | AX56: =AW56/$P56 -> 0 | AY56: 0 | AZ56: =AY56/$P56 -> 0 | BA56: 0 | BB56: =BA56/$P56 -> 0 | BC56: 0 | BD56: =BC56/$P56 -> 0 | BE56: =AS56+AU56+AW56+AY56+BA56+BC56 -> 0 | BF56: =BE56/$P56 -> 0 | BG56: 0 | BH56: =BG56/$P56 -> 0 | BI56: 0 | BJ56: =BI56/$P56 -> 0 | BK56: 0 | BL56: =BK56/$P56 -> 0 | BM56: 0 | BN56: =BM56/$P56 -> 0 | BO56: 0 | BP56: =BO56/$P56 -> 0 | BQ56: 0 | BR56: =BQ56/$P56 -> 0 | BS56: =BG56+BI56+BK56+BM56+BO56+BQ56 -> 0 | BT56: =BS56/$P56 -> 0 | BU56: 0 | BV56: =BU56/$P56 -> 0 | BW56: 0 | BX56: =BW56/$P56 -> 0 | BY56: 0 | BZ56: =BY56/$P56 -> 0 | CA56: 0 | CB56: =CA56/$P56 -> 0 | CC56: 0 | CD56: =CC56/$P56 -> 0 | CE56: 0 | CF56: =CE56/$P56 -> 0 | CG56: =BU56+BW56+BY56+CA56+CC56+CE56 -> 0 | CH56: =CG56/$P56 -> 0 | CI56: 0 | CJ56: =CI56/$P56 -> 0 | CK56: 0 | CL56: =CK56/$P56 -> 0 | CM56: 0 | CN56: =CM56/$P56 -> 0 | CO56: 0 | CP56: =CO56/$P56 -> 0 | CQ56: 0 | CR56: =CQ56/$P56 -> 0 | CS56: 0 | CT56: =CS56/$P56 -> 0 | CU56: =CI56+CK56+CM56+CO56+CQ56+CS56 -> 0 | CV56: =CU56/$P56 -> 0
C57: 44 | D57: Muro sin ventanas (Negro) | E57: =E5 -> 35.6 | F57: 1.45 | G57: =E57*F57 -> 51.62 | N57: =G57-K57 -> 51.62 | P57: =SUM(L57:O57) -> 51.62 | Q57: 0 | R57: =Q57/$P57 -> 0 | S57: 0 | T57: =S57/$P57 -> 0 | U57: 0 | V57: =U57/$P57 -> 0 | W57: 0 | X57: =W57/$P57 -> 0 | Y57: 0 | Z57: =Y57/$P57 -> 0 | AA57: 0 | AB57: =AA57/$P57 -> 0 | AC57: =Q57+S57+U57+W57+Y57+AA57 -> 0 | AD57: =AC57/$P57 -> 0 | AE57: 0 | AF57: =AE57/$P57 -> 0 | AG57: 0 | AH57: =AG57/$P57 -> 0 | AI57: 0 | AJ57: =AI57/$P57 -> 0 | AK57: 0 | AL57: =AK57/$P57 -> 0 | AM57: 0 | AN57: =AM57/$P57 -> 0 | AO57: 0 | AP57: =AO57/$P57 -> 0 | AQ57: =AE57+AG57+AI57+AK57+AM57+AO57 -> 0 | AR57: =AQ57/$P57 -> 0 | AS57: 0 | AT57: =AS57/$P57 -> 0 | AU57: 0 | AV57: =AU57/$P57 -> 0 | AW57: 0 | AX57: =AW57/$P57 -> 0 | AY57: 0 | AZ57: =AY57/$P57 -> 0 | BA57: 0 | BB57: =BA57/$P57 -> 0 | BC57: 0 | BD57: =BC57/$P57 -> 0 | BE57: =AS57+AU57+AW57+AY57+BA57+BC57 -> 0 | BF57: =BE57/$P57 -> 0 | BG57: 0 | BH57: =BG57/$P57 -> 0 | BI57: 0 | BJ57: =BI57/$P57 -> 0 | BK57: 0 | BL57: =BK57/$P57 -> 0 | BM57: 0 | BN57: =BM57/$P57 -> 0 | BO57: 0 | BP57: =BO57/$P57 -> 0 | BQ57: 0 | BR57: =BQ57/$P57 -> 0 | BS57: =BG57+BI57+BK57+BM57+BO57+BQ57 -> 0 | BT57: =BS57/$P57 -> 0 | BU57: 0 | BV57: =BU57/$P57 -> 0 | BW57: 0 | BX57: =BW57/$P57 -> 0 | BY57: 0 | BZ57: =BY57/$P57 -> 0 | CA57: 0 | CB57: =CA57/$P57 -> 0 | CC57: 0 | CD57: =CC57/$P57 -> 0 | CE57: 0 | CF57: =CE57/$P57 -> 0 | CG57: =BU57+BW57+BY57+CA57+CC57+CE57 -> 0 | CH57: =CG57/$P57 -> 0 | CI57: 0 | CJ57: =CI57/$P57 -> 0 | CK57: 0 | CL57: =CK57/$P57 -> 0 | CM57: 0 | CN57: =CM57/$P57 -> 0 | CO57: 0 | CP57: =CO57/$P57 -> 0 | CQ57: 0 | CR57: =CQ57/$P57 -> 0 | CS57: 0 | CT57: =CS57/$P57 -> 0 | CU57: =CI57+CK57+CM57+CO57+CQ57+CS57 -> 0 | CV57: =CU57/$P57 -> 0
C58: 45 | D58: Muro con ventanas (Negro) | E58: =E5 -> 35.6 | F58: 1.2 | G58: =E58*F58 -> 42.72 | H58: 1 | I58: 0.75 | J58: 14 | K58: =(H58*I58)*J58 -> 10.5 | N58: =G58-(K58+K62) -> 32.22 | P58: =SUM(L58:O58) -> 32.22 | Q58: 0 | R58: =Q58/$P58 -> 0 | S58: 0 | T58: =S58/$P58 -> 0 | U58: 0 | V58: =U58/$P58 -> 0 | W58: 0 | X58: =W58/$P58 -> 0 | Y58: 0 | Z58: =Y58/$P58 -> 0 | AA58: 0 | AB58: =AA58/$P58 -> 0 | AC58: =Q58+S58+U58+W58+Y58+AA58 -> 0 | AD58: =AC58/$P58 -> 0 | AE58: 0 | AF58: =AE58/$P58 -> 0 | AG58: 0 | AH58: =AG58/$P58 -> 0 | AI58: 0 | AJ58: =AI58/$P58 -> 0 | AK58: 0 | AL58: =AK58/$P58 -> 0 | AM58: 0 | AN58: =AM58/$P58 -> 0 | AO58: 0 | AP58: =AO58/$P58 -> 0 | AQ58: =AE58+AG58+AI58+AK58+AM58+AO58 -> 0 | AR58: =AQ58/$P58 -> 0 | AS58: 0 | AT58: =AS58/$P58 -> 0 | AU58: 0 | AV58: =AU58/$P58 -> 0 | AW58: 0 | AX58: =AW58/$P58 -> 0 | AY58: 0 | AZ58: =AY58/$P58 -> 0 | BA58: 0 | BB58: =BA58/$P58 -> 0 | BC58: 0 | BD58: =BC58/$P58 -> 0 | BE58: =AS58+AU58+AW58+AY58+BA58+BC58 -> 0 | BF58: =BE58/$P58 -> 0 | BG58: 0 | BH58: =BG58/$P58 -> 0 | BI58: 0 | BJ58: =BI58/$P58 -> 0 | BK58: 0 | BL58: =BK58/$P58 -> 0 | BM58: 0 | BN58: =BM58/$P58 -> 0 | BO58: 0 | BP58: =BO58/$P58 -> 0 | BQ58: 0 | BR58: =BQ58/$P58 -> 0 | BS58: =BG58+BI58+BK58+BM58+BO58+BQ58 -> 0 | BT58: =BS58/$P58 -> 0 | BU58: 0 | BV58: =BU58/$P58 -> 0 | BW58: 0 | BX58: =BW58/$P58 -> 0 | BY58: 0 | BZ58: =BY58/$P58 -> 0 | CA58: 0 | CB58: =CA58/$P58 -> 0 | CC58: 0 | CD58: =CC58/$P58 -> 0 | CE58: 0 | CF58: =CE58/$P58 -> 0 | CG58: =BU58+BW58+BY58+CA58+CC58+CE58 -> 0 | CH58: =CG58/$P58 -> 0 | CI58: 0 | CJ58: =CI58/$P58 -> 0 | CK58: 0 | CL58: =CK58/$P58 -> 0 | CM58: 0 | CN58: =CM58/$P58 -> 0 | CO58: 0 | CP58: =CO58/$P58 -> 0 | CQ58: 0 | CR58: =CQ58/$P58 -> 0 | CS58: 0 | CT58: =CS58/$P58 -> 0 | CU58: =CI58+CK58+CM58+CO58+CQ58+CS58 -> 0 | CV58: =CU58/$P58 -> 0
C59: 46 | D59: Placa de balcón (Negro) (x14) | E59: 0.3 | F59: 2.52 | G59: =E59*F59*14 -> 10.584 | N59: =G59 -> 10.584 | P59: =SUM(L59:O59) -> 10.584 | Q59: 0 | R59: =Q59/$P59 -> 0 | S59: 0 | T59: =S59/$P59 -> 0 | U59: 0 | V59: =U59/$P59 -> 0 | W59: 0 | X59: =W59/$P59 -> 0 | Y59: 0 | Z59: =Y59/$P59 -> 0 | AA59: 0 | AB59: =AA59/$P59 -> 0 | AC59: =Q59+S59+U59+W59+Y59+AA59 -> 0 | AD59: =AC59/$P59 -> 0 | AE59: 0 | AF59: =AE59/$P59 -> 0 | AG59: 0 | AH59: =AG59/$P59 -> 0 | AI59: 0 | AJ59: =AI59/$P59 -> 0 | AK59: 0 | AL59: =AK59/$P59 -> 0 | AM59: 0 | AN59: =AM59/$P59 -> 0 | AO59: 0 | AP59: =AO59/$P59 -> 0 | AQ59: =AE59+AG59+AI59+AK59+AM59+AO59 -> 0 | AR59: =AQ59/$P59 -> 0 | AS59: 0 | AT59: =AS59/$P59 -> 0 | AU59: 0 | AV59: =AU59/$P59 -> 0 | AW59: 0 | AX59: =AW59/$P59 -> 0 | AY59: 0 | AZ59: =AY59/$P59 -> 0 | BA59: 0 | BB59: =BA59/$P59 -> 0 | BC59: 0 | BD59: =BC59/$P59 -> 0 | BE59: =AS59+AU59+AW59+AY59+BA59+BC59 -> 0 | BF59: =BE59/$P59 -> 0 | BG59: 0 | BH59: =BG59/$P59 -> 0 | BI59: 0 | BJ59: =BI59/$P59 -> 0 | BK59: 0 | BL59: =BK59/$P59 -> 0 | BM59: 0 | BN59: =BM59/$P59 -> 0 | BO59: 0 | BP59: =BO59/$P59 -> 0 | BQ59: 0 | BR59: =BQ59/$P59 -> 0 | BS59: =BG59+BI59+BK59+BM59+BO59+BQ59 -> 0 | BT59: =BS59/$P59 -> 0 | BU59: 0 | BV59: =BU59/$P59 -> 0 | BW59: 0 | BX59: =BW59/$P59 -> 0 | BY59: 0 | BZ59: =BY59/$P59 -> 0 | CA59: 0 | CB59: =CA59/$P59 -> 0 | CC59: 0 | CD59: =CC59/$P59 -> 0 | CE59: 0 | CF59: =CE59/$P59 -> 0 | CG59: =BU59+BW59+BY59+CA59+CC59+CE59 -> 0 | CH59: =CG59/$P59 -> 0 | CI59: 0 | CJ59: =CI59/$P59 -> 0 | CK59: 0 | CL59: =CK59/$P59 -> 0 | CM59: 0 | CN59: =CM59/$P59 -> 0 | CO59: 0 | CP59: =CO59/$P59 -> 0 | CQ59: 0 | CR59: =CQ59/$P59 -> 0 | CS59: 0 | CT59: =CS59/$P59 -> 0 | CU59: =CI59+CK59+CM59+CO59+CQ59+CS59 -> 0 | CV59: =CU59/$P59 -> 0
C60: 46.1 | D60: Cielo raso balcón (X14) | E60: 0.6 | F60: 2.52 | G60: =E60*F60*14 -> 21.168 | O60: =G60 -> 21.168 | P60: =SUM(L60:O60) -> 21.168 | Q60: 0 | R60: =Q60/$P60 -> 0 | S60: 0 | T60: =S60/$P60 -> 0 | U60: 0 | V60: =U60/$P60 -> 0 | W60: 0 | X60: =W60/$P60 -> 0 | Y60: 0 | Z60: =Y60/$P60 -> 0 | AA60: 0 | AB60: =AA60/$P60 -> 0 | AC60: =Q60+S60+U60+W60+Y60+AA60 -> 0 | AD60: =AC60/$P60 -> 0 | AE60: 0 | AF60: =AE60/$P60 -> 0 | AG60: 0 | AH60: =AG60/$P60 -> 0 | AI60: 0 | AJ60: =AI60/$P60 -> 0 | AK60: 0 | AL60: =AK60/$P60 -> 0 | AM60: 0 | AN60: =AM60/$P60 -> 0 | AO60: 0 | AP60: =AO60/$P60 -> 0 | AQ60: =AE60+AG60+AI60+AK60+AM60+AO60 -> 0 | AR60: =AQ60/$P60 -> 0 | AS60: 0 | AT60: =AS60/$P60 -> 0 | AU60: 0 | AV60: =AU60/$P60 -> 0 | AW60: 0 | AX60: =AW60/$P60 -> 0 | AY60: 0 | AZ60: =AY60/$P60 -> 0 | BA60: 0 | BB60: =BA60/$P60 -> 0 | BC60: 0 | BD60: =BC60/$P60 -> 0 | BE60: =AS60+AU60+AW60+AY60+BA60+BC60 -> 0 | BF60: =BE60/$P60 -> 0 | BG60: 0 | BH60: =BG60/$P60 -> 0 | BI60: 0 | BJ60: =BI60/$P60 -> 0 | BK60: 0 | BL60: =BK60/$P60 -> 0 | BM60: 0 | BN60: =BM60/$P60 -> 0 | BO60: 0 | BP60: =BO60/$P60 -> 0 | BQ60: 0 | BR60: =BQ60/$P60 -> 0 | BS60: =BG60+BI60+BK60+BM60+BO60+BQ60 -> 0 | BT60: =BS60/$P60 -> 0 | BU60: 0 | BV60: =BU60/$P60 -> 0 | BW60: 0 | BX60: =BW60/$P60 -> 0 | BY60: 0 | BZ60: =BY60/$P60 -> 0 | CA60: 0 | CB60: =CA60/$P60 -> 0 | CC60: 0 | CD60: =CC60/$P60 -> 0 | CE60: 0 | CF60: =CE60/$P60 -> 0 | CG60: =BU60+BW60+BY60+CA60+CC60+CE60 -> 0 | CH60: =CG60/$P60 -> 0 | CI60: 0 | CJ60: =CI60/$P60 -> 0 | CK60: 0 | CL60: =CK60/$P60 -> 0 | CM60: 0 | CN60: =CM60/$P60 -> 0 | CO60: 0 | CP60: =CO60/$P60 -> 0 | CQ60: 0 | CR60: =CQ60/$P60 -> 0 | CS60: 0 | CT60: =CS60/$P60 -> 0 | CU60: =CI60+CK60+CM60+CO60+CQ60+CS60 -> 0 | CV60: =CU60/$P60 -> 0
C61: 47 | D61: Muro con ventanas (Negro) | E61: =E5 -> 35.6 | F61: 2.54 | G61: =E61*F61 -> 90.424 | H61: 1.5 | I61: 1.2 | J61: 14 | K61: =(H61*I61)*J61 -> 25.2 | M61: =G61-(K61+K62) -> 65.224 | P61: =SUM(L61:O61) -> 65.224 | Q61: 0 | R61: =Q61/$P61 -> 0 | S61: 0 | T61: =S61/$P61 -> 0 | U61: 0 | V61: =U61/$P61 -> 0 | W61: 0 | X61: =W61/$P61 -> 0 | Y61: 0 | Z61: =Y61/$P61 -> 0 | AA61: 0 | AB61: =AA61/$P61 -> 0 | AC61: =Q61+S61+U61+W61+Y61+AA61 -> 0 | AD61: =AC61/$P61 -> 0 | AE61: 0 | AF61: =AE61/$P61 -> 0 | AG61: 0 | AH61: =AG61/$P61 -> 0 | AI61: 0 | AJ61: =AI61/$P61 -> 0 | AK61: 0 | AL61: =AK61/$P61 -> 0 | AM61: 0 | AN61: =AM61/$P61 -> 0 | AO61: 0 | AP61: =AO61/$P61 -> 0 | AQ61: =AE61+AG61+AI61+AK61+AM61+AO61 -> 0 | AR61: =AQ61/$P61 -> 0 | AS61: 0 | AT61: =AS61/$P61 -> 0 | AU61: 0 | AV61: =AU61/$P61 -> 0 | AW61: 0 | AX61: =AW61/$P61 -> 0 | AY61: 0 | AZ61: =AY61/$P61 -> 0 | BA61: 0 | BB61: =BA61/$P61 -> 0 | BC61: 0 | BD61: =BC61/$P61 -> 0 | BE61: =AS61+AU61+AW61+AY61+BA61+BC61 -> 0 | BF61: =BE61/$P61 -> 0 | BG61: 0 | BH61: =BG61/$P61 -> 0 | BI61: 0 | BJ61: =BI61/$P61 -> 0 | BK61: 0 | BL61: =BK61/$P61 -> 0 | BM61: 0 | BN61: =BM61/$P61 -> 0 | BO61: 0 | BP61: =BO61/$P61 -> 0 | BQ61: 0 | BR61: =BQ61/$P61 -> 0 | BS61: =BG61+BI61+BK61+BM61+BO61+BQ61 -> 0 | BT61: =BS61/$P61 -> 0 | BU61: 0 | BV61: =BU61/$P61 -> 0 | BW61: 0 | BX61: =BW61/$P61 -> 0 | BY61: 0 | BZ61: =BY61/$P61 -> 0 | CA61: 0 | CB61: =CA61/$P61 -> 0 | CC61: 0 | CD61: =CC61/$P61 -> 0 | CE61: 0 | CF61: =CE61/$P61 -> 0 | CG61: =BU61+BW61+BY61+CA61+CC61+CE61 -> 0 | CH61: =CG61/$P61 -> 0 | CI61: 0 | CJ61: =CI61/$P61 -> 0 | CK61: 0 | CL61: =CK61/$P61 -> 0 | CM61: 0 | CN61: =CM61/$P61 -> 0 | CO61: 0 | CP61: =CO61/$P61 -> 0 | CQ61: 0 | CR61: =CQ61/$P61 -> 0 | CS61: 0 | CT61: =CS61/$P61 -> 0 | CU61: =CI61+CK61+CM61+CO61+CQ61+CS61 -> 0 | CV61: =CU61/$P61 -> 0
Q62: =SUM(Q5:Q59) -> 0 | R62: =SUM(R5:R59) -> 0 | S62: =SUM(S5:S59) -> 0 | T62: =SUM(T5:T59) -> 0 | U62: =SUM(U5:U59) -> 0 | V62: =SUM(V5:V59) -> 0 | W62: =SUM(W5:W59) -> 0 | X62: =SUM(X5:X59) -> 0 | ... AC62: =SUM(AC5:AC59) -> 0 | AD62: 0 | AE62: =SUM(AE5:AE59) -> 0 | AF62: =SUM(AF5:AF59) -> 0 | AG62: =SUM(AG5:AG59) -> 0 | AH62: =SUM(AH5:AH59) -> 0 | AI62: =SUM(AI5:AI59) -> 0 | AJ62: =SUM(AJ5:AJ59) -> 0 | AK62: =SUM(AK5:AK59) -> 0 | AL62: =SUM(AL5:AL59) -> 0 | ... AQ62: =SUM(AQ5:AQ59) -> 0 | AR62: =AQ62/$R64 -> 0 | AS62: =SUM(AS5:AS59) -> 0 | AT62: =SUM(AT5:AT59) -> 0 | AU62: =SUM(AU5:AU59) -> 0 | AV62: =SUM(AV5:AV59) -> 0 | AW62: =SUM(AW5:AW59) -> 0 | AX62: =SUM(AX5:AX59) -> 0 | AY62: =SUM(AY5:AY59) -> 0 | AZ62: =SUM(AZ5:AZ59) -> 0 | ... BE62: =SUM(BE5:BE59) -> 0 | BF62: =BE62/$R64 -> 0 | BG62: =SUM(BG5:BG59) -> 0 | BH62: =SUM(BH5:BH59) -> 0 | BI62: =SUM(BI5:BI59) -> 0 | BJ62: =SUM(BJ5:BJ59) -> 0 | BK62: =SUM(BK5:BK59) -> 0 | BL62: =SUM(BL5:BL59) -> 0 | BM62: =SUM(BM5:BM59) -> 0 | BN62: =SUM(BN5:BN59) -> 0 | ... BS62: =SUM(BS5:BS59) -> 0 | BT62: =BS62/$R64 -> 0 | BU62: =SUM(BU5:BU59) -> 0 | BV62: =SUM(BV5:BV59) -> 0 | BW62: =SUM(BW5:BW59) -> 0 | BX62: =SUM(BX5:BX59) -> 0 | BY62: =SUM(BY5:BY59) -> 0 | BZ62: =SUM(BZ5:BZ59) -> 0 | CA62: =SUM(CA5:CA59) -> 0 | CB62: =SUM(CB5:CB59) -> 0 | ... CG62: =SUM(CG5:CG59) -> 0 | CH62: =CG62/$R64 -> 0 | CI62: =SUM(CI5:CI59) -> 0 | CJ62: =SUM(CJ5:CJ59) -> 0 | CK62: =SUM(CK5:CK59) -> 0 | CL62: =SUM(CL5:CL59) -> 0 | CM62: =SUM(CM5:CM59) -> 0 | CN62: =SUM(CN5:CN59) -> 0 | CO62: =SUM(CO5:CO59) -> 0 | CP62: =SUM(CP5:CP59) -> 0 | ... CU62: =SUM(CU5:CU59) -> 0 | CV62: =CU62/$R64 -> 0
F63: =SUM(F5:F62)-(F13+F14+F25+F27+F36+F37+F41+F42+F53+F54+F59+F60+F16+F17+F19+F20) -> 108.55 | K63: =SUM(K5:K62) -> 565.12
D64: TOTAL M2 DE FACHADA SIN DESCUENTOS | G64: =SUM(G5:G63) -> 4308.162 | J64: TOTAL M2 DE FACHADA CON DESCUENTOS | N64: =SUM(L5:L63) -> 1704.062 | O64: =SUM(M5:M63) -> 621.68 | P64: =SUM(N5:N63) -> 1190.5 | Q64: =SUM(O5:O61) -> 226.8 | R64: =SUM(P5:P61) -> 3743.042
F65: =F63*35.8 -> 3886.09 | G65: 4222.23 | H65: =G64-N65 -> 565.12 | M65: =F65-H65 -> 3320.97 | N65: =SUM(N64:Q64) -> 3743.042
G67: =G64*300 -> 1292448.6 | N67: BANCO DE PINTURAS | P67: REN/M2 | Q67: 65
G68: =N65*500 -> 1871521 | N68: BLANCO | O68: VERDE | P68: NEGRO | Q68: BLANCO INTERIOR
F69: =N65*500 -> 1871521 | G69: =SUM(G67:G68) -> 3163969.6 | N69: =N64/$Q$67 -> 26.216338 | O69: =O64/$Q$67 -> 9.5643077 | P69: =P64/$Q$67 -> 18.315385 | Q69: =Q64/$Q$67 -> 3.4892308 | R69: =SUM(N69:Q69) -> 57.585262
L72: 11200 | M72: =L72/4.2 -> 2666.6667 | P72: APLICACIÓN DE PINTURA EN SUPERFICIE DE FACHADA
P73: CANTIDAD | Q73: CANTIDAD EJECUTADA | AC73: TOTAL EJECUTADO | AE73: CANTIDAD EJECUTADA | AQ73: TOTAL EJECUTADO | AS73: CANTIDAD EJECUTADA | BE73: TOTAL EJECUTADO | BG73: CANTIDAD EJECUTADA | BS73: TOTAL EJECUTADO | BU73: CANTIDAD EJECUTADA | CG73: TOTAL EJECUTADO | CI73: CANTIDAD EJECUTADA | CU73: TOTAL EJECUTADO
M74: =17000000/900 -> 18888.889 | Q74: 45817 | S74: =+Q74+1 -> 45818 | U74: =+S74+1 -> 45819 | W74: =+U74+1 -> 45820 | Y74: =+W74+1 -> 45821 | AA74: =+Y74+1 -> 45822 | AC74: SEMANA 1 | AE74: =AA74+2 -> 45824 | AG74: =+AE74+1 -> 45825 | AI74: =+AG74+1 -> 45826 | AK74: =+AI74+1 -> 45827 | AM74: =+AK74+1 -> 45828 | AO74: =+AM74+1 -> 45829 | AQ74: SEMANA 2 | AS74: =AO74+2 -> 45831 | AU74: =+AS74+1 -> 45832 | AW74: =+AU74+1 -> 45833 | AY74: =+AW74+1 -> 45834 | BA74: =+AY74+1 -> 45835 | BC74: =+BA74+1 -> 45836 | BE74: SEMANA 3 | BG74: =BC74+2 -> 45838 | BI74: =+BG74+1 -> 45839 | BK74: =+BI74+1 -> 45840 | BM74: =+BK74+1 -> 45841 | BO74: =+BM74+1 -> 45842 | BQ74: =+BO74+1 -> 45843 | BS74: SEMANA 4 | BU74: =BQ74+2 -> 45845 | BW74: =+BU74+1 -> 45846 | BY74: =+BW74+1 -> 45847 | CA74: =+BY74+1 -> 45848 | CC74: =+CA74+1 -> 45849 | CE74: =+CC74+1 -> 45850 | CG74: SEMANA 5 | CI74: =CE74+2 -> 45852 | CK74: =+CI74+1 -> 45853 | CM74: =+CK74+1 -> 45854 | CO74: =+CM74+1 -> 45855 | CQ74: =+CO74+1 -> 45856 | CS74: =+CQ74+1 -> 45857 | CU74: SEMANA 6
O75: FACHADA | P75: M2 | Q75: M2 | R75: % | S75: M2 | T75: % | U75: M2 | V75: % | W75: M2 | X75: % | Y75: M2 | Z75: % | AA75: M2 | AB75: % | AC75: M2 | AD75: % | AE75: M2 | AF75: % | AG75: M2 | AH75: % | AI75: M2 | AJ75: % | AK75: M2 | AL75: % | AM75: M2 | AN75: % | AO75: M2 | AP75: % | AQ75: M2 | AR75: % | AS75: M2 | AT75: % | AU75: M2 | AV75: % | AW75: M2 | AX75: % | AY75: M2 | AZ75: % | BA75: M2 | BB75: % | BC75: M2 | BD75: % | BE75: M2 | BF75: % | BG75: M2 | BH75: % | BI75: M2 | BJ75: % | BK75: M2 | BL75: % | BM75: M2 | BN75: % | BO75: M2 | BP75: % | BQ75: M2 | BR75: % | BS75: M2 | BT75: % | BU75: M2 | BV75: % | BW75: M2 | BX75: % | BY75: M2 | BZ75: % | CA75: M2 | CB75: % | CC75: M2 | CD75: % | CE75: M2 | CF75: % | CG75: M2 | CH75: % | CI75: M2 | CJ75: % | CK75: M2 | CL75: % | CM75: M2 | CN75: % | CO75: M2 | CP75: % | CQ75: M2 | CR75: % | CS75: M2 | CT75: % | CU75: M2 | CV75: %
L76: 110 | M76: =L76/N65 -> 0.029387862 | O76: CULATA IZQUIERDA | P76: =SUM(P5:P6) -> 318.86 | Q76: =SUM(Q5:Q6) -> 0 | R76: =Q76/$P76 -> 0 | S76: =SUM(S5:S6) -> 0 | T76: =S76/$P76 -> 0 | U76: =SUM(U5:U6) -> 0 | V76: =U76/$P76 -> 0 | W76: =SUM(W5:W6) -> 0 | X76: =W76/$P76 -> 0 | Y76: =SUM(Y5:Y6) -> 0 | Z76: =Y76/$P76 -> 0 | AA76: =SUM(AA5:AA6) -> 0 | AB76: =AA76/$P76 -> 0 | AC76: =Q76+S76+U76+W76+Y76+AA76 -> 0 | AD76: =AC76/$P76 -> 0 | AE76: =SUM(AE5:AE6) -> 0 | AF76: =AE76/$P76 -> 0 | AG76: =SUM(AG5:AG6) -> 0 | AH76: =AG76/$P76 -> 0 | AI76: =SUM(AI5:AI6) -> 0 | AJ76: =AI76/$P76 -> 0 | AK76: =SUM(AK5:AK6) -> 0 | AL76: =AK76/$P76 -> 0 | AM76: =SUM(AM5:AM6) -> 0 | AN76: =AM76/$P76 -> 0 | AO76: =SUM(AO5:AO6) -> 0 | AP76: =AO76/$P76 -> 0 | AQ76: =AE76+AG76+AI76+AK76+AM76+AO76 -> 0 | AR76: =AQ76/$P76 -> 0 | AS76: =SUM(AS5:AS6) -> 0 | AT76: =AS76/$P76 -> 0 | AU76: =SUM(AU5:AU6) -> 0 | AV76: =AU76/$P76 -> 0 | AW76: =SUM(AW5:AW6) -> 0 | AX76: =AW76/$P76 -> 0 | AY76: =SUM(AY5:AY6) -> 0 | AZ76: =AY76/$P76 -> 0 | BA76: =SUM(BA5:BA6) -> 0 | BB76: =BA76/$P76 -> 0 | BC76: =SUM(BC5:BC6) -> 0 | BD76: =BC76/$P76 -> 0 | BE76: =AS76+AU76+AW76+AY76+BA76+BC76 -> 0 | BF76: =BE76/$P76 -> 0 | BG76: =SUM(BG5:BG6) -> 0 | BH76: =BG76/$P76 -> 0 | BI76: =SUM(BI5:BI6) -> 0 | BJ76: =BI76/$P76 -> 0 | BK76: =SUM(BK5:BK6) -> 0 | BL76: =BK76/$P76 -> 0 | BM76: =SUM(BM5:BM6) -> 0 | BN76: =BM76/$P76 -> 0 | BO76: =SUM(BO5:BO6) -> 0 | BP76: =BO76/$P76 -> 0 | BQ76: =SUM(BQ5:BQ6) -> 0 | BR76: =BQ76/$P76 -> 0 | BS76: =BG76+BI76+BK76+BM76+BO76+BQ76 -> 0 | BT76: =BS76/$P76 -> 0 | BU76: =SUM(BU5:BU6) -> 0 | BV76: =BU76/$P76 -> 0 | BW76: =SUM(BW5:BW6) -> 0 | BX76: =BW76/$P76 -> 0 | BY76: =SUM(BY5:BY6) -> 0 | BZ76: =BY76/$P76 -> 0 | CA76: =SUM(CA5:CA6) -> 0 | CB76: =CA76/$P76 -> 0 | CC76: =SUM(CC5:CC6) -> 0 | CD76: =CC76/$P76 -> 0 | CE76: =SUM(CE5:CE6) -> 0 | CF76: =CE76/$P76 -> 0 | CG76: =BU76+BW76+BY76+CA76+CC76+CE76 -> 0 | CH76: =CG76/$P76 -> 0 | CI76: =SUM(CI5:CI6) -> 0 | CJ76: =CI76/$P76 -> 0 | CK76: =SUM(CK5:CK6) -> 0 | CL76: =CK76/$P76 -> 0 | CM76: =SUM(CM5:CM6) -> 0 | CN76: =CM76/$P76 -> 0 | CO76: =SUM(CO5:CO6) -> 0 | CP76: =CO76/$P76 -> 0 | CQ76: =SUM(CQ5:CQ6) -> 0 | CR76: =CQ76/$P76 -> 0 | CS76: =SUM(CS5:CS6) -> 0 | CT76: =CS76/$P76 -> 0 | CU76: =CI76+CK76+CM76+CO76+CQ76+CS76 -> 0 | CV76: =CU76/$P76 -> 0
O77: =B7 -> POSTERIOR | P77: =SUM(P7:P25) -> 1476.254 | Q77: =SUM(Q7:Q25) -> 0 | R77: =Q77/$P77 -> 0 | S77: =SUM(S7:S25) -> 0 | T77: =S77/$P77 -> 0 | U77: =SUM(U7:U25) -> 0 | V77: =U77/$P77 -> 0 | W77: =SUM(W7:W25) -> 0 | X77: =W77/$P77 -> 0 | Y77: =SUM(Y7:Y25) -> 0 | Z77: =Y77/$P77 -> 0 | AA77: =SUM(AA7:AA25) -> 0 | AB77: =AA77/$P77 -> 0 | AC77: =Q77+S77+U77+W77+Y77+AA77 -> 0 | AD77: =AC77/$P77 -> 0 | AE77: =SUM(AE7:AE25) -> 0 | AF77: =AE77/$P77 -> 0 | AG77: =SUM(AG7:AG25) -> 0 | AH77: =AG77/$P77 -> 0 | AI77: =SUM(AI7:AI25) -> 0 | AJ77: =AI77/$P77 -> 0 | AK77: =SUM(AK7:AK25) -> 0 | AL77: =AK77/$P77 -> 0 | AM77: =SUM(AM7:AM25) -> 0 | AN77: =AM77/$P77 -> 0 | AO77: =SUM(AO7:AO25) -> 0 | AP77: =AO77/$P77 -> 0 | AQ77: =AE77+AG77+AI77+AK77+AM77+AO77 -> 0 | AR77: =AQ77/$P77 -> 0 | AS77: =SUM(AS7:AS25) -> 0 | AT77: =AS77/$P77 -> 0 | AU77: =SUM(AU7:AU25) -> 0 | AV77: =AU77/$P77 -> 0 | AW77: =SUM(AW7:AW25) -> 0 | AX77: =AW77/$P77 -> 0 | AY77: =SUM(AY7:AY25) -> 0 | AZ77: =AY77/$P77 -> 0 | BA77: =SUM(BA7:BA25) -> 0 | BB77: =BA77/$P77 -> 0 | BC77: =SUM(BC7:BC25) -> 0 | BD77: =BC77/$P77 -> 0 | BE77: =AS77+AU77+AW77+AY77+BA77+BC77 -> 0 | BF77: =BE77/$P77 -> 0 | BG77: =SUM(BG7:BG25) -> 0 | BH77: =BG77/$P77 -> 0 | BI77: =SUM(BI7:BI25) -> 0 | BJ77: =BI77/$P77 -> 0 | BK77: =SUM(BK7:BK25) -> 0 | BL77: =BK77/$P77 -> 0 | BM77: =SUM(BM7:BM25) -> 0 | BN77: =BM77/$P77 -> 0 | BO77: =SUM(BO7:BO25) -> 0 | BP77: =BO77/$P77 -> 0 | BQ77: =SUM(BQ7:BQ25) -> 0 | BR77: =BQ77/$P77 -> 0 | BS77: =BG77+BI77+BK77+BM77+BO77+BQ77 -> 0 | BT77: =BS77/$P77 -> 0 | BU77: =SUM(BU7:BU25) -> 0 | BV77: =BU77/$P77 -> 0 | BW77: =SUM(BW7:BW25) -> 0 | BX77: =BW77/$P77 -> 0 | BY77: =SUM(BY7:BY25) -> 0 | BZ77: =BY77/$P77 -> 0 | CA77: =SUM(CA7:CA25) -> 0 | CB77: =CA77/$P77 -> 0 | CC77: =SUM(CC7:CC25) -> 0 | CD77: =CC77/$P77 -> 0 | CE77: =SUM(CE7:CE25) -> 0 | CF77: =CE77/$P77 -> 0 | CG77: =BU77+BW77+BY77+CA77+CC77+CE77 -> 0 | CH77: =CG77/$P77 -> 0 | CI77: =SUM(CI7:CI25) -> 0 | CJ77: =CI77/$P77 -> 0 | CK77: =SUM(CK7:CK25) -> 0 | CL77: =CK77/$P77 -> 0 | CM77: =SUM(CM7:CM25) -> 0 | CN77: =CM77/$P77 -> 0 | CO77: =SUM(CO7:CO25) -> 0 | CP77: =CO77/$P77 -> 0 | CQ77: =SUM(CQ7:CQ25) -> 0 | CR77: =CQ77/$P77 -> 0 | CS77: =SUM(CS7:CS25) -> 0 | CT77: =CS77/$P77 -> 0 | CU77: =CI77+CK77+CM77+CO77+CQ77+CS77 -> 0 | CV77: =CU77/$P77 -> 0
O78: =B26 -> CULATA DER | P78: =SUM(P26:P34) -> 486.346 | Q78: =SUM(Q26:Q34) -> 0 | R78: =Q78/$P78 -> 0 | S78: =SUM(S26:S34) -> 0 | T78: =S78/$P78 -> 0 | U78: =SUM(U26:U34) -> 0 | V78: =U78/$P78 -> 0 | W78: =SUM(W26:W34) -> 0 | X78: =W78/$P78 -> 0 | Y78: =SUM(Y26:Y34) -> 0 | Z78: =Y78/$P78 -> 0 | AA78: =SUM(AA26:AA34) -> 0 | AB78: =AA78/$P78 -> 0 | AC78: =Q78+S78+U78+W78+Y78+AA78 -> 0 | AD78: =AC78/$P78 -> 0 | AE78: =SUM(AE26:AE34) -> 0 | AF78: =AE78/$P78 -> 0 | AG78: =SUM(AG26:AG34) -> 0 | AH78: =AG78/$P78 -> 0 | AI78: =SUM(AI26:AI34) -> 0 | AJ78: =AI78/$P78 -> 0 | AK78: =SUM(AK26:AK34) -> 0 | AL78: =AK78/$P78 -> 0 | AM78: =SUM(AM26:AM34) -> 0 | AN78: =AM78/$P78 -> 0 | AO78: =SUM(AO26:AO34) -> 0 | AP78: =AO78/$P78 -> 0 | AQ78: =AE78+AG78+AI78+AK78+AM78+AO78 -> 0 | AR78: =AQ78/$P78 -> 0 | AS78: =SUM(AS26:AS34) -> 0 | AT78: =AS78/$P78 -> 0 | AU78: =SUM(AU26:AU34) -> 0 | AV78: =AU78/$P78 -> 0 | AW78: =SUM(AW26:AW34) -> 0 | AX78: =AW78/$P78 -> 0 | AY78: =SUM(AY26:AY34) -> 0 | AZ78: =AY78/$P78 -> 0 | BA78: =SUM(BA26:BA34) -> 0 | BB78: =BA78/$P78 -> 0 | BC78: =SUM(BC26:BC34) -> 0 | BD78: =BC78/$P78 -> 0 | BE78: =AS78+AU78+AW78+AY78+BA78+BC78 -> 0 | BF78: =BE78/$P78 -> 0 | BG78: =SUM(BG26:BG34) -> 0 | BH78: =BG78/$P78 -> 0 | BI78: =SUM(BI26:BI34) -> 0 | BJ78: =BI78/$P78 -> 0 | BK78: =SUM(BK26:BK34) -> 0 | BL78: =BK78/$P78 -> 0 | BM78: =SUM(BM26:BM34) -> 0 | BN78: =BM78/$P78 -> 0 | BO78: =SUM(BO26:BO34) -> 0 | BP78: =BO78/$P78 -> 0 | BQ78: =SUM(BQ26:BQ34) -> 0 | BR78: =BQ78/$P78 -> 0 | BS78: =BG78+BI78+BK78+BM78+BO78+BQ78 -> 0 | BT78: =BS78/$P78 -> 0 | BU78: =SUM(BU26:BU34) -> 0 | BV78: =BU78/$P78 -> 0 | BW78: =SUM(BW26:BW34) -> 0 | BX78: =BW78/$P78 -> 0 | BY78: =SUM(BY26:BY34) -> 0 | BZ78: =BY78/$P78 -> 0 | CA78: =SUM(CA26:CA34) -> 0 | CB78: =CA78/$P78 -> 0 | CC78: =SUM(CC26:CC34) -> 0 | CD78: =CC78/$P78 -> 0 | CE78: =SUM(CE26:CE34) -> 0 | CF78: =CE78/$P78 -> 0 | CG78: =BU78+BW78+BY78+CA78+CC78+CE78 -> 0 | CH78: =CG78/$P78 -> 0 | CI78: =SUM(CI26:CI34) -> 0 | CJ78: =CI78/$P78 -> 0 | CK78: =SUM(CK26:CK34) -> 0 | CL78: =CK78/$P78 -> 0 | CM78: =SUM(CM26:CM34) -> 0 | CN78: =CM78/$P78 -> 0 | CO78: =SUM(CO26:CO34) -> 0 | CP78: =CO78/$P78 -> 0 | CQ78: =SUM(CQ26:CQ34) -> 0 | CR78: =CQ78/$P78 -> 0 | CS78: =SUM(CS26:CS34) -> 0 | CT78: =CS78/$P78 -> 0 | CU78: =CI78+CK78+CM78+CO78+CQ78+CS78 -> 0 | CV78: =CU78/$P78 -> 0
O79: =B35 -> FRONTAL | P79: =SUM(P35:P61) -> 1461.582 | Q79: =SUM(Q35:Q61) -> 0 | R79: =Q79/$P79 -> 0 | S79: =SUM(S35:S61) -> 0 | T79: =S79/$P79 -> 0 | U79: =SUM(U35:U61) -> 0 | V79: =U79/$P79 -> 0 | W79: =SUM(W35:W61) -> 0 | X79: =W79/$P79 -> 0 | Y79: =SUM(Y35:Y61) -> 0 | Z79: =Y79/$P79 -> 0 | AA79: =SUM(AA35:AA61) -> 0 | AB79: =AA79/$P79 -> 0 | AC79: =Q79+S79+U79+W79+Y79+AA79 -> 0 | AD79: =AC79/$P79 -> 0 | AE79: =SUM(AE35:AE61) -> 0 | AF79: =AE79/$P79 -> 0 | AG79: =SUM(AG35:AG61) -> 0 | AH79: =AG79/$P79 -> 0 | AI79: =SUM(AI35:AI61) -> 0 | AJ79: =AI79/$P79 -> 0 | AK79: =SUM(AK35:AK61) -> 0 | AL79: =AK79/$P79 -> 0 | AM79: =SUM(AM35:AM61) -> 0 | AN79: =AM79/$P79 -> 0 | AO79: =SUM(AO35:AO61) -> 0 | AP79: =AO79/$P79 -> 0 | AQ79: =AE79+AG79+AI79+AK79+AM79+AO79 -> 0 | AR79: =AQ79/$P79 -> 0 | AS79: =SUM(AS35:AS61) -> 0 | AT79: =AS79/$P79 -> 0 | AU79: =SUM(AU35:AU61) -> 0 | AV79: =AU79/$P79 -> 0 | AW79: =SUM(AW35:AW61) -> 0 | AX79: =AW79/$P79 -> 0 | AY79: =SUM(AY35:AY61) -> 0 | AZ79: =AY79/$P79 -> 0 | BA79: =SUM(BA35:BA61) -> 0 | BB79: =BA79/$P79 -> 0 | BC79: =SUM(BC35:BC61) -> 0 | BD79: =BC79/$P79 -> 0 | BE79: =AS79+AU79+AW79+AY79+BA79+BC79 -> 0 | BF79: =BE79/$P79 -> 0 | BG79: =SUM(BG35:BG61) -> 0 | BH79: =BG79/$P79 -> 0 | BI79: =SUM(BI35:BI61) -> 0 | BJ79: =BI79/$P79 -> 0 | BK79: =SUM(BK35:BK61) -> 0 | BL79: =BK79/$P79 -> 0 | BM79: =SUM(BM35:BM61) -> 0 | BN79: =BM79/$P79 -> 0 | BO79: =SUM(BO35:BO61) -> 0 | BP79: =BO79/$P79 -> 0 | BQ79: =SUM(BQ35:BQ61) -> 0 | BR79: =BQ79/$P79 -> 0 | BS79: =BG79+BI79+BK79+BM79+BO79+BQ79 -> 0 | BT79: =BS79/$P79 -> 0 | BU79: =SUM(BU35:BU61) -> 0 | BV79: =BU79/$P79 -> 0 | BW79: =SUM(BW35:BW61) -> 0 | BX79: =BW79/$P79 -> 0 | BY79: =SUM(BY35:BY61) -> 0 | BZ79: =BY79/$P79 -> 0 | CA79: =SUM(CA35:CA61) -> 0 | CB79: =CA79/$P79 -> 0 | CC79: =SUM(CC35:CC61) -> 0 | CD79: =CC79/$P79 -> 0 | CE79: =SUM(CE35:CE61) -> 0 | CF79: =CE79/$P79 -> 0 | CG79: =BU79+BW79+BY79+CA79+CC79+CE79 -> 0 | CH79: =CG79/$P79 -> 0 | CI79: =SUM(CI35:CI61) -> 0 | CJ79: =CI79/$P79 -> 0 | CK79: =SUM(CK35:CK61) -> 0 | CL79: =CK79/$P79 -> 0 | CM79: =SUM(CM35:CM61) -> 0 | CN79: =CM79/$P79 -> 0 | CO79: =SUM(CO35:CO61) -> 0 | CP79: =CO79/$P79 -> 0 | CQ79: =SUM(CQ35:CQ61) -> 0 | CR79: =CQ79/$P79 -> 0 | CS79: =SUM(CS35:CS61) -> 0 | CT79: =CS79/$P79 -> 0 | CU79: =CI79+CK79+CM79+CO79+CQ79+CS79 -> 0 | CV79: =CU79/$P79 -> 0
P81: =SUM(P76:P80) -> 3743.042 | Q81: =SUM(Q76:Q80) -> 0 | R81: =Q81/$P81 -> 0 | S81: =SUM(S76:S80) -> 0 | T81: =S81/$P81 -> 0 | U81: =SUM(U76:U80) -> 0 | V81: =U81/$P81 -> 0 | W81: =SUM(W76:W80) -> 0 | X81: =W81/$P81 -> 0 | Y81: =SUM(Y76:Y80) -> 0 | Z81: =Y81/$P81 -> 0 | AA81: =SUM(AA76:AA80) -> 0 | AB81: =AA81/$P81 -> 0 | AC81: =SUM(AC76:AC80) -> 0 | AD81: =AC81/$P81 -> 0 | AE81: =SUM(AE76:AE80) -> 0 | AF81: =AE81/$P81 -> 0 | AG81: =SUM(AG76:AG80) -> 0 | AH81: =AG81/$P81 -> 0 | AI81: =SUM(AI76:AI80) -> 0 | AJ81: =AI81/$P81 -> 0 | AK81: =SUM(AK76:AK80) -> 0 | AL81: =AK81/$P81 -> 0 | AM81: =SUM(AM76:AM80) -> 0 | AN81: =AM81/$P81 -> 0 | AO81: =SUM(AO76:AO80) -> 0 | AP81: =AO81/$P81 -> 0 | AQ81: =SUM(AQ76:AQ80) -> 0 | AR81: =AQ81/$P81 -> 0 | AS81: =SUM(AS76:AS80) -> 0 | AT81: =AS81/$P81 -> 0 | AU81: =SUM(AU76:AU80) -> 0 | AV81: =AU81/$P81 -> 0 | AW81: =SUM(AW76:AW80) -> 0 | AX81: =AW81/$P81 -> 0 | AY81: =SUM(AY76:AY80) -> 0 | AZ81: =AY81/$P81 -> 0 | BA81: =SUM(BA76:BA80) -> 0 | BB81: =BA81/$P81 -> 0 | BC81: =SUM(BC76:BC80) -> 0 | BD81: =BC81/$P81 -> 0 | BE81: =SUM(BE76:BE80) -> 0 | BF81: =BE81/$P81 -> 0 | BG81: =SUM(BG76:BG80) -> 0 | BH81: =BG81/$P81 -> 0 | BI81: =SUM(BI76:BI80) -> 0 | BJ81: =BI81/$P81 -> 0 | BK81: =SUM(BK76:BK80) -> 0 | BL81: =BK81/$P81 -> 0 | BM81: =SUM(BM76:BM80) -> 0 | BN81: =BM81/$P81 -> 0 | BO81: =SUM(BO76:BO80) -> 0 | BP81: =BO81/$P81 -> 0 | BQ81: =SUM(BQ76:BQ80) -> 0 | BR81: =BQ81/$P81 -> 0 | BS81: =SUM(BS76:BS80) -> 0 | BT81: =BS81/$P81 -> 0 | BU81: =SUM(BU76:BU80) -> 0 | BV81: =BU81/$P81 -> 0 | BW81: =SUM(BW76:BW80) -> 0 | BX81: =BW81/$P81 -> 0 | BY81: =SUM(BY76:BY80) -> 0 | BZ81: =BY81/$P81 -> 0 | CA81: =SUM(CA76:CA80) -> 0 | CB81: =CA81/$P81 -> 0 | CC81: =SUM(CC76:CC80) -> 0 | CD81: =CC81/$P81 -> 0 | CE81: =SUM(CE76:CE80) -> 0 | CF81: =CE81/$P81 -> 0 | CG81: =SUM(CG76:CG80) -> 0 | CH81: =CG81/$P81 -> 0 | CI81: =SUM(CI76:CI80) -> 0 | CJ81: =CI81/$P81 -> 0 | CK81: =SUM(CK76:CK80) -> 0 | CL81: =CK81/$P81 -> 0 | CM81: =SUM(CM76:CM80) -> 0 | CN81: =CM81/$P81 -> 0 | CO81: =SUM(CO76:CO80) -> 0 | CP81: =CO81/$P81 -> 0 | CQ81: =SUM(CQ76:CQ80) -> 0 | CR81: =CQ81/$P81 -> 0 | CS81: =SUM(CS76:CS80) -> 0 | CT81: =CS81/$P81 -> 0 | CU81: =SUM(CU76:CU80) -> 0 | CV81: =CU81/$P81 -> 0
AC82: =+P81-AC81 -> 3743.042 | AD82: =AC82/P81 -> 1 | AQ82: =AC82-AQ81 -> 3743.042 | AR82: =AQ82/$P81 -> 1 | BE82: =AQ82-BE81 -> 3743.042 | BF82: =BE82/$P81 -> 1 | BS82: =BE82-BS81 -> 3743.042 | BT82: =BS82/$P81 -> 1 | CG82: =BS82-CG81 -> 3743.042 | CH82: =CG82/$P81 -> 1 | CU82: =CG82-CU81 -> 3743.042 | CV82: =CU82/$P81 -> 1

Sheet PINTURA T.VERDE
A2: EDIFICIO TORRE VERDE | Q2: CANTIDAD EJECUTADA | AC2: TOTAL EJECUTADO | AQ2: TOTAL EJECUTADO | BE2: TOTAL EJECUTADO | BG2: CANTIDAD EJECUTADA | BS2: TOTAL EJECUTADO | CG2: TOTAL EJECUTADO | CU2: TOTAL EJECUTADO
A3: REALIZADO POR: ARQ ALEXIS BETANCOURT | E3: DIMENSIONES | H3: DESCUENTOS | Q3: 45817 | S3: =+Q3+1 -> 45818 | U3: =+S3+1 -> 45819 | W3: =+U3+1 -> 45820 | Y3: =+W3+1 -> 45821 | AA3: =+Y3+1 -> 45822 | AC3: SEMANA 1 | AE3: =AA3+2 -> 45824 | AG3: =+AE3+1 -> 45825 | AI3: =+AG3+1 -> 45826 | AK3: =+AI3+1 -> 45827 | AM3: =+AK3+1 -> 45828 | AO3: =+AM3+1 -> 45829 | AQ3: SEMANA 2 | AS3: =AO3+2 -> 45831 | AU3: =+AS3+1 -> 45832 | AW3: =+AU3+1 -> 45833 | AY3: =+AW3+1 -> 45834 | BA3: =+AY3+1 -> 45835 | BC3: =+BA3+1 -> 45836 | BE3: SEMANA 3 | BG3: =BC3+2 -> 45838 | BI3: =+BG3+1 -> 45839 | BK3: =+BI3+1 -> 45840 | BM3: =+BK3+1 -> 45841 | BO3: =+BM3+1 -> 45842 | BQ3: =+BO3+1 -> 45843 | BS3: SEMANA 4 | BU3: =BQ3+2 -> 45845 | BW3: =+BU3+1 -> 45846 | BY3: =+BW3+1 -> 45847 | CA3: =+BY3+1 -> 45848 | CC3: =+CA3+1 -> 45849 | CE3: =+CC3+1 -> 45850 | CG3: SEMANA 5 | CI3: =CE3+2 -> 45852 | CK3: =+CI3+1 -> 45853 | CM3: =+CK3+1 -> 45854 | CO3: =+CM3+1 -> 45855 | CQ3: =+CO3+1 -> 45856 | CS3: =+CQ3+1 -> 45857 | CU3: SEMANA 6
A4: TORRE | B4: FACHADA | C4: SECCIÓN | D4: DESCRIPCIÓN | E4: ALTO | F4: ANCHO | G4: TOTAL (M2) | H4: ALTO | I4: ANCHO | J4: CANTIDAD | K4: TOTAL (M2) | L4: ÁREA TOTAL (BLANCO) | M4: ÁREA TOTAL (VERDE) | N4: ÁREA TOTAL (NEGRO) | O4: CIELO RASO | Q4: M2 | R4: % | S4: M2 | T4: % | U4: M2 | V4: % | W4: M2 | X4: % | Y4: M2 | Z4: % | AB4: % | AC4: M2 | AD4: % | AE4: M2 | AF4: % | AG4: M2 | AH4: % | AI4: M2 | AJ4: % | AK4: M2 | AL4: % | AM4: M2 | AN4: % | AP4: % | AQ4: M2 | AR4: % | AS4: M2 | AT4: % | AU4: M2 | AV4: % | AW4: M2 | AX4: % | AY4: M2 | AZ4: % | BA4: M2 | BB4: % | BD4: % | BE4: M2 | BF4: % | BG4: M2 | BH4: % | BI4: M2 | BJ4: % | BK4: M2 | BL4: % | BM4: M2 | BN4: % | BO4: M2 | BP4: % | BR4: % | BS4: M2 | BT4: % | BU4: M2 | BV4: % | BW4: M2 | BX4: % | BY4: M2 | BZ4: % | CA4: M2 | CB4: % | CC4: M2 | CD4: % | CF4: % | CG4: M2 | CH4: % | CI4: M2 | CJ4: % | CK4: M2 | CL4: % | CM4: M2 | CN4: % | CO4: M2 | CP4: % | CQ4: M2 | CR4: % | CT4: % | CU4: M2 | CV4: %
A5: B | B5: CULATA IZQ | C5: 1 | D5: Muro con ventana (Negro) | E5: =(2.5*14)+0.6 -> 35.6 | F5: 9.7 | G5: =E5*F5 -> 345.32 | H5: 1.5 | I5: 1.2 | J5: 14 | K5: =(H5*I5)*J5 -> 25.2 | N5: =G5-(K5+K6) -> 318.86 | P5: =SUM(L5:O5) -> 318.86 | Q5: 0 | R5: =Q5/$P5 -> 0 | S5: 0 | T5: =S5/$P5 -> 0 | U5: 0 | V5: =U5/$P5 -> 0 | W5: 0 | X5: =W5/$P5 -> 0 | Y5: 0 | Z5: =Y5/$P5 -> 0 | AA5: 0 | AB5: =AA5/$P5 -> 0 | AC5: =Q5+S5+U5+W5+Y5+AA5 -> 0 | AD5: =AC5/$P5 -> 0 | AE5: 0 | AF5: =AE5/$P5 -> 0 | AG5: 0 | AH5: =AG5/$P5 -> 0 | AI5: 0 | AJ5: =AI5/$P5 -> 0 | AK5: 0 | AL5: =AK5/$P5 -> 0 | AM5: 0 | AN5: =AM5/$P5 -> 0 | AO5: 0 | AP5: =AO5/$P5 -> 0 | AQ5: =AE5+AG5+AI5+AK5+AM5+AO5 -> 0 | AR5: =AQ5/$P5 -> 0 | AS5: 0 | AT5: =AS5/$P5 -> 0 | AU5: 0 | AV5: =AU5/$P5 -> 0 | AW5: 0 | AX5: =AW5/$P5 -> 0 | AY5: 0 | AZ5: =AY5/$P5 -> 0 | BA5: 0 | BB5: =BA5/$P5 -> 0 | BC5: 0 | BD5: =BC5/$P5 -> 0 | BE5: =AS5+AU5+AW5+AY5+BA5+BC5 -> 0 | BF5: =BE5/$P5 -> 0 | BG5: 0 | BH5: =BG5/$P5 -> 0 | BI5: 0 | BJ5: =BI5/$P5 -> 0 | BK5: 0 | BL5: =BK5/$P5 -> 0 | BM5: 0 | BN5: =BM5/$P5 -> 0 | BO5: 0 | BP5: =BO5/$P5 -> 0 | BQ5: 0 | BR5: =BQ5/$P5 -> 0 | BS5: =BG5+BI5+BK5+BM5+BO5+BQ5 -> 0 | BT5: =BS5/$P5 -> 0 | BU5: 0 | BV5: =BU5/$P5 -> 0 | BW5: 0 | BX5: =BW5/$P5 -> 0 | BY5: 0 | BZ5: =BY5/$P5 -> 0 | CA5: 0 | CB5: =CA5/$P5 -> 0 | CC5: 0 | CD5: =CC5/$P5 -> 0 | CE5: 0 | CF5: =CE5/$P5 -> 0 | CG5: =BU5+BW5+BY5+CA5+CC5+CE5 -> 0 | CH5: =CG5/$P5 -> 0 | CI5: 0 | CJ5: =CI5/$P5 -> 0 | CK5: 0 | CL5: =CK5/$P5 -> 0 | CM5: 0 | CN5: =CM5/$P5 -> 0 | CO5: 0 | CP5: =CO5/$P5 -> 0 | CQ5: 0 | CR5: =CQ5/$P5 -> 0 | CS5: 0 | CT5: =CS5/$P5 -> 0 | CU5: =CI5+CK5+CM5+CO5+CQ5+CS5 -> 0 | CV5: =CU5/$P5 -> 0
H6: 0.3 | I6: 0.3 | J6: 14 | K6: =(H6*I6)*J6 -> 1.26 | P6: =SUM(L6:O6) -> 0 | Q6: 0 | S6: 0 | U6: 0 | W6: 0 | Y6: 0 | AA6: 0 | AC6: =Q6+S6+U6+W6+Y6+AA6 -> 0 | AE6: 0 | AG6: 0 | AI6: 0 | AK6: 0 | AM6: 0 | AO6: 0 | AQ6: =AE6+AG6+AI6+AK6+AM6+AO6 -> 0 | AS6: 0 | AU6: 0 | AW6: 0 | AY6: 0 | BA6: 0 | BC6: 0 | BE6: =AS6+AU6+AW6+AY6+BA6+BC6 -> 0 | BG6: 0 | BI6: 0 | BK6: 0 | BM6: 0 | BO6: 0 | BQ6: 0 | BS6: =BG6+BI6+BK6+BM6+BO6+BQ6 -> 0 | BU6: 0 | BW6: 0 | BY6: 0 | CA6: 0 | CC6: 0 | CE6: 0 | CG6: =BU6+BW6+BY6+CA6+CC6+CE6 -> 0 | CI6: 0 | CK6: 0 | CM6: 0 | CO6: 0 | CQ6: 0 | CS6: 0 | CU6: =CI6+CK6+CM6+CO6+CQ6+CS6 -> 0
B7: POSTERIOR | C7: 2 | D7: Muro con ventana (Negro) | E7: =E5 -> 35.6 | F7: 6.1 | G7: =E7*F7 -> 217.16 | H7: 1.5 | I7: 1.2 | J7: 28 | K7: =(H7*I7)*J7 -> 50.4 | N7: =G7-K7 -> 166.76 | P7: =SUM(L7:O7) -> 166.76 | Q7: 0 | R7: =Q7/$P7 -> 0 | S7: 0 | T7: =S7/$P7 -> 0 | U7: 0 | V7: =U7/$P7 -> 0 | W7: 0 | X7: =W7/$P7 -> 0 | Y7: 0 | Z7: =Y7/$P7 -> 0 | AA7: 0 | AB7: =AA7/$P7 -> 0 | AC7: =Q7+S7+U7+W7+Y7+AA7 -> 0 | AD7: =AC7/$P7 -> 0 | AE7: 0 | AF7: =AE7/$P7 -> 0 | AG7: 0 | AH7: =AG7/$P7 -> 0 | AI7: 0 | AJ7: =AI7/$P7 -> 0 | AK7: 0 | AL7: =AK7/$P7 -> 0 | AM7: 0 | AN7: =AM7/$P7 -> 0 | AO7: 0 | AP7: =AO7/$P7 -> 0 | AQ7: =AE7+AG7+AI7+AK7+AM7+AO7 -> 0 | AR7: =AQ7/$P7 -> 0 | AS7: 0 | AT7: =AS7/$P7 -> 0 | AU7: 0 | AV7: =AU7/$P7 -> 0 | AW7: 0 | AX7: =AW7/$P7 -> 0 | AY7: 0 | AZ7: =AY7/$P7 -> 0 | BA7: 0 | BB7: =BA7/$P7 -> 0 | BC7: 0 | BD7: =BC7/$P7 -> 0 | BE7: =AS7+AU7+AW7+AY7+BA7+BC7 -> 0 | BF7: =BE7/$P7 -> 0 | BG7: 0 | BH7: =BG7/$P7 -> 0 | BI7: 0 | BJ7: =BI7/$P7 -> 0 | BK7: 0 | BL7: =BK7/$P7 -> 0 | BM7: 0 | BN7: =BM7/$P7 -> 0 | BO7: 0 | BP7: =BO7/$P7 -> 0 | BQ7: 0 | BR7: =BQ7/$P7 -> 0 | BS7: =BG7+BI7+BK7+BM7+BO7+BQ7 -> 0 | BT7: =BS7/$P7 -> 0 | BU7: 0 | BV7: =BU7/$P7 -> 0 | BW7: 0 | BX7: =BW7/$P7 -> 0 | BY7: 0 | BZ7: =BY7/$P7 -> 0 | CA7: 0 | CB7: =CA7/$P7 -> 0 | CC7: 0 | CD7: =CC7/$P7 -> 0 | CE7: 0 | CF7: =CE7/$P7 -> 0 | CG7: =BU7+BW7+BY7+CA7+CC7+CE7 -> 0 | CH7: =CG7/$P7 -> 0 | CI7: 0 | CJ7: =CI7/$P7 -> 0 | CK7: 0 | CL7: =CK7/$P7 -> 0 | CM7: 0 | CN7: =CM7/$P7 -> 0 | CO7: 0 | CP7: =CO7/$P7 -> 0 | CQ7: 0 | CR7: =CQ7/$P7 -> 0 | CS7: 0 | CT7: =CS7/$P7 -> 0 | CU7: =CI7+CK7+CM7+CO7+CQ7+CS7 -> 0 | CV7: =CU7/$P7 -> 0
C8: 3 | D8: Muro escaleras (Negro) | E8: 35 | F8: 3.1 | G8: =E8*F8 -> 108.5 | H8: 0.25 | I8: 3.1 | J8: 14 | K8: =(H8*I8)*J8 -> 10.85 | N8: =G8-K8 -> 97.65 | P8: =SUM(L8:O8) -> 97.65 | Q8: 0 | R8: =Q8/$P8 -> 0 | S8: 0 | T8: =S8/$P8 -> 0 | U8: 0 | V8: =U8/$P8 -> 0 | W8: 0 | X8: =W8/$P8 -> 0 | Y8: 0 | Z8: =Y8/$P8 -> 0 | AA8: 0 | AB8: =AA8/$P8 -> 0 | AC8: =Q8+S8+U8+W8+Y8+AA8 -> 0 | AD8: =AC8/$P8 -> 0 | AE8: 0 | AF8: =AE8/$P8 -> 0 | AG8: 0 | AH8: =AG8/$P8 -> 0 | AI8: 0 | AJ8: =AI8/$P8 -> 0 | AK8: 0 | AL8: =AK8/$P8 -> 0 | AM8: 0 | AN8: =AM8/$P8 -> 0 | AO8: 0 | AP8: =AO8/$P8 -> 0 | AQ8: =AE8+AG8+AI8+AK8+AM8+AO8 -> 0 | AR8: =AQ8/$P8 -> 0 | AS8: 0 | AT8: =AS8/$P8 -> 0 | AU8: 0 | AV8: =AU8/$P8 -> 0 | AW8: 0 | AX8: =AW8/$P8 -> 0 | AY8: 0 | AZ8: =AY8/$P8 -> 0 | BA8: 0 | BB8: =BA8/$P8 -> 0 | BC8: 0 | BD8: =BC8/$P8 -> 0 | BE8: =AS8+AU8+AW8+AY8+BA8+BC8 -> 0 | BF8: =BE8/$P8 -> 0 | BG8: 0 | BH8: =BG8/$P8 -> 0 | BI8: 0 | BJ8: =BI8/$P8 -> 0 | BK8: 0 | BL8: =BK8/$P8 -> 0 | BM8: 0 | BN8: =BM8/$P8 -> 0 | BO8: 0 | BP8: =BO8/$P8 -> 0 | BQ8: 0 | BR8: =BQ8/$P8 -> 0 | BS8: =BG8+BI8+BK8+BM8+BO8+BQ8 -> 0 | BT8: =BS8/$P8 -> 0 | BU8: 0 | BV8: =BU8/$P8 -> 0 | BW8: 0 | BX8: =BW8/$P8 -> 0 | BY8: 0 | BZ8: =BY8/$P8 -> 0 | CA8: 0 | CB8: =CA8/$P8 -> 0 | CC8: 0 | CD8: =CC8/$P8 -> 0 | CE8: 0 | CF8: =CE8/$P8 -> 0 | CG8: =BU8+BW8+BY8+CA8+CC8+CE8 -> 0 | CH8: =CG8/$P8 -> 0 | CI8: 0 | CJ8: =CI8/$P8 -> 0 | CK8: 0 | CL8: =CK8/$P8 -> 0 | CM8: 0 | CN8: =CM8/$P8 -> 0 | CO8: 0 | CP8: =CO8/$P8 -> 0 | CQ8: 0 | CR8: =CQ8/$P8 -> 0 | CS8: 0 | CT8: =CS8/$P8 -> 0 | CU8: =CI8+CK8+CM8+CO8+CQ8+CS8 -> 0 | CV8: =CU8/$P8 -> 0
C9: 4 | D9: Muro escaleras (Blanco) | E9: 35 | F9: 2.15 | G9: =E9*F9 -> 75.25 | L9: =G9-K9 -> 75.25 | P9: =SUM(L9:O9) -> 75.25 | Q9: 0 | R9: =Q9/$P9 -> 0 | S9: 0 | T9: =S9/$P9 -> 0 | U9: 0 | V9: =U9/$P9 -> 0 | W9: 0 | X9: =W9/$P9 -> 0 | Y9: 0 | Z9: =Y9/$P9 -> 0 | AA9: 0 | AB9: =AA9/$P9 -> 0 | AC9: =Q9+S9+U9+W9+Y9+AA9 -> 0 | AD9: =AC9/$P9 -> 0 | AE9: 0 | AF9: =AE9/$P9 -> 0 | AG9: 0 | AH9: =AG9/$P9 -> 0 | AI9: 0 | AJ9: =AI9/$P9 -> 0 | AK9: 0 | AL9: =AK9/$P9 -> 0 | AM9: 0 | AN9: =AM9/$P9 -> 0 | AO9: 0 | AP9: =AO9/$P9 -> 0 | AQ9: =AE9+AG9+AI9+AK9+AM9+AO9 -> 0 | AR9: =AQ9/$P9 -> 0 | AS9: 0 | AT9: =AS9/$P9 -> 0 | AU9: 0 | AV9: =AU9/$P9 -> 0 | AW9: 0 | AX9: =AW9/$P9 -> 0 | AY9: 0 | AZ9: =AY9/$P9 -> 0 | BA9: 0 | BB9: =BA9/$P9 -> 0 | BC9: 0 | BD9: =BC9/$P9 -> 0 | BE9: =AS9+AU9+AW9+AY9+BA9+BC9 -> 0 | BF9: =BE9/$P9 -> 0 | BG9: 0 | BH9: =BG9/$P9 -> 0 | BI9: 0 | BJ9: =BI9/$P9 -> 0 | BK9: 0 | BL9: =BK9/$P9 -> 0 | BM9: 0 | BN9: =BM9/$P9 -> 0 | BO9: 0 | BP9: =BO9/$P9 -> 0 | BQ9: 0 | BR9: =BQ9/$P9 -> 0 | BS9: =BG9+BI9+BK9+BM9+BO9+BQ9 -> 0 | BT9: =BS9/$P9 -> 0 | BU9: 0 | BV9: =BU9/$P9 -> 0 | BW9: 0 | BX9: =BW9/$P9 -> 0 | BY9: 0 | BZ9: =BY9/$P9 -> 0 | CA9: 0 | CB9: =CA9/$P9 -> 0 | CC9: 0 | CD9: =CC9/$P9 -> 0 | CE9: 0 | CF9: =CE9/$P9 -> 0 | CG9: =BU9+BW9+BY9+CA9+CC9+CE9 -> 0 | CH9: =CG9/$P9 -> 0 | CI9: 0 | CJ9: =CI9/$P9 -> 0 | CK9: 0 | CL9: =CK9/$P9 -> 0 | CM9: 0 | CN9: =CM9/$P9 -> 0 | CO9: 0 | CP9: =CO9/$P9 -> 0 | CQ9: 0 | CR9: =CQ9/$P9 -> 0 | CS9: 0 | CT9: =CS9/$P9 -> 0 | CU9: =CI9+CK9+CM9+CO9+CQ9+CS9 -> 0 | CV9: =CU9/$P9 -> 0
C10: 5 | D10: Muro escaleras (Blanco) | E10: =E8 -> 35 | F10: 1.8 | G10: =E10*F10 -> 63 | L10: =G10-K10 -> 63 | P10: =SUM(L10:O10) -> 63 | Q10: 0 | R10: =Q10/$P10 -> 0 | S10: 0 | T10: =S10/$P10 -> 0 | U10: 0 | V10: =U10/$P10 -> 0 | W10: 0 | X10: =W10/$P10 -> 0 | Y10: 0 | Z10: =Y10/$P10 -> 0 | AA10: 0 | AB10: =AA10/$P10 -> 0 | AC10: =Q10+S10+U10+W10+Y10+AA10 -> 0 | AD10: =AC10/$P10 -> 0 | AE10: 0 | AF10: =AE10/$P10 -> 0 | AG10: 0 | AH10: =AG10/$P10 -> 0 | AI10: 0 | AJ10: =AI10/$P10 -> 0 | AK10: 0 | AL10: =AK10/$P10 -> 0 | AM10: 0 | AN10: =AM10/$P10 -> 0 | AO10: 0 | AP10: =AO10/$P10 -> 0 | AQ10: =AE10+AG10+AI10+AK10+AM10+AO10 -> 0 | AR10: =AQ10/$P10 -> 0 | AS10: 0 | AT10: =AS10/$P10 -> 0 | AU10: 0 | AV10: =AU10/$P10 -> 0 | AW10: 0 | AX10: =AW10/$P10 -> 0 | AY10: 0 | AZ10: =AY10/$P10 -> 0 | BA10: 0 | BB10: =BA10/$P10 -> 0 | BC10: 0 | BD10: =BC10/$P10 -> 0 | BE10: =AS10+AU10+AW10+AY10+BA10+BC10 -> 0 | BF10: =BE10/$P10 -> 0 | BG10: 0 | BH10: =BG10/$P10 -> 0 | BI10: 0 | BJ10: =BI10/$P10 -> 0 | BK10: 0 | BL10: =BK10/$P10 -> 0 | BM10: 0 | BN10: =BM10/$P10 -> 0 | BO10: 0 | BP10: =BO10/$P10 -> 0 | BQ10: 0 | BR10: =BQ10/$P10 -> 0 | BS10: =BG10+BI10+BK10+BM10+BO10+BQ10 -> 0 | BT10: =BS10/$P10 -> 0 | BU10: 0 | BV10: =BU10/$P10 -> 0 | BW10: 0 | BX10: =BW10/$P10 -> 0 | BY10: 0 | BZ10: =BY10/$P10 -> 0 | CA10: 0 | CB10: =CA10/$P10 -> 0 | CC10: 0 | CD10: =CC10/$P10 -> 0 | CE10: 0 | CF10: =CE10/$P10 -> 0 | CG10: =BU10+BW10+BY10+CA10+CC10+CE10 -> 0 | CH10: =CG10/$P10 -> 0 | CI10: 0 | CJ10: =CI10/$P10 -> 0 | CK10: 0 | CL10: =CK10/$P10 -> 0 | CM10: 0 | CN10: =CM10/$P10 -> 0 | CO10: 0 | CP10: =CO10/$P10 -> 0 | CQ10: 0 | CR10: =CQ10/$P10 -> 0 | CS10: 0 | CT10: =CS10/$P10 -> 0 | CU10: =CI10+CK10+CM10+CO10+CQ10+CS10 -> 0 | CV10: =CU10/$P10 -> 0
C11: 6 | D11: Muro escaleras (Blanco) | E11: =E8 -> 35 | F11: 2.05 | G11: =E11*F11 -> 71.75 | L11: =G11-K11 -> 71.75 | P11: =SUM(L11:O11) -> 71.75 | Q11: 0 | R11: =Q11/$P11 -> 0 | S11: 0 | T11: =S11/$P11 -> 0 | U11: 0 | V11: =U11/$P11 -> 0 | W11: 0 | X11: =W11/$P11 -> 0 | Y11: 0 | Z11: =Y11/$P11 -> 0 | AA11: 0 | AB11: =AA11/$P11 -> 0 | AC11: =Q11+S11+U11+W11+Y11+AA11 -> 0 | AD11: =AC11/$P11 -> 0 | AE11: 0 | AF11: =AE11/$P11 -> 0 | AG11: 0 | AH11: =AG11/$P11 -> 0 | AI11: 0 | AJ11: =AI11/$P11 -> 0 | AK11: 0 | AL11: =AK11/$P11 -> 0 | AM11: 0 | AN11: =AM11/$P11 -> 0 | AO11: 0 | AP11: =AO11/$P11 -> 0 | AQ11: =AE11+AG11+AI11+AK11+AM11+AO11 -> 0 | AR11: =AQ11/$P11 -> 0 | AS11: 0 | AT11: =AS11/$P11 -> 0 | AU11: 0 | AV11: =AU11/$P11 -> 0 | AW11: 0 | AX11: =AW11/$P11 -> 0 | AY11: 0 | AZ11: =AY11/$P11 -> 0 | BA11: 0 | BB11: =BA11/$P11 -> 0 | BC11: 0 | BD11: =BC11/$P11 -> 0 | BE11: =AS11+AU11+AW11+AY11+BA11+BC11 -> 0 | BF11: =BE11/$P11 -> 0 | BG11: 0 | BH11: =BG11/$P11 -> 0 | BI11: 0 | BJ11: =BI11/$P11 -> 0 | BK11: 0 | BL11: =BK11/$P11 -> 0 | BM11: 0 | BN11: =BM11/$P11 -> 0 | BO11: 0 | BP11: =BO11/$P11 -> 0 | BQ11: 0 | BR11: =BQ11/$P11 -> 0 | BS11: =BG11+BI11+BK11+BM11+BO11+BQ11 -> 0 | BT11: =BS11/$P11 -> 0 | BU11: 0 | BV11: =BU11/$P11 -> 0 | BW11: 0 | BX11: =BW11/$P11 -> 0 | BY11: 0 | BZ11: =BY11/$P11 -> 0 | CA11: 0 | CB11: =CA11/$P11 -> 0 | CC11: 0 | CD11: =CC11/$P11 -> 0 | CE11: 0 | CF11: =CE11/$P11 -> 0 | CG11: =BU11+BW11+BY11+CA11+CC11+CE11 -> 0 | CH11: =CG11/$P11 -> 0 | CI11: 0 | CJ11: =CI11/$P11 -> 0 | CK11: 0 | CL11: =CK11/$P11 -> 0 | CM11: 0 | CN11: =CM11/$P11 -> 0 | CO11: 0 | CP11: =CO11/$P11 -> 0 | CQ11: 0 | CR11: =CQ11/$P11 -> 0 | CS11: 0 | CT11: =CS11/$P11 -> 0 | CU11: =CI11+CK11+CM11+CO11+CQ11+CS11 -> 0 | CV11: =CU11/$P11 -> 0
C12: 7 | D12: Antepecho poseta PF (Blanco) (X14) | E12: 0.5 | F12: 1.44 | G12: =E12*F12*14 -> 10.08 | L12: =G12-K12 -> 10.08 | P12: =SUM(L12:O12) -> 10.08 | Q12: 0 | R12: =Q12/$P12 -> 0 | S12: 0 | T12: =S12/$P12 -> 0 | U12: 0 | V12: =U12/$P12 -> 0 | W12: 0 | X12: =W12/$P12 -> 0 | Y12: 0 | Z12: =Y12/$P12 -> 0 | AA12: 0 | AB12: =AA12/$P12 -> 0 | AC12: =Q12+S12+U12+W12+Y12+AA12 -> 0 | AD12: =AC12/$P12 -> 0 | AE12: 0 | AF12: =AE12/$P12 -> 0 | AG12: 0 | AH12: =AG12/$P12 -> 0 | AI12: 0 | AJ12: =AI12/$P12 -> 0 | AK12: 0 | AL12: =AK12/$P12 -> 0 | AM12: 0 | AN12: =AM12/$P12 -> 0 | AO12: 0 | AP12: =AO12/$P12 -> 0 | AQ12: =AE12+AG12+AI12+AK12+AM12+AO12 -> 0 | AR12: =AQ12/$P12 -> 0 | AS12: 0 | AT12: =AS12/$P12 -> 0 | AU12: 0 | AV12: =AU12/$P12 -> 0 | AW12: 0 | AX12: =AW12/$P12 -> 0 | AY12: 0 | AZ12: =AY12/$P12 -> 0 | BA12: 0 | BB12: =BA12/$P12 -> 0 | BC12: 0 | BD12: =BC12/$P12 -> 0 | BE12: =AS12+AU12+AW12+AY12+BA12+BC12 -> 0 | BF12: =BE12/$P12 -> 0 | BG12: 0 | BH12: =BG12/$P12 -> 0 | BI12: 0 | BJ12: =BI12/$P12 -> 0 | BK12: 0 | BL12: =BK12/$P12 -> 0 | BM12: 0 | BN12: =BM12/$P12 -> 0 | BO12: 0 | BP12: =BO12/$P12 -> 0 | BQ12: 0 | BR12: =BQ12/$P12 -> 0 | BS12: =BG12+BI12+BK12+BM12+BO12+BQ12 -> 0 | BT12: =BS12/$P12 -> 0 | BU12: 0 | BV12: =BU12/$P12 -> 0 | BW12: 0 | BX12: =BW12/$P12 -> 0 | BY12: 0 | BZ12: =BY12/$P12 -> 0 | CA12: 0 | CB12: =CA12/$P12 -> 0 | CC12: 0 | CD12: =CC12/$P12 -> 0 | CE12: 0 | CF12: =CE12/$P12 -> 0 | CG12: =BU12+BW12+BY12+CA12+CC12+CE12 -> 0 | CH12: =CG12/$P12 -> 0 | CI12: 0 | CJ12: =CI12/$P12 -> 0 | CK12: 0 | CL12: =CK12/$P12 -> 0 | CM12: 0 | CN12: =CM12/$P12 -> 0 | CO12: 0 | CP12: =CO12/$P12 -> 0 | CQ12: 0 | CR12: =CQ12/$P12 -> 0 | CS12: 0 | CT12: =CS12/$P12 -> 0 | CU12: =CI12+CK12+CM12+CO12+CQ12+CS12 -> 0 | CV12: =CU12/$P12 -> 0
C13: 8 | D13: Muro escaleras (Blanco) | E13: 35 | F13: 5.18 | G13: =E13*F13 -> 181.3 | H13: 0.25 | I13: 3.1 | J13: 14 | K13: =(H13*I13)*J13 -> 10.85 | L13: =G13-K13 -> 170.45 | P13: =SUM(L13:O13) -> 170.45 | Q13: 0 | R13: =Q13/$P13 -> 0 | S13: 0 | T13: =S13/$P13 -> 0 | U13: 0 | V13: =U13/$P13 -> 0 | W13: 0 | X13: =W13/$P13 -> 0 | Y13: 0 | Z13: =Y13/$P13 -> 0 | AA13: 0 | AB13: =AA13/$P13 -> 0 | AC13: =Q13+S13+U13+W13+Y13+AA13 -> 0 | AD13: =AC13/$P13 -> 0 | AE13: 0 | AF13: =AE13/$P13 -> 0 | AG13: 0 | AH13: =AG13/$P13 -> 0 | AI13: 0 | AJ13: =AI13/$P13 -> 0 | AK13: 0 | AL13: =AK13/$P13 -> 0 | AM13: 0 | AN13: =AM13/$P13 -> 0 | AO13: 0 | AP13: =AO13/$P13 -> 0 | AQ13: =AE13+AG13+AI13+AK13+AM13+AO13 -> 0 | AR13: =AQ13/$P13 -> 0 | AS13: 0 | AT13: =AS13/$P13 -> 0 | AU13: 0 | AV13: =AU13/$P13 -> 0 | AW13: 0 | AX13: =AW13/$P13 -> 0 | AY13: 0 | AZ13: =AY13/$P13 -> 0 | BA13: 0 | BB13: =BA13/$P13 -> 0 | BC13: 0 | BD13: =BC13/$P13 -> 0 | BE13: =AS13+AU13+AW13+AY13+BA13+BC13 -> 0 | BF13: =BE13/$P13 -> 0 | BG13: 0 | BH13: =BG13/$P13 -> 0 | BI13: 0 | BJ13: =BI13/$P13 -> 0 | BK13: 0 | BL13: =BK13/$P13 -> 0 | BM13: 0 | BN13: =BM13/$P13 -> 0 | BO13: 0 | BP13: =BO13/$P13 -> 0 | BQ13: 0 | BR13: =BQ13/$P13 -> 0 | BS13: =BG13+BI13+BK13+BM13+BO13+BQ13 -> 0 | BT13: =BS13/$P13 -> 0 | BU13: 0 | BV13: =BU13/$P13 -> 0 | BW13: 0 | BX13: =BW13/$P13 -> 0 | BY13: 0 | BZ13: =BY13/$P13 -> 0 | CA13: 0 | CB13: =CA13/$P13 -> 0 | CC13: 0 | CD13: =CC13/$P13 -> 0 | CE13: 0 | CF13: =CE13/$P13 -> 0 | CG13: =BU13+BW13+BY13+CA13+CC13+CE13 -> 0 | CH13: =CG13/$P13 -> 0 | CI13: 0 | CJ13: =CI13/$P13 -> 0 | CK13: 0 | CL13: =CK13/$P13 -> 0 | CM13: 0 | CN13: =CM13/$P13 -> 0 | CO13: 0 | CP13: =CO13/$P13 -> 0 | CQ13: 0 | CR13: =CQ13/$P13 -> 0 | CS13: 0 | CT13: =CS13/$P13 -> 0 | CU13: =CI13+CK13+CM13+CO13+CQ13+CS13 -> 0 | CV13: =CU13/$P13 -> 0
C14: 8.1 | D14: Cielo raso escaleras (X14) | E14: 1 | F14: =2.15+1.44 -> 3.59 | G14: =E14*F14*14 -> 50.26 | O14: =G14 -> 50.26 | P14: =SUM(L14:O14) -> 50.26 | Q14: 0 | R14: =Q14/$P14 -> 0 | S14: 0 | T14: =S14/$P14 -> 0 | U14: 0 | V14: =U14/$P14 -> 0 | W14: 0 | X14: =W14/$P14 -> 0 | Y14: 0 | Z14: =Y14/$P14 -> 0 | AA14: 0 | AB14: =AA14/$P14 -> 0 | AC14: =Q14+S14+U14+W14+Y14+AA14 -> 0 | AD14: =AC14/$P14 -> 0 | AE14: 0 | AF14: =AE14/$P14 -> 0 | AG14: 0 | AH14: =AG14/$P14 -> 0 | AI14: 0 | AJ14: =AI14/$P14 -> 0 | AK14: 0 | AL14: =AK14/$P14 -> 0 | AM14: 0 | AN14: =AM14/$P14 -> 0 | AO14: 0 | AP14: =AO14/$P14 -> 0 | AQ14: =AE14+AG14+AI14+AK14+AM14+AO14 -> 0 | AR14: =AQ14/$P14 -> 0 | AS14: 0 | AT14: =AS14/$P14 -> 0 | AU14: 0 | AV14: =AU14/$P14 -> 0 | AW14: 0 | AX14: =AW14/$P14 -> 0 | AY14: 0 | AZ14: =AY14/$P14 -> 0 | BA14: 0 | BB14: =BA14/$P14 -> 0 | BC14: 0 | BD14: =BC14/$P14 -> 0 | BE14: =AS14+AU14+AW14+AY14+BA14+BC14 -> 0 | BF14: =BE14/$P14 -> 0 | BG14: 0 | BH14: =BG14/$P14 -> 0 | BI14: 0 | BJ14: =BI14/$P14 -> 0 | BK14: 0 | BL14: =BK14/$P14 -> 0 | BM14: 0 | BN14: =BM14/$P14 -> 0 | BO14: 0 | BP14: =BO14/$P14 -> 0 | BQ14: 0 | BR14: =BQ14/$P14 -> 0 | BS14: =BG14+BI14+BK14+BM14+BO14+BQ14 -> 0 | BT14: =BS14/$P14 -> 0 | BU14: 0 | BV14: =BU14/$P14 -> 0 | BW14: 0 | BX14: =BW14/$P14 -> 0 | BY14: 0 | BZ14: =BY14/$P14 -> 0 | CA14: 0 | CB14: =CA14/$P14 -> 0 | CC14: 0 | CD14: =CC14/$P14 -> 0 | CE14: 0 | CF14: =CE14/$P14 -> 0 | CG14: =BU14+BW14+BY14+CA14+CC14+CE14 -> 0 | CH14: =CG14/$P14 -> 0 | CI14: 0 | CJ14: =CI14/$P14 -> 0 | CK14: 0 | CL14: =CK14/$P14 -> 0 | CM14: 0 | CN14: =CM14/$P14 -> 0 | CO14: 0 | CP14: =CO14/$P14 -> 0 | CQ14: 0 | CR14: =CQ14/$P14 -> 0 | CS14: 0 | CT14: =CS14/$P14 -> 0 | CU14: =CI14+CK14+CM14+CO14+CQ14+CS14 -> 0 | CV14: =CU14/$P14 -> 0
C15: 9 | D15: Muro con ventana (Verde) | E15: =E5 -> 35.6 | F15: 5.3 | G15: =E15*F15 -> 188.68 | H15: 1.5 | I15: 1.2 | J15: 28 | K15: =(H15*I15)*J15 -> 50.4 | M15: =G15-K15 -> 138.28 | P15: =SUM(L15:O15) -> 138.28 | Q15: 0 | R15: =Q15/$P15 -> 0 | S15: 0 | T15: =S15/$P15 -> 0 | U15: 0 | V15: =U15/$P15 -> 0 | W15: 0 | X15: =W15/$P15 -> 0 | Y15: 0 | Z15: =Y15/$P15 -> 0 | AA15: 0 | AB15: =AA15/$P15 -> 0 | AC15: =Q15+S15+U15+W15+Y15+AA15 -> 0 | AD15: =AC15/$P15 -> 0 | AE15: 0 | AF15: =AE15/$P15 -> 0 | AG15: 0 | AH15: =AG15/$P15 -> 0 | AI15: 0 | AJ15: =AI15/$P15 -> 0 | AK15: 0 | AL15: =AK15/$P15 -> 0 | AM15: 0 | AN15: =AM15/$P15 -> 0 | AO15: 0 | AP15: =AO15/$P15 -> 0 | AQ15: =AE15+AG15+AI15+AK15+AM15+AO15 -> 0 | AR15: =AQ15/$P15 -> 0 | AS15: 0 | AT15: =AS15/$P15 -> 0 | AU15: 0 | AV15: =AU15/$P15 -> 0 | AW15: 0 | AX15: =AW15/$P15 -> 0 | AY15: 0 | AZ15: =AY15/$P15 -> 0 | BA15: 0 | BB15: =BA15/$P15 -> 0 | BC15: 0 | BD15: =BC15/$P15 -> 0 | BE15: =AS15+AU15+AW15+AY15+BA15+BC15 -> 0 | BF15: =BE15/$P15 -> 0 | BG15: 0 | BH15: =BG15/$P15 -> 0 | BI15: 0 | BJ15: =BI15/$P15 -> 0 | BK15: 0 | BL15: =BK15/$P15 -> 0 | BM15: 0 | BN15: =BM15/$P15 -> 0 | BO15: 0 | BP15: =BO15/$P15 -> 0 | BQ15: 0 | BR15: =BQ15/$P15 -> 0 | BS15: =BG15+BI15+BK15+BM15+BO15+BQ15 -> 0 | BT15: =BS15/$P15 -> 0 | BU15: 0 | BV15: =BU15/$P15 -> 0 | BW15: 0 | BX15: =BW15/$P15 -> 0 | BY15: 0 | BZ15: =BY15/$P15 -> 0 | CA15: 0 | CB15: =CA15/$P15 -> 0 | CC15: 0 | CD15: =CC15/$P15 -> 0 | CE15: 0 | CF15: =CE15/$P15 -> 0 | CG15: =BU15+BW15+BY15+CA15+CC15+CE15 -> 0 | CH15: =CG15/$P15 -> 0 | CI15: 0 | CJ15: =CI15/$P15 -> 0 | CK15: 0 | CL15: =CK15/$P15 -> 0 | CM15: 0 | CN15: =CM15/$P15 -> 0 | CO15: 0 | CP15: =CO15/$P15 -> 0 | CQ15: 0 | CR15: =CQ15/$P15 -> 0 | CS15: 0 | CT15: =CS15/$P15 -> 0 | CU15: =CI15+CK15+CM15+CO15+CQ15+CS15 -> 0 | CV15: =CU15/$P15 -> 0
C16: 10 | D16: Placa de balcón (Negro) (x14) | E16: 0.3 | F16: 2.91 | G16: =E16*F16*14 -> 12.222 | N16: =G16 -> 12.222 | P16: =SUM(L16:O16) -> 12.222 | Q16: 0 | R16: =Q16/$P16 -> 0 | S16: 0 | T16: =S16/$P16 -> 0 | U16: 0 | V16: =U16/$P16 -> 0 | W16: 0 | X16: =W16/$P16 -> 0 | Y16: 0 | Z16: =Y16/$P16 -> 0 | AA16: 0 | AB16: =AA16/$P16 -> 0 | AC16: =Q16+S16+U16+W16+Y16+AA16 -> 0 | AD16: =AC16/$P16 -> 0 | AE16: 0 | AF16: =AE16/$P16 -> 0 | AG16: 0 | AH16: =AG16/$P16 -> 0 | AI16: 0 | AJ16: =AI16/$P16 -> 0 | AK16: 0 | AL16: =AK16/$P16 -> 0 | AM16: 0 | AN16: =AM16/$P16 -> 0 | AO16: 0 | AP16: =AO16/$P16 -> 0 | AQ16: =AE16+AG16+AI16+AK16+AM16+AO16 -> 0 | AR16: =AQ16/$P16 -> 0 | AS16: 0 | AT16: =AS16/$P16 -> 0 | AU16: 0 | AV16: =AU16/$P16 -> 0 | AW16: 0 | AX16: =AW16/$P16 -> 0 | AY16: 0 | AZ16: =AY16/$P16 -> 0 | BA16: 0 | BB16: =BA16/$P16 -> 0 | BC16: 0 | BD16: =BC16/$P16 -> 0 | BE16: =AS16+AU16+AW16+AY16+BA16+BC16 -> 0 | BF16: =BE16/$P16 -> 0 | BG16: 0 | BH16: =BG16/$P16 -> 0 | BI16: 0 | BJ16: =BI16/$P16 -> 0 | BK16: 0 | BL16: =BK16/$P16 -> 0 | BM16: 0 | BN16: =BM16/$P16 -> 0 | BO16: 0 | BP16: =BO16/$P16 -> 0 | BQ16: 0 | BR16: =BQ16/$P16 -> 0 | BS16: =BG16+BI16+BK16+BM16+BO16+BQ16 -> 0 | BT16: =BS16/$P16 -> 0 | BU16: 0 | BV16: =BU16/$P16 -> 0 | BW16: 0 | BX16: =BW16/$P16 -> 0 | BY16: 0 | BZ16: =BY16/$P16 -> 0 | CA16: 0 | CB16: =CA16/$P16 -> 0 | CC16: 0 | CD16: =CC16/$P16 -> 0 | CE16: 0 | CF16: =CE16/$P16 -> 0 | CG16: =BU16+BW16+BY16+CA16+CC16+CE16 -> 0 | CH16: =CG16/$P16 -> 0 | CI16: 0 | CJ16: =CI16/$P16 -> 0 | CK16: 0 | CL16: =CK16/$P16 -> 0 | CM16: 0 | CN16: =CM16/$P16 -> 0 | CO16: 0 | CP16: =CO16/$P16 -> 0 | CQ16: 0 | CR16: =CQ16/$P16 -> 0 | CS16: 0 | CT16: =CS16/$P16 -> 0 | CU16: =CI16+CK16+CM16+CO16+CQ16+CS16 -> 0 | CV16: =CU16/$P16 -> 0
C17: 10.1 | D17: Cielo raso balcón (X14) | E17: 0.6 | F17: 1.71 | G17: =E17*F17*14 -> 14.364 | O17: =G17 -> 14.364 | P17: =SUM(L17:O17) -> 14.364 | Q17: 0 | R17: =Q17/$P17 -> 0 | S17: 0 | T17: =S17/$P17 -> 0 | U17: 0 | V17: =U17/$P17 -> 0 | W17: 0 | X17: =W17/$P17 -> 0 | Y17: 0 | Z17: =Y17/$P17 -> 0 | AA17: 0 | AB17: =AA17/$P17 -> 0 | AC17: =Q17+S17+U17+W17+Y17+AA17 -> 0 | AD17: =AC17/$P17 -> 0 | AE17: 0 | AF17: =AE17/$P17 -> 0 | AG17: 0 | AH17: =AG17/$P17 -> 0 | AI17: 0 | AJ17: =AI17/$P17 -> 0 | AK17: 0 | AL17: =AK17/$P17 -> 0 | AM17: 0 | AN17: =AM17/$P17 -> 0 | AO17: 0 | AP17: =AO17/$P17 -> 0 | AQ17: =AE17+AG17+AI17+AK17+AM17+AO17 -> 0 | AR17: =AQ17/$P17 -> 0 | AS17: 0 | AT17: =AS17/$P17 -> 0 | AU17: 0 | AV17: =AU17/$P17 -> 0 | AW17: 0 | AX17: =AW17/$P17 -> 0 | AY17: 0 | AZ17: =AY17/$P17 -> 0 | BA17: 0 | BB17: =BA17/$P17 -> 0 | BC17: 0 | BD17: =BC17/$P17 -> 0 | BE17: =AS17+AU17+AW17+AY17+BA17+BC17 -> 0 | BF17: =BE17/$P17 -> 0 | BG17: 0 | BH17: =BG17/$P17 -> 0 | BI17: 0 | BJ17: =BI17/$P17 -> 0 | BK17: 0 | BL17: =BK17/$P17 -> 0 | BM17: 0 | BN17: =BM17/$P17 -> 0 | BO17: 0 | BP17: =BO17/$P17 -> 0 | BQ17: 0 | BR17: =BQ17/$P17 -> 0 | BS17: =BG17+BI17+BK17+BM17+BO17+BQ17 -> 0 | BT17: =BS17/$P17 -> 0 | BU17: 0 | BV17: =BU17/$P17 -> 0 | BW17: 0 | BX17: =BW17/$P17 -> 0 | BY17: 0 | BZ17: =BY17/$P17 -> 0 | CA17: 0 | CB17: =CA17/$P17 -> 0 | CC17: 0 | CD17: =CC17/$P17 -> 0 | CE17: 0 | CF17: =CE17/$P17 -> 0 | CG17: =BU17+BW17+BY17+CA17+CC17+CE17 -> 0 | CH17: =CG17/$P17 -> 0 | CI17: 0 | CJ17: =CI17/$P17 -> 0 | CK17: 0 | CL17: =CK17/$P17 -> 0 | CM17: 0 | CN17: =CM17/$P17 -> 0 | CO17: 0 | CP17: =CO17/$P17 -> 0 | CQ17: 0 | CR17: =CQ17/$P17 -> 0 | CS17: 0 | CT17: =CS17/$P17 -> 0 | CU17: =CI17+CK17+CM17+CO17+CQ17+CS17 -> 0 | CV17: =CU17/$P17 -> 0
C18: 11 | D18: Muro con ventana (Verde) | E18: =E5 -> 35.6 | F18: 4.62 | G18: =E18*F18 -> 164.472 | H18: 1 | I18: 0.75 | J18: 28 | K18: =(H18*I18)*J18 -> 21 | M18: =G18-K18 -> 143.472 | P18: =SUM(L18:O18) -> 143.472 | Q18: 0 | R18: =Q18/$P18 -> 0 | S18: 0 | T18: =S18/$P18 -> 0 | U18: 0 | V18: =U18/$P18 -> 0 | W18: 0 | X18: =W18/$P18 -> 0 | Y18: 0 | Z18: =Y18/$P18 -> 0 | AA18: 0 | AB18: =AA18/$P18 -> 0 | AC18: =Q18+S18+U18+W18+Y18+AA18 -> 0 | AD18: =AC18/$P18 -> 0 | AE18: 0 | AF18: =AE18/$P18 -> 0 | AG18: 0 | AH18: =AG18/$P18 -> 0 | AI18: 0 | AJ18: =AI18/$P18 -> 0 | AK18: 0 | AL18: =AK18/$P18 -> 0 | AM18: 0 | AN18: =AM18/$P18 -> 0 | AO18: 0 | AP18: =AO18/$P18 -> 0 | AQ18: =AE18+AG18+AI18+AK18+AM18+AO18 -> 0 | AR18: =AQ18/$P18 -> 0 | AS18: 0 | AT18: =AS18/$P18 -> 0 | AU18: 0 | AV18: =AU18/$P18 -> 0 | AW18: 0 | AX18: =AW18/$P18 -> 0 | AY18: 0 | AZ18: =AY18/$P18 -> 0 | BA18: 0 | BB18: =BA18/$P18 -> 0 | BC18: 0 | BD18: =BC18/$P18 -> 0 | BE18: =AS18+AU18+AW18+AY18+BA18+BC18 -> 0 | BF18: =BE18/$P18 -> 0 | BG18: 0 | BH18: =BG18/$P18 -> 0 | BI18: 0 | BJ18: =BI18/$P18 -> 0 | BK18: 0 | BL18: =BK18/$P18 -> 0 | BM18: 0 | BN18: =BM18/$P18 -> 0 | BO18: 0 | BP18: =BO18/$P18 -> 0 | BQ18: 0 | BR18: =BQ18/$P18 -> 0 | BS18: =BG18+BI18+BK18+BM18+BO18+BQ18 -> 0 | BT18: =BS18/$P18 -> 0 | BU18: 0 | BV18: =BU18/$P18 -> 0 | BW18: 0 | BX18: =BW18/$P18 -> 0 | BY18: 0 | BZ18: =BY18/$P18 -> 0 | CA18: 0 | CB18: =CA18/$P18 -> 0 | CC18: 0 | CD18: =CC18/$P18 -> 0 | CE18: 0 | CF18: =CE18/$P18 -> 0 | CG18: =BU18+BW18+BY18+CA18+CC18+CE18 -> 0 | CH18: =CG18/$P18 -> 0 | CI18: 0 | CJ18: =CI18/$P18 -> 0 | CK18: 0 | CL18: =CK18/$P18 -> 0 | CM18: 0 | CN18: =CM18/$P18 -> 0 | CO18: 0 | CP18: =CO18/$P18 -> 0 | CQ18: 0 | CR18: =CQ18/$P18 -> 0 | CS18: 0 | CT18: =CS18/$P18 -> 0 | CU18: =CI18+CK18+CM18+CO18+CQ18+CS18 -> 0 | CV18: =CU18/$P18 -> 0
C19: 12 | D19: Placa de balcón (Negro) (x14) | E19: 0.3 | F19: 2.91 | G19: =E19*F19*14 -> 12.222 | N19: =G19 -> 12.222 | P19: =SUM(L19:O19) -> 12.222 | Q19: 0 | R19: =Q19/$P19 -> 0 | S19: 0 | T19: =S19/$P19 -> 0 | U19: 0 | V19: =U19/$P19 -> 0 | W19: 0 | X19: =W19/$P19 -> 0 | Y19: 0 | Z19: =Y19/$P19 -> 0 | AA19: 0 | AB19: =AA19/$P19 -> 0 | AC19: =Q19+S19+U19+W19+Y19+AA19 -> 0 | AD19: =AC19/$P19 -> 0 | AE19: 0 | AF19: =AE19/$P19 -> 0 | AG19: 0 | AH19: =AG19/$P19 -> 0 | AI19: 0 | AJ19: =AI19/$P19 -> 0 | AK19: 0 | AL19: =AK19/$P19 -> 0 | AM19: 0 | AN19: =AM19/$P19 -> 0 | AO19: 0 | AP19: =AO19/$P19 -> 0 | AQ19: =AE19+AG19+AI19+AK19+AM19+AO19 -> 0 | AR19: =AQ19/$P19 -> 0 | AS19: 0 | AT19: =AS19/$P19 -> 0 | AU19: 0 | AV19: =AU19/$P19 -> 0 | AW19: 0 | AX19: =AW19/$P19 -> 0 | AY19: 0 | AZ19: =AY19/$P19 -> 0 | BA19: 0 | BB19: =BA19/$P19 -> 0 | BC19: 0 | BD19: =BC19/$P19 -> 0 | BE19: =AS19+AU19+AW19+AY19+BA19+BC19 -> 0 | BF19: =BE19/$P19 -> 0 | BG19: 0 | BH19: =BG19/$P19 -> 0 | BI19: 0 | BJ19: =BI19/$P19 -> 0 | BK19: 0 | BL19: =BK19/$P19 -> 0 | BM19: 0 | BN19: =BM19/$P19 -> 0 | BO19: 0 | BP19: =BO19/$P19 -> 0 | BQ19: 0 | BR19: =BQ19/$P19 -> 0 | BS19: =BG19+BI19+BK19+BM19+BO19+BQ19 -> 0 | BT19: =BS19/$P19 -> 0 | BU19: 0 | BV19: =BU19/$P19 -> 0 | BW19: 0 | BX19: =BW19/$P19 -> 0 | BY19: 0 | BZ19: =BY19/$P19 -> 0 | CA19: 0 | CB19: =CA19/$P19 -> 0 | CC19: 0 | CD19: =CC19/$P19 -> 0 | CE19: 0 | CF19: =CE19/$P19 -> 0 | CG19: =BU19+BW19+BY19+CA19+CC19+CE19 -> 0 | CH19: =CG19/$P19 -> 0 | CI19: 0 | CJ19: =CI19/$P19 -> 0 | CK19: 0 | CL19: =CK19/$P19 -> 0 | CM19: 0 | CN19: =CM19/$P19 -> 0 | CO19: 0 | CP19: =CO19/$P19 -> 0 | CQ19: 0 | CR19: =CQ19/$P19 -> 0 | CS19: 0 | CT19: =CS19/$P19 -> 0 | CU19: =CI19+CK19+CM19+CO19+CQ19+CS19 -> 0 | CV19: =CU19/$P19 -> 0
C20: 12.1 | D20: Cielo raso balcón (X14) | E20: 0.6 | F20: 1.71 | G20: =E20*F20*14 -> 14.364 | O20: =G20 -> 14.364 | P20: =SUM(L20:O20) -> 14.364 | Q20: 0 | R20: =Q20/$P20 -> 0 | S20: 0 | T20: =S20/$P20 -> 0 | U20: 0 | V20: =U20/$P20 -> 0 | W20: 0 | X20: =W20/$P20 -> 0 | Y20: 0 | Z20: =Y20/$P20 -> 0 | AA20: 0 | AB20: =AA20/$P20 -> 0 | AC20: =Q20+S20+U20+W20+Y20+AA20 -> 0 | AD20: =AC20/$P20 -> 0 | AE20: 0 | AF20: =AE20/$P20 -> 0 | AG20: 0 | AH20: =AG20/$P20 -> 0 | AI20: 0 | AJ20: =AI20/$P20 -> 0 | AK20: 0 | AL20: =AK20/$P20 -> 0 | AM20: 0 | AN20: =AM20/$P20 -> 0 | AO20: 0 | AP20: =AO20/$P20 -> 0 | AQ20: =AE20+AG20+AI20+AK20+AM20+AO20 -> 0 | AR20: =AQ20/$P20 -> 0 | AS20: 0 | AT20: =AS20/$P20 -> 0 | AU20: 0 | AV20: =AU20/$P20 -> 0 | AW20: 0 | AX20: =AW20/$P20 -> 0 | AY20: 0 | AZ20: =AY20/$P20 -> 0 | BA20: 0 | BB20: =BA20/$P20 -> 0 | BC20: 0 | BD20: =BC20/$P20 -> 0 | BE20: =AS20+AU20+AW20+AY20+BA20+BC20 -> 0 | BF20: =BE20/$P20 -> 0 | BG20: 0 | BH20: =BG20/$P20 -> 0 | BI20: 0 | BJ20: =BI20/$P20 -> 0 | BK20: 0 | BL20: =BK20/$P20 -> 0 | BM20: 0 | BN20: =BM20/$P20 -> 0 | BO20: 0 | BP20: =BO20/$P20 -> 0 | BQ20: 0 | BR20: =BQ20/$P20 -> 0 | BS20: =BG20+BI20+BK20+BM20+BO20+BQ20 -> 0 | BT20: =BS20/$P20 -> 0 | BU20: 0 | BV20: =BU20/$P20 -> 0 | BW20: 0 | BX20: =BW20/$P20 -> 0 | BY20: 0 | BZ20: =BY20/$P20 -> 0 | CA20: 0 | CB20: =CA20/$P20 -> 0 | CC20: 0 | CD20: =CC20/$P20 -> 0 | CE20: 0 | CF20: =CE20/$P20 -> 0 | CG20: =BU20+BW20+BY20+CA20+CC20+CE20 -> 0 | CH20: =CG20/$P20 -> 0 | CI20: 0 | CJ20: =CI20/$P20 -> 0 | CK20: 0 | CL20: =CK20/$P20 -> 0 | CM20: 0 | CN20: =CM20/$P20 -> 0 | CO20: 0 | CP20: =CO20/$P20 -> 0 | CQ20: 0 | CR20: =CQ20/$P20 -> 0 | CS20: 0 | CT20: =CS20/$P20 -> 0 | CU20: =CI20+CK20+CM20+CO20+CQ20+CS20 -> 0 | CV20: =CU20/$P20 -> 0
C21: 13 | D21: Muro con ventana (Blanco) | E21: =E5 -> 35.6 | F21: 5.3 | G21: =E21*F21 -> 188.68 | H21: 1.5 | I21: 1.2 | J21: 28 | K21: =(H21*I21)*J21 -> 50.4 | L21: =G21-K21 -> 138.28 | P21: =SUM(L21:O21) -> 138.28 | Q21: 0 | R21: =Q21/$P21 -> 0 | S21: 0 | T21: =S21/$P21 -> 0 | U21: 0 | V21: =U21/$P21 -> 0 | W21: 0 | X21: =W21/$P21 -> 0 | Y21: 0 | Z21: =Y21/$P21 -> 0 | AA21: 0 | AB21: =AA21/$P21 -> 0 | AC21: =Q21+S21+U21+W21+Y21+AA21 -> 0 | AD21: =AC21/$P21 -> 0 | AE21: 0 | AF21: =AE21/$P21 -> 0 | AG21: 0 | AH21: =AG21/$P21 -> 0 | AI21: 0 | AJ21: =AI21/$P21 -> 0 | AK21: 0 | AL21: =AK21/$P21 -> 0 | AM21: 0 | AN21: =AM21/$P21 -> 0 | AO21: 0 | AP21: =AO21/$P21 -> 0 | AQ21: =AE21+AG21+AI21+AK21+AM21+AO21 -> 0 | AR21: =AQ21/$P21 -> 0 | AS21: 0 | AT21: =AS21/$P21 -> 0 | AU21: 0 | AV21: =AU21/$P21 -> 0 | AW21: 0 | AX21: =AW21/$P21 -> 0 | AY21: 0 | AZ21: =AY21/$P21 -> 0 | BA21: 0 | BB21: =BA21/$P21 -> 0 | BC21: 0 | BD21: =BC21/$P21 -> 0 | BE21: =AS21+AU21+AW21+AY21+BA21+BC21 -> 0 | BF21: =BE21/$P21 -> 0 | BG21: 0 | BH21: =BG21/$P21 -> 0 | BI21: 0 | BJ21: =BI21/$P21 -> 0 | BK21: 0 | BL21: =BK21/$P21 -> 0 | BM21: 0 | BN21: =BM21/$P21 -> 0 | BO21: 0 | BP21: =BO21/$P21 -> 0 | BQ21: 0 | BR21: =BQ21/$P21 -> 0 | BS21: =BG21+BI21+BK21+BM21+BO21+BQ21 -> 0 | BT21: =BS21/$P21 -> 0 | BU21: 0 | BV21: =BU21/$P21 -> 0 | BW21: 0 | BX21: =BW21/$P21 -> 0 | BY21: 0 | BZ21: =BY21/$P21 -> 0 | CA21: 0 | CB21: =CA21/$P21 -> 0 | CC21: 0 | CD21: =CC21/$P21 -> 0 | CE21: 0 | CF21: =CE21/$P21 -> 0 | CG21: =BU21+BW21+BY21+CA21+CC21+CE21 -> 0 | CH21: =CG21/$P21 -> 0 | CI21: 0 | CJ21: =CI21/$P21 -> 0 | CK21: 0 | CL21: =CK21/$P21 -> 0 | CM21: 0 | CN21: =CM21/$P21 -> 0 | CO21: 0 | CP21: =CO21/$P21 -> 0 | CQ21: 0 | CR21: =CQ21/$P21 -> 0 | CS21: 0 | CT21: =CS21/$P21 -> 0 | CU21: =CI21+CK21+CM21+CO21+CQ21+CS21 -> 0 | CV21: =CU21/$P21 -> 0
C22: 14 | D22: Muro escaleras (Blanco) | E22: 35 | F22: 4.8 | G22: =E22*F22 -> 168 | H22: 0.25 | I22: 3.1 | J22: 14 | K22: =(H22*I22)*J22 -> 10.85 | L22: =G22-K22 -> 157.15 | P22: =SUM(L22:O22) -> 157.15 | Q22: 0 | R22: =Q22/$P22 -> 0 | S22: 0 | T22: =S22/$P22 -> 0 | U22: 0 | V22: =U22/$P22 -> 0 | W22: 0 | X22: =W22/$P22 -> 0 | Y22: 0 | Z22: =Y22/$P22 -> 0 | AA22: 0 | AB22: =AA22/$P22 -> 0 | AC22: =Q22+S22+U22+W22+Y22+AA22 -> 0 | AD22: =AC22/$P22 -> 0 | AE22: 0 | AF22: =AE22/$P22 -> 0 | AG22: 0 | AH22: =AG22/$P22 -> 0 | AI22: 0 | AJ22: =AI22/$P22 -> 0 | AK22: 0 | AL22: =AK22/$P22 -> 0 | AM22: 0 | AN22: =AM22/$P22 -> 0 | AO22: 0 | AP22: =AO22/$P22 -> 0 | AQ22: =AE22+AG22+AI22+AK22+AM22+AO22 -> 0 | AR22: =AQ22/$P22 -> 0 | AS22: 0 | AT22: =AS22/$P22 -> 0 | AU22: 0 | AV22: =AU22/$P22 -> 0 | AW22: 0 | AX22: =AW22/$P22 -> 0 | AY22: 0 | AZ22: =AY22/$P22 -> 0 | BA22: 0 | BB22: =BA22/$P22 -> 0 | BC22: 0 | BD22: =BC22/$P22 -> 0 | BE22: =AS22+AU22+AW22+AY22+BA22+BC22 -> 0 | BF22: =BE22/$P22 -> 0 | BG22: 0 | BH22: =BG22/$P22 -> 0 | BI22: 0 | BJ22: =BI22/$P22 -> 0 | BK22: 0 | BL22: =BK22/$P22 -> 0 | BM22: 0 | BN22: =BM22/$P22 -> 0 | BO22: 0 | BP22: =BO22/$P22 -> 0 | BQ22: 0 | BR22: =BQ22/$P22 -> 0 | BS22: =BG22+BI22+BK22+BM22+BO22+BQ22 -> 0 | BT22: =BS22/$P22 -> 0 | BU22: 0 | BV22: =BU22/$P22 -> 0 | BW22: 0 | BX22: =BW22/$P22 -> 0 | BY22: 0 | BZ22: =BY22/$P22 -> 0 | CA22: 0 | CB22: =CA22/$P22 -> 0 | CC22: 0 | CD22: =CC22/$P22 -> 0 | CE22: 0 | CF22: =CE22/$P22 -> 0 | CG22: =BU22+BW22+BY22+CA22+CC22+CE22 -> 0 | CH22: =CG22/$P22 -> 0 | CI22: 0 | CJ22: =CI22/$P22 -> 0 | CK22: 0 | CL22: =CK22/$P22 -> 0 | CM22: 0 | CN22: =CM22/$P22 -> 0 | CO22: 0 | CP22: =CO22/$P22 -> 0 | CQ22: 0 | CR22: =CQ22/$P22 -> 0 | CS22: 0 | CT22: =CS22/$P22 -> 0 | CU22: =CI22+CK22+CM22+CO22+CQ22+CS22 -> 0 | CV22: =CU22/$P22 -> 0
C23: 15 | D23: Muro escaleras (Blanco) | E23: 35 | F23: 2.15 | G23: =E23*F23 -> 75.25 | L23: =G23-K23 -> 75.25 | P23: =SUM(L23:O23) -> 75.25 | Q23: 0 | R23: =Q23/$P23 -> 0 | S23: 0 | T23: =S23/$P23 -> 0 | U23: 0 | V23: =U23/$P23 -> 0 | W23: 0 | X23: =W23/$P23 -> 0 | Y23: 0 | Z23: =Y23/$P23 -> 0 | AA23: 0 | AB23: =AA23/$P23 -> 0 | AC23: =Q23+S23+U23+W23+Y23+AA23 -> 0 | AD23: =AC23/$P23 -> 0 | AE23: 0 | AF23: =AE23/$P23 -> 0 | AG23: 0 | AH23: =AG23/$P23 -> 0 | AI23: 0 | AJ23: =AI23/$P23 -> 0 | AK23: 0 | AL23: =AK23/$P23 -> 0 | AM23: 0 | AN23: =AM23/$P23 -> 0 | AO23: 0 | AP23: =AO23/$P23 -> 0 | AQ23: =AE23+AG23+AI23+AK23+AM23+AO23 -> 0 | AR23: =AQ23/$P23 -> 0 | AS23: 0 | AT23: =AS23/$P23 -> 0 | AU23: 0 | AV23: =AU23/$P23 -> 0 | AW23: 0 | AX23: =AW23/$P23 -> 0 | AY23: 0 | AZ23: =AY23/$P23 -> 0 | BA23: 0 | BB23: =BA23/$P23 -> 0 | BC23: 0 | BD23: =BC23/$P23 -> 0 | BE23: =AS23+AU23+AW23+AY23+BA23+BC23 -> 0 | BF23: =BE23/$P23 -> 0 | BG23: 0 | BH23: =BG23/$P23 -> 0 | BI23: 0 | BJ23: =BI23/$P23 -> 0 | BK23: 0 | BL23: =BK23/$P23 -> 0 | BM23: 0 | BN23: =BM23/$P23 -> 0 | BO23: 0 | BP23: =BO23/$P23 -> 0 | BQ23: 0 | BR23: =BQ23/$P23 -> 0 | BS23: =BG23+BI23+BK23+BM23+BO23+BQ23 -> 0 | BT23: =BS23/$P23 -> 0 | BU23: 0 | BV23: =BU23/$P23 -> 0 | BW23: 0 | BX23: =BW23/$P23 -> 0 | BY23: 0 | BZ23: =BY23/$P23 -> 0 | CA23: 0 | CB23: =CA23/$P23 -> 0 | CC23: 0 | CD23: =CC23/$P23 -> 0 | CE23: 0 | CF23: =CE23/$P23 -> 0 | CG23: =BU23+BW23+BY23+CA23+CC23+CE23 -> 0 | CH23: =CG23/$P23 -> 0 | CI23: 0 | CJ23: =CI23/$P23 -> 0 | CK23: 0 | CL23: =CK23/$P23 -> 0 | CM23: 0 | CN23: =CM23/$P23 -> 0 | CO23: 0 | CP23: =CO23/$P23 -> 0 | CQ23: 0 | CR23: =CQ23/$P23 -> 0 | CS23: 0 | CT23: =CS23/$P23 -> 0 | CU23: =CI23+CK23+CM23+CO23+CQ23+CS23 -> 0 | CV23: =CU23/$P23 -> 0
C24: 16 | D24: Muro escaleras (Blanco) | E24: 35 | F24: 1.42 | G24: =E24*F24 -> 49.7 | H24: 0.25 | I24: 3.1 | J24: 14 | K24: =(H24*I24)*J24 -> 10.85 | L24: =G24-K24 -> 38.85 | P24: =SUM(L24:O24) -> 38.85 | Q24: 0 | R24: =Q24/$P24 -> 0 | S24: 0 | T24: =S24/$P24 -> 0 | U24: 0 | V24: =U24/$P24 -> 0 | W24: 0 | X24: =W24/$P24 -> 0 | Y24: 0 | Z24: =Y24/$P24 -> 0 | AA24: 0 | AB24: =AA24/$P24 -> 0 | AC24: =Q24+S24+U24+W24+Y24+AA24 -> 0 | AD24: =AC24/$P24 -> 0 | AE24: 0 | AF24: =AE24/$P24 -> 0 | AG24: 0 | AH24: =AG24/$P24 -> 0 | AI24: 0 | AJ24: =AI24/$P24 -> 0 | AK24: 0 | AL24: =AK24/$P24 -> 0 | AM24: 0 | AN24: =AM24/$P24 -> 0 | AO24: 0 | AP24: =AO24/$P24 -> 0 | AQ24: =AE24+AG24+AI24+AK24+AM24+AO24 -> 0 | AR24: =AQ24/$P24 -> 0 | AS24: 0 | AT24: =AS24/$P24 -> 0 | AU24: 0 | AV24: =AU24/$P24 -> 0 | AW24: 0 | AX24: =AW24/$P24 -> 0 | AY24: 0 | AZ24: =AY24/$P24 -> 0 | BA24: 0 | BB24: =BA24/$P24 -> 0 | BC24: 0 | BD24: =BC24/$P24 -> 0 | BE24: =AS24+AU24+AW24+AY24+BA24+BC24 -> 0 | BF24: =BE24/$P24 -> 0 | BG24: 0 | BH24: =BG24/$P24 -> 0 | BI24: 0 | BJ24: =BI24/$P24 -> 0 | BK24: 0 | BL24: =BK24/$P24 -> 0 | BM24: 0 | BN24: =BM24/$P24 -> 0 | BO24: 0 | BP24: =BO24/$P24 -> 0 | BQ24: 0 | BR24: =BQ24/$P24 -> 0 | BS24: =BG24+BI24+BK24+BM24+BO24+BQ24 -> 0 | BT24: =BS24/$P24 -> 0 | BU24: 0 | BV24: =BU24/$P24 -> 0 | BW24: 0 | BX24: =BW24/$P24 -> 0 | BY24: 0 | BZ24: =BY24/$P24 -> 0 | CA24: 0 | CB24: =CA24/$P24 -> 0 | CC24: 0 | CD24: =CC24/$P24 -> 0 | CE24: 0 | CF24: =CE24/$P24 -> 0 | CG24: =BU24+BW24+BY24+CA24+CC24+CE24 -> 0 | CH24: =CG24/$P24 -> 0 | CI24: 0 | CJ24: =CI24/$P24 -> 0 | CK24: 0 | CL24: =CK24/$P24 -> 0 | CM24: 0 | CN24: =CM24/$P24 -> 0 | CO24: 0 | CP24: =CO24/$P24 -> 0 | CQ24: 0 | CR24: =CQ24/$P24 -> 0 | CS24: 0 | CT24: =CS24/$P24 -> 0 | CU24: =CI24+CK24+CM24+CO24+CQ24+CS24 -> 0 | CV24: =CU24/$P24 -> 0
C25: 16.1 | D25: Cielo raso balcón (X14) | E25: 1 | F25: 1.9 | G25: =E25*F25*14 -> 26.6 | O25: =G25 -> 26.6 | P25: =SUM(L25:O25) -> 26.6 | Q25: 0 | R25: =Q25/$P25 -> 0 | S25: 0 | T25: =S25/$P25 -> 0 | U25: 0 | V25: =U25/$P25 -> 0 | W25: 0 | X25: =W25/$P25 -> 0 | Y25: 0 | Z25: =Y25/$P25 -> 0 | AA25: 0 | AB25: =AA25/$P25 -> 0 | AC25: =Q25+S25+U25+W25+Y25+AA25 -> 0 | AD25: =AC25/$P25 -> 0 | AE25: 0 | AF25: =AE25/$P25 -> 0 | AG25: 0 | AH25: =AG25/$P25 -> 0 | AI25: 0 | AJ25: =AI25/$P25 -> 0 | AK25: 0 | AL25: =AK25/$P25 -> 0 | AM25: 0 | AN25: =AM25/$P25 -> 0 | AO25: 0 | AP25: =AO25/$P25 -> 0 | AQ25: =AE25+AG25+AI25+AK25+AM25+AO25 -> 0 | AR25: =AQ25/$P25 -> 0 | AS25: 0 | AT25: =AS25/$P25 -> 0 | AU25: 0 | AV25: =AU25/$P25 -> 0 | AW25: 0 | AX25: =AW25/$P25 -> 0 | AY25: 0 | AZ25: =AY25/$P25 -> 0 | BA25: 0 | BB25: =BA25/$P25 -> 0 | BC25: 0 | BD25: =BC25/$P25 -> 0 | BE25: =AS25+AU25+AW25+AY25+BA25+BC25 -> 0 | BF25: =BE25/$P25 -> 0 | BG25: 0 | BH25: =BG25/$P25 -> 0 | BI25: 0 | BJ25: =BI25/$P25 -> 0 | BK25: 0 | BL25: =BK25/$P25 -> 0 | BM25: 0 | BN25: =BM25/$P25 -> 0 | BO25: 0 | BP25: =BO25/$P25 -> 0 | BQ25: 0 | BR25: =BQ25/$P25 -> 0 | BS25: =BG25+BI25+BK25+BM25+BO25+BQ25 -> 0 | BT25: =BS25/$P25 -> 0 | BU25: 0 | BV25: =BU25/$P25 -> 0 | BW25: 0 | BX25: =BW25/$P25 -> 0 | BY25: 0 | BZ25: =BY25/$P25 -> 0 | CA25: 0 | CB25: =CA25/$P25 -> 0 | CC25: 0 | CD25: =CC25/$P25 -> 0 | CE25: 0 | CF25: =CE25/$P25 -> 0 | CG25: =BU25+BW25+BY25+CA25+CC25+CE25 -> 0 | CH25: =CG25/$P25 -> 0 | CI25: 0 | CJ25: =CI25/$P25 -> 0 | CK25: 0 | CL25: =CK25/$P25 -> 0 | CM25: 0 | CN25: =CM25/$P25 -> 0 | CO25: 0 | CP25: =CO25/$P25 -> 0 | CQ25: 0 | CR25: =CQ25/$P25 -> 0 | CS25: 0 | CT25: =CS25/$P25 -> 0 | CU25: =CI25+CK25+CM25+CO25+CQ25+CS25 -> 0 | CV25: =CU25/$P25 -> 0
B26: CULATA DER | C26: 17 | D26: Muro sin ventanas (Blanco) | E26: 35 | F26: 1.67 | G26: =E26*F26 -> 58.45 | L26: =G26-K26 -> 58.45 | P26: =SUM(L26:O26) -> 58.45 | Q26: 0 | R26: =Q26/$P26 -> 0 | S26: 0 | T26: =S26/$P26 -> 0 | U26: 0 | V26: =U26/$P26 -> 0 | W26: 0 | X26: =W26/$P26 -> 0 | Y26: 0 | Z26: =Y26/$P26 -> 0 | AA26: 0 | AB26: =AA26/$P26 -> 0 | AC26: =Q26+S26+U26+W26+Y26+AA26 -> 0 | AD26: =AC26/$P26 -> 0 | AE26: 0 | AF26: =AE26/$P26 -> 0 | AG26: 0 | AH26: =AG26/$P26 -> 0 | AI26: 0 | AJ26: =AI26/$P26 -> 0 | AK26: 0 | AL26: =AK26/$P26 -> 0 | AM26: 0 | AN26: =AM26/$P26 -> 0 | AO26: 0 | AP26: =AO26/$P26 -> 0 | AQ26: =AE26+AG26+AI26+AK26+AM26+AO26 -> 0 | AR26: =AQ26/$P26 -> 0 | AS26: 0 | AT26: =AS26/$P26 -> 0 | AU26: 0 | AV26: =AU26/$P26 -> 0 | AW26: 0 | AX26: =AW26/$P26 -> 0 | AY26: 0 | AZ26: =AY26/$P26 -> 0 | BA26: 0 | BB26: =BA26/$P26 -> 0 | BC26: 0 | BD26: =BC26/$P26 -> 0 | BE26: =AS26+AU26+AW26+AY26+BA26+BC26 -> 0 | BF26: =BE26/$P26 -> 0 | BG26: 0 | BH26: =BG26/$P26 -> 0 | BI26: 0 | BJ26: =BI26/$P26 -> 0 | BK26: 0 | BL26: =BK26/$P26 -> 0 | BM26: 0 | BN26: =BM26/$P26 -> 0 | BO26: 0 | BP26: =BO26/$P26 -> 0 | BQ26: 0 | BR26: =BQ26/$P26 -> 0 | BS26: =BG26+BI26+BK26+BM26+BO26+BQ26 -> 0 | BT26: =BS26/$P26 -> 0 | BU26: 0 | BV26: =BU26/$P26 -> 0 | BW26: 0 | BX26: =BW26/$P26 -> 0 | BY26: 0 | BZ26: =BY26/$P26 -> 0 | CA26: 0 | CB26: =CA26/$P26 -> 0 | CC26: 0 | CD26: =CC26/$P26 -> 0 | CE26: 0 | CF26: =CE26/$P26 -> 0 | CG26: =BU26+BW26+BY26+CA26+CC26+CE26 -> 0 | CH26: =CG26/$P26 -> 0 | CI26: 0 | CJ26: =CI26/$P26 -> 0 | CK26: 0 | CL26: =CK26/$P26 -> 0 | CM26: 0 | CN26: =CM26/$P26 -> 0 | CO26: 0 | CP26: =CO26/$P26 -> 0 | CQ26: 0 | CR26: =CQ26/$P26 -> 0 | CS26: 0 | CT26: =CS26/$P26 -> 0 | CU26: =CI26+CK26+CM26+CO26+CQ26+CS26 -> 0 | CV26: =CU26/$P26 -> 0
C27: 18 | D27: Antepecho balcones (Negro) (X14) | E27: 0.5 | F27: 1.26 | G27: =E27*F27*14 -> 8.82 | N27: =G27-K27 -> 8.82 | P27: =SUM(L27:O27) -> 8.82 | Q27: 0 | R27: =Q27/$P27 -> 0 | S27: 0 | T27: =S27/$P27 -> 0 | U27: 0 | V27: =U27/$P27 -> 0 | W27: 0 | X27: =W27/$P27 -> 0 | Y27: 0 | Z27: =Y27/$P27 -> 0 | AA27: 0 | AB27: =AA27/$P27 -> 0 | AC27: =Q27+S27+U27+W27+Y27+AA27 -> 0 | AD27: =AC27/$P27 -> 0 | AE27: 0 | AF27: =AE27/$P27 -> 0 | AG27: 0 | AH27: =AG27/$P27 -> 0 | AI27: 0 | AJ27: =AI27/$P27 -> 0 | AK27: 0 | AL27: =AK27/$P27 -> 0 | AM27: 0 | AN27: =AM27/$P27 -> 0 | AO27: 0 | AP27: =AO27/$P27 -> 0 | AQ27: =AE27+AG27+AI27+AK27+AM27+AO27 -> 0 | AR27: =AQ27/$P27 -> 0 | AS27: 0 | AT27: =AS27/$P27 -> 0 | AU27: 0 | AV27: =AU27/$P27 -> 0 | AW27: 0 | AX27: =AW27/$P27 -> 0 | AY27: 0 | AZ27: =AY27/$P27 -> 0 | BA27: 0 | BB27: =BA27/$P27 -> 0 | BC27: 0 | BD27: =BC27/$P27 -> 0 | BE27: =AS27+AU27+AW27+AY27+BA27+BC27 -> 0 | BF27: =BE27/$P27 -> 0 | BG27: 0 | BH27: =BG27/$P27 -> 0 | BI27: 0 | BJ27: =BI27/$P27 -> 0 | BK27: 0 | BL27: =BK27/$P27 -> 0 | BM27: 0 | BN27: =BM27/$P27 -> 0 | BO27: 0 | BP27: =BO27/$P27 -> 0 | BQ27: 0 | BR27: =BQ27/$P27 -> 0 | BS27: =BG27+BI27+BK27+BM27+BO27+BQ27 -> 0 | BT27: =BS27/$P27 -> 0 | BU27: 0 | BV27: =BU27/$P27 -> 0 | BW27: 0 | BX27: =BW27/$P27 -> 0 | BY27: 0 | BZ27: =BY27/$P27 -> 0 | CA27: 0 | CB27: =CA27/$P27 -> 0 | CC27: 0 | CD27: =CC27/$P27 -> 0 | CE27: 0 | CF27: =CE27/$P27 -> 0 | CG27: =BU27+BW27+BY27+CA27+CC27+CE27 -> 0 | CH27: =CG27/$P27 -> 0 | CI27: 0 | CJ27: =CI27/$P27 -> 0 | CK27: 0 | CL27: =CK27/$P27 -> 0 | CM27: 0 | CN27: =CM27/$P27 -> 0 | CO27: 0 | CP27: =CO27/$P27 -> 0 | CQ27: 0 | CR27: =CQ27/$P27 -> 0 | CS27: 0 | CT27: =CS27/$P27 -> 0 | CU27: =CI27+CK27+CM27+CO27+CQ27+CS27 -> 0 | CV27: =CU27/$P27 -> 0
C28: 19 | D28: Muro sin ventanas (Negro) | E28: =E5 -> 35.6 | F28: 2.5 | G28: =E28*F28 -> 89 | N28: =G28-K28 -> 89 | P28: =SUM(L28:O28) -> 89 | Q28: 0 | R28: =Q28/$P28 -> 0 | S28: 0 | T28: =S28/$P28 -> 0 | U28: 0 | V28: =U28/$P28 -> 0 | W28: 0 | X28: =W28/$P28 -> 0 | Y28: 0 | Z28: =Y28/$P28 -> 0 | AA28: 0 | AB28: =AA28/$P28 -> 0 | AC28: =Q28+S28+U28+W28+Y28+AA28 -> 0 | AD28: =AC28/$P28 -> 0 | AE28: 0 | AF28: =AE28/$P28 -> 0 | AG28: 0 | AH28: =AG28/$P28 -> 0 | AI28: 0 | AJ28: =AI28/$P28 -> 0 | AK28: 0 | AL28: =AK28/$P28 -> 0 | AM28: 0 | AN28: =AM28/$P28 -> 0 | AO28: 0 | AP28: =AO28/$P28 -> 0 | AQ28: =AE28+AG28+AI28+AK28+AM28+AO28 -> 0 | AR28: =AQ28/$P28 -> 0 | AS28: 0 | AT28: =AS28/$P28 -> 0 | AU28: 0 | AV28: =AU28/$P28 -> 0 | AW28: 0 | AX28: =AW28/$P28 -> 0 | AY28: 0 | AZ28: =AY28/$P28 -> 0 | BA28: 0 | BB28: =BA28/$P28 -> 0 | BC28: 0 | BD28: =BC28/$P28 -> 0 | BE28: =AS28+AU28+AW28+AY28+BA28+BC28 -> 0 | BF28: =BE28/$P28 -> 0 | BG28: 0 | BH28: =BG28/$P28 -> 0 | BI28: 0 | BJ28: =BI28/$P28 -> 0 | BK28: 0 | BL28: =BK28/$P28 -> 0 | BM28: 0 | BN28: =BM28/$P28 -> 0 | BO28: 0 | BP28: =BO28/$P28 -> 0 | BQ28: 0 | BR28: =BQ28/$P28 -> 0 | BS28: =BG28+BI28+BK28+BM28+BO28+BQ28 -> 0 | BT28: =BS28/$P28 -> 0 | BU28: 0 | BV28: =BU28/$P28 -> 0 | BW28: 0 | BX28: =BW28/$P28 -> 0 | BY28: 0 | BZ28: =BY28/$P28 -> 0 | CA28: 0 | CB28: =CA28/$P28 -> 0 | CC28: 0 | CD28: =CC28/$P28 -> 0 | CE28: 0 | CF28: =CE28/$P28 -> 0 | CG28: =BU28+BW28+BY28+CA28+CC28+CE28 -> 0 | CH28: =CG28/$P28 -> 0 | CI28: 0 | CJ28: =CI28/$P28 -> 0 | CK28: 0 | CL28: =CK28/$P28 -> 0 | CM28: 0 | CN28: =CM28/$P28 -> 0 | CO28: 0 | CP28: =CO28/$P28 -> 0 | CQ28: 0 | CR28: =CQ28/$P28 -> 0 | CS28: 0 | CT28: =CS28/$P28 -> 0 | CU28: =CI28+CK28+CM28+CO28+CQ28+CS28 -> 0 | CV28: =CU28/$P28 -> 0
C29: 20 | D29: Muro con ventanas (Blanco) | E29: =E5 -> 35.6 | F29: 2.33 | G29: =E29*F29 -> 82.948 | H29: 1 | I29: 0.75 | J29: 14 | K29: =(H29*I29)*J29 -> 10.5 | L29: =G29-K29 -> 72.448 | P29: =SUM(L29:O29) -> 72.448 | Q29: 0 | R29: =Q29/$P29 -> 0 | S29: 0 | T29: =S29/$P29 -> 0 | U29: 0 | V29: =U29/$P29 -> 0 | W29: 0 | X29: =W29/$P29 -> 0 | Y29: 0 | Z29: =Y29/$P29 -> 0 | AA29: 0 | AB29: =AA29/$P29 -> 0 | AC29: =Q29+S29+U29+W29+Y29+AA29 -> 0 | AD29: =AC29/$P29 -> 0 | AE29: 0 | AF29: =AE29/$P29 -> 0 | AG29: 0 | AH29: =AG29/$P29 -> 0 | AI29: 0 | AJ29: =AI29/$P29 -> 0 | AK29: 0 | AL29: =AK29/$P29 -> 0 | AM29: 0 | AN29: =AM29/$P29 -> 0 | AO29: 0 | AP29: =AO29/$P29 -> 0 | AQ29: =AE29+AG29+AI29+AK29+AM29+AO29 -> 0 | AR29: =AQ29/$P29 -> 0 | AS29: 0 | AT29: =AS29/$P29 -> 0 | AU29: 0 | AV29: =AU29/$P29 -> 0 | AW29: 0 | AX29: =AW29/$P29 -> 0 | AY29: 0 | AZ29: =AY29/$P29 -> 0 | BA29: 0 | BB29: =BA29/$P29 -> 0 | BC29: 0 | BD29: =BC29/$P29 -> 0 | BE29: =AS29+AU29+AW29+AY29+BA29+BC29 -> 0 | BF29: =BE29/$P29 -> 0 | BG29: 0 | BH29: =BG29/$P29 -> 0 | BI29: 0 | BJ29: =BI29/$P29 -> 0 | BK29: 0 | BL29: =BK29/$P29 -> 0 | BM29: 0 | BN29: =BM29/$P29 -> 0 | BO29: 0 | BP29: =BO29/$P29 -> 0 | BQ29: 0 | BR29: =BQ29/$P29 -> 0 | BS29: =BG29+BI29+BK29+BM29+BO29+BQ29 -> 0 | BT29: =BS29/$P29 -> 0 | BU29: 0 | BV29: =BU29/$P29 -> 0 | BW29: 0 | BX29: =BW29/$P29 -> 0 | BY29: 0 | BZ29: =BY29/$P29 -> 0 | CA29: 0 | CB29: =CA29/$P29 -> 0 | CC29: 0 | CD29: =CC29/$P29 -> 0 | CE29: 0 | CF29: =CE29/$P29 -> 0 | CG29: =BU29+BW29+BY29+CA29+CC29+CE29 -> 0 | CH29: =CG29/$P29 -> 0 | CI29: 0 | CJ29: =CI29/$P29 -> 0 | CK29: 0 | CL29: =CK29/$P29 -> 0 | CM29: 0 | CN29: =CM29/$P29 -> 0 | CO29: 0 | CP29: =CO29/$P29 -> 0 | CQ29: 0 | CR29: =CQ29/$P29 -> 0 | CS29: 0 | CT29: =CS29/$P29 -> 0 | CU29: =CI29+CK29+CM29+CO29+CQ29+CS29 -> 0 | CV29: =CU29/$P29 -> 0
C30: 21 | D30: Muro sin ventanas (Blanco) | E30: =E5 -> 35.6 | F30: 0.8 | G30: =E30*F30 -> 28.48 | L30: =G30-K30 -> 28.48 | P30: =SUM(L30:O30) -> 28.48 | Q30: 0 | R30: =Q30/$P30 -> 0 | S30: 0 | T30: =S30/$P30 -> 0 | U30: 0 | V30: =U30/$P30 -> 0 | W30: 0 | X30: =W30/$P30 -> 0 | Y30: 0 | Z30: =Y30/$P30 -> 0 | AA30: 0 | AB30: =AA30/$P30 -> 0 | AC30: =Q30+S30+U30+W30+Y30+AA30 -> 0 | AD30: =AC30/$P30 -> 0 | AE30: 0 | AF30: =AE30/$P30 -> 0 | AG30: 0 | AH30: =AG30/$P30 -> 0 | AI30: 0 | AJ30: =AI30/$P30 -> 0 | AK30: 0 | AL30: =AK30/$P30 -> 0 | AM30: 0 | AN30: =AM30/$P30 -> 0 | AO30: 0 | AP30: =AO30/$P30 -> 0 | AQ30: =AE30+AG30+AI30+AK30+AM30+AO30 -> 0 | AR30: =AQ30/$P30 -> 0 | AS30: 0 | AT30: =AS30/$P30 -> 0 | AU30: 0 | AV30: =AU30/$P30 -> 0 | AW30: 0 | AX30: =AW30/$P30 -> 0 | AY30: 0 | AZ30: =AY30/$P30 -> 0 | BA30: 0 | BB30: =BA30/$P30 -> 0 | BC30: 0 | BD30: =BC30/$P30 -> 0 | BE30: =AS30+AU30+AW30+AY30+BA30+BC30 -> 0 | BF30: =BE30/$P30 -> 0 | BG30: 0 | BH30: =BG30/$P30 -> 0 | BI30: 0 | BJ30: =BI30/$P30 -> 0 | BK30: 0 | BL30: =BK30/$P30 -> 0 | BM30: 0 | BN30: =BM30/$P30 -> 0 | BO30: 0 | BP30: =BO30/$P30 -> 0 | BQ30: 0 | BR30: =BQ30/$P30 -> 0 | BS30: =BG30+BI30+BK30+BM30+BO30+BQ30 -> 0 | BT30: =BS30/$P30 -> 0 | BU30: 0 | BV30: =BU30/$P30 -> 0 | BW30: 0 | BX30: =BW30/$P30 -> 0 | BY30: 0 | BZ30: =BY30/$P30 -> 0 | CA30: 0 | CB30: =CA30/$P30 -> 0 | CC30: 0 | CD30: =CC30/$P30 -> 0 | CE30: 0 | CF30: =CE30/$P30 -> 0 | CG30: =BU30+BW30+BY30+CA30+CC30+CE30 -> 0 | CH30: =CG30/$P30 -> 0 | CI30: 0 | CJ30: =CI30/$P30 -> 0 | CK30: 0 | CL30: =CK30/$P30 -> 0 | CM30: 0 | CN30: =CM30/$P30 -> 0 | CO30: 0 | CP30: =CO30/$P30 -> 0 | CQ30: 0 | CR30: =CQ30/$P30 -> 0 | CS30: 0 | CT30: =CS30/$P30 -> 0 | CU30: =CI30+CK30+CM30+CO30+CQ30+CS30 -> 0 | CV30: =CU30/$P30 -> 0
C31: 22 | D31: Muro con ventanas (Blanco) | E31: =E5 -> 35.6 | F31: 1.42 | G31: =E31*F31 -> 50.552 | H31: 0.3 | I31: 0.3 | J31: 14 | K31: =(H31*I31)*J31 -> 1.26 | L31: =G31-K31 -> 49.292 | P31: =SUM(L31:O31) -> 49.292 | Q31: 0 | R31: =Q31/$P31 -> 0 | S31: 0 | T31: =S31/$P31 -> 0 | U31: 0 | V31: =U31/$P31 -> 0 | W31: 0 | X31: =W31/$P31 -> 0 | Y31: 0 | Z31: =Y31/$P31 -> 0 | AA31: 0 | AB31: =AA31/$P31 -> 0 | AC31: =Q31+S31+U31+W31+Y31+AA31 -> 0 | AD31: =AC31/$P31 -> 0 | AE31: 0 | AF31: =AE31/$P31 -> 0 | AG31: 0 | AH31: =AG31/$P31 -> 0 | AI31: 0 | AJ31: =AI31/$P31 -> 0 | AK31: 0 | AL31: =AK31/$P31 -> 0 | AM31: 0 | AN31: =AM31/$P31 -> 0 | AO31: 0 | AP31: =AO31/$P31 -> 0 | AQ31: =AE31+AG31+AI31+AK31+AM31+AO31 -> 0 | AR31: =AQ31/$P31 -> 0 | AS31: 0 | AT31: =AS31/$P31 -> 0 | AU31: 0 | AV31: =AU31/$P31 -> 0 | AW31: 0 | AX31: =AW31/$P31 -> 0 | AY31: 0 | AZ31: =AY31/$P31 -> 0 | BA31: 0 | BB31: =BA31/$P31 -> 0 | BC31: 0 | BD31: =BC31/$P31 -> 0 | BE31: =AS31+AU31+AW31+AY31+BA31+BC31 -> 0 | BF31: =BE31/$P31 -> 0 | BG31: 0 | BH31: =BG31/$P31 -> 0 | BI31: 0 | BJ31: =BI31/$P31 -> 0 | BK31: 0 | BL31: =BK31/$P31 -> 0 | BM31: 0 | BN31: =BM31/$P31 -> 0 | BO31: 0 | BP31: =BO31/$P31 -> 0 | BQ31: 0 | BR31: =BQ31/$P31 -> 0 | BS31: =BG31+BI31+BK31+BM31+BO31+BQ31 -> 0 | BT31: =BS31/$P31 -> 0 | BU31: 0 | BV31: =BU31/$P31 -> 0 | BW31: 0 | BX31: =BW31/$P31 -> 0 | BY31: 0 | BZ31: =BY31/$P31 -> 0 | CA31: 0 | CB31: =CA31/$P31 -> 0 | CC31: 0 | CD31: =CC31/$P31 -> 0 | CE31: 0 | CF31: =CE31/$P31 -> 0 | CG31: =BU31+BW31+BY31+CA31+CC31+CE31 -> 0 | CH31: =CG31/$P31 -> 0 | CI31: 0 | CJ31: =CI31/$P31 -> 0 | CK31: 0 | CL31: =CK31/$P31 -> 0 | CM31: 0 | CN31: =CM31/$P31 -> 0 | CO31: 0 | CP31: =CO31/$P31 -> 0 | CQ31: 0 | CR31: =CQ31/$P31 -> 0 | CS31: 0 | CT31: =CS31/$P31 -> 0 | CU31: =CI31+CK31+CM31+CO31+CQ31+CS31 -> 0 | CV31: =CU31/$P31 -> 0
C32: 23 | D32: Muro sin ventanas (Blanco) | E32: =E5 -> 35.6 | F32: 1.72 | G32: =E32*F32 -> 61.232 | L32: =G32-K32 -> 61.232 | P32: =SUM(L32:O32) -> 61.232 | Q32: 0 | R32: =Q32/$P32 -> 0 | S32: 0 | T32: =S32/$P32 -> 0 | U32: 0 | V32: =U32/$P32 -> 0 | W32: 0 | X32: =W32/$P32 -> 0 | Y32: 0 | Z32: =Y32/$P32 -> 0 | AA32: 0 | AB32: =AA32/$P32 -> 0 | AC32: =Q32+S32+U32+W32+Y32+AA32 -> 0 | AD32: =AC32/$P32 -> 0 | AE32: 0 | AF32: =AE32/$P32 -> 0 | AG32: 0 | AH32: =AG32/$P32 -> 0 | AI32: 0 | AJ32: =AI32/$P32 -> 0 | AK32: 0 | AL32: =AK32/$P32 -> 0 | AM32: 0 | AN32: =AM32/$P32 -> 0 | AO32: 0 | AP32: =AO32/$P32 -> 0 | AQ32: =AE32+AG32+AI32+AK32+AM32+AO32 -> 0 | AR32: =AQ32/$P32 -> 0 | AS32: 0 | AT32: =AS32/$P32 -> 0 | AU32: 0 | AV32: =AU32/$P32 -> 0 | AW32: 0 | AX32: =AW32/$P32 -> 0 | AY32: 0 | AZ32: =AY32/$P32 -> 0 | BA32: 0 | BB32: =BA32/$P32 -> 0 | BC32: 0 | BD32: =BC32/$P32 -> 0 | BE32: =AS32+AU32+AW32+AY32+BA32+BC32 -> 0 | BF32: =BE32/$P32 -> 0 | BG32: 0 | BH32: =BG32/$P32 -> 0 | BI32: 0 | BJ32: =BI32/$P32 -> 0 | BK32: 0 | BL32: =BK32/$P32 -> 0 | BM32: 0 | BN32: =BM32/$P32 -> 0 | BO32: 0 | BP32: =BO32/$P32 -> 0 | BQ32: 0 | BR32: =BQ32/$P32 -> 0 | BS32: =BG32+BI32+BK32+BM32+BO32+BQ32 -> 0 | BT32: =BS32/$P32 -> 0 | BU32: 0 | BV32: =BU32/$P32 -> 0 | BW32: 0 | BX32: =BW32/$P32 -> 0 | BY32: 0 | BZ32: =BY32/$P32 -> 0 | CA32: 0 | CB32: =CA32/$P32 -> 0 | CC32: 0 | CD32: =CC32/$P32 -> 0 | CE32: 0 | CF32: =CE32/$P32 -> 0 | CG32: =BU32+BW32+BY32+CA32+CC32+CE32 -> 0 | CH32: =CG32/$P32 -> 0 | CI32: 0 | CJ32: =CI32/$P32 -> 0 | CK32: 0 | CL32: =CK32/$P32 -> 0 | CM32: 0 | CN32: =CM32/$P32 -> 0 | CO32: 0 | CP32: =CO32/$P32 -> 0 | CQ32: 0 | CR32: =CQ32/$P32 -> 0 | CS32: 0 | CT32: =CS32/$P32 -> 0 | CU32: =CI32+CK32+CM32+CO32+CQ32+CS32 -> 0 | CV32: =CU32/$P32 -> 0
C33: 24 | D33: Muro sin ventanas (Blanco) | E33: =E5 -> 35.6 | F33: 1.31 | G33: =E33*F33 -> 46.636 | L33: =G33-K33 -> 46.636 | P33: =SUM(L33:O33) -> 46.636 | Q33: 0 | R33: =Q33/$P33 -> 0 | S33: 0 | T33: =S33/$P33 -> 0 | U33: 0 | V33: =U33/$P33 -> 0 | W33: 0 | X33: =W33/$P33 -> 0 | Y33: 0 | Z33: =Y33/$P33 -> 0 | AA33: 0 | AB33: =AA33/$P33 -> 0 | AC33: =Q33+S33+U33+W33+Y33+AA33 -> 0 | AD33: =AC33/$P33 -> 0 | AE33: 0 | AF33: =AE33/$P33 -> 0 | AG33: 0 | AH33: =AG33/$P33 -> 0 | AI33: 0 | AJ33: =AI33/$P33 -> 0 | AK33: 0 | AL33: =AK33/$P33 -> 0 | AM33: 0 | AN33: =AM33/$P33 -> 0 | AO33: 0 | AP33: =AO33/$P33 -> 0 | AQ33: =AE33+AG33+AI33+AK33+AM33+AO33 -> 0 | AR33: =AQ33/$P33 -> 0 | AS33: 0 | AT33: =AS33/$P33 -> 0 | AU33: 0 | AV33: =AU33/$P33 -> 0 | AW33: 0 | AX33: =AW33/$P33 -> 0 | AY33: 0 | AZ33: =AY33/$P33 -> 0 | BA33: 0 | BB33: =BA33/$P33 -> 0 | BC33: 0 | BD33: =BC33/$P33 -> 0 | BE33: =AS33+AU33+AW33+AY33+BA33+BC33 -> 0 | BF33: =BE33/$P33 -> 0 | BG33: 0 | BH33: =BG33/$P33 -> 0 | BI33: 0 | BJ33: =BI33/$P33 -> 0 | BK33: 0 | BL33: =BK33/$P33 -> 0 | BM33: 0 | BN33: =BM33/$P33 -> 0 | BO33: 0 | BP33: =BO33/$P33 -> 0 | BQ33: 0 | BR33: =BQ33/$P33 -> 0 | BS33: =BG33+BI33+BK33+BM33+BO33+BQ33 -> 0 | BT33: =BS33/$P33 -> 0 | BU33: 0 | BV33: =BU33/$P33 -> 0 | BW33: 0 | BX33: =BW33/$P33 -> 0 | BY33: 0 | BZ33: =BY33/$P33 -> 0 | CA33: 0 | CB33: =CA33/$P33 -> 0 | CC33: 0 | CD33: =CC33/$P33 -> 0 | CE33: 0 | CF33: =CE33/$P33 -> 0 | CG33: =BU33+BW33+BY33+CA33+CC33+CE33 -> 0 | CH33: =CG33/$P33 -> 0 | CI33: 0 | CJ33: =CI33/$P33 -> 0 | CK33: 0 | CL33: =CK33/$P33 -> 0 | CM33: 0 | CN33: =CM33/$P33 -> 0 | CO33: 0 | CP33: =CO33/$P33 -> 0 | CQ33: 0 | CR33: =CQ33/$P33 -> 0 | CS33: 0 | CT33: =CS33/$P33 -> 0 | CU33: =CI33+CK33+CM33+CO33+CQ33+CS33 -> 0 | CV33: =CU33/$P33 -> 0
C34: 25 | D34: Muro con ventanas (Blanco) | E34: =E7 -> 35.6 | F34: 2.73 | G34: =E34*F34 -> 97.188 | H34: 1.5 | I34: 1.2 | J34: 14 | K34: =(H34*I34)*J34 -> 25.2 | L34: =G34-K34 -> 71.988 | P34: =SUM(L34:O34) -> 71.988 | Q34: 0 | R34: =Q34/$P34 -> 0 | S34: 0 | T34: =S34/$P34 -> 0 | U34: 0 | V34: =U34/$P34 -> 0 | W34: 0 | X34: =W34/$P34 -> 0 | Y34: 0 | Z34: =Y34/$P34 -> 0 | AA34: 0 | AB34: =AA34/$P34 -> 0 | AC34: =Q34+S34+U34+W34+Y34+AA34 -> 0 | AD34: =AC34/$P34 -> 0 | AE34: 0 | AF34: =AE34/$P34 -> 0 | AG34: 0 | AH34: =AG34/$P34 -> 0 | AI34: 0 | AJ34: =AI34/$P34 -> 0 | AK34: 0 | AL34: =AK34/$P34 -> 0 | AM34: 0 | AN34: =AM34/$P34 -> 0 | AO34: 0 | AP34: =AO34/$P34 -> 0 | AQ34: =AE34+AG34+AI34+AK34+AM34+AO34 -> 0 | AR34: =AQ34/$P34 -> 0 | AS34: 0 | AT34: =AS34/$P34 -> 0 | AU34: 0 | AV34: =AU34/$P34 -> 0 | AW34: 0 | AX34: =AW34/$P34 -> 0 | AY34: 0 | AZ34: =AY34/$P34 -> 0 | BA34: 0 | BB34: =BA34/$P34 -> 0 | BC34: 0 | BD34: =BC34/$P34 -> 0 | BE34: =AS34+AU34+AW34+AY34+BA34+BC34 -> 0 | BF34: =BE34/$P34 -> 0 | BG34: 0 | BH34: =BG34/$P34 -> 0 | BI34: 0 | BJ34: =BI34/$P34 -> 0 | BK34: 0 | BL34: =BK34/$P34 -> 0 | BM34: 0 | BN34: =BM34/$P34 -> 0 | BO34: 0 | BP34: =BO34/$P34 -> 0 | BQ34: 0 | BR34: =BQ34/$P34 -> 0 | BS34: =BG34+BI34+BK34+BM34+BO34+BQ34 -> 0 | BT34: =BS34/$P34 -> 0 | BU34: 0 | BV34: =BU34/$P34 -> 0 | BW34: 0 | BX34: =BW34/$P34 -> 0 | BY34: 0 | BZ34: =BY34/$P34 -> 0 | CA34: 0 | CB34: =CA34/$P34 -> 0 | CC34: 0 | CD34: =CC34/$P34 -> 0 | CE34: 0 | CF34: =CE34/$P34 -> 0 | CG34: =BU34+BW34+BY34+CA34+CC34+CE34 -> 0 | CH34: =CG34/$P34 -> 0 | CI34: 0 | CJ34: =CI34/$P34 -> 0 | CK34: 0 | CL34: =CK34/$P34 -> 0 | CM34: 0 | CN34: =CM34/$P34 -> 0 | CO34: 0 | CP34: =CO34/$P34 -> 0 | CQ34: 0 | CR34: =CQ34/$P34 -> 0 | CS34: 0 | CT34: =CS34/$P34 -> 0 | CU34: =CI34+CK34+CM34+CO34+CQ34+CS34 -> 0 | CV34: =CU34/$P34 -> 0
