Workbook

Sheet Acta Av Obra 01-nov 2025
A1: EDIFICIO EL MIRADOR
A2: CUADRO DE CONTROL GENERAL DE AVANCES DE LA OBRA
A3: INTERVENTOR : Ing. Luis Fernando Márquez Jaramillo MP 63202-21775 | E3: Rep. Legal: Sr Luis Jaime Manjarres Gongora-Administrador RL
A4: CONTRATISTA: FRESHHOUSE SAS | E4: Ubicación Edificio: Cra 19 # 26 N 69-Armenia | G4: Fecha: nov 14 de 2025 | H4: Acta 01- Periodo del
A5: ACTA DE AVANCE DE OBRA # 01-Periodo del 6 de octubre al 6 de noviembre de 2025 | H5: octubre 6 al 6 DE NOVIEMBRE DE 2025
A6: Capitulo | B6: Item | C6: Descripcion | D6: Unidad | E6: Cantidad | F6: Vr Unitario | G6: Valor Total | H6: Cantidad | I6: % avance | J6: Valor Total
A7: 1 | C7: PRELIMINARES | G7: =+G8+G9+G10+G11 -> 6300000 | J7: =+J8+J9+J10+J11 -> 75000
B8: 1.1 | C8: Campamento | D8: Gl | E8: 1 | F8: 700000 | G8: =+E8*F8 -> 700000 | H8: 0 | I8: =+H8/$E$8 -> 0 | J8: =+$F$8*H8 -> 0
B9: 1.2 | C9: Señalizacion y Seguridad | D9: Gl | E9: 1 | F9: 300000 | G9: =+E9*F9 -> 300000 | H9: 0.25 | I9: =+H9/$E$9 -> 0.25 | J9: =+$F$9*H9 -> 75000
B10: 1.3 | C10: Asesoria Técnica Externa | D10: Gl | E10: 1 | F10: 300000 | G10: =+E10*F10 -> 300000 | H10: 0 | I10: =+H10/$E$10 -> 0 | J10: =+$F$10*H10 -> 0
B11: 1.4 | C11: Recurso de respaldo por omision de diagnostico previo | D11: Gl | E11: 1 | F11: 5000000 | G11: =+E11*F11 -> 5000000 | H11: 0 | I11: =+H11/$E$11 -> 0 | J11: =+$F$11*H11 -> 0
A12: 2 | C12: PREPARACION DE SUPERFICIES | G12: =+G13+G14+G15 -> 53145176 | J12: =+J13+J14+J15 -> 12732525
B13: 2.1 | C13: Lavado General de Areas a Intervenir | D13: M2 | E13: =+'[1]TORRE 1'!C41+'[1]TORRE 1'!L70+'[1]TORRE 1'!M83+'[1]TORRE 1'!K92+'[1]TORRE 1'!K91+'[1]TORRE 1'!K90+'[1]TORRE 1'!K89+'[1]TORRE 1'!K88 -> 5019.5385 | F13: 3120 | G13: =+E13*F13 -> 15660960 | H13: 1970.04 | I13: =+H13/$E$13 -> 0.39247433 | J13: =+$F$13*H13 -> 6146524.8
B14: 2.2 | C14: Suministro y Restitucion de Graniplast (25%) | D14: M2 | E14: =+E17*0.25 -> 949.53575 | F14: 34000 | G14: =+E14*F14 -> 32284216 | H14: 105 | I14: =+H14/$E$14 -> 0.11058035 | J14: =+$F$14*H14 -> 3570000
B15: 2.3 | C15: Suministro y Restitucion de Mortero de fachada (10% 2,2) | D15: M2 | E15: 100 | F15: 52000 | G15: =+E15*F15 -> 5200000 | H15: 58 | I15: =+H15/$E$15 -> 0.58 | J15: =+$F$15*H15 -> 3016000
A16: 3 | C16: PINTURA | G16: =+G17+G18+G19+G20+G21+G22 -> 90759901 | J16: =+J17+J18+J19+J20+J21+J22 -> 14663300
B17: 3.1 | C17: Suministro y Aplicación de Pintura para exteriores, tipo KORAZA de Pintuco, IMPERMEABILIZANTE, en fachadas de concreto con revestimiento de graniplast | D17: M2 | E17: =+'[1]TORRE 1'!G41+'[1]TORRE 1'!F56+'[1]TORRE 1'!L70 -> 3798.143 | F17: 17500 | G17: =+E17*F17 -> 66467502 | H17: 433.64 | I17: =+H17/$E$17 -> 0.11417158 | J17: =+$F$17*H17 -> 7588700
B18: 3.2 | C18: Suministro y Aplicación de Pintura para exteriores, tipo KORAZA de Pintuco, IMPERMEABILIZANTE, sobre paredes de Concreto Limpio en fachadas | D18: M2 | E18: =+'[1]TORRE 1'!G72 -> 382.96 | F18: 19400.285 | G18: =+E18*F18 -> 7429533 | H18: 0 | I18: =+H18/$E$18 -> 0 | J18: =+$F$18*H18 -> 0
B19: 3.3 | C19: Suministro y Aplicación de Pintura gris basalto sobre alfajias de muros en los accesos del edificio y garajes | D19: ML | E19: =+'[1]TORRE 1'!G75 -> 53.65 | F19: 8100 | G19: =+E19*F19 -> 434565 | H19: 0 | I19: =+H19/$E$19 -> 0 | J19: =+$F$19*H19 -> 0
B20: 3.4 | C20: Suministro y Aplicación de Pintura, del tipo Pintulux tres en uno de pintuco, en puertas y ventanas de fachada | D20: M2 | E20: =2.2*2+('[1]TORRE 1'!K28) -> 71 | F20: 24300 | G20: =+E20*F20 -> 1725300 | H20: 0 | I20: =+H20/$E$20 -> 0 | J20: =+$F$20*H20 -> 0
B21: 3.5 | C21: Suministro y aplicación de pintura, del tipo pintulux 3 en 1 de pintuco, en barandas de parqueaderos | D21: ML | E21: =+(5.5+2.6)*3 -> 24.3 | F21: 22400 | G21: =+E21*F21 -> 544320 | H21: 0 | I21: =+H21/$E$21 -> 0 | J21: =+$F$21*H21 -> 0
B22: 3.6 | C22: Suministro y Aplicación de Pintura en interiores- Paredes y cielo raso de pasillos y porteria | D22: M2 | E22: =+'[1]TORRE 1'!L50 -> 1179.89 | F22: 12000 | G22: =+E22*F22 -> 14158680 | H22: 589.55 | I22: =+H22/$E$22 -> 0.49966522 | J22: =+$F$22*H22 -> 7074600
A23: 4 | C23: REPARACIONES y PROTECCIONES ESPECIALES | G23: =+G24+G25+G26+G27+G28+G29 -> 38695430 | J23: =+J24+J25+J26+J27+J28+J29 -> 635804
B24: 4.1 | C24: Suministro e instalacion de cortagoteras en fachadas y balcones | D24: ML | E24: =+'[1]TORRE 1'!L83 -> 346.79 | F24: 37000 | G24: =+E24*F24 -> 12831230 | H24: 0 | I24: =+H24/$E$24 -> 0 | J24: =+$F$24*H24 -> 0
B25: 4.2 | C25: Retiro y Restitucion de sellos en elementos vidriados de las areas comunes y fachadas del edificio (60%) | D25: ML | E25: =+'[1]TORRE 1'!I29*0.6 -> 1450.14 | F25: 5200 | G25: =+E25*F25 -> 7540728 | H25: 122.27 | I25: =+H25/$E$25 -> 0.084315997 | J25: =+$F$25*H25 -> 635804
B26: 4.3 | C26: Sellamiento de elementos varios en balcones | D26: ML | E26: =+'[1]TORRE 1'!L83 -> 346.79 | F26: 5200 | G26: =+E26*F26 -> 1803308 | H26: 0 | I26: =+H26/$E$26 -> 0 | J26: =+$F$26*H26 -> 0
B27: 4.4 | C27: Suministro e Instalacion de Alfajias en lamina en el perimetro y muros medianeros de las cubiertas del edificio | D27: ML | E27: =+'[1]TORRE 1'!K87 -> 122 | F27: 63000 | G27: =+E27*F27 -> 7686000 | H27: 0 | I27: =+H27/$E$27 -> 0 | J27: =+$F$27*H27 -> 0
B28: 4.5 | C28: Conformacion de escurrideros en antepechos de balcones y en otros elementos de la fachada | D28: M2 | E28: =+('[1]TORRE 1'!M83+'[1]TORRE 1'!K53+'[1]TORRE 1'!K55+'[1]TORRE 1'!C55:E55+'[1]TORRE 1'!C51:E51)*0.2+'[1]TORRE 1'!G71 -> 45.2797 | F28: 41200 | G28: =+E28*F28 -> 1865523.6 | H28: 0 | I28: =+H28/$E$28 -> 0 | J28: =+$F$28*H28 -> 0
B29: 4.6 | C29: Impermeabilizacion de muros internos en las cubiertas del edificio | D29: M2 | E29: =+'[1]TORRE 1'!K92 -> 97.6 | F29: 71400 | G29: =+E29*F29 -> 6968640 | H29: 0 | I29: =+H29/$E$29 -> 0 | J29: =+$F$29*H29 -> 0
A30: 5 | C30: TRATAMIENTO DE CUBIERTAS EN GENERAL | G30: =+G31+G32+G33+G34 -> 29601800 | J30: =+J31+J32+J33+J34 -> 0
B31: 5.1 | C31: Retiro de cubiertas antiguas y Suministro e Instalacion de Cubiertas Nuevas en Fibrocemento | D31: M2 | E31: =+'[1]TORRE 1'!K86 -> 395 | F31: 65000 | G31: =+E31*F31 -> 25675000 | H31: 0 | I31: =+H31/$E$31 -> 0 | J31: =+$F$31*H31 -> 0
B32: 5.2 | C32: Suministro e instalacion de teja translucida en vacio del edificio | D32: M2 | E32: 29.6 | F32: 71000 | G32: =+E32*F32 -> 2101600 | H32: 0 | I32: =+H32/$E$32 -> 0 | J32: =+$F$32*H32 -> 0
B33: 5.3 | C33: Impermeabilizacion de la placa del cuarto de maquinas | D33: M2 | E33: 35 | F33: 39000 | G33: =+E33*F33 -> 1365000 | H33: 0 | I33: =+H33/$E$33 -> 0 | J33: =+$F$33*H33 -> 0
B34: 5.4 | C34: Impermeabilizacion y tratamiento general a la viga canal de cubierta | D34: M2 | E34: 11.8 | F34: 39000 | G34: =+E34*F34 -> 460200 | H34: 0 | I34: =+H34/$E$34 -> 0 | J34: =+$F$34*H34 -> 0
A35: 6 | C35: ASEO DE OBRA Y RETIRO DE ESCOMBROS | G35: =+G36+G37 -> 1800000 | J35: =+J36+J37 -> 0
B36: 6.1 | C36: Aseo general durante y al final de la obra | D36: Gl | E36: 1 | F36: 500000 | G36: =+E36*F36 -> 500000 | H36: 0 | I36: =+H36/$E$36 -> 0 | J36: =+$F$36*H36 -> 0
B37: 6.2 | C37: Retiro de Escombros y disposicion final | D37: Gl | E37: 1 | F37: 1300000 | G37: =+E37*F37 -> 1300000 | H37: 0 | I37: =+H37/$E$37 -> 0 | J37: =+$F$37*H37 -> 0
A38: Aprobado por Interventoria: Ing. Luis Fernando Márquez Jaramillo | E38: costo directo | G38: =+G7+G12+G16+G23+G30+G35 -> 2.2030231e+08 | H38: costo directo | J38: =+J7+J12+J16+J23+J30+J35 -> 28106629
E39: A | F39: 0.08 | G39: =+$G$38*F39 -> 17624184 | H39: A | I39: 0.08 | J39: =+J38*I39 -> 2248530.3
E40: I | F40: 0.03 | G40: =+$G$38*F40 -> 6609069.2 | H40: I | I40: 0.03 | J40: =+J38*I40 -> 843198.86
E41: U | F41: 0.05 | G41: =+$G$38*F41 -> 11015115 | H41: U | I41: 0.05 | J41: =+J38*I41 -> 1405331.4
E42: Subtotal antes de IVA | G42: =+G38+G39+G40+G41 -> 2.5555067e+08 | H42: Subtotal antes de IVA | J42: =+J38+J39+J40+J41 -> 32603689
E43: IVA/U | F43: 0.19 | G43: =+G41*F43 -> 2092871.9 | H43: IVA/U | I43: 0.19 | J43: =+J41*I43 -> 267012.97
E44: total costo | G44: =+G42+G43 -> 2.5764355e+08 | H44: total costo | J44: =+J42+J43 -> 32870702
H45: retefuente | I45: -0.02 | J45: =+J42*I45 -> -652073.79
H46: amortizac anticipo | I46: -0.2 | J46: =+J44*I46 -> -6574140.5
H47: retegarantia | I47: -0.1 | J47: =+J44*I47 -> -3287070.2
C48: Valor Contrato | E48: =+G44 -> 2.5764355e+08 | H48: Total Desembolso | J48: =SUM(J44:J47) -> 22357418
C49: Valor Anticipo | E49: =+E48*20% -> 51528709
C50: Vr Amortizacion Anticipo esta acta | D50: 0.13 | E50: =+J46 -> -6574140.5
C51: Saldo por Amortizar | E51: =+E49+E50 -> 44954569
C52: Vr Esta Acta | E52: =+J44 -> 32870702
C53: % ejecucion | E53: =+E52/E48 -> 0.12758209

Sheet Acta Av Obra 02 - dic 15 2025
A1: EDIFICIO EL MIRADOR
A2: CUADRO DE CONTROL GENERAL DE AVANCES DE LA OBRA
A3: INTERVENTOR : Ing. Luis Fernando Márquez Jaramillo MP 63202-21775 | E3: Rep. Legal: Sr Luis Jaime Manjarres Gongora-Administrador RL
A4: CONTRATISTA: FRESHHOUSE SAS | E4: Ubicación Edificio: Cra 19 # 26 N 69-Armenia | G4: Fecha: nov 14 de 2025 | H4: Acta 01- Periodo del | K4: Acta 02- Periodo del | N4: Acumulado de actas
A5: ACTA DE AVANCE DE OBRA # 01-Periodo del 6 de octubre al 6 de noviembre de 2025 | H5: octubre 6 al 6 DE NOVIEMBRE DE 2025 | K5: noviembre 6 al 15 DE DICIEMBRE DE 2025 | N5: octubre 6 al 15 DE DICIEMBRE DE 2025
A6: Capitulo | B6: Item | C6: Descripcion | D6: Unidad | E6: Cantidad | F6: Vr Unitario | G6: Valor Total | H6: Cantidad | I6: % avance | J6: Valor Total | K6: Cantidad | L6: % avance | M6: Valor Total | N6: Cantidad | O6: % avance | P6: Valor Total
A7: 1 | C7: PRELIMINARES | G7: =+G8+G9+G10+G11 -> 6300000 | J7: =+J8+J9+J10+J11 -> 75000 | M7: =+M8+M9+M10+M11 -> 75000 | N7: =H7+K7 -> 0 | P7: =+P8+P9+P10+P11 -> 150000
B8: 1.1 | C8: Campamento | D8: Gl | E8: 1 | F8: 700000 | G8: =+E8*F8 -> 700000 | H8: 0 | I8: =+H8/$E$8 -> 0 | J8: =+$F$8*H8 -> 0 | K8: 0 | L8: =+K8/$E$8 -> 0 | M8: =+$F$8*K8 -> 0 | N8: =H8+K8 -> 0 | O8: =+N8/$E$8 -> 0 | P8: =+$F$8*N8 -> 0
B9: 1.2 | C9: Señalizacion y Seguridad | D9: Gl | E9: 1 | F9: 300000 | G9: =+E9*F9 -> 300000 | H9: 0.25 | I9: =+H9/$E$9 -> 0.25 | J9: =+$F$9*H9 -> 75000 | K9: 0.25 | L9: =+K9/$E$9 -> 0.25 | M9: =+$F$9*K9 -> 75000 | N9: =H9+K9 -> 0.5 | O9: =+N9/$E$9 -> 0.5 | P9: =+$F$9*N9 -> 150000
B10: 1.3 | C10: Asesoria Técnica Externa | D10: Gl | E10: 1 | F10: 300000 | G10: =+E10*F10 -> 300000 | H10: 0 | I10: =+H10/$E$10 -> 0 | J10: =+$F$10*H10 -> 0 | K10: 0 | L10: =+K10/$E$10 -> 0 | M10: =+$F$10*K10 -> 0 | N10: =H10+K10 -> 0 | O10: =+N10/$E$10 -> 0 | P10: =+$F$10*N10 -> 0
B11: 1.4 | C11: Recurso de respaldo por omision de diagnostico previo | D11: Gl | E11: 1 | F11: 5000000 | G11: =+E11*F11 -> 5000000 | H11: 0 | I11: =+H11/$E$11 -> 0 | J11: =+$F$11*H11 -> 0 | K11: 0 | L11: =+K11/$E$11 -> 0 | M11: =+$F$11*K11 -> 0 | N11: =H11+K11 -> 0 | O11: =+N11/$E$11 -> 0 | P11: =+$F$11*N11 -> 0
A12: 2 | C12: PREPARACION DE SUPERFICIES | G12: =+G13+G14+G15 -> 53145176 | J12: =+J13+J14+J15 -> 12732525 | M12: =+M13+M14+M15 -> 3204000 | N12: =H12+K12 -> 0 | P12: =+P13+P14+P15 -> 15936525
B13: 2.1 | C13: Lavado General de Areas a Intervenir | D13: M2 | E13: =+'[1]TORRE 1'!C41+'[1]TORRE 1'!L70+'[1]TORRE 1'!M83+'[1]TORRE 1'!K92+'[1]TORRE 1'!K91+'[1]TORRE 1'!K90+'[1]TORRE 1'!K89+'[1]TORRE 1'!K88 -> 5019.5385 | F13: 3120 | G13: =+E13*F13 -> 15660960 | H13: 1970.04 | I13: =+H13/$E$13 -> 0.39247433 | J13: =+$F$13*H13 -> 6146524.8 | K13: 0 | L13: =+K13/$E$13 -> 0 | M13: =+$F$13*K13 -> 0 | N13: =H13+K13 -> 1970.04 | O13: =+N13/$E$13 -> 0.39247433 | P13: =+$F$13*N13 -> 6146524.8
B14: 2.2 | C14: Suministro y Restitucion de Graniplast (25%) | D14: M2 | E14: =+E17*0.25 -> 949.53575 | F14: 34000 | G14: =+E14*F14 -> 32284216 | H14: 105 | I14: =+H14/$E$14 -> 0.11058035 | J14: =+$F$14*H14 -> 3570000 | K14: 56 | L14: =+K14/$E$14 -> 0.058976189 | M14: =+$F$14*K14 -> 1904000 | N14: =H14+K14 -> 161 | O14: =+N14/$E$14 -> 0.16955654 | P14: =+$F$14*N14 -> 5474000
B15: 2.3 | C15: Suministro y Restitucion de Mortero de fachada (10% 2,2) | D15: M2 | E15: 100 | F15: 52000 | G15: =+E15*F15 -> 5200000 | H15: 58 | I15: =+H15/$E$15 -> 0.58 | J15: =+$F$15*H15 -> 3016000 | K15: 25 | L15: =+K15/$E$15 -> 0.25 | M15: =+$F$15*K15 -> 1300000 | N15: =H15+K15 -> 83 | O15: =+N15/$E$15 -> 0.83 | P15: =+$F$15*N15 -> 4316000
A16: 3 | C16: PINTURA | G16: =+G17+G18+G19+G20+G21+G22 -> 90759901 | J16: =+J17+J18+J19+J20+J21+J22 -> 14663300 | M16: =+M17+M18+M19+M20+M21+M22 -> 27863747 | N16: =H16+K16 -> 0 | P16: =+P17+P18+P19+P20+P21+P22 -> 42527047
B17: 3.1 | C17: Suministro y Aplicación de Pintura para exteriores, tipo KORAZA de Pintuco, IMPERMEABILIZANTE, en fachadas de concreto con revestimiento de graniplast | D17: M2 | E17: =+'[1]TORRE 1'!G41+'[1]TORRE 1'!F56+'[1]TORRE 1'!L70 -> 3798.143 | F17: 17500 | G17: =+E17*F17 -> 66467502 | H17: 433.64 | I17: =+H17/$E$17 -> 0.11417158 | J17: =+$F$17*H17 -> 7588700 | K17: =Pintura!AE45 -> 1187.9581 | L17: =+K17/$E$17 -> 0.3127734 | M17: =+$F$17*K17 -> 20789267 | N17: =H17+K17 -> 1621.5981 | O17: =+N17/$E$17 -> 0.42694498 | P17: =+$F$17*N17 -> 28377967
B18: 3.2 | C18: Suministro y Aplicación de Pintura para exteriores, tipo KORAZA de Pintuco, IMPERMEABILIZANTE, sobre paredes de Concreto Limpio en fachadas | D18: M2 | E18: =+'[1]TORRE 1'!G72 -> 382.96 | F18: 19400.285 | G18: =+E18*F18 -> 7429533 | H18: 0 | I18: =+H18/$E$18 -> 0 | J18: =+$F$18*H18 -> 0 | K18: 0 | L18: =+K18/$E$18 -> 0 | M18: =+$F$18*K18 -> 0 | N18: =H18+K18 -> 0 | O18: =+N18/$E$18 -> 0 | P18: =+$F$18*N18 -> 0
B19: 3.3 | C19: Suministro y Aplicación de Pintura gris basalto sobre alfajias de muros en los accesos del edificio y garajes | D19: ML | E19: =+'[1]TORRE 1'!G75 -> 53.65 | F19: 8100 | G19: =+E19*F19 -> 434565 | H19: 0 | I19: =+H19/$E$19 -> 0 | J19: =+$F$19*H19 -> 0 | K19: 0 | L19: =+K19/$E$19 -> 0 | M19: =+$F$19*K19 -> 0 | N19: =H19+K19 -> 0 | O19: =+N19/$E$19 -> 0 | P19: =+$F$19*N19 -> 0
B20: 3.4 | C20: Suministro y Aplicación de Pintura, del tipo Pintulux tres en uno de pintuco, en puertas y ventanas de fachada | D20: M2 | E20: =2.2*2+('[1]TORRE 1'!K28) -> 71 | F20: 24300 | G20: =+E20*F20 -> 1725300 | H20: 0 | I20: =+H20/$E$20 -> 0 | J20: =+$F$20*H20 -> 0 | K20: 0 | L20: =+K20/$E$20 -> 0 | M20: =+$F$20*K20 -> 0 | N20: =H20+K20 -> 0 | O20: =+N20/$E$20 -> 0 | P20: =+$F$20*N20 -> 0
B21: 3.5 | C21: Suministro y aplicación de pintura, del tipo pintulux 3 en 1 de pintuco, en barandas de parqueaderos | D21: ML | E21: =+(5.5+2.6)*3 -> 24.3 | F21: 22400 | G21: =+E21*F21 -> 544320 | H21: 0 | I21: =+H21/$E$21 -> 0 | J21: =+$F$21*H21 -> 0 | K21: 0 | L21: =+K21/$E$21 -> 0 | M21: =+$F$21*K21 -> 0 | N21: =H21+K21 -> 0 | O21: =+N21/$E$21 -> 0 | P21: =+$F$21*N21 -> 0
B22: 3.6 | C22: Suministro y Aplicación de Pintura en interiores- Paredes y cielo raso de pasillos y porteria | D22: M2 | E22: =+'[1]TORRE 1'!L50 -> 1179.89 | F22: 12000 | G22: =+E22*F22 -> 14158680 | H22: 589.55 | I22: =+H22/$E$22 -> 0.49966522 | J22: =+$F$22*H22 -> 7074600 | K22: =Pintura!AE60 -> 589.54 | L22: =+K22/$E$22 -> 0.49965675 | M22: =+$F$22*K22 -> 7074480 | N22: =H22+K22 -> 1179.09 | O22: =+N22/$E$22 -> 0.99932197 | P22: =+$F$22*N22 -> 14149080
A23: 4 | C23: REPARACIONES y PROTECCIONES ESPECIALES | G23: =+G24+G25+G26+G27+G28+G29 -> 38695430 | J23: =+J24+J25+J26+J27+J28+J29 -> 635804 | M23: =+M24+M25+M26+M27+M28+M29 -> 4407492.4 | N23: =H23+K23 -> 0 | P23: =+P24+P25+P26+P27+P28+P29 -> 5043296.4
B24: 4.1 | C24: Suministro e instalacion de cortagoteras en fachadas y balcones | D24: ML | E24: =+'[1]TORRE 1'!L83 -> 346.79 | F24: 37000 | G24: =+E24*F24 -> 12831230 | H24: 0 | I24: =+H24/$E$24 -> 0 | J24: =+$F$24*H24 -> 0 | K24: 85 | L24: =+K24/$E$24 -> 0.24510511 | M24: =+$F$24*K24 -> 3145000 | N24: =H24+K24 -> 85 | O24: =+N24/$E$24 -> 0.24510511 | P24: =+$F$24*N24 -> 3145000
B25: 4.2 | C25: Retiro y Restitucion de sellos en elementos vidriados de las areas comunes y fachadas del edificio (60%) | D25: ML | E25: =+'[1]TORRE 1'!I29*0.6 -> 1450.14 | F25: 5200 | G25: =+E25*F25 -> 7540728 | H25: 122.27 | I25: =+H25/$E$25 -> 0.084315997 | J25: =+$F$25*H25 -> 635804 | K25: =Sellos!AE46 -> 242.787 | L25: =+K25/$E$25 -> 0.16742315 | M25: =+$F$25*K25 -> 1262492.4 | N25: =H25+K25 -> 365.057 | O25: =+N25/$E$25 -> 0.25173914 | P25: =+$F$25*N25 -> 1898296.4
B26: 4.3 | C26: Sellamiento de elementos varios en balcones | D26: ML | E26: =+'[1]TORRE 1'!L83 -> 346.79 | F26: 5200 | G26: =+E26*F26 -> 1803308 | H26: 0 | I26: =+H26/$E$26 -> 0 | J26: =+$F$26*H26 -> 0 | K26: 0 | L26: =+K26/$E$26 -> 0 | M26: =+$F$26*K26 -> 0 | N26: =H26+K26 -> 0 | O26: =+N26/$E$26 -> 0 | P26: =+$F$26*N26 -> 0
B27: 4.4 | C27: Suministro e Instalacion de Alfajias en lamina en el perimetro y muros medianeros de las cubiertas del edificio | D27: ML | E27: =+'[1]TORRE 1'!K87 -> 122 | F27: 63000 | G27: =+E27*F27 -> 7686000 | H27: 0 | I27: =+H27/$E$27 -> 0 | J27: =+$F$27*H27 -> 0 | K27: 0 | L27: =+K27/$E$27 -> 0 | M27: =+$F$27*K27 -> 0 | N27: =H27+K27 -> 0 | O27: =+N27/$E$27 -> 0 | P27: =+$F$27*N27 -> 0
B28: 4.5 | C28: Conformacion de escurrideros en antepechos de balcones y en otros elementos de la fachada | D28: M2 | E28: =+('[1]TORRE 1'!M83+'[1]TORRE 1'!K53+'[1]TORRE 1'!K55+'[1]TORRE 1'!C55:E55+'[1]TORRE 1'!C51:E51)*0.2+'[1]TORRE 1'!G71 -> 45.2797 | F28: 41200 | G28: =+E28*F28 -> 1865523.6 | H28: 0 | I28: =+H28/$E$28 -> 0 | J28: =+$F$28*H28 -> 0 | K28: 0 | L28: =+K28/$E$28 -> 0 | M28: =+$F$28*K28 -> 0 | N28: =H28+K28 -> 0 | O28: =+N28/$E$28 -> 0 | P28: =+$F$28*N28 -> 0
B29: 4.6 | C29: Impermeabilizacion de muros internos en las cubiertas del edificio | D29: M2 | E29: =+'[1]TORRE 1'!K92 -> 97.6 | F29: 71400 | G29: =+E29*F29 -> 6968640 | H29: 0 | I29: =+H29/$E$29 -> 0 | J29: =+$F$29*H29 -> 0 | K29: 0 | L29: =+K29/$E$29 -> 0 | M29: =+$F$29*K29 -> 0 | N29: =H29+K29 -> 0 | O29: =+N29/$E$29 -> 0 | P29: =+$F$29*N29 -> 0
A30: 5 | C30: TRATAMIENTO DE CUBIERTAS EN GENERAL | G30: =+G31+G32+G33+G34 -> 29601800 | J30: =+J31+J32+J33+J34 -> 0 | M30: =+M31+M32+M33+M34 -> 0 | P30: =+P31+P32+P33+P34+P35+P36 -> 0
B31: 5.1 | C31: Retiro de cubiertas antiguas y Suministro e Instalacion de Cubiertas Nuevas en Fibrocemento | D31: M2 | E31: =+'[1]TORRE 1'!K86 -> 395 | F31: 65000 | G31: =+E31*F31 -> 25675000 | H31: 0 | I31: =+H31/$E$31 -> 0 | J31: =+$F$31*H31 -> 0 | K31: 0 | L31: =+K31/$E$31 -> 0 | M31: =+$F$31*K31 -> 0 | N31: =H31+K31 -> 0 | O31: =+N31/$E$31 -> 0 | P31: =+$F$31*N31 -> 0
B32: 5.2 | C32: Suministro e instalacion de teja translucida en vacio del edificio | D32: M2 | E32: 29.6 | F32: 71000 | G32: =+E32*F32 -> 2101600 | H32: 0 | I32: =+H32/$E$32 -> 0 | J32: =+$F$32*H32 -> 0 | K32: 0 | L32: =+K32/$E$32 -> 0 | M32: =+$F$32*K32 -> 0 | N32: =H32+K32 -> 0 | O32: =+N32/$E$32 -> 0 | P32: =+$F$32*N32 -> 0
B33: 5.3 | C33: Impermeabilizacion de la placa del cuarto de maquinas | D33: M2 | E33: 35 | F33: 39000 | G33: =+E33*F33 -> 1365000 | H33: 0 | I33: =+H33/$E$33 -> 0 | J33: =+$F$33*H33 -> 0 | K33: 0 | L33: =+K33/$E$33 -> 0 | M33: =+$F$33*K33 -> 0 | N33: =H33+K33 -> 0 | O33: =+N33/$E$33 -> 0 | P33: =+$F$33*N33 -> 0
B34: 5.4 | C34: Impermeabilizacion y tratamiento general a la viga canal de cubierta | D34: M2 | E34: 11.8 | F34: 39000 | G34: =+E34*F34 -> 460200 | H34: 0 | I34: =+H34/$E$34 -> 0 | J34: =+$F$34*H34 -> 0 | K34: 0 | L34: =+K34/$E$34 -> 0 | M34: =+$F$34*K34 -> 0 | N34: =H34+K34 -> 0 | O34: =+N34/$E$34 -> 0 | P34: =+$F$34*N34 -> 0
A35: 6 | C35: ASEO DE OBRA Y RETIRO DE ESCOMBROS | G35: =+G36+G37 -> 1800000 | J35: =+J36+J37 -> 0 | M35: =+M36+M37 -> 0 | N35: =H35+K35 -> 0 | P35: =+P36+P37 -> 0
B36: 6.1 | C36: Aseo general durante y al final de la obra | D36: Gl | E36: 1 | F36: 500000 | G36: =+E36*F36 -> 500000 | H36: 0 | I36: =+H36/$E$36 -> 0 | J36: =+$F$36*H36 -> 0 | K36: 0 | L36: =+K36/$E$36 -> 0 | M36: =+$F$36*K36 -> 0 | N36: =H36+K36 -> 0 | O36: =+N36/$E$36 -> 0 | P36: =+$F$36*N36 -> 0
B37: 6.2 | C37: Retiro de Escombros y disposicion final | D37: Gl | E37: 1 | F37: 1300000 | G37: =+E37*F37 -> 1300000 | H37: 0 | I37: =+H37/$E$37 -> 0 | J37: =+$F$37*H37 -> 0 | K37: 0 | L37: =+K37/$E$37 -> 0 | M37: =+$F$37*K37 -> 0 | N37: =H37+K37 -> 0 | O37: =+N37/$E$37 -> 0 | P37: =+$F$37*N37 -> 0
A38: Aprobado por Interventoria: Ing. Luis Fernando Márquez Jaramillo | E38: costo directo | G38: =+G7+G12+G16+G23+G30+G35 -> 2.2030231e+08 | H38: costo directo | J38: =+J7+J12+J16+J23+J30+J35 -> 28106629 | K38: costo directo | M38: =+M7+M12+M16+M23+M30+M35 -> 35550239 | N38: costo directo | P38: =+P7+P12+P16+P23+P30+P35 -> 63656868
E39: A | F39: 0.08 | G39: =+$G$38*F39 -> 17624184 | H39: A | I39: 0.08 | J39: =+J38*I39 -> 2248530.3 | K39: A | L39: 0.08 | M39: =+M38*L39 -> 2844019.1 | N39: A | O39: 0.08 | P39: =+P38*O39 -> 5092549.4
E40: I | F40: 0.03 | G40: =+$G$38*F40 -> 6609069.2 | H40: I | I40: 0.03 | J40: =+J38*I40 -> 843198.86 | K40: I | L40: 0.03 | M40: =+M38*L40 -> 1066507.2 | N40: I | O40: 0.03 | P40: =+P38*O40 -> 1909706
E41: U | F41: 0.05 | G41: =+$G$38*F41 -> 11015115 | H41: U | I41: 0.05 | J41: =+J38*I41 -> 1405331.4 | K41: U | L41: 0.05 | M41: =+M38*L41 -> 1777512 | N41: U | O41: 0.05 | P41: =+P38*O41 -> 3182843.4
E42: Subtotal antes de IVA | G42: =+G38+G39+G40+G41 -> 2.5555067e+08 | H42: Subtotal antes de IVA | J42: =+J38+J39+J40+J41 -> 32603689 | K42: Subtotal antes de IVA | M42: =+M38+M39+M40+M41 -> 41238278 | N42: Subtotal antes de IVA | P42: =+P38+P39+P40+P41 -> 73841967
E43: IVA/U | F43: 0.19 | G43: =+G41*F43 -> 2092871.9 | H43: IVA/U | I43: 0.19 | J43: =+J41*I43 -> 267012.97 | K43: IVA/U | L43: 0.19 | M43: =+M41*L43 -> 337727.27 | N43: IVA/U | O43: 0.19 | P43: =+P41*O43 -> 604740.25
E44: total costo | G44: =+G42+G43 -> 2.5764355e+08 | H44: total costo | J44: =+J42+J43 -> 32870702 | K44: total costo | M44: =+M42+M43 -> 41576005 | N44: total costo | P44: =+P42+P43 -> 74446707
H45: retefuente | I45: -0.02 | J45: =+J42*I45 -> -652073.79 | K45: retefuente | L45: -0.02 | M45: =+M42*L45 -> -824765.55 | N45: retefuente | O45: -0.02 | P45: =+P42*O45 -> -1476839.3
H46: amortizac anticipo | I46: -0.2 | J46: =+J44*I46 -> -6574140.5 | K46: amortizac anticipo | L46: -0.2 | M46: =+M44*L46 -> -8315201 | N46: amortizac anticipo | O46: -0.2 | P46: =+P44*O46 -> -14889341
H47: retegarantia | I47: -0.1 | J47: =+J44*I47 -> -3287070.2 | K47: retegarantia | L47: -0.1 | M47: =+M44*L47 -> -4157600.5 | N47: retegarantia | O47: -0.1 | P47: =+P44*O47 -> -7444670.7
C48: Valor Contrato | E48: =+G44 -> 2.5764355e+08 | H48: Total Desembolso | J48: =SUM(J44:J47) -> 22357418 | K48: Total Desembolso | M48: =SUM(M44:M47) -> 28278438 | N48: Total Desembolso | P48: =SUM(P44:P47) -> 50635856
C49: Valor Anticipo | E49: =+E48*20% -> 51528709
C50: Vr Amortizacion Anticipo esta acta | D50: 0.13 | E50: =+J46 -> -6574140.5
C51: Saldo por Amortizar | E51: =+E49+E50 -> 44954569
C52: Vr Esta Acta | E52: =+J44 -> 32870702
C53: % ejecucion | E53: =+E52/E48 -> 0.12758209

Sheet Acta Av Obra 03 - ene 21 2026
A1: EDIFICIO EL MIRADOR
A2: CUADRO DE CONTROL GENERAL DE AVANCES DE LA OBRA
A3: INTERVENTOR : Ing. Luis Fernando Márquez Jaramillo MP 63202-21775 | E3: Rep. Legal: Sr Luis Jaime Manjarres Gongora-Administrador RL
A4: CONTRATISTA: FRESHHOUSE SAS | E4: Ubicación Edificio: Cra 19 # 26 N 69-Armenia | G4: Fecha: nov 14 de 2025 | H4: Acta 01- Periodo del | K4: Acta 02- Periodo del | N4: Acta 03- Periodo del | Q4: Acta 04- Periodo del | T4: Acumulado de actas
A5: ACTA DE AVANCE DE OBRA # 01-Periodo del 6 de octubre al 6 de noviembre de 2025 | H5: octubre 6 al 6 DE NOVIEMBRE DE 2025 | K5: noviembre 6 al 15 DE DICIEMBRE DE 2025 | N5: diciembre 16 al 20 DE ENERO DE 2026 | Q5: ENERO 20 AL 11 MARZO 2026 | T5: octubre 6 al 20 MARZO DE 2025
A6: Capitulo | B6: Item | C6: Descripcion | D6: Unidad | E6: Cantidad | F6: Vr Unitario | G6: Valor Total | H6: Cantidad | I6: % avance | J6: Valor Total | K6: Cantidad | L6: % avance | M6: Valor Total | N6: Cantidad | O6: % avance | P6: Valor Total | Q6: Cantidad | R6: % avance | S6: Valor Total | T6: Cantidad | U6: % avance | V6: Valor Total
A7: 1 | C7: PRELIMINARES | G7: =+G8+G9+G10+G11 -> 6300000 | J7: =+J8+J9+J10+J11 -> 75000 | M7: =+M8+M9+M10+M11 -> 75000 | P7: =+P8+P9+P10+P11 -> 75000 | S7: =+S8+S9+S10+S11 -> 75000 | V7: =+V8+V9+V10+V11 -> 300000
B8: 1.1 | C8: Campamento | D8: Gl | E8: 1 | F8: 700000 | G8: =+E8*F8 -> 700000 | H8: 0 | I8: =+H8/$E$8 -> 0 | J8: =+$F$8*H8 -> 0 | K8: 0 | L8: =+K8/$E$8 -> 0 | M8: =+$F$8*K8 -> 0 | N8: 0 | O8: =+N8/$E$8 -> 0 | P8: =+$F$8*N8 -> 0 | Q8: 0 | R8: =+Q8/$E$8 -> 0 | S8: =+$F$8*Q8 -> 0 | T8: =H8+K8+N8+Q8 -> 0 | U8: =+T8/$E$8 -> 0 | V8: =+$F$8*T8 -> 0
B9: 1.2 | C9: Señalizacion y Seguridad | D9: Gl | E9: 1 | F9: 300000 | G9: =+E9*F9 -> 300000 | H9: 0.25 | I9: =+H9/$E$9 -> 0.25 | J9: =+$F$9*H9 -> 75000 | K9: 0.25 | L9: =+K9/$E$9 -> 0.25 | M9: =+$F$9*K9 -> 75000 | N9: 0.25 | O9: =+N9/$E$9 -> 0.25 | P9: =+$F$9*N9 -> 75000 | Q9: 0.25 | R9: =+Q9/$E$9 -> 0.25 | S9: =+$F$9*Q9 -> 75000 | T9: =H9+K9+N9+Q9 -> 1 | U9: =+T9/$E$9 -> 1 | V9: =+$F$9*T9 -> 300000
B10: 1.3 | C10: Asesoria Técnica Externa | D10: Gl | E10: 1 | F10: 300000 | G10: =+E10*F10 -> 300000 | H10: 0 | I10: =+H10/$E$10 -> 0 | J10: =+$F$10*H10 -> 0 | K10: 0 | L10: =+K10/$E$10 -> 0 | M10: =+$F$10*K10 -> 0 | N10: 0 | O10: =+N10/$E$10 -> 0 | P10: =+$F$10*N10 -> 0 | Q10: 0 | R10: =+Q10/$E$10 -> 0 | S10: =+$F$10*Q10 -> 0 | T10: =H10+K10+N10+Q10 -> 0 | U10: =+T10/$E$10 -> 0 | V10: =+$F$10*T10 -> 0
B11: 1.4 | C11: Recurso de respaldo por omision de diagnostico previo | D11: Gl | E11: 1 | F11: 5000000 | G11: =+E11*F11 -> 5000000 | H11: 0 | I11: =+H11/$E$11 -> 0 | J11: =+$F$11*H11 -> 0 | K11: 0 | L11: =+K11/$E$11 -> 0 | M11: =+$F$11*K11 -> 0 | N11: 0 | O11: =+N11/$E$11 -> 0 | P11: =+$F$11*N11 -> 0 | Q11: 0 | R11: =+Q11/$E$11 -> 0 | S11: =+$F$11*Q11 -> 0 | T11: =H11+K11+N11+Q11 -> 0 | U11: =+T11/$E$11 -> 0 | V11: =+$F$11*T11 -> 0
A12: 2 | C12: PREPARACION DE SUPERFICIES | G12: =+G13+G14+G15 -> 53145176 | J12: =+J13+J14+J15 -> 12732525 | M12: =+M13+M14+M15 -> 3204000 | P12: =+P13+P14+P15 -> 4743337.4 | S12: =+S13+S14+S15 -> 4485420.7 | V12: =+V13+V14+V15 -> 25165283
B13: 2.1 | C13: Lavado General de Areas a Intervenir | D13: M2 | E13: =+'[1]TORRE 1'!C41+'[1]TORRE 1'!L70+'[1]TORRE 1'!M83+'[1]TORRE 1'!K92+'[1]TORRE 1'!K91+'[1]TORRE 1'!K90+'[1]TORRE 1'!K89+'[1]TORRE 1'!K88 -> 5019.5385 | F13: 3120 | G13: =+E13*F13 -> 15660960 | H13: 1970.04 | I13: =+H13/$E$13 -> 0.39247433 | J13: =+$F$13*H13 -> 6146524.8 | K13: 0 | L13: =+K13/$E$13 -> 0 | M13: =+$F$13*K13 -> 0 | N13: =Lavado!AA46 -> 389.72377 | O13: =+N13/$E$13 -> 0.077641355 | P13: =+$F$13*N13 -> 1215938.2 | Q13: =Lavado!W46-'Acta Av Obra 03 - ene 21 2026'!N13-'Acta Av Obra 03 - ene 21 2026'!H13 -> 1437.6348 | R13: =+Q13/$E$13 -> 0.28640777 | S13: =+$F$13*Q13 -> 4485420.7 | T13: =H13+K13+N13+Q13 -> 3797.3986 | U13: =+T13/$E$13 -> 0.75652345 | V13: =+$F$13*T13 -> 11847884
B14: 2.2 | C14: Suministro y Restitucion de Graniplast (25%) | D14: M2 | E14: =+E17*0.25 -> 949.53575 | F14: 34000 | G14: =+E14*F14 -> 32284216 | H14: 105 | I14: =+H14/$E$14 -> 0.11058035 | J14: =+$F$14*H14 -> 3570000 | K14: 56 | L14: =+K14/$E$14 -> 0.058976189 | M14: =+$F$14*K14 -> 1904000 | N14: =Graniplast!AC46 -> 85.394095 | O14: =+N14/$E$14 -> 0.089932469 | P14: =+$F$14*N14 -> 2903399.2 | Q14: =Graniplast!AF46 -> 0 | R14: =+Q14/$E$14 -> 0 | S14: =+$F$14*Q14 -> 0 | T14: =H14+K14+N14+Q14 -> 246.39409 | U14: =+T14/$E$14 -> 0.25948901 | V14: =+$F$14*T14 -> 8377399.2
B15: 2.3 | C15: Suministro y Restitucion de Mortero de fachada (10% 2,2) | D15: M2 | E15: 100 | F15: 52000 | G15: =+E15*F15 -> 5200000 | H15: 58 | I15: =+H15/$E$15 -> 0.58 | J15: =+$F$15*H15 -> 3016000 | K15: 25 | L15: =+K15/$E$15 -> 0.25 | M15: =+$F$15*K15 -> 1300000 | N15: 12 | O15: =+N15/$E$15 -> 0.12 | P15: =+$F$15*N15 -> 624000 | R15: =+Q15/$E$15 -> 0 | S15: =+$F$15*Q15 -> 0 | T15: =H15+K15+N15+Q15 -> 95 | U15: =+T15/$E$15 -> 0.95 | V15: =+$F$15*T15 -> 4940000
A16: 3 | C16: PINTURA | G16: =+G17+G18+G19+G20+G21+G22 -> 90759901 | J16: =+J17+J18+J19+J20+J21+J22 -> 14663300 | M16: =+M17+M18+M19+M20+M21+M22 -> 27863747 | P16: =+P17+P18+P19+P20+P21+P22 -> 9438746.4 | S16: =+S17+S18+S19+S20+S21+S22 -> 28637762 | V16: =+V17+V18+V19+V20+V21+V22 -> 80603556
B17: 3.1 | C17: Suministro y Aplicación de Pintura para exteriores, tipo KORAZA de Pintuco, IMPERMEABILIZANTE, en fachadas de concreto con revestimiento de graniplast | D17: M2 | E17: =+'[1]TORRE 1'!G41+'[1]TORRE 1'!F56+'[1]TORRE 1'!L70 -> 3798.143 | F17: 17500 | G17: =+E17*F17 -> 66467502 | H17: 433.64 | I17: =+H17/$E$17 -> 0.11417158 | J17: =+$F$17*H17 -> 7588700 | K17: =Pintura!AE45 -> 1187.9581 | L17: =+K17/$E$17 -> 0.3127734 | M17: =+$F$17*K17 -> 20789267 | N17: =Pintura!AG45 -> 539.35694 | O17: =+N17/$E$17 -> 0.14200543 | P17: =+$F$17*N17 -> 9438746.4 | Q17: =Pintura!AA42+Pintura!AA30+Pintura!AA25+Pintura!AA15-N17-K17-H17 -> 1636.4436 | R17: =+Q17/$E$17 -> 0.4308536 | S17: =+$F$17*Q17 -> 28637762 | T17: =H17+K17+N17+Q17 -> 3797.3986 | U17: =+T17/$E$17 -> 0.99980401 | V17: =+$F$17*T17 -> 66454476
B18: 3.2 | C18: Suministro y Aplicación de Pintura para exteriores, tipo KORAZA de Pintuco, IMPERMEABILIZANTE, sobre paredes de Concreto Limpio en fachadas | D18: M2 | E18: =+'[1]TORRE 1'!G72 -> 382.96 | F18: 19400.285 | G18: =+E18*F18 -> 7429533 | H18: 0 | I18: =+H18/$E$18 -> 0 | J18: =+$F$18*H18 -> 0 | K18: 0 | L18: =+K18/$E$18 -> 0 | M18: =+$F$18*K18 -> 0 | N18: 0 | O18: =+N18/$E$18 -> 0 | P18: =+$F$18*N18 -> 0 | Q18: 0 | R18: =+Q18/$E$18 -> 0 | S18: =+$F$18*Q18 -> 0 | T18: =H18+K18+N18+Q18 -> 0 | U18: =+T18/$E$18 -> 0 | V18: =+$F$18*T18 -> 0
B19: 3.3 | C19: Suministro y Aplicación de Pintura gris basalto sobre alfajias de muros en los accesos del edificio y garajes | D19: ML | E19: =+'[1]TORRE 1'!G75 -> 53.65 | F19: 8100 | G19: =+E19*F19 -> 434565 | H19: 0 | I19: =+H19/$E$19 -> 0 | J19: =+$F$19*H19 -> 0 | K19: 0 | L19: =+K19/$E$19 -> 0 | M19: =+$F$19*K19 -> 0 | N19: 0 | O19: =+N19/$E$19 -> 0 | P19: =+$F$19*N19 -> 0 | Q19: 0 | R19: =+Q19/$E$19 -> 0 | S19: =+$F$19*Q19 -> 0 | T19: =H19+K19+N19+Q19 -> 0 | U19: =+T19/$E$19 -> 0 | V19: =+$F$19*T19 -> 0
B20: 3.4 | C20: Suministro y Aplicación de Pintura, del tipo Pintulux tres en uno de pintuco, en puertas y ventanas de fachada | D20: M2 | E20: =2.2*2+('[1]TORRE 1'!K28) -> 71 | F20: 24300 | G20: =+E20*F20 -> 1725300 | H20: 0 | I20: =+H20/$E$20 -> 0 | J20: =+$F$20*H20 -> 0 | K20: 0 | L20: =+K20/$E$20 -> 0 | M20: =+$F$20*K20 -> 0 | N20: 0 | O20: =+N20/$E$20 -> 0 | P20: =+$F$20*N20 -> 0 | Q20: 0 | R20: =+Q20/$E$20 -> 0 | S20: =+$F$20*Q20 -> 0 | T20: =H20+K20+N20+Q20 -> 0 | U20: =+T20/$E$20 -> 0 | V20: =+$F$20*T20 -> 0
B21: 3.5 | C21: Suministro y aplicación de pintura, del tipo pintulux 3 en 1 de pintuco, en barandas de parqueaderos | D21: ML | E21: =+(5.5+2.6)*3 -> 24.3 | F21: 22400 | G21: =+E21*F21 -> 544320 | H21: 0 | I21: =+H21/$E$21 -> 0 | J21: =+$F$21*H21 -> 0 | K21: 0 | L21: =+K21/$E$21 -> 0 | M21: =+$F$21*K21 -> 0 | N21: 0 | O21: =+N21/$E$21 -> 0 | P21: =+$F$21*N21 -> 0 | Q21: 0 | R21: =+Q21/$E$21 -> 0 | S21: =+$F$21*Q21 -> 0 | T21: =H21+K21+N21+Q21 -> 0 | U21: =+T21/$E$21 -> 0 | V21: =+$F$21*T21 -> 0
B22: 3.6 | C22: Suministro y Aplicación de Pintura en interiores- Paredes y cielo raso de pasillos y porteria | D22: M2 | E22: =+'[1]TORRE 1'!L50 -> 1179.89 | F22: 12000 | G22: =+E22*F22 -> 14158680 | H22: 589.55 | I22: =+H22/$E$22 -> 0.49966522 | J22: =+$F$22*H22 -> 7074600 | K22: =Pintura!AE60 -> 589.54 | L22: =+K22/$E$22 -> 0.49965675 | M22: =+$F$22*K22 -> 7074480 | N22: 0 | O22: =+N22/$E$22 -> 0 | P22: =+$F$22*N22 -> 0 | Q22: =Pintura!AA60-'Acta Av Obra 03 - ene 21 2026'!H22-'Acta Av Obra 03 - ene 21 2026'!K22 -> 0 | R22: =+Q22/$E$22 -> 0 | S22: =+$F$22*Q22 -> 0 | T22: =H22+K22+N22+Q22 -> 1179.09 | U22: =+T22/$E$22 -> 0.99932197 | V22: =+$F$22*T22 -> 14149080
A23: 4 | C23: REPARACIONES y PROTECCIONES ESPECIALES | G23: =+G24+G25+G26+G27+G28+G29 -> 38695430 | J23: =+J24+J25+J26+J27+J28+J29 -> 635804 | M23: =+M24+M25+M26+M27+M28+M29 -> 4407492.4 | P23: =+P24+P25+P26+P27+P28+P29 -> 4026577 | S23: =+S24+S25+S26+S27+S28+S29 -> 3893866.6 | V23: =+V24+V25+V26+V27+V28+V29 -> 12963740
B24: 4.1 | C24: Suministro e instalacion de cortagoteras en fachadas y balcones | D24: ML | E24: =+'[1]TORRE 1'!L83 -> 346.79 | F24: 37000 | G24: =+E24*F24 -> 12831230 | H24: 0 | I24: =+H24/$E$24 -> 0 | J24: =+$F$24*H24 -> 0 | K24: 85 | L24: =+K24/$E$24 -> 0.24510511 | M24: =+$F$24*K24 -> 3145000 | N24: 58 | O24: =+N24/$E$24 -> 0.16724819 | P24: =+$F$24*N24 -> 2146000 | R24: =+Q24/$E$24 -> 0 | S24: =+$F$24*Q24 -> 0 | T24: =H24+K24+N24+Q24 -> 143 | U24: =+T24/$E$24 -> 0.4123533 | V24: =+$F$24*T24 -> 5291000
B25: 4.2 | C25: Retiro y Restitucion de sellos en elementos vidriados de las areas comunes y fachadas del edificio (60%) | D25: ML | E25: =+'[1]TORRE 1'!I29*0.6 -> 1450.14 | F25: 5200 | G25: =+E25*F25 -> 7540728 | H25: 122.27 | I25: =+H25/$E$25 -> 0.084315997 | J25: =+$F$25*H25 -> 635804 | K25: =Sellos!AE46 -> 242.787 | L25: =+K25/$E$25 -> 0.16742315 | M25: =+$F$25*K25 -> 1262492.4 | N25: =Sellos!AG46 -> 163.5725 | O25: =+N25/$E$25 -> 0.11279773 | P25: =+$F$25*N25 -> 850577 | Q25: =Sellos!AA46-'Acta Av Obra 03 - ene 21 2026'!N25-'Acta Av Obra 03 - ene 21 2026'!K25-'Acta Av Obra 03 - ene 21 2026'!H25 -> 748.8205 | R25: =+Q25/$E$25 -> 0.51637807 | S25: =+$F$25*Q25 -> 3893866.6 | T25: =H25+K25+N25+Q25 -> 1277.45 | U25: =+T25/$E$25 -> 0.88091495 | V25: =+$F$25*T25 -> 6642740
B26: 4.3 | C26: Sellamiento de elementos varios en balcones | D26: ML | E26: =+'[1]TORRE 1'!L83 -> 346.79 | F26: 5200 | G26: =+E26*F26 -> 1803308 | H26: 0 | I26: =+H26/$E$26 -> 0 | J26: =+$F$26*H26 -> 0 | K26: 0 | L26: =+K26/$E$26 -> 0 | M26: =+$F$26*K26 -> 0 | N26: 0 | O26: =+N26/$E$26 -> 0 | P26: =+$F$26*N26 -> 0 | Q26: 0 | R26: =+Q26/$E$26 -> 0 | S26: =+$F$26*Q26 -> 0 | T26: =H26+K26+N26+Q26 -> 0 | U26: =+T26/$E$26 -> 0 | V26: =+$F$26*T26 -> 0
B27: 4.4 | C27: Suministro e Instalacion de Alfajias en lamina en el perimetro y muros medianeros de las cubiertas del edificio | D27: ML | E27: =+'[1]TORRE 1'!K87 -> 122 | F27: 63000 | G27: =+E27*F27 -> 7686000 | H27: 0 | I27: =+H27/$E$27 -> 0 | J27: =+$F$27*H27 -> 0 | K27: 0 | L27: =+K27/$E$27 -> 0 | M27: =+$F$27*K27 -> 0 | N27: 0 | O27: =+N27/$E$27 -> 0 | P27: =+$F$27*N27 -> 0 | Q27: 0 | R27: =+Q27/$E$27 -> 0 | S27: =+$F$27*Q27 -> 0 | T27: =H27+K27+N27+Q27 -> 0 | U27: =+T27/$E$27 -> 0 | V27: =+$F$27*T27 -> 0
B28: 4.5 | C28: Conformacion de escurrideros en antepechos de balcones y en otros elementos de la fachada | D28: M2 | E28: =+('[1]TORRE 1'!M83+'[1]TORRE 1'!K53+'[1]TORRE 1'!K55+'[1]TORRE 1'!C55:E55+'[1]TORRE 1'!C51:E51)*0.2+'[1]TORRE 1'!G71 -> 45.2797 | F28: 41200 | G28: =+E28*F28 -> 1865523.6 | H28: 0 | I28: =+H28/$E$28 -> 0 | J28: =+$F$28*H28 -> 0 | K28: 0 | L28: =+K28/$E$28 -> 0 | M28: =+$F$28*K28 -> 0 | N28: 25 | O28: =+N28/$E$28 -> 0.5521238 | P28: =+$F$28*N28 -> 1030000 | R28: =+Q28/$E$28 -> 0 | S28: =+$F$28*Q28 -> 0 | T28: =H28+K28+N28+Q28 -> 25 | U28: =+T28/$E$28 -> 0.5521238 | V28: =+$F$28*T28 -> 1030000
B29: 4.6 | C29: Impermeabilizacion de muros internos en las cubiertas del edificio | D29: M2 | E29: =+'[1]TORRE 1'!K92 -> 97.6 | F29: 71400 | G29: =+E29*F29 -> 6968640 | H29: 0 | I29: =+H29/$E$29 -> 0 | J29: =+$F$29*H29 -> 0 | K29: 0 | L29: =+K29/$E$29 -> 0 | M29: =+$F$29*K29 -> 0 | N29: 0 | O29: =+N29/$E$29 -> 0 | P29: =+$F$29*N29 -> 0 | Q29: 0 | R29: =+Q29/$E$29 -> 0 | S29: =+$F$29*Q29 -> 0 | T29: =H29+K29+N29+Q29 -> 0 | U29: =+T29/$E$29 -> 0 | V29: =+$F$29*T29 -> 0
A30: 5 | C30: TRATAMIENTO DE CUBIERTAS EN GENERAL | G30: =+G31+G32+G33+G34 -> 29601800 | J30: =+J31+J32+J33+J34 -> 0 | M30: =+M31+M32+M33+M34 -> 0 | P30: =+P31+P32+P33+P34 -> 0 | S30: =+S31+S32+S33+S34 -> 0 | V30: =+V31+V32+V33+V34+V35+V36 -> 1150000
B31: 5.1 | C31: Retiro de cubiertas antiguas y Suministro e Instalacion de Cubiertas Nuevas en Fibrocemento | D31: M2 | E31: =+'[1]TORRE 1'!K86 -> 395 | F31: 65000 | G31: =+E31*F31 -> 25675000 | H31: 0 | I31: =+H31/$E$31 -> 0 | J31: =+$F$31*H31 -> 0 | K31: 0 | L31: =+K31/$E$31 -> 0 | M31: =+$F$31*K31 -> 0 | N31: 0 | O31: =+N31/$E$31 -> 0 | P31: =+$F$31*N31 -> 0 | Q31: 0 | R31: =+Q31/$E$31 -> 0 | S31: =+$F$31*Q31 -> 0 | T31: =H31+K31+N31+Q31 -> 0 | U31: =+T31/$E$31 -> 0 | V31: =+$F$31*T31 -> 0
B32: 5.2 | C32: Suministro e instalacion de teja translucida en vacio del edificio | D32: M2 | E32: 29.6 | F32: 71000 | G32: =+E32*F32 -> 2101600 | H32: 0 | I32: =+H32/$E$32 -> 0 | J32: =+$F$32*H32 -> 0 | K32: 0 | L32: =+K32/$E$32 -> 0 | M32: =+$F$32*K32 -> 0 | N32: 0 | O32: =+N32/$E$32 -> 0 | P32: =+$F$32*N32 -> 0 | Q32: 0 | R32: =+Q32/$E$32 -> 0 | S32: =+$F$32*Q32 -> 0 | T32: =H32+K32+N32+Q32 -> 0 | U32: =+T32/$E$32 -> 0 | V32: =+$F$32*T32 -> 0
B33: 5.3 | C33: Impermeabilizacion de la placa del cuarto de maquinas | D33: M2 | E33: 35 | F33: 39000 | G33: =+E33*F33 -> 1365000 | H33: 0 | I33: =+H33/$E$33 -> 0 | J33: =+$F$33*H33 -> 0 | K33: 0 | L33: =+K33/$E$33 -> 0 | M33: =+$F$33*K33 -> 0 | N33: 0 | O33: =+N33/$E$33 -> 0 | P33: =+$F$33*N33 -> 0 | Q33: 0 | R33: =+Q33/$E$33 -> 0 | S33: =+$F$33*Q33 -> 0 | T33: =H33+K33+N33+Q33 -> 0 | U33: =+T33/$E$33 -> 0 | V33: =+$F$33*T33 -> 0
B34: 5.4 | C34: Impermeabilizacion y tratamiento general a la viga canal de cubierta | D34: M2 | E34: 11.8 | F34: 39000 | G34: =+E34*F34 -> 460200 | H34: 0 | I34: =+H34/$E$34 -> 0 | J34: =+$F$34*H34 -> 0 | K34: 0 | L34: =+K34/$E$34 -> 0 | M34: =+$F$34*K34 -> 0 | N34: 0 | O34: =+N34/$E$34 -> 0 | P34: =+$F$34*N34 -> 0 | Q34: 0 | R34: =+Q34/$E$34 -> 0 | S34: =+$F$34*Q34 -> 0 | T34: =H34+K34+N34+Q34 -> 0 | U34: =+T34/$E$34 -> 0 | V34: =+$F$34*T34 -> 0
A35: 6 | C35: ASEO DE OBRA Y RETIRO DE ESCOMBROS | G35: =+G36+G37 -> 1800000 | J35: =+J36+J37 -> 0 | M35: =+M36+M37 -> 0 | P35: =+P36+P37 -> 0 | S35: =+S36+S37 -> 900000 | V35: =+V36+V37 -> 900000
B36: 6.1 | C36: Aseo general durante y al final de la obra | D36: Gl | E36: 1 | F36: 500000 | G36: =+E36*F36 -> 500000 | H36: 0 | I36: =+H36/$E$36 -> 0 | J36: =+$F$36*H36 -> 0 | K36: 0 | L36: =+K36/$E$36 -> 0 | M36: =+$F$36*K36 -> 0 | N36: 0 | O36: =+N36/$E$36 -> 0 | P36: =+$F$36*N36 -> 0 | Q36: 0.5 | R36: =+Q36/$E$36 -> 0.5 | S36: =+$F$36*Q36 -> 250000 | T36: =H36+K36+N36+Q36 -> 0.5 | U36: =+T36/$E$36 -> 0.5 | V36: =+$F$36*T36 -> 250000
B37: 6.2 | C37: Retiro de Escombros y disposicion final | D37: Gl | E37: 1 | F37: 1300000 | G37: =+E37*F37 -> 1300000 | H37: 0 | I37: =+H37/$E$37 -> 0 | J37: =+$F$37*H37 -> 0 | K37: 0 | L37: =+K37/$E$37 -> 0 | M37: =+$F$37*K37 -> 0 | N37: 0 | O37: =+N37/$E$37 -> 0 | P37: =+$F$37*N37 -> 0 | Q37: 0.5 | R37: =+Q37/$E$37 -> 0.5 | S37: =+$F$37*Q37 -> 650000 | T37: =H37+K37+N37+Q37 -> 0.5 | U37: =+T37/$E$37 -> 0.5 | V37: =+$F$37*T37 -> 650000
A38: Aprobado por Interventoria: Ing. Luis Fernando Márquez Jaramillo | E38: costo directo | G38: =+G7+G12+G16+G23+G30+G35 -> 2.2030231e+08 | H38: costo directo | J38: =+J7+J12+J16+J23+J30+J35 -> 28106629 | K38: costo directo | M38: =+M7+M12+M16+M23+M30+M35 -> 35550239 | N38: costo directo | P38: =+P7+P12+P16+P23+P30+P35 -> 18283661 | Q38: costo directo | S38: =+S7+S12+S16+S23+S30+S35 -> 37992050 | T38: costo directo | V38: =+V7+V12+V16+V23+V30+V35 -> 1.2108258e+08
E39: A | F39: 0.08 | G39: =+$G$38*F39 -> 17624184 | H39: A | I39: 0.08 | J39: =+J38*I39 -> 2248530.3 | K39: A | L39: 0.08 | M39: =+M38*L39 -> 2844019.1 | N39: A | O39: 0.08 | P39: =+P38*O39 -> 1462692.9 | Q39: A | R39: 0.08 | S39: =+S38*R39 -> 3039364 | T39: A | U39: 0.08 | V39: =+V38*U39 -> 9686606.3
E40: I | F40: 0.03 | G40: =+$G$38*F40 -> 6609069.2 | H40: I | I40: 0.03 | J40: =+J38*I40 -> 843198.86 | K40: I | L40: 0.03 | M40: =+M38*L40 -> 1066507.2 | N40: I | O40: 0.03 | P40: =+P38*O40 -> 548509.82 | Q40: I | R40: 0.03 | S40: =+S38*R40 -> 1139761.5 | T40: I | U40: 0.03 | V40: =+V38*U40 -> 3632477.4
E41: U | F41: 0.05 | G41: =+$G$38*F41 -> 11015115 | H41: U | I41: 0.05 | J41: =+J38*I41 -> 1405331.4 | K41: U | L41: 0.05 | M41: =+M38*L41 -> 1777512 | N41: U | O41: 0.05 | P41: =+P38*O41 -> 914183.04 | Q41: U | R41: 0.05 | S41: =+S38*R41 -> 1899602.5 | T41: U | U41: 0.05 | V41: =+V38*U41 -> 6054128.9
E42: Subtotal antes de IVA | G42: =+G38+G39+G40+G41 -> 2.5555067e+08 | H42: Subtotal antes de IVA | J42: =+J38+J39+J40+J41 -> 32603689 | K42: Subtotal antes de IVA | M42: =+M38+M39+M40+M41 -> 41238278 | N42: Subtotal antes de IVA | P42: =+P38+P39+P40+P41 -> 21209046 | Q42: Subtotal antes de IVA | S42: =+S38+S39+S40+S41 -> 44070778 | T42: Subtotal antes de IVA | V42: =+V38+V39+V40+V41 -> 1.4045579e+08
E43: IVA/U | F43: 0.19 | G43: =+G41*F43 -> 2092871.9 | H43: IVA/U | I43: 0.19 | J43: =+J41*I43 -> 267012.97 | K43: IVA/U | L43: 0.19 | M43: =+M41*L43 -> 337727.27 | N43: IVA/U | O43: 0.19 | P43: =+P41*O43 -> 173694.78 | Q43: IVA/U | R43: 0.19 | S43: =+S41*R43 -> 360924.47 | T43: IVA/U | U43: 0.19 | V43: =+V41*U43 -> 1150284.5
E44: total costo | G44: =+G42+G43 -> 2.5764355e+08 | H44: total costo | J44: =+J42+J43 -> 32870702 | K44: total costo | M44: =+M42+M43 -> 41576005 | N44: total costo | P44: =+P42+P43 -> 21382741 | Q44: total costo | S44: =+S42+S43 -> 44431702 | T44: total costo | V44: =+V42+V43 -> 1.4160608e+08
H45: retefuente | I45: -0.02 | J45: =+J42*I45 -> -652073.79 | K45: retefuente | L45: -0.02 | M45: =+M42*L45 -> -824765.55 | N45: retefuente | O45: -0.02 | P45: =+P42*O45 -> -424180.93 | Q45: retefuente | R45: -0.02 | S45: =+S42*R45 -> -881415.55 | T45: retefuente | U45: -0.02 | V45: =+V42*U45 -> -2809115.8
H46: amortizac anticipo | I46: -0.2 | J46: =+J44*I46 -> -6574140.5 | K46: amortizac anticipo | L46: -0.2 | M46: =+M44*L46 -> -8315201 | N46: amortizac anticipo | O46: -0.2 | P46: =+P44*O46 -> -4276548.3 | Q46: amortizac anticipo | R46: -0.2 | S46: =+S44*R46 -> -8886340.4 | T46: amortizac anticipo | U46: -0.2 | V46: =+V44*U46 -> -28321215
H47: retegarantia | I47: -0.1 | J47: =+J44*I47 -> -3287070.2 | K47: retegarantia | L47: -0.1 | M47: =+M44*L47 -> -4157600.5 | N47: retegarantia | O47: -0.1 | P47: =+P44*O47 -> -2138274.1 | Q47: retegarantia | R47: -0.1 | S47: =+S44*R47 -> -4443170.2 | T47: retegarantia | U47: -0.1 | V47: =+V44*U47 -> -14160608
C48: Valor Contrato | E48: =+G44 -> 2.5764355e+08 | H48: Total Desembolso | J48: =SUM(J44:J47) -> 22357418 | K48: Total Desembolso | M48: =SUM(M44:M47) -> 28278438 | N48: Total Desembolso | P48: =SUM(P44:P47) -> 14543738 | Q48: Total Desembolso | S48: =SUM(S44:S47) -> 30220776 | T48: Total Desembolso | V48: =SUM(V44:V47) -> 96315137
C49: Valor Anticipo | E49: =+E48*20% -> 51528709
C50: Vr Amortizacion Anticipo esta acta | D50: 0.13 | E50: =+J46 -> -6574140.5
C51: Saldo por Amortizar | E51: =+E49+E50 -> 44954569
C52: Vr Esta Acta | E52: =+J44 -> 32870702
C53: % ejecucion | E53: =+E52/E48 -> 0.12758209

Sheet Estado de la Obra
A6: Estado de obra - Actividades ejecutadas | D6: Semana # | E6: 12 | F6: 46042
A7: Edificio El Mirador
B9: Descripción | C9: UM | D9: Cantidad | E9: Cantidas Ejecutada | F9: Cantidad Restante | G9: Porcentaje restante | H9: %
B11: Lavado de superficie de fachada | C11: M2 | D11: =5019.54*0.76 -> 3814.8504 | E11: =Lavado!W46 -> 3797.3986 | F11: =D11-E11 -> 17.451792 | G11: =1-(E11/D11) -> 0.0045746989 | H11: =E11/D11 -> 0.9954253 | I11: 0.15 | J11: =H11*I11 -> 0.1493138
B13: Resane de superficie y aplicación de graniplast en superficie de fachada | C13: M2 | D13: =3798*0.125 -> 474.75 | E13: =Graniplast!W46 -> 246.39969 | F13: =D13-E13 -> 228.35031 | G13: =1-(E13/D13) -> 0.48099065 | H13: =E13/D13 -> 0.51900935 | I13: 0.15 | J13: =H13*I13 -> 0.077851403
B15: Aplicación de sello en ventanas y balcones | C15: M2 | D15: =1450.14*0.7 -> 1015.098 | E15: =Sellos!AA46 -> 1277.45 | F15: =D15-E15 -> -262.352 | G15: =1-(E15/D15) -> -0.25844992 | H15: =E15/D15 -> 1.2584499 | I15: 0.2 | J15: =H15*I15 -> 0.25168998
B17: Aplicación de pintura en superficie de fachada | C17: Und | D17: 4234.75 | E17: =Pintura!AA45 -> 3797.3986 | F17: =D17-E17 -> 437.35139 | G17: =1-(E17/D17) -> 0.10327679 | H17: =E17/D17 -> 0.89672321 | I17: 0.25 | J17: =H17*I17 -> 0.2241808
B19: Aplicación de pintura en pasillos | C19: CÑ | D19: 1179.89 | E19: =Pintura!AA60 -> 1179.09 | F19: =D19-E19 -> 0.8 | G19: =1-(E19/D19) -> 0.00067802931 | H19: =E19/D19 -> 0.99932197 | I19: 0.1 | J19: =H19*I19 -> 0.099932197
B21: Instalación de cortagoteras | C21: UND | D21: 346.79 | E21: 143.92 | F21: =D21-E21 -> 202.87 | G21: =1-(E21/D21) -> 0.5849938 | H21: =E21/D21 -> 0.4150062 | I21: 0.075 | J21: =H21*I21 -> 0.031125465
B23: Instalación de tejas UPVC | C23: UND | D23: 395 | E23: 0 | F23: =D23-E23 -> 395 | G23: =1-(E23/D23) -> 1 | H23: =E23/D23 -> 0 | I23: 0.075 | J23: =H23*I23 -> 0
B25: Estado General de la Obra | C25: GLB | D25: 1 | E25: =J25 -> 0.83409365 | F25: =D25-E25 -> 0.16590635 | G25: =1-(E25/D25) -> 0.16590635 | H25: =E25/D25 -> 0.83409365 | I25: =SUM(I11:I24) -> 1 | J25: =SUM(J11:J24) -> 0.83409365
B27: Plantilla | C27: UND | D27: 1 | E27: 1 | F27: =D27-E27 -> 0 | G27: 1 | H27: =E27/D27 -> 1

Sheet CO
A2: EDIFICIO EL MIRADOR
D3: DIMENSIONES | G3: DESCUENTOS
A4: TORRE | B4: SECCIÓN | C4: DESCRIPCIÓN | D4: ALTO | E4: ANCHO | F4: TOTAL (M2) | G4: ALTO | H4: ANCHO | I4: CANTIDAD | J4: TOTAL (M2) | K4: CARTERAS (ML) | L4: DILATACIÓN (ML) | M4: ÁREA TOTAL (BLANCA) | N4: ÁREA TOTAL (NEGRA) | O4: ÁREA TOTAL
C5: FACHADA ESTE
B6: 1 | C6: Muro con ventana (Blanca) | D6: =(2.6*5)+1 -> 14 | E6: 6.98 | F6: =D6*E6 -> 97.72 | G6: 2.2 | H6: 2 | I6: 4 | J6: =(G6*H6)*I6 -> 17.6 | K6: =((G6+H6)*2)*I6 -> 33.6 | M6: =F6-J6 -> 80.12 | O6: =M6+N6 -> 80.12
C7: Franja negra en fachada | D7: 1 | E7: 6.98 | F7: =D7*E7 -> 6.98 | N7: =F7-J7 -> 6.98 | O7: =M7+N7 -> 6.98
C8: Antepechos negros | D8: 1 | E8: 2.2 | F8: =D8*E8 -> 2.2 | M8: =F8-J8 -> 2.2 | O8: =M8+N8 -> 2.2
B9: 2 | C9: Culata baja sin ventanas (Blanca) | D9: 11 | E9: 3.2 | F9: =D9*E9 -> 35.2 | G9: 3.2 | H9: 1.5 | I9: 1 | J9: =(G9*H9)*I9 -> 4.8 | M9: =F9-J9 -> 30.4 | O9: =M9+N9 -> 30.4
C10: Culata Franja negra | D10: 1 | E10: 5.15 | F10: =D10*E10 -> 5.15 | N10: =F10-J10 -> 5.15 | O10: =M10+N10 -> 5.15
B11: 3 | C11: Muro con ventana (Blanca) | D11: =D13 -> 16.6 | E11: 3.35 | F11: =D11*E11 -> 55.61 | G11: 1.8 | H11: 1.8 | I11: 5 | J11: =(G11*H11)*I11 -> 16.2 | K11: =((G11+H11)*2)*I11 -> 36 | M11: =F11-J11 -> 39.41 | O11: =M11+N11 -> 39.41
C12: Franja negra en fachada | D12: 11 | E12: 0.8 | F12: =D12*E12 -> 8.8 | N12: =F12-J12 -> 8.8 | O12: =M12+N12 -> 8.8
A13: 1 | B13: 4 | C13: Culata alta sin ventanas (Blanca) | D13: =(2.6*6)+1 -> 16.6 | E13: 11.03 | F13: =D13*E13 -> 183.098 | G13: =(4*2.7) -> 10.8 | H13: 7 | I13: 1 | J13: =(G13*H13)*I13 -> 75.6 | M13: =F13-J13 -> 107.498 | O13: =M13+N13 -> 107.498
K15: =SUM(K6:K14) -> 69.6 | O15: =M15+N15 -> 0
C16: TOTAL M2 DE FACHADA SIN DESCUENTOS | F16: =SUM(F6:F15) -> 394.758 | I16: TOTAL M2 DE FACHADA CON DESCUENTOS | M16: =SUM(M6:M15) -> 259.628 | N16: =SUM(N6:N15) -> 20.93 | O16: =SUM(O6:O15) -> 280.558
C19: FACHADA ESTE
C20: Fachada General | F20: 1398
B21: 5 | C21: Muro con balcones y volumenes | D21: 25.2 | E21: =3.06+3.09+0.15+3+1+3.5+0.85+3+1+3.5+0.5 -> 22.65 | F21: =D21*E21 -> 570.78 | G21: 2.1 | H21: 6.15 | I21: 2 | J21: =(G21*H21)*I21 -> 25.83 | K21: =((G21*2+H21))*I21 -> 20.7 | M21: =F21-SUM(J21:J27) -> 350.225 | O21: =M21+N21 -> 350.225
G22: 2.1 | H22: 3 | I22: 4 | J22: =(G22*H22)*I22 -> 25.2 | K22: =((G22*2+H22))*I22 -> 28.8
G23: 1.65 | H23: 2.45 | I23: 5 | J23: =(G23*H23)*I23 -> 20.2125 | K23: =((G23*2+H23))*I23 -> 28.75
G24: 1.65 | H24: 2 | I24: 4 | J24: =(G24*H24)*I24 -> 13.2 | K24: =((G24*2+H24))*I24 -> 21.2
G25: 1.65 | H25: 3.5 | I25: 3 | J25: =(G25*H25)*I25 -> 17.325 | K25: =((G25*2+H25))*I25 -> 20.4
G26: 1.65 | H26: 1.55 | I26: 5 | J26: =(G26*H26)*I26 -> 12.7875 | K26: =((G26*2+H26))*I26 -> 24.25
G27: 2 | H27: 2.65 | I27: 20 | J27: =(G27*H27)*I27 -> 106 | K27: =((G27*2+H27))*I27 -> 133
C28: Muro culata parqueadero | D28: 9.4 | E28: 40 | F28: =D28*E28 -> 376 | M28: =F28 -> 376 | O28: =M28+N28 -> 376
B30: 6 | C30: Muro sin ventanas | D30: 21.5 | E30: 1.2 | F30: =D30*E30 -> 25.8 | M30: =F30 -> 25.8 | O30: =M30+N30 -> 25.8
B31: 7 | C31: Muro con balcones y volumenes | D31: 25.2 | E31: 7.5 | F31: =D31*E31 -> 189 | G31: 2.1 | H31: 2.4 | I31: 2 | J31: =(G31*H31)*I31 -> 10.08 | K31: =((G31*2+H31))*I31 -> 13.2 | M31: =F31-SUM(J31:J35) -> 117.73 | O31: =M31+N31 -> 117.73
G32: 1.65 | H32: 2.45 | I32: 2 | J32: =(G32*H32)*I32 -> 8.085 | K32: =((G32*2+H32))*I32 -> 11.5
G33: 1.65 | H33: 3.5 | I33: 1 | J33: =(G33*H33)*I33 -> 5.775 | K33: =((G33*2+H33))*I33 -> 6.8
G34: 1.65 | H34: 1.55 | I34: 4 | J34: =(G34*H34)*I34 -> 10.23 | K34: =((G34*2+H34))*I34 -> 19.4
G35: 2 | H35: 2.65 | I35: 7 | J35: =(G35*H35)*I35 -> 37.1 | K35: =((G35*2+H35))*I35 -> 46.55
K36: =SUM(K31:K35) -> 97.45
B37: 8 | C37: Muro sin ventanas | D37: 21.5 | E37: 1.2 | F37: =D37*E37 -> 25.8 | M37: =F37 -> 25.8 | O37: =M37+N37 -> 25.8
B39: 9 | C39: Muro con balcones y volumenes | D39: 25 | E39: 8.45 | F39: =D39*E39 -> 211.25 | G39: 1.65 | H39: 3 | I39: 4 | J39: =(G39*H39)*I39 -> 19.8 | K39: =((G39*2+H39))*I39 -> 25.2 | M39: =F39-SUM(J39:J43) -> 142.3925 | O39: =M39+N39 -> 142.3925
G40: 1.65 | H40: 3.35 | I40: 5 | J40: =(G40*H40)*I40 -> 27.6375 | K40: =((G40*2+H40))*I40 -> 33.25
G41: 1.65 | H41: 2.1 | I41: 4 | J41: =(G41*H41)*I41 -> 13.86 | K41: =((G41*2+H41))*I41 -> 21.6
G42: 1.35 | H42: 4.2 | I42: 1 | J42: =(G42*H42)*I42 -> 5.67 | K42: =((G42*2+H42))*I42 -> 6.9
G43: 1.35 | H43: 1.4 | I43: 1 | J43: =(G43*H43)*I43 -> 1.89 | K43: =((G43*2+H43))*I43 -> 4.1
K44: =SUM(K39:K43) -> 91.05
C46: TOTAL M2 DE FACHADA SIN DESCUENTOS | F46: =SUM(F21:F45) -> 1398.63 | I46: TOTAL M2 DE FACHADA CON DESCUENTOS | M46: =SUM(M21:M45) -> 1037.9475 | N46: =SUM(N21:N45) -> 0 | O46: =SUM(O21:O45) -> 1037.9475
C49: FACHADASUR
C50: Fachada General | F50: 545.6
B51: 10 | C51: Muro con balcones y volumenes | D51: 30.75 | E51: 17.75 | F51: =D51*E51 -> 545.8125 | G51: 2.1 | H51: 3 | I51: 14 | J51: =(G51*H51)*I51 -> 88.2 | K51: =((G51*2+H51))*I51 -> 100.8 | M51: =F51-SUM(J51:J55) -> 417.2325 | O51: =M51+N51 -> 417.2325
G52: 1.5 | H52: 0.8 | I52: 14 | J52: =(G52*H52)*I52 -> 16.8 | K52: =((G52*2+H52))*I52 -> 53.2
G53: 2.5 | H53: 0.35 | I53: 14 | J53: =(G53*H53)*I53 -> 12.25 | K53: =((G53*2+H53))*I53 -> 74.9
G54: 2.2 | H54: 0.75 | I54: 3 | J54: =(G54*H54)*I54 -> 4.95 | K54: =((G54*2+H54))*I54 -> 15.45
G55: 2.2 | H55: 2.9 | I55: 1 | J55: =(G55*H55)*I55 -> 6.38 | K55: =((G55*2+H55))*I55 -> 7.3
C57: TOTAL M2 DE FACHADA SIN DESCUENTOS | F57: =SUM(F51:F56) -> 545.8125 | I57: TOTAL M2 DE FACHADA CON DESCUENTOS | M57: =SUM(M51:M56) -> 417.2325 | N57: =SUM(N51:N56) -> 0 | O57: =SUM(O51:O56) -> 417.2325
C60: FACHADA OESTE
C61: Fachada General | F61: 1118
B62: 11 | C62: Muro con balcones y volumenes | D62: 27.2 | E62: 8.5 | F62: =D62*E62 -> 231.2 | G62: 1.65 | H62: 3.4 | I62: 6 | J62: =(G62*H62)*I62 -> 33.66 | K62: =((G62*2+H62))*I62 -> 40.2 | M62: =F62-SUM(J62:J65) -> 140.615 | O62: =M62+N62 -> 140.615
G63: 1.65 | H63: 3 | I63: 4 | J63: =(G63*H63)*I63 -> 19.8 | K63: =((G63*2+H63))*I63 -> 25.2
G64: 1.65 | H64: 2.1 | I64: 5 | J64: =(G64*H64)*I64 -> 17.325 | K64: =((G64*2+H64))*I64 -> 27
G65: 1.65 | H65: 2 | I65: 6 | J65: =(G65*H65)*I65 -> 19.8 | K65: =((G65*2+H65))*I65 -> 31.8
B66: 12 | C66: Muro sin ventanas | D66: 24 | E66: 2.15 | F66: =D66*E66 -> 51.6 | M66: =F66 -> 51.6 | O66: =M66+N66 -> 51.6
B67: 13 | C67: Muro con balcones y volumenes | D67: 27.2 | E67: 17.5 | F67: =D67*E67 -> 476 | G67: 1.5 | H67: 2 | I67: 20 | J67: =(G67*H67)*I67 -> 60 | K67: =((G67*2+H67))*I67 -> 100 | M67: =F67-SUM(J67:J69) -> 354 | O67: =M67+N67 -> 354
G68: 2 | H68: 2.5 | I68: 4 | J68: =(G68*H68)*I68 -> 20 | K68: =((G68*2+H68))*I68 -> 26
G69: 2.1 | H69: 2.5 | I69: 8 | J69: =(G69*H69)*I69 -> 42 | K69: =((G69*2+H69))*I69 -> 53.6
B70: 14 | C70: Muro sin ventanas | D70: 21.5 | E70: 1.5 | F70: =D70*E70 -> 32.25 | M70: =F70 -> 32.25 | O70: =M70+N70 -> 32.25
B72: 15 | C72: Muro con balcones y volumenes | D72: 27.2 | E72: 6.52 | F72: =D72*E72 -> 177.344 | G72: 1.65 | H72: 3 | I72: 2 | J72: =(G72*H72)*I72 -> 9.9 | K72: =((G72*2+H72))*I72 -> 12.6 | M72: =F72-SUM(J72:J75) -> 111.794 | O72: =M72+N72 -> 111.794
G73: 1.65 | H73: 2.1 | I73: 10 | J73: =(G73*H73)*I73 -> 34.65 | K73: =((G73*2+H73))*I73 -> 54
G74: 2.1 | H74: 2.5 | I74: 4 | J74: =(G74*H74)*I74 -> 21 | K74: =((G74*2+H74))*I74 -> 26.8
B75: 16 | C75: Muro sin ventanas | D75: 21.5 | E75: 0.7 | F75: =D75*E75 -> 15.05 | M75: =F75 -> 15.05 | O75: =M75+N75 -> 15.05
B77: 15 | C77: Muro con balcones y volumenes | D77: 27.2 | E77: 3.5 | F77: =D77*E77 -> 95.2 | G77: 1.65 | H77: 3 | I77: 2 | J77: =(G77*H77)*I77 -> 9.9 | K77: =((G77*2+H77))*I77 -> 12.6 | M77: =F77-SUM(J77:J79) -> 29.65 | O77: =M77+N77 -> 29.65
G78: 1.65 | H78: 2.1 | I78: 10 | J78: =(G78*H78)*I78 -> 34.65 | K78: =((G78*2+H78))*I78 -> 54
G79: 2.1 | H79: 2.5 | I79: 4 | J79: =(G79*H79)*I79 -> 21 | K79: =((G79*2+H79))*I79 -> 26.8
B80: General | C80: Volumes en fachada | D80: 3.55 | E80: 11 | F80: =D80*E80 -> 39.05 | M80: =F80 -> 39.05 | O80: =M80+N80 -> 39.05
C82: TOTAL M2 DE FACHADA SIN DESCUENTOS | F82: =SUM(F62:F80) -> 1117.694 | I82: TOTAL M2 DE FACHADA CON DESCUENTOS | M82: =SUM(M62:M79) -> 734.959 | N82: =SUM(N62:N79) -> 0 | O82: =SUM(O62:O79) -> 734.959
C85: TOTAL M2 DE FACHADA GENERAL SIN DESCUENTOS | F85: =F16+F46+F57+F82 -> 3456.8945 | I85: TOTAL M2 DE FACHADA CON DESCUENTOS | O85: =O16+O46+O57+O82 -> 2470.697
F87: 3798 | O87: =O85/F85 -> 0.71471577

Sheet CO SIF
A1: 45969
A2: EDIFICIO PANORAMIKA | F2: 1.0985 | G2: 1.1
F3: =E43 -> 0.60139175 | G3: =F43 -> 0
A4: FACHADA | B4: SECCIÓN | C4: DESCRIPCIÓN | D4: ÁREA TOTAL | E4: CON DESCUENTOS
C5: FACHADA NORTE
A6: SUR | B6: 1 | C6: Muro con ventanas y balcones | D6: =SUM(CO!F6:F8) -> 106.9 | E6: =D6*$F$2 -> 117.42965
B7: 2 | C7: Muro con ventanas y balcones | D7: =SUM(CO!F9:F10) -> 40.35 | E7: =D7*$F$2 -> 44.324475
B8: 3 | C8: Muro sin ventanas | D8: =SUM(CO!F11:F12) -> 64.41 | E8: =D8*$F$2 -> 70.754385
B9: 4 | C9: Muro culata sin ventanas | D9: =CO!F13 -> 183.098 | E9: =D9*$F$2 -> 201.13315
C11: TOTAL M2 DE FACHADA SIN DESCUENTOS | D11: =SUM(D6:D10) -> 394.758 | E11: =SUM(E6:E10) -> 433.64166
A14: ESTE | C14: FACHADA ESTE
B15: 5 | C15: Muro con balcones y volumenes | D15: =CO!F21 -> 570.78 | E15: =D15*$F$2 -> 627.00183
C16: Muro culata parqueadero | D16: =CO!F28 -> 376 | E16: =D16*$F$2 -> 413.036
B17: 6 | C17: Muros sin ventana | D17: =CO!F30 -> 25.8 | E17: =D17*$F$2 -> 28.3413
B18: 7 | C18: Muro con balcones y volumenes | D18: =CO!F31 -> 189 | E18: =D18*$F$2 -> 207.6165
B19: 8 | C19: Muro sin ventana | D19: =CO!F37 -> 25.8 | E19: =D19*$F$2 -> 28.3413
B20: 9 | C20: Muro con balcones y volumenes | D20: =CO!F39 -> 211.25 | E20: =D20*$F$2 -> 232.05812
C22: TOTAL M2 DE FACHADA SIN DESCUENTOS | D22: =SUM(D15:D20) -> 1398.63 | E22: =SUM(E15:E20) -> 1536.3951
A25: SUR | C25: FACHADA SUR
B26: 10 | C26: Muro con balcones y volumenes | D26: =CO!F51 -> 545.8125 | E26: =D26*$F$2 -> 599.57503
C28: TOTAL M2 DE FACHADA SIN DESCUENTOS | D28: =SUM(D26:D26) -> 545.8125 | E28: =SUM(E26:E26) -> 599.57503
A31: OESTE | C31: FACHADA OESTE
B32: 11 | C32: Muro con balcones y volumenes | D32: =CO!F62 -> 231.2 | E32: =D32*$F$2 -> 253.9732
B33: 12 | C33: Muro sin ventanas | D33: =CO!F66 -> 51.6 | E33: =D33*$F$2 -> 56.6826
B34: 13 | C34: Muro con balcones y volumenes | D34: =CO!F67 -> 476 | E34: =D34*$F$2 -> 522.886
B35: 14 | C35: Muro sin ventanas | D35: =CO!F70 -> 32.25 | E35: =D35*$F$2 -> 35.426625
B36: 15 | C36: Muro con balcones y volumenes | D36: =CO!F72 -> 177.344 | E36: =D36*$F$2 -> 194.81238
B37: 16 | C37: Muro sin ventanas | D37: =CO!F75 -> 15.05 | E37: =D37*$F$2 -> 16.532425
B38: 17 | C38: Muro con balcones y volumenes | D38: =CO!F77 -> 95.2 | E38: =D38*$F$2 -> 104.5772
B39: General | C39: Volumenes en fachada | D39: =CO!F80 -> 39.05 | E39: =D39*$F$2 -> 42.896425
C41: TOTAL M2 DE FACHADA SIN DESCUENTOS | D41: =SUM(D32:D40) -> 1117.694 | E41: =SUM(E32:E40) -> 1227.7869
A42: SUR | D42: =D11+D22+D28+D41 -> 3456.8945 | E42: =E11+E22+E28+E41 -> 3797.3986
D43: =3770-D42 -> 313.1055 | E43: =3798-E42 -> 0.60139175
D45: =D11+D22+D28+D41 -> 3456.8945 | E45: =E11+E22+E28+E41 -> 3797.3986 | F45: 3798
A48: Zonas interiores | B48: 9 | C48: Punto fijo | D48: 21.44
C49: Pasillos | D49: 58.95
C50: Cielo rasos | D50: 26.8
B51: 8 | C51: Punto fijo | D51: =$D$48 -> 21.44
C52: Pasillos | D52: =$D$49 -> 58.95
C53: Cielo rasos | D53: =$D$50 -> 26.8
B54: 7 | C54: Punto fijo | D54: =$D$48 -> 21.44
C55: Pasillos | D55: =$D$49 -> 58.95
C56: Cielo rasos | D56: =$D$50 -> 26.8
B57: 6 | C57: Punto fijo | D57: =$D$48 -> 21.44
C58: Pasillos | D58: =$D$49 -> 58.95
C59: Cielo rasos | D59: =$D$50 -> 26.8
B60: 5 | C60: Punto fijo | D60: =$D$48 -> 21.44
C61: Pasillos | D61: =$D$49 -> 58.95
C62: Cielo rasos | D62: =$D$50 -> 26.8
B63: 4 | C63: Punto fijo | D63: =$D$48 -> 21.44
C64: Pasillos | D64: =$D$49 -> 58.95
C65: Cielo rasos | D65: =$D$50 -> 26.8
B66: 3 | C66: Punto fijo | D66: =$D$48 -> 21.44
C67: Pasillos | D67: =$D$49 -> 58.95
C68: Cielo rasos | D68: =$D$50 -> 26.8
B69: 2 | C69: Punto fijo | D69: =$D$48 -> 21.44
C70: Pasillos | D70: =$D$49 -> 58.95
C71: Cielo rasos | D71: =$D$50 -> 26.8
B72: 1 | C72: Punto fijo | D72: =$D$48 -> 21.44
C73: Pasillos | D73: =$D$49 -> 58.95
C74: Cielo rasos | D74: =$D$50 -> 26.8
B75: S1 | C75: Punto fijo | D75: =$D$48 -> 21.44
C76: Pasillos | D76: =$D$49 -> 58.95
C77: Cielo rasos | D77: =$D$50 -> 26.8
B78: S2 | C78: Punto fijo | D78: =$D$48 -> 21.44
C79: Pasillos | D79: =$D$49 -> 58.95
C80: Cielo rasos | D80: =$D$50 -> 26.8
C82: TOTAL M2 INTERIORES | D82: =SUM(D48:D80) -> 1179.09

Sheet Lavado
A6: EDIFICIO EL MIRADOR - LAVADO DE FACHADA
E7: OCT 16 - 17 | G7: OCT 20 - 24 | I7: OCT 27 - 31 | K7: NOV 03 - 08 | M7: NOV 10 - 15 | O7: NOV 17 - 22 | Q7: NOV 24 - 29 | S7: DIC 01 - ENE 20 | U7: ENE 20 - MAR 11
A8: FACHADA | B8: SECCIÓN | C8: DESCRIPCIÓN | D8: M2 | E8: SEMANA 01 | G8: SEMANA 02 | I8: SEMANA 03 | K8: SEMANA 04 | M8: SEMANA 05 | O8: SEMANA 06 | Q8: SEMANA 07 | S8: SEMANA 08 - 12 | U8: SEMANA 08 - 12 | W8: Total Ejecutado | Y8: Total Ejecutado Acta 01 | AA8: Total Ejecutado Acta 03
E9: M2 | F9: % | G9: M2 | H9: % | I9: M2 | J9: % | K9: M2 | L9: % | M9: M2 | N9: % | O9: M2 | P9: % | Q9: M2 | R9: % | S9: M2 | T9: % | U9: M2 | V9: % | W9: M2 | X9: % | Y9: M2 | Z9: % | AA9: M2 | AB9: %
A10: NORTE | B10: 1 | C10: Muro con ventana | D10: ='CO SIF'!E6 -> 117.42965 | E10: =D10*F10 -> 58.714825 | F10: 0.5 | G10: =D10*H10 -> 58.714825 | H10: 0.5 | I10: =D10*J10 -> 0 | J10: 0 | K10: =D10*L10 -> 0 | L10: 0 | M10: =D10*N10 -> 0 | N10: 0 | O10: =D10*P10 -> 0 | P10: 0 | Q10: =D10*R10 -> 0 | R10: 0 | S10: =D10*T10 -> 0 | T10: 0 | U10: =F10*V10 -> 0 | V10: 0 | W10: =E10+G10+I10+K10+M10+O10+Q10 -> 117.42965 | X10: =W10/D10 -> 1 | Y10: =E10+G10+I10+K10+M10+O10+Q10 -> 117.42965 | Z10: =Y10/D10 -> 1 | AA10: =S10 -> 0 | AB10: =AA10/D10 -> 0
B11: 4 | C11: Muro con ventana | D11: ='CO SIF'!E7 -> 44.324475 | E11: 0 | F11: 0 | G11: =D11*H11 -> 44.324475 | H11: 1 | I11: =D11*J11 -> 0 | J11: 0 | K11: =D11*L11 -> 0 | L11: 0 | M11: =D11*N11 -> 0 | N11: 0 | O11: =D11*P11 -> 0 | P11: 0 | Q11: =D11*R11 -> 0 | R11: 0 | S11: =D11*T11 -> 0 | T11: 0 | U11: =F11*V11 -> 0 | V11: 0 | W11: =E11+G11+I11+K11+M11+O11+Q11 -> 44.324475 | X11: =W11/D11 -> 1 | Y11: =E11+G11+I11+K11+M11+O11+Q11 -> 44.324475 | Z11: =Y11/D11 -> 1 | AA11: =S11 -> 0 | AB11: =AA11/D11 -> 0
B12: 3 | C12: Culata baja sin ventanas | D12: ='CO SIF'!E8 -> 70.754385 | E12: 0 | F12: 0 | G12: =D12*H12 -> 70.754385 | H12: 1 | I12: =D12*J12 -> 0 | J12: 0 | K12: =D12*L12 -> 0 | L12: 0 | M12: =D12*N12 -> 0 | N12: 0 | O12: =D12*P12 -> 0 | P12: 0 | Q12: =D12*R12 -> 0 | R12: 0 | S12: =D12*T12 -> 0 | T12: 0 | U12: =F12*V12 -> 0 | V12: 0 | W12: =E12+G12+I12+K12+M12+O12+Q12 -> 70.754385 | X12: =W12/D12 -> 1 | Y12: =E12+G12+I12+K12+M12+O12+Q12 -> 70.754385 | Z12: =Y12/D12 -> 1 | AA12: =S12 -> 0 | AB12: =AA12/D12 -> 0
B13: 4 | C13: Culata alta sin ventanas | D13: ='CO SIF'!E9 -> 201.13315 | E13: 0 | F13: 0 | G13: =D13*H13 -> 0 | H13: 0 | I13: =D13*J13 -> 201.13315 | J13: 1 | K13: =D13*L13 -> 0 | L13: 0 | M13: =D13*N13 -> 0 | N13: 0 | O13: =D13*P13 -> 0 | P13: 0 | Q13: =D13*R13 -> 0 | R13: 0 | S13: =D13*T13 -> 0 | T13: 0 | U13: =F13*V13 -> 0 | V13: 0 | W13: =E13+G13+I13+K13+M13+O13+Q13 -> 201.13315 | X13: =W13/D13 -> 1 | Y13: =E13+G13+I13+K13+M13+O13+Q13 -> 201.13315 | Z13: =Y13/D13 -> 1 | AA13: =S13 -> 0 | AB13: =AA13/D13 -> 0
C15: TOTAL M2 DE FACHADA | D15: =SUM(D10:D14) -> 433.64166 | E15: =SUM(E10:E14) -> 58.714825 | F15: =E15/D15 -> 0.13539941 | G15: =SUM(G10:G13) -> 173.79369 | H15: =G15/D15 -> 0.40077719 | I15: =SUM(I10:I13) -> 201.13315 | J15: =I15/D15 -> 0.46382341 | K15: =SUM(K6:K13) -> 0 | L15: =K15/D15 -> 0 | M15: =SUM(M6:M13) -> 0 | N15: =M15/D15 -> 0 | O15: =SUM(O6:O13) -> 0 | P15: =O15/D15 -> 0 | Q15: =SUM(Q6:Q13) -> 0 | R15: =Q15/D15 -> 0 | S15: =SUM(S6:S13) -> 0 | T15: =S15/D15 -> 0 | U15: =SUM(U6:U13) -> 0 | V15: =U15/F15 -> 0 | W15: =SUM(W10:W13) -> 433.64166 | X15: =W15/D15 -> 1 | Y15: =SUM(Y10:Y13) -> 433.64166 | Z15: =Y15/D15 -> 1 | AA15: =SUM(AA10:AA13) -> 0 | AB15: =AA15/D15 -> 0
W16: =D15-W15 -> 0 | X16: =W16/D15 -> 0
A19: ESTE | B19: 5 | C19: Muro con balcones y volumenes | D19: ='CO SIF'!E15 -> 627.00183 | E19: =D19*F19 -> 0 | F19: 0 | G19: =D19*H19 -> 627.00183 | H19: 1 | I19: =J19*D19 -> 0 | J19: 0 | K19: =D19*L19 -> 0 | L19: 0 | M19: =D19*N19 -> 0 | N19: 0 | O19: =D19*P19 -> 0 | P19: 0 | Q19: =D19*R19 -> 0 | R19: 0 | S19: =D19*T19 -> 0 | T19: 0 | U19: =F19*V19 -> 0 | V19: 0 | W19: =E19+G19+I19+K19+M19+O19+Q19 -> 627.00183 | X19: =W19/D19 -> 1 | Y19: =E19+G19+I19+K19+M19+O19+Q19 -> 627.00183 | Z19: =Y19/D19 -> 1 | AA19: =S19 -> 0 | AB19: =AA19/D19 -> 0
C20: Muro culata parqueadero | D20: ='CO SIF'!E16 -> 413.036 | E20: =D20*F20 -> 0 | F20: 0 | G20: =D20*H20 -> 206.518 | H20: 0.5 | I20: =J20*D20 -> 206.518 | J20: 0.5 | K20: =D20*L20 -> 0 | L20: 0 | M20: =D20*N20 -> 0 | N20: 0 | O20: =D20*P20 -> 0 | P20: 0 | Q20: =D20*R20 -> 0 | R20: 0 | S20: =D20*T20 -> 0 | T20: 0 | U20: =F20*V20 -> 0 | V20: 0 | W20: =E20+G20+I20+K20+M20+O20+Q20 -> 413.036 | X20: =W20/D20 -> 1 | Y20: =E20+G20+I20+K20+M20+O20+Q20 -> 413.036 | Z20: =Y20/D20 -> 1 | AA20: =S20 -> 0 | AB20: =AA20/D20 -> 0
B21: 6 | C21: Muro sin ventanas | D21: ='CO SIF'!E17 -> 28.3413 | E21: =D21*F21 -> 0 | F21: 0 | G21: =D21*H21 -> 0 | H21: 0 | I21: =J21*D21 -> 28.3413 | J21: 1 | K21: =D21*L21 -> 0 | L21: 0 | M21: =D21*N21 -> 0 | N21: 0 | O21: =D21*P21 -> 0 | P21: 0 | Q21: =D21*R21 -> 0 | R21: 0 | S21: =D21*T21 -> 0 | T21: 0 | U21: =F21*V21 -> 0 | V21: 0 | W21: =E21+G21+I21+K21+M21+O21+Q21 -> 28.3413 | X21: =W21/D21 -> 1 | Y21: =E21+G21+I21+K21+M21+O21+Q21 -> 28.3413 | Z21: =Y21/D21 -> 1 | AA21: =S21 -> 0 | AB21: =AA21/D21 -> 0
B22: 7 | C22: Muro con balcones y volumenes | D22: ='CO SIF'!E18 -> 207.6165 | E22: =D22*F22 -> 0 | F22: 0 | G22: =D22*H22 -> 0 | H22: 0 | I22: =J22*D22 -> 207.6165 | J22: 1 | K22: =D22*L22 -> 0 | L22: 0 | M22: =D22*N22 -> 0 | N22: 0 | O22: =D22*P22 -> 0 | P22: 0 | Q22: =D22*R22 -> 0 | R22: 0 | S22: =D22*T22 -> 0 | T22: 0 | U22: =F22*V22 -> 0 | V22: 0 | W22: =E22+G22+I22+K22+M22+O22+Q22 -> 207.6165 | X22: =W22/D22 -> 1 | Y22: =E22+G22+I22+K22+M22+O22+Q22 -> 207.6165 | Z22: =Y22/D22 -> 1 | AA22: =S22 -> 0 | AB22: =AA22/D22 -> 0
B23: 8 | C23: Muro sin ventanas | D23: ='CO SIF'!E19 -> 28.3413 | E23: =D23*F23 -> 0 | F23: 0 | G23: =D23*H23 -> 0 | H23: 0 | I23: =J23*D23 -> 28.3413 | J23: 1 | K23: =D23*L23 -> 0 | L23: 0 | M23: =D23*N23 -> 0 | N23: 0 | O23: =D23*P23 -> 0 | P23: 0 | Q23: =D23*R23 -> 0 | R23: 0 | S23: =D23*T23 -> 0 | T23: 0 | U23: =F23*V23 -> 0 | V23: 0 | W23: =E23+G23+I23+K23+M23+O23+Q23 -> 28.3413 | X23: =W23/D23 -> 1 | Y23: =E23+G23+I23+K23+M23+O23+Q23 -> 28.3413 | Z23: =Y23/D23 -> 1 | AA23: =S23 -> 0 | AB23: =AA23/D23 -> 0
B24: 9 | C24: Muro con balcones y volumenes | D24: ='CO SIF'!E20 -> 232.05812 | E24: =D24*F24 -> 0 | F24: 0 | G24: =D24*H24 -> 0 | H24: 0 | I24: =J24*D24 -> 232.05812 | J24: 1 | K24: =D24*L24 -> 0 | L24: 0 | M24: =D24*N24 -> 0 | N24: 0 | O24: =D24*P24 -> 0 | P24: 0 | Q24: =D24*R24 -> 0 | R24: 0 | S24: =D24*T24 -> 0 | T24: 0 | U24: =F24*V24 -> 0 | V24: 0 | W24: =E24+G24+I24+K24+M24+O24+Q24 -> 232.05812 | X24: =W24/D24 -> 1 | Y24: =E24+G24+I24+K24+M24+O24+Q24 -> 232.05812 | Z24: =Y24/D24 -> 1 | AA24: =S24 -> 0 | AB24: =AA24/D24 -> 0
C26: TOTAL M2 DE FACHADA | D26: =SUM(D19:D25) -> 1536.3951 | E26: =SUM(E19:E25) -> 0 | F26: =E26/D26 -> 0 | G26: =SUM(G19:G25) -> 833.51983 | H26: =G26/D26 -> 0.54251661 | I26: =SUM(I19:I25) -> 702.87523 | J26: =I26/D26 -> 0.45748339 | K26: =SUM(K17:K24) -> 0 | L26: =K26/D26 -> 0 | M26: =SUM(M17:M24) -> 0 | N26: =M26/D26 -> 0 | O26: =SUM(O17:O24) -> 0 | P26: =O26/D26 -> 0 | Q26: =SUM(Q17:Q24) -> 0 | R26: =Q26/D26 -> 0 | S26: =SUM(S17:S24) -> 0 | T26: =S26/D26 -> 0 | U26: =SUM(U17:U24) -> 0 | V26: =U26/D26 -> 0 | W26: =SUM(W19:W24) -> 1536.3951 | X26: =W26/D26 -> 1 | Y26: =SUM(Y19:Y24) -> 1536.3951 | Z26: =Y26/D26 -> 1 | AA26: =SUM(AA19:AA24) -> 0 | AB26: =AA26/D26 -> 0
W27: =D26-W26 -> 0 | X27: =W27/D26 -> 0
A29: SUR | B29: 10 | C29: Muro con balcones y volumenes | D29: ='CO SIF'!E26 -> 599.57503 | E29: =D29*F29 -> 0 | F29: 0 | G29: =D29*H29 -> 0 | H29: 0 | I29: =D29*J29 -> 0 | J29: 0 | K29: =D29*L29 -> 0 | L29: 0 | M29: =D29*N29 -> 0 | N29: 0 | O29: =D29*P29 -> 0 | P29: 0 | Q29: =D29*R29 -> 0 | R29: 0 | S29: =D29*T29 -> 389.72377 | T29: 0.65 | U29: =D29*V29 -> 209.85126 | V29: 0.35 | W29: =E29+G29+I29+K29+M29+O29+Q29+S29+U29 -> 599.57503 | X29: =W29/D29 -> 1 | Y29: =E29+G29+I29+K29+M29+O29+Q29 -> 0 | Z29: =Y29/D29 -> 0 | AA29: =S29 -> 389.72377 | AB29: =AA29/D29 -> 0.65
C31: TOTAL M2 DE FACHADA | D31: =SUM(D29:D30) -> 599.57503 | E31: =SUM(E29:E30) -> 0 | F31: =E31/D31 -> 0 | G31: =SUM(G29:G29) -> 0 | H31: =G31/D31 -> 0 | I31: =SUM(I29:I29) -> 0 | J31: =I31/D31 -> 0 | K31: =SUM(K22:K29) -> 0 | L31: =K31/D31 -> 0 | M31: =SUM(M22:M29) -> 0 | N31: =M31/D31 -> 0 | O31: =SUM(O22:O29) -> 0 | P31: =O31/D31 -> 0 | Q31: =SUM(Q22:Q29) -> 0 | R31: =Q31/D31 -> 0 | S31: =SUM(S22:S29) -> 389.72377 | T31: =S31/D31 -> 0.65 | U31: =SUM(U22:U29) -> 209.85126 | V31: =U31/D31 -> 0.35 | W31: =SUM(W29:W29) -> 599.57503 | X31: =W31/D31 -> 1 | Y31: =SUM(Y29) -> 0 | Z31: =Y31/D31 -> 0 | AA31: =SUM(AA29) -> 389.72377 | AB31: =AA31/D31 -> 0.65
W32: =D31-W31 -> 0 | X32: =W32/D31 -> 0
A34: OESTE | B34: 11 | C34: Muro con balcones y volumenes | D34: ='CO SIF'!E32 -> 253.9732 | E34: =D34*F34 -> 0 | F34: 0 | G34: =D34*H34 -> 0 | H34: 0 | I34: =J34*D34 -> 0 | J34: 0 | K34: =D34*L34 -> 0 | L34: 0 | M34: =D34*N34 -> 0 | N34: 0 | O34: =D34*P34 -> 0 | P34: 0 | Q34: =D34*R34 -> 0 | R34: 0 | S34: =D34*T34 -> 0 | T34: 0 | U34: =D34*V34 -> 253.9732 | V34: 1 | W34: =E34+G34+I34+K34+M34+O34+Q34+S34+U34 -> 253.9732 | X34: =W34/D34 -> 1
B35: 12 | C35: Muro sin ventanas | D35: ='CO SIF'!E33 -> 56.6826 | E35: =D35*F35 -> 0 | F35: 0 | G35: =D35*H35 -> 0 | H35: 0 | I35: =J35*D35 -> 0 | J35: 0 | K35: =D35*L35 -> 0 | L35: 0 | M35: =D35*N35 -> 0 | N35: 0 | O35: =D35*P35 -> 0 | P35: 0 | Q35: =D35*R35 -> 0 | R35: 0 | S35: =D35*T35 -> 0 | T35: 0 | U35: =D35*V35 -> 56.6826 | V35: 1 | W35: =E35+G35+I35+K35+M35+O35+Q35+S35+U35 -> 56.6826 | X35: =W35/D35 -> 1
B36: 13 | C36: Muro con balcones y volumenes | D36: ='CO SIF'!E34 -> 522.886 | E36: =D36*F36 -> 0 | F36: 0 | G36: =D36*H36 -> 0 | H36: 0 | I36: =J36*D36 -> 0 | J36: 0 | K36: =D36*L36 -> 0 | L36: 0 | M36: =D36*N36 -> 0 | N36: 0 | O36: =D36*P36 -> 0 | P36: 0 | Q36: =D36*R36 -> 0 | R36: 0 | S36: =D36*T36 -> 0 | T36: 0 | U36: =D36*V36 -> 522.886 | V36: 1 | W36: =E36+G36+I36+K36+M36+O36+Q36+S36+U36 -> 522.886 | X36: =W36/D36 -> 1
B37: 14 | C37: Muro sin ventanas | D37: ='CO SIF'!E35 -> 35.426625 | E37: =D37*F37 -> 0 | F37: 0 | G37: =D37*H37 -> 0 | H37: 0 | I37: =J37*D37 -> 0 | J37: 0 | K37: =D37*L37 -> 0 | L37: 0 | M37: =D37*N37 -> 0 | N37: 0 | O37: =D37*P37 -> 0 | P37: 0 | Q37: =D37*R37 -> 0 | R37: 0 | S37: =D37*T37 -> 0 | T37: 0 | U37: =D37*V37 -> 35.426625 | V37: 1 | W37: =E37+G37+I37+K37+M37+O37+Q37+S37+U37 -> 35.426625 | X37: =W37/D37 -> 1
B38: 15 | C38: Muro con balcones y volumenes | D38: ='CO SIF'!E36 -> 194.81238 | E38: =D38*F38 -> 0 | F38: 0 | G38: =D38*H38 -> 0 | H38: 0 | I38: =J38*D38 -> 0 | J38: 0 | K38: =D38*L38 -> 0 | L38: 0 | M38: =D38*N38 -> 0 | N38: 0 | O38: =D38*P38 -> 0 | P38: 0 | Q38: =D38*R38 -> 0 | R38: 0 | S38: =D38*T38 -> 0 | T38: 0 | U38: =D38*V38 -> 194.81238 | V38: 1 | W38: =E38+G38+I38+K38+M38+O38+Q38+S38+U38 -> 194.81238 | X38: =W38/D38 -> 1
B39: 16 | C39: Muro sin ventanas | D39: ='CO SIF'!E37 -> 16.532425 | E39: =D39*F39 -> 0 | F39: 0 | G39: =D39*H39 -> 0 | H39: 0 | I39: =J39*D39 -> 0 | J39: 0 | K39: =D39*L39 -> 0 | L39: 0 | M39: =D39*N39 -> 0 | N39: 0 | O39: =D39*P39 -> 0 | P39: 0 | Q39: =D39*R39 -> 0 | R39: 0 | S39: =D39*T39 -> 0 | T39: 0 | U39: =D39*V39 -> 16.532425 | V39: 1 | W39: =E39+G39+I39+K39+M39+O39+Q39+S39+U39 -> 16.532425 | X39: =W39/D39 -> 1
B40: 17 | C40: Muro con balcones y volumenes | D40: ='CO SIF'!E38 -> 104.5772 | E40: =D40*F40 -> 0 | F40: 0 | G40: =D40*H40 -> 0 | H40: 0 | I40: =J40*D40 -> 0 | J40: 0 | K40: =D40*L40 -> 0 | L40: 0 | M40: =D40*N40 -> 0 | N40: 0 | O40: =D40*P40 -> 0 | P40: 0 | Q40: =D40*R40 -> 0 | R40: 0 | S40: =D40*T40 -> 0 | T40: 0 | U40: =D40*V40 -> 104.5772 | V40: 1 | W40: =E40+G40+I40+K40+M40+O40+Q40+S40+U40 -> 104.5772 | X40: =W40/D40 -> 1
C41: Volumenes en fachada | D41: ='CO SIF'!E39 -> 42.896425 | E41: =D41*F41 -> 0 | F41: 0 | G41: =D41*H41 -> 0 | H41: 0 | I41: =J41*D41 -> 0 | J41: 0 | K41: =D41*L41 -> 0 | L41: 0 | M41: =D41*N41 -> 0 | N41: 0 | O41: =D41*P41 -> 0 | P41: 0 | Q41: =D41*R41 -> 0 | R41: 0 | S41: =D41*T41 -> 0 | T41: 0 | U41: =D41*V41 -> 42.896425 | V41: 1 | W41: =E41+G41+I41+K41+M41+O41+Q41+S41+U41 -> 42.896425 | X41: =W41/D41 -> 1
C43: TOTAL M2 DE FACHADA | D43: =SUM(D34:D42) -> 1227.7869 | E43: =SUM(E34:E42) -> 0 | F43: =E43/D43 -> 0 | G43: =SUM(G34:G42) -> 0 | H43: =G43/D43 -> 0 | I43: =SUM(I34:I42) -> 0 | J43: =I43/D43 -> 0 | K43: =SUM(K35:K42) -> 0 | L43: =K43/D43 -> 0 | M43: =SUM(M35:M42) -> 0 | N43: =M43/D43 -> 0 | O43: =SUM(O35:O42) -> 0 | P43: =O43/D43 -> 0 | Q43: =SUM(Q35:Q42) -> 0 | R43: =Q43/D43 -> 0 | S43: =SUM(S34:S41) -> 0 | T43: =S43/D43 -> 0 | U43: =SUM(U34:U41) -> 1227.7869 | V43: =U43/D43 -> 1 | W43: =SUM(W34:W41) -> 1227.7869 | X43: =W43/D43 -> 1
W44: =D43-W43 -> 0 | X44: =W44/D43 -> 0
C46: TOTAL M2 DE FACHADAS GENERAL | D46: =D15+D26+D31+D43 -> 3797.3986 | H46: TOTAL M2 DE EJECUTADOS | W46: =W15+W26+W31+W43 -> 3797.3986 | X46: =W46/D46 -> 1 | Y46: =Y15+Y26+Y31+Y43 -> 1970.0367 | Z46: =Y46/D46 -> 0.51878586 | AA46: =AA15+AA26+AA31+AA43 -> 389.72377 | AB46: =AA46/D46 -> 0.10262914
W47: =D46-W46 -> 0 | X47: =W47/D46 -> 0

Sheet Sellos
A6: EDIFICIO EL MIRADOR - APLICACIÓN DE SELLOS
E7: OCT 16 - 17 | G7: OCT 20 - 24 | I7: OCT 27 - 31 | K7: NOV 03 - 08 | M7: NOV 10 - 15 | O7: NOV 17 - 22 | Q7: NOV 24 - 29 | S7: DIC 01 - 06 | U7: DIC 09 - 13 | W7: DIC 15 - ENE 20 | Y7: ENE 20 -MAR 11
A8: FACHADA | B8: SECCIÓN | C8: DESCRIPCIÓN | D8: M2 | E8: SEMANA 01 | G8: SEMANA 02 | I8: SEMANA 03 | K8: SEMANA 04 | M8: SEMANA 05 | O8: SEMANA 06 | Q8: SEMANA 07 | S8: Semana 08 | U8: Semana 09 | W8: Semana 10 - 12 | AA8: Total Ejecutado | AC8: Total Ejecutado Acta 01 | AE8: Total Ejecutado Acta 02 | AG8: Total Ejecutado Acta 03
E9: M2 | F9: % | G9: M2 | H9: % | I9: M2 | J9: % | K9: M2 | L9: % | M9: M2 | N9: % | O9: M2 | P9: % | Q9: M2 | R9: % | S9: M2 | T9: % | U9: M2 | V9: % | W9: M2 | X9: % | Y9: M2 | Z9: % | AA9: M2 | AB9: % | AC9: M2 | AD9: % | AE9: M2 | AF9: % | AG9: M2 | AH9: %
A10: NORTE | B10: 1 | C10: Muro con ventana | D10: =CO!K6 -> 33.6 | E10: =D10*F10 -> 0 | F10: 0 | G10: =D10*H10 -> 33.6 | H10: 1 | I10: =D10*J10 -> 0 | J10: 0 | K10: =F10*L10 -> 0 | L10: 0 | M10: =H10*N10 -> 0 | N10: 0 | O10: =J10*P10 -> 0 | P10: 0 | Q10: =L10*R10 -> 0 | R10: 0 | S10: =N10*T10 -> 0 | T10: 0 | U10: =D10*V10 -> 0 | V10: 0 | W10: =F10*D10 -> 0 | X10: 0 | Y10: =Z10*D10 -> 0 | Z10: 0 | AA10: =E10+G10+I10+K10+M10+O10+Q10+S10+U10+W10+Y10 -> 33.6 | AB10: =AA10/D10 -> 1 | AC10: =E10+G10+I10 -> 33.6 | AD10: =AC10/D10 -> 1 | AE10: =K10+M10+O10+Q10+S10+U10 -> 0 | AF10: =AE10/D10 -> 0 | AG10: =M10+O10+Q10+S10+U10+W10 -> 0 | AH10: =AG10/F10 -> #DIV/0!
B11: 4 | C11: Muro con ventana | D11: =CO!K11 -> 36 | E11: 0 | F11: 0 | G11: =D11*H11 -> 0 | H11: 0 | I11: =D11*J11 -> 0 | J11: 0 | K11: =F11*L11 -> 0 | L11: 0 | M11: =H11*N11 -> 0 | N11: 0 | O11: =J11*P11 -> 0 | P11: 0 | Q11: =L11*R11 -> 0 | R11: 0 | S11: =N11*T11 -> 0 | T11: 0 | U11: =D11*V11 -> 0 | V11: 0 | W11: =F11*D11 -> 0 | X11: 0 | Y11: =Z11*D11 -> 36 | Z11: 1 | AA11: =E11+G11+I11+K11+M11+O11+Q11+S11+U11+W11+Y11 -> 36 | AB11: =AA11/D11 -> 1 | AC11: =E11+G11+I11 -> 0 | AD11: =AC11/D11 -> 0 | AE11: =K11+M11+O11+Q11+S11+U11 -> 0 | AF11: =AE11/D11 -> 0 | AG11: =M11+O11+Q11+S11+U11+W11 -> 0 | AH11: =AG11/F11 -> #DIV/0!
B12: 3 | C12: Culata baja sin ventanas | D12: 0 | E12: 0 | F12: 0 | G12: =D12*H12 -> 0 | H12: 0 | I12: =D12*J12 -> 0 | J12: 0 | K12: =F12*L12 -> 0 | L12: 0 | M12: =H12*N12 -> 0 | N12: 0 | O12: =J12*P12 -> 0 | P12: 0 | Q12: =L12*R12 -> 0 | R12: 0 | S12: =N12*T12 -> 0 | T12: 0 | U12: =D12*V12 -> 0 | V12: 0 | W12: =F12*D12 -> 0 | X12: 0 | Y12: =Z12*D12 -> 0 | Z12: 1 | AA12: =E12+G12+I12+K12+M12+O12+Q12+S12+U12+W12+Y12 -> 0 | AB12: 0 | AC12: =E12+G12+I12 -> 0 | AD12: 0 | AE12: =K12+M12+O12+Q12+S12+U12 -> 0 | AF12: 0 | AG12: =M12+O12+Q12+S12+U12+W12 -> 0 | AH12: 0
B13: 4 | C13: Culata alta sin ventanas | D13: 0 | E13: 0 | F13: 0 | G13: =D13*H13 -> 0 | H13: 0 | I13: =D13*J13 -> 0 | J13: 0 | K13: =F13*L13 -> 0 | L13: 0 | M13: =H13*N13 -> 0 | N13: 0 | O13: =J13*P13 -> 0 | P13: 0 | Q13: =L13*R13 -> 0 | R13: 0 | S13: =N13*T13 -> 0 | T13: 0 | U13: =D13*V13 -> 0 | V13: 0 | W13: =F13*D13 -> 0 | X13: 0 | Y13: =Z13*D13 -> 0 | Z13: 1 | AA13: =E13+G13+I13+K13+M13+O13+Q13+S13+U13+W13+Y13 -> 0 | AB13: 0 | AC13: =E13+G13+I13 -> 0 | AD13: 0 | AE13: =K13+M13+O13+Q13+S13+U13 -> 0 | AF13: 0 | AG13: =M13+O13+Q13+S13+U13+W13 -> 0 | AH13: 0
C15: TOTAL M2 DE FACHADA | D15: =SUM(D10:D14) -> 69.6 | E15: =SUM(E10:E14) -> 0 | F15: =E15/D15 -> 0 | G15: =SUM(G10:G13) -> 33.6 | H15: =G15/D15 -> 0.48275862 | I15: =SUM(I10:I13) -> 0 | J15: =I15/D15 -> 0 | K15: =SUM(K6:K13) -> 0 | L15: =K15/D15 -> 0 | M15: =SUM(M6:M13) -> 0 | N15: =M15/D15 -> 0 | O15: =SUM(O6:O13) -> 0 | P15: =O15/D15 -> 0 | Q15: =SUM(Q6:Q13) -> 0 | R15: =Q15/D15 -> 0 | S15: =SUM(S6:S13) -> 0 | T15: =S15/D15 -> 0 | U15: =SUM(U6:U13) -> 0 | V15: =U15/D15 -> 0 | W15: =SUM(W6:W13) -> 0 | X15: =W15/D15 -> 0 | Y15: =SUM(Y6:Y13) -> 36 | Z15: =Y15/D15 -> 0.51724138 | AA15: =SUM(AA10:AA13) -> 69.6 | AB15: =AA15/D15 -> 1 | AC15: =SUM(AC10:AC13) -> 33.6 | AD15: =AC15/D15 -> 0.48275862 | AE15: =SUM(AE10:AE13) -> 0 | AF15: =AE15/D15 -> 0 | AG15: =SUM(AG10:AG13) -> 0 | AH15: =AG15/F15 -> #DIV/0!
AA16: =D15-AA15 -> 0 | AB16: =AA16/D15 -> 0
A19: ESTE | B19: 5 | C19: Muro con balcones y volumenes | D19: =SUM(CO!K21:K27) -> 277.1 | E19: =D19*F19 -> 0 | F19: 0 | G19: =D19*H19 -> 0 | H19: 0 | I19: =J19*D19 -> 88.672 | J19: 0.32 | K19: =L19*F19 -> 0 | L19: 0 | M19: =N19*H19 -> 0 | N19: 0 | O19: =P19*D19 -> 41.565 | P19: 0.15 | Q19: =R19*D19 -> 0 | R19: 0 | S19: =T19*N19 -> 0 | T19: 0 | U19: =D19*V19 -> 88.672 | V19: 0.32 | W19: =F19*X19 -> 0 | X19: 0.32 | Y19: =Z19*D19 -> 58.191 | Z19: 0.21 | AA19: =E19+G19+I19+K19+M19+O19+Q19+S19+U19+W19+Y19 -> 277.1 | AB19: =AA19/D19 -> 1 | AC19: =E19+G19+I19 -> 88.672 | AD19: =AC19/D19 -> 0.32 | AE19: =K19+M19+O19+Q19+S19+U19 -> 130.237 | AF19: =AE19/D19 -> 0.47 | AG19: =W19 -> 0 | AH19: =AG19/D19 -> 0
C20: Muro culata parqueadero | D20: 0 | E20: =D20*F20 -> 0 | F20: 0 | G20: =D20*H20 -> 0 | H20: 0 | I20: =J20*D20 -> 0 | J20: 0 | K20: =L20*F20 -> 0 | L20: 0 | M20: =N20*H20 -> 0 | N20: 0 | O20: =P20*J20 -> 0 | P20: 0 | Q20: =R20*D20 -> 0 | R20: 0 | S20: =T20*N20 -> 0 | T20: 0 | U20: =D20*V20 -> 0 | V20: 0 | W20: =F20*X20 -> 0 | X20: 0 | Y20: =Z20*D20 -> 0 | Z20: 1 | AA20: =E20+G20+I20+K20+M20+O20+Q20+S20+U20+W20+Y20 -> 0 | AB20: 0 | AC20: =E20+G20+I20 -> 0 | AD20: 0 | AE20: =K20+M20+O20+Q20+S20+U20 -> 0 | AF20: 0 | AG20: =W20 -> 0 | AH20: 0
B21: 6 | C21: Muro sin ventanas | D21: 0 | E21: =D21*F21 -> 0 | F21: 0 | G21: =D21*H21 -> 0 | H21: 0 | I21: =J21*D21 -> 0 | J21: 0 | K21: =L21*F21 -> 0 | L21: 0 | M21: =N21*H21 -> 0 | N21: 0 | O21: =P21*J21 -> 0 | P21: 0 | Q21: =R21*D21 -> 0 | R21: 0 | S21: =T21*N21 -> 0 | T21: 0 | U21: =D21*V21 -> 0 | V21: 0 | W21: =F21*X21 -> 0 | X21: 0 | Y21: =Z21*D21 -> 0 | Z21: 1 | AA21: =E21+G21+I21+K21+M21+O21+Q21+S21+U21+W21+Y21 -> 0 | AB21: 0 | AC21: =E21+G21+I21 -> 0 | AD21: 0 | AE21: =K21+M21+O21+Q21+S21+U21 -> 0 | AF21: 0 | AG21: =W21 -> 0 | AH21: 0
B22: 7 | C22: Muro con balcones y volumenes | D22: =SUM(CO!K31:K35) -> 97.45 | E22: =D22*F22 -> 0 | F22: 0 | G22: =D22*H22 -> 0 | H22: 0 | I22: =J22*D22 -> 0 | J22: 0 | K22: =L22*F22 -> 0 | L22: 0 | M22: =N22*H22 -> 0 | N22: 0 | O22: =P22*J22 -> 0 | P22: 0 | Q22: =R22*D22 -> 43.8525 | R22: 0.45 | S22: =T22*N22 -> 0 | T22: 0 | U22: =D22*V22 -> 43.8525 | V22: 0.45 | W22: =F22*X22 -> 0 | X22: 0.45 | Y22: =Z22*D22 -> 9.745 | Z22: 0.1 | AA22: =E22+G22+I22+K22+M22+O22+Q22+S22+U22+W22+Y22 -> 97.45 | AB22: =AA22/D22 -> 1 | AC22: =E22+G22+I22 -> 0 | AD22: =AC22/D22 -> 0 | AE22: =K22+M22+O22+Q22+S22+U22 -> 87.705 | AF22: =AE22/D22 -> 0.9 | AG22: =W22 -> 0 | AH22: =AG22/D22 -> 0
B23: 8 | C23: Muro sin ventanas | D23: 0 | E23: =D23*F23 -> 0 | F23: 0 | G23: =D23*H23 -> 0 | H23: 0 | I23: =J23*D23 -> 0 | J23: 0 | K23: =L23*F23 -> 0 | L23: 0 | M23: =N23*H23 -> 0 | N23: 0 | O23: =P23*J23 -> 0 | P23: 0 | Q23: =R23*D23 -> 0 | R23: 0 | S23: =T23*N23 -> 0 | T23: 0 | U23: =D23*V23 -> 0 | V23: 0 | W23: =F23*X23 -> 0 | X23: 0 | Y23: =Z23*D23 -> 0 | Z23: 1 | AA23: =E23+G23+I23+K23+M23+O23+Q23+S23+U23+W23+Y23 -> 0 | AB23: 0 | AC23: =E23+G23+I23 -> 0 | AD23: 0 | AE23: =K23+M23+O23+Q23+S23+U23 -> 0 | AF23: 0 | AG23: =W23 -> 0 | AH23: 0
B24: 9 | C24: Muro con balcones y volumenes | D24: =SUM(CO!K39:K43) -> 91.05 | E24: =D24*F24 -> 0 | F24: 0 | G24: =D24*H24 -> 0 | H24: 0 | I24: =J24*D24 -> 0 | J24: 0 | K24: =L24*F24 -> 0 | L24: 0 | M24: =N24*H24 -> 0 | N24: 0 | O24: =P24*J24 -> 0 | P24: 0 | Q24: =R24*D24 -> 33.6885 | R24: 0.37 | S24: =T24*N24 -> 0 | T24: 0 | U24: =D24*V24 -> 0 | V24: 0 | W24: =F24*D24 -> 0 | X24: 0 | Y24: =Z24*D24 -> 57.3615 | Z24: 0.63 | AA24: =E24+G24+I24+K24+M24+O24+Q24+S24+U24+W24+Y24 -> 91.05 | AB24: =AA24/D24 -> 1 | AC24: =E24+G24+I24 -> 0 | AD24: =AC24/D24 -> 0 | AE24: =K24+M24+O24+Q24+S24+U24 -> 33.6885 | AF24: =AE24/D24 -> 0.37 | AG24: =W24 -> 0 | AH24: =AG24/D24 -> 0
C26: TOTAL M2 DE FACHADA | D26: =SUM(D19:D25) -> 465.6 | E26: =SUM(E21:E25) -> 0 | F26: =E26/D26 -> 0 | G26: =SUM(G21:G24) -> 0 | H26: =G26/D26 -> 0 | I26: =SUM(I21:I24) -> 0 | J26: =I26/D26 -> 0 | K26: =SUM(K17:K24) -> 0 | L26: =K26/D26 -> 0 | M26: =SUM(M17:M24) -> 0 | N26: =M26/D26 -> 0 | O26: =SUM(O17:O24) -> 41.565 | P26: =O26/D26 -> 0.089271907 | Q26: =SUM(Q17:Q24) -> 77.541 | R26: =Q26/D26 -> 0.16653995 | S26: =SUM(S17:S24) -> 0 | T26: =S26/D26 -> 0 | U26: =SUM(U17:U24) -> 132.5245 | V26: =U26/D26 -> 0.28463166 | W26: =SUM(W17:W24) -> 0 | X26: =W26/D26 -> 0 | Y26: =SUM(Y17:Y24) -> 125.2975 | Z26: =Y26/D26 -> 0.26910975 | AA26: =SUM(AA19:AA24) -> 465.6 | AB26: =AA26/D26 -> 1 | AC26: =SUM(AC19:AC24) -> 88.672 | AD26: =AC26/D26 -> 0.19044674 | AE26: =SUM(AE21:AE24) -> 121.3935 | AF26: =AE26/D26 -> 0.26072487 | AG26: =SUM(AG21:AG24) -> 0 | AH26: =AG26/D26 -> 0
AA27: =D26-AA26 -> 0 | AB27: =AA27/D26 -> 0
A29: SUR | B29: 10 | C29: Muro con balcones y volumenes | D29: =SUM(CO!K51:K55) -> 251.65 | E29: =D29*F29 -> 0 | F29: 0 | G29: =D29*H29 -> 0 | H29: 0 | I29: =D29*J29 -> 0 | J29: 0 | K29: =F29*L29 -> 0 | L29: 0 | M29: =H29*N29 -> 0 | N29: 0 | O29: =J29*P29 -> 0 | P29: 0 | Q29: =L29*R29 -> 0 | R29: 0 | S29: =N29*T29 -> 0 | T29: 0 | U29: =D29*V29 -> 0 | V29: 0 | W29: =X29*D29 -> 163.5725 | X29: 0.65 | Y29: =Z29*D29 -> 88.0775 | Z29: 0.35 | AA29: =E29+G29+I29+K29+M29+O29+Q29+S29+U29+W29+Y29 -> 251.65 | AB29: =AA29/D29 -> 1 | AC29: =E29+G29+I29 -> 0 | AD29: =AC29/D29 -> 0 | AE29: =K29+M29+O29+Q29+S29+U29 -> 0 | AF29: =AE29/D29 -> 0 | AG29: =W29 -> 163.5725 | AH29: =AG29/D29 -> 0.65
C31: TOTAL M2 DE FACHADA | D31: =SUM(D29:D30) -> 251.65 | E31: =SUM(E26:E30) -> 0 | F31: =E31/D31 -> 0 | G31: =SUM(G26:G29) -> 0 | H31: =G31/D31 -> 0 | I31: =SUM(I26:I29) -> 0 | J31: =I31/D31 -> 0 | K31: =SUM(K22:K29) -> 0 | L31: =K31/D31 -> 0 | M31: =SUM(M22:M29) -> 0 | N31: =M31/D31 -> 0 | O31: =SUM(O22:O29) -> 41.565 | P31: =O31/D31 -> 0.16516988 | Q31: =SUM(Q22:Q29) -> 155.082 | R31: =Q31/D31 -> 0.61626068 | S31: =SUM(S22:S29) -> 0 | T31: =S31/D31 -> 0 | U31: =SUM(U22:U29) -> 176.377 | V31: =U31/D31 -> 0.70088218 | W31: =SUM(W22:W29) -> 163.5725 | X31: =W31/D31 -> 0.65 | Y31: =SUM(Y22:Y29) -> 280.4815 | Z31: =Y31/D31 -> 1.1145698 | AA31: =SUM(AA29:AA29) -> 251.65 | AB31: =AA31/D31 -> 1 | AC31: =SUM(AC24:AC29) -> 88.672 | AD31: =AC31/D31 -> 0.35236241 | AE31: =SUM(AE26:AE29) -> 121.3935 | AF31: =AE31/D31 -> 0.48239022 | AG31: =SUM(AG26:AG29) -> 163.5725 | AH31: =AG31/D31 -> 0.65
AA32: =D31-AA31 -> 0 | AB32: =AA32/D31 -> 0
A34: OESTE | B34: 11 | C34: Muro con balcones y volumenes | D34: =SUM(CO!K62:K65) -> 124.2 | E34: =D34*F34 -> 0 | F34: 0 | G34: =D34*H34 -> 0 | H34: 0 | I34: =J34*D34 -> 0 | J34: 0 | K34: =L34*F34 -> 0 | L34: 0 | M34: =N34*H34 -> 0 | N34: 0 | O34: =P34*J34 -> 0 | P34: 0 | Q34: =R34*L34 -> 0 | R34: 0 | S34: =T34*N34 -> 0 | T34: 0 | U34: =V34*P34 -> 0 | V34: 0 | W34: =F34*D34 -> 0 | X34: 0 | Y34: =Z34*D34 -> 124.2 | Z34: 1 | AA34: =E34+G34+I34+K34+M34+O34+Q34+S34+U34+W34+Y34 -> 124.2 | AB34: =AA34/D34 -> 1
B35: 12 | C35: Muro sin ventanas | D35: 0 | E35: =D35*F35 -> 0 | F35: 0 | G35: =D35*H35 -> 0 | H35: 0 | I35: =J35*D35 -> 0 | J35: 0 | K35: =L35*F35 -> 0 | L35: 0 | M35: =N35*H35 -> 0 | N35: 0 | O35: =P35*J35 -> 0 | P35: 0 | Q35: =R35*L35 -> 0 | R35: 0 | S35: =T35*N35 -> 0 | T35: 0 | U35: =V35*P35 -> 0 | V35: 0 | W35: =F35*D35 -> 0 | X35: 0 | Y35: =Z35*D35 -> 0 | Z35: 1 | AA35: =E35+G35+I35+K35+M35+O35+Q35+S35+U35+W35+Y35 -> 0 | AB35: 0
B36: 13 | C36: Muro con balcones y volumenes | D36: =SUM(CO!K67:K69) -> 179.6 | E36: =D36*F36 -> 0 | F36: 0 | G36: =D36*H36 -> 0 | H36: 0 | I36: =J36*D36 -> 0 | J36: 0 | K36: =L36*F36 -> 0 | L36: 0 | M36: =N36*H36 -> 0 | N36: 0 | O36: =P36*J36 -> 0 | P36: 0 | Q36: =R36*L36 -> 0 | R36: 0 | S36: =T36*N36 -> 0 | T36: 0 | U36: =V36*P36 -> 0 | V36: 0 | W36: =F36*D36 -> 0 | X36: 0 | Y36: =Z36*D36 -> 179.6 | Z36: 1 | AA36: =E36+G36+I36+K36+M36+O36+Q36+S36+U36+W36+Y36 -> 179.6 | AB36: =AA36/D36 -> 1
B37: 14 | C37: Muro sin ventanas | D37: 0 | E37: =D37*F37 -> 0 | F37: 0 | G37: =D37*H37 -> 0 | H37: 0 | I37: =J37*D37 -> 0 | J37: 0 | K37: =L37*F37 -> 0 | L37: 0 | M37: =N37*H37 -> 0 | N37: 0 | O37: =P37*J37 -> 0 | P37: 0 | Q37: =R37*L37 -> 0 | R37: 0 | S37: =T37*N37 -> 0 | T37: 0 | U37: =V37*P37 -> 0 | V37: 0 | W37: =F37*D37 -> 0 | X37: 0 | Y37: =Z37*D37 -> 0 | Z37: 1 | AA37: =E37+G37+I37+K37+M37+O37+Q37+S37+U37+W37+Y37 -> 0 | AB37: 0
B38: 15 | C38: Muro con balcones y volumenes | D38: =SUM(CO!K72:K74) -> 93.4 | E38: =D38*F38 -> 0 | F38: 0 | G38: =D38*H38 -> 0 | H38: 0 | I38: =J38*D38 -> 0 | J38: 0 | K38: =L38*F38 -> 0 | L38: 0 | M38: =N38*H38 -> 0 | N38: 0 | O38: =P38*J38 -> 0 | P38: 0 | Q38: =R38*L38 -> 0 | R38: 0 | S38: =T38*N38 -> 0 | T38: 0 | U38: =V38*P38 -> 0 | V38: 0 | W38: =F38*D38 -> 0 | X38: 0 | Y38: =Z38*D38 -> 93.4 | Z38: 1 | AA38: =E38+G38+I38+K38+M38+O38+Q38+S38+U38+W38+Y38 -> 93.4 | AB38: =AA38/D38 -> 1
B39: 16 | C39: Muro sin ventanas | D39: 0 | E39: =D39*F39 -> 0 | F39: 0 | G39: =D39*H39 -> 0 | H39: 0 | I39: =J39*D39 -> 0 | J39: 0 | K39: =L39*F39 -> 0 | L39: 0 | M39: =N39*H39 -> 0 | N39: 0 | O39: =P39*J39 -> 0 | P39: 0 | Q39: =R39*L39 -> 0 | R39: 0 | S39: =T39*N39 -> 0 | T39: 0 | U39: =V39*P39 -> 0 | V39: 0 | W39: =F39*D39 -> 0 | X39: 0 | Y39: =Z39*D39 -> 0 | Z39: 1 | AA39: =E39+G39+I39+K39+M39+O39+Q39+S39+U39+W39+Y39 -> 0 | AB39: 0
B40: 17 | C40: Muro con balcones y volumenes | D40: =SUM(CO!K77:K79) -> 93.4 | E40: =D40*F40 -> 0 | F40: 0 | G40: =D40*H40 -> 0 | H40: 0 | I40: =J40*D40 -> 0 | J40: 0 | K40: =L40*F40 -> 0 | L40: 0 | M40: =N40*H40 -> 0 | N40: 0 | O40: =P40*J40 -> 0 | P40: 0 | Q40: =R40*L40 -> 0 | R40: 0 | S40: =T40*N40 -> 0 | T40: 0 | U40: =V40*P40 -> 0 | V40: 0 | W40: =F40*D40 -> 0 | X40: 0 | Y40: =Z40*D40 -> 93.4 | Z40: 1 | AA40: =E40+G40+I40+K40+M40+O40+Q40+S40+U40+W40+Y40 -> 93.4 | AB40: =AA40/D40 -> 1
C41: Volumenes en fachada | D41: 0 | E41: =D41*F41 -> 0 | F41: 0 | G41: =D41*H41 -> 0 | H41: 0 | I41: =J41*D41 -> 0 | J41: 0 | K41: =L41*F41 -> 0 | L41: 0 | M41: =N41*H41 -> 0 | N41: 0 | O41: =P41*J41 -> 0 | P41: 0 | Q41: =R41*L41 -> 0 | R41: 0 | S41: =T41*N41 -> 0 | T41: 0 | U41: =V41*P41 -> 0 | V41: 0 | W41: =F41*D41 -> 0 | X41: 0 | Y41: =Z41*D41 -> 0 | Z41: 1 | AA41: =E41+G41+I41+K41+M41+O41+Q41+S41+U41+W41+Y41 -> 0 | AB41: 0
C43: TOTAL M2 DE FACHADA | D43: =SUM(D34:D42) -> 490.6 | E43: =SUM(E39:E42) -> 0 | F43: =E43/D43 -> 0 | G43: =SUM(G39:G42) -> 0 | H43: =G43/D43 -> 0 | I43: =SUM(I39:I42) -> 0 | J43: =I43/D43 -> 0 | K43: =SUM(K35:K42) -> 0 | L43: =K43/D43 -> 0 | M43: =SUM(M35:M42) -> 0 | N43: =M43/D43 -> 0 | O43: =SUM(O35:O42) -> 0 | P43: =O43/D43 -> 0 | Q43: =SUM(Q35:Q42) -> 0 | R43: =Q43/D43 -> 0 | S43: =SUM(S35:S42) -> 0 | T43: =S43/D43 -> 0 | U43: =SUM(U35:U42) -> 0 | V43: =U43/D43 -> 0 | W43: =SUM(W34:W41) -> 0 | X43: =W43/D43 -> 0 | Y43: =SUM(Y34:Y41) -> 490.6 | Z43: =Y43/D43 -> 1 | AA43: =SUM(AA34:AA41) -> 490.6 | AB43: =AA43/D43 -> 1
AA44: =D43-AA43 -> 0 | AB44: =AA44/D43 -> 0
C46: TOTAL M2 DE FACHADAS GENERAL | D46: =D15+D26+D31+D43 -> 1277.45 | H46: TOTAL M2 DE EJECUTADOS | AA46: =AA15+AA26+AA31+AA43 -> 1277.45 | AB46: =AA46/D46 -> 1 | AC46: =AC15+AC26+AC31+AC43 -> 210.944 | AD46: =AC46/D46 -> 0.16512897 | AE46: =AE15+AE26+AE31+AE43 -> 242.787 | AF46: =AE46/D46 -> 0.19005597 | AG46: =AG15+AG26+AG31+AG43 -> 163.5725 | AH46: =AG46/D46 -> 0.12804611
AA47: =D46-AA46 -> 0 | AB47: =AA47/D46 -> 0

Sheet Graniplast
A6: EDIFICIO EL MIRADOR - RESANE DE GRANIPLAST
E7: OCT 16 - 17 | G7: OCT 20 - 24 | I7: OCT 27 - 31 | K7: NOV 03 - 08 | M7: NOV 10 - 15 | O7: NOV 17 - 22 | Q7: NOV 24 - 29 | S7: DIC 09 - 13 | U7: DIC 15 - ENE 20
A8: FACHADA | B8: SECCIÓN | C8: DESCRIPCIÓN | D8: M2 | E8: SEMANA 01 | G8: SEMANA 02 | I8: SEMANA 03 | K8: SEMANA 04 | M8: SEMANA 05 | O8: SEMANA 06 | Q8: SEMANA 07 | S8: Semana 09 | U8: Semana 10 - 12 | W8: Total Ejecutado | Y8: Total Ejecutado Acta 01 | AA8: Total Ejecutado Acta 02 | AC8: Total Ejecutado Acta 02
E9: M2 | F9: % | G9: M2 | H9: % | I9: M2 | J9: % | K9: M2 | L9: % | M9: M2 | N9: % | O9: M2 | P9: % | Q9: M2 | R9: % | S9: M2 | T9: % | U9: M2 | V9: % | W9: M2 | X9: % | Y9: M2 | Z9: % | AA9: M2 | AB9: % | AC9: M2 | AD9: %
A10: NORTE | B10: 1 | C10: Muro con ventana | D10: ='CO SIF'!E6 -> 117.42965 | E10: 0 | F10: 0 | G10: 45 | H10: =G10/D10 -> 0.38320816 | I10: 0 | J10: =I10/D10 -> 0 | K10: =D10*L10 -> 0 | L10: 0 | M10: =D10*N10 -> 0 | N10: 0 | O10: =D10*P10 -> 0 | P10: 0 | Q10: =D10*R10 -> 0 | R10: 0 | S10: =D10*T10 -> 5.8714825 | T10: 0.05 | U10: =D10*V10 -> 3.5228895 | V10: 0.03 | W10: =E10+G10+I10+K10+M10+O10+Q10+S10+U10 -> 54.394372 | X10: =W10/D10 -> 0.46320816 | Y10: =E10+G10+I10+K10 -> 45 | Z10: =Y10/D10 -> 0.38320816 | AA10: =M10+O10+Q10+S10 -> 5.8714825 | AB10: =AA10/D10 -> 0.05 | AC10: =U10 -> 3.5228895 | AD10: =AC10/D10 -> 0.03
B11: 2 | C11: Muro con ventana | D11: ='CO SIF'!E7 -> 44.324475 | E11: 0 | F11: 0 | G11: 25 | H11: =G11/D11 -> 0.56402247 | I11: 0 | J11: =I11/D11 -> 0 | K11: =D11*L11 -> 0 | L11: 0 | M11: =D11*N11 -> 0 | N11: 0 | O11: =D11*P11 -> 0 | P11: 0 | Q11: =D11*R11 -> 0 | R11: 0 | S11: =D11*T11 -> 2.2162238 | T11: 0.05 | U11: =D11*V11 -> 2.2162238 | V11: 0.05 | W11: =E11+G11+I11+K11+M11+O11+Q11+S11+U11 -> 29.432448 | X11: =W11/D11 -> 0.66402247 | Y11: =E11+G11+I11+K11 -> 25 | Z11: =Y11/D11 -> 0.56402247 | AA11: =M11+O11+Q11+S11 -> 2.2162238 | AB11: =AA11/D11 -> 0.05 | AC11: =U11 -> 2.2162238 | AD11: =AC11/D11 -> 0.05
B12: 3 | C12: Culata baja sin ventanas | D12: ='CO SIF'!E8 -> 70.754385 | E12: 0 | F12: 0 | G12: 0 | H12: =G12/D12 -> 0 | I12: 0 | J12: =I12/D12 -> 0 | K12: =D12*L12 -> 0 | L12: 0 | M12: =D12*N12 -> 0 | N12: 0 | O12: =D12*P12 -> 0 | P12: 0 | Q12: =D12*R12 -> 0 | R12: 0 | S12: =D12*T12 -> 0 | T12: 0 | U12: =D12*V12 -> 0 | V12: 0 | W12: =E12+G12+I12+K12+M12+O12+Q12+S12+U12 -> 0 | X12: =W12/D12 -> 0 | Y12: =E12+G12+I12+K12 -> 0 | Z12: =Y12/D12 -> 0 | AA12: =M12+O12+Q12+S12 -> 0 | AB12: =AA12/D12 -> 0 | AC12: =U12 -> 0 | AD12: =AC12/D12 -> 0
B13: 4 | C13: Culata alta sin ventanas | D13: ='CO SIF'!E9 -> 201.13315 | E13: 0 | F13: 0 | G13: 0 | H13: =G13/D13 -> 0 | I13: 0 | J13: =I13/D13 -> 0 | K13: =D13*L13 -> 0 | L13: 0 | M13: =D13*N13 -> 0 | N13: 0 | O13: =D13*P13 -> 0 | P13: 0 | Q13: =D13*R13 -> 0 | R13: 0 | S13: =D13*T13 -> 0 | T13: 0 | U13: =D13*V13 -> 0 | V13: 0 | W13: =E13+G13+I13+K13+M13+O13+Q13+S13+U13 -> 0 | X13: =W13/D13 -> 0 | Y13: =E13+G13+I13+K13 -> 0 | Z13: =Y13/D13 -> 0 | AA13: =M13+O13+Q13+S13 -> 0 | AB13: =AA13/D13 -> 0 | AC13: =U13 -> 0 | AD13: =AC13/D13 -> 0
C15: TOTAL M2 DE FACHADA | D15: =SUM(D10:D14) -> 433.64166 | E15: =SUM(E10:E14) -> 0 | F15: =E15/D15 -> 0 | G15: =SUM(G10:G13) -> 70 | H15: =G15/D15 -> 0.1614236 | I15: =SUM(I10:I13) -> 0 | J15: =I15/D15 -> 0 | K15: =SUM(K6:K13) -> 0 | L15: =K15/D15 -> 0 | M15: =SUM(M6:M13) -> 0 | N15: =M15/D15 -> 0 | O15: =SUM(O6:O13) -> 0 | P15: =O15/D15 -> 0 | Q15: =SUM(Q6:Q13) -> 0 | R15: =Q15/D15 -> 0 | S15: =SUM(S6:S13) -> 8.0877063 | T15: =S15/D15 -> 0.018650667 | U15: =SUM(U10:U13) -> 5.7391133 | V15: =U15/D15 -> 0.013234691 | W15: =SUM(W10:W13) -> 83.826819 | X15: =W15/D15 -> 0.19330896 | Y15: =SUM(Y10:Y13) -> 70 | Z15: =Y15/D15 -> 0.1614236 | AA15: =SUM(AA10:AA13) -> 8.0877063 | AB15: =AA15/D15 -> 0.018650667 | AC15: =SUM(AC10:AC13) -> 5.7391133 | AD15: =AC15/D15 -> 0.013234691
W16: =D15-W15 -> 349.81484 | X16: =W16/D15 -> 0.80669104
A19: ESTE | B19: 5 | C19: Muro con balcones y volumenes | D19: ='CO SIF'!E15 -> 627.00183 | E19: 0 | F19: 0 | G19: 0 | H19: 0 | I19: 35 | J19: =I19/D19 -> 0.055821209 | K19: =D19*L19 -> 12.540037 | L19: 0.02 | M19: =D19*N19 -> 0 | N19: 0 | O19: =D19*P19 -> 0 | P19: 0 | Q19: =D19*R19 -> 0 | R19: 0 | S19: =D19*T19 -> 12.540037 | T19: 0.02 | U19: =D19*V19 -> 31.350092 | V19: 0.05 | W19: =E19+G19+I19+K19+M19+O19+Q19+S19+U19 -> 91.430165 | X19: =W19/D19 -> 0.14582121 | Y19: =E19+G19+I19+K19 -> 47.540037 | Z19: =Y19/D19 -> 0.075821209 | AA19: =M19+O19+Q19+S19 -> 12.540037 | AB19: =AA19/D19 -> 0.02 | AC19: =U19 -> 31.350092 | AD19: =AC19/D19 -> 0.05
C20: Muro culata parqueadero | D20: ='CO SIF'!E16 -> 413.036 | E20: 0 | F20: 0 | G20: 0 | H20: 0 | I20: 0 | J20: 0 | K20: =D20*L20 -> 0 | L20: 0 | M20: =D20*N20 -> 0 | N20: 0 | O20: =D20*P20 -> 0 | P20: 0 | Q20: =D20*R20 -> 0 | R20: 0 | S20: =D20*T20 -> 0 | T20: 0 | U20: =D20*V20 -> 0 | V20: 0 | W20: =E20+G20+I20+K20+M20+O20+Q20+S20+U20 -> 0 | X20: =W20/D20 -> 0 | Y20: =E20+G20+I20+K20 -> 0 | Z20: =Y20/D20 -> 0 | AA20: =M20+O20+Q20+S20 -> 0 | AB20: =AA20/D20 -> 0 | AC20: =U20 -> 0 | AD20: =AC20/D20 -> 0
B21: 6 | C21: Muro sin ventanas | D21: ='CO SIF'!E17 -> 28.3413 | E21: 0 | F21: 0 | G21: 0 | H21: 0 | I21: 0 | J21: 0 | K21: =D21*L21 -> 0 | L21: 0 | M21: =D21*N21 -> 0 | N21: 0 | O21: =D21*P21 -> 0 | P21: 0 | Q21: =D21*R21 -> 0 | R21: 0 | S21: =D21*T21 -> 0 | T21: 0 | U21: =D21*V21 -> 0.566826 | V21: 0.02 | W21: =E21+G21+I21+K21+M21+O21+Q21+S21+U21 -> 0.566826 | X21: =W21/D21 -> 0.02 | Y21: =E21+G21+I21+K21 -> 0 | Z21: =Y21/D21 -> 0 | AA21: =M21+O21+Q21+S21 -> 0 | AB21: =AA21/D21 -> 0 | AC21: =U21 -> 0.566826 | AD21: =AC21/D21 -> 0.02
B22: 7 | C22: Muro con balcones y volumenes | D22: ='CO SIF'!E18 -> 207.6165 | E22: 0 | F22: 0 | G22: 0 | H22: 0 | I22: 0 | J22: 0 | K22: =D22*L22 -> 22.837815 | L22: 0.11 | M22: =D22*N22 -> 0 | N22: 0 | O22: =D22*P22 -> 0 | P22: 0 | Q22: =D22*R22 -> 0 | R22: 0 | S22: =D22*T22 -> 0 | T22: 0 | U22: =D22*V22 -> 5.1904125 | V22: 0.025 | W22: =E22+G22+I22+K22+M22+O22+Q22+S22+U22 -> 28.028227 | X22: =W22/D22 -> 0.135 | Y22: =E22+G22+I22+K22 -> 22.837815 | Z22: =Y22/D22 -> 0.11 | AA22: =M22+O22+Q22+S22 -> 0 | AB22: =AA22/D22 -> 0 | AC22: =U22 -> 5.1904125 | AD22: =AC22/D22 -> 0.025
B23: 8 | C23: Muro sin ventanas | D23: ='CO SIF'!E19 -> 28.3413 | E23: 0 | F23: 0 | G23: 0 | H23: 0 | I23: 0 | J23: 0 | K23: =D23*L23 -> 0 | L23: 0 | M23: =D23*N23 -> 0 | N23: 0 | O23: =D23*P23 -> 0 | P23: 0 | Q23: =D23*R23 -> 0 | R23: 0 | S23: =D23*T23 -> 0 | T23: 0 | U23: =D23*V23 -> 0 | V23: 0 | W23: =E23+G23+I23+K23+M23+O23+Q23+S23+U23 -> 0 | X23: =W23/D23 -> 0 | Y23: =E23+G23+I23+K23 -> 0 | Z23: =Y23/D23 -> 0 | AA23: =M23+O23+Q23+S23 -> 0 | AB23: =AA23/D23 -> 0 | AC23: =U23 -> 0 | AD23: =AC23/D23 -> 0
B24: 9 | C24: Muro con balcones y volumenes | D24: ='CO SIF'!E20 -> 232.05812 | E24: 0 | F24: 0 | G24: 0 | H24: 0 | I24: 0 | J24: 0 | K24: =D24*L24 -> 0 | L24: 0 | M24: =D24*N24 -> 0 | N24: 0 | O24: =D24*P24 -> 0 | P24: 0 | Q24: =D24*R24 -> 0 | R24: 0 | S24: =D24*T24 -> 0 | T24: 0 | U24: =D24*V24 -> 18.56465 | V24: 0.08 | W24: =E24+G24+I24+K24+M24+O24+Q24+S24+U24 -> 18.56465 | X24: =W24/D24 -> 0.08 | Y24: =E24+G24+I24+K24 -> 0 | Z24: =Y24/D24 -> 0 | AA24: =M24+O24+Q24+S24 -> 0 | AB24: =AA24/D24 -> 0 | AC24: =U24 -> 18.56465 | AD24: =AC24/D24 -> 0.08
C26: TOTAL M2 DE FACHADA | D26: =SUM(D19:D25) -> 1536.3951 | E26: =SUM(E19:E25) -> 0 | F26: =E26/D26 -> 0 | G26: =SUM(G19:G25) -> 0 | H26: =G26/D26 -> 0 | I26: =SUM(I19:I25) -> 35 | J26: =I26/D26 -> 0.022780599 | K26: =SUM(K17:K24) -> 35.377852 | L26: =K26/D26 -> 0.023026533 | M26: =SUM(M17:M24) -> 0 | N26: =M26/D26 -> 0 | O26: =SUM(O17:O24) -> 0 | P26: =O26/D26 -> 0 | Q26: =SUM(Q17:Q24) -> 0 | R26: =Q26/D26 -> 0 | S26: =SUM(S17:S24) -> 12.540037 | T26: =S26/D26 -> 0.0081619871 | U26: =SUM(U19:U24) -> 55.67198 | V26: =U26/D26 -> 0.036235459 | W26: =SUM(W19:W24) -> 138.58987 | X26: =W26/D26 -> 0.090204578 | Y26: =SUM(Y19:Y24) -> 70.377852 | Z26: =Y26/D26 -> 0.045807132 | AA26: =SUM(AA19:AA24) -> 12.540037 | AB26: =AA26/D26 -> 0.0081619871 | AC26: =SUM(AC19:AC24) -> 55.67198 | AD26: =AC26/D26 -> 0.036235459
W27: =D26-W26 -> 1397.8052 | X27: =W27/D26 -> 0.90979542
A29: SUR | B29: 10 | C29: Muro con balcones y volumenes | D29: ='CO SIF'!E26 -> 599.57503 | E29: =D29*F29 -> 0 | F29: 0 | G29: =D29*H29 -> 0 | H29: 0 | I29: =D29*J29 -> 0 | J29: 0 | K29: =D29*L29 -> 0 | L29: 0 | M29: =D29*N29 -> 0 | N29: 0 | O29: =D29*P29 -> 0 | P29: 0 | Q29: =D29*R29 -> 0 | R29: 0 | S29: =D29*T29 -> 0 | T29: 0 | U29: =D29*V29 -> 23.983001 | V29: 0.04 | W29: =E29+G29+I29+K29+M29+O29+Q29+S29+U29 -> 23.983001 | X29: =W29/D29 -> 0.04 | Y29: =E29+G29+I29+K29 -> 0 | Z29: =Y29/D29 -> 0 | AA29: =M29+O29+Q29+S29 -> 0 | AB29: =AA29/D29 -> 0 | AC29: =U29 -> 23.983001 | AD29: =AC29/D29 -> 0.04
C31: TOTAL M2 DE FACHADA | D31: =SUM(D29:D30) -> 599.57503 | E31: =SUM(E29:E30) -> 0 | F31: =E31/D31 -> 0 | G31: =SUM(G29:G29) -> 0 | H31: =G31/D31 -> 0 | I31: =SUM(I29:I29) -> 0 | J31: =I31/D31 -> 0 | K31: =SUM(K22:K29) -> 58.215667 | L31: =K31/D31 -> 0.097094881 | M31: =SUM(M22:M29) -> 0 | N31: =M31/D31 -> 0 | O31: =SUM(O22:O29) -> 0 | P31: =O31/D31 -> 0 | Q31: =SUM(Q22:Q29) -> 0 | R31: =Q31/D31 -> 0 | S31: =SUM(S22:S29) -> 12.540037 | T31: =S31/D31 -> 0.020914875 | U31: =SUM(U29) -> 23.983001 | V31: =U31/D31 -> 0.04 | W31: =SUM(W29:W29) -> 23.983001 | X31: =W31/D31 -> 0.04 | Y31: =SUM(Y29) -> 0 | Z31: =Y31/D31 -> 0 | AA31: =SUM(AA29) -> 0 | AB31: =AA31/D31 -> 0 | AC31: =SUM(AC29) -> 23.983001 | AD31: =AC31/D31 -> 0.04
W32: =D31-W31 -> 575.59203 | X32: =W32/D31 -> 0.96
A34: OESTE | B34: 11 | C34: Muro con balcones y volumenes | D34: ='CO SIF'!E32 -> 253.9732 | E34: =D34*F34 -> 0 | F34: 0 | G34: =D34*H34 -> 0 | H34: 0 | I34: =J34*D34 -> 0 | J34: 0 | K34: =D34*L34 -> 0 | L34: 0 | M34: =D34*N34 -> 0 | N34: 0 | O34: =D34*P34 -> 0 | P34: 0 | Q34: =D34*R34 -> 0 | R34: 0 | S34: =F34*T34 -> 0 | T34: 0 | U34: =D34*V34 -> 0 | V34: 0 | W34: =E34+G34+I34 -> 0 | X34: =W34/D34 -> 0 | Y34: =E34+G34+I34+K34 -> 0 | Z34: =Y34/D34 -> 0 | AA34: =M34+O34+Q34+S34 -> 0 | AB34: =AA34/D34 -> 0 | AC34: =O34+Q34+S34+U34 -> 0 | AD34: =AC34/D34 -> 0
B35: 12 | C35: Muro sin ventanas | D35: ='CO SIF'!E33 -> 56.6826 | E35: =D35*F35 -> 0 | F35: 0 | G35: =D35*H35 -> 0 | H35: 0 | I35: =J35*D35 -> 0 | J35: 0 | K35: =D35*L35 -> 0 | L35: 0 | M35: =D35*N35 -> 0 | N35: 0 | O35: =D35*P35 -> 0 | P35: 0 | Q35: =D35*R35 -> 0 | R35: 0 | S35: =F35*T35 -> 0 | T35: 0 | U35: =D35*V35 -> 0 | V35: 0 | W35: =E35+G35+I35 -> 0 | X35: =W35/D35 -> 0 | Y35: =E35+G35+I35+K35 -> 0 | Z35: =Y35/D35 -> 0 | AA35: =M35+O35+Q35+S35 -> 0 | AB35: =AA35/D35 -> 0 | AC35: =O35+Q35+S35+U35 -> 0 | AD35: =AC35/D35 -> 0
B36: 13 | C36: Muro con balcones y volumenes | D36: ='CO SIF'!E34 -> 522.886 | E36: =D36*F36 -> 0 | F36: 0 | G36: =D36*H36 -> 0 | H36: 0 | I36: =J36*D36 -> 0 | J36: 0 | K36: =D36*L36 -> 0 | L36: 0 | M36: =D36*N36 -> 0 | N36: 0 | O36: =D36*P36 -> 0 | P36: 0 | Q36: =D36*R36 -> 0 | R36: 0 | S36: =F36*T36 -> 0 | T36: 0 | U36: =D36*V36 -> 0 | V36: 0 | W36: =E36+G36+I36 -> 0 | X36: =W36/D36 -> 0 | Y36: =E36+G36+I36+K36 -> 0 | Z36: =Y36/D36 -> 0 | AA36: =M36+O36+Q36+S36 -> 0 | AB36: =AA36/D36 -> 0 | AC36: =O36+Q36+S36+U36 -> 0 | AD36: =AC36/D36 -> 0
B37: 14 | C37: Muro sin ventanas | D37: ='CO SIF'!E35 -> 35.426625 | E37: =D37*F37 -> 0 | F37: 0 | G37: =D37*H37 -> 0 | H37: 0 | I37: =J37*D37 -> 0 | J37: 0 | K37: =D37*L37 -> 0 | L37: 0 | M37: =D37*N37 -> 0 | N37: 0 | O37: =D37*P37 -> 0 | P37: 0 | Q37: =D37*R37 -> 0 | R37: 0 | S37: =F37*T37 -> 0 | T37: 0 | U37: =D37*V37 -> 0 | V37: 0 | W37: =E37+G37+I37 -> 0 | X37: =W37/D37 -> 0 | Y37: =E37+G37+I37+K37 -> 0 | Z37: =Y37/D37 -> 0 | AA37: =M37+O37+Q37+S37 -> 0 | AB37: =AA37/D37 -> 0 | AC37: =O37+Q37+S37+U37 -> 0 | AD37: =AC37/D37 -> 0
B38: 15 | C38: Muro con balcones y volumenes | D38: ='CO SIF'!E36 -> 194.81238 | E38: =D38*F38 -> 0 | F38: 0 | G38: =D38*H38 -> 0 | H38: 0 | I38: =J38*D38 -> 0 | J38: 0 | K38: =D38*L38 -> 0 | L38: 0 | M38: =D38*N38 -> 0 | N38: 0 | O38: =D38*P38 -> 0 | P38: 0 | Q38: =D38*R38 -> 0 | R38: 0 | S38: =F38*T38 -> 0 | T38: 0 | U38: =D38*V38 -> 0 | V38: 0 | W38: =E38+G38+I38 -> 0 | X38: =W38/D38 -> 0 | Y38: =E38+G38+I38+K38 -> 0 | Z38: =Y38/D38 -> 0 | AA38: =M38+O38+Q38+S38 -> 0 | AB38: =AA38/D38 -> 0 | AC38: =O38+Q38+S38+U38 -> 0 | AD38: =AC38/D38 -> 0
B39: 16 | C39: Muro sin ventanas | D39: ='CO SIF'!E37 -> 16.532425 | E39: =D39*F39 -> 0 | F39: 0 | G39: =D39*H39 -> 0 | H39: 0 | I39: =J39*D39 -> 0 | J39: 0 | K39: =D39*L39 -> 0 | L39: 0 | M39: =D39*N39 -> 0 | N39: 0 | O39: =D39*P39 -> 0 | P39: 0 | Q39: =D39*R39 -> 0 | R39: 0 | S39: =F39*T39 -> 0 | T39: 0 | U39: =D39*V39 -> 0 | V39: 0 | W39: =E39+G39+I39 -> 0 | X39: =W39/D39 -> 0 | Y39: =E39+G39+I39+K39 -> 0 | Z39: =Y39/D39 -> 0 | AA39: =M39+O39+Q39+S39 -> 0 | AB39: =AA39/D39 -> 0 | AC39: =O39+Q39+S39+U39 -> 0 | AD39: =AC39/D39 -> 0
B40: 17 | C40: Muro con balcones y volumenes | D40: ='CO SIF'!E38 -> 104.5772 | E40: =D40*F40 -> 0 | F40: 0 | G40: =D40*H40 -> 0 | H40: 0 | I40: =J40*D40 -> 0 | J40: 0 | K40: =D40*L40 -> 0 | L40: 0 | M40: =D40*N40 -> 0 | N40: 0 | O40: =D40*P40 -> 0 | P40: 0 | Q40: =D40*R40 -> 0 | R40: 0 | S40: =F40*T40 -> 0 | T40: 0 | U40: =D40*V40 -> 0 | V40: 0 | W40: =E40+G40+I40 -> 0 | X40: =W40/D40 -> 0 | Y40: =E40+G40+I40+K40 -> 0 | Z40: =Y40/D40 -> 0 | AA40: =M40+O40+Q40+S40 -> 0 | AB40: =AA40/D40 -> 0 | AC40: =O40+Q40+S40+U40 -> 0 | AD40: =AC40/D40 -> 0
C41: Volumenes en fachada | D41: ='CO SIF'!E39 -> 42.896425 | E41: =D41*F41 -> 0 | F41: 0 | G41: =D41*H41 -> 0 | H41: 0 | I41: =J41*D41 -> 0 | J41: 0 | K41: =D41*L41 -> 0 | L41: 0 | M41: =D41*N41 -> 0 | N41: 0 | O41: =D41*P41 -> 0 | P41: 0 | Q41: =D41*R41 -> 0 | R41: 0 | S41: =D41*T41 -> 0 | T41: 0 | U41: =D41*V41 -> 0 | V41: 0 | W41: =E41+G41+I41 -> 0 | X41: =W41/D41 -> 0 | Y41: =E41+G41+I41+K41 -> 0 | Z41: =Y41/D41 -> 0 | AA41: =M41+O41+Q41+S41 -> 0 | AB41: =AA41/D41 -> 0 | AC41: =U41 -> 0 | AD41: =AC41/D41 -> 0
C43: TOTAL M2 DE FACHADA | D43: =SUM(D34:D42) -> 1227.7869 | E43: =SUM(E34:E42) -> 0 | F43: =E43/D43 -> 0 | G43: =SUM(G34:G42) -> 0 | H43: =G43/D43 -> 0 | I43: =SUM(I34:I42) -> 0 | J43: =I43/D43 -> 0 | K43: =SUM(K34:K41) -> 0 | L43: =K43/D43 -> 0 | M43: =SUM(M34:M41) -> 0 | N43: =M43/D43 -> 0 | O43: =SUM(O34:O41) -> 0 | P43: =O43/D43 -> 0 | Q43: =SUM(Q34:Q41) -> 0 | R43: =Q43/D43 -> 0 | S43: =SUM(S34:S41) -> 0 | T43: =S43/D43 -> 0 | U43: =SUM(U34:U41) -> 0 | V43: =U43/D43 -> 0 | W43: =SUM(W34:W41) -> 0 | X43: =W43/D43 -> 0 | Y43: =SUM(Y34:Y41) -> 0 | Z43: =Y43/D43 -> 0 | AA43: =SUM(AA34:AA41) -> 0 | AB43: =AA43/D43 -> 0 | AC43: =SUM(AC38:AC41) -> 0 | AD43: =AC43/D43 -> 0
W44: =D43-W43 -> 1227.7869 | X44: =W44/D43 -> 1
C46: TOTAL M2 DE FACHADAS GENERAL | D46: =D15+D26+D31+D43 -> 3797.3986 | H46: TOTAL M2 DE EJECUTADOS | W46: =W15+W26+W31+W43 -> 246.39969 | X46: =W46/D46 -> 0.064886443 | Y46: =Y15+Y26+Y31+Y43 -> 140.37785 | Z46: =Y46/D46 -> 0.036966847 | AA46: =AA15+AA26+AA31+AA43 -> 20.627743 | AB46: =AA46/D46 -> 0.0054320721 | AC46: =AC15+AC26+AC31+AC43 -> 85.394095 | AD46: =AC46/D46 -> 0.022487525
W47: =D46-W46 -> 3550.9989 | X47: =W47/D46 -> 0.93511356
A49: PASILLOS | B49: 9 | C49: Piso Completo | D49: =SUM('CO SIF'!D48:D50) -> 107.19 | E49: =D49*F49 -> 0 | F49: 0 | G49: =D49*H49 -> 0 | H49: 0 | I49: =J49*D49 -> 0 | J49: 0 | W49: =E49+G49+I49 -> 0 | X49: =W49/D49 -> 0
B50: 8 | C50: Piso Completo | D50: =$D$49 -> 107.19 | E50: =D50*F50 -> 0 | F50: 0 | G50: =D50*H50 -> 0 | H50: 0 | I50: =J50*D50 -> 0 | J50: 0 | W50: =E50+G50+I50 -> 0 | X50: =W50/D50 -> 0
B51: 7 | C51: Piso Completo | D51: =$D$49 -> 107.19 | E51: =D51*F51 -> 0 | F51: 0 | G51: =D51*H51 -> 0 | H51: 0 | I51: =J51*D51 -> 0 | J51: 0 | W51: =E51+G51+I51 -> 0 | X51: =W51/D51 -> 0
B52: 6 | C52: Piso Completo | D52: =$D$49 -> 107.19 | E52: =D52*F52 -> 0 | F52: 0 | G52: =D52*H52 -> 0 | H52: 0 | I52: =J52*D52 -> 0 | J52: 0 | W52: =E52+G52+I52 -> 0 | X52: =W52/D52 -> 0
B53: 5 | C53: Piso Completo | D53: =$D$49 -> 107.19 | E53: =D53*F53 -> 0 | F53: 0 | G53: =D53*H53 -> 0 | H53: 0 | I53: =J53*D53 -> 0 | J53: 0 | W53: =E53+G53+I53 -> 0 | X53: =W53/D53 -> 0
B54: 4 | C54: Piso Completo | D54: =$D$49 -> 107.19 | E54: =D54*F54 -> 0 | F54: 0 | G54: =D54*H54 -> 0 | H54: 0 | I54: =J54*D54 -> 0 | J54: 0 | W54: =E54+G54+I54 -> 0 | X54: =W54/D54 -> 0
B55: 3 | C55: Piso Completo | D55: =$D$49 -> 107.19 | E55: =D55*F55 -> 0 | F55: 0 | G55: =D55*H55 -> 0 | H55: 0 | I55: =J55*D55 -> 0 | J55: 0 | W55: =E55+G55+I55 -> 0 | X55: =W55/D55 -> 0
B56: 2 | C56: Piso Completo | D56: =$D$49 -> 107.19 | E56: =D56*F56 -> 0 | F56: 0 | G56: =D56*H56 -> 0 | H56: 0 | I56: =J56*D56 -> 0 | J56: 0 | W56: =E56+G56+I56 -> 0 | X56: =W56/D56 -> 0
B57: 1 | C57: Piso Completo | D57: =$D$49 -> 107.19 | E57: =D57*F57 -> 0 | F57: 0 | G57: =D57*H57 -> 0 | H57: 0 | I57: =J57*D57 -> 0 | J57: 0 | W57: =E57+G57+I57 -> 0 | X57: =W57/D57 -> 0
B58: S1 | C58: Piso Completo | D58: =$D$49 -> 107.19 | E58: =D58*F58 -> 0 | F58: 0 | G58: =D58*H58 -> 0 | H58: 0 | I58: =J58*D58 -> 0 | J58: 0 | W58: =E58+G58+I58 -> 0 | X58: =W58/D58 -> 0
B59: S2 | C59: Piso Completo | D59: =$D$49 -> 107.19 | E59: =D59*F59 -> 0 | F59: 0 | G59: =D59*H59 -> 0 | H59: 0 | I59: =J59*D59 -> 0 | J59: 0 | W59: =E59+G59+I59 -> 0 | X59: =W59/D59 -> 0
C61: TOTAL M2 DE FACHADA | D61: =SUM(D49:D58) -> 1071.9 | E61: =SUM(E49:E58) -> 0 | F61: =E61/D61 -> 0 | G61: =SUM(G49:G58) -> 0 | H61: =G61/D61 -> 0 | I61: =SUM(I49:I58) -> 0 | J61: =I61/D61 -> 0 | W61: =SUM(W49:W56) -> 0 | X61: =W61/D61 -> 0
W62: =D61-W61 -> 1071.9 | X62: =W62/D61 -> 1

Sheet Pintura
A6: EDIFICIO EL MIRADOR - LAVADO DE FACHADA
E7: OCT 16 - 17 | G7: OCT 20 - 24 | I7: OCT 27 - 31 | K7: NOV 03 - 08 | M7: NOV 10 - 15 | O7: NOV 17 - 22 | Q7: NOV 24 - 29 | S7: DIC 01 - 06 | U7: DIC 09 - 13 | W7: DIC 15 - ENE 20 | Y7: ENE 20 - MAR 11
A8: FACHADA | B8: SECCIÓN | C8: DESCRIPCIÓN | D8: M2 | E8: SEMANA 01 | G8: SEMANA 02 | I8: SEMANA 03 | K8: SEMANA 04 | M8: SEMANA 05 | O8: SEMANA 06 | Q8: SEMANA 07 | S8: Semana 08 | U8: Semana 09 | W8: Semana 10 - 12 | AA8: Total Ejecutado | AC8: Total Ejecutado Acta 01 | AE8: Total Ejecutado Acta 02 | AG8: Total Ejecutado Acta 03
E9: M2 | F9: % | G9: M2 | H9: % | I9: M2 | J9: % | K9: M2 | L9: % | M9: M2 | N9: % | O9: M2 | P9: % | Q9: M2 | R9: % | S9: M2 | T9: % | U9: M2 | V9: % | W9: M2 | X9: % | Y9: M2 | Z9: % | AA9: M2 | AB9: % | AC9: M2 | AD9: % | AE9: M2 | AF9: % | AG9: M2 | AH9: %
A10: NORTE | B10: 1 | C10: Muro con ventana | D10: ='CO SIF'!E6 -> 117.42965 | E10: =D10*F10 -> 0 | F10: 0 | G10: =D10*H10 -> 58.714825 | H10: 0.5 | I10: =D10*J10 -> 58.714825 | J10: 0.5 | K10: =D10*L10 -> 0 | L10: 0 | M10: =D10*N10 -> 0 | N10: 0 | O10: =D10*P10 -> 0 | P10: 0 | Q10: =D10*R10 -> 0 | R10: 0 | S10: =F10*T10 -> 0 | T10: 0 | U10: =D10*V10 -> 0 | V10: 0 | W10: =D10*X10 -> 0 | X10: 0 | Y10: =Z10*D10 -> 0 | Z10: 0 | AA10: =E10+G10+I10+K10+M10+O10+Q10+S10+U10+W10+Y10 -> 117.42965 | AB10: =AA10/D10 -> 1 | AC10: =E10+G10+I10 -> 117.42965 | AD10: =AC10/D10 -> 1 | AE10: =K10+M10+O10+Q10+S10 -> 0 | AF10: =AE10/D10 -> 0 | AG10: =M10+O10+Q10+S10+U10 -> 0 | AH10: =AG10/D10 -> 0
B11: 4 | C11: Muro con ventana | D11: ='CO SIF'!E7 -> 44.324475 | E11: =D11*F11 -> 0 | F11: 0 | G11: =D11*H11 -> 22.162237 | H11: 0.5 | I11: =D11*J11 -> 22.162237 | J11: 0.5 | K11: =D11*L11 -> 0 | L11: 0 | M11: =D11*N11 -> 0 | N11: 0 | O11: =D11*P11 -> 0 | P11: 0 | Q11: =D11*R11 -> 0 | R11: 0 | S11: =F11*T11 -> 0 | T11: 0 | U11: =D11*V11 -> 0 | V11: 0 | W11: =D11*X11 -> 0 | X11: 0 | Y11: =Z11*D11 -> 0 | Z11: 0 | AA11: =E11+G11+I11+K11+M11+O11+Q11+S11+U11+W11+Y11 -> 44.324475 | AB11: =AA11/D11 -> 1 | AC11: =E11+G11+I11 -> 44.324475 | AD11: =AC11/D11 -> 1 | AE11: =K11+M11+O11+Q11+S11 -> 0 | AF11: =AE11/D11 -> 0 | AG11: =M11+O11+Q11+S11+U11 -> 0 | AH11: =AG11/D11 -> 0
B12: 3 | C12: Culata baja sin ventanas | D12: ='CO SIF'!E8 -> 70.754385 | E12: =D12*F12 -> 0 | F12: 0 | G12: =D12*H12 -> 0 | H12: 0 | I12: =D12*J12 -> 70.754385 | J12: 1 | K12: =D12*L12 -> 0 | L12: 0 | M12: =D12*N12 -> 0 | N12: 0 | O12: =D12*P12 -> 0 | P12: 0 | Q12: =D12*R12 -> 0 | R12: 0 | S12: =F12*T12 -> 0 | T12: 0 | U12: =D12*V12 -> 0 | V12: 0 | W12: =D12*X12 -> 0 | X12: 0 | Y12: =Z12*D12 -> 0 | Z12: 0 | AA12: =E12+G12+I12+K12+M12+O12+Q12+S12+U12+W12+Y12 -> 70.754385 | AB12: =AA12/D12 -> 1 | AC12: =E12+G12+I12 -> 70.754385 | AD12: =AC12/D12 -> 1 | AE12: =K12+M12+O12+Q12+S12 -> 0 | AF12: =AE12/D12 -> 0 | AG12: =M12+O12+Q12+S12+U12 -> 0 | AH12: =AG12/D12 -> 0
B13: 4 | C13: Culata alta sin ventanas | D13: ='CO SIF'!E9 -> 201.13315 | E13: =D13*F13 -> 0 | F13: 0 | G13: =D13*H13 -> 0 | H13: 0 | I13: =D13*J13 -> 201.13315 | J13: 1 | K13: =D13*L13 -> 0 | L13: 0 | M13: =D13*N13 -> 0 | N13: 0 | O13: =D13*P13 -> 0 | P13: 0 | Q13: =D13*R13 -> 0 | R13: 0 | S13: =F13*T13 -> 0 | T13: 0 | U13: =D13*V13 -> 0 | V13: 0 | W13: =D13*X13 -> 0 | X13: 0 | Y13: =Z13*D13 -> 0 | Z13: 0 | AA13: =E13+G13+I13+K13+M13+O13+Q13+S13+U13+W13+Y13 -> 201.13315 | AB13: =AA13/D13 -> 1 | AC13: =E13+G13+I13 -> 201.13315 | AD13: =AC13/D13 -> 1 | AE13: =K13+M13+O13+Q13+S13 -> 0 | AF13: =AE13/D13 -> 0 | AG13: =M13+O13+Q13+S13+U13 -> 0 | AH13: =AG13/D13 -> 0
C15: TOTAL M2 DE FACHADA | D15: =SUM(D10:D14) -> 433.64166 | E15: =SUM(E10:E14) -> 0 | F15: =E15/D15 -> 0 | G15: =SUM(G10:G13) -> 80.877063 | H15: =G15/D15 -> 0.18650667 | I15: =SUM(I10:I13) -> 352.7646 | J15: =I15/D15 -> 0.81349333 | K15: =SUM(K6:K13) -> 0 | L15: =K15/D15 -> 0 | M15: =SUM(M6:M13) -> 0 | N15: =M15/D15 -> 0 | O15: =SUM(O6:O13) -> 0 | P15: =O15/D15 -> 0 | Q15: =SUM(Q6:Q13) -> 0 | R15: =Q15/D15 -> 0 | S15: =SUM(S6:S13) -> 0 | T15: =S15/D15 -> 0 | U15: =SUM(U6:U13) -> 0 | V15: =U15/D15 -> 0 | W15: =SUM(W6:W13) -> 0 | X15: =W15/D15 -> 0 | Y15: =SUM(Y6:Y13) -> 0 | Z15: =Y15/D15 -> 0 | AA15: =SUM(AA10:AA13) -> 433.64166 | AB15: =AA15/D15 -> 1 | AC15: =SUM(AC10:AC13) -> 433.64166 | AD15: =AC15/D15 -> 1 | AE15: =SUM(AE10:AE13) -> 0 | AF15: =AE15/D15 -> 0 | AG15: =SUM(AG10:AG13) -> 0 | AH15: =AG15/D15 -> 0
AA16: =D15-AA15 -> 0 | AB16: =AA16/D15 -> 0
A18: ESTE | B18: 5 | C18: Muro con balcones y volumenes | D18: ='CO SIF'!E15 -> 627.00183 | E18: =D18*F18 -> 0 | F18: 0 | G18: =D18*H18 -> 0 | H18: 0 | I18: =J18*D18 -> 0 | J18: 0 | K18: =D18*L18 -> 156.75046 | L18: 0.25 | M18: =D18*N18 -> 188.10055 | N18: 0.3 | O18: =D18*P18 -> 156.75046 | P18: 0.25 | Q18: =D18*R18 -> 106.59031 | R18: 0.17 | S18: =D18*T18 -> 0 | T18: 0 | U18: =D18*V18 -> 0 | V18: 0 | W18: =D18*X18 -> 18.810055 | X18: 0.03 | Y18: =Z18*D18 -> 0 | Z18: 0 | AA18: =E18+G18+I18+K18+M18+O18+Q18+S18+U18+W18+Y18 -> 627.00183 | AB18: =AA18/D18 -> 1 | AC18: =E18+G18+I18 -> 0 | AD18: =AC18/D18 -> 0 | AE18: =K18+M18+O18+Q18+S18 -> 608.19178 | AF18: =AE18/D18 -> 0.97 | AG18: =W18 -> 18.810055 | AH18: =AG18/D18 -> 0.03
C19: Muro culata parqueadero | D19: ='CO SIF'!E16 -> 413.036 | E19: =D19*F19 -> 0 | F19: 0 | G19: =D19*H19 -> 0 | H19: 0 | I19: =J19*D19 -> 0 | J19: 0 | K19: =D19*L19 -> 41.3036 | L19: 0.1 | M19: =D19*N19 -> 41.3036 | N19: 0.1 | O19: =D19*P19 -> 41.3036 | P19: 0.1 | Q19: =D19*R19 -> 41.3036 | R19: 0.1 | S19: =D19*T19 -> 0 | T19: 0 | U19: =D19*V19 -> 103.259 | V19: 0.25 | W19: =D19*X19 -> 144.5626 | X19: 0.35 | Y19: =Z19*D19 -> 0 | Z19: 0 | AA19: =E19+G19+I19+K19+M19+O19+Q19+S19+U19+W19+Y19 -> 413.036 | AB19: =AA19/D19 -> 1 | AC19: =E19+G19+I19 -> 0 | AD19: =AC19/D19 -> 0 | AE19: =K19+M19+O19+Q19+S19 -> 165.2144 | AF19: =AE19/D19 -> 0.4 | AG19: =W19 -> 144.5626 | AH19: =AG19/D19 -> 0.35
B20: 6 | C20: Muro sin ventanas | D20: ='CO SIF'!E17 -> 28.3413 | E20: =D20*F20 -> 0 | F20: 0 | G20: =D20*H20 -> 0 | H20: 0 | I20: =J20*D20 -> 0 | J20: 0 | K20: =D20*L20 -> 0 | L20: 0 | M20: =D20*N20 -> 0 | N20: 0 | O20: =D20*P20 -> 0 | P20: 0 | Q20: =D20*R20 -> 15.587715 | R20: 0.55 | S20: =D20*T20 -> 9.919455 | T20: 0.35 | U20: =D20*V20 -> 2.83413 | V20: 0.1 | W20: =D20*X20 -> 0 | X20: 0 | Y20: =Z20*D20 -> 0 | Z20: 0 | AA20: =E20+G20+I20+K20+M20+O20+Q20+S20+U20+W20+Y20 -> 28.3413 | AB20: =AA20/D20 -> 1 | AC20: =E20+G20+I20 -> 0 | AD20: =AC20/D20 -> 0 | AE20: =K20+M20+O20+Q20+S20 -> 25.50717 | AF20: =AE20/D20 -> 0.9 | AG20: =W20 -> 0 | AH20: =AG20/D20 -> 0
B21: 7 | C21: Muro con balcones y volumenes | D21: ='CO SIF'!E18 -> 207.6165 | E21: =D21*F21 -> 0 | F21: 0 | G21: =D21*H21 -> 0 | H21: 0 | I21: =J21*D21 -> 0 | J21: 0 | K21: =D21*L21 -> 0 | L21: 0 | M21: =D21*N21 -> 0 | N21: 0 | O21: =D21*P21 -> 62.28495 | P21: 0.3 | Q21: =D21*R21 -> 93.427425 | R21: 0.45 | S21: =D21*T21 -> 20.76165 | T21: 0.1 | U21: =D21*V21 -> 20.76165 | V21: 0.1 | W21: =D21*X21 -> 10.380825 | X21: 0.05 | Y21: =Z21*D21 -> 0 | Z21: 0 | AA21: =E21+G21+I21+K21+M21+O21+Q21+S21+U21+W21+Y21 -> 207.6165 | AB21: =AA21/D21 -> 1 | AC21: =E21+G21+I21 -> 0 | AD21: =AC21/D21 -> 0 | AE21: =K21+M21+O21+Q21+S21 -> 176.47403 | AF21: =AE21/D21 -> 0.85 | AG21: =W21 -> 10.380825 | AH21: =AG21/D21 -> 0.05
B22: 8 | C22: Muro sin ventanas | D22: ='CO SIF'!E19 -> 28.3413 | E22: =D22*F22 -> 0 | F22: 0 | G22: =D22*H22 -> 0 | H22: 0 | I22: =J22*D22 -> 0 | J22: 0 | K22: =D22*L22 -> 0 | L22: 0 | M22: =D22*N22 -> 0 | N22: 0 | O22: =D22*P22 -> 1.417065 | P22: 0.05 | Q22: =D22*R22 -> 14.17065 | R22: 0.5 | S22: =D22*T22 -> 11.33652 | T22: 0.4 | U22: =D22*V22 -> 0 | V22: 0 | W22: =D22*X22 -> 1.417065 | X22: 0.05 | Y22: =Z22*D22 -> 0 | Z22: 0 | AA22: =E22+G22+I22+K22+M22+O22+Q22+S22+U22+W22+Y22 -> 28.3413 | AB22: =AA22/D22 -> 1 | AC22: =E22+G22+I22 -> 0 | AD22: =AC22/D22 -> 0 | AE22: =K22+M22+O22+Q22+S22 -> 26.924235 | AF22: =AE22/D22 -> 0.95 | AG22: =W22 -> 1.417065 | AH22: =AG22/D22 -> 0.05
B23: 9 | C23: Muro con balcones y volumenes | D23: ='CO SIF'!E20 -> 232.05812 | E23: =D23*F23 -> 0 | F23: 0 | G23: =D23*H23 -> 0 | H23: 0 | I23: =J23*D23 -> 0 | J23: 0 | K23: =D23*L23 -> 0 | L23: 0 | M23: =D23*N23 -> 0 | N23: 0 | O23: =D23*P23 -> 0 | P23: 0 | Q23: =D23*R23 -> 92.82325 | R23: 0.4 | S23: =D23*T23 -> 92.82325 | T23: 0.4 | U23: =D23*V23 -> 0 | V23: 0 | W23: =D23*X23 -> 46.411625 | X23: 0.2 | Y23: =Z23*D23 -> 0 | Z23: 0 | AA23: =E23+G23+I23+K23+M23+O23+Q23+S23+U23+W23+Y23 -> 232.05812 | AB23: =AA23/D23 -> 1 | AC23: =E23+G23+I23 -> 0 | AD23: =AC23/D23 -> 0 | AE23: =K23+M23+O23+Q23+S23 -> 185.6465 | AF23: =AE23/D23 -> 0.8 | AG23: =W23 -> 46.411625 | AH23: =AG23/D23 -> 0.2
C25: TOTAL M2 DE FACHADA | D25: =SUM(D18:D24) -> 1536.3951 | E25: =SUM(E18:E24) -> 0 | F25: =E25/D25 -> 0 | G25: =SUM(G18:G24) -> 0 | H25: =G25/D25 -> 0 | I25: =SUM(I18:I24) -> 0 | J25: =I25/D25 -> 0 | K25: =SUM(K17:K23) -> 198.05406 | L25: =K25/D25 -> 0.12890829 | M25: =SUM(M17:M23) -> 229.40415 | N25: =M25/D25 -> 0.14931326 | O25: =SUM(O17:O23) -> 261.75607 | P25: =O25/D25 -> 0.17037029 | Q25: =SUM(Q17:Q23) -> 363.90295 | R25: =Q25/D25 -> 0.23685507 | S25: =SUM(S17:S23) -> 134.84087 | T25: =S25/D25 -> 0.087764455 | U25: =SUM(U16:U23) -> 126.85478 | V25: =U25/D25 -> 0.082566512 | W25: =SUM(W16:W23) -> 221.58217 | X25: =W25/D25 -> 0.14422213 | Y25: =SUM(Y16:Y23) -> 0 | Z25: =Y25/D25 -> 0 | AA25: =SUM(AA18:AA23) -> 1536.3951 | AB25: =AA25/D25 -> 1 | AC25: =SUM(AC18:AC23) -> 0 | AD25: =AC25/D25 -> 0 | AE25: =SUM(AE18:AE23) -> 1187.9581 | AF25: =AE25/D25 -> 0.77321136 | AG25: =SUM(AG18:AG23) -> 221.58217 | AH25: =AG25/D25 -> 0.14422213
AA26: =D25-AA25 -> 0 | AB26: =AA26/D25 -> 0
A28: SUR | B28: 10 | C28: Muro con balcones y volumenes | D28: ='CO SIF'!E26 -> 599.57503 | E28: =D28*F28 -> 0 | F28: 0 | G28: =D28*H28 -> 0 | H28: 0 | I28: =D28*J28 -> 0 | J28: 0 | K28: =D28*L28 -> 0 | L28: 0 | M28: =D28*N28 -> 0 | N28: 0 | O28: =D28*P28 -> 0 | P28: 0 | Q28: =D28*R28 -> 0 | R28: 0 | S28: =F28*T28 -> 0 | T28: 0 | U28: =D28*V28 -> 0 | V28: 0 | W28: =D28*X28 -> 317.77477 | X28: 0.53 | Y28: =Z28*D28 -> 281.80026 | Z28: 0.47 | AA28: =E28+G28+I28+K28+M28+O28+Q28+S28+U28+W28+Y28 -> 599.57503 | AB28: =AA28/D28 -> 1 | AC28: =E28+G28+I28 -> 0 | AD28: =AC28/D28 -> 0 | AE28: =K28+M28+O28+Q28+S28 -> 0 | AF28: =AE28/D28 -> 0 | AG28: =W28 -> 317.77477 | AH28: =AG28/D28 -> 0.53
C30: TOTAL M2 DE FACHADA | D30: =SUM(D28:D29) -> 599.57503 | E30: =SUM(E28:E29) -> 0 | F30: =E30/D30 -> 0 | G30: =SUM(G28:G28) -> 0 | H30: =G30/D30 -> 0 | I30: =SUM(I28:I28) -> 0 | J30: =I30/D30 -> 0 | K30: =SUM(K21:K28) -> 198.05406 | L30: =K30/D30 -> 0.33032406 | M30: =SUM(M21:M28) -> 229.40415 | N30: =M30/D30 -> 0.38261124 | O30: =SUM(O21:O28) -> 325.45809 | P30: =O30/D30 -> 0.54281461 | Q30: =SUM(Q21:Q28) -> 564.32428 | R30: =Q30/D30 -> 0.9412071 | S30: =SUM(S21:S28) -> 259.76229 | T30: =S30/D30 -> 0.43324402 | U30: =SUM(U21:U28) -> 147.61643 | V30: =U30/D30 -> 0.24620176 | W30: =SUM(W21:W28) -> 597.56645 | X30: =W30/D30 -> 0.99664999 | Y30: =SUM(Y21:Y28) -> 281.80026 | Z30: =Y30/D30 -> 0.47 | AA30: =SUM(AA28:AA28) -> 599.57503 | AB30: =AA30/D30 -> 1 | AC30: =SUM(AC28) -> 0 | AD30: =AC30/D30 -> 0 | AE30: =SUM(AE28) -> 0 | AF30: =AE30/D30 -> 0 | AG30: =SUM(AG28) -> 317.77477 | AH30: =AG30/D30 -> 0.53
AA31: =D30-AA30 -> 0 | AB31: =AA31/D30 -> 0
A33: OESTE | B33: 11 | C33: Muro con balcones y volumenes | D33: ='CO SIF'!E32 -> 253.9732 | E33: =D33*F33 -> 0 | F33: 0 | G33: =D33*H33 -> 0 | H33: 0 | I33: =J33*D33 -> 0 | J33: 0 | K33: =D33*L33 -> 0 | L33: 0 | M33: =D33*N33 -> 0 | N33: 0 | O33: =D33*P33 -> 0 | P33: 0 | Q33: =D33*R33 -> 0 | R33: 0 | S33: =F33*T33 -> 0 | T33: 0 | U33: =H33*V33 -> 0 | V33: 0 | W33: =D33*X33 -> 0 | X33: 0 | Y33: =Z33*D33 -> 253.9732 | Z33: 1 | AA33: =E33+G33+I33+K33+M33+O33+Q33+S33+U33+W33+Y33 -> 253.9732 | AB33: =AA33/D33 -> 1
B34: 12 | C34: Muro sin ventanas | D34: ='CO SIF'!E33 -> 56.6826 | E34: =D34*F34 -> 0 | F34: 0 | G34: =D34*H34 -> 0 | H34: 0 | I34: =J34*D34 -> 0 | J34: 0 | K34: =D34*L34 -> 0 | L34: 0 | M34: =D34*N34 -> 0 | N34: 0 | O34: =D34*P34 -> 0 | P34: 0 | Q34: =D34*R34 -> 0 | R34: 0 | S34: =F34*T34 -> 0 | T34: 0 | U34: =H34*V34 -> 0 | V34: 0 | W34: =D34*X34 -> 0 | X34: 0 | Y34: =Z34*D34 -> 56.6826 | Z34: 1 | AA34: =E34+G34+I34+K34+M34+O34+Q34+S34+U34+W34+Y34 -> 56.6826 | AB34: =AA34/D34 -> 1
B35: 13 | C35: Muro con balcones y volumenes | D35: ='CO SIF'!E34 -> 522.886 | E35: =D35*F35 -> 0 | F35: 0 | G35: =D35*H35 -> 0 | H35: 0 | I35: =J35*D35 -> 0 | J35: 0 | K35: =D35*L35 -> 0 | L35: 0 | M35: =D35*N35 -> 0 | N35: 0 | O35: =D35*P35 -> 0 | P35: 0 | Q35: =D35*R35 -> 0 | R35: 0 | S35: =F35*T35 -> 0 | T35: 0 | U35: =H35*V35 -> 0 | V35: 0 | W35: =D35*X35 -> 0 | X35: 0 | Y35: =Z35*D35 -> 522.886 | Z35: 1 | AA35: =E35+G35+I35+K35+M35+O35+Q35+S35+U35+W35+Y35 -> 522.886 | AB35: =AA35/D35 -> 1
B36: 14 | C36: Muro sin ventanas | D36: ='CO SIF'!E35 -> 35.426625 | E36: =D36*F36 -> 0 | F36: 0 | G36: =D36*H36 -> 0 | H36: 0 | I36: =J36*D36 -> 0 | J36: 0 | K36: =D36*L36 -> 0 | L36: 0 | M36: =D36*N36 -> 0 | N36: 0 | O36: =D36*P36 -> 0 | P36: 0 | Q36: =D36*R36 -> 0 | R36: 0 | S36: =F36*T36 -> 0 | T36: 0 | U36: =H36*V36 -> 0 | V36: 0 | W36: =D36*X36 -> 0 | X36: 0 | Y36: =Z36*D36 -> 35.426625 | Z36: 1 | AA36: =E36+G36+I36+K36+M36+O36+Q36+S36+U36+W36+Y36 -> 35.426625 | AB36: =AA36/D36 -> 1
B37: 15 | C37: Muro con balcones y volumenes | D37: ='CO SIF'!E36 -> 194.81238 | E37: =D37*F37 -> 0 | F37: 0 | G37: =D37*H37 -> 0 | H37: 0 | I37: =J37*D37 -> 0 | J37: 0 | K37: =D37*L37 -> 0 | L37: 0 | M37: =D37*N37 -> 0 | N37: 0 | O37: =D37*P37 -> 0 | P37: 0 | Q37: =D37*R37 -> 0 | R37: 0 | S37: =F37*T37 -> 0 | T37: 0 | U37: =H37*V37 -> 0 | V37: 0 | W37: =D37*X37 -> 0 | X37: 0 | Y37: =Z37*D37 -> 194.81238 | Z37: 1 | AA37: =E37+G37+I37+K37+M37+O37+Q37+S37+U37+W37+Y37 -> 194.81238 | AB37: =AA37/D37 -> 1
B38: 16 | C38: Muro sin ventanas | D38: ='CO SIF'!E37 -> 16.532425 | E38: =D38*F38 -> 0 | F38: 0 | G38: =D38*H38 -> 0 | H38: 0 | I38: =J38*D38 -> 0 | J38: 0 | K38: =D38*L38 -> 0 | L38: 0 | M38: =D38*N38 -> 0 | N38: 0 | O38: =D38*P38 -> 0 | P38: 0 | Q38: =D38*R38 -> 0 | R38: 0 | S38: =F38*T38 -> 0 | T38: 0 | U38: =H38*V38 -> 0 | V38: 0 | W38: =D38*X38 -> 0 | X38: 0 | Y38: =Z38*D38 -> 16.532425 | Z38: 1 | AA38: =E38+G38+I38+K38+M38+O38+Q38+S38+U38+W38+Y38 -> 16.532425 | AB38: =AA38/D38 -> 1
B39: 17 | C39: Muro con balcones y volumenes | D39: ='CO SIF'!E38 -> 104.5772 | E39: =D39*F39 -> 0 | F39: 0 | G39: =D39*H39 -> 0 | H39: 0 | I39: =J39*D39 -> 0 | J39: 0 | K39: =D39*L39 -> 0 | L39: 0 | M39: =D39*N39 -> 0 | N39: 0 | O39: =D39*P39 -> 0 | P39: 0 | Q39: =D39*R39 -> 0 | R39: 0 | S39: =F39*T39 -> 0 | T39: 0 | U39: =H39*V39 -> 0 | V39: 0 | W39: =D39*X39 -> 0 | X39: 0 | Y39: =Z39*D39 -> 104.5772 | Z39: 1 | AA39: =E39+G39+I39+K39+M39+O39+Q39+S39+U39+W39+Y39 -> 104.5772 | AB39: =AA39/D39 -> 1
C40: Volumenes en fachada | D40: ='CO SIF'!E39 -> 42.896425 | E40: =D40*F40 -> 0 | F40: 0 | G40: =D40*H40 -> 0 | H40: 0 | I40: =J40*D40 -> 0 | J40: 0 | K40: =D40*L40 -> 0 | L40: 0 | M40: =D40*N40 -> 0 | N40: 0 | O40: =D40*P40 -> 0 | P40: 0 | Q40: =D40*R40 -> 0 | R40: 0 | S40: =F40*T40 -> 0 | T40: 0 | U40: =D40*V40 -> 0 | V40: 0 | W40: =D40*X40 -> 0 | X40: 0 | Y40: =Z40*D40 -> 42.896425 | Z40: 1 | AA40: =E40+G40+I40+K40+M40+O40+Q40+S40+U40+W40+Y40 -> 42.896425 | AB40: =AA40/D40 -> 1
C42: TOTAL M2 DE FACHADA | D42: =SUM(D33:D41) -> 1227.7869 | E42: =SUM(E33:E41) -> 0 | F42: =E42/D42 -> 0 | G42: =SUM(G33:G41) -> 0 | H42: =G42/D42 -> 0 | I42: =SUM(I33:I41) -> 0 | J42: =I42/D42 -> 0 | K42: =SUM(K34:K41) -> 0 | L42: =K42/D42 -> 0 | M42: =SUM(M34:M41) -> 0 | N42: =M42/D42 -> 0 | O42: =SUM(O34:O41) -> 0 | P42: =O42/D42 -> 0 | Q42: =SUM(Q34:Q41) -> 0 | R42: =Q42/D42 -> 0 | S42: =SUM(S34:S41) -> 0 | T42: =S42/D42 -> 0 | U42: =SUM(U33:U40) -> 0 | V42: =U42/D42 -> 0 | W42: =SUM(W33:W40) -> 0 | X42: =W42/D42 -> 0 | Y42: =SUM(Y33:Y40) -> 1227.7869 | Z42: =Y42/D42 -> 1 | AA42: =SUM(AA33:AA40) -> 1227.7869 | AB42: =AA42/D42 -> 1
AA43: =D42-AA42 -> 0 | AB43: =AA43/D42 -> 0
C45: TOTAL M2 DE FACHADAS GENERAL | D45: =D15+D25+D30+D42 -> 3797.3986 | H45: TOTAL M2 DE EJECUTADOS | AA45: =AA15+AA25+AA30+AA42 -> 3797.3986 | AB45: =AA45/D45 -> 1 | AC45: =AC15+AC25+AC30+AC42 -> 433.64166 | AD45: =AC45/D45 -> 0.1141944 | AE45: =AE15+AE25+AE30+AE42 -> 1187.9581 | AF45: =AE45/D45 -> 0.31283471 | AG45: =AG15+AG25+AG30+AG42 -> 539.35694 | AH45: =AG45/D45 -> 0.14203327
AA46: =D45-AA45 -> 0 | AB46: =AA46/D45 -> 0
A48: PASILLOS | B48: 9 | C48: Piso Completo | D48: =SUM('CO SIF'!D48:D50) -> 107.19 | E48: =D48*F48 -> 0 | F48: 0 | G48: =D48*H48 -> 107.19 | H48: 1 | I48: =J48*D48 -> 0 | J48: 0 | K48: =L48*D48 -> 0 | L48: 0 | M48: =N48*D48 -> 0 | N48: 0 | O48: =P48*D48 -> 0 | P48: 0 | Q48: =R48*L48 -> 0 | R48: 0 | S48: =T48*N48 -> 0 | T48: 0 | U48: =V48*P48 -> 0 | V48: 0 | W48: =X48*D48 -> 0 | X48: 0 | Y48: =Z48*D48 -> 0 | Z48: 0 | AA48: =E48+G48+I48+K48+M48+O48+Q48+S48+U48+W48+Y48 -> 107.19 | AB48: =AA48/D48 -> 1
B49: 8 | C49: Piso Completo | D49: =$D$48 -> 107.19 | E49: =D49*F49 -> 0 | F49: 0 | G49: =D49*H49 -> 107.19 | H49: 1 | I49: =J49*D49 -> 0 | J49: 0 | K49: =L49*D49 -> 0 | L49: 0 | M49: =N49*D49 -> 0 | N49: 0 | O49: =P49*D49 -> 0 | P49: 0 | Q49: =R49*L49 -> 0 | R49: 0 | S49: =T49*N49 -> 0 | T49: 0 | U49: =V49*P49 -> 0 | V49: 0 | W49: =X49*D49 -> 0 | X49: 0 | Y49: =Z49*D49 -> 0 | Z49: 0 | AA49: =E49+G49+I49+K49+M49+O49+Q49+S49+U49+W49+Y49 -> 107.19 | AB49: =AA49/D49 -> 1
B50: 7 | C50: Piso Completo | D50: =$D$48 -> 107.19 | E50: =D50*F50 -> 0 | F50: 0 | G50: =D50*H50 -> 107.19 | H50: 1 | I50: =J50*D50 -> 0 | J50: 0 | K50: =L50*D50 -> 0 | L50: 0 | M50: =N50*D50 -> 0 | N50: 0 | O50: =P50*D50 -> 0 | P50: 0 | Q50: =R50*L50 -> 0 | R50: 0 | S50: =T50*N50 -> 0 | T50: 0 | U50: =V50*P50 -> 0 | V50: 0 | W50: =X50*D50 -> 0 | X50: 0 | Y50: =Z50*D50 -> 0 | Z50: 0 | AA50: =E50+G50+I50+K50+M50+O50+Q50+S50+U50+W50+Y50 -> 107.19 | AB50: =AA50/D50 -> 1
B51: 6 | C51: Piso Completo | D51: =$D$48 -> 107.19 | E51: =D51*F51 -> 0 | F51: 0 | G51: =D51*H51 -> 0 | H51: 0 | I51: =J51*D51 -> 107.19 | J51: 1 | K51: =L51*D51 -> 0 | L51: 0 | M51: =N51*D51 -> 0 | N51: 0 | O51: =P51*D51 -> 0 | P51: 0 | Q51: =R51*L51 -> 0 | R51: 0 | S51: =T51*N51 -> 0 | T51: 0 | U51: =V51*P51 -> 0 | V51: 0 | W51: =X51*D51 -> 0 | X51: 0 | Y51: =Z51*D51 -> 0 | Z51: 0 | AA51: =E51+G51+I51+K51+M51+O51+Q51+S51+U51+W51+Y51 -> 107.19 | AB51: =AA51/D51 -> 1
B52: 5 | C52: Piso Completo | D52: =$D$48 -> 107.19 | E52: =D52*F52 -> 0 | F52: 0 | G52: =D52*H52 -> 0 | H52: 0 | I52: =J52*D52 -> 107.19 | J52: 1 | K52: =L52*D52 -> 0 | L52: 0 | M52: =N52*D52 -> 0 | N52: 0 | O52: =P52*D52 -> 0 | P52: 0 | Q52: =R52*L52 -> 0 | R52: 0 | S52: =T52*N52 -> 0 | T52: 0 | U52: =V52*P52 -> 0 | V52: 0 | W52: =X52*D52 -> 0 | X52: 0 | Y52: =Z52*D52 -> 0 | Z52: 0 | AA52: =E52+G52+I52+K52+M52+O52+Q52+S52+U52+W52+Y52 -> 107.19 | AB52: =AA52/D52 -> 1
B53: 4 | C53: Piso Completo | D53: =$D$48 -> 107.19 | E53: =D53*F53 -> 0 | F53: 0 | G53: =D53*H53 -> 0 | H53: 0 | I53: =J53*D53 -> 53.595 | J53: 0.5 | K53: =L53*D53 -> 53.595 | L53: 0.5 | M53: =N53*D53 -> 0 | N53: 0 | O53: =P53*D53 -> 0 | P53: 0 | Q53: =R53*L53 -> 0 | R53: 0 | S53: =T53*N53 -> 0 | T53: 0 | U53: =V53*P53 -> 0 | V53: 0 | W53: =X53*D53 -> 0 | X53: 0 | Y53: =Z53*D53 -> 0 | Z53: 0 | AA53: =E53+G53+I53+K53+M53+O53+Q53+S53+U53+W53+Y53 -> 107.19 | AB53: =AA53/D53 -> 1
B54: 3 | C54: Piso Completo | D54: =$D$48 -> 107.19 | E54: =D54*F54 -> 0 | F54: 0 | G54: =D54*H54 -> 0 | H54: 0 | I54: =J54*D54 -> 0 | J54: 0 | K54: =L54*D54 -> 107.19 | L54: 1 | M54: =N54*D54 -> 0 | N54: 0 | O54: =P54*D54 -> 0 | P54: 0 | Q54: =R54*L54 -> 0 | R54: 0 | S54: =T54*N54 -> 0 | T54: 0 | U54: =V54*P54 -> 0 | V54: 0 | W54: =X54*D54 -> 0 | X54: 0 | Y54: =Z54*D54 -> 0 | Z54: 0 | AA54: =E54+G54+I54+K54+M54+O54+Q54+S54+U54+W54+Y54 -> 107.19 | AB54: =AA54/D54 -> 1
B55: 2 | C55: Piso Completo | D55: =$D$48 -> 107.19 | E55: =D55*F55 -> 0 | F55: 0 | G55: =D55*H55 -> 0 | H55: 0 | I55: =J55*D55 -> 0 | J55: 0 | K55: =L55*D55 -> 107.19 | L55: 1 | M55: =N55*D55 -> 0 | N55: 0 | O55: =P55*D55 -> 0 | P55: 0 | Q55: =R55*L55 -> 0 | R55: 0 | S55: =T55*N55 -> 0 | T55: 0 | U55: =V55*P55 -> 0 | V55: 0 | W55: =X55*D55 -> 0 | X55: 0 | Y55: =Z55*D55 -> 0 | Z55: 0 | AA55: =E55+G55+I55+K55+M55+O55+Q55+S55+U55+W55+Y55 -> 107.19 | AB55: =AA55/D55 -> 1
B56: 1 | C56: Piso Completo | D56: =$D$48 -> 107.19 | E56: =D56*F56 -> 0 | F56: 0 | G56: =D56*H56 -> 0 | H56: 0 | I56: =J56*D56 -> 0 | J56: 0 | K56: =L56*D56 -> 0 | L56: 0 | M56: =N56*D56 -> 53.595 | N56: 0.5 | O56: =P56*D56 -> 0 | P56: 0 | Q56: =R56*L56 -> 0 | R56: 0 | S56: =T56*N56 -> 0 | T56: 0 | U56: =V56*P56 -> 0 | V56: 0 | W56: =X56*D56 -> 53.595 | X56: 0.5 | Y56: =Z56*D56 -> 0 | Z56: 0 | AA56: =E56+G56+I56+K56+M56+O56+Q56+S56+U56+W56+Y56 -> 107.19 | AB56: =AA56/D56 -> 1
B57: S1 | C57: Piso Completo | D57: =$D$48 -> 107.19 | E57: =D57*F57 -> 0 | F57: 0 | G57: =D57*H57 -> 0 | H57: 0 | I57: =J57*D57 -> 0 | J57: 0 | K57: =L57*D57 -> 0 | L57: 0 | M57: =N57*D57 -> 53.595 | N57: 0.5 | O57: =P57*D57 -> 0 | P57: 0 | Q57: =R57*L57 -> 0 | R57: 0 | S57: =T57*N57 -> 0 | T57: 0 | U57: =V57*P57 -> 0 | V57: 0 | W57: =X57*D57 -> 0 | X57: 0 | Y57: =Z57*D57 -> 53.595 | Z57: 0.5 | AA57: =E57+G57+I57+K57+M57+O57+Q57+S57+U57+W57+Y57 -> 107.19 | AB57: =AA57/D57 -> 1
B58: S2 | C58: Piso Completo | D58: =$D$48 -> 107.19 | E58: =D58*F58 -> 0 | F58: 0 | G58: =D58*H58 -> 0 | H58: 0 | I58: =J58*D58 -> 0 | J58: 0 | K58: =L58*D58 -> 0 | L58: 0 | M58: =N58*D58 -> 53.595 | N58: 0.5 | O58: =P58*D58 -> 0 | P58: 0 | Q58: =R58*L58 -> 0 | R58: 0 | S58: =T58*N58 -> 0 | T58: 0 | U58: =V58*P58 -> 0 | V58: 0 | W58: =X58*D58 -> 0 | X58: 0 | Y58: =Z58*D58 -> 53.595 | Z58: 0.5 | AA58: =E58+G58+I58+K58+M58+O58+Q58+S58+U58+W58+Y58 -> 107.19 | AB58: =AA58/D58 -> 1
C60: TOTAL M2 DE FACHADA | D60: =SUM(D48:D57) -> 1071.9 | E60: =SUM(E48:E57) -> 0 | F60: =E60/D60 -> 0 | G60: =SUM(G48:G57) -> 321.57 | H60: =G60/D60 -> 0.3 | I60: =SUM(I48:I57) -> 267.975 | J60: =I60/D60 -> 0.25 | K60: =SUM(K48:K57) -> 267.975 | L60: =K60/D60 -> 0.25 | M60: =SUM(M48:M57) -> 107.19 | N60: =M60/D60 -> 0.1 | O60: =SUM(O48:O57) -> 0 | P60: =O60/D60 -> 0 | Q60: =SUM(Q48:Q57) -> 0 | R60: =Q60/D60 -> 0 | S60: =SUM(S48:S57) -> 0 | T60: =S60/$D$60 -> 0 | U60: =SUM(U48:U57) -> 0 | V60: =U60/$D$60 -> 0 | W60: =SUM(W48:W57) -> 53.595 | X60: =W60/$D$60 -> 0.05 | Y60: =SUM(Y48:Y57) -> 53.595 | Z60: =Y60/$D$60 -> 0.05 | AA60: =SUM(AA48:AA58) -> 1179.09 | AB60: =AA60/D60 -> 1.1 | AC60: 589.55 | AD60: =AC60/D60 -> 0.55000466 | AE60: =AA60-AC60 -> 589.54 | AF60: =AE60/D60 -> 0.54999534 | AG60: =AC60-AE60 -> 0.01 | AH60: =AG60/D60 -> 9.3292285e-06
AA61: =D60-AA60 -> -107.19 | AB61: =AA61/D60 -> -0.1
